{
  "type": "Feature",
  "properties": {
    "gn:admin1_code":"97",
    "gn:asciiname":"Bokraci",
    "gn:country_code":"SI",
    "gn:dem":269,
    "gn:feature_class":"P",
    "gn:feature_code":"PPL",
    "gn:name":"Bokra\u010di",
    "gn:population":69,
    "gn:timezone":"Europe/Ljubljana",
    "iso:country":"SI",
    "name:bos_x_preferred":[
        "Bokra\u010di"
    ],
    "name:epo_x_preferred":[
        "Bokra\u010di"
    ],
    "name:hrv_x_preferred":[
        "Bokra\u010di"
    ],
    "name:hun_x_preferred":[
        "Bokr\u00e1cs"
    ],
    "name:nld_x_preferred":[
        "Bokra\u010di"
    ],
    "name:pol_x_preferred":[
        "Bokra\u010di"
    ],
    "name:ron_x_preferred":[
        "Bokra\u010di"
    ],
    "name:slv_x_preferred":[
        "Bokra\u010di"
    ],
    "name:ukr_x_preferred":[
        "\u0411\u043e\u043a\u0440\u0430\u0447\u0456"
    ],
    "wof:name":"Bokraci",
    "wof:placetype":"locality",
    "wof:population":69
},
  "geometry": {"coordinates":[16.19603,46.73251],"type":"Point"}
}