{
  "type": "Feature",
  "properties": {
    "gn:admin1_code":"97",
    "gn:asciiname":"Bokraci",
    "gn:country_code":"SI",
    "gn:dem":269,
    "gn:feature_class":"P",
    "gn:feature_code":"PPL",
    "gn:name":"Bokra\u010di",
    "gn:population":69,
    "gn:timezone":"Europe/Ljubljana",
    "iso:country":"SI",
    "name:und_x_variant":[
        "Bokr\u00e1cs",
        "Bokra\u010di"
    ],
    "wof:name":"Bokraci",
    "wof:placetype":"locality",
    "wof:population":69
},
  "geometry": {"coordinates":[16.19603,46.73251],"type":"Point"}
}