{
  "type": "Feature",
  "properties": {
    "iso:country":"SI",
    "wof:name":"Dravlje",
    "wof:placetype":"neighbourhood"
},
  "geometry": {"coordinates":[14.47556024399278,46.08043551057104],"type":"Point"}
}