{
  "type": "Feature",
  "properties": {
    "gn:admin1_code":"B3",
    "gn:asciiname":"Kresnica",
    "gn:country_code":"SI",
    "gn:dem":391,
    "gn:feature_class":"P",
    "gn:feature_code":"PPL",
    "gn:name":"Kresnica",
    "gn:population":156,
    "gn:timezone":"Europe/Ljubljana",
    "iso:country":"SI",
    "name:bos_x_preferred":[
        "Kresnica"
    ],
    "name:ceb_x_preferred":[
        "Kresnica"
    ],
    "name:nld_x_preferred":[
        "Kresnica"
    ],
    "name:pol_x_preferred":[
        "Kresnica"
    ],
    "name:ron_x_preferred":[
        "Kresnica"
    ],
    "name:slv_x_preferred":[
        "Kresnica"
    ],
    "name:ukr_x_preferred":[
        "\u041a\u0440\u0435\u0441\u043d\u0438\u0446\u044f"
    ],
    "wof:name":"Kresnica",
    "wof:placetype":"locality",
    "wof:population":156
},
  "geometry": {"coordinates":[15.63162,46.67202],"type":"Point"}
}