{
  "type": "Feature",
  "properties": {
    "gn:admin1_code":"22",
    "gn:asciiname":"Krizevska Vas",
    "gn:country_code":"SI",
    "gn:dem":462,
    "gn:feature_class":"P",
    "gn:feature_code":"PPL",
    "gn:name":"Kri\u017eevska Vas",
    "gn:population":47,
    "gn:timezone":"Europe/Ljubljana",
    "iso:country":"SI",
    "name:bos_x_preferred":[
        "Kri\u017eevska vas"
    ],
    "name:nld_x_preferred":[
        "Kri\u017eevska vas"
    ],
    "name:pol_x_preferred":[
        "Kri\u017eevska vas"
    ],
    "name:ron_x_preferred":[
        "Kri\u017eevska vas"
    ],
    "name:slv_x_preferred":[
        "Kri\u017eevska vas"
    ],
    "name:ukr_x_preferred":[
        "\u041a\u0440\u0438\u0436\u0435\u0432\u0441\u044c\u043a\u0430 \u0412\u0430\u0441"
    ],
    "name:und_x_variant":[
        "Kri\u017eevska Vas"
    ],
    "wof:name":"Krizevska Vas",
    "wof:placetype":"locality",
    "wof:population":47
},
  "geometry": {"coordinates":[14.71711,46.10475],"type":"Point"}
}