{
  "type": "Feature",
  "properties": {
    "gn:admin1_code":"22",
    "gn:asciiname":"Krizevska Vas",
    "gn:country_code":"SI",
    "gn:dem":462,
    "gn:feature_class":"P",
    "gn:feature_code":"PPL",
    "gn:name":"Kri\u017eevska Vas",
    "gn:population":47,
    "gn:timezone":"Europe/Ljubljana",
    "iso:country":"SI",
    "name:und_x_variant":[
        "Kri\u017eevska Vas"
    ],
    "wof:name":"Krizevska Vas",
    "wof:placetype":"locality",
    "wof:population":47
},
  "geometry": {"coordinates":[14.71711,46.10475],"type":"Point"}
}