{
  "type": "Feature",
  "properties": {
    "gn:admin1_code":"19",
    "gn:asciiname":"Famlje",
    "gn:country_code":"SI",
    "gn:dem":372,
    "gn:feature_class":"P",
    "gn:feature_code":"PPL",
    "gn:name":"Famlje",
    "gn:population":147,
    "gn:timezone":"Europe/Ljubljana",
    "iso:country":"SI",
    "name:bos_x_preferred":[
        "Famlje"
    ],
    "name:ceb_x_preferred":[
        "Famlje"
    ],
    "name:ita_x_preferred":[
        "Famie"
    ],
    "name:nld_x_preferred":[
        "Famlje"
    ],
    "name:pol_x_preferred":[
        "Famlje"
    ],
    "name:ron_x_preferred":[
        "Famlje"
    ],
    "name:slv_x_preferred":[
        "Famlje"
    ],
    "name:ukr_x_preferred":[
        "\u0424\u0430\u043c\u043b\u0454"
    ],
    "wof:name":"Famlje",
    "wof:placetype":"locality",
    "wof:population":147
},
  "geometry": {"coordinates":[14.02122,45.66175],"type":"Point"}
}