{
  "type": "Feature",
  "properties": {
    "gn:admin1_code":"44",
    "gn:asciiname":"Dolenje Nekovo",
    "gn:country_code":"SI",
    "gn:dem":453,
    "gn:feature_class":"P",
    "gn:feature_code":"PPL",
    "gn:name":"Dolenje Nekovo",
    "gn:population":0,
    "gn:timezone":"Europe/Ljubljana",
    "iso:country":"SI",
    "wof:name":"Dolenje Nekovo",
    "wof:placetype":"locality"
},
  "geometry": {"coordinates":[13.63143,46.1023],"type":"Point"}
}