{
  "type": "Feature",
  "properties": {
    "gn:admin1_code":"K4",
    "gn:asciiname":"Marija Reka",
    "gn:country_code":"SI",
    "gn:dem":683,
    "gn:feature_class":"P",
    "gn:feature_code":"PPL",
    "gn:name":"Marija Reka",
    "gn:population":259,
    "gn:timezone":"Europe/Ljubljana",
    "iso:country":"SI",
    "name:ceb_x_preferred":[
        "Marija Reka"
    ],
    "name:hrv_x_preferred":[
        "Marija Reka"
    ],
    "name:nld_x_preferred":[
        "Marija Reka"
    ],
    "name:pol_x_preferred":[
        "Marija Reka"
    ],
    "name:ron_x_preferred":[
        "Marija Reka"
    ],
    "name:slv_x_preferred":[
        "Marija Reka"
    ],
    "name:ukr_x_preferred":[
        "\u041c\u0430\u0440\u0456\u044f \u0420\u0435\u043a\u0430"
    ],
    "wof:name":"Marija Reka",
    "wof:placetype":"locality",
    "wof:population":259
},
  "geometry": {"coordinates":[15.065,46.20833],"type":"Point"}
}