{
  "type": "Feature",
  "properties": {
    "gn:admin1_code":"K4",
    "gn:asciiname":"Marija Reka",
    "gn:country_code":"SI",
    "gn:dem":683,
    "gn:feature_class":"P",
    "gn:feature_code":"PPL",
    "gn:name":"Marija Reka",
    "gn:population":259,
    "gn:timezone":"Europe/Ljubljana",
    "iso:country":"SI",
    "wof:name":"Marija Reka",
    "wof:placetype":"locality",
    "wof:population":259
},
  "geometry": {"coordinates":[15.065,46.20833],"type":"Point"}
}