{
  "type": "Feature",
  "properties": {
    "gn:admin1_code":"I6",
    "gn:asciiname":"Buckovci",
    "gn:country_code":"SI",
    "gn:dem":248,
    "gn:feature_class":"P",
    "gn:feature_code":"PPL",
    "gn:name":"Bu\u010dkovci",
    "gn:population":119,
    "gn:timezone":"Europe/Ljubljana",
    "iso:country":"SI",
    "name:bos_x_preferred":[
        "Bu\u010dkovci"
    ],
    "name:ceb_x_preferred":[
        "Bu\u010dkovci"
    ],
    "name:hrv_x_preferred":[
        "Bu\u010dkovci"
    ],
    "name:nld_x_preferred":[
        "Bu\u010dkovci"
    ],
    "name:pol_x_preferred":[
        "Bu\u010dkovci"
    ],
    "name:ron_x_preferred":[
        "Bu\u010dkovci"
    ],
    "name:slv_x_preferred":[
        "Bu\u010dkovci"
    ],
    "name:ukr_x_preferred":[
        "\u0411\u0443\u0447\u043a\u043e\u0432\u0446\u0456"
    ],
    "name:und_x_variant":[
        "Bu\u010dkovci"
    ],
    "wof:name":"Buckovci",
    "wof:placetype":"locality",
    "wof:population":119
},
  "geometry": {"coordinates":[16.05,46.53333],"type":"Point"}
}