{
  "type": "Feature",
  "properties": {
    "gn:admin1_code":"P8",
    "gn:asciiname":"Kuljmanovi",
    "gn:country_code":"SI",
    "gn:dem":218,
    "gn:feature_class":"P",
    "gn:feature_code":"PPL",
    "gn:name":"Kuljmanovi",
    "gn:population":0,
    "gn:timezone":"Europe/Ljubljana",
    "iso:country":"SI",
    "wof:name":"Kuljmanovi",
    "wof:placetype":"locality"
},
  "geometry": {"coordinates":[16.04028,46.46472],"type":"Point"}
}