{
  "type": "Feature",
  "properties": {
    "gn:admin1_code":"54",
    "gn:asciiname":"Dovsko",
    "gn:country_code":"SI",
    "gn:dem":273,
    "gn:feature_class":"P",
    "gn:feature_code":"PPL",
    "gn:name":"Dov\u0161ko",
    "gn:population":242,
    "gn:timezone":"Europe/Ljubljana",
    "iso:country":"SI",
    "name:bos_x_preferred":[
        "Dov\u0161ko"
    ],
    "name:ceb_x_preferred":[
        "Dov\u0161ko"
    ],
    "name:hrv_x_preferred":[
        "Dov\u0161ko"
    ],
    "name:nld_x_preferred":[
        "Dov\u0161ko"
    ],
    "name:pol_x_preferred":[
        "Dov\u0161ko"
    ],
    "name:ron_x_preferred":[
        "Dov\u0161ko"
    ],
    "name:slv_x_preferred":[
        "Dov\u0161ko"
    ],
    "name:ukr_x_preferred":[
        "\u0414\u043e\u0432\u0448\u043a\u043e"
    ],
    "name:und_x_variant":[
        "Dov\u0161ko"
    ],
    "wof:name":"Dovsko",
    "wof:placetype":"locality",
    "wof:population":242
},
  "geometry": {"coordinates":[15.46356,46.02428],"type":"Point"}
}