{
  "type": "Feature",
  "properties": {
    "gn:admin1_code":"27",
    "gn:asciiname":"Hlavce Njive",
    "gn:country_code":"SI",
    "gn:dem":557,
    "gn:feature_class":"P",
    "gn:feature_code":"PPL",
    "gn:name":"Hlav\u010de Njive",
    "gn:population":69,
    "gn:timezone":"Europe/Ljubljana",
    "iso:country":"SI",
    "name:und_x_variant":[
        "Hlav\u010de Njive"
    ],
    "wof:name":"Hlavce Njive",
    "wof:placetype":"locality",
    "wof:population":69
},
  "geometry": {"coordinates":[14.13333,46.11667],"type":"Point"}
}