{
  "type": "Feature",
  "properties": {
    "gn:admin1_code":"J1",
    "gn:asciiname":"Slape",
    "gn:country_code":"SI",
    "gn:dem":264,
    "gn:feature_class":"P",
    "gn:feature_code":"PPL",
    "gn:name":"Slape",
    "gn:population":155,
    "gn:timezone":"Europe/Ljubljana",
    "iso:country":"SI",
    "name:bos_x_preferred":[
        "Slape"
    ],
    "name:ceb_x_preferred":[
        "Slape"
    ],
    "name:nld_x_preferred":[
        "Slape"
    ],
    "name:pol_x_preferred":[
        "Slape"
    ],
    "name:ron_x_preferred":[
        "Slape"
    ],
    "name:slv_x_preferred":[
        "Slape"
    ],
    "wof:name":"Slape",
    "wof:placetype":"locality",
    "wof:population":155
},
  "geometry": {"coordinates":[15.76716,46.34376],"type":"Point"}
}