{
  "type": "Feature",
  "properties": {
    "gn:admin1_code":"I4",
    "gn:asciiname":"Kapca",
    "gn:country_code":"SI",
    "gn:dem":163,
    "gn:feature_class":"P",
    "gn:feature_code":"PPL",
    "gn:name":"Kapca",
    "gn:population":441,
    "gn:timezone":"Europe/Ljubljana",
    "iso:country":"SI",
    "name:bos_x_preferred":[
        "Kapca"
    ],
    "name:ceb_x_preferred":[
        "Kapca"
    ],
    "name:epo_x_preferred":[
        "Kapca"
    ],
    "name:hrv_x_preferred":[
        "Kapca"
    ],
    "name:hun_x_preferred":[
        "Kapca"
    ],
    "name:nld_x_preferred":[
        "Kapca"
    ],
    "name:pol_x_preferred":[
        "Kapca"
    ],
    "name:ron_x_preferred":[
        "Kapca"
    ],
    "name:slv_x_preferred":[
        "Kapca"
    ],
    "name:ukr_x_preferred":[
        "\u041a\u0430\u043f\u0446\u0430"
    ],
    "name:und_x_variant":[
        "Gyertjano\u0161",
        "Kapcza"
    ],
    "wof:name":"Kapca",
    "wof:placetype":"locality",
    "wof:population":441
},
  "geometry": {"coordinates":[16.38278,46.55528],"type":"Point"}
}