{
  "type": "Feature",
  "properties": {
    "gn:admin1_code":"57",
    "gn:asciiname":"Vodisko",
    "gn:country_code":"SI",
    "gn:dem":369,
    "gn:feature_class":"P",
    "gn:feature_code":"PPL",
    "gn:name":"Vodi\u0161ko",
    "gn:population":49,
    "gn:timezone":"Europe/Ljubljana",
    "iso:country":"SI",
    "name:und_x_variant":[
        "Vodi\u0161ko"
    ],
    "wof:name":"Vodisko",
    "wof:placetype":"locality",
    "wof:population":49
},
  "geometry": {"coordinates":[15.23891,46.11152],"type":"Point"}
}