{
  "type": "Feature",
  "properties": {
    "gn:admin1_code":"57",
    "gn:asciiname":"Vodisko",
    "gn:country_code":"SI",
    "gn:dem":369,
    "gn:feature_class":"P",
    "gn:feature_code":"PPL",
    "gn:name":"Vodi\u0161ko",
    "gn:population":49,
    "gn:timezone":"Europe/Ljubljana",
    "iso:country":"SI",
    "name:bos_x_preferred":[
        "Vodi\u0161ko"
    ],
    "name:hrv_x_preferred":[
        "Vodi\u0161ko"
    ],
    "name:nld_x_preferred":[
        "Vodi\u0161ko"
    ],
    "name:pol_x_preferred":[
        "Vodi\u0161ko"
    ],
    "name:ron_x_preferred":[
        "Vodi\u0161ko"
    ],
    "name:slv_x_preferred":[
        "Vodi\u0161ko"
    ],
    "name:ukr_x_preferred":[
        "\u0412\u043e\u0434\u0438\u0448\u043a\u043e"
    ],
    "wof:name":"Vodisko",
    "wof:placetype":"locality",
    "wof:population":49
},
  "geometry": {"coordinates":[15.23891,46.11152],"type":"Point"}
}