{
  "type": "Feature",
  "properties": {
    "iso:country":"SI",
    "name:bos_x_preferred":[
        "Selo nad Polhovim Gradcem"
    ],
    "name:bul_x_preferred":[
        "\u0421\u0435\u043b\u043e \u043d\u0430\u0434 \u041f\u043e\u043b\u0445\u043e\u0432\u0438\u043c \u0413\u0440\u0430\u0434\u0446\u0435\u043c"
    ],
    "name:eng_x_preferred":[
        "Selo nad Polhovim Gradcem"
    ],
    "name:nld_x_preferred":[
        "Selo nad Polhovim Gradcem"
    ],
    "name:ron_x_preferred":[
        "Selo nad Polhovim Gradcem"
    ],
    "name:slv_x_preferred":[
        "Selo nad Polhovim Gradcem"
    ],
    "name:ukr_x_preferred":[
        "\u0421\u0435\u043b\u043e-\u043d\u0430\u0434-\u041f\u043e\u043b\u0445\u043e\u0432\u0438\u043c \u0413\u0440\u0430\u0434\u0446\u0435\u043c"
    ],
    "qs_pg:aaroncc":"SI",
    "qs_pg:name":"Selo Nad Polhovim Gradcem",
    "qs_pg:name_adm0":"Slovenija",
    "qs_pg:name_adm1":"Ljubljana",
    "qs_pg:photos":126,
    "qs_pg:photos_1k":26,
    "qs_pg:photos_9k":1,
    "qs_pg:photos_9r":3,
    "qs_pg:photos_all":126,
    "qs_pg:photos_sr":3,
    "qs_pg:pop_sr":0,
    "qs_pg:qs_pg_placetype":"locality",
    "qs_pg:qs_pg_placetype_gp":"Town",
    "qs_pg:woe_adm0":23424945,
    "woe:adm0_id":23424945,
    "woe:name_adm0":"Slovenija",
    "woe:name_adm1":"Ljubljana",
    "woe:placetype":"Town",
    "wof:name":"Selo Nad Polhovim Gradcem",
    "wof:placetype":"locality"
},
  "geometry": {"coordinates":[14.285108,46.114512],"type":"Point"}
}