{
  "type": "Feature",
  "properties": {
    "gn:admin1_code":"32",
    "gn:asciiname":"Sela pri Smarju",
    "gn:country_code":"SI",
    "gn:dem":355,
    "gn:feature_class":"P",
    "gn:feature_code":"PPL",
    "gn:name":"Sela pri \u0160marju",
    "gn:population":160,
    "gn:timezone":"Europe/Ljubljana",
    "iso:country":"SI",
    "name:und_x_variant":[
        "Seta",
        "Sela pri \u0160marju"
    ],
    "wof:name":"Sela pri Smarju",
    "wof:placetype":"locality",
    "wof:population":160
},
  "geometry": {"coordinates":[14.62199,45.95891],"type":"Point"}
}