{
  "type": "Feature",
  "properties": {
    "gn:admin1_code":"92",
    "gn:asciiname":"Zgornje Dobljezice",
    "gn:country_code":"SI",
    "gn:dem":414,
    "gn:feature_class":"P",
    "gn:feature_code":"PPL",
    "gn:name":"Zgornje Doblje\u017eice",
    "gn:population":0,
    "gn:timezone":"Europe/Ljubljana",
    "iso:country":"SI",
    "wof:name":"Zgornje Dobljezice",
    "wof:placetype":"locality"
},
  "geometry": {"coordinates":[15.54167,46.13056],"type":"Point"}
}