{
  "type": "Feature",
  "properties": {
    "gn:admin1_code":"35",
    "gn:asciiname":"Beka",
    "gn:country_code":"SI",
    "gn:dem":426,
    "gn:feature_class":"P",
    "gn:feature_code":"PPL",
    "gn:name":"Beka",
    "gn:population":9,
    "gn:timezone":"Europe/Ljubljana",
    "iso:country":"SI",
    "name:und_x_variant":[
        "Beca",
        "Beka"
    ],
    "wof:name":"Beka",
    "wof:placetype":"locality",
    "wof:population":9
},
  "geometry": {"coordinates":[13.89444,45.60056],"type":"Point"}
}