{
  "type": "Feature",
  "properties": {
    "gn:admin1_code":"38",
    "gn:asciiname":"Podbeze",
    "gn:country_code":"SI",
    "gn:dem":580,
    "gn:feature_class":"P",
    "gn:feature_code":"PPL",
    "gn:name":"Podbe\u017ee",
    "gn:population":85,
    "gn:timezone":"Europe/Ljubljana",
    "iso:country":"SI",
    "name:bos_x_preferred":[
        "Podbe\u017ee"
    ],
    "name:ceb_x_preferred":[
        "Podbe\u017ee"
    ],
    "name:hrv_x_preferred":[
        "Podbe\u017ee"
    ],
    "name:nld_x_preferred":[
        "Podbe\u017ee"
    ],
    "name:pol_x_preferred":[
        "Podbe\u017ee"
    ],
    "name:ron_x_preferred":[
        "Podbe\u017ee"
    ],
    "name:slv_x_preferred":[
        "Podbe\u017ee"
    ],
    "name:ukr_x_preferred":[
        "\u041f\u043e\u0434\u0431\u0435\u0436\u0435"
    ],
    "name:und_x_variant":[
        "Pobese"
    ],
    "wof:name":"Podbeze",
    "wof:placetype":"locality",
    "wof:population":85
},
  "geometry": {"coordinates":[14.15333,45.54833],"type":"Point"}
}