{
  "type": "Feature",
  "properties": {
    "gn:admin1_code":"38",
    "gn:asciiname":"Podbeze",
    "gn:country_code":"SI",
    "gn:dem":580,
    "gn:feature_class":"P",
    "gn:feature_code":"PPL",
    "gn:name":"Podbe\u017ee",
    "gn:population":85,
    "gn:timezone":"Europe/Ljubljana",
    "iso:country":"SI",
    "name:und_x_variant":[
        "Pobese",
        "Podbe\u017ee"
    ],
    "wof:name":"Podbeze",
    "wof:placetype":"locality",
    "wof:population":85
},
  "geometry": {"coordinates":[14.15333,45.54833],"type":"Point"}
}