{
  "type": "Feature",
  "properties": {
    "gn:admin1_code":"89",
    "gn:asciiname":"Vukovski Dol",
    "gn:country_code":"SI",
    "gn:dem":305,
    "gn:feature_class":"P",
    "gn:feature_code":"PPL",
    "gn:name":"Vukovski Dol",
    "gn:population":421,
    "gn:timezone":"Europe/Ljubljana",
    "iso:country":"SI",
    "name:bos_x_preferred":[
        "Vukovski Dol"
    ],
    "name:ceb_x_preferred":[
        "Vukovski Dol"
    ],
    "name:nld_x_preferred":[
        "Vukovski Dol"
    ],
    "name:pol_x_preferred":[
        "Vukovski Dol"
    ],
    "name:ron_x_preferred":[
        "Vukovski Dol"
    ],
    "name:slv_x_preferred":[
        "Vukovski Dol"
    ],
    "name:ukr_x_preferred":[
        "\u0412\u0443\u043a\u043e\u0432\u0441\u044c\u043a\u0438\u0439 \u0414\u043e\u043b"
    ],
    "wof:name":"Vukovski Dol",
    "wof:placetype":"locality",
    "wof:population":421
},
  "geometry": {"coordinates":[15.71692,46.62479],"type":"Point"}
}