{
  "type": "Feature",
  "properties": {
    "gn:admin1_code":"89",
    "gn:asciiname":"Vukovski Dol",
    "gn:country_code":"SI",
    "gn:dem":305,
    "gn:feature_class":"P",
    "gn:feature_code":"PPL",
    "gn:name":"Vukovski Dol",
    "gn:population":421,
    "gn:timezone":"Europe/Ljubljana",
    "iso:country":"SI",
    "wof:name":"Vukovski Dol",
    "wof:placetype":"locality",
    "wof:population":421
},
  "geometry": {"coordinates":[15.71692,46.62479],"type":"Point"}
}