{
  "type": "Feature",
  "properties": {
    "gn:admin1_code":"84",
    "gn:asciiname":"Smihel",
    "gn:country_code":"SI",
    "gn:dem":354,
    "gn:feature_class":"P",
    "gn:feature_code":"PPL",
    "gn:name":"\u0160mihel",
    "gn:population":277,
    "gn:timezone":"Europe/Ljubljana",
    "iso:country":"SI",
    "name:bos_x_preferred":[
        "\u0160mihel"
    ],
    "name:ceb_x_preferred":[
        "\u0160mihel"
    ],
    "name:deu_x_historical":[
        "Sankt  Michael"
    ],
    "name:deu_x_preferred":[
        "Sankt  Michael"
    ],
    "name:hun_x_preferred":[
        "\u0160mihel"
    ],
    "name:ita_x_historical":[
        "San Michele"
    ],
    "name:ita_x_preferred":[
        "San Michele"
    ],
    "name:nld_x_preferred":[
        "\u0160mihel"
    ],
    "name:pol_x_preferred":[
        "\u0160mihel"
    ],
    "name:ron_x_preferred":[
        "\u0160mihel"
    ],
    "name:slv_x_preferred":[
        "\u0160mihel"
    ],
    "name:ukr_x_preferred":[
        "\u0428\u043c\u0438\u0433\u0435\u043b"
    ],
    "name:und_x_variant":[
        "Sent Mihelj",
        "\u0160mihel"
    ],
    "wof:name":"Smihel",
    "wof:placetype":"locality",
    "wof:population":277
},
  "geometry": {"coordinates":[13.73694,45.95222],"type":"Point"}
}