{
  "type": "Feature",
  "properties": {
    "gn:admin1_code":"84",
    "gn:asciiname":"Smihel",
    "gn:country_code":"SI",
    "gn:dem":354,
    "gn:feature_class":"P",
    "gn:feature_code":"PPL",
    "gn:name":"\u0160mihel",
    "gn:population":277,
    "gn:timezone":"Europe/Ljubljana",
    "iso:country":"SI",
    "name:deu_x_historical":[
        "Sankt  Michael"
    ],
    "name:deu_x_preferred":[
        "Sankt  Michael"
    ],
    "name:ita_x_historical":[
        "San Michele"
    ],
    "name:ita_x_preferred":[
        "San Michele"
    ],
    "name:und_x_variant":[
        "Sent Mihelj",
        "\u0160mihel"
    ],
    "wof:name":"Smihel",
    "wof:placetype":"locality",
    "wof:population":277
},
  "geometry": {"coordinates":[13.73694,45.95222],"type":"Point"}
}