{
  "type": "Feature",
  "properties": {
    "gn:admin1_code":"H6",
    "gn:asciiname":"Smartno v Tuhinju",
    "gn:country_code":"SI",
    "gn:dem":466,
    "gn:feature_class":"P",
    "gn:feature_code":"PPL",
    "gn:name":"\u0160martno v Tuhinju",
    "gn:population":218,
    "gn:timezone":"Europe/Ljubljana",
    "iso:country":"SI",
    "name:bos_x_preferred":[
        "\u0160martno v Tuhinju"
    ],
    "name:ceb_x_preferred":[
        "\u0160martno v Tuhinju"
    ],
    "name:nld_x_preferred":[
        "\u0160martno v Tuhinju"
    ],
    "name:pol_x_preferred":[
        "\u0160martno v Tuhinju"
    ],
    "name:ron_x_preferred":[
        "\u0160martno v Tuhinju"
    ],
    "name:slv_x_preferred":[
        "\u0160martno v Tuhinju"
    ],
    "name:ukr_x_preferred":[
        "\u0428\u043c\u0430\u0440\u0442\u043d\u043e-\u0432-\u0422\u0443\u0445\u0438\u043d\u044e"
    ],
    "name:und_x_variant":[
        "\u0160martin",
        "\u0160martno v Tuhinji",
        "\u0160martno",
        "\u0160martno v Tuhinju"
    ],
    "wof:name":"Smartno v Tuhinju",
    "wof:placetype":"locality",
    "wof:population":218
},
  "geometry": {"coordinates":[14.73333,46.21667],"type":"Point"}
}