{
  "type": "Feature",
  "properties": {
    "gn:admin1_code":"B2",
    "gn:asciiname":"Voklo",
    "gn:country_code":"SI",
    "gn:dem":374,
    "gn:feature_class":"P",
    "gn:feature_code":"PPL",
    "gn:name":"Voklo",
    "gn:population":507,
    "gn:timezone":"Europe/Ljubljana",
    "iso:country":"SI",
    "name:bos_x_preferred":[
        "Voklo"
    ],
    "name:ceb_x_preferred":[
        "Voklo"
    ],
    "name:hrv_x_preferred":[
        "Voklo"
    ],
    "name:pol_x_preferred":[
        "Voklo"
    ],
    "name:ron_x_preferred":[
        "Voklo"
    ],
    "name:slv_x_preferred":[
        "Voklo"
    ],
    "name:ukr_x_preferred":[
        "\u0412\u043e\u043a\u043b\u043e"
    ],
    "wof:name":"Voklo",
    "wof:placetype":"locality",
    "wof:population":507
},
  "geometry": {"coordinates":[14.42306,46.21611],"type":"Point"}
}