{
  "type": "Feature",
  "properties": {
    "gn:admin1_code":"A1",
    "gn:asciiname":"Zgornji Kocjan",
    "gn:country_code":"SI",
    "gn:dem":265,
    "gn:feature_class":"P",
    "gn:feature_code":"PPL",
    "gn:name":"Zgornji Kocjan",
    "gn:population":30,
    "gn:timezone":"Europe/Ljubljana",
    "iso:country":"SI",
    "name:bos_x_preferred":[
        "Zgornji Kocjan"
    ],
    "name:nld_x_preferred":[
        "Zgornji Kocjan"
    ],
    "name:pol_x_preferred":[
        "Zgornji Kocjan"
    ],
    "name:ron_x_preferred":[
        "Zgornji Kocjan"
    ],
    "name:slv_x_preferred":[
        "Zgornji Kocjan"
    ],
    "name:ukr_x_preferred":[
        "\u0417\u0433\u043e\u0440\u043d\u0456\u0439 \u041a\u043e\u0446\u044f\u043d"
    ],
    "wof:name":"Zgornji Kocjan",
    "wof:placetype":"locality",
    "wof:population":30
},
  "geometry": {"coordinates":[16.04261,46.61373],"type":"Point"}
}