{
  "type": "Feature",
  "properties": {
    "gn:admin1_code":"11",
    "gn:asciiname":"Jezerce pri Smartnem",
    "gn:country_code":"SI",
    "gn:dem":392,
    "gn:feature_class":"P",
    "gn:feature_code":"PPL",
    "gn:name":"Jezerce pri \u0160martnem",
    "gn:population":69,
    "gn:timezone":"Europe/Ljubljana",
    "iso:country":"SI",
    "name:bos_x_preferred":[
        "Jezerce pri \u0160martnem"
    ],
    "name:hrv_x_preferred":[
        "Jezerce pri \u0160martnem"
    ],
    "name:ita_x_preferred":[
        "Jezerce pri \u0160martnem"
    ],
    "name:nld_x_preferred":[
        "Jezerce pri \u0160martnem"
    ],
    "name:pol_x_preferred":[
        "Jezerce pri \u0160martnem"
    ],
    "name:ron_x_preferred":[
        "Jezerce pri \u0160martnem"
    ],
    "name:slv_x_preferred":[
        "Jezerce pri \u0160martnem"
    ],
    "name:ukr_x_preferred":[
        "\u0404\u0437\u0435\u0440\u0446\u0435-\u043f\u0440\u0438-\u0428\u043c\u0430\u0440\u0442\u043d\u0435\u043c"
    ],
    "name:und_x_variant":[
        "Jezerce pri \u0160martnem"
    ],
    "wof:name":"Jezerce pri Smartnem",
    "wof:placetype":"locality",
    "wof:population":69
},
  "geometry": {"coordinates":[15.24772,46.30909000000001],"type":"Point"}
}