{
  "type": "Feature",
  "properties": {
    "gn:admin1_code":"G7",
    "gn:asciiname":"Raca",
    "gn:country_code":"SI",
    "gn:dem":307,
    "gn:feature_class":"P",
    "gn:feature_code":"PPL",
    "gn:name":"Ra\u010da",
    "gn:population":28,
    "gn:timezone":"Europe/Ljubljana",
    "iso:country":"SI",
    "name:bos_x_preferred":[
        "Ra\u010da"
    ],
    "name:pol_x_preferred":[
        "Ra\u010da"
    ],
    "name:ron_x_preferred":[
        "Ra\u010da"
    ],
    "name:slv_x_preferred":[
        "Ra\u010da"
    ],
    "name:ukr_x_preferred":[
        "\u0420\u0430\u0447\u0430"
    ],
    "name:und_x_variant":[
        "Ra\u010da"
    ],
    "wof:name":"Raca",
    "wof:placetype":"locality",
    "wof:population":28
},
  "geometry": {"coordinates":[14.66248,46.13471],"type":"Point"}
}