{
  "type": "Feature",
  "properties": {
    "iso:country":"SI",
    "name:bos_x_preferred":[
        "Ravno Brdo"
    ],
    "name:bul_x_preferred":[
        "\u0420\u0430\u0432\u043d\u043e \u0411\u044a\u0440\u0434\u043e"
    ],
    "name:nld_x_preferred":[
        "Ravno Brdo"
    ],
    "name:pol_x_preferred":[
        "Ravno Brdo"
    ],
    "name:ron_x_preferred":[
        "Ravno Brdo"
    ],
    "name:slv_x_preferred":[
        "Ravno Brdo"
    ],
    "name:ukr_x_preferred":[
        "\u0420\u0430\u0432\u043d\u043e \u0411\u0440\u0434\u043e"
    ],
    "wof:name":"Ravno Brdo",
    "wof:placetype":"neighbourhood"
},
  "geometry": {"coordinates":[14.69757998827067,46.01566072763024],"type":"Point"}
}