{
  "type": "Feature",
  "properties": {
    "gn:admin1_code":"B7",
    "gn:asciiname":"Storje",
    "gn:country_code":"SI",
    "gn:dem":352,
    "gn:feature_class":"P",
    "gn:feature_code":"PPL",
    "gn:name":"\u0160torje",
    "gn:population":325,
    "gn:timezone":"Europe/Ljubljana",
    "iso:country":"SI",
    "name:bos_x_preferred":[
        "\u0160torje"
    ],
    "name:ceb_x_preferred":[
        "\u0160torje"
    ],
    "name:ita_x_preferred":[
        "Storie"
    ],
    "name:nld_x_preferred":[
        "\u0160torje"
    ],
    "name:pol_x_preferred":[
        "\u0160torje"
    ],
    "name:ron_x_preferred":[
        "\u0160torje"
    ],
    "name:slv_x_preferred":[
        "\u0160torje"
    ],
    "name:ukr_x_preferred":[
        "\u0428\u0442\u043e\u0440\u0454"
    ],
    "wof:name":"Storje",
    "wof:placetype":"locality",
    "wof:population":325
},
  "geometry": {"coordinates":[13.92917,45.73861],"type":"Point"}
}