{
  "type": "Feature",
  "properties": {
    "gn:admin1_code":"B7",
    "gn:asciiname":"Storje",
    "gn:country_code":"SI",
    "gn:dem":352,
    "gn:feature_class":"P",
    "gn:feature_code":"PPL",
    "gn:name":"\u0160torje",
    "gn:population":325,
    "gn:timezone":"Europe/Ljubljana",
    "iso:country":"SI",
    "name:und_x_variant":[
        "Storie",
        "\u0160torje"
    ],
    "wof:name":"Storje",
    "wof:placetype":"locality",
    "wof:population":325
},
  "geometry": {"coordinates":[13.92917,45.73861],"type":"Point"}
}