{
  "type": "Feature",
  "properties": {
    "gn:admin1_code":"87",
    "gn:asciiname":"Oslusevci",
    "gn:country_code":"SI",
    "gn:dem":201,
    "gn:feature_class":"P",
    "gn:feature_code":"PPL",
    "gn:name":"Oslusevci",
    "gn:population":0,
    "gn:timezone":"Europe/Ljubljana",
    "iso:country":"SI",
    "name:bos_x_preferred":[
        "Oslu\u0161evci"
    ],
    "name:bul_x_preferred":[
        "\u041e\u0441\u043b\u0443\u0448\u0435\u0432\u0446\u0438"
    ],
    "name:ceb_x_preferred":[
        "Oslu\u0161evci"
    ],
    "name:nld_x_preferred":[
        "Oslu\u0161evci"
    ],
    "name:pol_x_preferred":[
        "Oslu\u0161evci"
    ],
    "name:ron_x_preferred":[
        "Oslu\u0161evci"
    ],
    "name:slv_x_preferred":[
        "Oslu\u0161evci"
    ],
    "name:ukr_x_preferred":[
        "\u041e\u0441\u043b\u0443\u0448\u0435\u0432\u0446\u0456"
    ],
    "wof:name":"Oslusevci",
    "wof:placetype":"locality",
    "wof:population":197
},
  "geometry": {"coordinates":[16.05472,46.41306],"type":"Point"}
}