{
  "type": "Feature",
  "properties": {
    "gn:admin1_code":"87",
    "gn:asciiname":"Oslusevci",
    "gn:country_code":"SI",
    "gn:dem":201,
    "gn:feature_class":"P",
    "gn:feature_code":"PPL",
    "gn:name":"Oslusevci",
    "gn:population":0,
    "gn:timezone":"Europe/Ljubljana",
    "iso:country":"SI",
    "wof:name":"Oslusevci",
    "wof:placetype":"locality"
},
  "geometry": {"coordinates":[16.05472,46.41306],"type":"Point"}
}