{
  "type": "Feature",
  "properties": {
    "gn:admin1_code":"H6",
    "gn:asciiname":"Crni Vrh v Tuhinju",
    "gn:country_code":"SI",
    "gn:dem":711,
    "gn:feature_class":"P",
    "gn:feature_code":"PPL",
    "gn:name":"\u010crni Vrh v Tuhinju",
    "gn:population":31,
    "gn:timezone":"Europe/Ljubljana",
    "iso:country":"SI",
    "name:und_x_variant":[
        "\u010crni Vrh v Tuhinju"
    ],
    "wof:name":"Crni Vrh v Tuhinju",
    "wof:placetype":"locality",
    "wof:population":31
},
  "geometry": {"coordinates":[14.80198,46.21831],"type":"Point"}
}