{
  "type": "Feature",
  "properties": {
    "iso:country":"SI",
    "name:ceb_x_preferred":[
        "Pance"
    ],
    "name:deu_x_preferred":[
        "Pance"
    ],
    "name:nld_x_preferred":[
        "Pance"
    ],
    "name:slv_x_preferred":[
        "Pance"
    ],
    "name:swe_x_preferred":[
        "Pance"
    ],
    "name:ukr_x_preferred":[
        "\u041f\u0430\u043d\u0441\u0435"
    ],
    "wof:name":"Pance",
    "wof:placetype":"neighbourhood"
},
  "geometry": {"coordinates":[14.66597556061462,45.99295201253712],"type":"Point"}
}