{
  "type": "Feature",
  "properties": {
    "gn:admin1_code":"B8",
    "gn:asciiname":"Dolenje Dole",
    "gn:country_code":"SI",
    "gn:dem":293,
    "gn:feature_class":"P",
    "gn:feature_code":"PPL",
    "gn:name":"Dolenje Dole",
    "gn:population":91,
    "gn:timezone":"Europe/Ljubljana",
    "iso:country":"SI",
    "name:bos_x_preferred":[
        "Dolenje Dole"
    ],
    "name:hrv_x_preferred":[
        "Dolenje Dole"
    ],
    "name:nld_x_preferred":[
        "Dolenje Dole"
    ],
    "name:pol_x_preferred":[
        "Dolenje Dole"
    ],
    "name:ron_x_preferred":[
        "Dolenje Dole"
    ],
    "name:slv_x_preferred":[
        "Dolenje Dole"
    ],
    "name:ukr_x_preferred":[
        "\u0414\u043e\u043b\u0435\u043d\u0454 \u0414\u043e\u043b\u0435"
    ],
    "wof:name":"Dolenje Dole",
    "wof:placetype":"locality",
    "wof:population":91
},
  "geometry": {"coordinates":[15.28333,45.93333],"type":"Point"}
}