{
  "type": "Feature",
  "properties": {
    "gn:admin1_code":"B8",
    "gn:asciiname":"Dolenje Dole",
    "gn:country_code":"SI",
    "gn:dem":293,
    "gn:feature_class":"P",
    "gn:feature_code":"PPL",
    "gn:name":"Dolenje Dole",
    "gn:population":91,
    "gn:timezone":"Europe/Ljubljana",
    "iso:country":"SI",
    "wof:name":"Dolenje Dole",
    "wof:placetype":"locality",
    "wof:population":91
},
  "geometry": {"coordinates":[15.28333,45.93333],"type":"Point"}
}