{
  "type": "Feature",
  "properties": {
    "gn:admin1_code":"O7",
    "gn:asciiname":"Ornuska Vas",
    "gn:country_code":"SI",
    "gn:dem":383,
    "gn:feature_class":"P",
    "gn:feature_code":"PPL",
    "gn:name":"Ornu\u0161ka Vas",
    "gn:population":50,
    "gn:timezone":"Europe/Ljubljana",
    "iso:country":"SI",
    "name:bos_x_preferred":[
        "Ornu\u0161ka vas"
    ],
    "name:hrv_x_preferred":[
        "Ornu\u0161ka vas"
    ],
    "name:nld_x_preferred":[
        "Ornu\u0161ka vas"
    ],
    "name:pol_x_preferred":[
        "Ornu\u0161ka vas"
    ],
    "name:ron_x_preferred":[
        "Ornu\u0161ka vas"
    ],
    "name:slv_x_preferred":[
        "Ornu\u0161ka vas"
    ],
    "name:ukr_x_preferred":[
        "\u041e\u0440\u043d\u0443\u0448\u043a\u0430 \u0412\u0430\u0441"
    ],
    "name:und_x_variant":[
        "Ornu\u0161ka Vas"
    ],
    "wof:name":"Ornuska Vas",
    "wof:placetype":"locality",
    "wof:population":50
},
  "geometry": {"coordinates":[15.13129,45.88991],"type":"Point"}
}