{
  "type": "Feature",
  "properties": {
    "gn:admin1_code":"O7",
    "gn:asciiname":"Ornuska Vas",
    "gn:country_code":"SI",
    "gn:dem":383,
    "gn:feature_class":"P",
    "gn:feature_code":"PPL",
    "gn:name":"Ornu\u0161ka Vas",
    "gn:population":50,
    "gn:timezone":"Europe/Ljubljana",
    "iso:country":"SI",
    "name:und_x_variant":[
        "Ornu\u0161ka Vas"
    ],
    "wof:name":"Ornuska Vas",
    "wof:placetype":"locality",
    "wof:population":50
},
  "geometry": {"coordinates":[15.13129,45.88991],"type":"Point"}
}