{
  "type": "Feature",
  "properties": {
    "gn:asciiname":"Malo Lesce",
    "gn:country_code":"SI",
    "gn:dem":445,
    "gn:feature_class":"P",
    "gn:feature_code":"PPL",
    "gn:name":"Malo Le\u0161\u010de",
    "gn:population":37,
    "gn:timezone":"Europe/Ljubljana",
    "iso:country":"SI",
    "name:bos_x_preferred":[
        "Malo Le\u0161\u010de"
    ],
    "name:hrv_x_preferred":[
        "Malo Le\u0161\u010de"
    ],
    "name:nld_x_preferred":[
        "Malo Le\u0161\u010de"
    ],
    "name:pol_x_preferred":[
        "Malo Le\u0161\u010de"
    ],
    "name:ron_x_preferred":[
        "Malo Le\u0161\u010de"
    ],
    "name:slv_x_preferred":[
        "Malo Le\u0161\u010de"
    ],
    "name:ukr_x_preferred":[
        "\u041c\u0430\u043b\u043e \u041b\u0435\u0449\u0435"
    ],
    "wof:name":"Malo Lesce",
    "wof:placetype":"locality",
    "wof:population":37
},
  "geometry": {"coordinates":[15.30504,45.69512],"type":"Point"}
}