{
  "type": "Feature",
  "properties": {
    "gn:admin1_code":"N8",
    "gn:asciiname":"Gradenc",
    "gn:country_code":"SI",
    "gn:dem":326,
    "gn:feature_class":"P",
    "gn:feature_code":"PPL",
    "gn:name":"Gradenc",
    "gn:population":76,
    "gn:timezone":"Europe/Ljubljana",
    "iso:country":"SI",
    "name:bos_x_preferred":[
        "Gradenc"
    ],
    "name:bul_x_preferred":[
        "\u0413\u0440\u0430\u0434\u0435\u043d\u0446"
    ],
    "name:hrv_x_preferred":[
        "Gradenc"
    ],
    "name:nld_x_preferred":[
        "Gradenc"
    ],
    "name:pol_x_preferred":[
        "Gradenc"
    ],
    "name:ron_x_preferred":[
        "Gradenc"
    ],
    "name:slv_x_preferred":[
        "Gradenc"
    ],
    "name:ukr_x_preferred":[
        "\u0413\u0440\u0430\u0434\u0435\u043d\u0446"
    ],
    "name:und_x_variant":[
        "Gradenec",
        "Gradence"
    ],
    "wof:name":"Gradenc",
    "wof:placetype":"locality",
    "wof:population":76
},
  "geometry": {"coordinates":[14.90806,45.81417],"type":"Point"}
}