{
  "type": "Feature",
  "properties": {
    "gn:admin1_code":"N8",
    "gn:asciiname":"Gradenc",
    "gn:country_code":"SI",
    "gn:dem":326,
    "gn:feature_class":"P",
    "gn:feature_code":"PPL",
    "gn:name":"Gradenc",
    "gn:population":76,
    "gn:timezone":"Europe/Ljubljana",
    "iso:country":"SI",
    "name:und_x_variant":[
        "Gradenec",
        "Gradence",
        "Gradenc"
    ],
    "wof:name":"Gradenc",
    "wof:placetype":"locality",
    "wof:population":76
},
  "geometry": {"coordinates":[14.90806,45.81417],"type":"Point"}
}