{
  "type": "Feature",
  "properties": {
    "gn:admin1_code":"O3",
    "gn:asciiname":"Vrbje",
    "gn:country_code":"SI",
    "gn:dem":460,
    "gn:feature_class":"P",
    "gn:feature_code":"PPL",
    "gn:name":"Vrbje",
    "gn:population":10,
    "gn:timezone":"Europe/Ljubljana",
    "iso:country":"SI",
    "name:bos_x_preferred":[
        "Vrbje"
    ],
    "name:ita_x_preferred":[
        "Vrbje"
    ],
    "name:nld_x_preferred":[
        "Vrbje"
    ],
    "name:pol_x_preferred":[
        "Vrbje"
    ],
    "name:ron_x_preferred":[
        "Vrbje"
    ],
    "name:slv_x_historical":[
        "Vrblje"
    ],
    "name:slv_x_preferred":[
        "Vrblje"
    ],
    "name:slv_x_variant":[
        "Vrbje"
    ],
    "name:ukr_x_preferred":[
        "\u0412\u0440\u0431\u0454"
    ],
    "wof:name":"Vrbje",
    "wof:placetype":"locality",
    "wof:population":10
},
  "geometry": {"coordinates":[15.47358,45.82565],"type":"Point"}
}