{
  "type": "Feature",
  "properties": {
    "gn:admin1_code":"B4",
    "gn:asciiname":"Veliki Ban",
    "gn:country_code":"SI",
    "gn:dem":738,
    "gn:feature_class":"P",
    "gn:feature_code":"PPL",
    "gn:name":"Veliki Ban",
    "gn:population":80,
    "gn:timezone":"Europe/Ljubljana",
    "iso:country":"SI",
    "name:bos_x_preferred":[
        "Veliki Ban"
    ],
    "name:fas_x_preferred":[
        "\u0648\u0644\u06cc\u06a9\u06cc \u0628\u0627\u0646"
    ],
    "name:hrv_x_preferred":[
        "Veliki Ban"
    ],
    "name:nld_x_preferred":[
        "Veliki Ban"
    ],
    "name:pol_x_preferred":[
        "Veliki Ban"
    ],
    "name:ron_x_preferred":[
        "Veliki Ban"
    ],
    "name:slv_x_preferred":[
        "Veliki Ban"
    ],
    "wof:name":"Veliki Ban",
    "wof:placetype":"locality",
    "wof:population":80
},
  "geometry": {"coordinates":[15.3876,45.80699],"type":"Point"}
}