{
  "type": "Feature",
  "properties": {
    "gn:admin1_code":"B4",
    "gn:asciiname":"Veliki Ban",
    "gn:country_code":"SI",
    "gn:dem":738,
    "gn:feature_class":"P",
    "gn:feature_code":"PPL",
    "gn:name":"Veliki Ban",
    "gn:population":80,
    "gn:timezone":"Europe/Ljubljana",
    "iso:country":"SI",
    "wof:name":"Veliki Ban",
    "wof:placetype":"locality",
    "wof:population":80
},
  "geometry": {"coordinates":[15.3876,45.80699],"type":"Point"}
}