{
  "type": "Feature",
  "properties": {
    "gn:admin1_code":"D8",
    "gn:asciiname":"Strmec",
    "gn:country_code":"SI",
    "gn:dem":576,
    "gn:feature_class":"P",
    "gn:feature_code":"PPL",
    "gn:name":"Strmec",
    "gn:population":7,
    "gn:timezone":"Europe/Ljubljana",
    "iso:country":"SI",
    "wof:name":"Strmec",
    "wof:placetype":"locality",
    "wof:population":7
},
  "geometry": {"coordinates":[14.63885,45.82152],"type":"Point"}
}