{
  "type": "Feature",
  "properties": {
    "gn:admin1_code":"44",
    "gn:asciiname":"Seniski Breg",
    "gn:country_code":"SI",
    "gn:dem":455,
    "gn:feature_class":"P",
    "gn:feature_code":"PPL",
    "gn:name":"Seni\u0161ki Breg",
    "gn:population":128,
    "gn:timezone":"Europe/Ljubljana",
    "iso:country":"SI",
    "name:bos_x_preferred":[
        "Seni\u0161ki Breg"
    ],
    "name:ceb_x_preferred":[
        "Seni\u0161ki Breg"
    ],
    "name:nld_x_preferred":[
        "Seni\u0161ki Breg"
    ],
    "name:pol_x_preferred":[
        "Seni\u0161ki Breg"
    ],
    "name:ron_x_preferred":[
        "Seni\u0161ki Breg"
    ],
    "name:slv_x_preferred":[
        "Seni\u0161ki Breg"
    ],
    "name:ukr_x_preferred":[
        "\u0421\u0435\u043d\u0438\u0448\u043a\u0438\u0439 \u0411\u0440\u0435\u0433"
    ],
    "wof:name":"Seniski Breg",
    "wof:placetype":"locality",
    "wof:population":128
},
  "geometry": {"coordinates":[13.70442,46.108],"type":"Point"}
}