{
  "type": "Feature",
  "properties": {
    "gn:admin1_code":"88",
    "gn:asciiname":"Grintovec pri Osilnici",
    "gn:country_code":"SI",
    "gn:dem":416,
    "gn:feature_class":"P",
    "gn:feature_code":"PPL",
    "gn:name":"Grintovec pri Osilnici",
    "gn:population":23,
    "gn:timezone":"Europe/Ljubljana",
    "iso:country":"SI",
    "name:bos_x_preferred":[
        "Grintovec pri Osilnici"
    ],
    "name:hrv_x_preferred":[
        "Grintovec pri Osilnici"
    ],
    "name:nld_x_preferred":[
        "Grintovec pri Osilnici"
    ],
    "name:pol_x_preferred":[
        "Grintovec pri Osilnici"
    ],
    "name:ron_x_preferred":[
        "Grintovec pri Osilnici"
    ],
    "name:slv_x_preferred":[
        "Grintovec pri Osilnici"
    ],
    "name:ukr_x_preferred":[
        "\u0413\u0440\u0438\u043d\u0442\u043e\u0432\u0435\u0446\u044c-\u043f\u0440\u0438-\u041e\u0441\u0438\u043b\u043d\u0438\u0446\u0456"
    ],
    "name:und_x_variant":[
        "Glintovec pri Osilnici"
    ],
    "wof:name":"Grintovec pri Osilnici",
    "wof:placetype":"locality",
    "wof:population":23
},
  "geometry": {"coordinates":[14.75417,45.52028],"type":"Point"}
}