{
  "type": "Feature",
  "properties": {
    "gn:admin1_code":"88",
    "gn:asciiname":"Grintovec pri Osilnici",
    "gn:country_code":"SI",
    "gn:dem":416,
    "gn:feature_class":"P",
    "gn:feature_code":"PPL",
    "gn:name":"Grintovec pri Osilnici",
    "gn:population":23,
    "gn:timezone":"Europe/Ljubljana",
    "iso:country":"SI",
    "name:und_x_variant":[
        "Glintovec pri Osilnici"
    ],
    "wof:name":"Grintovec pri Osilnici",
    "wof:placetype":"locality",
    "wof:population":23
},
  "geometry": {"coordinates":[14.75417,45.52028],"type":"Point"}
}