{
  "type": "Feature",
  "properties": {
    "gn:admin1_code":"F8",
    "gn:asciiname":"Gornji Crnci",
    "gn:country_code":"SI",
    "gn:dem":232,
    "gn:feature_class":"P",
    "gn:feature_code":"PPL",
    "gn:name":"Gornji \u010crnci",
    "gn:population":144,
    "gn:timezone":"Europe/Ljubljana",
    "iso:country":"SI",
    "name:und_x_variant":[
        "Kir\u00e1lysz\u00e9k",
        "Gornji \u010cmel",
        "\u010crnci",
        "Gornji \u010crnci"
    ],
    "wof:name":"Gornji Crnci",
    "wof:placetype":"locality",
    "wof:population":144
},
  "geometry": {"coordinates":[16.02778,46.74028],"type":"Point"}
}