{
  "type": "Feature",
  "properties": {
    "gn:admin1_code":"F8",
    "gn:asciiname":"Gornji Crnci",
    "gn:country_code":"SI",
    "gn:dem":232,
    "gn:feature_class":"P",
    "gn:feature_code":"PPL",
    "gn:name":"Gornji \u010crnci",
    "gn:population":144,
    "gn:timezone":"Europe/Ljubljana",
    "iso:country":"SI",
    "name:bos_x_preferred":[
        "Gornji \u010crnci"
    ],
    "name:bul_x_preferred":[
        "\u0413\u043e\u0440\u043d\u0438 \u0427\u0440\u044a\u043d\u0446\u0438"
    ],
    "name:ceb_x_preferred":[
        "Gornji \u010crnci"
    ],
    "name:epo_x_preferred":[
        "Gornji \u010crnci"
    ],
    "name:hrv_x_preferred":[
        "Gornji \u010crnci"
    ],
    "name:hun_x_preferred":[
        "Kir\u00e1lysz\u00e9k"
    ],
    "name:nld_x_preferred":[
        "Gornji \u010crnci"
    ],
    "name:pol_x_preferred":[
        "Gornji \u010crnci"
    ],
    "name:ron_x_preferred":[
        "Gornji \u010crnci"
    ],
    "name:slv_x_preferred":[
        "Gornji \u010crnci"
    ],
    "name:ukr_x_preferred":[
        "\u0413\u043e\u0440\u043d\u0456 \u0427\u0440\u043d\u0446\u0456"
    ],
    "name:und_x_variant":[
        "Gornji \u010cmel",
        "\u010crnci"
    ],
    "wof:name":"Gornji Crnci",
    "wof:placetype":"locality",
    "wof:population":144
},
  "geometry": {"coordinates":[16.02778,46.74028],"type":"Point"}
}