{
  "type": "Feature",
  "properties": {
    "gn:admin1_code":"54",
    "gn:asciiname":"Veliko Mrasevo",
    "gn:country_code":"SI",
    "gn:dem":179,
    "gn:feature_class":"P",
    "gn:feature_code":"PPL",
    "gn:name":"Veliko Mra\u0161evo",
    "gn:population":262,
    "gn:timezone":"Europe/Ljubljana",
    "iso:country":"SI",
    "name:und_x_variant":[
        "Veliko Mra\u0161evo"
    ],
    "wof:name":"Veliko Mrasevo",
    "wof:placetype":"locality",
    "wof:population":262
},
  "geometry": {"coordinates":[15.48333,45.88333],"type":"Point"}
}