{
  "type": "Feature",
  "properties": {
    "gn:admin1_code":"54",
    "gn:asciiname":"Veliko Mrasevo",
    "gn:country_code":"SI",
    "gn:dem":179,
    "gn:feature_class":"P",
    "gn:feature_code":"PPL",
    "gn:name":"Veliko Mra\u0161evo",
    "gn:population":262,
    "gn:timezone":"Europe/Ljubljana",
    "iso:country":"SI",
    "name:bos_x_preferred":[
        "Veliko Mra\u0161evo"
    ],
    "name:ceb_x_preferred":[
        "Veliko Mra\u0161evo"
    ],
    "name:fas_x_preferred":[
        "\u0648\u0644\u06cc\u06a9\u0648 \u0645\u0631\u0634\u0648\u0648"
    ],
    "name:hrv_x_preferred":[
        "Veliko Mra\u0161evo"
    ],
    "name:nld_x_preferred":[
        "Veliko Mra\u0161evo"
    ],
    "name:pol_x_preferred":[
        "Veliko Mra\u0161evo"
    ],
    "name:ron_x_preferred":[
        "Veliko Mra\u0161evo"
    ],
    "name:slv_x_preferred":[
        "Veliko Mra\u0161evo"
    ],
    "name:ukr_x_preferred":[
        "\u0412\u0435\u043b\u0438\u043a\u043e \u041c\u0440\u0430\u0448\u0435\u0432\u043e"
    ],
    "wof:name":"Veliko Mrasevo",
    "wof:placetype":"locality",
    "wof:population":262
},
  "geometry": {"coordinates":[15.48333,45.88333],"type":"Point"}
}