{
  "type": "Feature",
  "properties": {
    "iso:country":"SI",
    "name:bel_x_preferred":[
        "\u0420\u0443\u0434\u043d\u0456\u043a"
    ],
    "name:bos_x_preferred":[
        "Rudnik"
    ],
    "name:bul_x_preferred":[
        "\u0420\u0443\u0434\u043d\u0438\u043a"
    ],
    "name:ceb_x_preferred":[
        "Rudnik"
    ],
    "name:deu_x_preferred":[
        "Rudnik"
    ],
    "name:fra_x_preferred":[
        "Rudnik"
    ],
    "name:hrv_x_preferred":[
        "Rudnik"
    ],
    "name:ita_x_preferred":[
        "Rudnik"
    ],
    "name:nld_x_preferred":[
        "Rudnik"
    ],
    "name:pol_x_preferred":[
        "Rudnik"
    ],
    "name:ron_x_preferred":[
        "Rudnik"
    ],
    "name:rus_x_preferred":[
        "\u0420\u0443\u0434\u043d\u0438\u043a"
    ],
    "name:slv_x_preferred":[
        "Rudnik"
    ],
    "name:srp_x_preferred":[
        "\u0420\u0443\u0434\u043d\u0438\u043a"
    ],
    "name:swe_x_preferred":[
        "Rudnik"
    ],
    "name:ukr_x_preferred":[
        "\u0420\u0443\u0434\u043d\u0438\u043a"
    ],
    "wof:name":"Rudnik",
    "wof:placetype":"neighbourhood"
},
  "geometry": {"coordinates":[14.5319796449389,46.02611170809944],"type":"Point"}
}