{
  "type": "Feature",
  "properties": {
    "iso:country":"SI",
    "wof:name":"Rudnik",
    "wof:placetype":"neighbourhood"
},
  "geometry": {"coordinates":[14.5319796449389,46.02611170809944],"type":"Point"}
}