{
  "type": "Feature",
  "properties": {
    "gn:admin1_code":"K8",
    "gn:asciiname":"Koroski Selovec",
    "gn:country_code":"SI",
    "gn:dem":753,
    "gn:feature_class":"P",
    "gn:feature_code":"PPL",
    "gn:name":"Koro\u0161ki Selovec",
    "gn:population":95,
    "gn:timezone":"Europe/Ljubljana",
    "iso:country":"SI",
    "name:bos_x_preferred":[
        "Koro\u0161ki Selovec"
    ],
    "name:nld_x_preferred":[
        "Koro\u0161ki Selovec"
    ],
    "name:pol_x_preferred":[
        "Koro\u0161ki Selovec"
    ],
    "name:ron_x_preferred":[
        "Koro\u0161ki Selovec"
    ],
    "name:slv_x_preferred":[
        "Koro\u0161ki Selovec"
    ],
    "name:ukr_x_preferred":[
        "\u041a\u043e\u0440\u043e\u0448\u043a\u0438\u0439 \u0421\u0435\u043b\u043e\u0432\u0435\u0446\u044c"
    ],
    "name:und_x_variant":[
        "Koro\u0161ki Selovec"
    ],
    "wof:name":"Koroski Selovec",
    "wof:placetype":"locality",
    "wof:population":95
},
  "geometry": {"coordinates":[15.00381,46.55386],"type":"Point"}
}