{
  "type": "Feature",
  "properties": {
    "gn:admin1_code":"K8",
    "gn:asciiname":"Koroski Selovec",
    "gn:country_code":"SI",
    "gn:dem":753,
    "gn:feature_class":"P",
    "gn:feature_code":"PPL",
    "gn:name":"Koro\u0161ki Selovec",
    "gn:population":95,
    "gn:timezone":"Europe/Ljubljana",
    "iso:country":"SI",
    "name:und_x_variant":[
        "Koro\u0161ki Selovec"
    ],
    "wof:name":"Koroski Selovec",
    "wof:placetype":"locality",
    "wof:population":95
},
  "geometry": {"coordinates":[15.00381,46.55386],"type":"Point"}
}