{
  "type": "Feature",
  "properties": {
    "gn:admin1_code":"17",
    "gn:asciiname":"Lokve",
    "gn:country_code":"SI",
    "gn:dem":183,
    "gn:feature_class":"P",
    "gn:feature_code":"PPL",
    "gn:name":"Lokve",
    "gn:population":514,
    "gn:timezone":"Europe/Ljubljana",
    "iso:country":"SI",
    "wof:name":"Lokve",
    "wof:placetype":"locality",
    "wof:population":514
},
  "geometry": {"coordinates":[15.17389,45.60167],"type":"Point"}
}