{
  "type": "Feature",
  "properties": {
    "gn:admin1_code":"17",
    "gn:asciiname":"Lokve",
    "gn:country_code":"SI",
    "gn:dem":183,
    "gn:feature_class":"P",
    "gn:feature_code":"PPL",
    "gn:name":"Lokve",
    "gn:population":514,
    "gn:timezone":"Europe/Ljubljana",
    "iso:country":"SI",
    "name:bos_x_preferred":[
        "Lokve"
    ],
    "name:ceb_x_preferred":[
        "Lokve"
    ],
    "name:hrv_x_preferred":[
        "Lokve"
    ],
    "name:nld_x_preferred":[
        "Lokve"
    ],
    "name:pol_x_preferred":[
        "Lokve"
    ],
    "name:ron_x_preferred":[
        "Lokve"
    ],
    "name:slv_x_preferred":[
        "Lokve"
    ],
    "name:ukr_x_preferred":[
        "\u041b\u043e\u043a\u0432\u0435"
    ],
    "wof:name":"Lokve",
    "wof:placetype":"locality",
    "wof:population":514
},
  "geometry": {"coordinates":[15.17389,45.60167],"type":"Point"}
}