{
  "type": "Feature",
  "properties": {
    "gn:admin1_code":"D8",
    "gn:asciiname":"Hrustovo",
    "gn:country_code":"SI",
    "gn:dem":539,
    "gn:feature_class":"P",
    "gn:feature_code":"PPL",
    "gn:name":"Hrustovo",
    "gn:population":36,
    "gn:timezone":"Europe/Ljubljana",
    "iso:country":"SI",
    "name:bos_x_preferred":[
        "Hrustovo"
    ],
    "name:nld_x_preferred":[
        "Hrustovo"
    ],
    "name:pol_x_preferred":[
        "Hrustovo"
    ],
    "name:ron_x_preferred":[
        "Hrustovo"
    ],
    "name:slv_x_preferred":[
        "Hrustovo"
    ],
    "name:ukr_x_preferred":[
        "\u0425\u0440\u0443\u0441\u0442\u043e\u0432\u043e"
    ],
    "wof:name":"Hrustovo",
    "wof:placetype":"locality",
    "wof:population":36
},
  "geometry": {"coordinates":[14.60608,45.84044],"type":"Point"}
}