{
  "type": "Feature",
  "properties": {
    "gn:admin1_code":"B9",
    "gn:asciiname":"Draga",
    "gn:country_code":"SI",
    "gn:dem":389,
    "gn:feature_class":"P",
    "gn:feature_code":"PPL",
    "gn:name":"Draga",
    "gn:population":136,
    "gn:timezone":"Europe/Ljubljana",
    "iso:country":"SI",
    "name:bos_x_preferred":[
        "Draga"
    ],
    "name:ceb_x_preferred":[
        "Draga"
    ],
    "name:hrv_x_preferred":[
        "Draga"
    ],
    "name:nld_x_preferred":[
        "Draga"
    ],
    "name:pol_x_preferred":[
        "Draga"
    ],
    "name:ron_x_preferred":[
        "Draga"
    ],
    "name:slv_x_preferred":[
        "Draga"
    ],
    "name:ukr_x_preferred":[
        "\u0414\u0440\u0430\u0433\u0430"
    ],
    "wof:name":"Draga",
    "wof:placetype":"locality",
    "wof:population":136
},
  "geometry": {"coordinates":[14.35321,46.14783],"type":"Point"}
}