{
  "type": "Feature",
  "properties": {
    "gn:admin1_code":"H6",
    "gn:asciiname":"Tunjiska Mlaka",
    "gn:country_code":"SI",
    "gn:dem":388,
    "gn:feature_class":"P",
    "gn:feature_code":"PPL",
    "gn:name":"Tunji\u0161ka Mlaka",
    "gn:population":318,
    "gn:timezone":"Europe/Ljubljana",
    "iso:country":"SI",
    "name:bos_x_preferred":[
        "Tunji\u0161ka Mlaka"
    ],
    "name:ceb_x_preferred":[
        "Tunji\u0161ka Mlaka"
    ],
    "name:pol_x_preferred":[
        "Tunji\u0161ka Mlaka"
    ],
    "name:ron_x_preferred":[
        "Tunji\u0161ka Mlaka"
    ],
    "name:slv_x_preferred":[
        "Tunji\u0161ka Mlaka"
    ],
    "name:ukr_x_preferred":[
        "\u0422\u0443\u043d\u0456\u0448\u043a\u0430 \u041c\u043b\u0430\u043a\u0430"
    ],
    "name:und_x_variant":[
        "Tunji\u0161ka Mlaka"
    ],
    "wof:name":"Tunjiska Mlaka",
    "wof:placetype":"locality",
    "wof:population":318
},
  "geometry": {"coordinates":[14.58364,46.23412],"type":"Point"}
}