{
  "type": "Feature",
  "properties": {
    "gn:admin1_code":"52",
    "gn:asciiname":"Prase",
    "gn:country_code":"SI",
    "gn:dem":360,
    "gn:feature_class":"P",
    "gn:feature_code":"PPL",
    "gn:name":"Pra\u0161e",
    "gn:population":214,
    "gn:timezone":"Europe/Ljubljana",
    "iso:country":"SI",
    "name:bos_x_preferred":[
        "Pra\u0161e"
    ],
    "name:ceb_x_preferred":[
        "Pra\u0161e"
    ],
    "name:hrv_x_preferred":[
        "Pra\u0161e"
    ],
    "name:nld_x_preferred":[
        "Pra\u0161e"
    ],
    "name:pol_x_preferred":[
        "Pra\u0161e"
    ],
    "name:ron_x_preferred":[
        "Pra\u0161e"
    ],
    "name:slv_x_preferred":[
        "Pra\u0161e"
    ],
    "name:ukr_x_preferred":[
        "\u041f\u0440\u0430\u0448\u0435"
    ],
    "name:und_x_variant":[
        "Pra\u0161e"
    ],
    "wof:name":"Prase",
    "wof:placetype":"locality",
    "wof:population":214
},
  "geometry": {"coordinates":[14.40194,46.19472],"type":"Point"}
}