{
  "type": "Feature",
  "properties": {
    "gn:admin1_code":"L9",
    "gn:asciiname":"Racica",
    "gn:country_code":"SI",
    "gn:dem":507,
    "gn:feature_class":"P",
    "gn:feature_code":"PPL",
    "gn:name":"Ra\u010dica",
    "gn:population":54,
    "gn:timezone":"Europe/Ljubljana",
    "iso:country":"SI",
    "name:bos_x_preferred":[
        "Ra\u010dica"
    ],
    "name:nld_x_preferred":[
        "Ra\u010dica"
    ],
    "name:pol_x_preferred":[
        "Ra\u010dica"
    ],
    "name:ron_x_preferred":[
        "Ra\u010dica"
    ],
    "name:slv_x_preferred":[
        "Ra\u010dica"
    ],
    "name:ukr_x_preferred":[
        "\u0420\u0430\u0447\u0438\u0446\u044f"
    ],
    "wof:name":"Racica",
    "wof:placetype":"locality",
    "wof:population":54
},
  "geometry": {"coordinates":[14.75293,46.03877],"type":"Point"}
}