{
  "type": "Feature",
  "properties": {
    "gn:admin1_code":"L9",
    "gn:asciiname":"Racica",
    "gn:country_code":"SI",
    "gn:dem":507,
    "gn:feature_class":"P",
    "gn:feature_code":"PPL",
    "gn:name":"Ra\u010dica",
    "gn:population":54,
    "gn:timezone":"Europe/Ljubljana",
    "iso:country":"SI",
    "name:und_x_variant":[
        "Ra\u010dica"
    ],
    "wof:name":"Racica",
    "wof:placetype":"locality",
    "wof:population":54
},
  "geometry": {"coordinates":[14.75293,46.03877],"type":"Point"}
}