{
  "type": "Feature",
  "properties": {
    "gn:admin1_code":"J7",
    "gn:asciiname":"Gorenje Lakovnice",
    "gn:country_code":"SI",
    "gn:dem":250,
    "gn:feature_class":"P",
    "gn:feature_code":"PPL",
    "gn:name":"Gorenje Lakovnice",
    "gn:population":82,
    "gn:timezone":"Europe/Ljubljana",
    "iso:country":"SI",
    "name:bos_x_preferred":[
        "Gorenje Lakovnice"
    ],
    "name:hrv_x_preferred":[
        "Gorenje Lakovnice"
    ],
    "name:nld_x_preferred":[
        "Gorenje Lakovnice"
    ],
    "name:pol_x_preferred":[
        "Gorenje Lakovnice"
    ],
    "name:ron_x_preferred":[
        "Gorenje Lakovnice"
    ],
    "name:slv_x_preferred":[
        "Gorenje Lakovnice"
    ],
    "name:ukr_x_preferred":[
        "\u0413\u043e\u0440\u0435\u043d\u0454 \u041b\u0430\u043a\u043e\u0432\u043d\u0438\u0446\u0435"
    ],
    "wof:name":"Gorenje Lakovnice",
    "wof:placetype":"locality",
    "wof:population":82
},
  "geometry": {"coordinates":[15.16667,45.75],"type":"Point"}
}