{
  "type": "Feature",
  "properties": {
    "gn:admin1_code":"J7",
    "gn:asciiname":"Laze",
    "gn:country_code":"SI",
    "gn:dem":334,
    "gn:feature_class":"P",
    "gn:feature_code":"PPL",
    "gn:name":"Laze",
    "gn:population":68,
    "gn:timezone":"Europe/Ljubljana",
    "iso:country":"SI",
    "name:bos_x_preferred":[
        "Laze"
    ],
    "name:hrv_x_preferred":[
        "Laze"
    ],
    "name:nld_x_preferred":[
        "Laze"
    ],
    "name:pol_x_preferred":[
        "Laze"
    ],
    "name:ron_x_preferred":[
        "Laze"
    ],
    "name:slv_x_preferred":[
        "Laze"
    ],
    "name:ukr_x_preferred":[
        "\u041b\u0430\u0437\u0435"
    ],
    "wof:name":"Laze",
    "wof:placetype":"locality",
    "wof:population":68
},
  "geometry": {"coordinates":[15.13538,45.70138],"type":"Point"}
}