{
  "type": "Feature",
  "properties": {
    "gn:admin1_code":"J1",
    "gn:asciiname":"Stanecka Vas",
    "gn:country_code":"SI",
    "gn:dem":275,
    "gn:feature_class":"P",
    "gn:feature_code":"PPL",
    "gn:name":"Stane\u010dka Vas",
    "gn:population":94,
    "gn:timezone":"Europe/Ljubljana",
    "iso:country":"SI",
    "name:bos_x_preferred":[
        "Stane\u010dka vas"
    ],
    "name:nld_x_preferred":[
        "Stane\u010dka vas"
    ],
    "name:pol_x_preferred":[
        "Stane\u010dka vas"
    ],
    "name:ron_x_preferred":[
        "Stane\u010dka vas"
    ],
    "name:slv_x_preferred":[
        "Stane\u010dka vas"
    ],
    "name:und_x_variant":[
        "Stane\u010dka Vas"
    ],
    "wof:name":"Stanecka Vas",
    "wof:placetype":"locality",
    "wof:population":94
},
  "geometry": {"coordinates":[15.7458,46.34237],"type":"Point"}
}