{
  "type": "Feature",
  "properties": {
    "gn:admin1_code":"B8",
    "gn:asciiname":"Osrecje",
    "gn:country_code":"SI",
    "gn:dem":228,
    "gn:feature_class":"P",
    "gn:feature_code":"PPL",
    "gn:name":"Osre\u010dje",
    "gn:population":78,
    "gn:timezone":"Europe/Ljubljana",
    "iso:country":"SI",
    "name:bos_x_preferred":[
        "Osre\u010dje"
    ],
    "name:hrv_x_preferred":[
        "Osre\u010dje"
    ],
    "name:nld_x_preferred":[
        "Osre\u010dje"
    ],
    "name:pol_x_preferred":[
        "Osre\u010dje"
    ],
    "name:ron_x_preferred":[
        "Osre\u010dje"
    ],
    "name:slv_x_preferred":[
        "Osre\u010dje"
    ],
    "name:ukr_x_preferred":[
        "\u041e\u0441\u0440\u0435\u0447\u0454"
    ],
    "wof:name":"Osrecje",
    "wof:placetype":"locality",
    "wof:population":78
},
  "geometry": {"coordinates":[15.27912,45.88967],"type":"Point"}
}