{
  "type": "Feature",
  "properties": {
    "gn:admin1_code":"54",
    "gn:asciiname":"Ravni",
    "gn:country_code":"SI",
    "gn:dem":237,
    "gn:feature_class":"P",
    "gn:feature_code":"PPL",
    "gn:name":"Ravni",
    "gn:population":63,
    "gn:timezone":"Europe/Ljubljana",
    "iso:country":"SI",
    "name:und_x_variant":[
        "Ravno"
    ],
    "wof:name":"Ravni",
    "wof:placetype":"locality",
    "wof:population":63
},
  "geometry": {"coordinates":[15.40523,45.94167],"type":"Point"}
}