{
  "type": "Feature",
  "properties": {
    "gn:admin1_code":"13",
    "gn:asciiname":"Zahrib",
    "gn:country_code":"SI",
    "gn:dem":711,
    "gn:feature_class":"P",
    "gn:feature_code":"PPL",
    "gn:name":"Zahrib",
    "gn:population":4,
    "gn:timezone":"Europe/Ljubljana",
    "iso:country":"SI",
    "name:bos_x_preferred":[
        "Zahrib"
    ],
    "name:hrv_x_preferred":[
        "Zahrib"
    ],
    "name:nld_x_preferred":[
        "Zahrib"
    ],
    "name:pol_x_preferred":[
        "Zahrib"
    ],
    "name:ron_x_preferred":[
        "Zahrib"
    ],
    "name:slv_x_preferred":[
        "Zahrib"
    ],
    "name:ukr_x_preferred":[
        "\u0417\u0430\u0445\u0440\u0438\u0431"
    ],
    "name:urd_x_preferred":[
        "\u0632\u06c1\u0631\u0628"
    ],
    "wof:name":"Zahrib",
    "wof:placetype":"locality",
    "wof:population":4
},
  "geometry": {"coordinates":[14.4943,45.8496],"type":"Point"}
}