{
  "type": "Feature",
  "properties": {
    "gn:admin1_code":"13",
    "gn:asciiname":"Zahrib",
    "gn:country_code":"SI",
    "gn:dem":711,
    "gn:feature_class":"P",
    "gn:feature_code":"PPL",
    "gn:name":"Zahrib",
    "gn:population":4,
    "gn:timezone":"Europe/Ljubljana",
    "iso:country":"SI",
    "wof:name":"Zahrib",
    "wof:placetype":"locality",
    "wof:population":4
},
  "geometry": {"coordinates":[14.4943,45.8496],"type":"Point"}
}