{
  "type": "Feature",
  "properties": {
    "gn:admin1_code":"F3",
    "gn:asciiname":"Radana Vas",
    "gn:country_code":"SI",
    "gn:dem":368,
    "gn:feature_class":"P",
    "gn:feature_code":"PPL",
    "gn:name":"Radana Vas",
    "gn:population":145,
    "gn:timezone":"Europe/Ljubljana",
    "iso:country":"SI",
    "name:bos_x_preferred":[
        "Radana vas"
    ],
    "name:ceb_x_preferred":[
        "Radana Vas"
    ],
    "name:hrv_x_preferred":[
        "Radana vas"
    ],
    "name:nld_x_preferred":[
        "Radana vas"
    ],
    "name:pol_x_preferred":[
        "Radana vas"
    ],
    "name:ron_x_preferred":[
        "Radana vas"
    ],
    "name:slv_x_preferred":[
        "Radana vas"
    ],
    "name:ukr_x_preferred":[
        "\u0420\u0430\u0434\u0430\u043d\u0430 \u0412\u0430\u0441"
    ],
    "wof:name":"Radana Vas",
    "wof:placetype":"locality",
    "wof:population":145
},
  "geometry": {"coordinates":[15.40402,46.36605],"type":"Point"}
}