{
  "type": "Feature",
  "properties": {
    "gn:admin1_code":"F3",
    "gn:asciiname":"Radana Vas",
    "gn:country_code":"SI",
    "gn:dem":368,
    "gn:feature_class":"P",
    "gn:feature_code":"PPL",
    "gn:name":"Radana Vas",
    "gn:population":145,
    "gn:timezone":"Europe/Ljubljana",
    "iso:country":"SI",
    "wof:name":"Radana Vas",
    "wof:placetype":"locality",
    "wof:population":145
},
  "geometry": {"coordinates":[15.40402,46.36605],"type":"Point"}
}