{
  "type": "Feature",
  "properties": {
    "gn:admin1_code":"68",
    "gn:asciiname":"Ucak",
    "gn:country_code":"SI",
    "gn:dem":567,
    "gn:feature_class":"P",
    "gn:feature_code":"PPL",
    "gn:name":"U\u010dak",
    "gn:population":37,
    "gn:timezone":"Europe/Ljubljana",
    "iso:country":"SI",
    "name:und_x_variant":[
        "U\u010dak"
    ],
    "wof:name":"Ucak",
    "wof:placetype":"locality",
    "wof:population":37
},
  "geometry": {"coordinates":[14.86385,46.18795],"type":"Point"}
}