{
  "type": "Feature",
  "properties": {
    "gn:admin1_code":"68",
    "gn:asciiname":"Ucak",
    "gn:country_code":"SI",
    "gn:dem":567,
    "gn:feature_class":"P",
    "gn:feature_code":"PPL",
    "gn:name":"U\u010dak",
    "gn:population":37,
    "gn:timezone":"Europe/Ljubljana",
    "iso:country":"SI",
    "name:bos_x_preferred":[
        "U\u010dak"
    ],
    "name:nld_x_preferred":[
        "U\u010dak"
    ],
    "name:pol_x_preferred":[
        "U\u010dak"
    ],
    "name:ron_x_preferred":[
        "U\u010dak"
    ],
    "name:slv_x_preferred":[
        "U\u010dak"
    ],
    "name:ukr_x_preferred":[
        "\u0423\u0447\u0430\u043a"
    ],
    "name:urd_x_preferred":[
        "\u0627\u0686\u0627\u06a9"
    ],
    "wof:name":"Ucak",
    "wof:placetype":"locality",
    "wof:population":37
},
  "geometry": {"coordinates":[14.86385,46.18795],"type":"Point"}
}