{
  "type": "Feature",
  "properties": {
    "gn:admin1_code":"87",
    "gn:asciiname":"Senesci",
    "gn:country_code":"SI",
    "gn:dem":260,
    "gn:feature_class":"P",
    "gn:feature_code":"PPL",
    "gn:name":"Sene\u0161ci",
    "gn:population":240,
    "gn:timezone":"Europe/Ljubljana",
    "iso:country":"SI",
    "name:bos_x_preferred":[
        "Sene\u0161ci"
    ],
    "name:bul_x_preferred":[
        "\u0421\u0435\u043d\u0435\u0448\u0446\u0438"
    ],
    "name:ceb_x_preferred":[
        "Sene\u0161ci"
    ],
    "name:nld_x_preferred":[
        "Sene\u0161ci"
    ],
    "name:pol_x_preferred":[
        "Sene\u0161ci"
    ],
    "name:ron_x_preferred":[
        "Sene\u0161ci"
    ],
    "name:slv_x_preferred":[
        "Sene\u0161ci"
    ],
    "name:ukr_x_preferred":[
        "\u0421\u0435\u043d\u0435\u0448\u0446\u0456"
    ],
    "name:und_x_variant":[
        "Sene\u0161ci"
    ],
    "wof:name":"Senesci",
    "wof:placetype":"locality",
    "wof:population":240
},
  "geometry": {"coordinates":[16.09258,46.42747],"type":"Point"}
}