{
  "type": "Feature",
  "properties": {
    "gn:admin1_code":"B9",
    "gn:asciiname":"Knape",
    "gn:country_code":"SI",
    "gn:dem":494,
    "gn:feature_class":"P",
    "gn:feature_code":"PPL",
    "gn:name":"Knape",
    "gn:population":78,
    "gn:timezone":"Europe/Ljubljana",
    "iso:country":"SI",
    "name:bos_x_preferred":[
        "Knape"
    ],
    "name:hrv_x_preferred":[
        "Knape"
    ],
    "name:nld_x_preferred":[
        "Knape"
    ],
    "name:pol_x_preferred":[
        "Knape"
    ],
    "name:ron_x_preferred":[
        "Knape"
    ],
    "name:slv_x_preferred":[
        "Knape"
    ],
    "name:ukr_x_preferred":[
        "\u041a\u043d\u0430\u043f\u0435"
    ],
    "wof:name":"Knape",
    "wof:placetype":"locality",
    "wof:population":78
},
  "geometry": {"coordinates":[14.25085,46.21834000000001],"type":"Point"}
}