{
  "type": "Feature",
  "properties": {
    "gn:admin1_code":"61",
    "gn:asciiname":"Smartno pod Smarno Goro",
    "gn:country_code":"SI",
    "gn:dem":324,
    "gn:feature_class":"P",
    "gn:feature_code":"PPL",
    "gn:name":"\u0160martno pod \u0160marno Goro",
    "gn:population":0,
    "gn:timezone":"Europe/Ljubljana",
    "iso:country":"SI",
    "name:slv_x_preferred":[
        "\u0160martno pod \u0160marno goro"
    ],
    "name:und_x_variant":[
        "\u0160martno",
        "\u0160martin",
        "\u0160martno pod \u0160marno Goro"
    ],
    "wof:name":"Smartno pod Smarno Goro",
    "wof:placetype":"locality"
},
  "geometry": {"coordinates":[14.48333,46.13333],"type":"Point"}
}