{
  "type": "Feature",
  "properties": {
    "gn:admin1_code":"D8",
    "gn:asciiname":"Zgonce",
    "gn:country_code":"SI",
    "gn:dem":598,
    "gn:feature_class":"P",
    "gn:feature_code":"PPL",
    "gn:name":"Zgon\u010de",
    "gn:population":8,
    "gn:timezone":"Europe/Ljubljana",
    "iso:country":"SI",
    "name:und_x_variant":[
        "Zgon\u010de"
    ],
    "wof:name":"Zgonce",
    "wof:placetype":"locality",
    "wof:population":8
},
  "geometry": {"coordinates":[14.58611,45.83167],"type":"Point"}
}