{
  "type": "Feature",
  "properties": {
    "gn:admin1_code":"46",
    "gn:asciiname":"Sedlo",
    "gn:country_code":"SI",
    "gn:dem":523,
    "gn:feature_class":"P",
    "gn:feature_code":"PPL",
    "gn:name":"Sedlo",
    "gn:population":81,
    "gn:timezone":"Europe/Ljubljana",
    "iso:country":"SI",
    "name:bos_x_preferred":[
        "Sedlo"
    ],
    "name:ita_x_preferred":[
        "Sedula"
    ],
    "name:nld_x_preferred":[
        "Sedlo"
    ],
    "name:pol_x_preferred":[
        "Sedlo"
    ],
    "name:ron_x_preferred":[
        "Sedlo"
    ],
    "name:slv_x_preferred":[
        "Sedlo"
    ],
    "name:ukr_x_preferred":[
        "\u0421\u0435\u0434\u043b\u043e"
    ],
    "wof:name":"Sedlo",
    "wof:placetype":"locality",
    "wof:population":81
},
  "geometry": {"coordinates":[13.44083,46.25472],"type":"Point"}
}