{
  "type": "Feature",
  "properties": {
    "gn:admin1_code":"46",
    "gn:asciiname":"Sedlo",
    "gn:country_code":"SI",
    "gn:dem":523,
    "gn:feature_class":"P",
    "gn:feature_code":"PPL",
    "gn:name":"Sedlo",
    "gn:population":81,
    "gn:timezone":"Europe/Ljubljana",
    "iso:country":"SI",
    "name:und_x_variant":[
        "Sedula",
        "Sedlo"
    ],
    "wof:name":"Sedlo",
    "wof:placetype":"locality",
    "wof:population":81
},
  "geometry": {"coordinates":[13.44083,46.25472],"type":"Point"}
}