{
  "type": "Feature",
  "properties": {
    "gn:admin1_code":"L8",
    "gn:asciiname":"Jesovec",
    "gn:country_code":"SI",
    "gn:dem":262,
    "gn:feature_class":"P",
    "gn:feature_code":"PPL",
    "gn:name":"Je\u0161ovec",
    "gn:population":17,
    "gn:timezone":"Europe/Ljubljana",
    "iso:country":"SI",
    "name:und_x_variant":[
        "Je\u0161ovec"
    ],
    "wof:name":"Jesovec",
    "wof:placetype":"locality",
    "wof:population":17
},
  "geometry": {"coordinates":[15.63115,46.33084],"type":"Point"}
}