{
  "type": "Feature",
  "properties": {
    "gn:admin1_code":"A7",
    "gn:asciiname":"Zgornje Negonje",
    "gn:country_code":"SI",
    "gn:dem":448,
    "gn:feature_class":"P",
    "gn:feature_code":"PPL",
    "gn:name":"Zgornje Negonje",
    "gn:population":130,
    "gn:timezone":"Europe/Ljubljana",
    "iso:country":"SI",
    "name:bos_x_preferred":[
        "Zgornje Negonje"
    ],
    "name:bul_x_preferred":[
        "\u0417\u0433\u043e\u0440\u043d\u0435 \u041d\u0435\u0433\u043e\u043d\u0435"
    ],
    "name:ceb_x_preferred":[
        "Zgornje Negonje"
    ],
    "name:hrv_x_preferred":[
        "Zgornje Negonje"
    ],
    "name:nld_x_preferred":[
        "Zgornje Negonje"
    ],
    "name:pol_x_preferred":[
        "Zgornje Negonje"
    ],
    "name:ron_x_preferred":[
        "Zgornje Negonje"
    ],
    "name:slv_x_preferred":[
        "Zgornje Negonje"
    ],
    "name:ukr_x_preferred":[
        "\u0417\u0433\u043e\u0440\u043d\u0454 \u041d\u0435\u0433\u043e\u043d\u0454"
    ],
    "wof:name":"Zgornje Negonje",
    "wof:placetype":"locality",
    "wof:population":130
},
  "geometry": {"coordinates":[15.62572,46.26743],"type":"Point"}
}