{
  "type": "Feature",
  "properties": {
    "gn:admin1_code":"A7",
    "gn:asciiname":"Zgornje Negonje",
    "gn:country_code":"SI",
    "gn:dem":448,
    "gn:feature_class":"P",
    "gn:feature_code":"PPL",
    "gn:name":"Zgornje Negonje",
    "gn:population":130,
    "gn:timezone":"Europe/Ljubljana",
    "iso:country":"SI",
    "wof:name":"Zgornje Negonje",
    "wof:placetype":"locality",
    "wof:population":130
},
  "geometry": {"coordinates":[15.62572,46.26743],"type":"Point"}
}