{
  "type": "Feature",
  "properties": {
    "gn:admin1_code":"04",
    "gn:asciiname":"Praprotnica",
    "gn:country_code":"SI",
    "gn:dem":1263,
    "gn:feature_class":"P",
    "gn:feature_code":"PPL",
    "gn:name":"Praprotnica",
    "gn:population":0,
    "gn:timezone":"Europe/Ljubljana",
    "iso:country":"SI",
    "name:bos_x_preferred":[
        "Praprotnica"
    ],
    "name:hrv_x_preferred":[
        "Praprotnica"
    ],
    "name:nld_x_preferred":[
        "Praprotnica"
    ],
    "name:pol_x_preferred":[
        "Praprotnica"
    ],
    "name:ron_x_preferred":[
        "Praprotnica"
    ],
    "name:slv_x_preferred":[
        "Praprotnica"
    ],
    "name:ukr_x_preferred":[
        "\u041f\u0440\u0430\u043f\u0440\u043e\u0442\u043d\u0438\u0446\u044f"
    ],
    "wof:name":"Praprotnica",
    "wof:placetype":"locality"
},
  "geometry": {"coordinates":[13.91972,46.32944000000001],"type":"Point"}
}