{
  "type": "Feature",
  "properties": {
    "gn:admin1_code":"04",
    "gn:asciiname":"Praprotnica",
    "gn:country_code":"SI",
    "gn:dem":1263,
    "gn:feature_class":"P",
    "gn:feature_code":"PPL",
    "gn:name":"Praprotnica",
    "gn:population":0,
    "gn:timezone":"Europe/Ljubljana",
    "iso:country":"SI",
    "wof:name":"Praprotnica",
    "wof:placetype":"locality"
},
  "geometry": {"coordinates":[13.91972,46.32944000000001],"type":"Point"}
}