{
  "type": "Feature",
  "properties": {
    "gn:admin1_code":"L7",
    "gn:asciiname":"Okrog",
    "gn:country_code":"SI",
    "gn:dem":309,
    "gn:feature_class":"P",
    "gn:feature_code":"PPL",
    "gn:name":"Okrog",
    "gn:population":98,
    "gn:timezone":"Europe/Ljubljana",
    "iso:country":"SI",
    "name:bos_x_preferred":[
        "Okrog"
    ],
    "name:nld_x_preferred":[
        "Okrog"
    ],
    "name:pol_x_preferred":[
        "Okrog"
    ],
    "name:ron_x_preferred":[
        "Okrog"
    ],
    "name:slv_x_preferred":[
        "Okrog"
    ],
    "name:ukr_x_preferred":[
        "\u041e\u043a\u0440\u043e\u0433"
    ],
    "wof:name":"Okrog",
    "wof:placetype":"locality",
    "wof:population":98
},
  "geometry": {"coordinates":[15.47136,46.25088],"type":"Point"}
}