{
  "type": "Feature",
  "properties": {
    "gn:admin1_code":"50",
    "gn:asciiname":"Socerga",
    "gn:country_code":"SI",
    "gn:dem":297,
    "gn:feature_class":"P",
    "gn:feature_code":"PPL",
    "gn:name":"So\u010derga",
    "gn:population":66,
    "gn:timezone":"Europe/Ljubljana",
    "iso:country":"SI",
    "name:bos_x_preferred":[
        "So\u010derga"
    ],
    "name:bul_x_preferred":[
        "\u0421\u043e\u0447\u0435\u0440\u0433\u0430"
    ],
    "name:ita_x_preferred":[
        "San Quirico"
    ],
    "name:nld_x_preferred":[
        "So\u010derga"
    ],
    "name:pol_x_preferred":[
        "So\u010derga"
    ],
    "name:ron_x_preferred":[
        "So\u010derga"
    ],
    "name:slv_x_preferred":[
        "So\u010derga"
    ],
    "name:ukr_x_preferred":[
        "\u0421\u043e\u0447\u0435\u0440\u0433\u0430"
    ],
    "wof:name":"Socerga",
    "wof:placetype":"locality",
    "wof:population":66
},
  "geometry": {"coordinates":[13.89472,45.46444],"type":"Point"}
}