{
  "type": "Feature",
  "properties": {
    "gn:admin1_code":"54",
    "gn:asciiname":"Spodnje Pijavsko",
    "gn:country_code":"SI",
    "gn:dem":229,
    "gn:feature_class":"P",
    "gn:feature_code":"PPL",
    "gn:name":"Spodnje Pijav\u0161ko",
    "gn:population":20,
    "gn:timezone":"Europe/Ljubljana",
    "iso:country":"SI",
    "name:und_x_variant":[
        "Spodnje Pijav\u0161ko"
    ],
    "wof:name":"Spodnje Pijavsko",
    "wof:placetype":"locality",
    "wof:population":20
},
  "geometry": {"coordinates":[15.44806,45.98427],"type":"Point"}
}