{
  "type": "Feature",
  "properties": {
    "gn:admin1_code":"54",
    "gn:asciiname":"Spodnje Pijavsko",
    "gn:country_code":"SI",
    "gn:dem":229,
    "gn:feature_class":"P",
    "gn:feature_code":"PPL",
    "gn:name":"Spodnje Pijav\u0161ko",
    "gn:population":20,
    "gn:timezone":"Europe/Ljubljana",
    "iso:country":"SI",
    "name:bos_x_preferred":[
        "Spodnje Pijav\u0161ko"
    ],
    "name:hrv_x_preferred":[
        "Spodnje Pijav\u0161ko"
    ],
    "name:nld_x_preferred":[
        "Spodnje Pijav\u0161ko"
    ],
    "name:pol_x_preferred":[
        "Spodnje Pijav\u0161ko"
    ],
    "name:ron_x_preferred":[
        "Spodnje Pijav\u0161ko"
    ],
    "name:slv_x_preferred":[
        "Spodnje Pijav\u0161ko"
    ],
    "name:ukr_x_preferred":[
        "\u0421\u043f\u043e\u0434\u043d\u0454 \u041f\u0456\u044f\u0432\u0448\u043a\u043e"
    ],
    "wof:name":"Spodnje Pijavsko",
    "wof:placetype":"locality",
    "wof:population":20
},
  "geometry": {"coordinates":[15.44806,45.98427],"type":"Point"}
}