{
  "type": "Feature",
  "properties": {
    "gn:admin1_code":"I6",
    "gn:asciiname":"Sitarovci",
    "gn:country_code":"SI",
    "gn:dem":192,
    "gn:feature_class":"P",
    "gn:feature_code":"PPL",
    "gn:name":"Sitarovci",
    "gn:population":31,
    "gn:timezone":"Europe/Ljubljana",
    "iso:country":"SI",
    "wof:name":"Sitarovci",
    "wof:placetype":"locality",
    "wof:population":31
},
  "geometry": {"coordinates":[16.0815,46.52353],"type":"Point"}
}