{
  "type": "Feature",
  "properties": {
    "gn:admin1_code":"I6",
    "gn:asciiname":"Sitarovci",
    "gn:country_code":"SI",
    "gn:dem":192,
    "gn:feature_class":"P",
    "gn:feature_code":"PPL",
    "gn:name":"Sitarovci",
    "gn:population":31,
    "gn:timezone":"Europe/Ljubljana",
    "iso:country":"SI",
    "name:bos_x_preferred":[
        "Sitarovci"
    ],
    "name:hrv_x_preferred":[
        "Sitarovci"
    ],
    "name:nld_x_preferred":[
        "Sitarovci"
    ],
    "name:pol_x_preferred":[
        "Sitarovci"
    ],
    "name:ron_x_preferred":[
        "Sitarovci"
    ],
    "name:slv_x_preferred":[
        "Sitarovci"
    ],
    "name:ukr_x_preferred":[
        "\u0421\u0438\u0442\u0430\u0440\u043e\u0432\u0446\u0456"
    ],
    "wof:name":"Sitarovci",
    "wof:placetype":"locality",
    "wof:population":31
},
  "geometry": {"coordinates":[16.0815,46.52353],"type":"Point"}
}