{
  "type": "Feature",
  "properties": {
    "gn:admin1_code":"D4",
    "gn:asciiname":"Vrh pri Sobracah",
    "gn:cc2":"SI",
    "gn:country_code":"SI",
    "gn:dem":370,
    "gn:feature_class":"P",
    "gn:feature_code":"PPL",
    "gn:name":"Vrh pri Sobra\u010dah",
    "gn:population":24,
    "gn:timezone":"Europe/Ljubljana",
    "iso:country":"SI",
    "name:und_x_variant":[
        "Vrh"
    ],
    "wof:name":"Vrh pri Sobracah",
    "wof:placetype":"locality",
    "wof:population":24
},
  "geometry": {"coordinates":[14.88218,45.98575],"type":"Point"}
}