{
  "type": "Feature",
  "properties": {
    "gn:admin1_code":"D4",
    "gn:asciiname":"Vrh pri Sobracah",
    "gn:cc2":"SI",
    "gn:country_code":"SI",
    "gn:dem":370,
    "gn:feature_class":"P",
    "gn:feature_code":"PPL",
    "gn:name":"Vrh pri Sobra\u010dah",
    "gn:population":24,
    "gn:timezone":"Europe/Ljubljana",
    "iso:country":"SI",
    "name:bos_x_preferred":[
        "Vrh pri Sobra\u010dah"
    ],
    "name:nld_x_preferred":[
        "Vrh pri Sobra\u010dah"
    ],
    "name:pol_x_preferred":[
        "Vrh pri Sobra\u010dah"
    ],
    "name:ron_x_preferred":[
        "Vrh pri Sobra\u010dah"
    ],
    "name:slv_x_preferred":[
        "Vrh pri Sobra\u010dah"
    ],
    "name:ukr_x_preferred":[
        "\u0412\u0440\u0445-\u043f\u0440\u0438-\u0421\u043e\u0431\u0440\u0430\u0447\u0430\u0445"
    ],
    "name:und_x_variant":[
        "Vrh"
    ],
    "wof:name":"Vrh pri Sobracah",
    "wof:placetype":"locality",
    "wof:population":24
},
  "geometry": {"coordinates":[14.88218,45.98575],"type":"Point"}
}