{
  "type": "Feature",
  "properties": {
    "gn:admin1_code":"D8",
    "gn:asciiname":"Luzarji",
    "gn:country_code":"SI",
    "gn:dem":651,
    "gn:feature_class":"P",
    "gn:feature_code":"PPL",
    "gn:name":"Lu\u017earji",
    "gn:population":14,
    "gn:timezone":"Europe/Ljubljana",
    "iso:country":"SI",
    "name:bos_x_preferred":[
        "Lu\u017earji"
    ],
    "name:nld_x_preferred":[
        "Lu\u017earji"
    ],
    "name:pol_x_preferred":[
        "Lu\u017earji"
    ],
    "name:ron_x_preferred":[
        "Lu\u017earji"
    ],
    "name:slv_x_preferred":[
        "Lu\u017earji"
    ],
    "name:ukr_x_preferred":[
        "\u041b\u0443\u0436\u0430\u0440\u0456"
    ],
    "wof:name":"Luzarji",
    "wof:placetype":"locality",
    "wof:population":14
},
  "geometry": {"coordinates":[14.56417,45.79972],"type":"Point"}
}