{
  "type": "Feature",
  "properties": {
    "gn:admin1_code":"D8",
    "gn:asciiname":"Luzarji",
    "gn:country_code":"SI",
    "gn:dem":651,
    "gn:feature_class":"P",
    "gn:feature_code":"PPL",
    "gn:name":"Lu\u017earji",
    "gn:population":14,
    "gn:timezone":"Europe/Ljubljana",
    "iso:country":"SI",
    "name:und_x_variant":[
        "Lu\u017earji"
    ],
    "wof:name":"Luzarji",
    "wof:placetype":"locality",
    "wof:population":14
},
  "geometry": {"coordinates":[14.56417,45.79972],"type":"Point"}
}