{
  "type": "Feature",
  "properties": {
    "gn:admin1_code":"I6",
    "gn:asciiname":"Presika",
    "gn:country_code":"SI",
    "gn:dem":239,
    "gn:feature_class":"P",
    "gn:feature_code":"PPL",
    "gn:name":"Presika",
    "gn:population":144,
    "gn:timezone":"Europe/Ljubljana",
    "iso:country":"SI",
    "name:bos_x_preferred":[
        "Presika"
    ],
    "name:ceb_x_preferred":[
        "Presika"
    ],
    "name:deu_x_preferred":[
        "Presika"
    ],
    "name:hrv_x_preferred":[
        "Presika"
    ],
    "name:nld_x_preferred":[
        "Presika"
    ],
    "name:pol_x_preferred":[
        "Presika"
    ],
    "name:ron_x_preferred":[
        "Presika"
    ],
    "name:slv_x_preferred":[
        "Presika"
    ],
    "name:ukr_x_preferred":[
        "\u041f\u0440\u0435\u0441\u0438\u043a\u0430"
    ],
    "wof:name":"Presika",
    "wof:placetype":"locality",
    "wof:population":144
},
  "geometry": {"coordinates":[16.2382,46.50045],"type":"Point"}
}