{
  "type": "Feature",
  "properties": {
    "gn:admin1_code":"N3",
    "gn:asciiname":"Ivenca",
    "gn:country_code":"SI",
    "gn:dem":276,
    "gn:feature_class":"P",
    "gn:feature_code":"PPL",
    "gn:name":"Ivenca",
    "gn:population":187,
    "gn:timezone":"Europe/Ljubljana",
    "iso:country":"SI",
    "name:bos_x_preferred":[
        "Ivenca"
    ],
    "name:ceb_x_preferred":[
        "Ivenca"
    ],
    "name:hrv_x_preferred":[
        "Ivenca"
    ],
    "name:nld_x_preferred":[
        "Ivenca"
    ],
    "name:pol_x_preferred":[
        "Ivenca"
    ],
    "name:ron_x_preferred":[
        "Ivenca"
    ],
    "name:slv_x_preferred":[
        "Ivenca"
    ],
    "name:ukr_x_preferred":[
        "\u0406\u0432\u0435\u043d\u0446\u0430"
    ],
    "wof:name":"Ivenca",
    "wof:placetype":"locality",
    "wof:population":187
},
  "geometry": {"coordinates":[15.3105,46.30259],"type":"Point"}
}