{
  "type": "Feature",
  "properties": {
    "gn:admin1_code":"N3",
    "gn:asciiname":"Ivenca",
    "gn:country_code":"SI",
    "gn:dem":276,
    "gn:feature_class":"P",
    "gn:feature_code":"PPL",
    "gn:name":"Ivenca",
    "gn:population":187,
    "gn:timezone":"Europe/Ljubljana",
    "iso:country":"SI",
    "wof:name":"Ivenca",
    "wof:placetype":"locality",
    "wof:population":187
},
  "geometry": {"coordinates":[15.3105,46.30259],"type":"Point"}
}