{
  "type": "Feature",
  "properties": {
    "gn:admin1_code":"77",
    "gn:asciiname":"Limbarska Gora",
    "gn:country_code":"SI",
    "gn:dem":700,
    "gn:feature_class":"P",
    "gn:feature_code":"PPL",
    "gn:name":"Limbarska Gora",
    "gn:population":118,
    "gn:timezone":"Europe/Ljubljana",
    "iso:country":"SI",
    "wof:name":"Limbarska Gora",
    "wof:placetype":"locality",
    "wof:population":118
},
  "geometry": {"coordinates":[14.77252,46.15773],"type":"Point"}
}