{
  "type": "Feature",
  "properties": {
    "gn:admin1_code":"77",
    "gn:asciiname":"Limbarska Gora",
    "gn:country_code":"SI",
    "gn:dem":700,
    "gn:feature_class":"P",
    "gn:feature_code":"PPL",
    "gn:name":"Limbarska Gora",
    "gn:population":118,
    "gn:timezone":"Europe/Ljubljana",
    "iso:country":"SI",
    "name:bos_x_preferred":[
        "Limbarska Gora"
    ],
    "name:ceb_x_preferred":[
        "Limbarska Gora"
    ],
    "name:nld_x_preferred":[
        "Limbarska Gora"
    ],
    "name:pol_x_preferred":[
        "Limbarska Gora"
    ],
    "name:ron_x_preferred":[
        "Limbarska Gora"
    ],
    "name:slv_x_preferred":[
        "Limbarska Gora"
    ],
    "name:ukr_x_preferred":[
        "\u041b\u0438\u043c\u0431\u0430\u0440\u0441\u044c\u043a\u0430 \u0413\u043e\u0440\u0430"
    ],
    "wof:name":"Limbarska Gora",
    "wof:placetype":"locality",
    "wof:population":118
},
  "geometry": {"coordinates":[14.77252,46.15773],"type":"Point"}
}