{
  "type": "Feature",
  "properties": {
    "gn:admin1_code":"I4",
    "gn:asciiname":"Centiba",
    "gn:country_code":"SI",
    "gn:dem":198,
    "gn:feature_class":"P",
    "gn:feature_code":"PPL",
    "gn:name":"\u010centiba",
    "gn:population":839,
    "gn:timezone":"Europe/Ljubljana",
    "iso:country":"SI",
    "name:und_x_variant":[
        "Csentev\u00f6lgy",
        "Csente",
        "\u010centiba"
    ],
    "wof:name":"Centiba",
    "wof:placetype":"locality",
    "wof:population":839
},
  "geometry": {"coordinates":[16.4975,46.55556],"type":"Point"}
}