{
  "type": "Feature",
  "properties": {
    "gn:admin1_code":"I4",
    "gn:asciiname":"Centiba",
    "gn:country_code":"SI",
    "gn:dem":198,
    "gn:feature_class":"P",
    "gn:feature_code":"PPL",
    "gn:name":"\u010centiba",
    "gn:population":839,
    "gn:timezone":"Europe/Ljubljana",
    "iso:country":"SI",
    "name:bos_x_preferred":[
        "\u010centiba"
    ],
    "name:ceb_x_preferred":[
        "\u010centiba"
    ],
    "name:epo_x_preferred":[
        "\u010centiba"
    ],
    "name:hrv_x_preferred":[
        "\u010centiba"
    ],
    "name:hun_x_preferred":[
        "Csente"
    ],
    "name:nld_x_preferred":[
        "\u010centiba"
    ],
    "name:pol_x_preferred":[
        "\u010centiba"
    ],
    "name:ron_x_preferred":[
        "\u010centiba"
    ],
    "name:slv_x_preferred":[
        "\u010centiba"
    ],
    "name:ukr_x_preferred":[
        "\u0427\u0435\u043d\u0442\u0438\u0431\u0430"
    ],
    "name:und_x_variant":[
        "Csentev\u00f6lgy"
    ],
    "wof:name":"Centiba",
    "wof:placetype":"locality",
    "wof:population":839
},
  "geometry": {"coordinates":[16.4975,46.55556],"type":"Point"}
}