{
  "type": "Feature",
  "properties": {
    "gn:admin1_code":"89",
    "gn:asciiname":"Jareninski Dol",
    "gn:country_code":"SI",
    "gn:dem":270,
    "gn:feature_class":"P",
    "gn:feature_code":"PPL",
    "gn:name":"Jareninski Dol",
    "gn:population":391,
    "gn:timezone":"Europe/Ljubljana",
    "iso:country":"SI",
    "name:bos_x_preferred":[
        "Jareninski Dol"
    ],
    "name:ceb_x_preferred":[
        "Jareninski Dol"
    ],
    "name:nld_x_preferred":[
        "Jareninski Dol"
    ],
    "name:pol_x_preferred":[
        "Jareninski Dol"
    ],
    "name:ron_x_preferred":[
        "Jareninski Dol"
    ],
    "name:slv_x_preferred":[
        "Jareninski Dol"
    ],
    "name:ukr_x_preferred":[
        "\u042f\u0440\u0435\u043d\u0438\u043d\u0441\u044c\u043a\u0438\u0439 \u0414\u043e\u043b"
    ],
    "name:urd_x_preferred":[
        "\u062c\u0631\u0646\u0646\u0633\u06a9\u06cc \u0688\u0648\u0644"
    ],
    "wof:name":"Jareninski Dol",
    "wof:placetype":"locality",
    "wof:population":391
},
  "geometry": {"coordinates":[15.69889,46.62889000000001],"type":"Point"}
}