{
  "type": "Feature",
  "properties": {
    "gn:admin1_code":"89",
    "gn:asciiname":"Jareninski Dol",
    "gn:country_code":"SI",
    "gn:dem":270,
    "gn:feature_class":"P",
    "gn:feature_code":"PPL",
    "gn:name":"Jareninski Dol",
    "gn:population":391,
    "gn:timezone":"Europe/Ljubljana",
    "iso:country":"SI",
    "wof:name":"Jareninski Dol",
    "wof:placetype":"locality",
    "wof:population":391
},
  "geometry": {"coordinates":[15.69889,46.62889000000001],"type":"Point"}
}