{
  "type": "Feature",
  "properties": {
    "iso:country":"SI",
    "name:slv_x_preferred":[
        "Je\u017eica"
    ],
    "wof:name":"Jezica",
    "wof:placetype":"neighbourhood"
},
  "geometry": {"coordinates":[14.51241023811987,46.0940874996428],"type":"Point"}
}