{
  "type": "Feature",
  "properties": {
    "gn:admin1_code":"D7",
    "gn:asciiname":"Bevce",
    "gn:country_code":"SI",
    "gn:dem":414,
    "gn:feature_class":"P",
    "gn:feature_code":"PPL",
    "gn:name":"Bev\u010de",
    "gn:population":322,
    "gn:timezone":"Europe/Ljubljana",
    "iso:country":"SI",
    "name:und_x_variant":[
        "Bev\u010de"
    ],
    "wof:name":"Bevce",
    "wof:placetype":"locality",
    "wof:population":322
},
  "geometry": {"coordinates":[15.14384,46.35636],"type":"Point"}
}