{
  "type": "Feature",
  "properties": {
    "gn:admin1_code":"D7",
    "gn:asciiname":"Bevce",
    "gn:country_code":"SI",
    "gn:dem":414,
    "gn:feature_class":"P",
    "gn:feature_code":"PPL",
    "gn:name":"Bev\u010de",
    "gn:population":322,
    "gn:timezone":"Europe/Ljubljana",
    "iso:country":"SI",
    "name:bos_x_preferred":[
        "Bev\u010de"
    ],
    "name:ceb_x_preferred":[
        "Bev\u010de"
    ],
    "name:hrv_x_preferred":[
        "Bev\u010de"
    ],
    "name:ita_x_preferred":[
        "Bev\u010de"
    ],
    "name:nld_x_preferred":[
        "Bev\u010de"
    ],
    "name:pol_x_preferred":[
        "Bev\u010de"
    ],
    "name:ron_x_preferred":[
        "Bev\u010de"
    ],
    "name:slv_x_preferred":[
        "Bev\u010de"
    ],
    "name:ukr_x_preferred":[
        "\u0411\u0435\u0432\u0447\u0435"
    ],
    "wof:name":"Bevce",
    "wof:placetype":"locality",
    "wof:population":322
},
  "geometry": {"coordinates":[15.14384,46.35636],"type":"Point"}
}