{
  "type": "Feature",
  "properties": {
    "gn:admin1_code":"84",
    "gn:asciiname":"Podlesce",
    "gn:country_code":"SI",
    "gn:dem":718,
    "gn:feature_class":"P",
    "gn:feature_code":"PPL",
    "gn:name":"Podle\u0161\u010de",
    "gn:population":0,
    "gn:timezone":"Europe/Ljubljana",
    "iso:country":"SI",
    "wof:name":"Podlesce",
    "wof:placetype":"locality"
},
  "geometry": {"coordinates":[13.71448,46.05575],"type":"Point"}
}