{
  "type": "Feature",
  "properties": {
    "gn:admin1_code":"J6",
    "gn:asciiname":"Poljane pri Mirni Peci",
    "gn:country_code":"SI",
    "gn:dem":337,
    "gn:feature_class":"P",
    "gn:feature_code":"PPL",
    "gn:name":"Poljane pri Mirni Pe\u010di",
    "gn:population":73,
    "gn:timezone":"Europe/Ljubljana",
    "iso:country":"SI",
    "name:bos_x_preferred":[
        "Poljane pri Mirni Pe\u010di"
    ],
    "name:hrv_x_preferred":[
        "Poljane pri Mirni Pe\u010di"
    ],
    "name:nld_x_preferred":[
        "Poljane pri Mirni Pe\u010di"
    ],
    "name:pol_x_preferred":[
        "Poljane pri Mirni Pe\u010di"
    ],
    "name:ron_x_preferred":[
        "Poljane pri Mirni Pe\u010di"
    ],
    "name:slv_x_preferred":[
        "Poljane pri Mirni Pe\u010di"
    ],
    "name:ukr_x_preferred":[
        "\u041f\u043e\u043b\u044f\u043d\u0435-\u043f\u0440\u0438-\u041c\u0438\u0440\u043d\u0456\u0439 \u041f\u0435\u0447\u0456"
    ],
    "wof:name":"Poljane pri Mirni Peci",
    "wof:placetype":"locality",
    "wof:population":73
},
  "geometry": {"coordinates":[15.09137,45.89081],"type":"Point"}
}