{
  "type": "Feature",
  "properties": {
    "gn:admin1_code":"J6",
    "gn:asciiname":"Poljane pri Mirni Peci",
    "gn:country_code":"SI",
    "gn:dem":337,
    "gn:feature_class":"P",
    "gn:feature_code":"PPL",
    "gn:name":"Poljane pri Mirni Pe\u010di",
    "gn:population":73,
    "gn:timezone":"Europe/Ljubljana",
    "iso:country":"SI",
    "name:und_x_variant":[
        "Poljane pri Mirni Pe\u010di"
    ],
    "wof:name":"Poljane pri Mirni Peci",
    "wof:placetype":"locality",
    "wof:population":73
},
  "geometry": {"coordinates":[15.09137,45.89081],"type":"Point"}
}