{
  "type": "Feature",
  "properties": {
    "gn:admin1_code":"H6",
    "gn:asciiname":"Zakal",
    "gn:country_code":"SI",
    "gn:dem":655,
    "gn:feature_class":"P",
    "gn:feature_code":"PPL",
    "gn:name":"Zakal",
    "gn:population":58,
    "gn:timezone":"Europe/Ljubljana",
    "iso:country":"SI",
    "wof:name":"Zakal",
    "wof:placetype":"locality",
    "wof:population":58
},
  "geometry": {"coordinates":[14.57396,46.26561],"type":"Point"}
}