{
  "type": "Feature",
  "properties": {
    "gn:admin1_code":"44",
    "gn:asciiname":"Plave",
    "gn:country_code":"SI",
    "gn:dem":310,
    "gn:feature_class":"P",
    "gn:feature_code":"PPL",
    "gn:name":"Plave",
    "gn:population":249,
    "gn:timezone":"Europe/Ljubljana",
    "iso:country":"SI",
    "name:bos_x_preferred":[
        "Plave"
    ],
    "name:ceb_x_preferred":[
        "Plave"
    ],
    "name:ita_x_preferred":[
        "Plava"
    ],
    "name:nld_x_preferred":[
        "Plave"
    ],
    "name:pol_x_preferred":[
        "Plave"
    ],
    "name:ron_x_preferred":[
        "Plave"
    ],
    "name:slv_x_preferred":[
        "Plave"
    ],
    "name:ukr_x_preferred":[
        "\u041f\u043b\u0430\u0432\u0435"
    ],
    "name:und_x_variant":[
        "Plava",
        "Plave"
    ],
    "wof:name":"Plave",
    "wof:placetype":"locality",
    "wof:population":249
},
  "geometry": {"coordinates":[13.5975,46.04222],"type":"Point"}
}