{
  "type": "Feature",
  "properties": {
    "gn:admin1_code":"N3",
    "gn:asciiname":"Tomaz nad Vojnikom",
    "gn:country_code":"SI",
    "gn:dem":332,
    "gn:feature_class":"P",
    "gn:feature_code":"PPL",
    "gn:name":"Toma\u017e nad Vojnikom",
    "gn:population":72,
    "gn:timezone":"Europe/Ljubljana",
    "iso:country":"SI",
    "name:und_x_variant":[
        "Toma\u017e nad Vojnikom"
    ],
    "wof:name":"Tomaz nad Vojnikom",
    "wof:placetype":"locality",
    "wof:population":72
},
  "geometry": {"coordinates":[15.32598,46.28803],"type":"Point"}
}