{
  "type": "Feature",
  "properties": {
    "gn:admin1_code":"N3",
    "gn:asciiname":"Tomaz nad Vojnikom",
    "gn:country_code":"SI",
    "gn:dem":332,
    "gn:feature_class":"P",
    "gn:feature_code":"PPL",
    "gn:name":"Toma\u017e nad Vojnikom",
    "gn:population":72,
    "gn:timezone":"Europe/Ljubljana",
    "iso:country":"SI",
    "name:bos_x_preferred":[
        "Toma\u017e nad Vojnikom"
    ],
    "name:hrv_x_preferred":[
        "Toma\u017e nad Vojnikom"
    ],
    "name:nld_x_preferred":[
        "Toma\u017e nad Vojnikom"
    ],
    "name:pol_x_preferred":[
        "Toma\u017e nad Vojnikom"
    ],
    "name:ron_x_preferred":[
        "Toma\u017e nad Vojnikom"
    ],
    "name:slv_x_preferred":[
        "Toma\u017e nad Vojnikom"
    ],
    "name:ukr_x_preferred":[
        "\u0422\u043e\u043c\u0430\u0436-\u043d\u0430\u0434-\u0412\u043e\u0439\u043d\u0438\u043a\u043e\u043c"
    ],
    "name:und_x_variant":[
        "Toma\u017e nad Vojnikom"
    ],
    "wof:name":"Tomaz nad Vojnikom",
    "wof:placetype":"locality",
    "wof:population":72
},
  "geometry": {"coordinates":[15.32598,46.28803],"type":"Point"}
}