{
  "type": "Feature",
  "properties": {
    "gn:gn_country":"SI",
    "gn:gn_fcode":"PPL",
    "gn:gn_pop":0,
    "gn:population":7,
    "iso:country":"SI",
    "name:eng_x_preferred":[
        "Lukanja"
    ],
    "name:nld_x_preferred":[
        "Lukanja"
    ],
    "name:ron_x_preferred":[
        "Lukanja"
    ],
    "name:slv_x_preferred":[
        "Lukanja"
    ],
    "name:ukr_x_preferred":[
        "\u041b\u0443\u043a\u0430\u043d\u044f"
    ],
    "qs_pg:aaroncc":"SI",
    "qs_pg:gn_country":"SI",
    "qs_pg:gn_fcode":"PPL",
    "qs_pg:gn_pop":0,
    "qs_pg:name":"Lukanja",
    "qs_pg:name_adm0":"Slovenija",
    "qs_pg:name_adm1":"Slovenska Bistrica",
    "qs_pg:photos":20,
    "qs_pg:photos_1k":4,
    "qs_pg:photos_9k":1,
    "qs_pg:photos_9r":1,
    "qs_pg:photos_all":20,
    "qs_pg:photos_sr":1,
    "qs_pg:pop_sr":0,
    "qs_pg:qs_pg_placetype":"locality",
    "qs_pg:qs_pg_placetype_gp":"Town",
    "qs_pg:woe_adm0":23424945,
    "woe:adm0_id":23424945,
    "woe:name_adm0":"Slovenija",
    "woe:name_adm1":"Slovenska Bistrica",
    "woe:placetype":"Town",
    "wof:name":"Lukanja",
    "wof:placetype":"locality",
    "wof:population":7
},
  "geometry": {"coordinates":[15.3975,46.43944],"type":"Point"}
}