{
  "type": "Feature",
  "properties": {
    "gn:admin1_code":"B8",
    "gn:asciiname":"Zagrad",
    "gn:country_code":"SI",
    "gn:dem":287,
    "gn:feature_class":"P",
    "gn:feature_code":"PPL",
    "gn:name":"Zagrad",
    "gn:population":88,
    "gn:timezone":"Europe/Ljubljana",
    "iso:country":"SI",
    "name:bos_x_preferred":[
        "Zagrad"
    ],
    "name:hrv_x_preferred":[
        "Zagrad"
    ],
    "name:nld_x_preferred":[
        "Zagrad"
    ],
    "name:pol_x_preferred":[
        "Zagrad"
    ],
    "name:ron_x_preferred":[
        "Zagrad"
    ],
    "name:slv_x_preferred":[
        "Zagrad"
    ],
    "name:ukr_x_preferred":[
        "\u0417\u0430\u0433\u0440\u0430\u0434"
    ],
    "name:urd_x_preferred":[
        "\u0632\u06af\u0631\u0627\u0688"
    ],
    "wof:name":"Zagrad",
    "wof:placetype":"locality",
    "wof:population":88
},
  "geometry": {"coordinates":[15.25,45.93333],"type":"Point"}
}