{
  "type": "Feature",
  "properties": {
    "gn:admin1_code":"B8",
    "gn:asciiname":"Zagrad",
    "gn:country_code":"SI",
    "gn:dem":287,
    "gn:feature_class":"P",
    "gn:feature_code":"PPL",
    "gn:name":"Zagrad",
    "gn:population":88,
    "gn:timezone":"Europe/Ljubljana",
    "iso:country":"SI",
    "wof:name":"Zagrad",
    "wof:placetype":"locality",
    "wof:population":88
},
  "geometry": {"coordinates":[15.25,45.93333],"type":"Point"}
}