{
  "type": "Feature",
  "properties": {
    "gn:admin1_code":"D4",
    "gn:asciiname":"Smaver",
    "gn:country_code":"SI",
    "gn:dem":371,
    "gn:feature_class":"P",
    "gn:feature_code":"PPL",
    "gn:name":"\u0160maver",
    "gn:population":70,
    "gn:timezone":"Europe/Ljubljana",
    "iso:country":"SI",
    "name:bos_x_preferred":[
        "\u0160maver"
    ],
    "name:nld_x_preferred":[
        "\u0160maver"
    ],
    "name:pol_x_preferred":[
        "\u0160maver"
    ],
    "name:ron_x_preferred":[
        "\u0160maver"
    ],
    "name:slv_x_preferred":[
        "\u0160maver"
    ],
    "name:ukr_x_preferred":[
        "\u0428\u043c\u0430\u0432\u0435\u0440"
    ],
    "name:und_x_variant":[
        "\u0160maver"
    ],
    "wof:name":"Smaver",
    "wof:placetype":"locality",
    "wof:population":70
},
  "geometry": {"coordinates":[15.02386,45.87135],"type":"Point"}
}