{
  "type": "Feature",
  "properties": {
    "gn:admin1_code":"J9",
    "gn:asciiname":"Sv. Peter",
    "gn:country_code":"SI",
    "gn:dem":161,
    "gn:feature_class":"P",
    "gn:feature_code":"PPL",
    "gn:name":"Sv. Peter",
    "gn:population":379,
    "gn:timezone":"Europe/Ljubljana",
    "iso:country":"SI",
    "name:und_x_variant":[
        "Sempeter",
        "Sent Peter",
        "Sveti Peter"
    ],
    "wof:name":"Sv. Peter",
    "wof:placetype":"locality",
    "wof:population":379
},
  "geometry": {"coordinates":[13.68139,45.47194],"type":"Point"}
}