{
  "type": "Feature",
  "properties": {
    "gn:admin1_code":"C2",
    "gn:asciiname":"Spodnji Razbor",
    "gn:country_code":"SI",
    "gn:dem":858,
    "gn:feature_class":"P",
    "gn:feature_code":"PPL",
    "gn:name":"Spodnji Razbor",
    "gn:population":217,
    "gn:timezone":"Europe/Ljubljana",
    "iso:country":"SI",
    "name:bos_x_preferred":[
        "Spodnji Razbor"
    ],
    "name:ceb_x_preferred":[
        "Spodnji Razbor"
    ],
    "name:ita_x_preferred":[
        "Spodnji Razbor"
    ],
    "name:nld_x_preferred":[
        "Spodnji Razbor"
    ],
    "name:pol_x_preferred":[
        "Spodnji Razbor"
    ],
    "name:ron_x_preferred":[
        "Spodnji Razbor"
    ],
    "name:slv_x_preferred":[
        "Spodnji Razbor"
    ],
    "name:ukr_x_preferred":[
        "\u0421\u043f\u043e\u0434\u043d\u0456\u0439 \u0420\u0430\u0437\u0431\u043e\u0440"
    ],
    "wof:name":"Spodnji Razbor",
    "wof:placetype":"locality",
    "wof:population":217
},
  "geometry": {"coordinates":[15.03916,46.44888],"type":"Point"}
}