{
  "type": "Feature",
  "properties": {
    "gn:admin1_code":"C2",
    "gn:asciiname":"Spodnji Razbor",
    "gn:country_code":"SI",
    "gn:dem":858,
    "gn:feature_class":"P",
    "gn:feature_code":"PPL",
    "gn:name":"Spodnji Razbor",
    "gn:population":217,
    "gn:timezone":"Europe/Ljubljana",
    "iso:country":"SI",
    "wof:name":"Spodnji Razbor",
    "wof:placetype":"locality",
    "wof:population":217
},
  "geometry": {"coordinates":[15.03916,46.44888],"type":"Point"}
}