{
  "type": "Feature",
  "properties": {
    "gn:admin1_code":"08",
    "gn:asciiname":"Blatno",
    "gn:country_code":"SI",
    "gn:dem":248,
    "gn:feature_class":"P",
    "gn:feature_code":"PPL",
    "gn:name":"Blatno",
    "gn:population":156,
    "gn:timezone":"Europe/Ljubljana",
    "iso:country":"SI",
    "wof:name":"Blatno",
    "wof:placetype":"locality",
    "wof:population":156
},
  "geometry": {"coordinates":[15.62278,45.984],"type":"Point"}
}