{
  "type": "Feature",
  "properties": {
    "gn:admin1_code":"08",
    "gn:asciiname":"Blatno",
    "gn:country_code":"SI",
    "gn:dem":248,
    "gn:feature_class":"P",
    "gn:feature_code":"PPL",
    "gn:name":"Blatno",
    "gn:population":156,
    "gn:timezone":"Europe/Ljubljana",
    "iso:country":"SI",
    "name:bos_x_preferred":[
        "Blatno"
    ],
    "name:ceb_x_preferred":[
        "Blatno"
    ],
    "name:hrv_x_preferred":[
        "Blatno"
    ],
    "name:nld_x_preferred":[
        "Blatno"
    ],
    "name:pol_x_preferred":[
        "Blatno"
    ],
    "name:ron_x_preferred":[
        "Blatno"
    ],
    "name:slv_x_preferred":[
        "Blatno"
    ],
    "name:ukr_x_preferred":[
        "\u0411\u043b\u0430\u0442\u043d\u043e"
    ],
    "wof:name":"Blatno",
    "wof:placetype":"locality",
    "wof:population":156
},
  "geometry": {"coordinates":[15.62278,45.984],"type":"Point"}
}