{
  "type": "Feature",
  "properties": {
    "gn:admin1_code":"52",
    "gn:asciiname":"Jama",
    "gn:country_code":"SI",
    "gn:dem":364,
    "gn:feature_class":"P",
    "gn:feature_code":"PPL",
    "gn:name":"Jama",
    "gn:population":239,
    "gn:timezone":"Europe/Ljubljana",
    "iso:country":"SI",
    "wof:name":"Jama",
    "wof:placetype":"locality",
    "wof:population":239
},
  "geometry": {"coordinates":[14.39254,46.19861],"type":"Point"}
}