{
  "type": "Feature",
  "properties": {
    "gn:admin1_code":"P6",
    "gn:asciiname":"Zgornja Senarska",
    "gn:country_code":"SI",
    "gn:dem":237,
    "gn:feature_class":"P",
    "gn:feature_code":"PPL",
    "gn:name":"Zgornja Senarska",
    "gn:population":118,
    "gn:timezone":"Europe/Ljubljana",
    "iso:country":"SI",
    "wof:name":"Zgornja Senarska",
    "wof:placetype":"locality",
    "wof:population":118
},
  "geometry": {"coordinates":[15.87361,46.56528],"type":"Point"}
}