{
  "type": "Feature",
  "properties": {
    "gn:admin1_code":"P6",
    "gn:asciiname":"Zgornja Senarska",
    "gn:country_code":"SI",
    "gn:dem":237,
    "gn:feature_class":"P",
    "gn:feature_code":"PPL",
    "gn:name":"Zgornja Senarska",
    "gn:population":118,
    "gn:timezone":"Europe/Ljubljana",
    "iso:country":"SI",
    "name:bos_x_preferred":[
        "Zgornja Senarska"
    ],
    "name:bul_x_preferred":[
        "\u0417\u0433\u043e\u0440\u043d\u044f \u0421\u0435\u043d\u0430\u0440\u0441\u043a\u0430"
    ],
    "name:ceb_x_preferred":[
        "Zgornja Senarska"
    ],
    "name:nld_x_preferred":[
        "Zgornja Senarska"
    ],
    "name:pol_x_preferred":[
        "Zgornja Senarska"
    ],
    "name:ron_x_preferred":[
        "Zgornja Senarska"
    ],
    "name:slv_x_preferred":[
        "Zgornja Senarska"
    ],
    "name:ukr_x_preferred":[
        "\u0417\u0433\u043e\u0440\u043d\u044f \u0421\u0435\u043d\u0430\u0440\u0441\u043a\u0430"
    ],
    "wof:name":"Zgornja Senarska",
    "wof:placetype":"locality",
    "wof:population":118
},
  "geometry": {"coordinates":[15.87361,46.56528],"type":"Point"}
}