{
  "type": "Feature",
  "properties": {
    "gn:admin1_code":"08",
    "gn:asciiname":"Borst",
    "gn:country_code":"SI",
    "gn:dem":146,
    "gn:feature_class":"P",
    "gn:feature_code":"PPL",
    "gn:name":"Bor\u0161t",
    "gn:population":151,
    "gn:timezone":"Europe/Ljubljana",
    "iso:country":"SI",
    "name:bos_x_preferred":[
        "Bor\u0161t"
    ],
    "name:ceb_x_preferred":[
        "Bor\u0161t"
    ],
    "name:hrv_x_preferred":[
        "Bor\u0161t"
    ],
    "name:nld_x_preferred":[
        "Bor\u0161t"
    ],
    "name:pol_x_preferred":[
        "Bor\u0161t"
    ],
    "name:ron_x_preferred":[
        "Bor\u0161t"
    ],
    "name:slv_x_preferred":[
        "Bor\u0161t"
    ],
    "name:ukr_x_preferred":[
        "\u0411\u043e\u0440\u0448\u0442"
    ],
    "wof:name":"Borst",
    "wof:placetype":"locality",
    "wof:population":151
},
  "geometry": {"coordinates":[15.55,45.88333],"type":"Point"}
}