{
  "type": "Feature",
  "properties": {
    "gn:admin1_code":"08",
    "gn:asciiname":"Borst",
    "gn:country_code":"SI",
    "gn:dem":146,
    "gn:feature_class":"P",
    "gn:feature_code":"PPL",
    "gn:name":"Bor\u0161t",
    "gn:population":151,
    "gn:timezone":"Europe/Ljubljana",
    "iso:country":"SI",
    "name:und_x_variant":[
        "Bor\u0161t"
    ],
    "wof:name":"Borst",
    "wof:placetype":"locality",
    "wof:population":151
},
  "geometry": {"coordinates":[15.55,45.88333],"type":"Point"}
}