{
  "type": "Feature",
  "properties": {
    "gn:admin1_code":"B3",
    "gn:asciiname":"Zgornje Vrtice",
    "gn:country_code":"SI",
    "gn:dem":363,
    "gn:feature_class":"P",
    "gn:feature_code":"PPL",
    "gn:name":"Zgornje Vrti\u010de",
    "gn:population":71,
    "gn:timezone":"Europe/Ljubljana",
    "iso:country":"SI",
    "name:bos_x_preferred":[
        "Zgornje Vrti\u010de"
    ],
    "name:hrv_x_preferred":[
        "Zgornje Vrti\u010de"
    ],
    "name:nld_x_preferred":[
        "Zgornje Vrti\u010de"
    ],
    "name:pol_x_preferred":[
        "Zgornje Vrti\u010de"
    ],
    "name:ron_x_preferred":[
        "Zgornje Vrti\u010de"
    ],
    "name:slv_x_preferred":[
        "Zgornje Vrti\u010de"
    ],
    "name:ukr_x_preferred":[
        "\u0417\u0433\u043e\u0440\u043d\u0454 \u0412\u0440\u0442\u0438\u0447\u0435"
    ],
    "name:und_x_variant":[
        "Zgornje Vrti\u010de"
    ],
    "wof:name":"Zgornje Vrtice",
    "wof:placetype":"locality",
    "wof:population":71
},
  "geometry": {"coordinates":[15.6173,46.66152],"type":"Point"}
}