{
  "type": "Feature",
  "properties": {
    "gn:admin1_code":"B3",
    "gn:asciiname":"Zgornje Vrtice",
    "gn:country_code":"SI",
    "gn:dem":363,
    "gn:feature_class":"P",
    "gn:feature_code":"PPL",
    "gn:name":"Zgornje Vrti\u010de",
    "gn:population":71,
    "gn:timezone":"Europe/Ljubljana",
    "iso:country":"SI",
    "name:und_x_variant":[
        "Zgornje Vrti\u010de"
    ],
    "wof:name":"Zgornje Vrtice",
    "wof:placetype":"locality",
    "wof:population":71
},
  "geometry": {"coordinates":[15.6173,46.66152],"type":"Point"}
}