{
  "type": "Feature",
  "properties": {
    "gn:admin1_code":"D4",
    "gn:asciiname":"Pekel",
    "gn:country_code":"SI",
    "gn:dem":284,
    "gn:feature_class":"P",
    "gn:feature_code":"PPL",
    "gn:name":"Pekel",
    "gn:population":70,
    "gn:timezone":"Europe/Ljubljana",
    "iso:country":"SI",
    "wof:name":"Pekel",
    "wof:placetype":"locality",
    "wof:population":70
},
  "geometry": {"coordinates":[15.00428,45.91763],"type":"Point"}
}