{
  "type": "Feature",
  "properties": {
    "gn:admin1_code":"D2",
    "gn:asciiname":"Trtnik",
    "gn:country_code":"SI",
    "gn:dem":978,
    "gn:feature_class":"P",
    "gn:feature_code":"PPL",
    "gn:name":"Trtnik",
    "gn:population":23,
    "gn:timezone":"Europe/Ljubljana",
    "iso:country":"SI",
    "name:und_x_variant":[
        "Tertenico",
        "Trtnik"
    ],
    "wof:name":"Trtnik",
    "wof:placetype":"locality",
    "wof:population":23
},
  "geometry": {"coordinates":[13.95533,46.21267],"type":"Point"}
}