{
  "type": "Feature",
  "properties": {
    "gn:admin1_code":"D2",
    "gn:asciiname":"Trtnik",
    "gn:country_code":"SI",
    "gn:dem":978,
    "gn:feature_class":"P",
    "gn:feature_code":"PPL",
    "gn:name":"Trtnik",
    "gn:population":23,
    "gn:timezone":"Europe/Ljubljana",
    "iso:country":"SI",
    "name:bos_x_preferred":[
        "Trtnik"
    ],
    "name:bul_x_preferred":[
        "\u0422\u0440\u044a\u0442\u043d\u0438\u043a"
    ],
    "name:fas_x_preferred":[
        "\u062a\u0631\u062a\u0646\u06cc\u06a9"
    ],
    "name:nld_x_preferred":[
        "Trtnik"
    ],
    "name:pol_x_preferred":[
        "Trtnik"
    ],
    "name:ron_x_preferred":[
        "Trtnik"
    ],
    "name:slv_x_preferred":[
        "Trtnik"
    ],
    "name:ukr_x_preferred":[
        "\u0422\u0440\u0442\u043d\u0438\u043a"
    ],
    "name:und_x_variant":[
        "Tertenico"
    ],
    "wof:name":"Trtnik",
    "wof:placetype":"locality",
    "wof:population":23
},
  "geometry": {"coordinates":[13.95533,46.21267],"type":"Point"}
}