{
  "type": "Feature",
  "properties": {
    "gn:admin1_code":"G7",
    "gn:asciiname":"Brdo",
    "gn:country_code":"SI",
    "gn:dem":367,
    "gn:feature_class":"P",
    "gn:feature_code":"PPL",
    "gn:name":"Brdo",
    "gn:population":100,
    "gn:timezone":"Europe/Ljubljana",
    "iso:country":"SI",
    "name:bos_x_preferred":[
        "Brdo"
    ],
    "name:nld_x_preferred":[
        "Brdo"
    ],
    "name:pol_x_preferred":[
        "Brdo"
    ],
    "name:ron_x_preferred":[
        "Brdo"
    ],
    "name:slv_x_preferred":[
        "Brdo"
    ],
    "name:ukr_x_preferred":[
        "\u0411\u0440\u0434\u043e"
    ],
    "wof:name":"Brdo",
    "wof:placetype":"locality",
    "wof:population":100
},
  "geometry": {"coordinates":[14.64222,46.12278],"type":"Point"}
}