{
  "type": "Feature",
  "properties": {
    "gn:admin1_code":"K9",
    "gn:asciiname":"Sprinc",
    "gn:country_code":"SI",
    "gn:dem":234,
    "gn:feature_class":"P",
    "gn:feature_code":"PPL",
    "gn:name":"\u0160princ",
    "gn:population":137,
    "gn:timezone":"Europe/Ljubljana",
    "iso:country":"SI",
    "name:bos_x_preferred":[
        "\u0160princ"
    ],
    "name:ceb_x_preferred":[
        "\u0160princ"
    ],
    "name:epo_x_preferred":[
        "\u0160princ"
    ],
    "name:hrv_x_preferred":[
        "\u0160princ"
    ],
    "name:nld_x_preferred":[
        "\u0160princ"
    ],
    "name:pol_x_preferred":[
        "\u0160princ"
    ],
    "name:ron_x_preferred":[
        "\u0160princ"
    ],
    "name:slv_x_preferred":[
        "\u0160princ"
    ],
    "name:ukr_x_preferred":[
        "\u0428\u043f\u0440\u0438\u043d\u0446"
    ],
    "wof:name":"Sprinc",
    "wof:placetype":"locality",
    "wof:population":137
},
  "geometry": {"coordinates":[16.25825,46.50756],"type":"Point"}
}