{
  "type": "Feature",
  "properties": {
    "gn:admin1_code":"K9",
    "gn:asciiname":"Sprinc",
    "gn:country_code":"SI",
    "gn:dem":234,
    "gn:feature_class":"P",
    "gn:feature_code":"PPL",
    "gn:name":"\u0160princ",
    "gn:population":137,
    "gn:timezone":"Europe/Ljubljana",
    "iso:country":"SI",
    "name:und_x_variant":[
        "\u0160princ"
    ],
    "wof:name":"Sprinc",
    "wof:placetype":"locality",
    "wof:population":137
},
  "geometry": {"coordinates":[16.25825,46.50756],"type":"Point"}
}