{
  "type": "Feature",
  "properties": {
    "gn:admin1_code":"87",
    "gn:asciiname":"Hajndl",
    "gn:country_code":"SI",
    "gn:dem":261,
    "gn:feature_class":"P",
    "gn:feature_code":"PPL",
    "gn:name":"Hajndl",
    "gn:population":116,
    "gn:timezone":"Europe/Ljubljana",
    "iso:country":"SI",
    "name:bos_x_preferred":[
        "Hajndl"
    ],
    "name:bul_x_preferred":[
        "\u0425\u0430\u0439\u043d\u0434\u044a\u043b"
    ],
    "name:ceb_x_preferred":[
        "Hajndl"
    ],
    "name:nld_x_preferred":[
        "Hajndl"
    ],
    "name:pol_x_preferred":[
        "Hajndl"
    ],
    "name:ron_x_preferred":[
        "Hajndl"
    ],
    "name:slv_x_preferred":[
        "Hajndl"
    ],
    "name:ukr_x_preferred":[
        "\u0413\u0430\u0439\u043d\u0434\u043b"
    ],
    "wof:name":"Hajndl",
    "wof:placetype":"locality",
    "wof:population":116
},
  "geometry": {"coordinates":[16.12555,46.41566],"type":"Point"}
}