{
  "type": "Feature",
  "properties": {
    "gn:admin1_code":"G1",
    "gn:asciiname":"Svetinci",
    "gn:country_code":"SI",
    "gn:dem":274,
    "gn:feature_class":"P",
    "gn:feature_code":"PPL",
    "gn:name":"Svetinci",
    "gn:population":155,
    "gn:timezone":"Europe/Ljubljana",
    "iso:country":"SI",
    "name:bos_x_preferred":[
        "Svetinci"
    ],
    "name:ceb_x_preferred":[
        "Svetinci"
    ],
    "name:nld_x_preferred":[
        "Svetinci"
    ],
    "name:pol_x_preferred":[
        "Svetinci"
    ],
    "name:ron_x_preferred":[
        "Svetinci"
    ],
    "name:slv_x_preferred":[
        "Svetinci"
    ],
    "name:ukr_x_preferred":[
        "\u0421\u0432\u0435\u0442\u0438\u043d\u0446\u0456"
    ],
    "wof:name":"Svetinci",
    "wof:placetype":"locality",
    "wof:population":155
},
  "geometry": {"coordinates":[15.90123,46.49918],"type":"Point"}
}