{
  "type": "Feature",
  "properties": {
    "gn:admin1_code":"O1",
    "gn:asciiname":"Slatina",
    "gn:country_code":"SI",
    "gn:dem":273,
    "gn:feature_class":"P",
    "gn:feature_code":"PPL",
    "gn:name":"Slatina",
    "gn:population":101,
    "gn:timezone":"Europe/Ljubljana",
    "iso:country":"SI",
    "name:bos_x_preferred":[
        "Slatina"
    ],
    "name:ceb_x_preferred":[
        "Slatina"
    ],
    "name:nld_x_preferred":[
        "Slatina"
    ],
    "name:pol_x_preferred":[
        "Slatina"
    ],
    "name:ron_x_preferred":[
        "Slatina"
    ],
    "name:slv_x_preferred":[
        "Slatina"
    ],
    "name:ukr_x_preferred":[
        "\u0421\u043b\u0430\u0442\u0438\u043d\u0430"
    ],
    "wof:name":"Slatina",
    "wof:placetype":"locality",
    "wof:population":101
},
  "geometry": {"coordinates":[15.97301,46.32983],"type":"Point"}
}