{
  "type": "Feature",
  "properties": {
    "gn:admin1_code":"O1",
    "gn:asciiname":"Slatina",
    "gn:country_code":"SI",
    "gn:dem":273,
    "gn:feature_class":"P",
    "gn:feature_code":"PPL",
    "gn:name":"Slatina",
    "gn:population":101,
    "gn:timezone":"Europe/Ljubljana",
    "iso:country":"SI",
    "wof:name":"Slatina",
    "wof:placetype":"locality",
    "wof:population":101
},
  "geometry": {"coordinates":[15.97301,46.32983],"type":"Point"}
}