{
  "type": "Feature",
  "properties": {
    "iso:country":"SI",
    "wof:name":"Zgornja Besnica",
    "wof:placetype":"neighbourhood"
},
  "geometry": {"coordinates":[14.6869398309598,46.03348456073948],"type":"Point"}
}