{
  "type": "Feature",
  "properties": {
    "gn:admin1_code":"I3",
    "gn:asciiname":"Spodnje Partinje",
    "gn:country_code":"SI",
    "gn:dem":247,
    "gn:feature_class":"P",
    "gn:feature_code":"PPL",
    "gn:name":"Spodnje Partinje",
    "gn:population":134,
    "gn:timezone":"Europe/Ljubljana",
    "iso:country":"SI",
    "wof:name":"Spodnje Partinje",
    "wof:placetype":"locality",
    "wof:population":134
},
  "geometry": {"coordinates":[15.78275,46.57898],"type":"Point"}
}