{
  "type": "Feature",
  "properties": {
    "gn:admin1_code":"I3",
    "gn:asciiname":"Spodnje Partinje",
    "gn:country_code":"SI",
    "gn:dem":247,
    "gn:feature_class":"P",
    "gn:feature_code":"PPL",
    "gn:name":"Spodnje Partinje",
    "gn:population":134,
    "gn:timezone":"Europe/Ljubljana",
    "iso:country":"SI",
    "name:bos_x_preferred":[
        "Spodnje Partinje"
    ],
    "name:ceb_x_preferred":[
        "Spodnje Partinje"
    ],
    "name:nld_x_preferred":[
        "Spodnje Partinje"
    ],
    "name:pol_x_preferred":[
        "Spodnje Partinje"
    ],
    "name:ron_x_preferred":[
        "Spodnje Partinje"
    ],
    "name:slv_x_preferred":[
        "Spodnje Partinje"
    ],
    "name:ukr_x_preferred":[
        "\u0421\u043f\u043e\u0434\u043d\u0454 \u041f\u0430\u0440\u0442\u0438\u043d\u0454"
    ],
    "wof:name":"Spodnje Partinje",
    "wof:placetype":"locality",
    "wof:population":134
},
  "geometry": {"coordinates":[15.78275,46.57898],"type":"Point"}
}