{
  "type": "Feature",
  "properties": {
    "gn:admin1_code":"D2",
    "gn:asciiname":"Kneske Ravne",
    "gn:country_code":"SI",
    "gn:dem":832,
    "gn:feature_class":"P",
    "gn:feature_code":"PPL",
    "gn:name":"Kne\u0161ke Ravne",
    "gn:population":13,
    "gn:timezone":"Europe/Ljubljana",
    "iso:country":"SI",
    "name:bos_x_preferred":[
        "Kne\u0161ke Ravne"
    ],
    "name:bul_x_preferred":[
        "\u041a\u043d\u0435\u0448\u043a\u0435 \u0420\u0430\u0432\u043d\u0435"
    ],
    "name:nld_x_preferred":[
        "Kne\u0161ke Ravne"
    ],
    "name:pol_x_preferred":[
        "Kne\u0161ke Ravne"
    ],
    "name:ron_x_preferred":[
        "Kne\u0161ke Ravne"
    ],
    "name:sco_x_preferred":[
        "Kne\u0161ke Ravne"
    ],
    "name:slv_x_preferred":[
        "Kne\u0161ke Ravne"
    ],
    "name:ukr_x_preferred":[
        "\u041a\u043d\u0435\u0448\u043a\u0435 \u0420\u0430\u0432\u043d\u0435"
    ],
    "wof:name":"Kneske Ravne",
    "wof:placetype":"locality",
    "wof:population":13
},
  "geometry": {"coordinates":[13.83322,46.22032],"type":"Point"}
}