{
  "type": "Feature",
  "properties": {
    "gn:admin1_code":"08",
    "gn:asciiname":"Vrhovska Vas",
    "gn:country_code":"SI",
    "gn:dem":248,
    "gn:feature_class":"P",
    "gn:feature_code":"PPL",
    "gn:name":"Vrhovska Vas",
    "gn:population":57,
    "gn:timezone":"Europe/Ljubljana",
    "iso:country":"SI",
    "wof:name":"Vrhovska Vas",
    "wof:placetype":"locality",
    "wof:population":57
},
  "geometry": {"coordinates":[15.5157,45.85983],"type":"Point"}
}