{
  "type": "Feature",
  "properties": {
    "gn:admin1_code":"08",
    "gn:asciiname":"Vrhovska Vas",
    "gn:country_code":"SI",
    "gn:dem":248,
    "gn:feature_class":"P",
    "gn:feature_code":"PPL",
    "gn:name":"Vrhovska Vas",
    "gn:population":57,
    "gn:timezone":"Europe/Ljubljana",
    "iso:country":"SI",
    "name:bos_x_preferred":[
        "Vrhovska vas"
    ],
    "name:hrv_x_preferred":[
        "Vrhovska vas"
    ],
    "name:nld_x_preferred":[
        "Vrhovska vas"
    ],
    "name:pol_x_preferred":[
        "Vrhovska vas"
    ],
    "name:ron_x_preferred":[
        "Vrhovska vas"
    ],
    "name:slv_x_preferred":[
        "Vrhovska vas"
    ],
    "name:ukr_x_preferred":[
        "\u0412\u0440\u0445\u043e\u0432\u0441\u044c\u043a\u0430 \u0412\u0430\u0441"
    ],
    "wof:name":"Vrhovska Vas",
    "wof:placetype":"locality",
    "wof:population":57
},
  "geometry": {"coordinates":[15.5157,45.85983],"type":"Point"}
}