{
  "type": "Feature",
  "properties": {
    "gn:admin1_code":"54",
    "gn:asciiname":"Osredek pri Trski Gori",
    "gn:country_code":"SI",
    "gn:dem":303,
    "gn:feature_class":"P",
    "gn:feature_code":"PPL",
    "gn:name":"Osredek pri Tr\u0161ki Gori",
    "gn:population":41,
    "gn:timezone":"Europe/Ljubljana",
    "iso:country":"SI",
    "name:bos_x_preferred":[
        "Osredek pri Tr\u0161ki Gori"
    ],
    "name:hrv_x_preferred":[
        "Osredek pri Tr\u0161ki Gori"
    ],
    "name:nld_x_preferred":[
        "Osredek pri Tr\u0161ki Gori"
    ],
    "name:pol_x_preferred":[
        "Osredek pri Tr\u0161ki Gori"
    ],
    "name:ron_x_preferred":[
        "Osredek pri Tr\u0161ki Gori"
    ],
    "name:slv_x_preferred":[
        "Osredek pri Tr\u0161ki Gori"
    ],
    "name:ukr_x_preferred":[
        "\u041e\u0441\u0440\u0435\u0434\u0435\u043a-\u043f\u0440\u0438-\u0422\u0440\u0448\u043a\u0456 \u0413\u043e\u0440\u0456"
    ],
    "name:und_x_variant":[
        "Osredek pri Tr\u0161ki Gori"
    ],
    "wof:name":"Osredek pri Trski Gori",
    "wof:placetype":"locality",
    "wof:population":41
},
  "geometry": {"coordinates":[15.4631,45.9599],"type":"Point"}
}