{
  "type": "Feature",
  "properties": {
    "gn:admin1_code":"54",
    "gn:asciiname":"Osredek pri Trski Gori",
    "gn:country_code":"SI",
    "gn:dem":303,
    "gn:feature_class":"P",
    "gn:feature_code":"PPL",
    "gn:name":"Osredek pri Tr\u0161ki Gori",
    "gn:population":41,
    "gn:timezone":"Europe/Ljubljana",
    "iso:country":"SI",
    "name:und_x_variant":[
        "Osredek pri Tr\u0161ki Gori"
    ],
    "wof:name":"Osredek pri Trski Gori",
    "wof:placetype":"locality",
    "wof:population":41
},
  "geometry": {"coordinates":[15.4631,45.9599],"type":"Point"}
}