{
  "type": "Feature",
  "properties": {
    "gn:admin1_code":"L7",
    "gn:asciiname":"Dobje pri Lesicnem",
    "gn:country_code":"SI",
    "gn:dem":425,
    "gn:feature_class":"P",
    "gn:feature_code":"PPL",
    "gn:name":"Dobje pri Lesi\u010dnem",
    "gn:population":81,
    "gn:timezone":"Europe/Ljubljana",
    "iso:country":"SI",
    "name:bos_x_preferred":[
        "Dobje pri Lesi\u010dnem"
    ],
    "name:hrv_x_preferred":[
        "Dobje pri Lesi\u010dnem"
    ],
    "name:nld_x_preferred":[
        "Dobje pri Lesi\u010dnem"
    ],
    "name:pol_x_preferred":[
        "Dobje pri Lesi\u010dnem"
    ],
    "name:ron_x_preferred":[
        "Dobje pri Lesi\u010dnem"
    ],
    "name:slv_x_preferred":[
        "Dobje pri Lesi\u010dnem"
    ],
    "name:ukr_x_preferred":[
        "\u0414\u043e\u0431\u0454-\u043f\u0440\u0438-\u041b\u0435\u0441\u0438\u0447\u043d\u0435\u043c"
    ],
    "name:und_x_variant":[
        "Dobje"
    ],
    "wof:name":"Dobje pri Lesicnem",
    "wof:placetype":"locality",
    "wof:population":81
},
  "geometry": {"coordinates":[15.46667,46.11667],"type":"Point"}
}