{
  "type": "Feature",
  "properties": {
    "gn:admin1_code":"L7",
    "gn:asciiname":"Dobje pri Lesicnem",
    "gn:country_code":"SI",
    "gn:dem":425,
    "gn:feature_class":"P",
    "gn:feature_code":"PPL",
    "gn:name":"Dobje pri Lesi\u010dnem",
    "gn:population":81,
    "gn:timezone":"Europe/Ljubljana",
    "iso:country":"SI",
    "name:und_x_variant":[
        "Dobje",
        "Dobje pri Lesi\u010dnem"
    ],
    "wof:name":"Dobje pri Lesicnem",
    "wof:placetype":"locality",
    "wof:population":81
},
  "geometry": {"coordinates":[15.46667,46.11667],"type":"Point"}
}