{
  "type": "Feature",
  "properties": {
    "gn:admin1_code":"24",
    "gn:asciiname":"Zamenci",
    "gn:country_code":"SI",
    "gn:dem":214,
    "gn:feature_class":"P",
    "gn:feature_code":"PPL",
    "gn:name":"\u017damenci",
    "gn:population":72,
    "gn:timezone":"Europe/Ljubljana",
    "iso:country":"SI",
    "name:und_x_variant":[
        "\u017dalmance",
        "\u017damenci"
    ],
    "wof:name":"Zamenci",
    "wof:placetype":"locality",
    "wof:population":72
},
  "geometry": {"coordinates":[15.9759,46.44057],"type":"Point"}
}