{
  "type": "Feature",
  "properties": {
    "gn:admin1_code":"39",
    "gn:asciiname":"Sticna",
    "gn:country_code":"SI",
    "gn:dem":421,
    "gn:feature_class":"P",
    "gn:feature_code":"PPL",
    "gn:name":"Sti\u010dna",
    "gn:population":799,
    "gn:timezone":"Europe/Ljubljana",
    "iso:country":"SI",
    "name:und_x_variant":[
        "Sittich",
        "Sti\u010dna"
    ],
    "wof:name":"Sticna",
    "wof:placetype":"locality",
    "wof:population":799
},
  "geometry": {"coordinates":[14.81028,45.96056],"type":"Point"}
}