{
  "type": "Feature",
  "properties": {
    "gn:admin1_code":"D4",
    "gn:asciiname":"Goljek",
    "gn:country_code":"SI",
    "gn:dem":435,
    "gn:feature_class":"P",
    "gn:feature_code":"PPL",
    "gn:name":"Goljek",
    "gn:population":64,
    "gn:timezone":"Europe/Ljubljana",
    "iso:country":"SI",
    "wof:name":"Goljek",
    "wof:placetype":"locality",
    "wof:population":64
},
  "geometry": {"coordinates":[14.99195,45.95882],"type":"Point"}
}