{
  "type": "Feature",
  "properties": {
    "gn:admin1_code":"88",
    "gn:asciiname":"Mirtovici",
    "gn:country_code":"SI",
    "gn:dem":369,
    "gn:feature_class":"P",
    "gn:feature_code":"PPL",
    "gn:name":"Mirtovi\u010di",
    "gn:population":9,
    "gn:timezone":"Europe/Ljubljana",
    "iso:country":"SI",
    "name:bos_x_preferred":[
        "Mirtovi\u010di"
    ],
    "name:hrv_x_preferred":[
        "Mirtovi\u010di"
    ],
    "name:nld_x_preferred":[
        "Mirtovi\u010di"
    ],
    "name:pol_x_preferred":[
        "Mirtovi\u010di"
    ],
    "name:ron_x_preferred":[
        "Mirtovi\u010di"
    ],
    "name:slv_x_historical":[
        "Mrtovc",
        "Mrtovec"
    ],
    "name:slv_x_preferred":[
        "Mrtovc"
    ],
    "name:slv_x_variant":[
        "Mrtovec",
        "Mirtovi\u010di"
    ],
    "name:ukr_x_preferred":[
        "\u041c\u0438\u0440\u0442\u043e\u0432\u0438\u0447\u0456"
    ],
    "name:und_x_variant":[
        "Mirtovi\u010di"
    ],
    "wof:name":"Mirtovici",
    "wof:placetype":"locality",
    "wof:population":9
},
  "geometry": {"coordinates":[14.78381,45.51319],"type":"Point"}
}