{
  "type": "Feature",
  "properties": {
    "gn:admin1_code":"D8",
    "gn:asciiname":"Poznikovo",
    "gn:country_code":"SI",
    "gn:dem":574,
    "gn:feature_class":"P",
    "gn:feature_code":"PPL",
    "gn:name":"Poznikovo",
    "gn:population":21,
    "gn:timezone":"Europe/Ljubljana",
    "iso:country":"SI",
    "wof:name":"Poznikovo",
    "wof:placetype":"locality",
    "wof:population":21
},
  "geometry": {"coordinates":[14.61037,45.80595],"type":"Point"}
}