{
  "type": "Feature",
  "properties": {
    "gn:admin1_code":"D8",
    "gn:asciiname":"Poznikovo",
    "gn:country_code":"SI",
    "gn:dem":574,
    "gn:feature_class":"P",
    "gn:feature_code":"PPL",
    "gn:name":"Poznikovo",
    "gn:population":21,
    "gn:timezone":"Europe/Ljubljana",
    "iso:country":"SI",
    "name:bos_x_preferred":[
        "Poznikovo"
    ],
    "name:nld_x_preferred":[
        "Poznikovo"
    ],
    "name:pol_x_preferred":[
        "Poznikovo"
    ],
    "name:ron_x_preferred":[
        "Poznikovo"
    ],
    "name:slv_x_preferred":[
        "Poznikovo"
    ],
    "name:ukr_x_preferred":[
        "\u041f\u043e\u0437\u043d\u0438\u043a\u043e\u0432\u043e"
    ],
    "wof:name":"Poznikovo",
    "wof:placetype":"locality",
    "wof:population":21
},
  "geometry": {"coordinates":[14.61037,45.80595],"type":"Point"}
}