{
  "type": "Feature",
  "properties": {
    "gn:admin1_code":"13",
    "gn:asciiname":"Blocice",
    "gn:country_code":"SI",
    "gn:dem":609,
    "gn:feature_class":"P",
    "gn:feature_code":"PPL",
    "gn:name":"Blo\u010dice",
    "gn:population":114,
    "gn:timezone":"Europe/Ljubljana",
    "iso:country":"SI",
    "name:und_x_variant":[
        "Obloschiz",
        "Blo\u010dice"
    ],
    "wof:name":"Blocice",
    "wof:placetype":"locality",
    "wof:population":114
},
  "geometry": {"coordinates":[14.4575,45.76111],"type":"Point"}
}