{
  "type": "Feature",
  "properties": {
    "gn:admin1_code":"13",
    "gn:asciiname":"Blocice",
    "gn:country_code":"SI",
    "gn:dem":609,
    "gn:feature_class":"P",
    "gn:feature_code":"PPL",
    "gn:name":"Blo\u010dice",
    "gn:population":114,
    "gn:timezone":"Europe/Ljubljana",
    "iso:country":"SI",
    "name:bos_x_preferred":[
        "Blo\u010dice"
    ],
    "name:ceb_x_preferred":[
        "Blo\u010dice"
    ],
    "name:hrv_x_preferred":[
        "Blo\u010dice"
    ],
    "name:nld_x_preferred":[
        "Blo\u010dice"
    ],
    "name:pol_x_preferred":[
        "Blo\u010dice"
    ],
    "name:ron_x_preferred":[
        "Blo\u010dice"
    ],
    "name:slv_x_preferred":[
        "Blo\u010dice"
    ],
    "name:ukr_x_preferred":[
        "\u0411\u043b\u043e\u0447\u0438\u0446\u0435"
    ],
    "name:und_x_variant":[
        "Obloschiz"
    ],
    "wof:name":"Blocice",
    "wof:placetype":"locality",
    "wof:population":114
},
  "geometry": {"coordinates":[14.4575,45.76111],"type":"Point"}
}