{
  "type": "Feature",
  "properties": {
    "gn:admin1_code":"97",
    "gn:asciiname":"Puzevci",
    "gn:country_code":"SI",
    "gn:dem":210,
    "gn:feature_class":"P",
    "gn:feature_code":"PPL",
    "gn:name":"Pu\u017eevci",
    "gn:population":181,
    "gn:timezone":"Europe/Ljubljana",
    "iso:country":"SI",
    "name:und_x_variant":[
        "Gornji Pu\u017eevci",
        "Puzanci",
        "Dolnji Pu\u017eevci",
        "S\u00fcr\u00fch\u00e1za",
        "P\u00e1lmafa",
        "Pu\u017eeci",
        "Pu\u017eavci",
        "S\u00fcr\u00fch\u00e1z",
        "Pu\u017eevci"
    ],
    "wof:name":"Puzevci",
    "wof:placetype":"locality",
    "wof:population":181
},
  "geometry": {"coordinates":[16.08611,46.7125],"type":"Point"}
}