{
  "type": "Feature",
  "properties": {
    "gn:admin1_code":"94",
    "gn:asciiname":"Malo Ubeljsko",
    "gn:country_code":"SI",
    "gn:dem":573,
    "gn:feature_class":"P",
    "gn:feature_code":"PPL",
    "gn:name":"Malo Ubeljsko",
    "gn:population":51,
    "gn:timezone":"Europe/Ljubljana",
    "iso:country":"SI",
    "name:bos_x_preferred":[
        "Malo Ubeljsko"
    ],
    "name:hrv_x_preferred":[
        "Malo Ubeljsko"
    ],
    "name:nld_x_preferred":[
        "Malo Ubeljsko"
    ],
    "name:pol_x_preferred":[
        "Malo Ubeljsko"
    ],
    "name:ron_x_preferred":[
        "Malo Ubeljsko"
    ],
    "name:slv_x_preferred":[
        "Malo Ubeljsko"
    ],
    "name:ukr_x_preferred":[
        "\u041c\u0430\u043b\u043e \u0423\u0431\u0435\u043b\u044c\u0441\u044c\u043a\u043e"
    ],
    "name:und_x_variant":[
        "Malo Ubelisko"
    ],
    "wof:name":"Malo Ubeljsko",
    "wof:placetype":"locality",
    "wof:population":51
},
  "geometry": {"coordinates":[14.07861,45.77194],"type":"Point"}
}