{
  "type": "Feature",
  "properties": {
    "gn:admin1_code":"94",
    "gn:asciiname":"Malo Ubeljsko",
    "gn:country_code":"SI",
    "gn:dem":573,
    "gn:feature_class":"P",
    "gn:feature_code":"PPL",
    "gn:name":"Malo Ubeljsko",
    "gn:population":51,
    "gn:timezone":"Europe/Ljubljana",
    "iso:country":"SI",
    "name:und_x_variant":[
        "Malo Ubelisko",
        "Malo Ubeljsko"
    ],
    "wof:name":"Malo Ubeljsko",
    "wof:placetype":"locality",
    "wof:population":51
},
  "geometry": {"coordinates":[14.07861,45.77194],"type":"Point"}
}