{
  "type": "Feature",
  "properties": {
    "gn:admin1_code":"I3",
    "gn:asciiname":"Zgornji Zerjavci",
    "gn:country_code":"SI",
    "gn:dem":250,
    "gn:feature_class":"P",
    "gn:feature_code":"PPLL",
    "gn:name":"Zgornji \u017derjavci",
    "gn:population":261,
    "gn:timezone":"Europe/Ljubljana",
    "iso:country":"SI",
    "name:und_x_variant":[
        "Zgornji \u017derjavci"
    ],
    "wof:name":"Zgornji Zerjavci",
    "wof:placetype":"locality",
    "wof:population":261
},
  "geometry": {"coordinates":[15.83806,46.60194],"type":"Point"}
}