{
  "type": "Feature",
  "properties": {
    "gn:admin1_code":"I3",
    "gn:asciiname":"Zgornji Zerjavci",
    "gn:country_code":"SI",
    "gn:dem":250,
    "gn:feature_class":"P",
    "gn:feature_code":"PPLL",
    "gn:name":"Zgornji \u017derjavci",
    "gn:population":261,
    "gn:timezone":"Europe/Ljubljana",
    "iso:country":"SI",
    "name:bos_x_preferred":[
        "Zgornji \u017derjavci"
    ],
    "name:ceb_x_preferred":[
        "Zgornji \u017derjavci"
    ],
    "name:nld_x_preferred":[
        "Zgornji \u017derjavci"
    ],
    "name:pol_x_preferred":[
        "Zgornji \u017derjavci"
    ],
    "name:ron_x_preferred":[
        "Zgornji \u017derjavci"
    ],
    "name:slv_x_preferred":[
        "Zgornji \u017derjavci"
    ],
    "name:ukr_x_preferred":[
        "\u0417\u0433\u043e\u0440\u043d\u0456 \u0416\u0435\u0440\u044f\u0432\u0446\u0456"
    ],
    "wof:name":"Zgornji Zerjavci",
    "wof:placetype":"locality",
    "wof:population":261
},
  "geometry": {"coordinates":[15.83806,46.60194],"type":"Point"}
}