{
  "type": "Feature",
  "properties": {
    "iso:country":"SI",
    "name:bos_x_preferred":[
        "Spodnji Duplek"
    ],
    "name:ceb_x_preferred":[
        "Spodnji Duplek"
    ],
    "name:che_x_preferred":[
        "\u0421\u043f\u043e\u0434\u043d\u0438\u0439 \u0414\u0443\u043f\u043b\u0435\u043a"
    ],
    "name:eng_x_preferred":[
        "Spodnji Duplek"
    ],
    "name:fra_x_preferred":[
        "Spodnji Duplek"
    ],
    "name:hrv_x_preferred":[
        "Spodnji Duplek"
    ],
    "name:nld_x_preferred":[
        "Spodnji Duplek"
    ],
    "name:pol_x_preferred":[
        "Spodnji Duplek"
    ],
    "name:ron_x_preferred":[
        "Spodnji Duplek"
    ],
    "name:slv_x_preferred":[
        "Spodnji Duplek"
    ],
    "name:tat_x_preferred":[
        "\u0421\u043f\u043e\u0434\u043d\u0438\u0439 \u0414\u0443\u043f\u043b\u0435\u043a"
    ],
    "name:tha_x_preferred":[
        "\u0e2a\u0e42\u0e1b\u0e14\u0e19\u0e34\u0e22\u0e35\u0e14\u0e39\u0e41\u0e1b\u0e25\u0e47\u0e01"
    ],
    "name:ukr_x_preferred":[
        "\u0421\u043f\u043e\u0434\u043d\u0456\u0439 \u0414\u0443\u043f\u043b\u0435\u043a"
    ],
    "name:zho_x_preferred":[
        "\u4e0b\u675c\u666e\u840a\u514b"
    ],
    "qs_pg:aaroncc":"SI",
    "qs_pg:name":"Spodnji Duplek",
    "qs_pg:name_adm0":"Slovenija",
    "qs_pg:name_adm1":"Maribor",
    "qs_pg:photos":22,
    "qs_pg:photos_1k":4,
    "qs_pg:photos_9k":1,
    "qs_pg:photos_9r":1,
    "qs_pg:photos_all":22,
    "qs_pg:photos_sr":1,
    "qs_pg:pop_sr":0,
    "qs_pg:qs_pg_placetype":"locality",
    "qs_pg:qs_pg_placetype_gp":"Town",
    "qs_pg:woe_adm0":23424945,
    "woe:adm0_id":23424945,
    "woe:name_adm0":"Slovenija",
    "woe:name_adm1":"Maribor",
    "woe:placetype":"Town",
    "wof:name":"Spodnji Duplek",
    "wof:placetype":"locality"
},
  "geometry": {"coordinates":[15.735683,46.504624],"type":"Point"}
}