{
  "type": "Feature",
  "properties": {
    "iso:country":"SI",
    "name:bos_x_preferred":[
        "Spodnji Duplek"
    ],
    "name:dut_x_preferred":[
        "Spodnji Duplek"
    ],
    "name:eng_x_preferred":[
        "Spodnji Duplek"
    ],
    "name:rum_x_preferred":[
        "Spodnji Duplek"
    ],
    "name:slv_x_preferred":[
        "Spodnji Duplek"
    ],
    "name:ukr_x_preferred":[
        "\u0421\u043f\u043e\u0434\u043d\u0456\u0439 \u0414\u0443\u043f\u043b\u0435\u043a"
    ],
    "qs_pg:aaroncc":"SI",
    "qs_pg:name":"Spodnji Duplek",
    "qs_pg:name_adm0":"Slovenija",
    "qs_pg:name_adm1":"Maribor",
    "qs_pg:photos":22,
    "qs_pg:photos_1k":4,
    "qs_pg:photos_9k":1,
    "qs_pg:photos_9r":1,
    "qs_pg:photos_all":22,
    "qs_pg:photos_sr":1,
    "qs_pg:pop_sr":0,
    "qs_pg:qs_pg_placetype":"locality",
    "qs_pg:qs_pg_placetype_gp":"Town",
    "qs_pg:woe_adm0":23424945,
    "woe:adm0_id":23424945,
    "woe:name_adm0":"Slovenija",
    "woe:name_adm1":"Maribor",
    "woe:placetype":"Town",
    "wof:name":"Spodnji Duplek",
    "wof:placetype":"locality"
},
  "geometry": {"coordinates":[15.735683,46.5046245],"type":"Point"}
}