{
  "type": "Feature",
  "properties": {
    "gn:admin1_code":"D4",
    "gn:asciiname":"Brezovica pri Mirni",
    "gn:country_code":"SI",
    "gn:dem":272,
    "gn:feature_class":"P",
    "gn:feature_code":"PPL",
    "gn:name":"Brezovica pri Mirni",
    "gn:population":132,
    "gn:timezone":"Europe/Ljubljana",
    "iso:country":"SI",
    "name:bos_x_preferred":[
        "Brezovica pri Mirni"
    ],
    "name:ceb_x_preferred":[
        "Brezovica pri Mirni"
    ],
    "name:hrv_x_preferred":[
        "Brezovica pri Mirni"
    ],
    "name:nld_x_preferred":[
        "Brezovica pri Mirni"
    ],
    "name:pol_x_preferred":[
        "Brezovica pri Mirni"
    ],
    "name:ron_x_preferred":[
        "Brezovica pri Mirni"
    ],
    "name:slv_x_preferred":[
        "Brezovica pri Mirni"
    ],
    "name:ukr_x_preferred":[
        "\u0411\u0440\u0435\u0437\u043e\u0432\u0438\u0446\u044f-\u043f\u0440\u0438-\u041c\u0438\u0440\u043d\u0456"
    ],
    "wof:name":"Brezovica pri Mirni",
    "wof:placetype":"locality",
    "wof:population":132
},
  "geometry": {"coordinates":[15.04028,45.93826],"type":"Point"}
}