{
  "type": "Feature",
  "properties": {
    "gn:admin1_code":"D4",
    "gn:asciiname":"Brezovica pri Mirni",
    "gn:country_code":"SI",
    "gn:dem":272,
    "gn:feature_class":"P",
    "gn:feature_code":"PPL",
    "gn:name":"Brezovica pri Mirni",
    "gn:population":132,
    "gn:timezone":"Europe/Ljubljana",
    "iso:country":"SI",
    "wof:name":"Brezovica pri Mirni",
    "wof:placetype":"locality",
    "wof:population":132
},
  "geometry": {"coordinates":[15.04028,45.93826],"type":"Point"}
}