{
  "type": "Feature",
  "properties": {
    "gn:admin1_code":"73",
    "gn:asciiname":"Sela pri Jugorju",
    "gn:country_code":"SI",
    "gn:dem":546,
    "gn:feature_class":"P",
    "gn:feature_code":"PPL",
    "gn:name":"Sela pri Jugorju",
    "gn:population":45,
    "gn:timezone":"Europe/Ljubljana",
    "iso:country":"SI",
    "name:bos_x_preferred":[
        "Sela pri Jugorju"
    ],
    "name:hrv_x_preferred":[
        "Sela pri Jugorju"
    ],
    "name:nld_x_preferred":[
        "Sela pri Jugorju"
    ],
    "name:pol_x_preferred":[
        "Sela pri Jugorju"
    ],
    "name:ron_x_preferred":[
        "Sela pri Jugorju"
    ],
    "name:slv_x_preferred":[
        "Sela pri Jugorju"
    ],
    "name:ukr_x_preferred":[
        "\u0421\u0435\u043b\u0430-\u043f\u0440\u0438-\u042e\u0433\u043e\u0440\u044e"
    ],
    "name:und_x_variant":[
        "Sela"
    ],
    "wof:name":"Sela pri Jugorju",
    "wof:placetype":"locality",
    "wof:population":45
},
  "geometry": {"coordinates":[15.22664,45.71018],"type":"Point"}
}