{
  "type": "Feature",
  "properties": {
    "gn:admin1_code":"K8",
    "gn:asciiname":"Tolsti Vrh pri Ravnah na Koroskem",
    "gn:country_code":"SI",
    "gn:dem":512,
    "gn:feature_class":"P",
    "gn:feature_code":"PPL",
    "gn:name":"Tolsti Vrh pri Ravnah na Koro\u0161kem",
    "gn:population":0,
    "gn:timezone":"Europe/Ljubljana",
    "iso:country":"SI",
    "name:und_x_variant":[
        "Tolsti Vrh",
        "Tolsti Vrh pri Ravnah na Koro\u0161kem"
    ],
    "wof:name":"Tolsti Vrh pri Ravnah na Koroskem",
    "wof:placetype":"locality"
},
  "geometry": {"coordinates":[14.95,46.56667],"type":"Point"}
}