{
  "type": "Feature",
  "properties": {
    "gn:admin1_code":"A3",
    "gn:asciiname":"Posavec",
    "gn:country_code":"SI",
    "gn:dem":394,
    "gn:feature_class":"P",
    "gn:feature_code":"PPL",
    "gn:name":"Posavec",
    "gn:population":387,
    "gn:timezone":"Europe/Ljubljana",
    "iso:country":"SI",
    "wof:name":"Posavec",
    "wof:placetype":"locality",
    "wof:population":387
},
  "geometry": {"coordinates":[14.24051,46.3109],"type":"Point"}
}