{
  "type": "Feature",
  "properties": {
    "gn:admin1_code":"A3",
    "gn:asciiname":"Posavec",
    "gn:country_code":"SI",
    "gn:dem":394,
    "gn:feature_class":"P",
    "gn:feature_code":"PPL",
    "gn:name":"Posavec",
    "gn:population":387,
    "gn:timezone":"Europe/Ljubljana",
    "iso:country":"SI",
    "name:bos_x_preferred":[
        "Posavec"
    ],
    "name:ceb_x_preferred":[
        "Posavec"
    ],
    "name:hrv_x_preferred":[
        "Posavec"
    ],
    "name:nld_x_preferred":[
        "Posavec"
    ],
    "name:pol_x_preferred":[
        "Posavec"
    ],
    "name:ron_x_preferred":[
        "Posavec"
    ],
    "name:slv_x_preferred":[
        "Posavec"
    ],
    "name:ukr_x_preferred":[
        "\u041f\u043e\u0441\u0430\u0432\u0435\u0446\u044c"
    ],
    "wof:name":"Posavec",
    "wof:placetype":"locality",
    "wof:population":387
},
  "geometry": {"coordinates":[14.24051,46.3109],"type":"Point"}
}