{
  "type": "Feature",
  "properties": {
    "gn:admin1_code":"B7",
    "gn:asciiname":"Gradnje",
    "gn:country_code":"SI",
    "gn:dem":365,
    "gn:feature_class":"P",
    "gn:feature_code":"PPL",
    "gn:name":"Gradnje",
    "gn:population":13,
    "gn:timezone":"Europe/Ljubljana",
    "iso:country":"SI",
    "wof:name":"Gradnje",
    "wof:placetype":"locality",
    "wof:population":13
},
  "geometry": {"coordinates":[13.88614,45.77791],"type":"Point"}
}