{
  "type": "Feature",
  "properties": {
    "gn:admin1_code":"D2",
    "gn:asciiname":"Dolje",
    "gn:country_code":"SI",
    "gn:dem":218,
    "gn:feature_class":"P",
    "gn:feature_code":"PPL",
    "gn:name":"Dolje",
    "gn:population":157,
    "gn:timezone":"Europe/Ljubljana",
    "iso:country":"SI",
    "wof:name":"Dolje",
    "wof:placetype":"locality",
    "wof:population":157
},
  "geometry": {"coordinates":[13.71291,46.19531],"type":"Point"}
}