{
  "type": "Feature",
  "properties": {
    "gn:admin1_code":"A7",
    "gn:asciiname":"Zgornje Secovo",
    "gn:country_code":"SI",
    "gn:dem":362,
    "gn:feature_class":"P",
    "gn:feature_code":"PPL",
    "gn:name":"Zgornje Se\u010dovo",
    "gn:population":99,
    "gn:timezone":"Europe/Ljubljana",
    "iso:country":"SI",
    "name:bos_x_preferred":[
        "Zgornje Se\u010dovo"
    ],
    "name:bul_x_preferred":[
        "\u0417\u0433\u043e\u0440\u043d\u0435 \u0421\u0435\u0447\u043e\u0432\u043e"
    ],
    "name:hrv_x_preferred":[
        "Zgornje Se\u010dovo"
    ],
    "name:nld_x_preferred":[
        "Zgornje Se\u010dovo"
    ],
    "name:pol_x_preferred":[
        "Zgornje Se\u010dovo"
    ],
    "name:ron_x_preferred":[
        "Zgornje Se\u010dovo"
    ],
    "name:slv_x_preferred":[
        "Zgornje Se\u010dovo"
    ],
    "name:ukr_x_preferred":[
        "\u0417\u0433\u043e\u0440\u043d\u0454 \u0421\u0435\u0447\u043e\u0432\u043e"
    ],
    "wof:name":"Zgornje Secovo",
    "wof:placetype":"locality",
    "wof:population":99
},
  "geometry": {"coordinates":[15.65926,46.25978],"type":"Point"}
}