{
  "type": "Feature",
  "properties": {
    "gn:admin1_code":"A7",
    "gn:asciiname":"Zgornje Secovo",
    "gn:country_code":"SI",
    "gn:dem":362,
    "gn:feature_class":"P",
    "gn:feature_code":"PPL",
    "gn:name":"Zgornje Se\u010dovo",
    "gn:population":99,
    "gn:timezone":"Europe/Ljubljana",
    "iso:country":"SI",
    "name:und_x_variant":[
        "Zgornje Se\u010dovo"
    ],
    "wof:name":"Zgornje Secovo",
    "wof:placetype":"locality",
    "wof:population":99
},
  "geometry": {"coordinates":[15.65926,46.25978],"type":"Point"}
}