{
  "type": "Feature",
  "properties": {
    "gn:admin1_code":"D2",
    "gn:asciiname":"Poljubinj",
    "gn:country_code":"SI",
    "gn:dem":488,
    "gn:feature_class":"P",
    "gn:feature_code":"PPL",
    "gn:name":"Poljubinj",
    "gn:population":456,
    "gn:timezone":"Europe/Ljubljana",
    "iso:country":"SI",
    "name:bos_x_preferred":[
        "Poljubinj"
    ],
    "name:bul_x_preferred":[
        "\u041f\u043e\u043b\u044e\u0431\u0438\u043d"
    ],
    "name:ceb_x_preferred":[
        "Poljubinj"
    ],
    "name:nld_x_preferred":[
        "Poljubinj"
    ],
    "name:pol_x_preferred":[
        "Poljubinj"
    ],
    "name:ron_x_preferred":[
        "Poljubinj"
    ],
    "name:slv_x_preferred":[
        "Poljubinj"
    ],
    "name:ukr_x_preferred":[
        "\u041f\u043e\u043b\u044e\u0431\u0456\u043d\u044c"
    ],
    "wof:name":"Poljubinj",
    "wof:placetype":"locality",
    "wof:population":456
},
  "geometry": {"coordinates":[13.76611,46.18427],"type":"Point"}
}