{
  "type": "Feature",
  "properties": {
    "gn:admin1_code":"E7",
    "gn:asciiname":"Zavine",
    "gn:country_code":"SI",
    "gn:dem":453,
    "gn:feature_class":"P",
    "gn:feature_code":"PPL",
    "gn:name":"Zavine",
    "gn:population":80,
    "gn:timezone":"Europe/Ljubljana",
    "iso:country":"SI",
    "wof:name":"Zavine",
    "wof:placetype":"locality",
    "wof:population":80
},
  "geometry": {"coordinates":[14.97244,46.15226],"type":"Point"}
}