{
  "type": "Feature",
  "properties": {
    "gn:admin1_code":"B3",
    "gn:asciiname":"Kozjak pri Cersaku",
    "gn:country_code":"SI",
    "gn:dem":294,
    "gn:feature_class":"P",
    "gn:feature_code":"PPL",
    "gn:name":"Kozjak pri Cer\u0161aku",
    "gn:population":158,
    "gn:timezone":"Europe/Ljubljana",
    "iso:country":"SI",
    "name:und_x_variant":[
        "Kozjak",
        "Kozjak pri Cer\u0161aku"
    ],
    "wof:name":"Kozjak pri Cersaku",
    "wof:placetype":"locality",
    "wof:population":158
},
  "geometry": {"coordinates":[15.68675,46.69875],"type":"Point"}
}