{
  "type": "Feature",
  "properties": {
    "gn:admin1_code":"B3",
    "gn:asciiname":"Kozjak pri Cersaku",
    "gn:country_code":"SI",
    "gn:dem":294,
    "gn:feature_class":"P",
    "gn:feature_code":"PPL",
    "gn:name":"Kozjak pri Cer\u0161aku",
    "gn:population":158,
    "gn:timezone":"Europe/Ljubljana",
    "iso:country":"SI",
    "name:bos_x_preferred":[
        "Kozjak pri Cer\u0161aku"
    ],
    "name:ceb_x_preferred":[
        "Kozjak pri Cer\u0161aku"
    ],
    "name:nld_x_preferred":[
        "Kozjak pri Cer\u0161aku"
    ],
    "name:pol_x_preferred":[
        "Kozjak pri Cer\u0161aku"
    ],
    "name:ron_x_preferred":[
        "Kozjak pri Cer\u0161aku"
    ],
    "name:slv_x_preferred":[
        "Kozjak pri Cer\u0161aku"
    ],
    "name:ukr_x_preferred":[
        "\u041a\u043e\u0437\u044f\u043a-\u043f\u0440\u0438-\u0426\u0435\u0440\u0448\u0430\u043a\u0443"
    ],
    "name:und_x_variant":[
        "Kozjak"
    ],
    "wof:name":"Kozjak pri Cersaku",
    "wof:placetype":"locality",
    "wof:population":158
},
  "geometry": {"coordinates":[15.68675,46.69875],"type":"Point"}
}