{
  "type": "Feature",
  "properties": {
    "gn:admin1_code":"52",
    "gn:asciiname":"Povlje",
    "gn:country_code":"SI",
    "gn:dem":1010,
    "gn:feature_class":"P",
    "gn:feature_code":"PPL",
    "gn:name":"Povlje",
    "gn:population":37,
    "gn:timezone":"Europe/Ljubljana",
    "iso:country":"SI",
    "wof:name":"Povlje",
    "wof:placetype":"locality",
    "wof:population":37
},
  "geometry": {"coordinates":[14.38408,46.33658],"type":"Point"}
}