{
  "type": "Feature",
  "properties": {
    "gn:admin1_code":"52",
    "gn:asciiname":"Povlje",
    "gn:country_code":"SI",
    "gn:dem":1010,
    "gn:feature_class":"P",
    "gn:feature_code":"PPL",
    "gn:name":"Povlje",
    "gn:population":37,
    "gn:timezone":"Europe/Ljubljana",
    "iso:country":"SI",
    "name:bos_x_preferred":[
        "Povlje"
    ],
    "name:hrv_x_preferred":[
        "Povlje"
    ],
    "name:nld_x_preferred":[
        "Povlje"
    ],
    "name:pol_x_preferred":[
        "Povlje"
    ],
    "name:ron_x_preferred":[
        "Povlje"
    ],
    "name:slv_x_preferred":[
        "Povlje"
    ],
    "name:ukr_x_preferred":[
        "\u041f\u043e\u0432\u043b\u0454"
    ],
    "wof:name":"Povlje",
    "wof:placetype":"locality",
    "wof:population":37
},
  "geometry": {"coordinates":[14.38408,46.33658],"type":"Point"}
}