{
  "type": "Feature",
  "properties": {
    "gn:admin1_code":"87",
    "gn:asciiname":"Cerovec Stanka Vraza",
    "gn:country_code":"SI",
    "gn:dem":274,
    "gn:feature_class":"P",
    "gn:feature_code":"PPL",
    "gn:name":"Cerovec Stanka Vraza",
    "gn:population":126,
    "gn:timezone":"Europe/Ljubljana",
    "iso:country":"SI",
    "wof:name":"Cerovec Stanka Vraza",
    "wof:placetype":"locality",
    "wof:population":126
},
  "geometry": {"coordinates":[16.16422,46.47781],"type":"Point"}
}