{
  "type": "Feature",
  "properties": {
    "gn:admin1_code":"87",
    "gn:asciiname":"Cerovec Stanka Vraza",
    "gn:country_code":"SI",
    "gn:dem":274,
    "gn:feature_class":"P",
    "gn:feature_code":"PPL",
    "gn:name":"Cerovec Stanka Vraza",
    "gn:population":126,
    "gn:timezone":"Europe/Ljubljana",
    "iso:country":"SI",
    "name:bos_x_preferred":[
        "Cerovec Stanka Vraza"
    ],
    "name:bul_x_preferred":[
        "\u0426\u0435\u0440\u043e\u0432\u0435\u0446 \u0421\u0442\u0430\u043d\u043a\u0430 \u0412\u0440\u0430\u0437\u0430"
    ],
    "name:ceb_x_preferred":[
        "Cerovec Stanka Vraza"
    ],
    "name:nld_x_preferred":[
        "Cerovec Stanka Vraza"
    ],
    "name:pol_x_preferred":[
        "Cerovec Stanka Vraza"
    ],
    "name:ron_x_preferred":[
        "Cerovec Stanka Vraza"
    ],
    "name:slv_x_preferred":[
        "Cerovec Stanka Vraza"
    ],
    "name:ukr_x_preferred":[
        "\u0426\u0435\u0440\u043e\u0432\u0435\u0446\u044c \u0421\u0442\u0430\u043d\u043a\u0430 \u0412\u0440\u0430\u0437\u0430"
    ],
    "wof:name":"Cerovec Stanka Vraza",
    "wof:placetype":"locality",
    "wof:population":126
},
  "geometry": {"coordinates":[16.16422,46.47781],"type":"Point"}
}