{
  "type": "Feature",
  "properties": {
    "gn:admin1_code":"D3",
    "gn:asciiname":"Zgornja Svina",
    "gn:country_code":"SI",
    "gn:dem":677,
    "gn:feature_class":"P",
    "gn:feature_code":"PPL",
    "gn:name":"Zgornja Svina",
    "gn:population":0,
    "gn:timezone":"Europe/Ljubljana",
    "iso:country":"SI",
    "wof:name":"Zgornja Svina",
    "wof:placetype":"locality"
},
  "geometry": {"coordinates":[15.06861,46.18306],"type":"Point"}
}