{
  "type": "Feature",
  "properties": {
    "gn:admin1_code":"61",
    "gn:asciiname":"Mali Vrh pri Prezganju",
    "gn:country_code":"SI",
    "gn:dem":675,
    "gn:feature_class":"P",
    "gn:feature_code":"PPL",
    "gn:name":"Mali Vrh pri Pre\u017eganju",
    "gn:population":81,
    "gn:timezone":"Europe/Ljubljana",
    "iso:country":"SI",
    "name:bos_x_preferred":[
        "Mali Vrh pri Pre\u017eganju"
    ],
    "name:bul_x_preferred":[
        "\u041c\u0430\u043b\u0438 \u0412\u0440\u044a\u0445 \u043f\u0440\u0438 \u041f\u0440\u0435\u0436\u0433\u0430\u043d\u044e"
    ],
    "name:nld_x_preferred":[
        "Mali Vrh pri Pre\u017eganju"
    ],
    "name:pol_x_preferred":[
        "Mali Vrh pri Pre\u017eganju"
    ],
    "name:ron_x_preferred":[
        "Mali Vrh pri Pre\u017eganju"
    ],
    "name:slv_x_preferred":[
        "Mali Vrh pri Pre\u017eganju"
    ],
    "name:ukr_x_preferred":[
        "\u041c\u0430\u043b\u0438\u0439 \u0412\u0440\u0445-\u043f\u0440\u0438-\u041f\u0440\u0435\u0436\u0433\u0430\u043d\u044e"
    ],
    "name:und_x_variant":[
        "Mali Vrh pri Pre\u017eganju"
    ],
    "wof:name":"Mali Vrh pri Prezganju",
    "wof:placetype":"locality",
    "wof:population":81
},
  "geometry": {"coordinates":[14.73302,46.00439],"type":"Point"}
}