{
  "type": "Feature",
  "properties": {
    "gn:admin1_code":"P7",
    "gn:asciiname":"Zgornje Partinje",
    "gn:country_code":"SI",
    "gn:dem":320,
    "gn:feature_class":"P",
    "gn:feature_code":"PPLL",
    "gn:name":"Zgornje Partinje",
    "gn:population":569,
    "gn:timezone":"Europe/Ljubljana",
    "iso:country":"SI",
    "name:bos_x_preferred":[
        "Zgornje Partinje"
    ],
    "name:ceb_x_preferred":[
        "Zgornje Partinje"
    ],
    "name:nld_x_preferred":[
        "Zgornje Partinje"
    ],
    "name:pol_x_preferred":[
        "Zgornje Partinje"
    ],
    "name:ron_x_preferred":[
        "Zgornje Partinje"
    ],
    "name:slv_x_preferred":[
        "Zgornje Partinje"
    ],
    "name:ukr_x_preferred":[
        "\u0417\u0433\u043e\u0440\u043d\u0454 \u041f\u0430\u0440\u0442\u0438\u043d\u0454"
    ],
    "name:und_x_variant":[
        "Partinje",
        "Zgornje Partinje"
    ],
    "wof:name":"Zgornje Partinje",
    "wof:placetype":"locality",
    "wof:population":569
},
  "geometry": {"coordinates":[15.75861,46.59556],"type":"Point"}
}