{
  "type": "Feature",
  "properties": {
    "gn:admin1_code":"P7",
    "gn:asciiname":"Zgornje Partinje",
    "gn:country_code":"SI",
    "gn:dem":320,
    "gn:feature_class":"P",
    "gn:feature_code":"PPLL",
    "gn:name":"Zgornje Partinje",
    "gn:population":569,
    "gn:timezone":"Europe/Ljubljana",
    "iso:country":"SI",
    "name:und_x_variant":[
        "Partinje",
        "Zgornje Partinje"
    ],
    "wof:name":"Zgornje Partinje",
    "wof:placetype":"locality",
    "wof:population":569
},
  "geometry": {"coordinates":[15.75861,46.59556],"type":"Point"}
}