{
  "type": "Feature",
  "properties": {
    "gn:admin1_code":"A1",
    "gn:asciiname":"Kapelski Vrh",
    "gn:country_code":"SI",
    "gn:dem":271,
    "gn:feature_class":"P",
    "gn:feature_code":"PPL",
    "gn:name":"Kapelski Vrh",
    "gn:population":243,
    "gn:timezone":"Europe/Ljubljana",
    "iso:country":"SI",
    "name:bos_x_preferred":[
        "Kapelski Vrh"
    ],
    "name:ceb_x_preferred":[
        "Kapelski Vrh"
    ],
    "name:nld_x_preferred":[
        "Kapelski Vrh"
    ],
    "name:pol_x_preferred":[
        "Kapelski Vrh"
    ],
    "name:ron_x_preferred":[
        "Kapelski Vrh"
    ],
    "name:slv_x_preferred":[
        "Kapelski Vrh"
    ],
    "name:ukr_x_preferred":[
        "\u041a\u0430\u043f\u0435\u043b\u0441\u044c\u043a\u0438\u0439 \u0412\u0440\u0445"
    ],
    "wof:name":"Kapelski Vrh",
    "wof:placetype":"locality",
    "wof:population":243
},
  "geometry": {"coordinates":[16.02819,46.61413],"type":"Point"}
}