{
  "type": "Feature",
  "properties": {
    "gn:admin1_code":"O9",
    "gn:asciiname":"Grusovlje",
    "gn:country_code":"SI",
    "gn:dem":378,
    "gn:feature_class":"P",
    "gn:feature_code":"PPL",
    "gn:name":"Gru\u0161ovlje",
    "gn:population":72,
    "gn:timezone":"Europe/Ljubljana",
    "iso:country":"SI",
    "name:bos_x_preferred":[
        "Gru\u0161ovlje"
    ],
    "name:nld_x_preferred":[
        "Gru\u0161ovlje"
    ],
    "name:pol_x_preferred":[
        "Gru\u0161ovlje"
    ],
    "name:ron_x_preferred":[
        "Gru\u0161ovlje"
    ],
    "name:slv_x_preferred":[
        "Gru\u0161ovlje"
    ],
    "name:ukr_x_preferred":[
        "\u0413\u0440\u0443\u0448\u043e\u0432\u043b\u0454"
    ],
    "name:und_x_variant":[
        "Gru\u0161ovlje"
    ],
    "wof:name":"Grusovlje",
    "wof:placetype":"locality",
    "wof:population":72
},
  "geometry": {"coordinates":[14.88118,46.31789000000001],"type":"Point"}
}