{
  "type": "Feature",
  "properties": {
    "gn:admin1_code":"26",
    "gn:asciiname":"Dvorjane",
    "gn:country_code":"SI",
    "gn:dem":231,
    "gn:feature_class":"P",
    "gn:feature_code":"PPL",
    "gn:name":"Dvorjane",
    "gn:population":714,
    "gn:timezone":"Europe/Ljubljana",
    "iso:country":"SI",
    "wof:name":"Dvorjane",
    "wof:placetype":"locality",
    "wof:population":714
},
  "geometry": {"coordinates":[15.76336,46.49116],"type":"Point"}
}