{
  "type": "Feature",
  "properties": {
    "gn:admin1_code":"26",
    "gn:asciiname":"Dvorjane",
    "gn:country_code":"SI",
    "gn:dem":231,
    "gn:feature_class":"P",
    "gn:feature_code":"PPL",
    "gn:name":"Dvorjane",
    "gn:population":714,
    "gn:timezone":"Europe/Ljubljana",
    "iso:country":"SI",
    "name:bos_x_preferred":[
        "Dvorjane"
    ],
    "name:ceb_x_preferred":[
        "Dvorjane"
    ],
    "name:nld_x_preferred":[
        "Dvorjane"
    ],
    "name:pol_x_preferred":[
        "Dvorjane"
    ],
    "name:ron_x_preferred":[
        "Dvorjane"
    ],
    "name:slv_x_preferred":[
        "Dvorjane"
    ],
    "name:ukr_x_preferred":[
        "\u0414\u0432\u043e\u0440\u044f\u043d\u0435"
    ],
    "wof:name":"Dvorjane",
    "wof:placetype":"locality",
    "wof:population":714
},
  "geometry": {"coordinates":[15.76336,46.49116],"type":"Point"}
}