{
  "type": "Feature",
  "properties": {
    "gn:admin1_code":"H7",
    "gn:asciiname":"Konca Vas",
    "gn:country_code":"SI",
    "gn:dem":479,
    "gn:feature_class":"P",
    "gn:feature_code":"PPL",
    "gn:name":"Konca Vas",
    "gn:population":113,
    "gn:timezone":"Europe/Ljubljana",
    "iso:country":"SI",
    "wof:name":"Konca Vas",
    "wof:placetype":"locality",
    "wof:population":113
},
  "geometry": {"coordinates":[14.84571,45.67311],"type":"Point"}
}