{
  "type": "Feature",
  "properties": {
    "gn:admin1_code":"H7",
    "gn:asciiname":"Konca Vas",
    "gn:country_code":"SI",
    "gn:dem":479,
    "gn:feature_class":"P",
    "gn:feature_code":"PPL",
    "gn:name":"Konca Vas",
    "gn:population":113,
    "gn:timezone":"Europe/Ljubljana",
    "iso:country":"SI",
    "name:bos_x_preferred":[
        "Konca vas"
    ],
    "name:ceb_x_preferred":[
        "Konca Vas"
    ],
    "name:hrv_x_preferred":[
        "Konca vas"
    ],
    "name:nld_x_preferred":[
        "Konca vas"
    ],
    "name:pol_x_preferred":[
        "Konca vas"
    ],
    "name:ron_x_preferred":[
        "Konca vas"
    ],
    "name:slv_x_preferred":[
        "Konca vas"
    ],
    "name:ukr_x_preferred":[
        "\u041a\u043e\u043d\u0446\u0430 \u0412\u0430\u0441"
    ],
    "wof:name":"Konca Vas",
    "wof:placetype":"locality",
    "wof:population":113
},
  "geometry": {"coordinates":[14.84571,45.67311],"type":"Point"}
}