{
  "type": "Feature",
  "properties": {
    "gn:admin1_code":"H9",
    "gn:asciiname":"Kuzelj",
    "gn:country_code":"SI",
    "gn:dem":251,
    "gn:feature_class":"P",
    "gn:feature_code":"PPL",
    "gn:name":"Ku\u017eelj",
    "gn:population":53,
    "gn:timezone":"Europe/Ljubljana",
    "iso:country":"SI",
    "wof:name":"Kuzelj",
    "wof:placetype":"locality",
    "wof:population":53
},
  "geometry": {"coordinates":[14.81043,45.47732],"type":"Point"}
}