{
  "type": "Feature",
  "properties": {
    "gn:admin1_code":"H9",
    "gn:asciiname":"Kuzelj",
    "gn:country_code":"SI",
    "gn:dem":251,
    "gn:feature_class":"P",
    "gn:feature_code":"PPL",
    "gn:name":"Ku\u017eelj",
    "gn:population":53,
    "gn:timezone":"Europe/Ljubljana",
    "iso:country":"SI",
    "name:bos_x_preferred":[
        "Ku\u017eelj"
    ],
    "name:hrv_x_preferred":[
        "Ku\u017eelj"
    ],
    "name:nld_x_preferred":[
        "Ku\u017eelj"
    ],
    "name:pol_x_preferred":[
        "Ku\u017eelj"
    ],
    "name:ron_x_preferred":[
        "Ku\u017eelj"
    ],
    "name:sco_x_preferred":[
        "Ku\u017eelj"
    ],
    "name:slv_x_preferred":[
        "Ku\u017eelj"
    ],
    "name:ukr_x_preferred":[
        "\u041a\u0443\u0436\u0435\u043b\u044c"
    ],
    "wof:name":"Kuzelj",
    "wof:placetype":"locality",
    "wof:population":53
},
  "geometry": {"coordinates":[14.81043,45.47732],"type":"Point"}
}