{
  "type": "Feature",
  "properties": {
    "gn:admin1_code":"I5",
    "gn:asciiname":"Spodnje Jelenje",
    "gn:country_code":"SI",
    "gn:dem":737,
    "gn:feature_class":"P",
    "gn:feature_code":"PPL",
    "gn:name":"Spodnje Jelenje",
    "gn:population":33,
    "gn:timezone":"Europe/Ljubljana",
    "iso:country":"SI",
    "name:bos_x_preferred":[
        "Spodnje Jelenje"
    ],
    "name:bul_x_preferred":[
        "\u0421\u043f\u043e\u0434\u043d\u0435 \u0419\u0435\u043b\u0435\u043d\u0435"
    ],
    "name:nld_x_preferred":[
        "Spodnje Jelenje"
    ],
    "name:pol_x_preferred":[
        "Spodnje Jelenje"
    ],
    "name:ron_x_preferred":[
        "Spodnje Jelenje"
    ],
    "name:slv_x_preferred":[
        "Spodnje Jelenje"
    ],
    "name:ukr_x_preferred":[
        "\u0421\u043f\u043e\u0434\u043d\u0454 \u0404\u043b\u0435\u043d\u0454"
    ],
    "wof:name":"Spodnje Jelenje",
    "wof:placetype":"locality",
    "wof:population":33
},
  "geometry": {"coordinates":[15.00364,46.04046],"type":"Point"}
}