{
  "type": "Feature",
  "properties": {
    "gn:admin1_code":"F2",
    "gn:asciiname":"Muhovec",
    "gn:country_code":"SI",
    "gn:dem":600,
    "gn:feature_class":"P",
    "gn:feature_code":"PPL",
    "gn:name":"Muhovec",
    "gn:population":0,
    "gn:timezone":"Europe/Ljubljana",
    "iso:country":"SI",
    "wof:name":"Muhovec",
    "wof:placetype":"locality"
},
  "geometry": {"coordinates":[14.09611,46.07222],"type":"Point"}
}