{
  "type": "Feature",
  "properties": {
    "gn:admin1_code":"P3",
    "gn:asciiname":"Dol pri Smarjeti",
    "gn:country_code":"SI",
    "gn:dem":203,
    "gn:feature_class":"P",
    "gn:feature_code":"PPL",
    "gn:name":"Dol pri \u0160marjeti",
    "gn:population":34,
    "gn:timezone":"Europe/Ljubljana",
    "iso:country":"SI",
    "name:und_x_variant":[
        "Dol pri \u0160marjeti"
    ],
    "wof:name":"Dol pri Smarjeti",
    "wof:placetype":"locality",
    "wof:population":34
},
  "geometry": {"coordinates":[15.22591,45.91614000000001],"type":"Point"}
}