{
  "type": "Feature",
  "properties": {
    "gn:admin1_code":"P3",
    "gn:asciiname":"Dol pri Smarjeti",
    "gn:country_code":"SI",
    "gn:dem":203,
    "gn:feature_class":"P",
    "gn:feature_code":"PPL",
    "gn:name":"Dol pri \u0160marjeti",
    "gn:population":34,
    "gn:timezone":"Europe/Ljubljana",
    "iso:country":"SI",
    "name:bos_x_preferred":[
        "Dol pri \u0160marjeti"
    ],
    "name:hrv_x_preferred":[
        "Dol pri \u0160marjeti"
    ],
    "name:nld_x_preferred":[
        "Dol pri \u0160marjeti"
    ],
    "name:pol_x_preferred":[
        "Dol pri \u0160marjeti"
    ],
    "name:ron_x_preferred":[
        "Dol pri \u0160marjeti"
    ],
    "name:slv_x_preferred":[
        "Dol pri \u0160marjeti"
    ],
    "name:ukr_x_preferred":[
        "\u0414\u043e\u043b-\u043f\u0440\u0438-\u0428\u043c\u0430\u0440\u0454\u0442\u0456"
    ],
    "wof:name":"Dol pri Smarjeti",
    "wof:placetype":"locality",
    "wof:population":34
},
  "geometry": {"coordinates":[15.22591,45.91614000000001],"type":"Point"}
}