{
  "type": "Feature",
  "properties": {
    "gn:admin1_code":"L1",
    "gn:asciiname":"Dolenji Lazi",
    "gn:country_code":"SI",
    "gn:dem":499,
    "gn:feature_class":"P",
    "gn:feature_code":"PPL",
    "gn:name":"Dolenji Lazi",
    "gn:population":288,
    "gn:timezone":"Europe/Ljubljana",
    "iso:country":"SI",
    "name:bos_x_preferred":[
        "Dolenji Lazi"
    ],
    "name:ceb_x_preferred":[
        "Dolenji Lazi"
    ],
    "name:nld_x_preferred":[
        "Dolenji Lazi"
    ],
    "name:pol_x_preferred":[
        "Dolenji Lazi"
    ],
    "name:ron_x_preferred":[
        "Dolenji Lazi"
    ],
    "name:slv_x_preferred":[
        "Dolenji Lazi"
    ],
    "name:ukr_x_preferred":[
        "\u0414\u043e\u043b\u0435\u043d\u0456 \u041b\u0430\u0437\u0456"
    ],
    "wof:name":"Dolenji Lazi",
    "wof:placetype":"locality",
    "wof:population":288
},
  "geometry": {"coordinates":[14.7175,45.76417],"type":"Point"}
}