{
  "type": "Feature",
  "properties": {
    "gn:admin1_code":"L1",
    "gn:asciiname":"Dolenji Lazi",
    "gn:country_code":"SI",
    "gn:dem":499,
    "gn:feature_class":"P",
    "gn:feature_code":"PPL",
    "gn:name":"Dolenji Lazi",
    "gn:population":288,
    "gn:timezone":"Europe/Ljubljana",
    "iso:country":"SI",
    "wof:name":"Dolenji Lazi",
    "wof:placetype":"locality",
    "wof:population":288
},
  "geometry": {"coordinates":[14.7175,45.76417],"type":"Point"}
}