{
  "type": "Feature",
  "properties": {
    "gn:admin1_code":"08",
    "gn:asciiname":"Zupeca Vas",
    "gn:country_code":"SI",
    "gn:dem":154,
    "gn:feature_class":"P",
    "gn:feature_code":"PPL",
    "gn:name":"\u017dupe\u010da Vas",
    "gn:population":222,
    "gn:timezone":"Europe/Ljubljana",
    "iso:country":"SI",
    "name:bos_x_preferred":[
        "\u017dupe\u010da vas"
    ],
    "name:ceb_x_preferred":[
        "\u017dupe\u010da Vas"
    ],
    "name:hrv_x_preferred":[
        "\u017dupe\u010da vas"
    ],
    "name:nld_x_preferred":[
        "\u017dupe\u010da vas"
    ],
    "name:pol_x_preferred":[
        "\u017dupe\u010da vas"
    ],
    "name:ron_x_preferred":[
        "\u017dupe\u010da vas"
    ],
    "name:slv_x_preferred":[
        "\u017dupe\u010da vas"
    ],
    "name:ukr_x_preferred":[
        "\u0416\u0443\u043f\u0435\u0447\u0430 \u0412\u0430\u0441"
    ],
    "name:und_x_variant":[
        "\u017dupe\u010da Vas"
    ],
    "wof:name":"Zupeca Vas",
    "wof:placetype":"locality",
    "wof:population":222
},
  "geometry": {"coordinates":[15.53181,45.8914],"type":"Point"}
}