{
  "type": "Feature",
  "properties": {
    "gn:admin1_code":"H7",
    "gn:asciiname":"Muha Vas",
    "gn:country_code":"SI",
    "gn:dem":559,
    "gn:feature_class":"P",
    "gn:feature_code":"PPL",
    "gn:name":"Muha Vas",
    "gn:population":0,
    "gn:timezone":"Europe/Ljubljana",
    "iso:country":"SI",
    "name:bos_x_preferred":[
        "Muha vas"
    ],
    "name:deu_x_historical":[
        "Oberfliegendorf"
    ],
    "name:deu_x_preferred":[
        "Oberfliegendorf"
    ],
    "name:pol_x_preferred":[
        "Muha vas"
    ],
    "name:slv_x_historical":[
        "Gorenja Turkova Draga"
    ],
    "name:slv_x_preferred":[
        "Gorenja Turkova Draga"
    ],
    "name:slv_x_variant":[
        "Muha vas"
    ],
    "wof:name":"Muha Vas",
    "wof:placetype":"locality"
},
  "geometry": {"coordinates":[14.93056,45.53556],"type":"Point"}
}