{
  "type": "Feature",
  "properties": {
    "gn:admin1_code":"54",
    "gn:asciiname":"Raka",
    "gn:country_code":"SI",
    "gn:dem":263,
    "gn:feature_class":"P",
    "gn:feature_code":"PPL",
    "gn:name":"Raka",
    "gn:population":311,
    "gn:timezone":"Europe/Ljubljana",
    "iso:country":"SI",
    "name:und_x_variant":[
        "Raku",
        "Raka"
    ],
    "wof:name":"Raka",
    "wof:placetype":"locality",
    "wof:population":311
},
  "geometry": {"coordinates":[15.38417,45.92972],"type":"Point"}
}