{
  "type": "Feature",
  "properties": {
    "gn:admin1_code":"54",
    "gn:asciiname":"Raka",
    "gn:country_code":"SI",
    "gn:dem":263,
    "gn:feature_class":"P",
    "gn:feature_code":"PPL",
    "gn:name":"Raka",
    "gn:population":311,
    "gn:timezone":"Europe/Ljubljana",
    "iso:country":"SI",
    "name:bos_x_preferred":[
        "Raka"
    ],
    "name:ceb_x_preferred":[
        "Raka"
    ],
    "name:hrv_x_preferred":[
        "Raka"
    ],
    "name:nld_x_preferred":[
        "Raka"
    ],
    "name:pol_x_preferred":[
        "Raka"
    ],
    "name:ron_x_preferred":[
        "Raka"
    ],
    "name:sco_x_preferred":[
        "Raka"
    ],
    "name:slv_x_preferred":[
        "Raka"
    ],
    "name:ukr_x_preferred":[
        "\u0420\u0430\u043a\u0430"
    ],
    "name:und_x_variant":[
        "Raku"
    ],
    "wof:name":"Raka",
    "wof:placetype":"locality",
    "wof:population":311
},
  "geometry": {"coordinates":[15.38417,45.92972],"type":"Point"}
}