{
  "type": "Feature",
  "properties": {
    "gn:admin1_code":"F8",
    "gn:asciiname":"Gerlinci",
    "gn:country_code":"SI",
    "gn:dem":333,
    "gn:feature_class":"P",
    "gn:feature_code":"PPL",
    "gn:name":"Gerlinci",
    "gn:population":334,
    "gn:timezone":"Europe/Ljubljana",
    "iso:country":"SI",
    "name:bos_x_preferred":[
        "Gerlinci"
    ],
    "name:bul_x_preferred":[
        "\u0413\u0435\u0440\u043b\u0438\u043d\u0446\u0438"
    ],
    "name:ceb_x_preferred":[
        "Gerlinci"
    ],
    "name:deu_x_preferred":[
        "Gerlinci"
    ],
    "name:epo_x_preferred":[
        "Gerlinci"
    ],
    "name:hrv_x_preferred":[
        "Gerlinci"
    ],
    "name:hun_x_preferred":[
        "G\u00f6rhegy"
    ],
    "name:nld_x_preferred":[
        "Gerlinci"
    ],
    "name:pol_x_preferred":[
        "Gerlinci"
    ],
    "name:ron_x_preferred":[
        "Gerlinci"
    ],
    "name:slv_x_preferred":[
        "Gerlinci"
    ],
    "name:ukr_x_preferred":[
        "\u0413\u0435\u0440\u043b\u0438\u043d\u0446\u0456"
    ],
    "name:und_x_variant":[
        "G\u00f6rhegy",
        "Grlinci",
        "J\u00f6rgelsdorf",
        "Gerlinci"
    ],
    "wof:name":"Gerlinci",
    "wof:placetype":"locality",
    "wof:population":334
},
  "geometry": {"coordinates":[16.00944,46.75833],"type":"Point"}
}