{
  "type": "Feature",
  "properties": {
    "gn:admin1_code":"D8",
    "gn:asciiname":"Dvorska Vas",
    "gn:country_code":"SI",
    "gn:dem":613,
    "gn:feature_class":"P",
    "gn:feature_code":"PPL",
    "gn:name":"Dvorska Vas",
    "gn:population":119,
    "gn:timezone":"Europe/Ljubljana",
    "iso:country":"SI",
    "wof:name":"Dvorska Vas",
    "wof:placetype":"locality",
    "wof:population":119
},
  "geometry": {"coordinates":[14.63583,45.80972],"type":"Point"}
}