{
  "type": "Feature",
  "properties": {
    "gn:admin1_code":"D8",
    "gn:asciiname":"Dvorska Vas",
    "gn:country_code":"SI",
    "gn:dem":613,
    "gn:feature_class":"P",
    "gn:feature_code":"PPL",
    "gn:name":"Dvorska Vas",
    "gn:population":119,
    "gn:timezone":"Europe/Ljubljana",
    "iso:country":"SI",
    "name:bos_x_preferred":[
        "Dvorska vas"
    ],
    "name:ceb_x_preferred":[
        "Dvorska Vas"
    ],
    "name:nld_x_preferred":[
        "Dvorska vas"
    ],
    "name:pol_x_preferred":[
        "Dvorska vas"
    ],
    "name:ron_x_preferred":[
        "Dvorska vas"
    ],
    "name:slv_x_preferred":[
        "Dvorska vas"
    ],
    "name:ukr_x_preferred":[
        "\u0414\u0432\u043e\u0440\u0441\u044c\u043a\u0430 \u0412\u0430\u0441"
    ],
    "wof:name":"Dvorska Vas",
    "wof:placetype":"locality",
    "wof:population":119
},
  "geometry": {"coordinates":[14.63583,45.80972],"type":"Point"}
}