{
  "type": "Feature",
  "properties": {
    "gn:admin1_code":"17",
    "gn:asciiname":"Milici",
    "gn:country_code":"SI",
    "gn:dem":258,
    "gn:feature_class":"P",
    "gn:feature_code":"PPL",
    "gn:name":"Mili\u010di",
    "gn:population":19,
    "gn:timezone":"Europe/Ljubljana",
    "iso:country":"SI",
    "name:bos_x_preferred":[
        "Mili\u010di"
    ],
    "name:hrv_x_preferred":[
        "Mili\u010di"
    ],
    "name:nld_x_preferred":[
        "Mili\u010di"
    ],
    "name:pol_x_preferred":[
        "Mili\u010di"
    ],
    "name:ron_x_preferred":[
        "Mili\u010di"
    ],
    "name:slv_x_preferred":[
        "Mili\u010di"
    ],
    "name:srp_x_preferred":[
        "\u041c\u0438\u043b\u0438\u045b\u0438"
    ],
    "name:ukr_x_preferred":[
        "\u041c\u0438\u043b\u0438\u0447\u0456"
    ],
    "name:und_x_variant":[
        "Mili\u010di"
    ],
    "wof:name":"Milici",
    "wof:placetype":"locality",
    "wof:population":19
},
  "geometry": {"coordinates":[15.3588,45.49291],"type":"Point"}
}