{
  "type": "Feature",
  "properties": {
    "gn:admin1_code":"94",
    "gn:asciiname":"Velika Brda",
    "gn:country_code":"SI",
    "gn:dem":544,
    "gn:feature_class":"P",
    "gn:feature_code":"PPL",
    "gn:name":"Velika Brda",
    "gn:population":43,
    "gn:timezone":"Europe/Ljubljana",
    "iso:country":"SI",
    "name:bos_x_preferred":[
        "Velika Brda"
    ],
    "name:fas_x_preferred":[
        "\u0648\u0644\u06cc\u06a9\u0627 \u0628\u0631\u062f\u0627"
    ],
    "name:hrv_x_preferred":[
        "Velika Brda"
    ],
    "name:nld_x_preferred":[
        "Velika Brda"
    ],
    "name:pol_x_preferred":[
        "Velika Brda"
    ],
    "name:ron_x_preferred":[
        "Velika Brda"
    ],
    "name:slv_x_historical":[
        "Veliko Brdo"
    ],
    "name:slv_x_preferred":[
        "Veliko Brdo"
    ],
    "name:slv_x_variant":[
        "Velika Brda"
    ],
    "name:ukr_x_preferred":[
        "\u0412\u0435\u043b\u0438\u043a\u0430 \u0411\u0440\u0434\u0430"
    ],
    "name:und_x_variant":[
        "Berdo"
    ],
    "wof:name":"Velika Brda",
    "wof:placetype":"locality",
    "wof:population":43
},
  "geometry": {"coordinates":[14.11194,45.77167],"type":"Point"}
}