{
  "type": "Feature",
  "properties": {
    "gn:admin1_code":"K1",
    "gn:asciiname":"Spodnje Gruskovje",
    "gn:country_code":"SI",
    "gn:dem":333,
    "gn:feature_class":"P",
    "gn:feature_code":"PPL",
    "gn:name":"Spodnje Gru\u0161kovje",
    "gn:population":50,
    "gn:timezone":"Europe/Ljubljana",
    "iso:country":"SI",
    "name:bos_x_preferred":[
        "Spodnje Gru\u0161kovje"
    ],
    "name:hrv_x_preferred":[
        "Spodnje Gru\u0161kovje"
    ],
    "name:nld_x_preferred":[
        "Spodnje Gru\u0161kovje"
    ],
    "name:pol_x_preferred":[
        "Spodnje Gru\u0161kovje"
    ],
    "name:ron_x_preferred":[
        "Spodnje Gru\u0161kovje"
    ],
    "name:slv_x_preferred":[
        "Spodnje Gru\u0161kovje"
    ],
    "name:ukr_x_preferred":[
        "\u0421\u043f\u043e\u0434\u043d\u0454 \u0413\u0440\u0443\u0448\u043a\u043e\u0432\u0454"
    ],
    "name:und_x_variant":[
        "Spodnje Gru\u0161kovje"
    ],
    "wof:name":"Spodnje Gruskovje",
    "wof:placetype":"locality",
    "wof:population":50
},
  "geometry": {"coordinates":[15.90075,46.33091],"type":"Point"}
}