{
  "type": "Feature",
  "properties": {
    "gn:admin1_code":"K1",
    "gn:asciiname":"Spodnje Gruskovje",
    "gn:country_code":"SI",
    "gn:dem":333,
    "gn:feature_class":"P",
    "gn:feature_code":"PPL",
    "gn:name":"Spodnje Gru\u0161kovje",
    "gn:population":50,
    "gn:timezone":"Europe/Ljubljana",
    "iso:country":"SI",
    "name:und_x_variant":[
        "Spodnje Gru\u0161kovje"
    ],
    "wof:name":"Spodnje Gruskovje",
    "wof:placetype":"locality",
    "wof:population":50
},
  "geometry": {"coordinates":[15.90075,46.33091],"type":"Point"}
}