{
  "type": "Feature",
  "properties": {
    "gn:admin1_code":"F6",
    "gn:asciiname":"Mramorovo pri Pajkovem",
    "gn:country_code":"SI",
    "gn:dem":700,
    "gn:feature_class":"P",
    "gn:feature_code":"PPL",
    "gn:name":"Mramorovo pri Pajkovem",
    "gn:population":15,
    "gn:timezone":"Europe/Ljubljana",
    "iso:country":"SI",
    "wof:name":"Mramorovo pri Pajkovem",
    "wof:placetype":"locality",
    "wof:population":15
},
  "geometry": {"coordinates":[14.49211,45.80985],"type":"Point"}
}