{
  "type": "Feature",
  "properties": {
    "gn:admin1_code":"L8",
    "gn:asciiname":"Bajgot",
    "gn:country_code":"SI",
    "gn:dem":1055,
    "gn:feature_class":"P",
    "gn:feature_code":"PPL",
    "gn:name":"Bajgot",
    "gn:population":0,
    "gn:timezone":"Europe/Ljubljana",
    "iso:country":"SI",
    "wof:name":"Bajgot",
    "wof:placetype":"locality"
},
  "geometry": {"coordinates":[15.44944,46.48139000000001],"type":"Point"}
}