{
  "type": "Feature",
  "properties": {
    "gn:admin1_code":"94",
    "gn:asciiname":"Hrusevje",
    "gn:country_code":"SI",
    "gn:dem":542,
    "gn:feature_class":"P",
    "gn:feature_code":"PPL",
    "gn:name":"Hru\u0161evje",
    "gn:population":248,
    "gn:timezone":"Europe/Ljubljana",
    "iso:country":"SI",
    "name:und_x_variant":[
        "Cruscevie",
        "Hru\u0161evje"
    ],
    "wof:name":"Hrusevje",
    "wof:placetype":"locality",
    "wof:population":248
},
  "geometry": {"coordinates":[14.10639,45.76056],"type":"Point"}
}