{
  "type": "Feature",
  "properties": {
    "gn:admin1_code":"94",
    "gn:asciiname":"Hrusevje",
    "gn:country_code":"SI",
    "gn:dem":542,
    "gn:feature_class":"P",
    "gn:feature_code":"PPL",
    "gn:name":"Hru\u0161evje",
    "gn:population":248,
    "gn:timezone":"Europe/Ljubljana",
    "iso:country":"SI",
    "name:bos_x_preferred":[
        "Hru\u0161evje"
    ],
    "name:ceb_x_preferred":[
        "Hru\u0161evje"
    ],
    "name:hrv_x_preferred":[
        "Hru\u0161evje"
    ],
    "name:nld_x_preferred":[
        "Hru\u0161evje"
    ],
    "name:pol_x_preferred":[
        "Hru\u0161evje"
    ],
    "name:ron_x_preferred":[
        "Hru\u0161evje"
    ],
    "name:slv_x_preferred":[
        "Hru\u0161evje"
    ],
    "name:ukr_x_preferred":[
        "\u0425\u0440\u0443\u0448\u0435\u0432\u0454"
    ],
    "name:und_x_variant":[
        "Cruscevie"
    ],
    "wof:name":"Hrusevje",
    "wof:placetype":"locality",
    "wof:population":248
},
  "geometry": {"coordinates":[14.10639,45.76056],"type":"Point"}
}