{
  "type": "Feature",
  "properties": {
    "gn:admin1_code":"P8",
    "gn:asciiname":"Gradisce",
    "gn:country_code":"SI",
    "gn:dem":283,
    "gn:feature_class":"P",
    "gn:feature_code":"PPL",
    "gn:name":"Gradi\u0161\u010de",
    "gn:population":41,
    "gn:timezone":"Europe/Ljubljana",
    "iso:country":"SI",
    "name:und_x_variant":[
        "Gradi\u0161\u010de"
    ],
    "wof:name":"Gradisce",
    "wof:placetype":"locality",
    "wof:population":41
},
  "geometry": {"coordinates":[16.07445,46.47209],"type":"Point"}
}