{
  "type": "Feature",
  "properties": {
    "gn:admin1_code":"J7",
    "gn:asciiname":"Dolenje Lakovnice",
    "gn:country_code":"SI",
    "gn:dem":255,
    "gn:feature_class":"P",
    "gn:feature_code":"PPL",
    "gn:name":"Dolenje Lakovnice",
    "gn:population":79,
    "gn:timezone":"Europe/Ljubljana",
    "iso:country":"SI",
    "name:bos_x_preferred":[
        "Dolenje Lakovnice"
    ],
    "name:hrv_x_preferred":[
        "Dolenje Lakovnice"
    ],
    "name:nld_x_preferred":[
        "Dolenje Lakovnice"
    ],
    "name:pol_x_preferred":[
        "Dolenje Lakovnice"
    ],
    "name:ron_x_preferred":[
        "Dolenje Lakovnice"
    ],
    "name:slv_x_preferred":[
        "Dolenje Lakovnice"
    ],
    "name:ukr_x_preferred":[
        "\u0414\u043e\u043b\u0435\u043d\u0454 \u041b\u0430\u043a\u043e\u0432\u043d\u0438\u0446\u0435"
    ],
    "wof:name":"Dolenje Lakovnice",
    "wof:placetype":"locality",
    "wof:population":79
},
  "geometry": {"coordinates":[15.17381,45.75042],"type":"Point"}
}