{
  "type": "Feature",
  "properties": {
    "gn:admin1_code":"J7",
    "gn:asciiname":"Dolenje Lakovnice",
    "gn:country_code":"SI",
    "gn:dem":255,
    "gn:feature_class":"P",
    "gn:feature_code":"PPL",
    "gn:name":"Dolenje Lakovnice",
    "gn:population":79,
    "gn:timezone":"Europe/Ljubljana",
    "iso:country":"SI",
    "wof:name":"Dolenje Lakovnice",
    "wof:placetype":"locality",
    "wof:population":79
},
  "geometry": {"coordinates":[15.17381,45.75042],"type":"Point"}
}