{
  "type": "Feature",
  "properties": {
    "gn:admin1_code":"J7",
    "gn:asciiname":"Potov Vrh",
    "gn:country_code":"SI",
    "gn:dem":241,
    "gn:feature_class":"P",
    "gn:feature_code":"PPL",
    "gn:name":"Potov Vrh",
    "gn:population":171,
    "gn:timezone":"Europe/Ljubljana",
    "iso:country":"SI",
    "name:bos_x_preferred":[
        "Potov Vrh"
    ],
    "name:ceb_x_preferred":[
        "Potov Vrh"
    ],
    "name:hrv_x_preferred":[
        "Potov Vrh"
    ],
    "name:nld_x_preferred":[
        "Potov Vrh"
    ],
    "name:pol_x_preferred":[
        "Potov Vrh"
    ],
    "name:ron_x_preferred":[
        "Potov Vrh"
    ],
    "name:slv_x_preferred":[
        "Potov Vrh"
    ],
    "name:ukr_x_preferred":[
        "\u041f\u043e\u0442\u043e\u0432 \u0412\u0440\u0445"
    ],
    "wof:name":"Potov Vrh",
    "wof:placetype":"locality",
    "wof:population":171
},
  "geometry": {"coordinates":[15.2295,45.80771],"type":"Point"}
}