{
  "type": "Feature",
  "properties": {
    "gn:admin1_code":"J7",
    "gn:asciiname":"Potov Vrh",
    "gn:country_code":"SI",
    "gn:dem":241,
    "gn:feature_class":"P",
    "gn:feature_code":"PPL",
    "gn:name":"Potov Vrh",
    "gn:population":171,
    "gn:timezone":"Europe/Ljubljana",
    "iso:country":"SI",
    "wof:name":"Potov Vrh",
    "wof:placetype":"locality",
    "wof:population":171
},
  "geometry": {"coordinates":[15.2295,45.80771],"type":"Point"}
}