{
  "type": "Feature",
  "properties": {
    "gn:admin1_code":"G6",
    "gn:asciiname":"Businec",
    "gn:country_code":"SI",
    "gn:dem":207,
    "gn:feature_class":"P",
    "gn:feature_code":"PPL",
    "gn:name":"Bu\u0161inec",
    "gn:population":40,
    "gn:timezone":"Europe/Ljubljana",
    "iso:country":"SI",
    "name:bos_x_preferred":[
        "Bu\u0161inec"
    ],
    "name:hrv_x_preferred":[
        "Bu\u0161inec"
    ],
    "name:nld_x_preferred":[
        "Bu\u0161inec"
    ],
    "name:pol_x_preferred":[
        "Bu\u0161inec"
    ],
    "name:ron_x_preferred":[
        "Bu\u0161inec"
    ],
    "name:slv_x_preferred":[
        "Bu\u0161inec"
    ],
    "name:ukr_x_preferred":[
        "\u0411\u0443\u0448\u0438\u043d\u0435\u0446\u044c"
    ],
    "wof:name":"Businec",
    "wof:placetype":"locality",
    "wof:population":40
},
  "geometry": {"coordinates":[15.07312,45.72821],"type":"Point"}
}