{
  "type": "Feature",
  "properties": {
    "gn:admin1_code":"N3",
    "gn:asciiname":"Polze",
    "gn:country_code":"SI",
    "gn:dem":331,
    "gn:feature_class":"P",
    "gn:feature_code":"PPL",
    "gn:name":"Pol\u017ee",
    "gn:population":102,
    "gn:timezone":"Europe/Ljubljana",
    "iso:country":"SI",
    "name:bos_x_preferred":[
        "Pol\u017ee"
    ],
    "name:ceb_x_preferred":[
        "Pol\u017ee"
    ],
    "name:hrv_x_preferred":[
        "Pol\u017ee"
    ],
    "name:nld_x_preferred":[
        "Pol\u017ee"
    ],
    "name:pol_x_preferred":[
        "Pol\u017ee"
    ],
    "name:ron_x_preferred":[
        "Pol\u017ee"
    ],
    "name:slv_x_preferred":[
        "Pol\u017ee"
    ],
    "name:ukr_x_preferred":[
        "\u041f\u043e\u043b\u0436\u0435"
    ],
    "name:und_x_variant":[
        "Pol\u017ee"
    ],
    "wof:name":"Polze",
    "wof:placetype":"locality",
    "wof:population":102
},
  "geometry": {"coordinates":[15.276,46.31713],"type":"Point"}
}