{
  "type": "Feature",
  "properties": {
    "gn:admin1_code":"H5",
    "gn:asciiname":"Spodnje Jezersko",
    "gn:country_code":"SI",
    "gn:dem":781,
    "gn:feature_class":"P",
    "gn:feature_code":"PPL",
    "gn:name":"Spodnje Jezersko",
    "gn:population":96,
    "gn:timezone":"Europe/Ljubljana",
    "iso:country":"SI",
    "wof:name":"Spodnje Jezersko",
    "wof:placetype":"locality",
    "wof:population":96
},
  "geometry": {"coordinates":[14.46667,46.38333],"type":"Point"}
}