{
  "type": "Feature",
  "properties": {
    "gn:admin1_code":"H5",
    "gn:asciiname":"Spodnje Jezersko",
    "gn:country_code":"SI",
    "gn:dem":781,
    "gn:feature_class":"P",
    "gn:feature_code":"PPL",
    "gn:name":"Spodnje Jezersko",
    "gn:population":96,
    "gn:timezone":"Europe/Ljubljana",
    "iso:country":"SI",
    "name:bos_x_preferred":[
        "Spodnje Jezersko"
    ],
    "name:bul_x_preferred":[
        "\u0421\u043f\u043e\u0434\u043d\u0435 \u0415\u0437\u0435\u0440\u0441\u043a\u043e"
    ],
    "name:hrv_x_preferred":[
        "Spodnje Jezersko"
    ],
    "name:nld_x_preferred":[
        "Spodnje Jezersko"
    ],
    "name:pol_x_preferred":[
        "Spodnje Jezersko"
    ],
    "name:ron_x_preferred":[
        "Spodnje Jezersko"
    ],
    "name:slv_x_preferred":[
        "Spodnje Jezersko"
    ],
    "name:ukr_x_preferred":[
        "\u0421\u043f\u043e\u0434\u043d\u0454 \u0404\u0437\u0435\u0440\u0441\u044c\u043a\u043e"
    ],
    "wof:name":"Spodnje Jezersko",
    "wof:placetype":"locality",
    "wof:population":96
},
  "geometry": {"coordinates":[14.46667,46.38333],"type":"Point"}
}