{
  "type": "Feature",
  "properties": {
    "gn:admin1_code":"27",
    "gn:asciiname":"Dolenja Ravan",
    "gn:country_code":"SI",
    "gn:dem":633,
    "gn:feature_class":"P",
    "gn:feature_code":"PPL",
    "gn:name":"Dolenja Ravan",
    "gn:population":14,
    "gn:timezone":"Europe/Ljubljana",
    "iso:country":"SI",
    "name:und_x_variant":[
        "Dolenji Ravni",
        "Dolenja Ravan"
    ],
    "wof:name":"Dolenja Ravan",
    "wof:placetype":"locality",
    "wof:population":14
},
  "geometry": {"coordinates":[14.14274,46.15013],"type":"Point"}
}