{
  "type": "Feature",
  "properties": {
    "gn:admin1_code":"27",
    "gn:asciiname":"Dolenja Ravan",
    "gn:country_code":"SI",
    "gn:dem":633,
    "gn:feature_class":"P",
    "gn:feature_code":"PPL",
    "gn:name":"Dolenja Ravan",
    "gn:population":14,
    "gn:timezone":"Europe/Ljubljana",
    "iso:country":"SI",
    "name:bos_x_preferred":[
        "Dolenja Ravan"
    ],
    "name:hrv_x_preferred":[
        "Dolenja Ravan"
    ],
    "name:nld_x_preferred":[
        "Dolenja Ravan"
    ],
    "name:pol_x_preferred":[
        "Dolenja Ravan"
    ],
    "name:ron_x_preferred":[
        "Dolenja Ravan"
    ],
    "name:slv_x_preferred":[
        "Dolenja Ravan"
    ],
    "name:ukr_x_preferred":[
        "\u0414\u043e\u043b\u0435\u043d\u044f \u0420\u0430\u0432\u0430\u043d"
    ],
    "name:und_x_variant":[
        "Dolenji Ravni",
        "Dolenja Ravan"
    ],
    "wof:name":"Dolenja Ravan",
    "wof:placetype":"locality",
    "wof:population":14
},
  "geometry": {"coordinates":[14.14274,46.15013],"type":"Point"}
}