{
  "type": "Feature",
  "properties": {
    "gn:admin1_code":"H6",
    "gn:asciiname":"Podhruska",
    "gn:country_code":"SI",
    "gn:dem":424,
    "gn:feature_class":"P",
    "gn:feature_code":"PPL",
    "gn:name":"Podhru\u0161ka",
    "gn:population":62,
    "gn:timezone":"Europe/Ljubljana",
    "iso:country":"SI",
    "name:bos_x_preferred":[
        "Podhru\u0161ka"
    ],
    "name:pol_x_preferred":[
        "Podhru\u0161ka"
    ],
    "name:ron_x_preferred":[
        "Podhru\u0161ka"
    ],
    "name:slv_x_preferred":[
        "Podhru\u0161ka"
    ],
    "name:ukr_x_preferred":[
        "\u041f\u043e\u0434\u0445\u0440\u0443\u0448\u043a\u0430"
    ],
    "name:und_x_variant":[
        "Podhru\u0161ka"
    ],
    "wof:name":"Podhruska",
    "wof:placetype":"locality",
    "wof:population":62
},
  "geometry": {"coordinates":[14.67085,46.2243],"type":"Point"}
}