{
  "type": "Feature",
  "properties": {
    "gn:admin1_code":"G9",
    "gn:asciiname":"Skorba",
    "gn:country_code":"SI",
    "gn:dem":227,
    "gn:feature_class":"P",
    "gn:feature_code":"PPL",
    "gn:name":"Skorba",
    "gn:population":364,
    "gn:timezone":"Europe/Ljubljana",
    "iso:country":"SI",
    "name:bos_x_preferred":[
        "Skorba"
    ],
    "name:ceb_x_preferred":[
        "Skorba"
    ],
    "name:nld_x_preferred":[
        "Skorba"
    ],
    "name:pol_x_preferred":[
        "Skorba"
    ],
    "name:ron_x_preferred":[
        "Skorba"
    ],
    "name:slv_x_preferred":[
        "Skorba"
    ],
    "name:srp_x_preferred":[
        "\u0421\u043a\u043e\u0440\u0431\u0430"
    ],
    "name:ukr_x_preferred":[
        "\u0421\u043a\u043e\u0440\u0431\u0430"
    ],
    "wof:name":"Skorba",
    "wof:placetype":"locality",
    "wof:population":364
},
  "geometry": {"coordinates":[15.83333,46.41667],"type":"Point"}
}