{
  "type": "Feature",
  "properties": {
    "gn:admin1_code":"B4",
    "gn:asciiname":"Ledeca Vas",
    "gn:country_code":"SI",
    "gn:dem":173,
    "gn:feature_class":"P",
    "gn:feature_code":"PPL",
    "gn:name":"Lede\u010da Vas",
    "gn:population":85,
    "gn:timezone":"Europe/Ljubljana",
    "iso:country":"SI",
    "name:und_x_variant":[
        "Lede\u010da Vas"
    ],
    "wof:name":"Ledeca Vas",
    "wof:placetype":"locality",
    "wof:population":85
},
  "geometry": {"coordinates":[15.36256,45.84491],"type":"Point"}
}