{
  "type": "Feature",
  "properties": {
    "gn:admin1_code":"B8",
    "gn:asciiname":"Gabrnik",
    "gn:country_code":"SI",
    "gn:dem":259,
    "gn:feature_class":"P",
    "gn:feature_code":"PPL",
    "gn:name":"Gabrnik",
    "gn:population":12,
    "gn:timezone":"Europe/Ljubljana",
    "iso:country":"SI",
    "name:slv_x_historical":[
        "Gabernik"
    ],
    "name:slv_x_preferred":[
        "Gabernik"
    ],
    "wof:name":"Gabrnik",
    "wof:placetype":"locality",
    "wof:population":12
},
  "geometry": {"coordinates":[15.26868,45.93117],"type":"Point"}
}