{
  "type": "Feature",
  "properties": {
    "gn:admin1_code":"B8",
    "gn:asciiname":"Gabrnik",
    "gn:country_code":"SI",
    "gn:dem":259,
    "gn:feature_class":"P",
    "gn:feature_code":"PPL",
    "gn:name":"Gabrnik",
    "gn:population":12,
    "gn:timezone":"Europe/Ljubljana",
    "iso:country":"SI",
    "name:bos_x_preferred":[
        "Gabrnik"
    ],
    "name:hrv_x_preferred":[
        "Gabrnik"
    ],
    "name:nld_x_preferred":[
        "Gabrnik"
    ],
    "name:pol_x_preferred":[
        "Gabrnik"
    ],
    "name:ron_x_preferred":[
        "Gabrnik"
    ],
    "name:slv_x_historical":[
        "Gabernik"
    ],
    "name:slv_x_preferred":[
        "Gabernik"
    ],
    "name:slv_x_variant":[
        "Gabrnik"
    ],
    "name:ukr_x_preferred":[
        "\u0413\u0430\u0431\u0440\u043d\u0438\u043a"
    ],
    "wof:name":"Gabrnik",
    "wof:placetype":"locality",
    "wof:population":12
},
  "geometry": {"coordinates":[15.26868,45.93117],"type":"Point"}
}