{
  "type": "Feature",
  "properties": {
    "gn:admin1_code":"H6",
    "gn:asciiname":"Zgornje Palovce",
    "gn:country_code":"SI",
    "gn:dem":691,
    "gn:feature_class":"P",
    "gn:feature_code":"PPL",
    "gn:name":"Zgornje Palov\u010de",
    "gn:population":40,
    "gn:timezone":"Europe/Ljubljana",
    "iso:country":"SI",
    "name:bos_x_preferred":[
        "Zgornje Palov\u010de"
    ],
    "name:pol_x_preferred":[
        "Zgornje Palov\u010de"
    ],
    "name:ron_x_preferred":[
        "Zgornje Palov\u010de"
    ],
    "name:slv_x_preferred":[
        "Zgornje Palov\u010de"
    ],
    "name:ukr_x_preferred":[
        "\u0417\u0433\u043e\u0440\u043d\u0454 \u041f\u0430\u043b\u043e\u0432\u0447\u0435"
    ],
    "name:und_x_variant":[
        "Zgornje Palovi\u010de",
        "Zgornje Palov\u010de"
    ],
    "wof:name":"Zgornje Palovce",
    "wof:placetype":"locality",
    "wof:population":40
},
  "geometry": {"coordinates":[14.64756,46.21328],"type":"Point"}
}