{
  "type": "Feature",
  "properties": {
    "gn:admin1_code":"J9",
    "gn:asciiname":"Dragonja",
    "gn:country_code":"SI",
    "gn:dem":72,
    "gn:feature_class":"P",
    "gn:feature_code":"PPL",
    "gn:name":"Dragonja",
    "gn:population":383,
    "gn:timezone":"Europe/Ljubljana",
    "iso:country":"SI",
    "name:bos_x_preferred":[
        "Dragonja"
    ],
    "name:bul_x_preferred":[
        "\u0414\u0440\u0430\u0433\u043e\u043d\u044f"
    ],
    "name:ceb_x_preferred":[
        "Dragonja"
    ],
    "name:ita_x_preferred":[
        "Dragogna"
    ],
    "name:pol_x_preferred":[
        "Dragonja"
    ],
    "name:ron_x_preferred":[
        "Dragonja"
    ],
    "name:slv_x_preferred":[
        "Dragonja"
    ],
    "name:ukr_x_preferred":[
        "\u0414\u0440\u0430\u0433\u043e\u043d\u044f"
    ],
    "name:und_x_variant":[
        "Feran"
    ],
    "wof:name":"Dragonja",
    "wof:placetype":"locality",
    "wof:population":383
},
  "geometry": {"coordinates":[13.66,45.46056],"type":"Point"}
}