{
  "type": "Feature",
  "properties": {
    "gn:admin1_code":"19",
    "gn:asciiname":"Otosce",
    "gn:country_code":"SI",
    "gn:dem":361,
    "gn:feature_class":"P",
    "gn:feature_code":"PPL",
    "gn:name":"Oto\u0161\u010de",
    "gn:population":21,
    "gn:timezone":"Europe/Ljubljana",
    "iso:country":"SI",
    "name:bos_x_preferred":[
        "Oto\u0161\u010de"
    ],
    "name:ita_x_preferred":[
        "Vitozza"
    ],
    "name:nld_x_preferred":[
        "Oto\u0161\u010de"
    ],
    "name:pol_x_preferred":[
        "Oto\u0161\u010de"
    ],
    "name:ron_x_preferred":[
        "Oto\u0161\u010de"
    ],
    "name:slv_x_preferred":[
        "Oto\u0161\u010de"
    ],
    "name:ukr_x_preferred":[
        "\u041e\u0442\u043e\u0449\u0435"
    ],
    "name:und_x_variant":[
        "Vrtov\u0161\u010de",
        "Oto\u0161\u010de"
    ],
    "wof:name":"Otosce",
    "wof:placetype":"locality",
    "wof:population":21
},
  "geometry": {"coordinates":[14.02833,45.76056],"type":"Point"}
}