{
  "type": "Feature",
  "properties": {
    "gn:admin1_code":"D5",
    "gn:asciiname":"Lom pod Storzicem",
    "gn:country_code":"SI",
    "gn:dem":718,
    "gn:feature_class":"P",
    "gn:feature_code":"PPL",
    "gn:name":"Lom pod Storzicem",
    "gn:population":346,
    "gn:timezone":"Europe/Ljubljana",
    "iso:country":"SI",
    "name:und_x_variant":[
        "Lom",
        "Lom pod Stor\u017ei\u010dem"
    ],
    "wof:name":"Lom pod Storzicem",
    "wof:placetype":"locality",
    "wof:population":346
},
  "geometry": {"coordinates":[14.33639,46.36694],"type":"Point"}
}