{
  "type": "Feature",
  "properties": {
    "gn:admin1_code":"L1",
    "gn:asciiname":"Blate",
    "gn:country_code":"SI",
    "gn:dem":487,
    "gn:feature_class":"P",
    "gn:feature_code":"PPL",
    "gn:name":"Blate",
    "gn:population":61,
    "gn:timezone":"Europe/Ljubljana",
    "iso:country":"SI",
    "name:bos_x_preferred":[
        "Blate"
    ],
    "name:nld_x_preferred":[
        "Blate"
    ],
    "name:pol_x_preferred":[
        "Blate"
    ],
    "name:ron_x_preferred":[
        "Blate"
    ],
    "name:slv_x_preferred":[
        "Blate"
    ],
    "name:ukr_x_preferred":[
        "\u0411\u043b\u0430\u0442\u0435"
    ],
    "name:und_x_variant":[
        "Blata",
        "Blate"
    ],
    "wof:name":"Blate",
    "wof:placetype":"locality",
    "wof:population":61
},
  "geometry": {"coordinates":[14.7441,45.69585],"type":"Point"}
}