{
  "type": "Feature",
  "properties": {
    "gn:admin1_code":"I9",
    "gn:asciiname":"Mlinari",
    "gn:country_code":"SI",
    "gn:dem":667,
    "gn:feature_class":"P",
    "gn:feature_code":"PPL",
    "gn:name":"Mlinari",
    "gn:population":0,
    "gn:timezone":"Europe/Ljubljana",
    "iso:country":"SI",
    "wof:name":"Mlinari",
    "wof:placetype":"locality"
},
  "geometry": {"coordinates":[14.69889,46.30667],"type":"Point"}
}