{
  "type": "Feature",
  "properties": {
    "gn:admin1_code":"L7",
    "gn:asciiname":"Unise",
    "gn:country_code":"SI",
    "gn:dem":330,
    "gn:feature_class":"P",
    "gn:feature_code":"PPL",
    "gn:name":"Uni\u0161e",
    "gn:population":41,
    "gn:timezone":"Europe/Ljubljana",
    "iso:country":"SI",
    "name:und_x_variant":[
        "Uni\u0161e"
    ],
    "wof:name":"Unise",
    "wof:placetype":"locality",
    "wof:population":41
},
  "geometry": {"coordinates":[15.43816,46.24393],"type":"Point"}
}