{
  "type": "Feature",
  "properties": {
    "gn:admin1_code":"L7",
    "gn:asciiname":"Unise",
    "gn:country_code":"SI",
    "gn:dem":330,
    "gn:feature_class":"P",
    "gn:feature_code":"PPL",
    "gn:name":"Uni\u0161e",
    "gn:population":41,
    "gn:timezone":"Europe/Ljubljana",
    "iso:country":"SI",
    "name:bos_x_preferred":[
        "Uni\u0161e"
    ],
    "name:hrv_x_preferred":[
        "Uni\u0161e"
    ],
    "name:nld_x_preferred":[
        "Uni\u0161e"
    ],
    "name:pol_x_preferred":[
        "Uni\u0161e"
    ],
    "name:ron_x_preferred":[
        "Uni\u0161e"
    ],
    "name:slv_x_preferred":[
        "Uni\u0161e"
    ],
    "name:ukr_x_preferred":[
        "\u0423\u043d\u0438\u0448\u0435"
    ],
    "wof:name":"Unise",
    "wof:placetype":"locality",
    "wof:population":41
},
  "geometry": {"coordinates":[15.43816,46.24393],"type":"Point"}
}