{
  "type": "Feature",
  "properties": {
    "gn:admin1_code":"29",
    "gn:asciiname":"Stavesinci",
    "gn:country_code":"SI",
    "gn:dem":209,
    "gn:feature_class":"P",
    "gn:feature_code":"PPL",
    "gn:name":"Stave\u0161inci",
    "gn:population":80,
    "gn:timezone":"Europe/Ljubljana",
    "iso:country":"SI",
    "name:bos_x_preferred":[
        "Stave\u0161inci"
    ],
    "name:hrv_x_preferred":[
        "Stave\u0161inci"
    ],
    "name:nld_x_preferred":[
        "Stave\u0161inci"
    ],
    "name:pol_x_preferred":[
        "Stave\u0161inci"
    ],
    "name:ron_x_preferred":[
        "Stave\u0161inci"
    ],
    "name:slv_x_preferred":[
        "Stave\u0161inci"
    ],
    "name:ukr_x_preferred":[
        "\u0421\u0442\u0430\u0432\u0435\u0448\u0438\u043d\u0446\u0456"
    ],
    "name:und_x_variant":[
        "Stave\u0161inci"
    ],
    "wof:name":"Stavesinci",
    "wof:placetype":"locality",
    "wof:population":80
},
  "geometry": {"coordinates":[15.98296,46.60562],"type":"Point"}
}