{
  "type": "Feature",
  "properties": {
    "gn:admin1_code":"40",
    "gn:asciiname":"Baredi",
    "gn:country_code":"SI",
    "gn:dem":141,
    "gn:feature_class":"P",
    "gn:feature_code":"PPL",
    "gn:name":"Baredi",
    "gn:population":145,
    "gn:timezone":"Europe/Ljubljana",
    "iso:country":"SI",
    "name:bos_x_preferred":[
        "Baredi"
    ],
    "name:ceb_x_preferred":[
        "Baredi"
    ],
    "name:ita_x_preferred":[
        "Bar\u00e9"
    ],
    "name:pol_x_preferred":[
        "Baredi"
    ],
    "name:ron_x_preferred":[
        "Baredi"
    ],
    "name:slv_x_preferred":[
        "Baredi"
    ],
    "name:ukr_x_preferred":[
        "\u0411\u0430\u0440\u0435\u0434\u0438"
    ],
    "wof:name":"Baredi",
    "wof:placetype":"locality",
    "wof:population":145
},
  "geometry": {"coordinates":[13.67915,45.51597],"type":"Point"}
}