{
  "type": "Feature",
  "properties": {
    "gn:admin1_code":"D2",
    "gn:asciiname":"Volce",
    "gn:cc2":"SI",
    "gn:country_code":"SI",
    "gn:dem":201,
    "gn:feature_class":"P",
    "gn:feature_code":"PPL",
    "gn:name":"Vol\u010de",
    "gn:population":588,
    "gn:timezone":"Europe/Ljubljana",
    "iso:country":"SI",
    "name:bos_x_preferred":[
        "Vol\u010de"
    ],
    "name:bul_x_preferred":[
        "\u0412\u043e\u043b\u0447\u0435"
    ],
    "name:ceb_x_preferred":[
        "Vol\u010de"
    ],
    "name:ita_x_preferred":[
        "Volzana"
    ],
    "name:nld_x_preferred":[
        "Vol\u010de"
    ],
    "name:pol_x_preferred":[
        "Vol\u010de"
    ],
    "name:ron_x_preferred":[
        "Vol\u010de"
    ],
    "name:slv_x_preferred":[
        "Vol\u010de"
    ],
    "name:ukr_x_preferred":[
        "\u0412\u043e\u043b\u0447\u0435"
    ],
    "wof:name":"Volce",
    "wof:placetype":"locality",
    "wof:population":588
},
  "geometry": {"coordinates":[13.70785,46.1754],"type":"Point"}
}