{
  "type": "Feature",
  "properties": {
    "gn:gn_country":"SI",
    "gn:gn_fcode":"PPL",
    "gn:gn_pop":0,
    "gn:population":178,
    "iso:country":"SI",
    "name:unk_x_variant":[
        "Antignano d\u2019Istria"
    ],
    "qs_pg:aaroncc":"SI",
    "qs_pg:gn_country":"SI",
    "qs_pg:gn_fcode":"PPL",
    "qs_pg:gn_pop":0,
    "qs_pg:name":"Tinjan",
    "qs_pg:name_adm0":"Slovenija",
    "qs_pg:name_adm1":"Koper",
    "qs_pg:photos":23,
    "qs_pg:photos_1k":5,
    "qs_pg:photos_9k":1,
    "qs_pg:photos_9r":1,
    "qs_pg:photos_all":23,
    "qs_pg:photos_sr":1,
    "qs_pg:pop_sr":0,
    "qs_pg:qs_pg_placetype":"locality",
    "qs_pg:qs_pg_placetype_gp":"Town",
    "qs_pg:woe_adm0":23424945,
    "woe:adm0_id":23424945,
    "woe:name_adm0":"Slovenija",
    "woe:name_adm1":"Koper",
    "woe:placetype":"Town",
    "wof:name":"Tinjan",
    "wof:placetype":"locality",
    "wof:population":178
},
  "geometry": {"coordinates":[13.835,45.56222],"type":"Point"}
}