{
  "type": "Feature",
  "properties": {
    "gn:admin1_code":"B9",
    "gn:asciiname":"Trata",
    "gn:country_code":"SI",
    "gn:dem":359,
    "gn:feature_class":"P",
    "gn:feature_code":"PPL",
    "gn:name":"Trata",
    "gn:population":206,
    "gn:timezone":"Europe/Ljubljana",
    "iso:country":"SI",
    "name:bos_x_preferred":[
        "Trata"
    ],
    "name:ceb_x_preferred":[
        "Trata"
    ],
    "name:nld_x_preferred":[
        "Trata"
    ],
    "name:pol_x_preferred":[
        "Trata"
    ],
    "name:ron_x_preferred":[
        "Trata"
    ],
    "name:slv_x_preferred":[
        "Trata"
    ],
    "name:ukr_x_preferred":[
        "\u0422\u0440\u0430\u0442\u0430"
    ],
    "wof:name":"Trata",
    "wof:placetype":"locality",
    "wof:population":206
},
  "geometry": {"coordinates":[14.34573,46.17729],"type":"Point"}
}