{
  "type": "Feature",
  "properties": {
    "gn:admin1_code":"91",
    "gn:asciiname":"Parje",
    "gn:country_code":"SI",
    "gn:dem":543,
    "gn:feature_class":"P",
    "gn:feature_code":"PPL",
    "gn:name":"Parje",
    "gn:population":110,
    "gn:timezone":"Europe/Ljubljana",
    "iso:country":"SI",
    "name:bos_x_preferred":[
        "Parje"
    ],
    "name:ceb_x_preferred":[
        "Parje"
    ],
    "name:hrv_x_preferred":[
        "Parje"
    ],
    "name:nld_x_preferred":[
        "Parje"
    ],
    "name:pol_x_preferred":[
        "Parje"
    ],
    "name:ron_x_preferred":[
        "Parje"
    ],
    "name:slv_x_preferred":[
        "Parje"
    ],
    "name:ukr_x_preferred":[
        "\u041f\u0430\u0440\u0454"
    ],
    "name:und_x_variant":[
        "Parie"
    ],
    "wof:name":"Parje",
    "wof:placetype":"locality",
    "wof:population":110
},
  "geometry": {"coordinates":[14.21717,45.66259],"type":"Point"}
}