{
  "type": "Feature",
  "properties": {
    "gn:admin1_code":"L4",
    "gn:asciiname":"Salovci",
    "gn:country_code":"SI",
    "gn:dem":221,
    "gn:feature_class":"P",
    "gn:feature_code":"PPL",
    "gn:name":"\u0160alovci",
    "gn:population":191,
    "gn:timezone":"Europe/Ljubljana",
    "iso:country":"SI",
    "name:und_x_variant":[
        "\u0160alovci"
    ],
    "wof:name":"Salovci",
    "wof:placetype":"locality",
    "wof:population":191
},
  "geometry": {"coordinates":[16.22583,46.425],"type":"Point"}
}