{
  "type": "Feature",
  "properties": {
    "gn:admin1_code":"L4",
    "gn:asciiname":"Salovci",
    "gn:country_code":"SI",
    "gn:dem":221,
    "gn:feature_class":"P",
    "gn:feature_code":"PPL",
    "gn:name":"\u0160alovci",
    "gn:population":191,
    "gn:timezone":"Europe/Ljubljana",
    "iso:country":"SI",
    "name:bos_x_preferred":[
        "\u0160alovci"
    ],
    "name:ceb_x_preferred":[
        "\u0160alovci"
    ],
    "name:nld_x_preferred":[
        "\u0160alovci"
    ],
    "name:pol_x_preferred":[
        "\u0160alovci"
    ],
    "name:ron_x_preferred":[
        "\u0160alovci"
    ],
    "name:slv_x_preferred":[
        "\u0160alovci"
    ],
    "name:ukr_x_preferred":[
        "\u0428\u0430\u043b\u043e\u0432\u0446\u0456"
    ],
    "wof:name":"Salovci",
    "wof:placetype":"locality",
    "wof:population":191
},
  "geometry": {"coordinates":[16.22583,46.425],"type":"Point"}
}