{
  "type": "Feature",
  "properties": {
    "gn:admin1_code":"O3",
    "gn:asciiname":"Dobe",
    "gn:country_code":"SI",
    "gn:dem":172,
    "gn:feature_class":"P",
    "gn:feature_code":"PPL",
    "gn:name":"Dobe",
    "gn:population":96,
    "gn:timezone":"Europe/Ljubljana",
    "iso:country":"SI",
    "name:bos_x_preferred":[
        "Dobe"
    ],
    "name:ita_x_preferred":[
        "Dobe"
    ],
    "name:nld_x_preferred":[
        "Dobe"
    ],
    "name:pol_x_preferred":[
        "Dobe"
    ],
    "name:ron_x_preferred":[
        "Dobe"
    ],
    "name:slv_x_preferred":[
        "Dobe"
    ],
    "name:ukr_x_preferred":[
        "\u0414\u043e\u0431\u0435"
    ],
    "wof:name":"Dobe",
    "wof:placetype":"locality",
    "wof:population":96
},
  "geometry": {"coordinates":[15.40167,45.84741],"type":"Point"}
}