{
  "type": "Feature",
  "properties": {
    "gn:admin1_code":"O3",
    "gn:asciiname":"Dobe",
    "gn:country_code":"SI",
    "gn:dem":172,
    "gn:feature_class":"P",
    "gn:feature_code":"PPL",
    "gn:name":"Dobe",
    "gn:population":96,
    "gn:timezone":"Europe/Ljubljana",
    "iso:country":"SI",
    "wof:name":"Dobe",
    "wof:placetype":"locality",
    "wof:population":96
},
  "geometry": {"coordinates":[15.40167,45.84741],"type":"Point"}
}