{
  "type": "Feature",
  "properties": {
    "gn:admin1_code":"D4",
    "gn:asciiname":"Zelezno",
    "gn:country_code":"SI",
    "gn:dem":282,
    "gn:feature_class":"P",
    "gn:feature_code":"PPL",
    "gn:name":"\u017delezno",
    "gn:population":51,
    "gn:timezone":"Europe/Ljubljana",
    "iso:country":"SI",
    "name:und_x_variant":[
        "\u017delezno"
    ],
    "wof:name":"Zelezno",
    "wof:placetype":"locality",
    "wof:population":51
},
  "geometry": {"coordinates":[14.96306,45.88083],"type":"Point"}
}