{
  "type": "Feature",
  "properties": {
    "gn:admin1_code":"89",
    "gn:asciiname":"Hrenca",
    "gn:country_code":"SI",
    "gn:dem":377,
    "gn:feature_class":"P",
    "gn:feature_code":"PPL",
    "gn:name":"Hrenca",
    "gn:population":144,
    "gn:timezone":"Europe/Ljubljana",
    "iso:country":"SI",
    "name:bos_x_preferred":[
        "Hrenca"
    ],
    "name:bul_x_preferred":[
        "\u0425\u0440\u0435\u043d\u0446\u0430"
    ],
    "name:ceb_x_preferred":[
        "Hrenca"
    ],
    "name:nld_x_preferred":[
        "Hrenca"
    ],
    "name:pol_x_preferred":[
        "Hrenca"
    ],
    "name:ron_x_preferred":[
        "Hrenca"
    ],
    "name:slv_x_preferred":[
        "Hrenca"
    ],
    "name:ukr_x_preferred":[
        "\u0425\u0440\u0435\u043d\u0446\u0430"
    ],
    "wof:name":"Hrenca",
    "wof:placetype":"locality",
    "wof:population":144
},
  "geometry": {"coordinates":[15.71667,46.56667],"type":"Point"}
}