{
  "type": "Feature",
  "properties": {
    "gn:admin1_code":"B6",
    "gn:asciiname":"Zgornje Vodale",
    "gn:country_code":"SI",
    "gn:dem":443,
    "gn:feature_class":"P",
    "gn:feature_code":"PPL",
    "gn:name":"Zgornje Vodale",
    "gn:population":35,
    "gn:timezone":"Europe/Ljubljana",
    "iso:country":"SI",
    "name:slv_x_historical":[
        "Gorenje Vodale"
    ],
    "name:slv_x_preferred":[
        "Gorenje Vodale"
    ],
    "wof:name":"Zgornje Vodale",
    "wof:placetype":"locality",
    "wof:population":35
},
  "geometry": {"coordinates":[15.23329,45.96127],"type":"Point"}
}