{
  "type": "Feature",
  "properties": {
    "gn:admin1_code":"B6",
    "gn:asciiname":"Zgornje Vodale",
    "gn:country_code":"SI",
    "gn:dem":443,
    "gn:feature_class":"P",
    "gn:feature_code":"PPL",
    "gn:name":"Zgornje Vodale",
    "gn:population":35,
    "gn:timezone":"Europe/Ljubljana",
    "iso:country":"SI",
    "name:bos_x_preferred":[
        "Zgornje Vodale"
    ],
    "name:nld_x_preferred":[
        "Zgornje Vodale"
    ],
    "name:pol_x_preferred":[
        "Zgornje Vodale"
    ],
    "name:ron_x_preferred":[
        "Zgornje Vodale"
    ],
    "name:slv_x_historical":[
        "Gorenje Vodale"
    ],
    "name:slv_x_preferred":[
        "Gorenje Vodale"
    ],
    "name:slv_x_variant":[
        "Zgornje Vodale"
    ],
    "name:ukr_x_preferred":[
        "\u0417\u0433\u043e\u0440\u043d\u0454 \u0412\u043e\u0434\u0430\u043b\u0435"
    ],
    "wof:name":"Zgornje Vodale",
    "wof:placetype":"locality",
    "wof:population":35
},
  "geometry": {"coordinates":[15.23329,45.96127],"type":"Point"}
}