{
  "type": "Feature",
  "properties": {
    "gn:gn_country":"SI",
    "gn:gn_fcode":"PPLA",
    "gn:gn_pop":4497,
    "gn:population":4503,
    "iso:country":"SI",
    "name:cat_x_preferred":[
        "Ru\u0161e"
    ],
    "name:deu_x_historical":[
        "Maria Rast"
    ],
    "name:deu_x_preferred":[
        "Maria Rast"
    ],
    "name:eng_x_preferred":[
        "Ru\u0161e"
    ],
    "name:ita_x_preferred":[
        "Ru\u0161e"
    ],
    "name:jpn_x_preferred":[
        "\u30eb\u30b7\u30a7"
    ],
    "name:nld_x_preferred":[
        "Ru\u0161e"
    ],
    "name:ron_x_preferred":[
        "Ru\u0161e"
    ],
    "name:slv_x_preferred":[
        "Ob\u010dina Ru\u0161e"
    ],
    "name:unk_x_variant":[
        "Ro\u0161e"
    ],
    "qs_pg:aaroncc":"SI",
    "qs_pg:gn_country":"SI",
    "qs_pg:gn_fcode":"PPLA",
    "qs_pg:gn_pop":4497,
    "qs_pg:name":"Ru\u0161e",
    "qs_pg:photos_9r":0,
    "qs_pg:photos_sr":0,
    "qs_pg:pop_sr":4,
    "qs_pg:qs_pg_placetype":"locality",
    "wof:name":"Ru\u0161e",
    "wof:placetype":"locality",
    "wof:population":4503
},
  "geometry": {"coordinates":[15.51583,46.53944],"type":"Point"}
}