{
  "type": "Feature",
  "properties": {
    "gn:country":"SI",
    "gn:fcode":"PPLA",
    "gn:population":4497,
    "iso:country":"SI",
    "name:ara_x_preferred":[
        "\u0631\u0648\u0634\u0647"
    ],
    "name:bos_x_preferred":[
        "Ru\u0161e"
    ],
    "name:cat_x_preferred":[
        "Ru\u0161e"
    ],
    "name:ceb_x_preferred":[
        "Ru\u0161e"
    ],
    "name:deu_x_historical":[
        "Maria Rast"
    ],
    "name:deu_x_preferred":[
        "Maria Rast"
    ],
    "name:deu_x_variant":[
        "Ru\u0161e"
    ],
    "name:eng_x_preferred":[
        "Ru\u0161e"
    ],
    "name:fas_x_preferred":[
        "\u0631\u0648\u0634\u0647"
    ],
    "name:fra_x_preferred":[
        "Ru\u0161e"
    ],
    "name:hrv_x_preferred":[
        "Ru\u0161e"
    ],
    "name:ita_x_preferred":[
        "Ru\u0161e"
    ],
    "name:jpn_x_preferred":[
        "\u30eb\u30b7\u30a7"
    ],
    "name:lit_x_preferred":[
        "Ru\u0161\u0117s"
    ],
    "name:nld_x_preferred":[
        "Ru\u0161e"
    ],
    "name:pol_x_preferred":[
        "Ru\u0161e"
    ],
    "name:por_x_preferred":[
        "Ru\u0161e"
    ],
    "name:ron_x_preferred":[
        "Ru\u0161e"
    ],
    "name:rus_x_preferred":[
        "\u0420\u0443\u0448\u0435"
    ],
    "name:slk_x_preferred":[
        "Ru\u0161e"
    ],
    "name:slv_x_preferred":[
        "Ob\u010dina Ru\u0161e"
    ],
    "name:slv_x_variant":[
        "Ru\u0161e"
    ],
    "name:spa_x_preferred":[
        "Ru\u0161e"
    ],
    "name:srp_x_preferred":[
        "\u0420\u0443\u0448\u0435"
    ],
    "name:ukr_x_preferred":[
        "\u0420\u0443\u0448\u0435"
    ],
    "name:und_x_variant":[
        "Ro\u0161e"
    ],
    "name:vie_x_preferred":[
        "Ru\u0161e"
    ],
    "qs_pg:aaroncc":"SI",
    "qs_pg:gn_country":"SI",
    "qs_pg:gn_fcode":"PPLA",
    "qs_pg:gn_pop":4497,
    "qs_pg:name":"Ru\u0161e",
    "qs_pg:photos_9r":0,
    "qs_pg:photos_sr":0,
    "qs_pg:pop_sr":4,
    "qs_pg:qs_pg_placetype":"locality",
    "wof:name":"Ru\u0161e",
    "wof:placetype":"locality",
    "wof:population":4503
},
  "geometry": {"coordinates":[15.51583,46.53944],"type":"Point"}
}