{
  "type": "Feature",
  "properties": {
    "gn:admin1_code":"I5",
    "gn:asciiname":"Mala Stanga",
    "gn:country_code":"SI",
    "gn:dem":586,
    "gn:feature_class":"P",
    "gn:feature_code":"PPL",
    "gn:name":"Mala \u0160tanga",
    "gn:population":33,
    "gn:timezone":"Europe/Ljubljana",
    "iso:country":"SI",
    "name:und_x_variant":[
        "Mala \u0160tanga"
    ],
    "wof:name":"Mala Stanga",
    "wof:placetype":"locality",
    "wof:population":33
},
  "geometry": {"coordinates":[14.76,46.06167],"type":"Point"}
}