{
  "type": "Feature",
  "properties": {
    "gn:admin1_code":"N8",
    "gn:asciiname":"Vinkov Vrh",
    "gn:country_code":"SI",
    "gn:dem":371,
    "gn:feature_class":"P",
    "gn:feature_code":"PPL",
    "gn:name":"Vinkov Vrh",
    "gn:population":43,
    "gn:timezone":"Europe/Ljubljana",
    "iso:country":"SI",
    "name:bos_x_preferred":[
        "Vinkov Vrh"
    ],
    "name:bul_x_preferred":[
        "\u0412\u0438\u043d\u043a\u043e\u0432 \u0412\u0440\u044a\u0445"
    ],
    "name:hrv_x_preferred":[
        "Vinkov Vrh"
    ],
    "name:nld_x_preferred":[
        "Vinkov Vrh"
    ],
    "name:pol_x_preferred":[
        "Vinkov Vrh"
    ],
    "name:ron_x_preferred":[
        "Vinkov Vrh"
    ],
    "name:slv_x_preferred":[
        "Vinkov Vrh"
    ],
    "name:ukr_x_preferred":[
        "\u0412\u0438\u043d\u043a\u043e\u0432 \u0412\u0440\u0445"
    ],
    "wof:name":"Vinkov Vrh",
    "wof:placetype":"locality",
    "wof:population":43
},
  "geometry": {"coordinates":[14.98384,45.80644],"type":"Point"}
}