{
  "type": "Feature",
  "properties": {
    "gn:admin1_code":"17",
    "gn:asciiname":"Zapudje",
    "gn:country_code":"SI",
    "gn:dem":546,
    "gn:feature_class":"P",
    "gn:feature_code":"PPL",
    "gn:name":"Zapudje",
    "gn:population":71,
    "gn:timezone":"Europe/Ljubljana",
    "iso:country":"SI",
    "name:bos_x_preferred":[
        "Zapudje"
    ],
    "name:hrv_x_preferred":[
        "Zapudje"
    ],
    "name:nld_x_preferred":[
        "Zapudje"
    ],
    "name:pol_x_preferred":[
        "Zapudje"
    ],
    "name:ron_x_preferred":[
        "Zapudje"
    ],
    "name:slv_x_preferred":[
        "Zapudje"
    ],
    "name:ukr_x_preferred":[
        "\u0417\u0430\u043f\u0443\u0434\u0454"
    ],
    "wof:name":"Zapudje",
    "wof:placetype":"locality",
    "wof:population":71
},
  "geometry": {"coordinates":[15.15542,45.49436],"type":"Point"}
}