{
  "type": "Feature",
  "properties": {
    "gn:admin1_code":"17",
    "gn:asciiname":"Zapudje",
    "gn:country_code":"SI",
    "gn:dem":546,
    "gn:feature_class":"P",
    "gn:feature_code":"PPL",
    "gn:name":"Zapudje",
    "gn:population":71,
    "gn:timezone":"Europe/Ljubljana",
    "iso:country":"SI",
    "wof:name":"Zapudje",
    "wof:placetype":"locality",
    "wof:population":71
},
  "geometry": {"coordinates":[15.15542,45.49436],"type":"Point"}
}