{
  "type": "Feature",
  "properties": {
    "gn:admin1_code":"A1",
    "gn:asciiname":"Melanjski Vrh",
    "gn:country_code":"SI",
    "gn:dem":265,
    "gn:feature_class":"P",
    "gn:feature_code":"PPL",
    "gn:name":"Melanjski Vrh",
    "gn:population":25,
    "gn:timezone":"Europe/Ljubljana",
    "iso:country":"SI",
    "wof:name":"Melanjski Vrh",
    "wof:placetype":"locality",
    "wof:population":25
},
  "geometry": {"coordinates":[16.01193,46.62029],"type":"Point"}
}