{
  "type": "Feature",
  "properties": {
    "gn:admin1_code":"98",
    "gn:asciiname":"Planica",
    "gn:country_code":"SI",
    "gn:dem":712,
    "gn:feature_class":"P",
    "gn:feature_code":"PPL",
    "gn:name":"Planica",
    "gn:population":136,
    "gn:timezone":"Europe/Ljubljana",
    "iso:country":"SI",
    "name:bos_x_preferred":[
        "Planica"
    ],
    "name:ceb_x_preferred":[
        "Planica"
    ],
    "name:nld_x_preferred":[
        "Planica"
    ],
    "name:pol_x_preferred":[
        "Planica"
    ],
    "name:ron_x_preferred":[
        "Planica"
    ],
    "name:slv_x_preferred":[
        "Planica"
    ],
    "name:ukr_x_preferred":[
        "\u041f\u043b\u0430\u043d\u0438\u0446\u044f"
    ],
    "wof:name":"Planica",
    "wof:placetype":"locality",
    "wof:population":136
},
  "geometry": {"coordinates":[15.56919,46.47202],"type":"Point"}
}