{
  "type": "Feature",
  "properties": {
    "gn:admin1_code":"F9",
    "gn:asciiname":"Drbetinci",
    "gn:country_code":"SI",
    "gn:dem":286,
    "gn:feature_class":"P",
    "gn:feature_code":"PPL",
    "gn:name":"Drbetinci",
    "gn:population":233,
    "gn:timezone":"Europe/Ljubljana",
    "iso:country":"SI",
    "name:bos_x_preferred":[
        "Drbetinci"
    ],
    "name:bul_x_preferred":[
        "\u0414\u044a\u0440\u0431\u0435\u0442\u0438\u043d\u0446\u0438"
    ],
    "name:ceb_x_preferred":[
        "Drbetinci"
    ],
    "name:nld_x_preferred":[
        "Drbetinci"
    ],
    "name:pol_x_preferred":[
        "Drbetinci"
    ],
    "name:ron_x_preferred":[
        "Drbetinci"
    ],
    "name:slv_x_preferred":[
        "Drbetinci"
    ],
    "name:ukr_x_preferred":[
        "\u0414\u0440\u0431\u0435\u0442\u0438\u043d\u0446\u0456"
    ],
    "name:und_x_variant":[
        "Sveti Andraz",
        "Derbetici"
    ],
    "wof:name":"Drbetinci",
    "wof:placetype":"locality",
    "wof:population":233
},
  "geometry": {"coordinates":[15.93021,46.53503],"type":"Point"}
}