{
  "type": "Feature",
  "properties": {
    "gn:admin1_code":"F9",
    "gn:asciiname":"Drbetinci",
    "gn:country_code":"SI",
    "gn:dem":286,
    "gn:feature_class":"P",
    "gn:feature_code":"PPL",
    "gn:name":"Drbetinci",
    "gn:population":233,
    "gn:timezone":"Europe/Ljubljana",
    "iso:country":"SI",
    "name:und_x_variant":[
        "Sveti Andraz",
        "Derbetici",
        "Drbetinci"
    ],
    "wof:name":"Drbetinci",
    "wof:placetype":"locality",
    "wof:population":233
},
  "geometry": {"coordinates":[15.93021,46.53503],"type":"Point"}
}