{
  "type": "Feature",
  "properties": {
    "gn:admin1_code":"39",
    "gn:asciiname":"Metnaj",
    "gn:country_code":"SI",
    "gn:dem":594,
    "gn:feature_class":"P",
    "gn:feature_code":"PPL",
    "gn:name":"Metnaj",
    "gn:population":115,
    "gn:timezone":"Europe/Ljubljana",
    "iso:country":"SI",
    "name:bos_x_preferred":[
        "Metnaj"
    ],
    "name:ceb_x_preferred":[
        "Metnaj"
    ],
    "name:nld_x_preferred":[
        "Metnaj"
    ],
    "name:pol_x_preferred":[
        "Metnaj"
    ],
    "name:ron_x_preferred":[
        "Metnaj"
    ],
    "name:slv_x_preferred":[
        "Metnaj"
    ],
    "name:ukr_x_preferred":[
        "\u041c\u0435\u0442\u043d\u0430\u0439"
    ],
    "wof:name":"Metnaj",
    "wof:placetype":"locality",
    "wof:population":115
},
  "geometry": {"coordinates":[14.80139,45.98472],"type":"Point"}
}