{
  "type": "Feature",
  "properties": {
    "gn:admin1_code":"39",
    "gn:asciiname":"Metnaj",
    "gn:country_code":"SI",
    "gn:dem":594,
    "gn:feature_class":"P",
    "gn:feature_code":"PPL",
    "gn:name":"Metnaj",
    "gn:population":115,
    "gn:timezone":"Europe/Ljubljana",
    "iso:country":"SI",
    "wof:name":"Metnaj",
    "wof:placetype":"locality",
    "wof:population":115
},
  "geometry": {"coordinates":[14.80139,45.98472],"type":"Point"}
}