{
  "type": "Feature",
  "properties": {
    "gn:admin1_code":"64",
    "gn:asciiname":"Zibrse",
    "gn:country_code":"SI",
    "gn:dem":698,
    "gn:feature_class":"P",
    "gn:feature_code":"PPL",
    "gn:name":"\u017dibr\u0161e",
    "gn:population":166,
    "gn:timezone":"Europe/Ljubljana",
    "iso:country":"SI",
    "name:bos_x_preferred":[
        "\u017dibr\u0161e"
    ],
    "name:ceb_x_preferred":[
        "\u017dibr\u0161e"
    ],
    "name:nld_x_preferred":[
        "\u017dibr\u0161e"
    ],
    "name:pol_x_preferred":[
        "\u017dibr\u0161e"
    ],
    "name:ron_x_preferred":[
        "\u017dibr\u0161e"
    ],
    "name:slv_x_preferred":[
        "\u017dibr\u0161e"
    ],
    "name:ukr_x_preferred":[
        "\u0416\u0438\u0431\u0440\u0448\u0435"
    ],
    "name:und_x_variant":[
        "\u017dibr\u0161e"
    ],
    "wof:name":"Zibrse",
    "wof:placetype":"locality",
    "wof:population":166
},
  "geometry": {"coordinates":[14.17611,45.93667],"type":"Point"}
}