{
  "type": "Feature",
  "properties": {
    "iso:country":"SI",
    "name:ceb_x_preferred":[
        "\u010crnu\u010de District"
    ],
    "name:deu_x_preferred":[
        "\u010crnu\u010de"
    ],
    "name:eng_x_preferred":[
        "\u010crnu\u010de"
    ],
    "name:eng_x_variant":[
        "\u010crnu\u010de District"
    ],
    "name:pol_x_preferred":[
        "\u010crnu\u010de"
    ],
    "name:slv_x_preferred":[
        "\u010cetrtna skupnost \u010crnu\u010de"
    ],
    "name:slv_x_variant":[
        "\u010crnu\u010de"
    ],
    "name:und_x_colloquial":[
        "Crnuce"
    ],
    "name:und_x_preferred":[
        "\u010crnu\u010de"
    ],
    "name:unk_x_variant":[
        "\u010crnu\u010de",
        "\u010crnu\u010de"
    ],
    "qs:gn_adm0_cc":"SI",
    "qs:gn_fcode":"PPL",
    "qs:gn_local":3196359,
    "qs:gn_nam_loc":"Ljubljana, Ljubljana, Ljubljana, SI",
    "qs:gn_namadm1":"61",
    "qs:gn_name":"\u010crnu\u010de",
    "qs:local_max":13863,
    "qs:local_sum":25230,
    "qs:localhoods":13,
    "qs:name":"\u010crnu\u010de",
    "qs:name_adm0":"Slovenija",
    "qs:name_adm1":"Ljubljana",
    "qs:name_adm2":"Ljubljana",
    "qs:name_local":"Ljubljana",
    "qs:photo_max":84,
    "qs:photo_sum":146,
    "qs:placetype":"Suburb",
    "qs:quad_count":19,
    "qs:woe_adm0":23424945,
    "qs:woe_adm1":55848364,
    "qs:woe_adm2":12591568,
    "qs:woe_lau":0,
    "qs:woe_local":530634,
    "qs:woe_ver":"7.10.0",
    "wd:wordcount":172,
    "wof:lang":[
        "unk"
    ],
    "wof:name":"Crnuce",
    "wof:placetype":"neighbourhood"
},
  "geometry": {"coordinates":[14.533147,46.102496],"type":"Point"}
}