{
  "type": "Feature",
  "properties": {
    "gn:admin1_code":"13",
    "gn:asciiname":"Zerovnica",
    "gn:country_code":"SI",
    "gn:dem":563,
    "gn:feature_class":"P",
    "gn:feature_code":"PPL",
    "gn:name":"\u017derovnica",
    "gn:population":202,
    "gn:timezone":"Europe/Ljubljana",
    "iso:country":"SI",
    "name:und_x_variant":[
        "\u017derovnica"
    ],
    "wof:name":"Zerovnica",
    "wof:placetype":"locality",
    "wof:population":202
},
  "geometry": {"coordinates":[14.42528,45.7575],"type":"Point"}
}