{
  "type": "Feature",
  "properties": {
    "gn:admin1_code":"91",
    "gn:asciiname":"Slovenska Vas",
    "gn:country_code":"SI",
    "gn:dem":579,
    "gn:feature_class":"P",
    "gn:feature_code":"PPL",
    "gn:name":"Slovenska Vas",
    "gn:population":43,
    "gn:timezone":"Europe/Ljubljana",
    "iso:country":"SI",
    "name:slv_x_historical":[
        "Nem\u0161ka vas"
    ],
    "name:slv_x_preferred":[
        "Nem\u0161ka vas"
    ],
    "wof:name":"Slovenska Vas",
    "wof:placetype":"locality",
    "wof:population":43
},
  "geometry": {"coordinates":[14.22189,45.70658],"type":"Point"}
}