{
  "type": "Feature",
  "properties": {
    "gn:admin1_code":"91",
    "gn:asciiname":"Slovenska Vas",
    "gn:country_code":"SI",
    "gn:dem":579,
    "gn:feature_class":"P",
    "gn:feature_code":"PPL",
    "gn:name":"Slovenska Vas",
    "gn:population":43,
    "gn:timezone":"Europe/Ljubljana",
    "iso:country":"SI",
    "name:bos_x_preferred":[
        "Slovenska vas"
    ],
    "name:hrv_x_preferred":[
        "Slovenska vas"
    ],
    "name:ita_x_preferred":[
        "Villa Santandrea"
    ],
    "name:nld_x_preferred":[
        "Slovenska vas"
    ],
    "name:pol_x_preferred":[
        "Slovenska vas"
    ],
    "name:ron_x_preferred":[
        "Slovenska vas"
    ],
    "name:slv_x_historical":[
        "Nem\u0161ka vas"
    ],
    "name:slv_x_preferred":[
        "Nem\u0161ka vas"
    ],
    "name:slv_x_variant":[
        "Slovenska vas"
    ],
    "name:ukr_x_preferred":[
        "\u0421\u043b\u043e\u0432\u0435\u043d\u0441\u044c\u043a\u0430 \u0412\u0430\u0441"
    ],
    "wof:name":"Slovenska Vas",
    "wof:placetype":"locality",
    "wof:population":43
},
  "geometry": {"coordinates":[14.22189,45.70658],"type":"Point"}
}