{
  "type": "Feature",
  "properties": {
    "gn:admin1_code":"J7",
    "gn:asciiname":"Dolenje Kronovo",
    "gn:country_code":"SI",
    "gn:dem":166,
    "gn:feature_class":"P",
    "gn:feature_code":"PPL",
    "gn:name":"Dolenje Kronovo",
    "gn:population":119,
    "gn:timezone":"Europe/Ljubljana",
    "iso:country":"SI",
    "name:bos_x_preferred":[
        "Dolenje Kronovo"
    ],
    "name:ceb_x_preferred":[
        "Dolenje Kronovo"
    ],
    "name:hrv_x_preferred":[
        "Dolenje Kronovo"
    ],
    "name:nld_x_preferred":[
        "Dolenje Kronovo"
    ],
    "name:pol_x_preferred":[
        "Dolenje Kronovo"
    ],
    "name:ron_x_preferred":[
        "Dolenje Kronovo"
    ],
    "name:slv_x_preferred":[
        "Dolenje Kronovo"
    ],
    "name:ukr_x_preferred":[
        "\u0414\u043e\u043b\u0435\u043d\u0454 \u041a\u0440\u043e\u043d\u043e\u0432\u043e"
    ],
    "wof:name":"Dolenje Kronovo",
    "wof:placetype":"locality",
    "wof:population":119
},
  "geometry": {"coordinates":[15.25,45.85],"type":"Point"}
}