{
  "type": "Feature",
  "properties": {
    "gn:admin1_code":"J7",
    "gn:asciiname":"Dolenje Kronovo",
    "gn:country_code":"SI",
    "gn:dem":166,
    "gn:feature_class":"P",
    "gn:feature_code":"PPL",
    "gn:name":"Dolenje Kronovo",
    "gn:population":119,
    "gn:timezone":"Europe/Ljubljana",
    "iso:country":"SI",
    "wof:name":"Dolenje Kronovo",
    "wof:placetype":"locality",
    "wof:population":119
},
  "geometry": {"coordinates":[15.25,45.85],"type":"Point"}
}