{
  "type": "Feature",
  "properties": {
    "gn:admin1_code":"B6",
    "gn:asciiname":"Laze pri Bostanju",
    "gn:country_code":"SI",
    "gn:dem":472,
    "gn:feature_class":"P",
    "gn:feature_code":"PPL",
    "gn:name":"Laze pri Bo\u0161tanju",
    "gn:population":33,
    "gn:timezone":"Europe/Ljubljana",
    "iso:country":"SI",
    "name:bos_x_preferred":[
        "Laze pri Bo\u0161tanju"
    ],
    "name:nld_x_preferred":[
        "Laze pri Bo\u0161tanju"
    ],
    "name:pol_x_preferred":[
        "Laze pri Bo\u0161tanju"
    ],
    "name:ron_x_preferred":[
        "Laze pri Bo\u0161tanju"
    ],
    "name:slv_x_preferred":[
        "Laze pri Bo\u0161tanju"
    ],
    "name:ukr_x_preferred":[
        "\u041b\u0430\u0437\u0435-\u043f\u0440\u0438-\u0411\u043e\u0448\u0442\u0430\u043d\u044e"
    ],
    "name:und_x_variant":[
        "Laze pri Bo\u0161tanju"
    ],
    "wof:name":"Laze pri Bostanju",
    "wof:placetype":"locality",
    "wof:population":33
},
  "geometry": {"coordinates":[15.27373,45.99084000000001],"type":"Point"}
}