{
  "type": "Feature",
  "properties": {
    "gn:admin1_code":"P8",
    "gn:asciiname":"Senik",
    "gn:country_code":"SI",
    "gn:dem":237,
    "gn:feature_class":"P",
    "gn:feature_code":"PPL",
    "gn:name":"Senik",
    "gn:population":90,
    "gn:timezone":"Europe/Ljubljana",
    "iso:country":"SI",
    "name:bos_x_preferred":[
        "Senik"
    ],
    "name:nld_x_preferred":[
        "Senik"
    ],
    "name:pol_x_preferred":[
        "Senik"
    ],
    "name:ron_x_preferred":[
        "Senik"
    ],
    "name:slv_x_preferred":[
        "Senik"
    ],
    "name:ukr_x_preferred":[
        "\u0421\u0435\u043d\u0438\u043a"
    ],
    "wof:name":"Senik",
    "wof:placetype":"locality",
    "wof:population":90
},
  "geometry": {"coordinates":[16.09167,46.45694],"type":"Point"}
}