{
  "type": "Feature",
  "properties": {
    "gn:admin1_code":"F5",
    "gn:asciiname":"Hrastje ob Bistrici",
    "gn:country_code":"SI",
    "gn:dem":303,
    "gn:feature_class":"P",
    "gn:feature_code":"PPL",
    "gn:name":"Hrastje ob Bistrici",
    "gn:population":148,
    "gn:timezone":"Europe/Ljubljana",
    "iso:country":"SI",
    "name:bos_x_preferred":[
        "Hrastje ob Bistrici"
    ],
    "name:ceb_x_preferred":[
        "Hrastje ob Bistrici"
    ],
    "name:hrv_x_preferred":[
        "Hrastje ob Bistrici"
    ],
    "name:nld_x_preferred":[
        "Hrastje ob Bistrici"
    ],
    "name:pol_x_preferred":[
        "Hrastje ob Bistrici"
    ],
    "name:ron_x_preferred":[
        "Hrastje ob Bistrici"
    ],
    "name:slv_x_preferred":[
        "Hrastje ob Bistrici"
    ],
    "name:ukr_x_preferred":[
        "\u0425\u0440\u0430\u0441\u0442\u0454-\u043e\u0431-\u0411\u0438\u0441\u0442\u0440\u0438\u0446\u0456"
    ],
    "name:und_x_variant":[
        "Hrastje",
        "Hrastje ob Bistrici"
    ],
    "wof:name":"Hrastje ob Bistrici",
    "wof:placetype":"locality",
    "wof:population":148
},
  "geometry": {"coordinates":[15.63333,46.06667],"type":"Point"}
}