{
  "type": "Feature",
  "properties": {
    "gn:admin1_code":"F5",
    "gn:asciiname":"Hrastje ob Bistrici",
    "gn:country_code":"SI",
    "gn:dem":303,
    "gn:feature_class":"P",
    "gn:feature_code":"PPL",
    "gn:name":"Hrastje ob Bistrici",
    "gn:population":148,
    "gn:timezone":"Europe/Ljubljana",
    "iso:country":"SI",
    "name:und_x_variant":[
        "Hrastje",
        "Hrastje ob Bistrici"
    ],
    "wof:name":"Hrastje ob Bistrici",
    "wof:placetype":"locality",
    "wof:population":148
},
  "geometry": {"coordinates":[15.63333,46.06667],"type":"Point"}
}