{
  "type": "Feature",
  "properties": {
    "gn:admin1_code":"22",
    "gn:asciiname":"Osredke",
    "gn:country_code":"SI",
    "gn:dem":348,
    "gn:feature_class":"P",
    "gn:feature_code":"PPL",
    "gn:name":"Osredke",
    "gn:population":67,
    "gn:timezone":"Europe/Ljubljana",
    "iso:country":"SI",
    "wof:name":"Osredke",
    "wof:placetype":"locality",
    "wof:population":67
},
  "geometry": {"coordinates":[14.68306,46.10873],"type":"Point"}
}