{
  "type": "Feature",
  "properties": {
    "gn:admin1_code":"D8",
    "gn:asciiname":"Velika Slevica",
    "gn:country_code":"SI",
    "gn:dem":600,
    "gn:feature_class":"P",
    "gn:feature_code":"PPL",
    "gn:name":"Velika Slevica",
    "gn:population":48,
    "gn:timezone":"Europe/Ljubljana",
    "iso:country":"SI",
    "wof:name":"Velika Slevica",
    "wof:placetype":"locality",
    "wof:population":48
},
  "geometry": {"coordinates":[14.61639,45.81472],"type":"Point"}
}