{
  "type": "Feature",
  "properties": {
    "gn:admin1_code":"D8",
    "gn:asciiname":"Velika Slevica",
    "gn:country_code":"SI",
    "gn:dem":600,
    "gn:feature_class":"P",
    "gn:feature_code":"PPL",
    "gn:name":"Velika Slevica",
    "gn:population":48,
    "gn:timezone":"Europe/Ljubljana",
    "iso:country":"SI",
    "name:bos_x_preferred":[
        "Velika Slevica"
    ],
    "name:fas_x_preferred":[
        "\u0648\u0644\u06cc\u06a9\u0627 \u0633\u0644\u0648\u06cc\u06a9\u0627"
    ],
    "name:nld_x_preferred":[
        "Velika Slevica"
    ],
    "name:pol_x_preferred":[
        "Velika Slevica"
    ],
    "name:ron_x_preferred":[
        "Velika Slevica"
    ],
    "name:slv_x_preferred":[
        "Velika Slevica"
    ],
    "name:ukr_x_preferred":[
        "\u0412\u0435\u043b\u0438\u043a\u0430 \u0421\u043b\u0435\u0432\u0438\u0446\u044f"
    ],
    "wof:name":"Velika Slevica",
    "wof:placetype":"locality",
    "wof:population":48
},
  "geometry": {"coordinates":[14.61639,45.81472],"type":"Point"}
}