{
  "type": "Feature",
  "properties": {
    "gn:admin1_code":"O8",
    "gn:asciiname":"Krizeca Vas",
    "gn:country_code":"SI",
    "gn:dem":269,
    "gn:feature_class":"P",
    "gn:feature_code":"PPL",
    "gn:name":"Kri\u017ee\u010da Vas",
    "gn:population":84,
    "gn:timezone":"Europe/Ljubljana",
    "iso:country":"SI",
    "name:bos_x_preferred":[
        "Kri\u017ee\u010da vas"
    ],
    "name:nld_x_preferred":[
        "Kri\u017ee\u010da vas"
    ],
    "name:pol_x_preferred":[
        "Kri\u017ee\u010da vas"
    ],
    "name:ron_x_preferred":[
        "Kri\u017ee\u010da vas"
    ],
    "name:slv_x_preferred":[
        "Kri\u017ee\u010da vas"
    ],
    "name:ukr_x_preferred":[
        "\u041a\u0440\u0438\u0436\u0435\u0447\u0430 \u0412\u0430\u0441"
    ],
    "name:und_x_variant":[
        "Kri\u017ee\u010da Vas"
    ],
    "wof:name":"Krizeca Vas",
    "wof:placetype":"locality",
    "wof:population":84
},
  "geometry": {"coordinates":[15.61209,46.31204],"type":"Point"}
}