{
  "type": "Feature",
  "properties": {
    "gn:country":"SI",
    "gn:fcode":"PPL",
    "gn:population":0,
    "iso:country":"SI",
    "name:bos_x_preferred":[
        "Bo\u0161tanj"
    ],
    "name:ceb_x_preferred":[
        "Bo\u0161tanj"
    ],
    "name:che_x_preferred":[
        "\u0411\u043e\u0448\u0442\u0430\u043d\u044c"
    ],
    "name:deu_x_preferred":[
        "Bo\u0161tanj"
    ],
    "name:eng_x_preferred":[
        "Bo\u0161tanj"
    ],
    "name:fra_x_preferred":[
        "Bo\u0161tanj"
    ],
    "name:hrv_x_preferred":[
        "Bo\u0161tanj"
    ],
    "name:mkd_x_preferred":[
        "\u0411\u043e\u0448\u0442\u0430\u045a"
    ],
    "name:nld_x_preferred":[
        "Bo\u0161tanj"
    ],
    "name:pol_x_preferred":[
        "Bo\u0161tanj"
    ],
    "name:ron_x_preferred":[
        "Bo\u0161tanj"
    ],
    "name:slv_x_preferred":[
        "Bo\u0161tanj"
    ],
    "name:tat_x_preferred":[
        "\u0411\u043e\u0448\u0442\u0430\u043d\u044c"
    ],
    "name:ukr_x_preferred":[
        "\u0411\u043e\u0448\u0442\u0430\u043d\u044c"
    ],
    "qs_pg:aaroncc":"SI",
    "qs_pg:gn_country":"SI",
    "qs_pg:gn_fcode":"PPL",
    "qs_pg:gn_pop":0,
    "qs_pg:name":"Bo\u00b5tanj",
    "qs_pg:name_adm0":"Slovenija",
    "qs_pg:name_adm1":"Sevnica",
    "qs_pg:photos":42,
    "qs_pg:photos_1k":9,
    "qs_pg:photos_9k":1,
    "qs_pg:photos_9r":2,
    "qs_pg:photos_all":42,
    "qs_pg:photos_sr":2,
    "qs_pg:pop_sr":0,
    "qs_pg:qs_pg_placetype":"locality",
    "qs_pg:qs_pg_placetype_gp":"Town",
    "qs_pg:woe_adm0":23424945,
    "woe:adm0_id":23424945,
    "woe:name_adm0":"Slovenija",
    "woe:name_adm1":"Sevnica",
    "woe:placetype":"Town",
    "wof:name":"Bo\u00b5tanj",
    "wof:placetype":"locality",
    "wof:population":312
},
  "geometry": {"coordinates":[15.2825,46.01444],"type":"Point"}
}