{
  "type": "Feature",
  "properties": {
    "gn:admin1_code":"N3",
    "gn:asciiname":"Kladnart",
    "gn:country_code":"SI",
    "gn:dem":404,
    "gn:feature_class":"P",
    "gn:feature_code":"PPL",
    "gn:name":"Kladnart",
    "gn:population":4,
    "gn:timezone":"Europe/Ljubljana",
    "iso:country":"SI",
    "wof:name":"Kladnart",
    "wof:placetype":"locality",
    "wof:population":4
},
  "geometry": {"coordinates":[15.36343,46.30778],"type":"Point"}
}