{
  "type": "Feature",
  "properties": {
    "gn:admin1_code":"N3",
    "gn:asciiname":"Kladnart",
    "gn:country_code":"SI",
    "gn:dem":404,
    "gn:feature_class":"P",
    "gn:feature_code":"PPL",
    "gn:name":"Kladnart",
    "gn:population":4,
    "gn:timezone":"Europe/Ljubljana",
    "iso:country":"SI",
    "name:bos_x_preferred":[
        "Kladnart"
    ],
    "name:hrv_x_preferred":[
        "Kladnart"
    ],
    "name:nld_x_preferred":[
        "Kladnart"
    ],
    "name:pol_x_preferred":[
        "Kladnart"
    ],
    "name:ron_x_preferred":[
        "Kladnart"
    ],
    "name:slv_x_preferred":[
        "Kladnart"
    ],
    "name:ukr_x_preferred":[
        "\u041a\u043b\u0430\u0434\u043d\u0430\u0440\u0442"
    ],
    "wof:name":"Kladnart",
    "wof:placetype":"locality",
    "wof:population":4
},
  "geometry": {"coordinates":[15.36343,46.30778],"type":"Point"}
}