{
  "type": "Feature",
  "properties": {
    "gn:admin1_code":"L7",
    "gn:asciiname":"Zaga",
    "gn:country_code":"SI",
    "gn:dem":520,
    "gn:feature_class":"P",
    "gn:feature_code":"PPL",
    "gn:name":"Zaga",
    "gn:population":0,
    "gn:timezone":"Europe/Ljubljana",
    "iso:country":"SI",
    "wof:name":"Zaga",
    "wof:placetype":"locality"
},
  "geometry": {"coordinates":[15.41917,46.08944],"type":"Point"}
}