{
  "type": "Feature",
  "properties": {
    "gn:admin1_code":"27",
    "gn:asciiname":"Zirovski Vrh Sv. Antona",
    "gn:country_code":"SI",
    "gn:dem":773,
    "gn:feature_class":"P",
    "gn:feature_code":"PPL",
    "gn:name":"\u017dirovski Vrh Sv. Antona",
    "gn:population":59,
    "gn:timezone":"Europe/Ljubljana",
    "iso:country":"SI",
    "name:bos_x_preferred":[
        "\u017dirovski Vrh Svetega Antona"
    ],
    "name:hrv_x_preferred":[
        "\u017dirovski Vrh Sv. Antona"
    ],
    "name:nld_x_preferred":[
        "\u017dirovski Vrh Sv. Antona"
    ],
    "name:pol_x_preferred":[
        "\u017dirovski Vrh Svetega Antona"
    ],
    "name:ron_x_preferred":[
        "\u017dirovski Vrh Svetega Antona"
    ],
    "name:slv_x_preferred":[
        "\u017dirovski Vrh Svetega Antona"
    ],
    "name:ukr_x_preferred":[
        "\u0416\u0438\u0440\u043e\u0432\u0441\u044c\u043a\u0438\u0439 \u0412\u0440\u0445 \u0421\u0432\u0435\u0442\u0435\u0433\u0430 \u0410\u043d\u0442\u043e\u043d\u0430"
    ],
    "wof:name":"Zirovski Vrh Sv. Antona",
    "wof:placetype":"locality",
    "wof:population":59
},
  "geometry": {"coordinates":[14.12809,46.082],"type":"Point"}
}