{
  "type": "Feature",
  "properties": {
    "gn:admin1_code":"O4",
    "gn:asciiname":"Log pri Brezovici",
    "gn:country_code":"SI",
    "gn:dem":444,
    "gn:feature_class":"P",
    "gn:feature_code":"PPLA",
    "gn:name":"Log pri Brezovici",
    "gn:population":1634,
    "gn:timezone":"Europe/Ljubljana",
    "iso:country":"SI",
    "name:bos_x_preferred":[
        "Log pri Brezovici"
    ],
    "name:ceb_x_preferred":[
        "Log pri Brezovici"
    ],
    "name:nld_x_preferred":[
        "Log pri Brezovici"
    ],
    "name:pol_x_preferred":[
        "Log pri Brezovici"
    ],
    "name:ron_x_preferred":[
        "Log pri Brezovici"
    ],
    "name:slv_x_preferred":[
        "Log pri Brezovici"
    ],
    "name:srp_x_preferred":[
        "\u041b\u043e\u0433 \u043f\u0440\u0438 \u0411\u0440\u0435\u0437\u043e\u0432\u0438\u0446\u0438"
    ],
    "name:ukr_x_preferred":[
        "\u041b\u043e\u0433-\u043f\u0440\u0438-\u0411\u0440\u0435\u0437\u043e\u0432\u0438\u0446\u0456"
    ],
    "name:und_x_variant":[
        "Log"
    ],
    "wof:name":"Log pri Brezovici",
    "wof:placetype":"locality",
    "wof:population":1634
},
  "geometry": {"coordinates":[14.36667,46.01667],"type":"Point"}
}