{
  "type": "Feature",
  "properties": {
    "gn:admin1_code":"L9",
    "gn:asciiname":"Visnji Grm",
    "gn:country_code":"SI",
    "gn:dem":482,
    "gn:feature_class":"P",
    "gn:feature_code":"PPL",
    "gn:name":"Vi\u0161nji Grm",
    "gn:population":23,
    "gn:timezone":"Europe/Ljubljana",
    "iso:country":"SI",
    "name:bos_x_preferred":[
        "Vi\u0161nji Grm"
    ],
    "name:nld_x_preferred":[
        "Vi\u0161nji Grm"
    ],
    "name:pol_x_preferred":[
        "Vi\u0161nji Grm"
    ],
    "name:ron_x_preferred":[
        "Vi\u0161nji Grm"
    ],
    "name:slv_x_preferred":[
        "Vi\u0161nji Grm"
    ],
    "name:ukr_x_preferred":[
        "\u0412\u0438\u0448\u043d\u0456\u0439 \u0413\u0440\u043c"
    ],
    "name:und_x_variant":[
        "Vi\u0161nji Grm"
    ],
    "wof:name":"Visnji Grm",
    "wof:placetype":"locality",
    "wof:population":23
},
  "geometry": {"coordinates":[14.88101,46.00725],"type":"Point"}
}