{
  "type": "Feature",
  "properties": {
    "gn:admin1_code":"B6",
    "gn:asciiname":"Krizisce",
    "gn:country_code":"SI",
    "gn:dem":247,
    "gn:feature_class":"P",
    "gn:feature_code":"PPL",
    "gn:name":"Kri\u017ei\u0161\u010de",
    "gn:population":39,
    "gn:timezone":"Europe/Ljubljana",
    "iso:country":"SI",
    "name:bos_x_preferred":[
        "Kri\u017ei\u0161\u010de"
    ],
    "name:pol_x_preferred":[
        "Kri\u017ei\u0161\u010de"
    ],
    "name:slv_x_preferred":[
        "Kri\u017ei\u0161\u010de"
    ],
    "wof:name":"Krizisce",
    "wof:placetype":"locality",
    "wof:population":39
},
  "geometry": {"coordinates":[15.20718,45.9965],"type":"Point"}
}