{
  "type": "Feature",
  "properties": {
    "gn:population":1558,
    "iso:country":"SI",
    "name:bos_x_preferred":[
        "Rogatec"
    ],
    "name:ceb_x_preferred":[
        "Rogatec"
    ],
    "name:che_x_preferred":[
        "\u0420\u043e\u0433\u0430\u0442\u0435\u0446\u044c"
    ],
    "name:deu_x_preferred":[
        "Rohitsch"
    ],
    "name:eng_x_preferred":[
        "Rogatec"
    ],
    "name:fra_x_preferred":[
        "Rogatec"
    ],
    "name:hbs_x_preferred":[
        "Rogatec"
    ],
    "name:heb_x_preferred":[
        "\u05e8\u05d5\u05d2\u05d0\u05d8\u05e7"
    ],
    "name:hrv_x_preferred":[
        "Rogatec"
    ],
    "name:hun_x_preferred":[
        "Rogatec"
    ],
    "name:nld_x_preferred":[
        "Rogatec"
    ],
    "name:pol_x_preferred":[
        "Rogatec"
    ],
    "name:ron_x_preferred":[
        "Rogatec"
    ],
    "name:rus_x_preferred":[
        "\u0420\u043e\u0433\u0430\u0442\u0435\u0446"
    ],
    "name:slv_x_preferred":[
        "Rogatec"
    ],
    "name:srp_x_preferred":[
        "\u0420\u043e\u0433\u0430\u0442\u0435\u0446"
    ],
    "name:tat_x_preferred":[
        "\u0420\u043e\u0433\u0430\u0442\u0435\u0446\u044c"
    ],
    "name:tha_x_preferred":[
        "\u0e23\u0e2d\u0e01\u0e32\u0e40\u0e15\u0e34\u0e15\u0e2a\u0e4c"
    ],
    "name:ukr_x_preferred":[
        "\u0420\u043e\u0433\u0430\u0442\u0435\u0446\u044c"
    ],
    "name:vie_x_preferred":[
        "Rogatec"
    ],
    "name:zho_x_preferred":[
        "\u7f85\u52a0\u6cf0\u8328"
    ],
    "qs:a0":"Slovenija",
    "qs:a1":"*",
    "qs:a1r":"0",
    "qs:adm0":"Slovenija",
    "qs:la_lc":"*",
    "qs:level":"locality",
    "qs:loc":"Rogatec",
    "qs:loc_alt":"Rogatec",
    "qs:pop":0,
    "qs:type":"buffered point",
    "wof:name":"Rogatec",
    "wof:placetype":"locality",
    "wof:population":1558
},
  "geometry": {"coordinates":[15.712143,46.229898],"type":"Point"}
}