{
  "type": "Feature",
  "properties": {
    "gn:admin1_code":"B7",
    "gn:asciiname":"Ponikve",
    "gn:country_code":"SI",
    "gn:dem":364,
    "gn:feature_class":"P",
    "gn:feature_code":"PPL",
    "gn:name":"Ponikve",
    "gn:population":119,
    "gn:timezone":"Europe/Ljubljana",
    "iso:country":"SI",
    "name:bos_x_preferred":[
        "Ponikve"
    ],
    "name:ceb_x_preferred":[
        "Ponikve"
    ],
    "name:pol_x_preferred":[
        "Ponikve"
    ],
    "name:ron_x_preferred":[
        "Ponikve"
    ],
    "name:sco_x_preferred":[
        "Ponikve"
    ],
    "name:slv_x_preferred":[
        "Ponikve"
    ],
    "name:ukr_x_preferred":[
        "\u041f\u043e\u043d\u0438\u043a\u0432\u0435"
    ],
    "name:und_x_variant":[
        "Paniqua",
        "Ponikve"
    ],
    "wof:name":"Ponikve",
    "wof:placetype":"locality",
    "wof:population":119
},
  "geometry": {"coordinates":[13.86611,45.79111],"type":"Point"}
}