{
  "type": "Feature",
  "properties": {
    "gn:admin1_code":"C1",
    "gn:asciiname":"Dole pri Skofljici",
    "gn:country_code":"SI",
    "gn:dem":349,
    "gn:feature_class":"P",
    "gn:feature_code":"PPL",
    "gn:name":"Dole pri \u0160kofljici",
    "gn:population":45,
    "gn:timezone":"Europe/Ljubljana",
    "iso:country":"SI",
    "name:bos_x_preferred":[
        "Dole pri \u0160kofljici"
    ],
    "name:nld_x_preferred":[
        "Dole pri \u0160kofljici"
    ],
    "name:pol_x_preferred":[
        "Dole pri \u0160kofljici"
    ],
    "name:ron_x_preferred":[
        "Dole pri \u0160kofljici"
    ],
    "name:slv_x_preferred":[
        "Dole pri \u0160kofljici"
    ],
    "name:ukr_x_preferred":[
        "\u0414\u043e\u043b\u0435-\u043f\u0440\u0438-\u0428\u043a\u043e\u0444\u043b\u0456\u0446\u0456"
    ],
    "wof:name":"Dole pri Skofljici",
    "wof:placetype":"locality",
    "wof:population":45
},
  "geometry": {"coordinates":[14.59582,45.99871],"type":"Point"}
}