{
  "type": "Feature",
  "properties": {
    "iso:country":"SI",
    "name:bos_x_preferred":[
        "Vnajnarje"
    ],
    "name:bul_x_preferred":[
        "\u0412\u043d\u0430\u0439\u043d\u0430\u0440\u0435"
    ],
    "name:ceb_x_preferred":[
        "Vnajnarje"
    ],
    "name:nld_x_preferred":[
        "Vnajnarje"
    ],
    "name:pol_x_preferred":[
        "Vnajnarje"
    ],
    "name:ron_x_preferred":[
        "Vnajnarje"
    ],
    "name:slv_x_preferred":[
        "Vnajnarje"
    ],
    "name:ukr_x_preferred":[
        "\u0412\u043d\u0430\u0439\u043d\u0430\u0440\u0454"
    ],
    "wof:name":"Vnajnarje",
    "wof:placetype":"neighbourhood"
},
  "geometry": {"coordinates":[14.68204114467312,46.0429610369337],"type":"Point"}
}