{
  "type": "Feature",
  "properties": {
    "iso:country":"SI",
    "wof:name":"Vnajnarje",
    "wof:placetype":"neighbourhood"
},
  "geometry": {"coordinates":[14.68204114467312,46.0429610369337],"type":"Point"}
}