{
  "type": "Feature",
  "properties": {
    "gn:admin1_code":"I5",
    "gn:asciiname":"Tepe",
    "gn:country_code":"SI",
    "gn:dem":568,
    "gn:feature_class":"P",
    "gn:feature_code":"PPL",
    "gn:name":"Tepe",
    "gn:population":185,
    "gn:timezone":"Europe/Ljubljana",
    "iso:country":"SI",
    "name:bos_x_preferred":[
        "Tepe"
    ],
    "name:bul_x_preferred":[
        "\u0422\u0435\u043f\u0435"
    ],
    "name:ceb_x_preferred":[
        "Tepe"
    ],
    "name:nld_x_preferred":[
        "Tepe"
    ],
    "name:pol_x_preferred":[
        "Tepe"
    ],
    "name:ron_x_preferred":[
        "Tepe"
    ],
    "name:slv_x_preferred":[
        "Tepe"
    ],
    "name:ukr_x_preferred":[
        "\u0422\u0435\u043f\u0435"
    ],
    "wof:name":"Tepe",
    "wof:placetype":"locality",
    "wof:population":185
},
  "geometry": {"coordinates":[14.9425,46.07972],"type":"Point"}
}