{
  "type": "Feature",
  "properties": {
    "gn:admin1_code":"I5",
    "gn:asciiname":"Tepe",
    "gn:country_code":"SI",
    "gn:dem":568,
    "gn:feature_class":"P",
    "gn:feature_code":"PPL",
    "gn:name":"Tepe",
    "gn:population":185,
    "gn:timezone":"Europe/Ljubljana",
    "iso:country":"SI",
    "wof:name":"Tepe",
    "wof:placetype":"locality",
    "wof:population":185
},
  "geometry": {"coordinates":[14.9425,46.07972],"type":"Point"}
}