{
  "type": "Feature",
  "properties": {
    "gn:admin1_code":"25",
    "gn:asciiname":"Vrata",
    "gn:country_code":"SI",
    "gn:dem":756,
    "gn:feature_class":"P",
    "gn:feature_code":"PPL",
    "gn:name":"Vrata",
    "gn:population":107,
    "gn:timezone":"Europe/Ljubljana",
    "iso:country":"SI",
    "name:bos_x_preferred":[
        "Vrata"
    ],
    "name:bul_x_preferred":[
        "\u0412\u0440\u0430\u0442\u0430"
    ],
    "name:ceb_x_preferred":[
        "Vrata"
    ],
    "name:nld_x_preferred":[
        "Vrata"
    ],
    "name:pol_x_preferred":[
        "Vrata"
    ],
    "name:ron_x_preferred":[
        "Vrata"
    ],
    "name:slv_x_preferred":[
        "Vrata"
    ],
    "name:ukr_x_preferred":[
        "\u0412\u0440\u0430\u0442\u0430"
    ],
    "wof:name":"Vrata",
    "wof:placetype":"locality",
    "wof:population":107
},
  "geometry": {"coordinates":[15.09184,46.61741],"type":"Point"}
}