{
  "type": "Feature",
  "properties": {
    "gn:admin1_code":"I6",
    "gn:asciiname":"Desnjak",
    "gn:country_code":"SI",
    "gn:dem":254,
    "gn:feature_class":"P",
    "gn:feature_code":"PPL",
    "gn:name":"Desnjak",
    "gn:population":142,
    "gn:timezone":"Europe/Ljubljana",
    "iso:country":"SI",
    "name:bos_x_preferred":[
        "Desnjak"
    ],
    "name:ceb_x_preferred":[
        "Desnjak"
    ],
    "name:hrv_x_preferred":[
        "Desnjak"
    ],
    "name:nld_x_preferred":[
        "Desnjak"
    ],
    "name:pol_x_preferred":[
        "Desnjak"
    ],
    "name:ron_x_preferred":[
        "Desnjak"
    ],
    "name:slv_x_preferred":[
        "Desnjak"
    ],
    "name:ukr_x_preferred":[
        "\u0414\u0435\u0441\u043d\u044f\u043a"
    ],
    "wof:name":"Desnjak",
    "wof:placetype":"locality",
    "wof:population":142
},
  "geometry": {"coordinates":[16.133,46.49133],"type":"Point"}
}