{
  "type": "Feature",
  "properties": {
    "gn:admin1_code":"I6",
    "gn:asciiname":"Desnjak",
    "gn:country_code":"SI",
    "gn:dem":254,
    "gn:feature_class":"P",
    "gn:feature_code":"PPL",
    "gn:name":"Desnjak",
    "gn:population":142,
    "gn:timezone":"Europe/Ljubljana",
    "iso:country":"SI",
    "wof:name":"Desnjak",
    "wof:placetype":"locality",
    "wof:population":142
},
  "geometry": {"coordinates":[16.133,46.49133],"type":"Point"}
}