{
  "type": "Feature",
  "properties": {
    "gn:admin1_code":"82",
    "gn:asciiname":"Spodnja Besnica",
    "gn:country_code":"SI",
    "gn:dem":418,
    "gn:feature_class":"P",
    "gn:feature_code":"PPL",
    "gn:name":"Spodnja Besnica",
    "gn:population":905,
    "gn:timezone":"Europe/Ljubljana",
    "iso:country":"SI",
    "wof:name":"Spodnja Besnica",
    "wof:placetype":"locality",
    "wof:population":905
},
  "geometry": {"coordinates":[14.30572,46.25749],"type":"Point"}
}