{
  "type": "Feature",
  "properties": {
    "gn:admin1_code":"82",
    "gn:asciiname":"Spodnja Besnica",
    "gn:country_code":"SI",
    "gn:dem":418,
    "gn:feature_class":"P",
    "gn:feature_code":"PPL",
    "gn:name":"Spodnja Besnica",
    "gn:population":905,
    "gn:timezone":"Europe/Ljubljana",
    "iso:country":"SI",
    "name:bos_x_preferred":[
        "Spodnja Besnica"
    ],
    "name:ceb_x_preferred":[
        "Spodnja Besnica"
    ],
    "name:hrv_x_preferred":[
        "Spodnja Besnica"
    ],
    "name:nld_x_preferred":[
        "Spodnja Besnica"
    ],
    "name:pol_x_preferred":[
        "Spodnja Besnica"
    ],
    "name:ron_x_preferred":[
        "Spodnja Besnica"
    ],
    "name:slv_x_preferred":[
        "Spodnja Besnica"
    ],
    "name:ukr_x_preferred":[
        "\u0421\u043f\u043e\u0434\u043d\u044f \u0411\u0435\u0441\u043d\u0438\u0446\u044f"
    ],
    "wof:name":"Spodnja Besnica",
    "wof:placetype":"locality",
    "wof:population":905
},
  "geometry": {"coordinates":[14.30572,46.25749],"type":"Point"}
}