{
  "type": "Feature",
  "properties": {
    "gn:admin1_code":"57",
    "gn:asciiname":"Lazise",
    "gn:country_code":"SI",
    "gn:dem":530,
    "gn:feature_class":"P",
    "gn:feature_code":"PPL",
    "gn:name":"Lazi\u0161e",
    "gn:population":85,
    "gn:timezone":"Europe/Ljubljana",
    "iso:country":"SI",
    "wof:name":"Lazise",
    "wof:placetype":"locality",
    "wof:population":85
},
  "geometry": {"coordinates":[15.24353,46.1259],"type":"Point"}
}