{
  "type": "Feature",
  "properties": {
    "gn:gn_country":"SI",
    "gn:gn_fcode":"PPL",
    "gn:gn_pop":0,
    "gn:population":610,
    "iso:country":"SI",
    "name:dut_x_preferred":[
        "Seno\u017ee\u010de"
    ],
    "name:eng_x_preferred":[
        "Seno\u017ee\u010de"
    ],
    "name:ger_x_preferred":[
        "Seno\u017ee\u010de"
    ],
    "name:ita_x_preferred":[
        "Senosecchia"
    ],
    "name:pol_x_preferred":[
        "Seno\u017ee\u010de"
    ],
    "name:rum_x_preferred":[
        "Seno\u017ee\u010de"
    ],
    "name:slv_x_preferred":[
        "Seno\u017ee\u010de"
    ],
    "name:ukr_x_preferred":[
        "\u0421\u0435\u043d\u043e\u0436\u0435\u0447\u0435"
    ],
    "name:unk_x_variant":[
        "Senos\u00e9cchia"
    ],
    "qs_pg:aaroncc":"SI",
    "qs_pg:gn_country":"SI",
    "qs_pg:gn_fcode":"PPL",
    "qs_pg:gn_pop":0,
    "qs_pg:name":"Seno\u017ee\u010de",
    "qs_pg:name_adm0":"Slovenija",
    "qs_pg:name_adm1":"Sezana",
    "qs_pg:photos":97,
    "qs_pg:photos_1k":20,
    "qs_pg:photos_9k":1,
    "qs_pg:photos_9r":3,
    "qs_pg:photos_all":97,
    "qs_pg:photos_sr":3,
    "qs_pg:pop_sr":0,
    "qs_pg:qs_pg_placetype":"locality",
    "qs_pg:qs_pg_placetype_gp":"Town",
    "qs_pg:woe_adm0":23424945,
    "woe:adm0_id":23424945,
    "woe:name_adm0":"Slovenija",
    "woe:name_adm1":"Sezana",
    "woe:placetype":"Town",
    "wof:name":"Seno\u017ee\u010de",
    "wof:placetype":"locality",
    "wof:population":610
},
  "geometry": {"coordinates":[14.04111,45.72111],"type":"Point"}
}