{
  "type": "Feature",
  "properties": {
    "gn:admin1_code":"L7",
    "gn:asciiname":"Vodice pri Kalobju",
    "gn:country_code":"SI",
    "gn:dem":543,
    "gn:feature_class":"P",
    "gn:feature_code":"PPL",
    "gn:name":"Vodice pri Kalobju",
    "gn:population":76,
    "gn:timezone":"Europe/Ljubljana",
    "iso:country":"SI",
    "name:bos_x_preferred":[
        "Vodice pri Kalobju"
    ],
    "name:hrv_x_preferred":[
        "Vodice pri Kalobju"
    ],
    "name:nld_x_preferred":[
        "Vodice pri Kalobju"
    ],
    "name:pol_x_preferred":[
        "Vodice pri Kalobju"
    ],
    "name:ron_x_preferred":[
        "Vodice pri Kalobju"
    ],
    "name:slv_x_preferred":[
        "Vodice pri Kalobju"
    ],
    "name:ukr_x_preferred":[
        "\u0412\u043e\u0434\u0438\u0446\u0435-\u043f\u0440\u0438-\u041a\u0430\u043b\u043e\u0431\u044e"
    ],
    "wof:name":"Vodice pri Kalobju",
    "wof:placetype":"locality",
    "wof:population":76
},
  "geometry": {"coordinates":[15.3645,46.14764],"type":"Point"}
}