{
  "type": "Feature",
  "properties": {
    "gn:admin1_code":"04",
    "gn:asciiname":"Log v Bohinju",
    "gn:country_code":"SI",
    "gn:dem":578,
    "gn:feature_class":"P",
    "gn:feature_code":"PPL",
    "gn:name":"Log v Bohinju",
    "gn:population":17,
    "gn:timezone":"Europe/Ljubljana",
    "iso:country":"SI",
    "name:bos_x_preferred":[
        "Log v Bohinju"
    ],
    "name:hrv_x_preferred":[
        "Log v Bohinju"
    ],
    "name:ita_x_preferred":[
        "Log v Bohinju"
    ],
    "name:nld_x_preferred":[
        "Log v Bohinju"
    ],
    "name:pol_x_preferred":[
        "Log v Bohinju"
    ],
    "name:ron_x_preferred":[
        "Log v Bohinju"
    ],
    "name:slv_x_preferred":[
        "Log v Bohinju"
    ],
    "name:ukr_x_preferred":[
        "\u041b\u043e\u0433-\u0443-\u0411\u043e\u0445\u0456\u043d\u044e"
    ],
    "wof:name":"Log v Bohinju",
    "wof:placetype":"locality",
    "wof:population":17
},
  "geometry": {"coordinates":[13.98455,46.28418],"type":"Point"}
}