{
  "type": "Feature",
  "properties": {
    "gn:admin1_code":"C5",
    "gn:asciiname":"Pustike",
    "gn:country_code":"SI",
    "gn:dem":274,
    "gn:feature_class":"P",
    "gn:feature_code":"PPL",
    "gn:name":"Pustike",
    "gn:population":83,
    "gn:timezone":"Europe/Ljubljana",
    "iso:country":"SI",
    "name:bos_x_preferred":[
        "Pustike"
    ],
    "name:hrv_x_preferred":[
        "Pustike"
    ],
    "name:nld_x_preferred":[
        "Pustike"
    ],
    "name:pol_x_preferred":[
        "Pustike"
    ],
    "name:ron_x_preferred":[
        "Pustike"
    ],
    "name:slv_x_preferred":[
        "Pustike"
    ],
    "name:ukr_x_preferred":[
        "\u041f\u0443\u0441\u0442\u0438\u043a\u0435"
    ],
    "wof:name":"Pustike",
    "wof:placetype":"locality",
    "wof:population":83
},
  "geometry": {"coordinates":[15.56579,46.19726],"type":"Point"}
}