{
  "type": "Feature",
  "properties": {
    "gn:admin1_code":"H9",
    "gn:asciiname":"Briga",
    "gn:country_code":"SI",
    "gn:dem":570,
    "gn:feature_class":"P",
    "gn:feature_code":"PPL",
    "gn:name":"Briga",
    "gn:population":15,
    "gn:timezone":"Europe/Ljubljana",
    "iso:country":"SI",
    "wof:name":"Briga",
    "wof:placetype":"locality",
    "wof:population":15
},
  "geometry": {"coordinates":[14.86334,45.51997],"type":"Point"}
}