{
  "type": "Feature",
  "properties": {
    "gn:admin1_code":"I5",
    "gn:asciiname":"Klanec pri Gabrovki",
    "gn:country_code":"SI",
    "gn:dem":483,
    "gn:feature_class":"P",
    "gn:feature_code":"PPL",
    "gn:name":"Klanec pri Gabrovki",
    "gn:population":34,
    "gn:timezone":"Europe/Ljubljana",
    "iso:country":"SI",
    "name:bos_x_preferred":[
        "Klanec pri Gabrovki"
    ],
    "name:bul_x_preferred":[
        "\u041a\u043b\u0430\u043d\u0435\u0446 \u043f\u0440\u0438 \u0413\u0430\u0431\u0440\u043e\u0432\u043a\u0438"
    ],
    "name:nld_x_preferred":[
        "Klanec pri Gabrovki"
    ],
    "name:pol_x_preferred":[
        "Klanec pri Gabrovki"
    ],
    "name:ron_x_preferred":[
        "Klanec pri Gabrovki"
    ],
    "name:slv_x_preferred":[
        "Klanec pri Gabrovki"
    ],
    "name:ukr_x_preferred":[
        "\u041a\u043b\u0430\u043d\u0435\u0446\u044c-\u043f\u0440\u0438-\u0413\u0430\u0431\u0440\u043e\u0432\u043a\u0456"
    ],
    "wof:name":"Klanec pri Gabrovki",
    "wof:placetype":"locality",
    "wof:population":34
},
  "geometry": {"coordinates":[14.98612,45.99359000000001],"type":"Point"}
}