{
  "type": "Feature",
  "properties": {
    "gn:admin1_code":"I5",
    "gn:asciiname":"Klanec pri Gabrovki",
    "gn:country_code":"SI",
    "gn:dem":483,
    "gn:feature_class":"P",
    "gn:feature_code":"PPL",
    "gn:name":"Klanec pri Gabrovki",
    "gn:population":34,
    "gn:timezone":"Europe/Ljubljana",
    "iso:country":"SI",
    "wof:name":"Klanec pri Gabrovki",
    "wof:placetype":"locality",
    "wof:population":34
},
  "geometry": {"coordinates":[14.98612,45.99359000000001],"type":"Point"}
}