{
  "type": "Feature",
  "properties": {
    "gn:admin1_code":"N5",
    "gn:asciiname":"Podkraj",
    "gn:country_code":"SI",
    "gn:dem":442,
    "gn:feature_class":"P",
    "gn:feature_code":"PPL",
    "gn:name":"Podkraj",
    "gn:population":209,
    "gn:timezone":"Europe/Ljubljana",
    "iso:country":"SI",
    "wof:name":"Podkraj",
    "wof:placetype":"locality",
    "wof:population":209
},
  "geometry": {"coordinates":[15.1502,46.32738],"type":"Point"}
}