{
  "type": "Feature",
  "properties": {
    "gn:admin1_code":"N5",
    "gn:asciiname":"Podkraj",
    "gn:country_code":"SI",
    "gn:dem":442,
    "gn:feature_class":"P",
    "gn:feature_code":"PPL",
    "gn:name":"Podkraj",
    "gn:population":209,
    "gn:timezone":"Europe/Ljubljana",
    "iso:country":"SI",
    "name:ceb_x_preferred":[
        "Podkraj"
    ],
    "name:hrv_x_preferred":[
        "Podkraj"
    ],
    "name:nld_x_preferred":[
        "Podkraj"
    ],
    "name:pol_x_preferred":[
        "Podkraj"
    ],
    "name:ron_x_preferred":[
        "Podkraj"
    ],
    "name:slv_x_preferred":[
        "Podkraj"
    ],
    "name:ukr_x_preferred":[
        "\u041f\u043e\u0434\u043a\u0440\u0430\u0439"
    ],
    "wof:name":"Podkraj",
    "wof:placetype":"locality",
    "wof:population":209
},
  "geometry": {"coordinates":[15.1502,46.32738],"type":"Point"}
}