{
  "type": "Feature",
  "properties": {
    "gn:admin1_code":"L7",
    "gn:asciiname":"Tajhte",
    "gn:country_code":"SI",
    "gn:dem":461,
    "gn:feature_class":"P",
    "gn:feature_code":"PPL",
    "gn:name":"Tajhte",
    "gn:population":62,
    "gn:timezone":"Europe/Ljubljana",
    "iso:country":"SI",
    "wof:name":"Tajhte",
    "wof:placetype":"locality",
    "wof:population":62
},
  "geometry": {"coordinates":[15.417,46.11937],"type":"Point"}
}