{
  "type": "Feature",
  "properties": {
    "gn:admin1_code":"P3",
    "gn:asciiname":"Gradenje",
    "gn:country_code":"SI",
    "gn:dem":218,
    "gn:feature_class":"P",
    "gn:feature_code":"PPL",
    "gn:name":"Gradenje",
    "gn:population":42,
    "gn:timezone":"Europe/Ljubljana",
    "iso:country":"SI",
    "wof:name":"Gradenje",
    "wof:placetype":"locality",
    "wof:population":42
},
  "geometry": {"coordinates":[15.26345,45.87256],"type":"Point"}
}