{
  "type": "Feature",
  "properties": {
    "gn:admin1_code":"P3",
    "gn:asciiname":"Gradenje",
    "gn:country_code":"SI",
    "gn:dem":218,
    "gn:feature_class":"P",
    "gn:feature_code":"PPL",
    "gn:name":"Gradenje",
    "gn:population":42,
    "gn:timezone":"Europe/Ljubljana",
    "iso:country":"SI",
    "name:bos_x_preferred":[
        "Gradenje"
    ],
    "name:hrv_x_preferred":[
        "Gradenje"
    ],
    "name:nld_x_preferred":[
        "Gradenje"
    ],
    "name:pol_x_preferred":[
        "Gradenje"
    ],
    "name:ron_x_preferred":[
        "Gradenje"
    ],
    "name:slv_x_preferred":[
        "Gradenje"
    ],
    "name:ukr_x_preferred":[
        "\u0413\u0440\u0430\u0434\u0435\u043d\u0454"
    ],
    "wof:name":"Gradenje",
    "wof:placetype":"locality",
    "wof:population":42
},
  "geometry": {"coordinates":[15.26345,45.87256],"type":"Point"}
}