{
  "type": "Feature",
  "properties": {
    "gn:admin1_code":"22",
    "gn:asciiname":"Dolsko",
    "gn:country_code":"SI",
    "gn:dem":261,
    "gn:feature_class":"P",
    "gn:feature_code":"PPL",
    "gn:name":"Dolsko",
    "gn:population":595,
    "gn:timezone":"Europe/Ljubljana",
    "iso:country":"SI",
    "name:bos_x_preferred":[
        "Dolsko"
    ],
    "name:ceb_x_preferred":[
        "Dolsko"
    ],
    "name:nld_x_preferred":[
        "Dolsko"
    ],
    "name:pol_x_preferred":[
        "Dolsko"
    ],
    "name:ron_x_preferred":[
        "Dolsko"
    ],
    "name:slv_x_preferred":[
        "Dolsko"
    ],
    "name:ukr_x_preferred":[
        "\u0414\u043e\u043b\u0441\u043a\u043e"
    ],
    "wof:name":"Dolsko",
    "wof:placetype":"locality",
    "wof:population":595
},
  "geometry": {"coordinates":[14.67722,46.09194],"type":"Point"}
}