{
  "type": "Feature",
  "properties": {
    "gn:admin1_code":"01",
    "gn:asciiname":"Gojace",
    "gn:country_code":"SI",
    "gn:dem":179,
    "gn:feature_class":"P",
    "gn:feature_code":"PPL",
    "gn:name":"Goja\u010de",
    "gn:population":174,
    "gn:timezone":"Europe/Ljubljana",
    "iso:country":"SI",
    "name:bos_x_preferred":[
        "Goja\u010de"
    ],
    "name:bul_x_preferred":[
        "\u0413\u043e\u044f\u0447\u0435"
    ],
    "name:ceb_x_preferred":[
        "Goja\u010de"
    ],
    "name:hun_x_preferred":[
        "Goja\u010de"
    ],
    "name:ita_x_preferred":[
        "Goiaci"
    ],
    "name:nld_x_preferred":[
        "Goja\u010de"
    ],
    "name:pol_x_preferred":[
        "Goja\u010de"
    ],
    "name:ron_x_preferred":[
        "Goja\u010de"
    ],
    "name:slv_x_preferred":[
        "Goja\u010de"
    ],
    "name:srp_x_preferred":[
        "\u0413\u043e\u0458\u0430\u0447\u0435"
    ],
    "name:ukr_x_preferred":[
        "\u0490\u043e\u044f\u0447\u0435"
    ],
    "wof:name":"Gojace",
    "wof:placetype":"locality",
    "wof:population":174
},
  "geometry": {"coordinates":[13.79556,45.9025],"type":"Point"}
}