{
  "type": "Feature",
  "properties": {
    "gn:admin1_code":"G2",
    "gn:asciiname":"Jezerce pri Dobjem",
    "gn:country_code":"SI",
    "gn:dem":500,
    "gn:feature_class":"P",
    "gn:feature_code":"PPL",
    "gn:name":"Jezerce pri Dobjem",
    "gn:population":65,
    "gn:timezone":"Europe/Ljubljana",
    "iso:country":"SI",
    "wof:name":"Jezerce pri Dobjem",
    "wof:placetype":"locality",
    "wof:population":65
},
  "geometry": {"coordinates":[15.39583,46.14917],"type":"Point"}
}