{
  "type": "Feature",
  "properties": {
    "gn:admin1_code":"44",
    "gn:asciiname":"Loga",
    "gn:country_code":"SI",
    "gn:dem":197,
    "gn:feature_class":"P",
    "gn:feature_code":"PPL",
    "gn:name":"Loga",
    "gn:population":0,
    "gn:timezone":"Europe/Ljubljana",
    "iso:country":"SI",
    "wof:name":"Loga",
    "wof:placetype":"locality"
},
  "geometry": {"coordinates":[13.65753,46.10027],"type":"Point"}
}