{
  "type": "Feature",
  "properties": {
    "iso:country":"SI",
    "wof:name":"Zgornja Zadobrova\n",
    "wof:placetype":"neighbourhood"
},
  "geometry": {"coordinates":[14.58209599432153,46.06981420281745],"type":"Point"}
}