{
  "type": "Feature",
  "properties": {
    "iso:country":"SI",
    "wof:name":"Zgornja Zadobrova",
    "wof:placetype":"neighbourhood"
},
  "geometry": {"coordinates":[14.582096,46.069814],"type":"Point"}
}