{
  "type": "Feature",
  "properties": {
    "gn:admin1_code":"12",
    "gn:asciiname":"Sveti Lenart",
    "gn:country_code":"SI",
    "gn:dem":900,
    "gn:feature_class":"P",
    "gn:feature_code":"PPL",
    "gn:name":"Sveti Lenart",
    "gn:population":36,
    "gn:timezone":"Europe/Ljubljana",
    "iso:country":"SI",
    "wof:name":"Sveti Lenart",
    "wof:placetype":"locality",
    "wof:population":36
},
  "geometry": {"coordinates":[14.54937,46.26979],"type":"Point"}
}