{
  "type": "Feature",
  "properties": {
    "gn:admin1_code":"C5",
    "gn:asciiname":"Lekmarje",
    "gn:country_code":"SI",
    "gn:dem":348,
    "gn:feature_class":"P",
    "gn:feature_code":"PPL",
    "gn:name":"Lekmarje",
    "gn:population":58,
    "gn:timezone":"Europe/Ljubljana",
    "iso:country":"SI",
    "name:bos_x_preferred":[
        "Lekmarje"
    ],
    "name:hrv_x_preferred":[
        "Lekmarje"
    ],
    "name:nld_x_preferred":[
        "Lekmarje"
    ],
    "name:pol_x_preferred":[
        "Lekmarje"
    ],
    "name:ron_x_preferred":[
        "Lekmarje"
    ],
    "name:slv_x_preferred":[
        "Lekmarje"
    ],
    "name:ukr_x_preferred":[
        "\u041b\u0435\u043a\u043c\u0430\u0440\u0454"
    ],
    "wof:name":"Lekmarje",
    "wof:placetype":"locality",
    "wof:population":58
},
  "geometry": {"coordinates":[15.50502,46.19157],"type":"Point"}
}