{
  "type": "Feature",
  "properties": {
    "gn:admin1_code":"09",
    "gn:asciiname":"Zabnica",
    "gn:country_code":"SI",
    "gn:dem":291,
    "gn:feature_class":"P",
    "gn:feature_code":"PPL",
    "gn:name":"\u017dabnica",
    "gn:population":299,
    "gn:timezone":"Europe/Ljubljana",
    "iso:country":"SI",
    "name:bos_x_preferred":[
        "\u017dabnica"
    ],
    "name:ceb_x_preferred":[
        "\u017dabnica"
    ],
    "name:nld_x_preferred":[
        "\u017dabnica"
    ],
    "name:pol_x_preferred":[
        "\u017dabnica"
    ],
    "name:ron_x_preferred":[
        "\u017dabnica"
    ],
    "name:slv_x_preferred":[
        "\u017dabnica"
    ],
    "name:ukr_x_preferred":[
        "\u0416\u0430\u0431\u043d\u0438\u0446\u044f"
    ],
    "name:und_x_variant":[
        "\u017dabnica"
    ],
    "name:urd_x_preferred":[
        "\u0698\u0627\u0628\u0646\u06cc\u062a\u0633\u0627"
    ],
    "wof:name":"Zabnica",
    "wof:placetype":"locality",
    "wof:population":299
},
  "geometry": {"coordinates":[14.40305,46.00155],"type":"Point"}
}