{
  "type": "Feature",
  "properties": {
    "gn:admin1_code":"09",
    "gn:asciiname":"Zabnica",
    "gn:country_code":"SI",
    "gn:dem":291,
    "gn:feature_class":"P",
    "gn:feature_code":"PPL",
    "gn:name":"\u017dabnica",
    "gn:population":299,
    "gn:timezone":"Europe/Ljubljana",
    "iso:country":"SI",
    "name:und_x_variant":[
        "\u017dabnica"
    ],
    "wof:name":"Zabnica",
    "wof:placetype":"locality",
    "wof:population":299
},
  "geometry": {"coordinates":[14.40305,46.00155],"type":"Point"}
}