{
  "type": "Feature",
  "properties": {
    "gn:admin1_code":"N9",
    "gn:asciiname":"Zgornje Konjisce",
    "gn:country_code":"SI",
    "gn:dem":226,
    "gn:feature_class":"P",
    "gn:feature_code":"PPL",
    "gn:name":"Zgornje Konji\u0161\u010de",
    "gn:population":95,
    "gn:timezone":"Europe/Ljubljana",
    "iso:country":"SI",
    "name:bos_x_preferred":[
        "Zgornje Konji\u0161\u010de"
    ],
    "name:ces_x_preferred":[
        "Zgornje Konji\u0161\u010de"
    ],
    "name:hrv_x_preferred":[
        "Zgornje Konji\u0161\u010de"
    ],
    "name:nld_x_preferred":[
        "Zgornje Konji\u0161\u010de"
    ],
    "name:pol_x_preferred":[
        "Zgornje Konji\u0161\u010de"
    ],
    "name:ron_x_preferred":[
        "Zgornje Konji\u0161\u010de"
    ],
    "name:slv_x_preferred":[
        "Zgornje Konji\u0161\u010de"
    ],
    "name:ukr_x_preferred":[
        "\u0417\u0433\u043e\u0440\u043d\u0454 \u041a\u043e\u043d\u0456\u0449\u0435"
    ],
    "name:und_x_variant":[
        "Zgornje Konji\u0161\u010de"
    ],
    "wof:name":"Zgornje Konjisce",
    "wof:placetype":"locality",
    "wof:population":95
},
  "geometry": {"coordinates":[15.82582,46.7141],"type":"Point"}
}