{
  "type": "Feature",
  "properties": {
    "gn:admin1_code":"01",
    "gn:asciiname":"Koboli",
    "gn:country_code":"SI",
    "gn:dem":271,
    "gn:feature_class":"P",
    "gn:feature_code":"PPL",
    "gn:name":"Koboli",
    "gn:population":18,
    "gn:timezone":"Europe/Ljubljana",
    "iso:country":"SI",
    "name:bos_x_preferred":[
        "Koboli"
    ],
    "name:nld_x_preferred":[
        "Koboli"
    ],
    "name:pol_x_preferred":[
        "Koboli"
    ],
    "name:ron_x_preferred":[
        "Koboli"
    ],
    "name:slv_x_preferred":[
        "Koboli"
    ],
    "name:ukr_x_preferred":[
        "\u041a\u043e\u0431\u043e\u043b\u0456"
    ],
    "name:und_x_variant":[
        "Kobali",
        "Koboli"
    ],
    "wof:name":"Koboli",
    "wof:placetype":"locality",
    "wof:population":18
},
  "geometry": {"coordinates":[13.87825,45.81592],"type":"Point"}
}