{
  "type": "Feature",
  "properties": {
    "gn:admin1_code":"C4",
    "gn:asciiname":"Prezigal",
    "gn:country_code":"SI",
    "gn:dem":291,
    "gn:feature_class":"P",
    "gn:feature_code":"PPL",
    "gn:name":"Pre\u017eigal",
    "gn:population":23,
    "gn:timezone":"Europe/Ljubljana",
    "iso:country":"SI",
    "name:bos_x_preferred":[
        "Pre\u017eigal"
    ],
    "name:hrv_x_preferred":[
        "Pre\u017eigal"
    ],
    "name:nld_x_preferred":[
        "Pre\u017eigal"
    ],
    "name:pol_x_preferred":[
        "Pre\u017eigal"
    ],
    "name:ron_x_preferred":[
        "Pre\u017eigal"
    ],
    "name:slv_x_preferred":[
        "Pre\u017eigal"
    ],
    "name:ukr_x_preferred":[
        "\u041f\u0440\u0435\u0436\u0438\u0433\u0430\u043b"
    ],
    "name:und_x_variant":[
        "Pre\u017eigal"
    ],
    "wof:name":"Prezigal",
    "wof:placetype":"locality",
    "wof:population":23
},
  "geometry": {"coordinates":[15.46322,46.33517],"type":"Point"}
}