{
  "type": "Feature",
  "properties": {
    "gn:admin1_code":"71",
    "gn:asciiname":"Studencice",
    "gn:country_code":"SI",
    "gn:dem":566,
    "gn:feature_class":"P",
    "gn:feature_code":"PPL",
    "gn:name":"Studen\u010dice",
    "gn:population":150,
    "gn:timezone":"Europe/Ljubljana",
    "iso:country":"SI",
    "name:bos_x_preferred":[
        "Studen\u010dice"
    ],
    "name:ceb_x_preferred":[
        "Studen\u010dice"
    ],
    "name:nld_x_preferred":[
        "Studen\u010dice"
    ],
    "name:pol_x_preferred":[
        "Studen\u010dice"
    ],
    "name:ron_x_preferred":[
        "Studen\u010dice"
    ],
    "name:slv_x_preferred":[
        "Studen\u010dice"
    ],
    "name:srp_x_preferred":[
        "\u0421\u0442\u0443\u0434\u0435\u043d\u0447\u0438\u0446\u0435"
    ],
    "name:ukr_x_preferred":[
        "\u0421\u0442\u0443\u0434\u0435\u043d\u0447\u0438\u0446\u0435"
    ],
    "name:und_x_variant":[
        "Studen\u010dice"
    ],
    "wof:name":"Studencice",
    "wof:placetype":"locality",
    "wof:population":150
},
  "geometry": {"coordinates":[14.37116,46.12531],"type":"Point"}
}