{
  "type": "Feature",
  "properties": {
    "gn:admin1_code":"11",
    "gn:asciiname":"Lancberk",
    "gn:country_code":"SI",
    "gn:dem":489,
    "gn:feature_class":"P",
    "gn:feature_code":"PPL",
    "gn:name":"Lancberk",
    "gn:population":0,
    "gn:timezone":"Europe/Ljubljana",
    "iso:country":"SI",
    "wof:name":"Lancberk",
    "wof:placetype":"locality"
},
  "geometry": {"coordinates":[15.23278,46.31917],"type":"Point"}
}