{
  "type": "Feature",
  "properties": {
    "gn:admin1_code":"D1",
    "gn:asciiname":"Dragotinci",
    "gn:country_code":"SI",
    "gn:dem":203,
    "gn:feature_class":"P",
    "gn:feature_code":"PPL",
    "gn:name":"Dragotinci",
    "gn:population":130,
    "gn:timezone":"Europe/Ljubljana",
    "iso:country":"SI",
    "name:bos_x_preferred":[
        "Dragotinci"
    ],
    "name:ceb_x_preferred":[
        "Dragotinci"
    ],
    "name:hrv_x_preferred":[
        "Dragotinci"
    ],
    "name:nld_x_preferred":[
        "Dragotinci"
    ],
    "name:pol_x_preferred":[
        "Dragotinci"
    ],
    "name:ron_x_preferred":[
        "Dragotinci"
    ],
    "name:slv_x_preferred":[
        "Dragotinci"
    ],
    "name:ukr_x_preferred":[
        "\u0414\u0440\u0430\u0433\u043e\u0442\u0438\u043d\u0446\u0456"
    ],
    "wof:name":"Dragotinci",
    "wof:placetype":"locality",
    "wof:population":130
},
  "geometry": {"coordinates":[16.03639,46.58361],"type":"Point"}
}