{
  "type": "Feature",
  "properties": {
    "iso:country":"SI",
    "name:slv_x_preferred":[
        "Spodnja Hru\u0161ica"
    ],
    "wof:name":"Spodnja Hrusica",
    "wof:placetype":"neighbourhood"
},
  "geometry": {"coordinates":[14.55937395346116,46.04251773320505],"type":"Point"}
}