{
  "type": "Feature",
  "properties": {
    "gn:admin1_code":"J8",
    "gn:asciiname":"Raskovec",
    "gn:country_code":"SI",
    "gn:dem":328,
    "gn:feature_class":"P",
    "gn:feature_code":"PPL",
    "gn:name":"Raskovec",
    "gn:population":72,
    "gn:timezone":"Europe/Ljubljana",
    "iso:country":"SI",
    "wof:name":"Raskovec",
    "wof:placetype":"locality",
    "wof:population":72
},
  "geometry": {"coordinates":[15.47569,46.37273],"type":"Point"}
}