{
  "type": "Feature",
  "properties": {
    "gn:admin1_code":"57",
    "gn:asciiname":"Lahov Graben",
    "gn:country_code":"SI",
    "gn:dem":694,
    "gn:feature_class":"P",
    "gn:feature_code":"PPL",
    "gn:name":"Lahov Graben",
    "gn:population":122,
    "gn:timezone":"Europe/Ljubljana",
    "iso:country":"SI",
    "wof:name":"Lahov Graben",
    "wof:placetype":"locality",
    "wof:population":122
},
  "geometry": {"coordinates":[15.31554,46.09094],"type":"Point"}
}