{
  "type": "Feature",
  "properties": {
    "gn:admin1_code":"57",
    "gn:asciiname":"Lahov Graben",
    "gn:country_code":"SI",
    "gn:dem":694,
    "gn:feature_class":"P",
    "gn:feature_code":"PPL",
    "gn:name":"Lahov Graben",
    "gn:population":122,
    "gn:timezone":"Europe/Ljubljana",
    "iso:country":"SI",
    "name:bos_x_preferred":[
        "Lahov Graben"
    ],
    "name:ceb_x_preferred":[
        "Lahov Graben"
    ],
    "name:hrv_x_preferred":[
        "Lahov Graben"
    ],
    "name:nld_x_preferred":[
        "Lahov Graben"
    ],
    "name:pol_x_preferred":[
        "Lahov Graben"
    ],
    "name:ron_x_preferred":[
        "Lahov Graben"
    ],
    "name:slv_x_preferred":[
        "Lahov Graben"
    ],
    "name:ukr_x_preferred":[
        "\u041b\u0430\u0445\u043e\u0432 \u0413\u0440\u0430\u0431\u0435\u043d"
    ],
    "name:urd_x_preferred":[
        "\u0644\u0627\u06c1\u0648\u0648 \u06af\u0631\u0627\u0628\u06cc\u0646"
    ],
    "wof:name":"Lahov Graben",
    "wof:placetype":"locality",
    "wof:population":122
},
  "geometry": {"coordinates":[15.31554,46.09094],"type":"Point"}
}