{
  "type": "Feature",
  "properties": {
    "gn:admin1_code":"01",
    "gn:asciiname":"Bacarji",
    "gn:country_code":"SI",
    "gn:dem":90,
    "gn:feature_class":"P",
    "gn:feature_code":"PPLL",
    "gn:name":"Ba\u010darji",
    "gn:population":0,
    "gn:timezone":"Europe/Ljubljana",
    "iso:country":"SI",
    "wof:name":"Bacarji",
    "wof:placetype":"locality"
},
  "geometry": {"coordinates":[13.89755,45.86515],"type":"Point"}
}