{
  "type": "Feature",
  "properties": {
    "gn:admin1_code":"H6",
    "gn:asciiname":"Spodnje Palovce",
    "gn:country_code":"SI",
    "gn:dem":721,
    "gn:feature_class":"P",
    "gn:feature_code":"PPL",
    "gn:name":"Spodnje Palov\u010de",
    "gn:population":80,
    "gn:timezone":"Europe/Ljubljana",
    "iso:country":"SI",
    "name:und_x_variant":[
        "Spodnje Palovi\u010de",
        "Spodnje Palov\u010de"
    ],
    "wof:name":"Spodnje Palovce",
    "wof:placetype":"locality",
    "wof:population":80
},
  "geometry": {"coordinates":[14.66667,46.21667],"type":"Point"}
}