{
  "type": "Feature",
  "properties": {
    "gn:admin1_code":"44",
    "gn:asciiname":"Vrtace",
    "gn:country_code":"SI",
    "gn:dem":640,
    "gn:feature_class":"P",
    "gn:feature_code":"PPL",
    "gn:name":"Vrta\u010de",
    "gn:population":0,
    "gn:timezone":"Europe/Ljubljana",
    "iso:country":"SI",
    "name:slv_x_historical":[
        "Vrta\u010da"
    ],
    "name:slv_x_preferred":[
        "Vrta\u010da"
    ],
    "wof:name":"Vrtace",
    "wof:placetype":"locality"
},
  "geometry": {"coordinates":[13.57193,46.06454],"type":"Point"}
}