{
  "type": "Feature",
  "properties": {
    "gn:admin1_code":"G1",
    "gn:asciiname":"Gomilci",
    "gn:country_code":"SI",
    "gn:dem":274,
    "gn:feature_class":"P",
    "gn:feature_code":"PPL",
    "gn:name":"Gomilci",
    "gn:population":65,
    "gn:timezone":"Europe/Ljubljana",
    "iso:country":"SI",
    "wof:name":"Gomilci",
    "wof:placetype":"locality",
    "wof:population":65
},
  "geometry": {"coordinates":[15.90014,46.49126],"type":"Point"}
}