{
  "type": "Feature",
  "properties": {
    "gn:admin1_code":"G1",
    "gn:asciiname":"Gomilci",
    "gn:country_code":"SI",
    "gn:dem":274,
    "gn:feature_class":"P",
    "gn:feature_code":"PPL",
    "gn:name":"Gomilci",
    "gn:population":65,
    "gn:timezone":"Europe/Ljubljana",
    "iso:country":"SI",
    "name:bos_x_preferred":[
        "Gomilci"
    ],
    "name:nld_x_preferred":[
        "Gomilci"
    ],
    "name:pol_x_preferred":[
        "Gomilci"
    ],
    "name:ron_x_preferred":[
        "Gomilci"
    ],
    "name:slv_x_preferred":[
        "Gomilci"
    ],
    "name:ukr_x_preferred":[
        "\u0413\u043e\u043c\u0438\u043b\u0446\u0456"
    ],
    "wof:name":"Gomilci",
    "wof:placetype":"locality",
    "wof:population":65
},
  "geometry": {"coordinates":[15.90014,46.49126],"type":"Point"}
}