{
  "type": "Feature",
  "properties": {
    "gn:admin1_code":"O3",
    "gn:asciiname":"Avgustine",
    "gn:country_code":"SI",
    "gn:dem":323,
    "gn:feature_class":"P",
    "gn:feature_code":"PPL",
    "gn:name":"Avgu\u0161tine",
    "gn:population":30,
    "gn:timezone":"Europe/Ljubljana",
    "iso:country":"SI",
    "name:bos_x_preferred":[
        "Avgu\u0161tine"
    ],
    "name:ita_x_preferred":[
        "Avgu\u0161tine"
    ],
    "name:nld_x_preferred":[
        "Avgu\u0161tine"
    ],
    "name:pol_x_preferred":[
        "Avgu\u0161tine"
    ],
    "name:ron_x_preferred":[
        "Avgu\u0161tine"
    ],
    "name:slv_x_preferred":[
        "Avgu\u0161tine"
    ],
    "name:ukr_x_preferred":[
        "\u0410\u0432\u0433\u0443\u0448\u0442\u0438\u043d\u0435"
    ],
    "name:und_x_variant":[
        "Avgu\u0161tine"
    ],
    "wof:name":"Avgustine",
    "wof:placetype":"locality",
    "wof:population":30
},
  "geometry": {"coordinates":[15.44171,45.83782],"type":"Point"}
}