{
  "type": "Feature",
  "properties": {
    "gn:admin1_code":"L8",
    "gn:asciiname":"Kovaca Vas",
    "gn:country_code":"SI",
    "gn:dem":383,
    "gn:feature_class":"P",
    "gn:feature_code":"PPL",
    "gn:name":"Kova\u010da Vas",
    "gn:population":557,
    "gn:timezone":"Europe/Ljubljana",
    "iso:country":"SI",
    "name:bos_x_preferred":[
        "Kova\u010da vas"
    ],
    "name:ceb_x_preferred":[
        "Kova\u010da Vas"
    ],
    "name:nld_x_preferred":[
        "Kova\u010da vas"
    ],
    "name:pol_x_preferred":[
        "Kova\u010da vas"
    ],
    "name:ron_x_preferred":[
        "Kova\u010da vas"
    ],
    "name:slv_x_preferred":[
        "Kova\u010da vas"
    ],
    "name:ukr_x_preferred":[
        "\u041a\u043e\u0432\u0430\u0447\u0430 \u0412\u0430\u0441"
    ],
    "wof:name":"Kovaca Vas",
    "wof:placetype":"locality",
    "wof:population":557
},
  "geometry": {"coordinates":[15.5595,46.41073],"type":"Point"}
}