{
  "type": "Feature",
  "properties": {
    "gn:admin1_code":"L8",
    "gn:asciiname":"Kovaca Vas",
    "gn:country_code":"SI",
    "gn:dem":383,
    "gn:feature_class":"P",
    "gn:feature_code":"PPL",
    "gn:name":"Kova\u010da Vas",
    "gn:population":557,
    "gn:timezone":"Europe/Ljubljana",
    "iso:country":"SI",
    "name:und_x_variant":[
        "Kova\u010da Vas"
    ],
    "wof:name":"Kovaca Vas",
    "wof:placetype":"locality",
    "wof:population":557
},
  "geometry": {"coordinates":[15.5595,46.41073],"type":"Point"}
}