{
  "type": "Feature",
  "properties": {
    "gn:admin1_code":"L7",
    "gn:asciiname":"Cerovec",
    "gn:country_code":"SI",
    "gn:dem":285,
    "gn:feature_class":"P",
    "gn:feature_code":"PPL",
    "gn:name":"Cerovec",
    "gn:population":146,
    "gn:timezone":"Europe/Ljubljana",
    "iso:country":"SI",
    "name:bos_x_preferred":[
        "Cerovec"
    ],
    "name:ceb_x_preferred":[
        "Cerovec"
    ],
    "name:hrv_x_preferred":[
        "Cerovec"
    ],
    "name:nld_x_preferred":[
        "Cerovec"
    ],
    "name:pol_x_preferred":[
        "Cerovec"
    ],
    "name:ron_x_preferred":[
        "Cerovec"
    ],
    "name:slv_x_preferred":[
        "Cerovec"
    ],
    "name:ukr_x_preferred":[
        "\u0426\u0435\u0440\u043e\u0432\u0435\u0446\u044c"
    ],
    "wof:name":"Cerovec",
    "wof:placetype":"locality",
    "wof:population":146
},
  "geometry": {"coordinates":[15.36171,46.25355],"type":"Point"}
}