{
  "type": "Feature",
  "properties": {
    "gn:admin1_code":"L7",
    "gn:asciiname":"Cerovec",
    "gn:country_code":"SI",
    "gn:dem":285,
    "gn:feature_class":"P",
    "gn:feature_code":"PPL",
    "gn:name":"Cerovec",
    "gn:population":146,
    "gn:timezone":"Europe/Ljubljana",
    "iso:country":"SI",
    "wof:name":"Cerovec",
    "wof:placetype":"locality",
    "wof:population":146
},
  "geometry": {"coordinates":[15.36171,46.25355],"type":"Point"}
}