{
  "type": "Feature",
  "properties": {
    "gn:admin1_code":"39",
    "gn:asciiname":"Zaborst pri Sentvidu",
    "gn:country_code":"SI",
    "gn:dem":358,
    "gn:feature_class":"P",
    "gn:feature_code":"PPL",
    "gn:name":"Zabor\u0161t pri \u0160entvidu",
    "gn:population":90,
    "gn:timezone":"Europe/Ljubljana",
    "iso:country":"SI",
    "name:bos_x_preferred":[
        "Zabor\u0161t pri \u0160entvidu"
    ],
    "name:nld_x_preferred":[
        "Zabor\u0161t pri \u0160entvidu"
    ],
    "name:pol_x_preferred":[
        "Zabor\u0161t pri \u0160entvidu"
    ],
    "name:ron_x_preferred":[
        "Zabor\u0161t pri \u0160entvidu"
    ],
    "name:slv_x_preferred":[
        "Zabor\u0161t pri \u0160entvidu"
    ],
    "name:ukr_x_preferred":[
        "\u0417\u0430\u0431\u043e\u0440\u0448\u0442-\u043f\u0440\u0438-\u0428\u0435\u043d\u0442\u0432\u0438\u0434\u0443"
    ],
    "name:und_x_variant":[
        "Zabor\u0161t",
        "Zabor\u0161t pri \u0160entvidu"
    ],
    "name:urd_x_preferred":[
        "\u0632\u0628\u0648\u0631\u0634\u062a \u067e\u0631 \u0634\u06cc\u0646\u062a\u0648\u062f\u0648"
    ],
    "wof:name":"Zaborst pri Sentvidu",
    "wof:placetype":"locality",
    "wof:population":90
},
  "geometry": {"coordinates":[14.87,45.96472],"type":"Point"}
}