{
  "type": "Feature",
  "properties": {
    "gn:admin1_code":"39",
    "gn:asciiname":"Zaborst pri Sentvidu",
    "gn:country_code":"SI",
    "gn:dem":358,
    "gn:feature_class":"P",
    "gn:feature_code":"PPL",
    "gn:name":"Zabor\u0161t pri \u0160entvidu",
    "gn:population":90,
    "gn:timezone":"Europe/Ljubljana",
    "iso:country":"SI",
    "name:und_x_variant":[
        "Zabor\u0161t",
        "Zabor\u0161t pri \u0160entvidu"
    ],
    "wof:name":"Zaborst pri Sentvidu",
    "wof:placetype":"locality",
    "wof:population":90
},
  "geometry": {"coordinates":[14.87,45.96472],"type":"Point"}
}