{
  "type": "Feature",
  "properties": {
    "gn:population":2862,
    "iso:country":"SI",
    "name:bos_x_preferred":[
        "Brezovica pri Ljubljani"
    ],
    "name:dut_x_preferred":[
        "Brezovica pri Ljubljani"
    ],
    "name:eng_x_preferred":[
        "Brezovica pri Ljubljani"
    ],
    "name:hbs_x_preferred":[
        "Brezovica pri Ljubljani"
    ],
    "name:nld_x_preferred":[
        "Brezovica pri Ljubljani"
    ],
    "name:ron_x_preferred":[
        "Brezovica pri Ljubljani"
    ],
    "name:rum_x_preferred":[
        "Brezovica pri Ljubljani"
    ],
    "name:slv_x_preferred":[
        "Brezovica pri Ljubljani"
    ],
    "name:srp_x_preferred":[
        "\u0411\u0440\u0435\u0437\u043e\u0432\u0438\u0446\u0430 \u043f\u0440\u0438 \u0409\u0443\u0431\u0459\u0430\u043d\u0438"
    ],
    "name:ukr_x_preferred":[
        "\u0411\u0440\u0435\u0437\u043e\u0432\u0438\u0446\u044f-\u043f\u0440\u0438-\u041b\u044e\u0431\u043b\u044f\u043d\u0456"
    ],
    "name:unk_x_variant":[
        "Brezovica"
    ],
    "name:urd_x_preferred":[
        "\u0628\u0631\u06cc\u0632\u0648\u0648\u06cc\u062a\u0633\u0627 \u067e\u0631\u06cc \u0644\u06cc\u0648\u0628\u0644\u06cc\u0627\u0646\u06cc"
    ],
    "qs:a0":"Slovenija",
    "qs:a1":"*",
    "qs:a1r":"0",
    "qs:adm0":"Slovenija",
    "qs:la_lc":"*",
    "qs:level":"locality",
    "qs:loc":"Brezovica pri Ljubljani",
    "qs:loc_alt":"Brezovica pri Ljubljani",
    "qs:pop":0,
    "qs:type":"buffered point",
    "qs_pg:aaroncc":"SI",
    "qs_pg:name":"Brezovica Pri Ljubljani",
    "qs_pg:name_adm0":"Slovenija",
    "qs_pg:name_adm1":"Ljubljana",
    "qs_pg:photos":13,
    "qs_pg:photos_1k":3,
    "qs_pg:photos_9k":1,
    "qs_pg:photos_9r":1,
    "qs_pg:photos_all":13,
    "qs_pg:photos_sr":1,
    "qs_pg:pop_sr":0,
    "qs_pg:qs_pg_placetype":"locality",
    "qs_pg:qs_pg_placetype_gp":"Town",
    "qs_pg:woe_adm0":23424945,
    "wd:wordcount":472,
    "wof:name":"Brezovica pri Ljubljani",
    "wof:placetype":"locality",
    "wof:population":2862
},
  "geometry": {"coordinates":[14.414683,46.030624],"type":"Point"}
}