{
  "type": "Feature",
  "properties": {
    "gn:admin1_code":"H7",
    "gn:asciiname":"Podjetnisko Naselje Kocevje",
    "gn:country_code":"SI",
    "gn:dem":469,
    "gn:feature_class":"P",
    "gn:feature_code":"PPL",
    "gn:name":"Podjetni\u0161ko Naselje Ko\u010devje",
    "gn:population":0,
    "gn:timezone":"Europe/Ljubljana",
    "iso:country":"SI",
    "name:bos_x_preferred":[
        "Podjetni\u0161ko naselje Ko\u010devje"
    ],
    "name:pol_x_preferred":[
        "Podjetni\u0161ko naselje Ko\u010devje"
    ],
    "name:slv_x_preferred":[
        "Podjetni\u0161ko naselje Ko\u010devje"
    ],
    "name:und_x_variant":[
        "Podjetni\u0161ko Naselje Ko\u010devje"
    ],
    "wof:name":"Podjetnisko Naselje Kocevje",
    "wof:placetype":"locality"
},
  "geometry": {"coordinates":[14.8501,45.65459],"type":"Point"}
}