{
  "type": "Feature",
  "properties": {
    "gn:admin1_code":"I5",
    "gn:asciiname":"Slavina",
    "gn:country_code":"SI",
    "gn:dem":644,
    "gn:feature_class":"P",
    "gn:feature_code":"PPL",
    "gn:name":"Slavina",
    "gn:population":17,
    "gn:timezone":"Europe/Ljubljana",
    "iso:country":"SI",
    "name:bos_x_preferred":[
        "Slavina"
    ],
    "name:bul_x_preferred":[
        "\u0421\u043b\u0430\u0432\u0438\u043d\u0430"
    ],
    "name:nld_x_preferred":[
        "Slavina"
    ],
    "name:pol_x_preferred":[
        "Slavina"
    ],
    "name:ron_x_preferred":[
        "Slavina"
    ],
    "name:slv_x_preferred":[
        "Slavina"
    ],
    "name:ukr_x_preferred":[
        "\u0421\u043b\u0430\u0432\u0438\u043d\u0430"
    ],
    "wof:name":"Slavina",
    "wof:placetype":"locality",
    "wof:population":17
},
  "geometry": {"coordinates":[15.04739,46.0244],"type":"Point"}
}