{
  "type": "Feature",
  "properties": {
    "gn:admin1_code":"89",
    "gn:asciiname":"Vosek",
    "gn:country_code":"SI",
    "gn:dem":261,
    "gn:feature_class":"P",
    "gn:feature_code":"PPL",
    "gn:name":"Vosek",
    "gn:population":317,
    "gn:timezone":"Europe/Ljubljana",
    "iso:country":"SI",
    "name:bos_x_preferred":[
        "Vosek"
    ],
    "name:ceb_x_preferred":[
        "Vosek"
    ],
    "name:nld_x_preferred":[
        "Vosek"
    ],
    "name:pol_x_preferred":[
        "Vosek"
    ],
    "name:ron_x_preferred":[
        "Vosek"
    ],
    "name:slv_x_preferred":[
        "Vosek"
    ],
    "name:ukr_x_preferred":[
        "\u0412\u043e\u0441\u0435\u043a"
    ],
    "wof:name":"Vosek",
    "wof:placetype":"locality",
    "wof:population":317
},
  "geometry": {"coordinates":[15.71618,46.59178],"type":"Point"}
}