{
  "type": "Feature",
  "properties": {
    "gn:admin1_code":"L7",
    "gn:asciiname":"Prapretno",
    "gn:country_code":"SI",
    "gn:dem":599,
    "gn:feature_class":"P",
    "gn:feature_code":"PPL",
    "gn:name":"Prapretno",
    "gn:population":83,
    "gn:timezone":"Europe/Ljubljana",
    "iso:country":"SI",
    "name:bos_x_preferred":[
        "Prapretno"
    ],
    "name:hrv_x_preferred":[
        "Prapretno"
    ],
    "name:nld_x_preferred":[
        "Prapretno"
    ],
    "name:pol_x_preferred":[
        "Prapretno"
    ],
    "name:ron_x_preferred":[
        "Prapretno"
    ],
    "name:slv_x_preferred":[
        "Prapretno"
    ],
    "name:ukr_x_preferred":[
        "\u041f\u0440\u0430\u043f\u0440\u0435\u0442\u043d\u043e"
    ],
    "wof:name":"Prapretno",
    "wof:placetype":"locality",
    "wof:population":83
},
  "geometry": {"coordinates":[15.37668,46.07964000000001],"type":"Point"}
}