{
  "type": "Feature",
  "properties": {
    "gn:admin1_code":"08",
    "gn:asciiname":"Cundrovec",
    "gn:country_code":"SI",
    "gn:dem":152,
    "gn:feature_class":"P",
    "gn:feature_code":"PPL",
    "gn:name":"Cundrovec",
    "gn:population":131,
    "gn:timezone":"Europe/Ljubljana",
    "iso:country":"SI",
    "wof:name":"Cundrovec",
    "wof:placetype":"locality",
    "wof:population":131
},
  "geometry": {"coordinates":[15.61146,45.92994],"type":"Point"}
}