{
  "type": "Feature",
  "properties": {
    "gn:admin1_code":"08",
    "gn:asciiname":"Cundrovec",
    "gn:country_code":"SI",
    "gn:dem":152,
    "gn:feature_class":"P",
    "gn:feature_code":"PPL",
    "gn:name":"Cundrovec",
    "gn:population":131,
    "gn:timezone":"Europe/Ljubljana",
    "iso:country":"SI",
    "name:bos_x_preferred":[
        "Cundrovec"
    ],
    "name:ceb_x_preferred":[
        "Cundrovec"
    ],
    "name:hrv_x_preferred":[
        "Cundrovec"
    ],
    "name:pol_x_preferred":[
        "Cundrovec"
    ],
    "name:ron_x_preferred":[
        "Cundrovec"
    ],
    "name:slv_x_preferred":[
        "Cundrovec"
    ],
    "name:ukr_x_preferred":[
        "\u0426\u0443\u043d\u0434\u0440\u043e\u0432\u0435\u0446\u044c"
    ],
    "wof:name":"Cundrovec",
    "wof:placetype":"locality",
    "wof:population":131
},
  "geometry": {"coordinates":[15.61146,45.92994],"type":"Point"}
}