{
  "type": "Feature",
  "properties": {
    "gn:admin1_code":"D7",
    "gn:asciiname":"Paski Kozjak",
    "gn:country_code":"SI",
    "gn:dem":813,
    "gn:feature_class":"P",
    "gn:feature_code":"PPL",
    "gn:name":"Pa\u0161ki Kozjak",
    "gn:population":234,
    "gn:timezone":"Europe/Ljubljana",
    "iso:country":"SI",
    "name:bos_x_preferred":[
        "Pa\u0161ki Kozjak"
    ],
    "name:ceb_x_preferred":[
        "Pa\u0161ki Kozjak"
    ],
    "name:hrv_x_preferred":[
        "Pa\u0161ki Kozjak"
    ],
    "name:ita_x_preferred":[
        "Pa\u0161ki Kozjak"
    ],
    "name:mkd_x_preferred":[
        "\u041f\u0430\u0448\u043a\u0438 \u041a\u043e\u0437\u0458\u0430\u043a"
    ],
    "name:nld_x_preferred":[
        "Pa\u0161ki Kozjak"
    ],
    "name:pol_x_preferred":[
        "Pa\u0161ki Kozjak"
    ],
    "name:ron_x_preferred":[
        "Pa\u0161ki Kozjak"
    ],
    "name:slv_x_preferred":[
        "Pa\u0161ki Kozjak"
    ],
    "name:ukr_x_preferred":[
        "\u041f\u0430\u0448\u043a\u0438\u0439 \u041a\u043e\u0437\u044f\u043a"
    ],
    "name:und_x_variant":[
        "Pa\u0161ki Kozjak"
    ],
    "wof:name":"Paski Kozjak",
    "wof:placetype":"locality",
    "wof:population":234
},
  "geometry": {"coordinates":[15.17992,46.37559],"type":"Point"}
}