{
  "type": "Feature",
  "properties": {
    "gn:admin1_code":"D7",
    "gn:asciiname":"Paski Kozjak",
    "gn:country_code":"SI",
    "gn:dem":813,
    "gn:feature_class":"P",
    "gn:feature_code":"PPL",
    "gn:name":"Pa\u0161ki Kozjak",
    "gn:population":234,
    "gn:timezone":"Europe/Ljubljana",
    "iso:country":"SI",
    "name:und_x_variant":[
        "Pa\u0161ki Kozjak"
    ],
    "wof:name":"Paski Kozjak",
    "wof:placetype":"locality",
    "wof:population":234
},
  "geometry": {"coordinates":[15.17992,46.37559],"type":"Point"}
}