{
  "type": "Feature",
  "properties": {
    "gn:admin1_code":"52",
    "gn:asciiname":"Trstenik",
    "gn:country_code":"SI",
    "gn:dem":511,
    "gn:feature_class":"P",
    "gn:feature_code":"PPL",
    "gn:name":"Trstenik",
    "gn:population":375,
    "gn:timezone":"Europe/Ljubljana",
    "iso:country":"SI",
    "wof:name":"Trstenik",
    "wof:placetype":"locality",
    "wof:population":375
},
  "geometry": {"coordinates":[14.37,46.31833],"type":"Point"}
}