{
  "type": "Feature",
  "properties": {
    "gn:admin1_code":"52",
    "gn:asciiname":"Trstenik",
    "gn:country_code":"SI",
    "gn:dem":511,
    "gn:feature_class":"P",
    "gn:feature_code":"PPL",
    "gn:name":"Trstenik",
    "gn:population":375,
    "gn:timezone":"Europe/Ljubljana",
    "iso:country":"SI",
    "name:bos_x_preferred":[
        "Trstenik"
    ],
    "name:ceb_x_preferred":[
        "Trstenik"
    ],
    "name:hrv_x_preferred":[
        "Trstenik"
    ],
    "name:nld_x_preferred":[
        "Trstenik"
    ],
    "name:pol_x_preferred":[
        "Trstenik"
    ],
    "name:ron_x_preferred":[
        "Trstenik"
    ],
    "name:slv_x_preferred":[
        "Trstenik"
    ],
    "name:ukr_x_preferred":[
        "\u0422\u0440\u0441\u0442\u0435\u043d\u0438\u043a"
    ],
    "wof:name":"Trstenik",
    "wof:placetype":"locality",
    "wof:population":375
},
  "geometry": {"coordinates":[14.37,46.31833],"type":"Point"}
}