{
  "type": "Feature",
  "properties": {
    "gn:admin1_code":"O3",
    "gn:asciiname":"Kocarija",
    "gn:country_code":"SI",
    "gn:dem":245,
    "gn:feature_class":"P",
    "gn:feature_code":"PPL",
    "gn:name":"Ko\u010darija",
    "gn:population":65,
    "gn:timezone":"Europe/Ljubljana",
    "iso:country":"SI",
    "name:bos_x_preferred":[
        "Ko\u010darija"
    ],
    "name:ita_x_preferred":[
        "Ko\u010darija"
    ],
    "name:nld_x_preferred":[
        "Ko\u010darija"
    ],
    "name:pol_x_preferred":[
        "Ko\u010darija"
    ],
    "name:ron_x_preferred":[
        "Ko\u010darija"
    ],
    "name:slv_x_preferred":[
        "Ko\u010darija"
    ],
    "name:ukr_x_preferred":[
        "\u041a\u043e\u0447\u0430\u0440\u0456\u044f"
    ],
    "wof:name":"Kocarija",
    "wof:placetype":"locality",
    "wof:population":65
},
  "geometry": {"coordinates":[15.39906,45.83145],"type":"Point"}
}