{
  "type": "Feature",
  "properties": {
    "gn:admin1_code":"B7",
    "gn:asciiname":"Rasa",
    "gn:country_code":"SI",
    "gn:dem":344,
    "gn:feature_class":"P",
    "gn:feature_code":"PPL",
    "gn:name":"Ra\u0161a",
    "gn:population":0,
    "gn:timezone":"Europe/Ljubljana",
    "iso:country":"SI",
    "name:und_x_variant":[
        "Ra\u0161a"
    ],
    "wof:name":"Rasa",
    "wof:placetype":"locality"
},
  "geometry": {"coordinates":[13.88693,45.78812],"type":"Point"}
}