{
  "type": "Feature",
  "properties": {
    "gn:admin1_code":"74",
    "gn:asciiname":"Podkraj pri Mezici",
    "gn:country_code":"SI",
    "gn:dem":620,
    "gn:feature_class":"P",
    "gn:feature_code":"PPL",
    "gn:name":"Podkraj pri Me\u017eici",
    "gn:population":113,
    "gn:timezone":"Europe/Ljubljana",
    "iso:country":"SI",
    "name:und_x_variant":[
        "Podkraj pri Me\u017eici"
    ],
    "wof:name":"Podkraj pri Mezici",
    "wof:placetype":"locality",
    "wof:population":113
},
  "geometry": {"coordinates":[14.83637,46.52231],"type":"Point"}
}