{
  "type": "Feature",
  "properties": {
    "gn:admin1_code":"J5",
    "gn:asciiname":"Vojscica",
    "gn:country_code":"SI",
    "gn:dem":297,
    "gn:feature_class":"P",
    "gn:feature_code":"PPL",
    "gn:name":"Voj\u0161\u010dica",
    "gn:population":227,
    "gn:timezone":"Europe/Ljubljana",
    "iso:country":"SI",
    "name:bos_x_preferred":[
        "Voj\u0161\u010dica"
    ],
    "name:ceb_x_preferred":[
        "Voj\u0161\u010dica"
    ],
    "name:ita_x_preferred":[
        "Voissizza"
    ],
    "name:nld_x_preferred":[
        "Voj\u0161\u010dica"
    ],
    "name:pol_x_preferred":[
        "Voj\u0161\u010dica"
    ],
    "name:ron_x_preferred":[
        "Voj\u0161\u010dica"
    ],
    "name:slv_x_preferred":[
        "Voj\u0161\u010dica"
    ],
    "name:ukr_x_preferred":[
        "\u0412\u043e\u0439\u0449\u0438\u0446\u044f"
    ],
    "name:und_x_variant":[
        "Voisizza di Comeno",
        "Voischizza"
    ],
    "wof:name":"Vojscica",
    "wof:placetype":"locality",
    "wof:population":227
},
  "geometry": {"coordinates":[13.67167,45.82861],"type":"Point"}
}