{
  "type": "Feature",
  "properties": {
    "gn:admin1_code":"J8",
    "gn:asciiname":"Kovaski Vrh",
    "gn:country_code":"SI",
    "gn:dem":611,
    "gn:feature_class":"P",
    "gn:feature_code":"PPL",
    "gn:name":"Kova\u0161ki Vrh",
    "gn:population":51,
    "gn:timezone":"Europe/Ljubljana",
    "iso:country":"SI",
    "name:bos_x_preferred":[
        "Kova\u0161ki Vrh"
    ],
    "name:nld_x_preferred":[
        "Kova\u0161ki Vrh"
    ],
    "name:pol_x_preferred":[
        "Kova\u0161ki Vrh"
    ],
    "name:ron_x_preferred":[
        "Kova\u0161ki Vrh"
    ],
    "name:slv_x_preferred":[
        "Kova\u0161ki Vrh"
    ],
    "name:ukr_x_preferred":[
        "\u041a\u043e\u0432\u0430\u0448\u043a\u0438\u0439 \u0412\u0440\u0445"
    ],
    "wof:name":"Kovaski Vrh",
    "wof:placetype":"locality",
    "wof:population":51
},
  "geometry": {"coordinates":[15.41314,46.39916],"type":"Point"}
}