{
  "type": "Feature",
  "properties": {
    "gn:admin1_code":"J8",
    "gn:asciiname":"Kovaski Vrh",
    "gn:country_code":"SI",
    "gn:dem":611,
    "gn:feature_class":"P",
    "gn:feature_code":"PPL",
    "gn:name":"Kova\u0161ki Vrh",
    "gn:population":51,
    "gn:timezone":"Europe/Ljubljana",
    "iso:country":"SI",
    "name:und_x_variant":[
        "Kova\u0161ki Vrh"
    ],
    "wof:name":"Kovaski Vrh",
    "wof:placetype":"locality",
    "wof:population":51
},
  "geometry": {"coordinates":[15.41314,46.39916],"type":"Point"}
}