{
  "type": "Feature",
  "properties": {
    "gn:admin1_code":"D1",
    "gn:asciiname":"Brezje",
    "gn:country_code":"SI",
    "gn:dem":247,
    "gn:feature_class":"P",
    "gn:feature_code":"PPL",
    "gn:name":"Brezje",
    "gn:population":36,
    "gn:timezone":"Europe/Ljubljana",
    "iso:country":"SI",
    "name:bos_x_preferred":[
        "Brezje"
    ],
    "name:hrv_x_preferred":[
        "Brezje"
    ],
    "name:nld_x_preferred":[
        "Brezje"
    ],
    "name:pol_x_preferred":[
        "Brezje"
    ],
    "name:ron_x_preferred":[
        "Brezje"
    ],
    "name:slv_x_preferred":[
        "Brezje"
    ],
    "name:ukr_x_preferred":[
        "\u0411\u0440\u0435\u0437\u0454"
    ],
    "wof:name":"Brezje",
    "wof:placetype":"locality",
    "wof:population":36
},
  "geometry": {"coordinates":[16.00375,46.56386],"type":"Point"}
}