{
  "type": "Feature",
  "properties": {
    "gn:admin1_code":"87",
    "gn:asciiname":"Lunovec",
    "gn:country_code":"SI",
    "gn:dem":293,
    "gn:feature_class":"P",
    "gn:feature_code":"PPL",
    "gn:name":"Lunovec",
    "gn:population":28,
    "gn:timezone":"Europe/Ljubljana",
    "iso:country":"SI",
    "name:bos_x_preferred":[
        "Lunovec"
    ],
    "name:bul_x_preferred":[
        "\u041b\u0443\u043d\u043e\u0432\u0435\u0446"
    ],
    "name:nld_x_preferred":[
        "Lunovec"
    ],
    "name:pol_x_preferred":[
        "Lunovec"
    ],
    "name:ron_x_preferred":[
        "Lunovec"
    ],
    "name:slv_x_preferred":[
        "Lunovec"
    ],
    "name:ukr_x_preferred":[
        "\u041b\u0443\u043d\u043e\u0432\u0435\u0446\u044c"
    ],
    "wof:name":"Lunovec",
    "wof:placetype":"locality",
    "wof:population":28
},
  "geometry": {"coordinates":[16.10282999999999,46.44066],"type":"Point"}
}