{
  "type": "Feature",
  "properties": {
    "gn:admin1_code":"87",
    "gn:asciiname":"Lunovec",
    "gn:country_code":"SI",
    "gn:dem":293,
    "gn:feature_class":"P",
    "gn:feature_code":"PPL",
    "gn:name":"Lunovec",
    "gn:population":28,
    "gn:timezone":"Europe/Ljubljana",
    "iso:country":"SI",
    "wof:name":"Lunovec",
    "wof:placetype":"locality",
    "wof:population":28
},
  "geometry": {"coordinates":[16.10282999999999,46.44066],"type":"Point"}
}