{
  "type": "Feature",
  "properties": {
    "gn:admin1_code":"42",
    "gn:asciiname":"Rotman",
    "gn:country_code":"SI",
    "gn:dem":287,
    "gn:feature_class":"P",
    "gn:feature_code":"PPL",
    "gn:name":"Rotman",
    "gn:population":158,
    "gn:timezone":"Europe/Ljubljana",
    "iso:country":"SI",
    "name:bos_x_preferred":[
        "Rotman"
    ],
    "name:ceb_x_preferred":[
        "Rotman"
    ],
    "name:nld_x_preferred":[
        "Rotman"
    ],
    "name:pol_x_preferred":[
        "Rotman"
    ],
    "name:ron_x_preferred":[
        "Rotman"
    ],
    "name:slv_x_preferred":[
        "Rotman"
    ],
    "name:ukr_x_preferred":[
        "\u0420\u043e\u0442\u043c\u0430\u043d"
    ],
    "wof:name":"Rotman",
    "wof:placetype":"locality",
    "wof:population":158
},
  "geometry": {"coordinates":[15.98364,46.48075],"type":"Point"}
}