{
  "type": "Feature",
  "properties": {
    "gn:admin1_code":"L1",
    "gn:asciiname":"Breg pri Ribnici na Dol.",
    "gn:country_code":"SI",
    "gn:dem":496,
    "gn:feature_class":"P",
    "gn:feature_code":"PPL",
    "gn:name":"Breg pri Ribnici na Dol.",
    "gn:population":287,
    "gn:timezone":"Europe/Ljubljana",
    "iso:country":"SI",
    "wof:name":"Breg pri Ribnici na Dol.",
    "wof:placetype":"locality",
    "wof:population":287
},
  "geometry": {"coordinates":[14.71413,45.75078],"type":"Point"}
}