{
  "type": "Feature",
  "properties": {
    "gn:admin1_code":"B6",
    "gn:asciiname":"Vranje",
    "gn:country_code":"SI",
    "gn:dem":271,
    "gn:feature_class":"P",
    "gn:feature_code":"PPL",
    "gn:name":"Vranje",
    "gn:population":104,
    "gn:timezone":"Europe/Ljubljana",
    "iso:country":"SI",
    "wof:name":"Vranje",
    "wof:placetype":"locality",
    "wof:population":104
},
  "geometry": {"coordinates":[15.35,46.03333],"type":"Point"}
}