{
  "type": "Feature",
  "properties": {
    "gn:admin1_code":"B6",
    "gn:asciiname":"Vranje",
    "gn:country_code":"SI",
    "gn:dem":271,
    "gn:feature_class":"P",
    "gn:feature_code":"PPL",
    "gn:name":"Vranje",
    "gn:population":104,
    "gn:timezone":"Europe/Ljubljana",
    "iso:country":"SI",
    "name:bos_x_preferred":[
        "Vranje"
    ],
    "name:ceb_x_preferred":[
        "Vranje"
    ],
    "name:nld_x_preferred":[
        "Vranje"
    ],
    "name:pol_x_preferred":[
        "Vranje"
    ],
    "name:ron_x_preferred":[
        "Vranje"
    ],
    "name:slv_x_preferred":[
        "Vranje"
    ],
    "name:ukr_x_preferred":[
        "\u0412\u0440\u0430\u043d\u0454"
    ],
    "wof:name":"Vranje",
    "wof:placetype":"locality",
    "wof:population":104
},
  "geometry": {"coordinates":[15.35,46.03333],"type":"Point"}
}