{
  "type": "Feature",
  "properties": {
    "gn:admin1_code":"61",
    "gn:asciiname":"Dolgo Brdo",
    "gn:country_code":"SI",
    "gn:dem":481,
    "gn:feature_class":"P",
    "gn:feature_code":"PPL",
    "gn:name":"Dolgo Brdo",
    "gn:population":63,
    "gn:timezone":"Europe/Ljubljana",
    "iso:country":"SI",
    "name:bos_x_preferred":[
        "Dolgo Brdo"
    ],
    "name:bul_x_preferred":[
        "\u0414\u043e\u043b\u0433\u043e \u0411\u044a\u0440\u0434\u043e"
    ],
    "name:nld_x_preferred":[
        "Dolgo Brdo"
    ],
    "name:pol_x_preferred":[
        "Dolgo Brdo"
    ],
    "name:ron_x_preferred":[
        "Dolgo Brdo"
    ],
    "name:slv_x_preferred":[
        "Dolgo Brdo"
    ],
    "name:ukr_x_preferred":[
        "\u0414\u043e\u043b\u0433\u043e \u0411\u0440\u0434\u043e"
    ],
    "wof:name":"Dolgo Brdo",
    "wof:placetype":"locality",
    "wof:population":63
},
  "geometry": {"coordinates":[14.72415,46.04587],"type":"Point"}
}