{
  "type": "Feature",
  "properties": {
    "gn:admin1_code":"61",
    "gn:asciiname":"Dolgo Brdo",
    "gn:country_code":"SI",
    "gn:dem":481,
    "gn:feature_class":"P",
    "gn:feature_code":"PPL",
    "gn:name":"Dolgo Brdo",
    "gn:population":63,
    "gn:timezone":"Europe/Ljubljana",
    "iso:country":"SI",
    "wof:name":"Dolgo Brdo",
    "wof:placetype":"locality",
    "wof:population":63
},
  "geometry": {"coordinates":[14.72415,46.04587],"type":"Point"}
}