{
  "type": "Feature",
  "properties": {
    "gn:admin1_code":"92",
    "gn:asciiname":"Nezbise",
    "gn:country_code":"SI",
    "gn:dem":204,
    "gn:feature_class":"P",
    "gn:feature_code":"PPL",
    "gn:name":"Nezbi\u0161e",
    "gn:population":147,
    "gn:timezone":"Europe/Ljubljana",
    "iso:country":"SI",
    "name:bos_x_preferred":[
        "Nezbi\u0161e"
    ],
    "name:ceb_x_preferred":[
        "Nezbi\u0161e"
    ],
    "name:hrv_x_preferred":[
        "Nezbi\u0161e"
    ],
    "name:nld_x_preferred":[
        "Nezbi\u0161e"
    ],
    "name:pol_x_preferred":[
        "Nezbi\u0161e"
    ],
    "name:ron_x_preferred":[
        "Nezbi\u0161e"
    ],
    "name:slv_x_preferred":[
        "Nezbi\u0161e"
    ],
    "name:ukr_x_preferred":[
        "\u041d\u0435\u0437\u0431\u0438\u0448\u0435"
    ],
    "name:und_x_variant":[
        "Nezbi\u0161e"
    ],
    "wof:name":"Nezbise",
    "wof:placetype":"locality",
    "wof:population":147
},
  "geometry": {"coordinates":[15.6084,46.19806],"type":"Point"}
}