{
  "type": "Feature",
  "properties": {
    "gn:admin1_code":"H6",
    "gn:asciiname":"Potok v Crni",
    "gn:country_code":"SI",
    "gn:dem":791,
    "gn:feature_class":"P",
    "gn:feature_code":"PPL",
    "gn:name":"Potok v \u010crni",
    "gn:population":32,
    "gn:timezone":"Europe/Ljubljana",
    "iso:country":"SI",
    "name:und_x_variant":[
        "Potok v \u010crni"
    ],
    "wof:name":"Potok v Crni",
    "wof:placetype":"locality",
    "wof:population":32
},
  "geometry": {"coordinates":[14.63984,46.27062],"type":"Point"}
}