{
  "type": "Feature",
  "properties": {
    "gn:admin1_code":"76",
    "gn:asciiname":"Repnik",
    "gn:country_code":"SI",
    "gn:dem":1148,
    "gn:feature_class":"P",
    "gn:feature_code":"PPL",
    "gn:name":"Repnik",
    "gn:population":0,
    "gn:timezone":"Europe/Ljubljana",
    "iso:country":"SI",
    "wof:name":"Repnik",
    "wof:placetype":"locality"
},
  "geometry": {"coordinates":[15.2225,46.46944000000001],"type":"Point"}
}