{
  "type": "Feature",
  "properties": {
    "gn:admin1_code":"32",
    "gn:asciiname":"Gornji Rogatec",
    "gn:country_code":"SI",
    "gn:dem":393,
    "gn:feature_class":"P",
    "gn:feature_code":"PPL",
    "gn:name":"Gornji Rogatec",
    "gn:population":41,
    "gn:timezone":"Europe/Ljubljana",
    "iso:country":"SI",
    "wof:name":"Gornji Rogatec",
    "wof:placetype":"locality",
    "wof:population":41
},
  "geometry": {"coordinates":[14.60142,45.91669],"type":"Point"}
}