{
  "type": "Feature",
  "properties": {
    "gn:admin1_code":"32",
    "gn:asciiname":"Gornji Rogatec",
    "gn:country_code":"SI",
    "gn:dem":393,
    "gn:feature_class":"P",
    "gn:feature_code":"PPL",
    "gn:name":"Gornji Rogatec",
    "gn:population":41,
    "gn:timezone":"Europe/Ljubljana",
    "iso:country":"SI",
    "name:bos_x_preferred":[
        "Gornji Rogatec"
    ],
    "name:nld_x_preferred":[
        "Gornji Rogatec"
    ],
    "name:pol_x_preferred":[
        "Gornji Rogatec"
    ],
    "name:ron_x_preferred":[
        "Gornji Rogatec"
    ],
    "name:slv_x_preferred":[
        "Gornji Rogatec"
    ],
    "name:srp_x_preferred":[
        "\u0413\u043e\u0440\u045a\u0438 \u0420\u043e\u0433\u0430\u0442\u0435\u0446"
    ],
    "name:ukr_x_preferred":[
        "\u0413\u043e\u0440\u043d\u044c\u0457 \u0420\u043e\u0433\u0430\u0442\u0435\u0446\u044c"
    ],
    "wof:name":"Gornji Rogatec",
    "wof:placetype":"locality",
    "wof:population":41
},
  "geometry": {"coordinates":[14.60142,45.91669],"type":"Point"}
}