{
  "type": "Feature",
  "properties": {
    "gn:admin1_code":"P8",
    "gn:asciiname":"Mala Vas pri Ormozu",
    "gn:country_code":"SI",
    "gn:dem":259,
    "gn:feature_class":"P",
    "gn:feature_code":"PPL",
    "gn:name":"Mala Vas pri Ormo\u017eu",
    "gn:population":113,
    "gn:timezone":"Europe/Ljubljana",
    "iso:country":"SI",
    "name:bos_x_preferred":[
        "Mala vas pri Ormo\u017eu"
    ],
    "name:bul_x_preferred":[
        "\u041c\u0430\u043b\u0430 \u0432\u0430\u0441 \u043f\u0440\u0438 \u041e\u0440\u043c\u043e\u0436\u0443"
    ],
    "name:ceb_x_preferred":[
        "Mala Vas pri Ormo\u017eu"
    ],
    "name:nld_x_preferred":[
        "Mala vas pri Ormo\u017eu"
    ],
    "name:pol_x_preferred":[
        "Mala vas pri Ormo\u017eu"
    ],
    "name:ron_x_preferred":[
        "Mala vas pri Ormo\u017eu"
    ],
    "name:slv_x_preferred":[
        "Mala vas pri Ormo\u017eu"
    ],
    "name:ukr_x_preferred":[
        "\u041c\u0430\u043b\u0430 \u0412\u0430\u0441-\u043f\u0440\u0438-\u041e\u0440\u043c\u043e\u0436\u0443"
    ],
    "wof:name":"Mala Vas pri Ormozu",
    "wof:placetype":"locality",
    "wof:population":113
},
  "geometry": {"coordinates":[16.072,46.46675],"type":"Point"}
}