{
  "type": "Feature",
  "properties": {
    "gn:admin1_code":"P8",
    "gn:asciiname":"Mala Vas pri Ormozu",
    "gn:country_code":"SI",
    "gn:dem":259,
    "gn:feature_class":"P",
    "gn:feature_code":"PPL",
    "gn:name":"Mala Vas pri Ormo\u017eu",
    "gn:population":113,
    "gn:timezone":"Europe/Ljubljana",
    "iso:country":"SI",
    "name:und_x_variant":[
        "Mala Vas pri Ormo\u017eu"
    ],
    "wof:name":"Mala Vas pri Ormozu",
    "wof:placetype":"locality",
    "wof:population":113
},
  "geometry": {"coordinates":[16.072,46.46675],"type":"Point"}
}