{
  "type": "Feature",
  "properties": {
    "gn:admin1_code":"94",
    "gn:asciiname":"Malni",
    "gn:country_code":"SI",
    "gn:dem":533,
    "gn:feature_class":"P",
    "gn:feature_code":"PPL",
    "gn:name":"Malni",
    "gn:population":0,
    "gn:timezone":"Europe/Ljubljana",
    "iso:country":"SI",
    "name:bos_x_preferred":[
        "Malni"
    ],
    "name:hrv_x_preferred":[
        "Malni"
    ],
    "name:nld_x_preferred":[
        "Malni"
    ],
    "name:pol_x_preferred":[
        "Malni"
    ],
    "name:ron_x_preferred":[
        "Malni"
    ],
    "name:slv_x_preferred":[
        "Malni"
    ],
    "name:ukr_x_preferred":[
        "\u041c\u0430\u043b\u043d\u0456"
    ],
    "name:und_x_variant":[
        "Malne",
        "Mulini",
        "Malni"
    ],
    "wof:name":"Malni",
    "wof:placetype":"locality"
},
  "geometry": {"coordinates":[14.26083,45.82194000000001],"type":"Point"}
}