{
  "type": "Feature",
  "properties": {
    "gn:admin1_code":"B6",
    "gn:asciiname":"Razbor",
    "gn:country_code":"SI",
    "gn:dem":433,
    "gn:feature_class":"P",
    "gn:feature_code":"PPL",
    "gn:name":"Razbor",
    "gn:population":150,
    "gn:timezone":"Europe/Ljubljana",
    "iso:country":"SI",
    "name:bos_x_preferred":[
        "Razbor"
    ],
    "name:ceb_x_preferred":[
        "Razbor"
    ],
    "name:nld_x_preferred":[
        "Razbor"
    ],
    "name:pol_x_preferred":[
        "Razbor"
    ],
    "name:ron_x_preferred":[
        "Razbor"
    ],
    "name:slv_x_preferred":[
        "Razbor"
    ],
    "name:ukr_x_preferred":[
        "\u0420\u0430\u0437\u0431\u043e\u0440"
    ],
    "wof:name":"Razbor",
    "wof:placetype":"locality",
    "wof:population":150
},
  "geometry": {"coordinates":[15.26373,46.05893],"type":"Point"}
}