{
  "type": "Feature",
  "properties": {
    "gn:admin1_code":"B1",
    "gn:asciiname":"Krupa",
    "gn:country_code":"SI",
    "gn:dem":163,
    "gn:feature_class":"P",
    "gn:feature_code":"PPL",
    "gn:name":"Krupa",
    "gn:population":49,
    "gn:timezone":"Europe/Ljubljana",
    "iso:country":"SI",
    "name:bos_x_preferred":[
        "Krupa"
    ],
    "name:deu_x_preferred":[
        "Krupa"
    ],
    "name:hrv_x_preferred":[
        "Krupa"
    ],
    "name:nld_x_preferred":[
        "Krupa"
    ],
    "name:pol_x_preferred":[
        "Krupa"
    ],
    "name:ron_x_preferred":[
        "Krupa"
    ],
    "name:slv_x_preferred":[
        "Krupa"
    ],
    "name:ukr_x_preferred":[
        "\u041a\u0440\u0443\u043f\u0430"
    ],
    "wof:name":"Krupa",
    "wof:placetype":"locality",
    "wof:population":49
},
  "geometry": {"coordinates":[15.23033,45.63784],"type":"Point"}
}