{
  "type": "Feature",
  "properties": {
    "gn:admin1_code":"37",
    "gn:asciiname":"Tomiselj",
    "gn:country_code":"SI",
    "gn:dem":298,
    "gn:feature_class":"P",
    "gn:feature_code":"PPL",
    "gn:name":"Tomi\u0161elj",
    "gn:population":299,
    "gn:timezone":"Europe/Ljubljana",
    "iso:country":"SI",
    "name:und_x_variant":[
        "Tomi\u0161elj"
    ],
    "wof:name":"Tomiselj",
    "wof:placetype":"locality",
    "wof:population":299
},
  "geometry": {"coordinates":[14.48194,45.96417],"type":"Point"}
}