{
  "type": "Feature",
  "properties": {
    "gn:admin1_code":"37",
    "gn:asciiname":"Tomiselj",
    "gn:country_code":"SI",
    "gn:dem":298,
    "gn:feature_class":"P",
    "gn:feature_code":"PPL",
    "gn:name":"Tomi\u0161elj",
    "gn:population":299,
    "gn:timezone":"Europe/Ljubljana",
    "iso:country":"SI",
    "name:bos_x_preferred":[
        "Tomi\u0161elj"
    ],
    "name:bul_x_preferred":[
        "\u0422\u043e\u043c\u0438\u0448\u0435\u043b"
    ],
    "name:ceb_x_preferred":[
        "Tomi\u0161elj"
    ],
    "name:nld_x_preferred":[
        "Tomi\u0161elj"
    ],
    "name:pol_x_preferred":[
        "Tomi\u0161elj"
    ],
    "name:ron_x_preferred":[
        "Tomi\u0161elj"
    ],
    "name:slv_x_preferred":[
        "Tomi\u0161elj"
    ],
    "name:ukr_x_preferred":[
        "\u0422\u043e\u043c\u0438\u0448\u0435\u043b\u044c"
    ],
    "wof:name":"Tomiselj",
    "wof:placetype":"locality",
    "wof:population":299
},
  "geometry": {"coordinates":[14.48194,45.96417],"type":"Point"}
}