{
  "type": "Feature",
  "properties": {
    "gn:admin1_code":"E5",
    "gn:asciiname":"Jerinov Gric",
    "gn:country_code":"SI",
    "gn:dem":550,
    "gn:feature_class":"P",
    "gn:feature_code":"PPL",
    "gn:name":"Jerinov Gri\u010d",
    "gn:population":56,
    "gn:timezone":"Europe/Ljubljana",
    "iso:country":"SI",
    "name:bos_x_preferred":[
        "Jerinov Gri\u010d"
    ],
    "name:pol_x_preferred":[
        "Jerinov Gri\u010d"
    ],
    "name:ron_x_preferred":[
        "Jerinov Gri\u010d"
    ],
    "name:slv_x_preferred":[
        "Jerinov Gri\u010d"
    ],
    "name:ukr_x_preferred":[
        "\u0404\u0440\u0438\u043d\u043e\u0432 \u0413\u0440\u0438\u0447"
    ],
    "name:und_x_variant":[
        "Jermov Gri\u010d",
        "Jerinov Gri\u010d"
    ],
    "wof:name":"Jerinov Gric",
    "wof:placetype":"locality",
    "wof:population":56
},
  "geometry": {"coordinates":[14.23,45.9525],"type":"Point"}
}