{
  "type": "Feature",
  "properties": {
    "gn:admin1_code":"77",
    "gn:asciiname":"Hrib nad Ribcami",
    "gn:country_code":"SI",
    "gn:dem":458,
    "gn:feature_class":"P",
    "gn:feature_code":"PPL",
    "gn:name":"Hrib nad Rib\u010dami",
    "gn:population":33,
    "gn:timezone":"Europe/Ljubljana",
    "iso:country":"SI",
    "name:bos_x_preferred":[
        "Hrib nad Rib\u010dami"
    ],
    "name:nld_x_preferred":[
        "Hrib nad Rib\u010dami"
    ],
    "name:pol_x_preferred":[
        "Hrib nad Rib\u010dami"
    ],
    "name:ron_x_preferred":[
        "Hrib nad Rib\u010dami"
    ],
    "name:slv_x_preferred":[
        "Hrib nad Rib\u010dami"
    ],
    "name:ukr_x_preferred":[
        "\u0425\u0440\u0438\u0431-\u043d\u0430\u0434-\u0420\u0438\u0431\u0447\u0430\u043c\u0438"
    ],
    "wof:name":"Hrib nad Ribcami",
    "wof:placetype":"locality",
    "wof:population":33
},
  "geometry": {"coordinates":[14.7577,46.11391],"type":"Point"}
}