{
  "type": "Feature",
  "properties": {
    "gn:admin1_code":"77",
    "gn:asciiname":"Hrib nad Ribcami",
    "gn:country_code":"SI",
    "gn:dem":458,
    "gn:feature_class":"P",
    "gn:feature_code":"PPL",
    "gn:name":"Hrib nad Rib\u010dami",
    "gn:population":33,
    "gn:timezone":"Europe/Ljubljana",
    "iso:country":"SI",
    "name:und_x_variant":[
        "Hrib nad Rib\u010dami"
    ],
    "wof:name":"Hrib nad Ribcami",
    "wof:placetype":"locality",
    "wof:population":33
},
  "geometry": {"coordinates":[14.7577,46.11391],"type":"Point"}
}