{
  "type": "Feature",
  "properties": {
    "gn:admin1_code":"F6",
    "gn:asciiname":"Rozance",
    "gn:country_code":"SI",
    "gn:dem":729,
    "gn:feature_class":"P",
    "gn:feature_code":"PPL",
    "gn:name":"Ro\u017ean\u010de",
    "gn:population":9,
    "gn:timezone":"Europe/Ljubljana",
    "iso:country":"SI",
    "name:bos_x_preferred":[
        "Ro\u017ean\u010de"
    ],
    "name:hrv_x_preferred":[
        "Ro\u017ean\u010de"
    ],
    "name:nld_x_preferred":[
        "Ro\u017ean\u010de"
    ],
    "name:pol_x_preferred":[
        "Ro\u017ean\u010de"
    ],
    "name:ron_x_preferred":[
        "Ro\u017ean\u010de"
    ],
    "name:slv_x_preferred":[
        "Ro\u017ean\u010de"
    ],
    "name:ukr_x_preferred":[
        "\u0420\u043e\u0436\u0430\u043d\u0447\u0435"
    ],
    "name:und_x_variant":[
        "Ro\u017ean\u010de"
    ],
    "wof:name":"Rozance",
    "wof:placetype":"locality",
    "wof:population":9
},
  "geometry": {"coordinates":[14.46492,45.80931],"type":"Point"}
}