{
  "type": "Feature",
  "properties": {
    "gn:admin1_code":"14",
    "gn:asciiname":"Lazec",
    "gn:country_code":"SI",
    "gn:dem":543,
    "gn:feature_class":"P",
    "gn:feature_code":"PPL",
    "gn:name":"Lazec",
    "gn:population":116,
    "gn:timezone":"Europe/Ljubljana",
    "iso:country":"SI",
    "name:bos_x_preferred":[
        "Lazec"
    ],
    "name:ceb_x_preferred":[
        "Lazec"
    ],
    "name:nld_x_preferred":[
        "Lazec"
    ],
    "name:pol_x_preferred":[
        "Lazec"
    ],
    "name:ron_x_preferred":[
        "Lazec"
    ],
    "name:slv_x_preferred":[
        "Lazec"
    ],
    "name:ukr_x_preferred":[
        "\u041b\u0430\u0437\u0435\u0446\u044c"
    ],
    "wof:name":"Lazec",
    "wof:placetype":"locality",
    "wof:population":116
},
  "geometry": {"coordinates":[13.97603,46.09466],"type":"Point"}
}