{
  "type": "Feature",
  "properties": {
    "iso:country":"SI",
    "name:bos_x_preferred":[
        "Vrhovci"
    ],
    "name:fra_x_preferred":[
        "Vrhovci"
    ],
    "name:hrv_x_preferred":[
        "Vrhovci"
    ],
    "name:hun_x_preferred":[
        "Vrhovci"
    ],
    "name:nld_x_preferred":[
        "Vrhovci"
    ],
    "name:slv_x_preferred":[
        "Vrhovci"
    ],
    "name:srp_x_preferred":[
        "\u0412\u0440\u0445\u043e\u0432\u0446\u0438"
    ],
    "wof:name":"Vrhovci",
    "wof:placetype":"neighbourhood"
},
  "geometry": {"coordinates":[14.4589519974161,46.04271632352483],"type":"Point"}
}