{
  "type": "Feature",
  "properties": {
    "iso:country":"SI",
    "wof:name":"Vrhovci",
    "wof:placetype":"neighbourhood"
},
  "geometry": {"coordinates":[14.4589519974161,46.04271632352483],"type":"Point"}
}