{
  "type": "Feature",
  "properties": {
    "gn:admin1_code":"46",
    "gn:asciiname":"Leskovca",
    "gn:country_code":"SI",
    "gn:dem":1483,
    "gn:feature_class":"P",
    "gn:feature_code":"PPL",
    "gn:name":"Leskovca",
    "gn:population":0,
    "gn:timezone":"Europe/Ljubljana",
    "iso:country":"SI",
    "name:bos_x_preferred":[
        "Leskovca"
    ],
    "name:hrv_x_preferred":[
        "Leskovca"
    ],
    "name:nld_x_preferred":[
        "Leskovca"
    ],
    "name:pol_x_preferred":[
        "Leskovca"
    ],
    "name:ron_x_preferred":[
        "Leskovca"
    ],
    "name:slv_x_preferred":[
        "Leskovca"
    ],
    "name:ukr_x_preferred":[
        "\u041b\u0435\u0441\u043a\u043e\u0432\u0446\u0430"
    ],
    "wof:name":"Leskovca",
    "wof:placetype":"locality"
},
  "geometry": {"coordinates":[13.68389,46.25028],"type":"Point"}
}