{
  "type": "Feature",
  "properties": {
    "gn:admin1_code":"01",
    "gn:asciiname":"Cergoli",
    "gn:country_code":"SI",
    "gn:dem":766,
    "gn:feature_class":"P",
    "gn:feature_code":"PPLL",
    "gn:name":"Cergoli",
    "gn:population":0,
    "gn:timezone":"Europe/Ljubljana",
    "iso:country":"SI",
    "name:slv_x_historical":[
        "Cergole"
    ],
    "name:slv_x_preferred":[
        "Cergole"
    ],
    "wof:name":"Cergoli",
    "wof:placetype":"locality"
},
  "geometry": {"coordinates":[14.0322,45.87053],"type":"Point"}
}