{
  "type": "Feature",
  "properties": {
    "gn:admin1_code":"J5",
    "gn:asciiname":"Sela na Krasu",
    "gn:country_code":"SI",
    "gn:dem":227,
    "gn:feature_class":"P",
    "gn:feature_code":"PPL",
    "gn:name":"Sela na Krasu",
    "gn:population":157,
    "gn:timezone":"Europe/Ljubljana",
    "iso:country":"SI",
    "name:und_x_variant":[
        "Selo",
        "Sella delle Trincee",
        "Sela na Krasu"
    ],
    "wof:name":"Sela na Krasu",
    "wof:placetype":"locality",
    "wof:population":157
},
  "geometry": {"coordinates":[13.61639,45.82139],"type":"Point"}
}