{
  "type": "Feature",
  "properties": {
    "gn:admin1_code":"40",
    "gn:asciiname":"Dobrava",
    "gn:country_code":"SI",
    "gn:dem":37,
    "gn:feature_class":"P",
    "gn:feature_code":"PPL",
    "gn:name":"Dobrava",
    "gn:population":237,
    "gn:timezone":"Europe/Ljubljana",
    "iso:country":"SI",
    "name:bos_x_preferred":[
        "Dobrava"
    ],
    "name:ceb_x_preferred":[
        "Dobrava"
    ],
    "name:nld_x_preferred":[
        "Dobrava"
    ],
    "name:pol_x_preferred":[
        "Dobrava"
    ],
    "name:ron_x_preferred":[
        "Dobrava"
    ],
    "name:slv_x_preferred":[
        "Dobrava"
    ],
    "name:ukr_x_preferred":[
        "\u0414\u043e\u0431\u0440\u0430\u0432\u0430"
    ],
    "wof:name":"Dobrava",
    "wof:placetype":"locality",
    "wof:population":237
},
  "geometry": {"coordinates":[13.62515,45.52939],"type":"Point"}
}