{
  "type": "Feature",
  "properties": {
    "gn:admin1_code":"F3",
    "gn:asciiname":"Loska Gora pri Zrecah",
    "gn:country_code":"SI",
    "gn:dem":632,
    "gn:feature_class":"P",
    "gn:feature_code":"PPL",
    "gn:name":"Lo\u0161ka Gora pri Zre\u010dah",
    "gn:population":159,
    "gn:timezone":"Europe/Ljubljana",
    "iso:country":"SI",
    "name:bos_x_preferred":[
        "Lo\u0161ka Gora pri Zre\u010dah"
    ],
    "name:ceb_x_preferred":[
        "Lo\u0161ka Gora pri Zre\u010dah"
    ],
    "name:hrv_x_preferred":[
        "Lo\u0161ka Gora pri Zre\u010dah"
    ],
    "name:nld_x_preferred":[
        "Lo\u0161ka Gora pri Zre\u010dah"
    ],
    "name:pol_x_preferred":[
        "Lo\u0161ka Gora pri Zre\u010dah"
    ],
    "name:ron_x_preferred":[
        "Lo\u0161ka Gora pri Zre\u010dah"
    ],
    "name:slv_x_preferred":[
        "Lo\u0161ka Gora pri Zre\u010dah"
    ],
    "name:ukr_x_preferred":[
        "\u041b\u043e\u0448\u043a\u0430 \u0413\u043e\u0440\u0430-\u043f\u0440\u0438-\u0417\u0440\u0435\u0447\u0430\u0445"
    ],
    "wof:name":"Loska Gora pri Zrecah",
    "wof:placetype":"locality",
    "wof:population":159
},
  "geometry": {"coordinates":[15.3633,46.39202],"type":"Point"}
}