{
  "type": "Feature",
  "properties": {
    "gn:admin1_code":"O1",
    "gn:asciiname":"Pristava",
    "gn:country_code":"SI",
    "gn:dem":240,
    "gn:feature_class":"P",
    "gn:feature_code":"PPL",
    "gn:name":"Pristava",
    "gn:population":192,
    "gn:timezone":"Europe/Ljubljana",
    "iso:country":"SI",
    "name:bos_x_preferred":[
        "Pristava"
    ],
    "name:ceb_x_preferred":[
        "Pristava"
    ],
    "name:nld_x_preferred":[
        "Pristava"
    ],
    "name:pol_x_preferred":[
        "Pristava"
    ],
    "name:ron_x_preferred":[
        "Pristava"
    ],
    "name:slv_x_preferred":[
        "Pristava"
    ],
    "name:ukr_x_preferred":[
        "\u041f\u0440\u0438\u0441\u0442\u0430\u0432\u0430"
    ],
    "wof:name":"Pristava",
    "wof:placetype":"locality",
    "wof:population":192
},
  "geometry": {"coordinates":[15.9781,46.33835],"type":"Point"}
}