{
  "type": "Feature",
  "properties": {
    "gn:admin1_code":"17",
    "gn:asciiname":"Petrova Vas",
    "gn:country_code":"SI",
    "gn:dem":428,
    "gn:feature_class":"P",
    "gn:feature_code":"PPL",
    "gn:name":"Petrova Vas",
    "gn:population":102,
    "gn:timezone":"Europe/Ljubljana",
    "iso:country":"SI",
    "wof:name":"Petrova Vas",
    "wof:placetype":"locality",
    "wof:population":102
},
  "geometry": {"coordinates":[15.14922,45.61305],"type":"Point"}
}