{
  "type": "Feature",
  "properties": {
    "gn:admin1_code":"17",
    "gn:asciiname":"Petrova Vas",
    "gn:country_code":"SI",
    "gn:dem":428,
    "gn:feature_class":"P",
    "gn:feature_code":"PPL",
    "gn:name":"Petrova Vas",
    "gn:population":102,
    "gn:timezone":"Europe/Ljubljana",
    "iso:country":"SI",
    "name:bos_x_preferred":[
        "Petrova vas"
    ],
    "name:ceb_x_preferred":[
        "Petrova Vas"
    ],
    "name:hrv_x_preferred":[
        "Petrova vas"
    ],
    "name:nld_x_preferred":[
        "Petrova vas"
    ],
    "name:pol_x_preferred":[
        "Petrova vas"
    ],
    "name:ron_x_preferred":[
        "Petrova vas"
    ],
    "name:slv_x_preferred":[
        "Petrova vas"
    ],
    "name:ukr_x_preferred":[
        "\u041f\u0435\u0442\u0440\u043e\u0432\u0430 \u0412\u0430\u0441"
    ],
    "wof:name":"Petrova Vas",
    "wof:placetype":"locality",
    "wof:population":102
},
  "geometry": {"coordinates":[15.14922,45.61305],"type":"Point"}
}