{
  "type": "Feature",
  "properties": {
    "gn:admin1_code":"44",
    "gn:asciiname":"Zapotok",
    "gn:country_code":"SI",
    "gn:dem":591,
    "gn:feature_class":"P",
    "gn:feature_code":"PPL",
    "gn:name":"Zapotok",
    "gn:population":7,
    "gn:timezone":"Europe/Ljubljana",
    "iso:country":"SI",
    "wof:name":"Zapotok",
    "wof:placetype":"locality",
    "wof:population":7
},
  "geometry": {"coordinates":[13.55856,46.07333],"type":"Point"}
}