{
  "type": "Feature",
  "properties": {
    "gn:admin1_code":"L7",
    "gn:asciiname":"Golobinjek pri Planini",
    "gn:country_code":"SI",
    "gn:dem":475,
    "gn:feature_class":"P",
    "gn:feature_code":"PPL",
    "gn:name":"Golobinjek pri Planini",
    "gn:population":46,
    "gn:timezone":"Europe/Ljubljana",
    "iso:country":"SI",
    "wof:name":"Golobinjek pri Planini",
    "wof:placetype":"locality",
    "wof:population":46
},
  "geometry": {"coordinates":[15.39913,46.09165],"type":"Point"}
}