{
  "type": "Feature",
  "properties": {
    "gn:admin1_code":"L7",
    "gn:asciiname":"Golobinjek pri Planini",
    "gn:country_code":"SI",
    "gn:dem":475,
    "gn:feature_class":"P",
    "gn:feature_code":"PPL",
    "gn:name":"Golobinjek pri Planini",
    "gn:population":46,
    "gn:timezone":"Europe/Ljubljana",
    "iso:country":"SI",
    "name:bos_x_preferred":[
        "Golobinjek pri Planini"
    ],
    "name:hrv_x_preferred":[
        "Golobinjek pri Planini"
    ],
    "name:nld_x_preferred":[
        "Golobinjek pri Planini"
    ],
    "name:pol_x_preferred":[
        "Golobinjek pri Planini"
    ],
    "name:ron_x_preferred":[
        "Golobinjek pri Planini"
    ],
    "name:slv_x_preferred":[
        "Golobinjek pri Planini"
    ],
    "name:ukr_x_preferred":[
        "\u0413\u043e\u043b\u043e\u0431\u0438\u043d\u0454\u043a-\u043f\u0440\u0438-\u041f\u043b\u0430\u043d\u0438\u043d\u0456"
    ],
    "wof:name":"Golobinjek pri Planini",
    "wof:placetype":"locality",
    "wof:population":46
},
  "geometry": {"coordinates":[15.39913,46.09165],"type":"Point"}
}