{
  "type": "Feature",
  "properties": {
    "gn:admin1_code":"07",
    "gn:asciiname":"Kozarno",
    "gn:country_code":"SI",
    "gn:dem":136,
    "gn:feature_class":"P",
    "gn:feature_code":"PPL",
    "gn:name":"Kozarno",
    "gn:population":41,
    "gn:timezone":"Europe/Ljubljana",
    "iso:country":"SI",
    "name:bos_x_preferred":[
        "Kozarno"
    ],
    "name:ita_x_preferred":[
        "Cosarna"
    ],
    "name:nld_x_preferred":[
        "Kozarno"
    ],
    "name:pol_x_preferred":[
        "Kozarno"
    ],
    "name:ron_x_preferred":[
        "Kozarno"
    ],
    "name:slv_x_preferred":[
        "Kozarno"
    ],
    "name:ukr_x_preferred":[
        "\u041a\u043e\u0437\u0430\u0440\u043d\u043e"
    ],
    "wof:name":"Kozarno",
    "wof:placetype":"locality",
    "wof:population":41
},
  "geometry": {"coordinates":[13.52033,46.008],"type":"Point"}
}