{
  "type": "Feature",
  "properties": {
    "gn:admin1_code":"50",
    "gn:asciiname":"Triban",
    "gn:country_code":"SI",
    "gn:dem":81,
    "gn:feature_class":"P",
    "gn:feature_code":"PPL",
    "gn:name":"Triban",
    "gn:population":168,
    "gn:timezone":"Europe/Ljubljana",
    "iso:country":"SI",
    "name:bos_x_preferred":[
        "Triban"
    ],
    "name:bul_x_preferred":[
        "\u0422\u0440\u0438\u0431\u0430\u043d"
    ],
    "name:ceb_x_preferred":[
        "Triban"
    ],
    "name:nld_x_preferred":[
        "Triban"
    ],
    "name:pol_x_preferred":[
        "Triban"
    ],
    "name:ron_x_preferred":[
        "Triban"
    ],
    "name:slv_x_preferred":[
        "Triban"
    ],
    "name:ukr_x_preferred":[
        "\u0422\u0440\u0438\u0431\u0430\u043d"
    ],
    "wof:name":"Triban",
    "wof:placetype":"locality",
    "wof:population":168
},
  "geometry": {"coordinates":[13.7578,45.52505],"type":"Point"}
}