{
  "type": "Feature",
  "properties": {
    "gn:admin1_code":"B1",
    "gn:asciiname":"Sovinek",
    "gn:country_code":"SI",
    "gn:dem":198,
    "gn:feature_class":"P",
    "gn:feature_code":"PPL",
    "gn:name":"Sovinek",
    "gn:population":80,
    "gn:timezone":"Europe/Ljubljana",
    "iso:country":"SI",
    "name:bos_x_preferred":[
        "Sovinek"
    ],
    "name:pol_x_preferred":[
        "Sovinek"
    ],
    "name:slv_x_preferred":[
        "Sovinek"
    ],
    "name:ukr_x_preferred":[
        "\u0421\u043e\u0432\u0438\u043d\u0435\u043a"
    ],
    "wof:name":"Sovinek",
    "wof:placetype":"locality",
    "wof:population":80
},
  "geometry": {"coordinates":[15.20678,45.64722],"type":"Point"}
}