{
  "type": "Feature",
  "properties": {
    "gn:admin1_code":"L7",
    "gn:asciiname":"Jazbin Vrh",
    "gn:country_code":"SI",
    "gn:dem":480,
    "gn:feature_class":"P",
    "gn:feature_code":"PPL",
    "gn:name":"Jazbin Vrh",
    "gn:population":40,
    "gn:timezone":"Europe/Ljubljana",
    "iso:country":"SI",
    "wof:name":"Jazbin Vrh",
    "wof:placetype":"locality",
    "wof:population":40
},
  "geometry": {"coordinates":[15.37369,46.16798],"type":"Point"}
}