{
  "type": "Feature",
  "properties": {
    "gn:admin1_code":"L7",
    "gn:asciiname":"Jazbin Vrh",
    "gn:country_code":"SI",
    "gn:dem":480,
    "gn:feature_class":"P",
    "gn:feature_code":"PPL",
    "gn:name":"Jazbin Vrh",
    "gn:population":40,
    "gn:timezone":"Europe/Ljubljana",
    "iso:country":"SI",
    "name:bos_x_preferred":[
        "Jazbin Vrh"
    ],
    "name:hrv_x_preferred":[
        "Jazbin Vrh"
    ],
    "name:nld_x_preferred":[
        "Jazbin Vrh"
    ],
    "name:pol_x_preferred":[
        "Jazbin Vrh"
    ],
    "name:ron_x_preferred":[
        "Jazbin Vrh"
    ],
    "name:slv_x_preferred":[
        "Jazbin Vrh"
    ],
    "name:ukr_x_preferred":[
        "\u042f\u0437\u0431\u0438\u043d \u0412\u0440\u0445"
    ],
    "wof:name":"Jazbin Vrh",
    "wof:placetype":"locality",
    "wof:population":40
},
  "geometry": {"coordinates":[15.37369,46.16798],"type":"Point"}
}