{
  "type": "Feature",
  "properties": {
    "gn:admin1_code":"O1",
    "gn:asciiname":"Pohorje",
    "gn:country_code":"SI",
    "gn:dem":263,
    "gn:feature_class":"P",
    "gn:feature_code":"PPL",
    "gn:name":"Pohorje",
    "gn:population":109,
    "gn:timezone":"Europe/Ljubljana",
    "iso:country":"SI",
    "name:bos_x_preferred":[
        "Pohorje"
    ],
    "name:ceb_x_preferred":[
        "Pohorje"
    ],
    "name:nld_x_preferred":[
        "Pohorje"
    ],
    "name:pol_x_preferred":[
        "Pohorje"
    ],
    "name:ron_x_preferred":[
        "Pohorje"
    ],
    "name:slv_x_preferred":[
        "Pohorje"
    ],
    "name:ukr_x_preferred":[
        "\u041f\u043e\u0445\u043e\u0440\u0454"
    ],
    "wof:name":"Pohorje",
    "wof:placetype":"locality",
    "wof:population":109
},
  "geometry": {"coordinates":[15.9852,46.31891],"type":"Point"}
}