{
  "type": "Feature",
  "properties": {
    "gn:admin1_code":"D8",
    "gn:asciiname":"Gradisce",
    "gn:country_code":"SI",
    "gn:dem":530,
    "gn:feature_class":"P",
    "gn:feature_code":"PPL",
    "gn:name":"Gradi\u0161\u010de",
    "gn:population":16,
    "gn:timezone":"Europe/Ljubljana",
    "iso:country":"SI",
    "name:bos_x_preferred":[
        "Gradi\u0161\u010de"
    ],
    "name:nld_x_preferred":[
        "Gradi\u0161\u010de"
    ],
    "name:pol_x_preferred":[
        "Gradi\u0161\u010de"
    ],
    "name:ron_x_preferred":[
        "Gradi\u0161\u010de"
    ],
    "name:slv_x_preferred":[
        "Gradi\u0161\u010de"
    ],
    "name:ukr_x_preferred":[
        "\u0413\u0440\u0430\u0434\u0438\u0449\u0435"
    ],
    "wof:name":"Gradisce",
    "wof:placetype":"locality",
    "wof:population":16
},
  "geometry": {"coordinates":[14.57439,45.84321],"type":"Point"}
}