{
  "type": "Feature",
  "properties": {
    "gn:admin1_code":"D8",
    "gn:asciiname":"Gradisce",
    "gn:country_code":"SI",
    "gn:dem":530,
    "gn:feature_class":"P",
    "gn:feature_code":"PPL",
    "gn:name":"Gradi\u0161\u010de",
    "gn:population":16,
    "gn:timezone":"Europe/Ljubljana",
    "iso:country":"SI",
    "name:und_x_variant":[
        "Gradi\u0161\u010de"
    ],
    "wof:name":"Gradisce",
    "wof:placetype":"locality",
    "wof:population":16
},
  "geometry": {"coordinates":[14.57439,45.84321],"type":"Point"}
}