{
  "type": "Feature",
  "properties": {
    "gn:admin1_code":"39",
    "gn:asciiname":"Veliko Crnelo",
    "gn:country_code":"SI",
    "gn:dem":341,
    "gn:feature_class":"P",
    "gn:feature_code":"PPL",
    "gn:name":"Veliko \u010crnelo",
    "gn:population":86,
    "gn:timezone":"Europe/Ljubljana",
    "iso:country":"SI",
    "name:bos_x_preferred":[
        "Veliko \u010crnelo"
    ],
    "name:fas_x_preferred":[
        "\u0648\u0644\u06cc\u06a9\u0648 \u0686\u0631\u0646\u0644\u0648"
    ],
    "name:nld_x_preferred":[
        "Veliko \u010crnelo"
    ],
    "name:pol_x_preferred":[
        "Veliko \u010crnelo"
    ],
    "name:ron_x_preferred":[
        "Veliko \u010crnelo"
    ],
    "name:slv_x_preferred":[
        "Veliko \u010crnelo"
    ],
    "name:ukr_x_preferred":[
        "\u0412\u0435\u043b\u0438\u043a\u043e \u0427\u0440\u043d\u0435\u043b\u043e"
    ],
    "wof:name":"Veliko Crnelo",
    "wof:placetype":"locality",
    "wof:population":86
},
  "geometry": {"coordinates":[14.79833,45.9275],"type":"Point"}
}