{
  "type": "Feature",
  "properties": {
    "gn:admin1_code":"D2",
    "gn:asciiname":"Pluznje",
    "gn:country_code":"SI",
    "gn:dem":466,
    "gn:feature_class":"P",
    "gn:feature_code":"PPL",
    "gn:name":"Plu\u017enje",
    "gn:population":0,
    "gn:timezone":"Europe/Ljubljana",
    "iso:country":"SI",
    "name:slv_x_historical":[
        "Plu\u017ene"
    ],
    "name:slv_x_preferred":[
        "Plu\u017ene"
    ],
    "wof:name":"Pluznje",
    "wof:placetype":"locality"
},
  "geometry": {"coordinates":[13.84786,46.0172],"type":"Point"}
}