{
  "type": "Feature",
  "properties": {
    "iso:country":"SI",
    "name:slv_x_preferred":[
        "Podutik"
    ],
    "wof:name":"Podutik",
    "wof:placetype":"neighbourhood"
},
  "geometry": {"coordinates":[14.4507122471765,46.07186163842777],"type":"Point"}
}