{
  "type": "Feature",
  "properties": {
    "gn:admin1_code":"94",
    "gn:asciiname":"Ravberkomanda",
    "gn:country_code":"SI",
    "gn:dem":599,
    "gn:feature_class":"P",
    "gn:feature_code":"PPLL",
    "gn:name":"Ravberkomanda",
    "gn:population":0,
    "gn:timezone":"Europe/Ljubljana",
    "iso:country":"SI",
    "name:slv_x_preferred":[
        "Rauberkomanda"
    ],
    "wof:name":"Ravberkomanda",
    "wof:placetype":"locality"
},
  "geometry": {"coordinates":[14.22839,45.79379],"type":"Point"}
}