{
  "type": "Feature",
  "properties": {
    "gn:admin1_code":"08",
    "gn:asciiname":"Perisce",
    "gn:country_code":"SI",
    "gn:dem":233,
    "gn:feature_class":"P",
    "gn:feature_code":"PPL",
    "gn:name":"Peri\u0161\u010de",
    "gn:population":16,
    "gn:timezone":"Europe/Ljubljana",
    "iso:country":"SI",
    "name:und_x_variant":[
        "Pori\u0161\u010de",
        "Peri\u0161\u010de"
    ],
    "wof:name":"Perisce",
    "wof:placetype":"locality",
    "wof:population":16
},
  "geometry": {"coordinates":[15.66408,45.8473],"type":"Point"}
}