{
  "type": "Feature",
  "properties": {
    "gn:admin1_code":"B4",
    "gn:asciiname":"Dolenje Gradisce pri Sentj.",
    "gn:country_code":"SI",
    "gn:dem":166,
    "gn:feature_class":"P",
    "gn:feature_code":"PPL",
    "gn:name":"Dolenje Gradi\u0161\u010de pri \u0160entj.",
    "gn:population":116,
    "gn:timezone":"Europe/Ljubljana",
    "iso:country":"SI",
    "name:und_x_variant":[
        "Dolenje Gradi\u0161\u010de pri \u0160entj."
    ],
    "wof:name":"Dolenje Gradisce pri Sentj.",
    "wof:placetype":"locality",
    "wof:population":116
},
  "geometry": {"coordinates":[15.29089,45.84818],"type":"Point"}
}