{
  "type": "Feature",
  "properties": {
    "gn:admin1_code":"G4",
    "gn:asciiname":"Hrastenice",
    "gn:country_code":"SI",
    "gn:dem":351,
    "gn:feature_class":"P",
    "gn:feature_code":"PPL",
    "gn:name":"Hrastenice",
    "gn:population":48,
    "gn:timezone":"Europe/Ljubljana",
    "iso:country":"SI",
    "name:bos_x_preferred":[
        "Hrastenice"
    ],
    "name:bul_x_preferred":[
        "\u0425\u0440\u0430\u0441\u0442\u0435\u043d\u0438\u0446\u0435"
    ],
    "name:nld_x_preferred":[
        "Hrastenice"
    ],
    "name:pol_x_preferred":[
        "Hrastenice"
    ],
    "name:ron_x_preferred":[
        "Hrastenice"
    ],
    "name:slv_x_preferred":[
        "Hrastenice"
    ],
    "name:ukr_x_preferred":[
        "\u0425\u0440\u0430\u0441\u0442\u0435\u043d\u0438\u0446\u0435"
    ],
    "name:und_x_variant":[
        "Hrastenica"
    ],
    "wof:name":"Hrastenice",
    "wof:placetype":"locality",
    "wof:population":48
},
  "geometry": {"coordinates":[14.3805,46.07511],"type":"Point"}
}