{
  "type": "Feature",
  "properties": {
    "gn:admin1_code":"H6",
    "gn:asciiname":"Stolnik",
    "gn:country_code":"SI",
    "gn:dem":457,
    "gn:feature_class":"P",
    "gn:feature_code":"PPL",
    "gn:name":"Stolnik",
    "gn:population":123,
    "gn:timezone":"Europe/Ljubljana",
    "iso:country":"SI",
    "name:bos_x_preferred":[
        "Stolnik"
    ],
    "name:ceb_x_preferred":[
        "Stolnik"
    ],
    "name:pol_x_preferred":[
        "Stolnik"
    ],
    "name:ron_x_preferred":[
        "Stolnik"
    ],
    "name:slv_x_preferred":[
        "Stolnik"
    ],
    "name:ukr_x_preferred":[
        "\u0421\u0442\u043e\u043b\u043d\u0438\u043a"
    ],
    "wof:name":"Stolnik",
    "wof:placetype":"locality",
    "wof:population":123
},
  "geometry": {"coordinates":[14.58804,46.25162],"type":"Point"}
}