{
  "type": "Feature",
  "properties": {
    "gn:admin1_code":"88",
    "gn:asciiname":"Ribjek",
    "gn:country_code":"SI",
    "gn:dem":325,
    "gn:feature_class":"P",
    "gn:feature_code":"PPL",
    "gn:name":"Ribjek",
    "gn:population":21,
    "gn:timezone":"Europe/Ljubljana",
    "iso:country":"SI",
    "name:bos_x_preferred":[
        "Ribjek"
    ],
    "name:hrv_x_preferred":[
        "Ribjek"
    ],
    "name:nld_x_preferred":[
        "Ribjek"
    ],
    "name:pol_x_preferred":[
        "Ribjek"
    ],
    "name:ron_x_preferred":[
        "Ribjek"
    ],
    "name:slv_x_preferred":[
        "Ribjek"
    ],
    "name:ukr_x_preferred":[
        "\u0420\u0438\u0431\u0454\u043a"
    ],
    "wof:name":"Ribjek",
    "wof:placetype":"locality",
    "wof:population":21
},
  "geometry": {"coordinates":[14.73083,45.53528],"type":"Point"}
}