{
  "type": "Feature",
  "properties": {
    "gn:admin1_code":"D4",
    "gn:asciiname":"Kamni Potok",
    "gn:country_code":"SI",
    "gn:dem":281,
    "gn:feature_class":"P",
    "gn:feature_code":"PPL",
    "gn:name":"Kamni Potok",
    "gn:population":77,
    "gn:timezone":"Europe/Ljubljana",
    "iso:country":"SI",
    "name:bos_x_preferred":[
        "Kamni Potok"
    ],
    "name:hrv_x_preferred":[
        "Kamni Potok"
    ],
    "name:nld_x_preferred":[
        "Kamni Potok"
    ],
    "name:pol_x_preferred":[
        "Kamni Potok"
    ],
    "name:ron_x_preferred":[
        "Kamni Potok"
    ],
    "name:slv_x_preferred":[
        "Kamni Potok"
    ],
    "name:ukr_x_preferred":[
        "\u041a\u0430\u043c\u043d\u0438\u0439 \u041f\u043e\u0442\u043e\u043a"
    ],
    "wof:name":"Kamni Potok",
    "wof:placetype":"locality",
    "wof:population":77
},
  "geometry": {"coordinates":[14.97548,45.91844],"type":"Point"}
}