{
  "type": "Feature",
  "properties": {
    "gn:admin1_code":"57",
    "gn:asciiname":"Brodnice",
    "gn:country_code":"SI",
    "gn:dem":264,
    "gn:feature_class":"P",
    "gn:feature_code":"PPL",
    "gn:name":"Brodnice",
    "gn:population":60,
    "gn:timezone":"Europe/Ljubljana",
    "iso:country":"SI",
    "wof:name":"Brodnice",
    "wof:placetype":"locality",
    "wof:population":60
},
  "geometry": {"coordinates":[15.27355,46.11375],"type":"Point"}
}