{
  "type": "Feature",
  "properties": {
    "gn:admin1_code":"57",
    "gn:asciiname":"Brodnice",
    "gn:country_code":"SI",
    "gn:dem":264,
    "gn:feature_class":"P",
    "gn:feature_code":"PPL",
    "gn:name":"Brodnice",
    "gn:population":60,
    "gn:timezone":"Europe/Ljubljana",
    "iso:country":"SI",
    "name:bos_x_preferred":[
        "Brodnice"
    ],
    "name:hrv_x_preferred":[
        "Brodnice"
    ],
    "name:nld_x_preferred":[
        "Brodnice"
    ],
    "name:pol_x_preferred":[
        "Brodnice"
    ],
    "name:ron_x_preferred":[
        "Brodnice"
    ],
    "name:slv_x_preferred":[
        "Brodnice"
    ],
    "name:ukr_x_preferred":[
        "\u0411\u0440\u043e\u0434\u043d\u0438\u0446\u0435"
    ],
    "wof:name":"Brodnice",
    "wof:placetype":"locality",
    "wof:population":60
},
  "geometry": {"coordinates":[15.27355,46.11375],"type":"Point"}
}