{
  "type": "Feature",
  "properties": {
    "gn:admin1_code":"57",
    "gn:asciiname":"Trnov Hrib",
    "gn:country_code":"SI",
    "gn:dem":490,
    "gn:feature_class":"P",
    "gn:feature_code":"PPL",
    "gn:name":"Trnov Hrib",
    "gn:population":50,
    "gn:timezone":"Europe/Ljubljana",
    "iso:country":"SI",
    "wof:name":"Trnov Hrib",
    "wof:placetype":"locality",
    "wof:population":50
},
  "geometry": {"coordinates":[15.18505,46.15291],"type":"Point"}
}