{
  "type": "Feature",
  "properties": {
    "gn:admin1_code":"B3",
    "gn:asciiname":"Cirknica",
    "gn:country_code":"SI",
    "gn:dem":288,
    "gn:feature_class":"P",
    "gn:feature_code":"PPL",
    "gn:name":"Cirknica",
    "gn:population":112,
    "gn:timezone":"Europe/Ljubljana",
    "iso:country":"SI",
    "wof:name":"Cirknica",
    "wof:placetype":"locality",
    "wof:population":112
},
  "geometry": {"coordinates":[15.65459,46.6567],"type":"Point"}
}