{
  "type": "Feature",
  "properties": {
    "gn:admin1_code":"B3",
    "gn:asciiname":"Cirknica",
    "gn:country_code":"SI",
    "gn:dem":288,
    "gn:feature_class":"P",
    "gn:feature_code":"PPL",
    "gn:name":"Cirknica",
    "gn:population":112,
    "gn:timezone":"Europe/Ljubljana",
    "iso:country":"SI",
    "name:bos_x_preferred":[
        "Cirknica"
    ],
    "name:ceb_x_preferred":[
        "Cirknica"
    ],
    "name:nld_x_preferred":[
        "Cirknica"
    ],
    "name:pol_x_preferred":[
        "Cirknica"
    ],
    "name:ron_x_preferred":[
        "Cirknica"
    ],
    "name:slv_x_preferred":[
        "Cirknica"
    ],
    "name:ukr_x_preferred":[
        "\u0426\u0438\u0440\u043a\u043d\u0438\u0446\u044f"
    ],
    "wof:name":"Cirknica",
    "wof:placetype":"locality",
    "wof:population":112
},
  "geometry": {"coordinates":[15.65459,46.6567],"type":"Point"}
}