{
  "type": "Feature",
  "properties": {
    "gn:admin1_code":"82",
    "gn:asciiname":"Polica",
    "gn:country_code":"SI",
    "gn:dem":428,
    "gn:feature_class":"P",
    "gn:feature_code":"PPL",
    "gn:name":"Polica",
    "gn:population":112,
    "gn:timezone":"Europe/Ljubljana",
    "iso:country":"SI",
    "name:bos_x_preferred":[
        "Polica"
    ],
    "name:ceb_x_preferred":[
        "Polica"
    ],
    "name:hrv_x_preferred":[
        "Polica"
    ],
    "name:ita_x_preferred":[
        "Polica"
    ],
    "name:nld_x_preferred":[
        "Polica"
    ],
    "name:pol_x_preferred":[
        "Polica"
    ],
    "name:ron_x_preferred":[
        "Polica"
    ],
    "name:slv_x_preferred":[
        "Polica"
    ],
    "name:ukr_x_preferred":[
        "\u041f\u043e\u043b\u0438\u0446\u044f"
    ],
    "wof:name":"Polica",
    "wof:placetype":"locality",
    "wof:population":112
},
  "geometry": {"coordinates":[14.33129,46.26916],"type":"Point"}
}