{
  "type": "Feature",
  "properties": {
    "gn:admin1_code":"B3",
    "gn:asciiname":"Cersak",
    "gn:country_code":"SI",
    "gn:dem":312,
    "gn:feature_class":"P",
    "gn:feature_code":"PPL",
    "gn:name":"Cer\u0161ak",
    "gn:population":708,
    "gn:timezone":"Europe/Ljubljana",
    "iso:country":"SI",
    "name:bos_x_preferred":[
        "Cer\u0161ak"
    ],
    "name:ceb_x_preferred":[
        "Cer\u0161ak"
    ],
    "name:deu_x_preferred":[
        "Cer\u0161ak"
    ],
    "name:nld_x_preferred":[
        "Cer\u0161ak"
    ],
    "name:pol_x_preferred":[
        "Cer\u0161ak"
    ],
    "name:ron_x_preferred":[
        "Cer\u0161ak"
    ],
    "name:slv_x_preferred":[
        "Cer\u0161ak"
    ],
    "name:ukr_x_preferred":[
        "\u0426\u0435\u0440\u0448\u0430\u043a"
    ],
    "wof:name":"Cersak",
    "wof:placetype":"locality",
    "wof:population":708
},
  "geometry": {"coordinates":[15.66917,46.69917],"type":"Point"}
}