{
  "type": "Feature",
  "properties": {
    "gn:admin1_code":"B3",
    "gn:asciiname":"Cersak",
    "gn:country_code":"SI",
    "gn:dem":312,
    "gn:feature_class":"P",
    "gn:feature_code":"PPL",
    "gn:name":"Cer\u0161ak",
    "gn:population":708,
    "gn:timezone":"Europe/Ljubljana",
    "iso:country":"SI",
    "name:und_x_variant":[
        "Cer\u0161ak"
    ],
    "wof:name":"Cersak",
    "wof:placetype":"locality",
    "wof:population":708
},
  "geometry": {"coordinates":[15.66917,46.69917],"type":"Point"}
}