{
  "type": "Feature",
  "properties": {
    "gn:admin1_code":"L1",
    "gn:asciiname":"Hrovaca",
    "gn:country_code":"SI",
    "gn:dem":545,
    "gn:feature_class":"P",
    "gn:feature_code":"PPL",
    "gn:name":"Hrova\u010da",
    "gn:population":201,
    "gn:timezone":"Europe/Ljubljana",
    "iso:country":"SI",
    "name:bos_x_preferred":[
        "Hrova\u010da"
    ],
    "name:ceb_x_preferred":[
        "Hrova\u010da"
    ],
    "name:nld_x_preferred":[
        "Hrova\u010da"
    ],
    "name:pol_x_preferred":[
        "Hrova\u010da"
    ],
    "name:ron_x_preferred":[
        "Hrova\u010da"
    ],
    "name:slv_x_preferred":[
        "Hrova\u010da"
    ],
    "name:ukr_x_preferred":[
        "\u0425\u0440\u043e\u0432\u0430\u0447\u0430"
    ],
    "wof:name":"Hrovaca",
    "wof:placetype":"locality",
    "wof:population":201
},
  "geometry": {"coordinates":[14.76086,45.74463],"type":"Point"}
}