{
  "type": "Feature",
  "properties": {
    "gn:admin1_code":"L1",
    "gn:asciiname":"Hrovaca",
    "gn:country_code":"SI",
    "gn:dem":545,
    "gn:feature_class":"P",
    "gn:feature_code":"PPL",
    "gn:name":"Hrova\u010da",
    "gn:population":201,
    "gn:timezone":"Europe/Ljubljana",
    "iso:country":"SI",
    "name:und_x_variant":[
        "Hrova\u010da"
    ],
    "wof:name":"Hrovaca",
    "wof:placetype":"locality",
    "wof:population":201
},
  "geometry": {"coordinates":[14.76086,45.74463],"type":"Point"}
}