{
  "type": "Feature",
  "properties": {
    "gn:admin1_code":"32",
    "gn:asciiname":"Veliki Vrh pri Smarju",
    "gn:country_code":"SI",
    "gn:dem":359,
    "gn:feature_class":"P",
    "gn:feature_code":"PPL",
    "gn:name":"Veliki Vrh pri \u0160marju",
    "gn:population":324,
    "gn:timezone":"Europe/Ljubljana",
    "iso:country":"SI",
    "name:und_x_variant":[
        "Veliki-Vrh",
        "Veliki Vrh pri \u0160marju"
    ],
    "wof:name":"Veliki Vrh pri Smarju",
    "wof:placetype":"locality",
    "wof:population":324
},
  "geometry": {"coordinates":[14.60389,45.98083],"type":"Point"}
}