{
  "type": "Feature",
  "properties": {
    "gn:admin1_code":"17",
    "gn:asciiname":"Doblicka Gora",
    "gn:country_code":"SI",
    "gn:dem":281,
    "gn:feature_class":"P",
    "gn:feature_code":"PPL",
    "gn:name":"Dobli\u010dka Gora",
    "gn:population":71,
    "gn:timezone":"Europe/Ljubljana",
    "iso:country":"SI",
    "name:bos_x_preferred":[
        "Dobli\u010dka Gora"
    ],
    "name:hrv_x_preferred":[
        "Dobli\u010dka Gora"
    ],
    "name:nld_x_preferred":[
        "Dobli\u010dka Gora"
    ],
    "name:pol_x_preferred":[
        "Dobli\u010dka Gora"
    ],
    "name:ron_x_preferred":[
        "Dobli\u010dka Gora"
    ],
    "name:slv_x_preferred":[
        "Dobli\u010dka Gora"
    ],
    "name:ukr_x_preferred":[
        "\u0414\u043e\u0431\u043b\u0438\u0447\u043a\u0430 \u0413\u043e\u0440\u0430"
    ],
    "name:und_x_variant":[
        "Dobli\u010dka Gora"
    ],
    "wof:name":"Doblicka Gora",
    "wof:placetype":"locality",
    "wof:population":71
},
  "geometry": {"coordinates":[15.13747,45.5627],"type":"Point"}
}