{
  "type": "Feature",
  "properties": {
    "gn:admin1_code":"17",
    "gn:asciiname":"Gorenji Radenci",
    "gn:country_code":"SI",
    "gn:dem":250,
    "gn:feature_class":"P",
    "gn:feature_code":"PPL",
    "gn:name":"Gorenji Radenci",
    "gn:population":26,
    "gn:timezone":"Europe/Ljubljana",
    "iso:country":"SI",
    "wof:name":"Gorenji Radenci",
    "wof:placetype":"locality",
    "wof:population":26
},
  "geometry": {"coordinates":[15.08934,45.47037],"type":"Point"}
}