{
  "type": "Feature",
  "properties": {
    "gn:admin1_code":"17",
    "gn:asciiname":"Gorenji Radenci",
    "gn:country_code":"SI",
    "gn:dem":250,
    "gn:feature_class":"P",
    "gn:feature_code":"PPL",
    "gn:name":"Gorenji Radenci",
    "gn:population":26,
    "gn:timezone":"Europe/Ljubljana",
    "iso:country":"SI",
    "name:bos_x_preferred":[
        "Gorenji Radenci"
    ],
    "name:hrv_x_preferred":[
        "Gorenji Radenci"
    ],
    "name:nld_x_preferred":[
        "Gorenji Radenci"
    ],
    "name:pol_x_preferred":[
        "Gorenji Radenci"
    ],
    "name:ron_x_preferred":[
        "Gorenji Radenci"
    ],
    "name:slv_x_preferred":[
        "Gorenji Radenci"
    ],
    "name:ukr_x_preferred":[
        "\u0413\u043e\u0440\u0435\u043d\u0456 \u0420\u0430\u0434\u0435\u043d\u0446\u0456"
    ],
    "wof:name":"Gorenji Radenci",
    "wof:placetype":"locality",
    "wof:population":26
},
  "geometry": {"coordinates":[15.08934,45.47037],"type":"Point"}
}