{
  "type": "Feature",
  "properties": {
    "gn:admin1_code":"84",
    "gn:asciiname":"Preserje",
    "gn:country_code":"SI",
    "gn:dem":178,
    "gn:feature_class":"P",
    "gn:feature_code":"PPL",
    "gn:name":"Preserje",
    "gn:population":466,
    "gn:timezone":"Europe/Ljubljana",
    "iso:country":"SI",
    "name:bos_x_preferred":[
        "Preserje"
    ],
    "name:ceb_x_preferred":[
        "Preserje"
    ],
    "name:nld_x_preferred":[
        "Preserje"
    ],
    "name:pol_x_preferred":[
        "Preserje"
    ],
    "name:ron_x_preferred":[
        "Preserje"
    ],
    "name:slv_x_preferred":[
        "Preserje"
    ],
    "name:ukr_x_preferred":[
        "\u041f\u0440\u0435\u0441\u0435\u0440\u0454"
    ],
    "name:und_x_variant":[
        "Rihemberk",
        "Preserje"
    ],
    "wof:name":"Preserje",
    "wof:placetype":"locality",
    "wof:population":466
},
  "geometry": {"coordinates":[13.78778,45.87139000000001],"type":"Point"}
}