{
  "type": "Feature",
  "properties": {
    "gn:admin1_code":"C5",
    "gn:asciiname":"Topolovec",
    "gn:country_code":"SI",
    "gn:dem":284,
    "gn:feature_class":"P",
    "gn:feature_code":"PPL",
    "gn:name":"Topolovec",
    "gn:population":20,
    "gn:timezone":"Europe/Ljubljana",
    "iso:country":"SI",
    "name:bos_x_preferred":[
        "Topolovec"
    ],
    "name:hrv_x_preferred":[
        "Topolovec"
    ],
    "name:nld_x_preferred":[
        "Topolovec"
    ],
    "name:pol_x_preferred":[
        "Topolovec"
    ],
    "name:ron_x_preferred":[
        "Topolovec"
    ],
    "name:slv_x_preferred":[
        "Topolovec"
    ],
    "name:ukr_x_preferred":[
        "\u0422\u043e\u043f\u043e\u043b\u043e\u0432\u0435\u0446\u044c"
    ],
    "wof:name":"Topolovec",
    "wof:placetype":"locality",
    "wof:population":20
},
  "geometry": {"coordinates":[15.56132,46.26075],"type":"Point"}
}