{
  "type": "Feature",
  "properties": {
    "gn:admin1_code":"C5",
    "gn:asciiname":"Topolovec",
    "gn:country_code":"SI",
    "gn:dem":284,
    "gn:feature_class":"P",
    "gn:feature_code":"PPL",
    "gn:name":"Topolovec",
    "gn:population":20,
    "gn:timezone":"Europe/Ljubljana",
    "iso:country":"SI",
    "wof:name":"Topolovec",
    "wof:placetype":"locality",
    "wof:population":20
},
  "geometry": {"coordinates":[15.56132,46.26075],"type":"Point"}
}