{
  "type": "Feature",
  "properties": {
    "gn:admin1_code":"92",
    "gn:asciiname":"Brezovec pri Polju",
    "gn:country_code":"SI",
    "gn:dem":278,
    "gn:feature_class":"P",
    "gn:feature_code":"PPL",
    "gn:name":"Brezovec pri Polju",
    "gn:population":74,
    "gn:timezone":"Europe/Ljubljana",
    "iso:country":"SI",
    "name:bos_x_preferred":[
        "Brezovec pri Polju"
    ],
    "name:hrv_x_preferred":[
        "Brezovec pri Polju"
    ],
    "name:nld_x_preferred":[
        "Brezovec pri Polju"
    ],
    "name:pol_x_preferred":[
        "Brezovec pri Polju"
    ],
    "name:ron_x_preferred":[
        "Brezovec pri Polju"
    ],
    "name:slv_x_preferred":[
        "Brezovec pri Polju"
    ],
    "name:ukr_x_preferred":[
        "\u0411\u0440\u0435\u0437\u043e\u0432\u0435\u0446\u044c-\u043f\u0440\u0438-\u041f\u043e\u043b\u044e"
    ],
    "wof:name":"Brezovec pri Polju",
    "wof:placetype":"locality",
    "wof:population":74
},
  "geometry": {"coordinates":[15.5939,46.08702],"type":"Point"}
}