{
  "type": "Feature",
  "properties": {
    "gn:admin1_code":"92",
    "gn:asciiname":"Brezovec pri Polju",
    "gn:country_code":"SI",
    "gn:dem":278,
    "gn:feature_class":"P",
    "gn:feature_code":"PPL",
    "gn:name":"Brezovec pri Polju",
    "gn:population":74,
    "gn:timezone":"Europe/Ljubljana",
    "iso:country":"SI",
    "wof:name":"Brezovec pri Polju",
    "wof:placetype":"locality",
    "wof:population":74
},
  "geometry": {"coordinates":[15.5939,46.08702],"type":"Point"}
}