{
  "type": "Feature",
  "properties": {
    "gn:admin1_code":"E7",
    "gn:asciiname":"Kotredez",
    "gn:country_code":"SI",
    "gn:dem":416,
    "gn:feature_class":"P",
    "gn:feature_code":"PPL",
    "gn:name":"Kotrede\u017e",
    "gn:population":191,
    "gn:timezone":"Europe/Ljubljana",
    "iso:country":"SI",
    "name:ceb_x_preferred":[
        "Kotrede\u017e"
    ],
    "name:nld_x_preferred":[
        "Kotrede\u017e"
    ],
    "name:pol_x_preferred":[
        "Kotrede\u017e"
    ],
    "name:ron_x_preferred":[
        "Kotrede\u017e"
    ],
    "name:slv_x_preferred":[
        "Kotrede\u017e"
    ],
    "name:ukr_x_preferred":[
        "\u041a\u043e\u0442\u0440\u0435\u0434\u0435\u0436"
    ],
    "name:und_x_variant":[
        "Kotrede\u017e"
    ],
    "wof:name":"Kotredez",
    "wof:placetype":"locality",
    "wof:population":191
},
  "geometry": {"coordinates":[14.99641,46.15804],"type":"Point"}
}