{
  "type": "Feature",
  "properties": {
    "gn:admin1_code":"D2",
    "gn:asciiname":"Dolgi Laz",
    "gn:country_code":"SI",
    "gn:dem":690,
    "gn:feature_class":"P",
    "gn:feature_code":"PPL",
    "gn:name":"Dolgi Laz",
    "gn:population":14,
    "gn:timezone":"Europe/Ljubljana",
    "iso:country":"SI",
    "name:bos_x_preferred":[
        "Dolgi Laz"
    ],
    "name:bul_x_preferred":[
        "\u0414\u043e\u043b\u0433\u0438 \u041b\u0430\u0437"
    ],
    "name:nld_x_preferred":[
        "Dolgi Laz"
    ],
    "name:pol_x_preferred":[
        "Dolgi Laz"
    ],
    "name:ron_x_preferred":[
        "Dolgi Laz"
    ],
    "name:slv_x_preferred":[
        "Dolgi Laz"
    ],
    "name:ukr_x_preferred":[
        "\u0414\u043e\u043b\u0433\u0438\u0439 \u041b\u0430\u0437"
    ],
    "wof:name":"Dolgi Laz",
    "wof:placetype":"locality",
    "wof:population":14
},
  "geometry": {"coordinates":[13.74527,46.11468],"type":"Point"}
}