{
  "type": "Feature",
  "properties": {
    "gn:admin1_code":"08",
    "gn:asciiname":"Vrhje",
    "gn:country_code":"SI",
    "gn:dem":179,
    "gn:feature_class":"P",
    "gn:feature_code":"PPL",
    "gn:name":"Vrhje",
    "gn:population":227,
    "gn:timezone":"Europe/Ljubljana",
    "iso:country":"SI",
    "wof:name":"Vrhje",
    "wof:placetype":"locality",
    "wof:population":227
},
  "geometry": {"coordinates":[15.68333,45.95],"type":"Point"}
}