{
  "type": "Feature",
  "properties": {
    "gn:admin1_code":"08",
    "gn:asciiname":"Kamence",
    "gn:country_code":"SI",
    "gn:dem":399,
    "gn:feature_class":"P",
    "gn:feature_code":"PPL",
    "gn:name":"Kamence",
    "gn:population":10,
    "gn:timezone":"Europe/Ljubljana",
    "iso:country":"SI",
    "name:bos_x_preferred":[
        "Kamence"
    ],
    "name:hrv_x_preferred":[
        "Kamence"
    ],
    "name:nld_x_preferred":[
        "Kamence"
    ],
    "name:pol_x_preferred":[
        "Kamence"
    ],
    "name:ron_x_preferred":[
        "Kamence"
    ],
    "name:slv_x_historical":[
        "Kamenice"
    ],
    "name:slv_x_preferred":[
        "Kamenice"
    ],
    "name:slv_x_variant":[
        "Kamence"
    ],
    "name:ukr_x_preferred":[
        "\u041a\u0430\u043c\u0435\u043d\u0446\u0435"
    ],
    "wof:name":"Kamence",
    "wof:placetype":"locality",
    "wof:population":10
},
  "geometry": {"coordinates":[15.5612,45.84822],"type":"Point"}
}