{
  "type": "Feature",
  "properties": {
    "gn:admin1_code":"07",
    "gn:asciiname":"Nozno",
    "gn:country_code":"SI",
    "gn:dem":354,
    "gn:feature_class":"P",
    "gn:feature_code":"PPL",
    "gn:name":"Nozno",
    "gn:population":31,
    "gn:timezone":"Europe/Ljubljana",
    "iso:country":"SI",
    "name:bos_x_preferred":[
        "Nozno"
    ],
    "name:nld_x_preferred":[
        "Nozno"
    ],
    "name:pol_x_preferred":[
        "Nozno"
    ],
    "name:ron_x_preferred":[
        "Nozno"
    ],
    "name:slv_x_preferred":[
        "Nozno"
    ],
    "name:ukr_x_preferred":[
        "\u041d\u043e\u0437\u043d\u043e"
    ],
    "wof:name":"Nozno",
    "wof:placetype":"locality",
    "wof:population":31
},
  "geometry": {"coordinates":[13.54426,46.03629],"type":"Point"}
}