{
  "type": "Feature",
  "properties": {
    "gn:admin1_code":"L4",
    "gn:asciiname":"Markovci",
    "gn:country_code":"SI",
    "gn:dem":309,
    "gn:feature_class":"P",
    "gn:feature_code":"PPL",
    "gn:name":"Markovci",
    "gn:population":267,
    "gn:timezone":"Europe/Ljubljana",
    "iso:country":"SI",
    "name:bos_x_preferred":[
        "Markovci"
    ],
    "name:ceb_x_preferred":[
        "Markovci"
    ],
    "name:epo_x_preferred":[
        "Markovci"
    ],
    "name:hun_x_preferred":[
        "Marokr\u00e9t"
    ],
    "name:pol_x_preferred":[
        "Markovci"
    ],
    "name:ron_x_preferred":[
        "Markovci"
    ],
    "name:slv_x_preferred":[
        "Markovci"
    ],
    "name:ukr_x_preferred":[
        "\u041c\u0430\u0440\u043a\u043e\u0432\u0446\u0456"
    ],
    "wof:name":"Markovci",
    "wof:placetype":"locality",
    "wof:population":267
},
  "geometry": {"coordinates":[16.23361,46.84444000000001],"type":"Point"}
}