{
  "type": "Feature",
  "properties": {
    "gn:admin1_code":"L4",
    "gn:asciiname":"Markovci",
    "gn:country_code":"SI",
    "gn:dem":309,
    "gn:feature_class":"P",
    "gn:feature_code":"PPL",
    "gn:name":"Markovci",
    "gn:population":267,
    "gn:timezone":"Europe/Ljubljana",
    "iso:country":"SI",
    "name:und_x_variant":[
        "Marokr\u00e9t",
        "Markovci"
    ],
    "wof:name":"Markovci",
    "wof:placetype":"locality",
    "wof:population":267
},
  "geometry": {"coordinates":[16.23361,46.84444000000001],"type":"Point"}
}