{
  "type": "Feature",
  "properties": {
    "gn:gn_country":"SI",
    "gn:gn_fcode":"PPL",
    "gn:gn_pop":0,
    "gn:population":102,
    "iso:country":"SI",
    "name:unk_x_variant":[
        "Goregna di Buciue"
    ],
    "qs_pg:aaroncc":"SI",
    "qs_pg:gn_country":"SI",
    "qs_pg:gn_fcode":"PPL",
    "qs_pg:gn_pop":0,
    "qs_pg:name":"Gorenje",
    "qs_pg:name_adm0":"Slovenija",
    "qs_pg:name_adm1":"Postojna",
    "qs_pg:photos":283,
    "qs_pg:photos_1k":57,
    "qs_pg:photos_9k":1,
    "qs_pg:photos_9r":4,
    "qs_pg:photos_all":283,
    "qs_pg:photos_sr":5,
    "qs_pg:pop_sr":0,
    "qs_pg:qs_pg_placetype":"locality",
    "qs_pg:qs_pg_placetype_gp":"Town",
    "qs_pg:woe_adm0":23424945,
    "woe:adm0_id":23424945,
    "woe:name_adm0":"Slovenija",
    "woe:name_adm1":"Postojna",
    "woe:placetype":"Town",
    "wof:name":"Gorenje",
    "wof:placetype":"locality",
    "wof:population":102
},
  "geometry": {"coordinates":[14.14194,45.82667],"type":"Point"}
}