{
  "type": "Feature",
  "properties": {
    "gn:country":"SI",
    "gn:fcode":"PPL",
    "gn:population":0,
    "iso:country":"SI",
    "name:ces_x_preferred":[
        "Gorenje"
    ],
    "name:dan_x_preferred":[
        "Gorenje"
    ],
    "name:deu_x_preferred":[
        "Gorenje"
    ],
    "name:fin_x_preferred":[
        "Gorenje"
    ],
    "name:fra_x_preferred":[
        "Gorenje"
    ],
    "name:hun_x_preferred":[
        "Gorenje"
    ],
    "name:lav_x_preferred":[
        "Gorenje"
    ],
    "name:nld_x_preferred":[
        "Gorenje d.d."
    ],
    "name:nor_x_preferred":[
        "Gorenje"
    ],
    "name:pol_x_preferred":[
        "Gorenje"
    ],
    "name:ron_x_preferred":[
        "Gorenje"
    ],
    "name:rus_x_preferred":[
        "Gorenje"
    ],
    "name:slk_x_preferred":[
        "Gorenje"
    ],
    "name:slv_x_preferred":[
        "Gorenje"
    ],
    "name:spa_x_preferred":[
        "Gorenje"
    ],
    "name:srp_x_preferred":[
        "\u0413\u043e\u0440\u0435\u045a\u0435"
    ],
    "name:swe_x_preferred":[
        "Gorenje"
    ],
    "name:ukr_x_preferred":[
        "Gorenje"
    ],
    "name:und_x_variant":[
        "Goregna di Buciue"
    ],
    "qs_pg:aaroncc":"SI",
    "qs_pg:gn_country":"SI",
    "qs_pg:gn_fcode":"PPL",
    "qs_pg:gn_pop":0,
    "qs_pg:name":"Gorenje",
    "qs_pg:name_adm0":"Slovenija",
    "qs_pg:name_adm1":"Postojna",
    "qs_pg:photos":283,
    "qs_pg:photos_1k":57,
    "qs_pg:photos_9k":1,
    "qs_pg:photos_9r":4,
    "qs_pg:photos_all":283,
    "qs_pg:photos_sr":5,
    "qs_pg:pop_sr":0,
    "qs_pg:qs_pg_placetype":"locality",
    "qs_pg:qs_pg_placetype_gp":"Town",
    "qs_pg:woe_adm0":23424945,
    "woe:adm0_id":23424945,
    "woe:name_adm0":"Slovenija",
    "woe:name_adm1":"Postojna",
    "woe:placetype":"Town",
    "wof:name":"Gorenje",
    "wof:placetype":"locality",
    "wof:population":102
},
  "geometry": {"coordinates":[14.14194,45.82667],"type":"Point"}
}