{
  "type": "Feature",
  "properties": {
    "gn:admin1_code":"50",
    "gn:asciiname":"Puce",
    "gn:country_code":"SI",
    "gn:dem":252,
    "gn:feature_class":"P",
    "gn:feature_code":"PPL",
    "gn:name":"Pu\u010de",
    "gn:population":249,
    "gn:timezone":"Europe/Ljubljana",
    "iso:country":"SI",
    "name:bos_x_preferred":[
        "Pu\u010de"
    ],
    "name:bul_x_preferred":[
        "\u041f\u0443\u0447\u0435"
    ],
    "name:ceb_x_preferred":[
        "Pu\u010de"
    ],
    "name:ita_x_preferred":[
        "Puzzole"
    ],
    "name:nld_x_preferred":[
        "Pu\u010de"
    ],
    "name:pol_x_preferred":[
        "Pu\u010de"
    ],
    "name:ron_x_preferred":[
        "Pu\u010de"
    ],
    "name:slv_x_preferred":[
        "Pu\u010de"
    ],
    "name:ukr_x_preferred":[
        "\u041f\u0443\u0447\u0435"
    ],
    "wof:name":"Puce",
    "wof:placetype":"locality",
    "wof:population":249
},
  "geometry": {"coordinates":[13.72083,45.475],"type":"Point"}
}