{
  "type": "Feature",
  "properties": {
    "gn:admin1_code":"A7",
    "gn:asciiname":"Brestovec",
    "gn:country_code":"SI",
    "gn:dem":254,
    "gn:feature_class":"P",
    "gn:feature_code":"PPL",
    "gn:name":"Brestovec",
    "gn:population":156,
    "gn:timezone":"Europe/Ljubljana",
    "iso:country":"SI",
    "wof:name":"Brestovec",
    "wof:placetype":"locality",
    "wof:population":156
},
  "geometry": {"coordinates":[15.62681,46.21431],"type":"Point"}
}