{
  "type": "Feature",
  "properties": {
    "gn:admin1_code":"A7",
    "gn:asciiname":"Brestovec",
    "gn:country_code":"SI",
    "gn:dem":254,
    "gn:feature_class":"P",
    "gn:feature_code":"PPL",
    "gn:name":"Brestovec",
    "gn:population":156,
    "gn:timezone":"Europe/Ljubljana",
    "iso:country":"SI",
    "name:bos_x_preferred":[
        "Brestovec"
    ],
    "name:bul_x_preferred":[
        "\u0411\u0440\u0435\u0441\u0442\u043e\u0432\u0435\u0446"
    ],
    "name:ceb_x_preferred":[
        "Brestovec"
    ],
    "name:hrv_x_preferred":[
        "Brestovec"
    ],
    "name:nld_x_preferred":[
        "Brestovec"
    ],
    "name:pol_x_preferred":[
        "Brestovec"
    ],
    "name:ron_x_preferred":[
        "Brestovec"
    ],
    "name:slv_x_preferred":[
        "Brestovec"
    ],
    "name:ukr_x_preferred":[
        "\u0411\u0440\u0435\u0441\u0442\u043e\u0432\u0435\u0446\u044c"
    ],
    "wof:name":"Brestovec",
    "wof:placetype":"locality",
    "wof:population":156
},
  "geometry": {"coordinates":[15.62681,46.21431],"type":"Point"}
}