{
  "type": "Feature",
  "properties": {
    "gn:admin1_code":"66",
    "gn:asciiname":"Lazec",
    "gn:country_code":"SI",
    "gn:dem":804,
    "gn:feature_class":"P",
    "gn:feature_code":"PPL",
    "gn:name":"Lazec",
    "gn:population":42,
    "gn:timezone":"Europe/Ljubljana",
    "iso:country":"SI",
    "wof:name":"Lazec",
    "wof:placetype":"locality",
    "wof:population":42
},
  "geometry": {"coordinates":[14.63306,45.65],"type":"Point"}
}