{
  "type": "Feature",
  "properties": {
    "gn:admin1_code":"D8",
    "gn:asciiname":"Uzmani",
    "gn:country_code":"SI",
    "gn:dem":859,
    "gn:feature_class":"P",
    "gn:feature_code":"PPL",
    "gn:name":"Uzmani",
    "gn:population":18,
    "gn:timezone":"Europe/Ljubljana",
    "iso:country":"SI",
    "name:bos_x_preferred":[
        "Uzmani"
    ],
    "name:nld_x_preferred":[
        "Uzmani"
    ],
    "name:pol_x_preferred":[
        "Uzmani"
    ],
    "name:ron_x_preferred":[
        "Uzmani"
    ],
    "name:slv_x_preferred":[
        "Uzmani"
    ],
    "name:ukr_x_preferred":[
        "\u0423\u0437\u043c\u0430\u043d\u0438"
    ],
    "wof:name":"Uzmani",
    "wof:placetype":"locality",
    "wof:population":18
},
  "geometry": {"coordinates":[14.52944,45.8516],"type":"Point"}
}