{
  "type": "Feature",
  "properties": {
    "gn:admin1_code":"81",
    "gn:asciiname":"Gortina",
    "gn:country_code":"SI",
    "gn:dem":370,
    "gn:feature_class":"P",
    "gn:feature_code":"PPL",
    "gn:name":"Gortina",
    "gn:population":601,
    "gn:timezone":"Europe/Ljubljana",
    "iso:country":"SI",
    "wof:name":"Gortina",
    "wof:placetype":"locality",
    "wof:population":601
},
  "geometry": {"coordinates":[15.12639,46.60583],"type":"Point"}
}