{
  "type": "Feature",
  "properties": {
    "gn:admin1_code":"50",
    "gn:asciiname":"Kastelec",
    "gn:country_code":"SI",
    "gn:dem":319,
    "gn:feature_class":"P",
    "gn:feature_code":"PPL",
    "gn:name":"Kastelec",
    "gn:population":70,
    "gn:timezone":"Europe/Ljubljana",
    "iso:country":"SI",
    "name:und_x_variant":[
        "Castel",
        "Kastelec"
    ],
    "wof:name":"Kastelec",
    "wof:placetype":"locality",
    "wof:population":70
},
  "geometry": {"coordinates":[13.87278,45.58111],"type":"Point"}
}