{
  "type": "Feature",
  "properties": {
    "gn:admin1_code":"50",
    "gn:asciiname":"Kastelec",
    "gn:country_code":"SI",
    "gn:dem":319,
    "gn:feature_class":"P",
    "gn:feature_code":"PPL",
    "gn:name":"Kastelec",
    "gn:population":70,
    "gn:timezone":"Europe/Ljubljana",
    "iso:country":"SI",
    "name:bos_x_preferred":[
        "Kastelec"
    ],
    "name:bul_x_preferred":[
        "\u041a\u0430\u0441\u0442\u0435\u043b\u0435\u0446"
    ],
    "name:ita_x_preferred":[
        "Castel"
    ],
    "name:nld_x_preferred":[
        "Kastelec"
    ],
    "name:pol_x_preferred":[
        "Kastelec"
    ],
    "name:ron_x_preferred":[
        "Kastelec"
    ],
    "name:slv_x_preferred":[
        "Kastelec"
    ],
    "name:ukr_x_preferred":[
        "\u041a\u0430\u0441\u0442\u0435\u043b\u0435\u0446\u044c"
    ],
    "wof:name":"Kastelec",
    "wof:placetype":"locality",
    "wof:population":70
},
  "geometry": {"coordinates":[13.87278,45.58111],"type":"Point"}
}