{
  "type": "Feature",
  "properties": {
    "gn:admin1_code":"E7",
    "gn:asciiname":"Zabava",
    "gn:country_code":"SI",
    "gn:dem":528,
    "gn:feature_class":"P",
    "gn:feature_code":"PPL",
    "gn:name":"Zabava",
    "gn:population":55,
    "gn:timezone":"Europe/Ljubljana",
    "iso:country":"SI",
    "wof:name":"Zabava",
    "wof:placetype":"locality",
    "wof:population":55
},
  "geometry": {"coordinates":[14.89009,46.1426],"type":"Point"}
}