{
  "type": "Feature",
  "properties": {
    "gn:admin1_code":"E7",
    "gn:asciiname":"Zabava",
    "gn:country_code":"SI",
    "gn:dem":528,
    "gn:feature_class":"P",
    "gn:feature_code":"PPL",
    "gn:name":"Zabava",
    "gn:population":55,
    "gn:timezone":"Europe/Ljubljana",
    "iso:country":"SI",
    "name:nld_x_preferred":[
        "Zabava"
    ],
    "name:pol_x_preferred":[
        "Zabava"
    ],
    "name:ron_x_preferred":[
        "Zabava"
    ],
    "name:slv_x_preferred":[
        "Zabava"
    ],
    "name:ukr_x_preferred":[
        "\u0417\u0430\u0431\u0430\u0432\u0430"
    ],
    "name:urd_x_preferred":[
        "\u0632\u0627\u0628\u0627\u0648\u0627"
    ],
    "wof:name":"Zabava",
    "wof:placetype":"locality",
    "wof:population":55
},
  "geometry": {"coordinates":[14.89009,46.1426],"type":"Point"}
}