{
  "type": "Feature",
  "properties": {
    "gn:admin1_code":"37",
    "gn:asciiname":"Babna Gorica",
    "gn:country_code":"SI",
    "gn:dem":284,
    "gn:feature_class":"P",
    "gn:feature_code":"PPL",
    "gn:name":"Babna Gorica",
    "gn:population":0,
    "gn:timezone":"Europe/Ljubljana",
    "iso:country":"SI",
    "name:und_x_variant":[
        "Babina Gorica",
        "Babna Gorica"
    ],
    "wof:name":"Babna Gorica",
    "wof:placetype":"locality"
},
  "geometry": {"coordinates":[14.51306,45.98528],"type":"Point"}
}