{
  "type": "Feature",
  "properties": {
    "iso:country":"SI",
    "name:bos_x_preferred":[
        "Begunje na Gorenjskem"
    ],
    "name:dut_x_preferred":[
        "Begunje na Gorenjskem"
    ],
    "name:eng_x_preferred":[
        "Begunje na Gorenjskem"
    ],
    "name:ger_x_preferred":[
        "Begunje"
    ],
    "name:gre_x_preferred":[
        "\u039c\u03c0\u03ad\u03b3\u03ba\u03bf\u03c5\u03bd\u03b9\u03b5"
    ],
    "name:hrv_x_preferred":[
        "Begunje na Gorenjskem"
    ],
    "name:rum_x_preferred":[
        "Begunje na Gorenjskem"
    ],
    "name:slv_x_preferred":[
        "Begunje na Gorenjskem"
    ],
    "name:swe_x_preferred":[
        "Begunje"
    ],
    "name:ukr_x_preferred":[
        "\u0411\u0435\u0433\u0443\u043d\u0454 \u043d\u0430 \u0413\u043e\u0440\u0435\u043d\u044c\u0441\u044c\u043a\u0435\u043c"
    ],
    "qs_pg:aaroncc":"SI",
    "qs_pg:name":"Begunje Na Gorenjskem",
    "qs_pg:name_adm0":"Slovenija",
    "qs_pg:name_adm1":"Radovljica",
    "qs_pg:photos":109,
    "qs_pg:photos_1k":22,
    "qs_pg:photos_9k":1,
    "qs_pg:photos_9r":3,
    "qs_pg:photos_all":109,
    "qs_pg:photos_sr":3,
    "qs_pg:pop_sr":0,
    "qs_pg:qs_pg_placetype":"locality",
    "qs_pg:qs_pg_placetype_gp":"Town",
    "qs_pg:woe_adm0":23424945,
    "woe:adm0_id":23424945,
    "woe:name_adm0":"Slovenija",
    "woe:name_adm1":"Radovljica",
    "woe:placetype":"Town",
    "wof:name":"Begunje Na Gorenjskem",
    "wof:placetype":"locality"
},
  "geometry": {"coordinates":[14.215536,46.384241],"type":"Point"}
}