{
  "type": "Feature",
  "properties": {
    "gn:admin1_code":"13",
    "gn:asciiname":"Scurkovo",
    "gn:country_code":"SI",
    "gn:dem":702,
    "gn:feature_class":"P",
    "gn:feature_code":"PPL",
    "gn:name":"\u0160\u010durkovo",
    "gn:population":0,
    "gn:timezone":"Europe/Ljubljana",
    "iso:country":"SI",
    "name:und_x_variant":[
        "\u0160\u010durkovo"
    ],
    "wof:name":"Scurkovo",
    "wof:placetype":"locality"
},
  "geometry": {"coordinates":[14.48081,45.83136],"type":"Point"}
}