{
  "type": "Feature",
  "properties": {
    "gn:admin1_code":"E1",
    "gn:asciiname":"Sanabor",
    "gn:country_code":"SI",
    "gn:dem":328,
    "gn:feature_class":"P",
    "gn:feature_code":"PPL",
    "gn:name":"Sanabor",
    "gn:population":89,
    "gn:timezone":"Europe/Ljubljana",
    "iso:country":"SI",
    "name:bos_x_preferred":[
        "Sanabor"
    ],
    "name:hun_x_preferred":[
        "Sanabor"
    ],
    "name:nld_x_preferred":[
        "Sanabor"
    ],
    "name:pol_x_preferred":[
        "Sanabor"
    ],
    "name:ron_x_preferred":[
        "Sanabor"
    ],
    "name:slv_x_preferred":[
        "Sanabor"
    ],
    "name:ukr_x_preferred":[
        "\u0421\u0430\u043d\u0430\u0431\u043e\u0440"
    ],
    "name:und_x_variant":[
        "Senabor-Val Bella"
    ],
    "wof:name":"Sanabor",
    "wof:placetype":"locality",
    "wof:population":89
},
  "geometry": {"coordinates":[13.98694,45.87389],"type":"Point"}
}