{
  "type": "Feature",
  "properties": {
    "gn:admin1_code":"L7",
    "gn:asciiname":"Planina pri Sevnici",
    "gn:country_code":"SI",
    "gn:dem":458,
    "gn:feature_class":"P",
    "gn:feature_code":"PPL",
    "gn:name":"Planina pri Sevnici",
    "gn:population":378,
    "gn:timezone":"Europe/Ljubljana",
    "iso:country":"SI",
    "name:bos_x_preferred":[
        "Planina pri Sevnici"
    ],
    "name:ceb_x_preferred":[
        "Planina pri Sevnici"
    ],
    "name:hrv_x_preferred":[
        "Planina pri Sevnici"
    ],
    "name:nld_x_preferred":[
        "Planina pri Sevnici"
    ],
    "name:pol_x_preferred":[
        "Planina pri Sevnici"
    ],
    "name:ron_x_preferred":[
        "Planina pri Sevnici"
    ],
    "name:sco_x_preferred":[
        "Planina pri Sevnici"
    ],
    "name:slv_x_preferred":[
        "Planina pri Sevnici"
    ],
    "name:srp_x_preferred":[
        "\u041f\u043b\u0430\u043d\u0438\u043d\u0430 \u043f\u0440\u0438 \u0421\u0435\u0432\u043d\u0438\u0446\u0438"
    ],
    "name:ukr_x_preferred":[
        "\u041f\u043b\u0430\u043d\u0438\u043d\u0430-\u043f\u0440\u0438-\u0421\u0435\u0432\u043d\u0438\u0446\u0456"
    ],
    "name:und_x_variant":[
        "Planina",
        "Planina pri Sevnici"
    ],
    "wof:name":"Planina pri Sevnici",
    "wof:placetype":"locality",
    "wof:population":378
},
  "geometry": {"coordinates":[15.40944,46.11139],"type":"Point"}
}