{
  "type": "Feature",
  "properties": {
    "gn:admin1_code":"L7",
    "gn:asciiname":"Planina pri Sevnici",
    "gn:country_code":"SI",
    "gn:dem":458,
    "gn:feature_class":"P",
    "gn:feature_code":"PPL",
    "gn:name":"Planina pri Sevnici",
    "gn:population":378,
    "gn:timezone":"Europe/Ljubljana",
    "iso:country":"SI",
    "name:und_x_variant":[
        "Planina",
        "Planina pri Sevnici"
    ],
    "wof:name":"Planina pri Sevnici",
    "wof:placetype":"locality",
    "wof:population":378
},
  "geometry": {"coordinates":[15.40944,46.11139],"type":"Point"}
}