{
  "type": "Feature",
  "properties": {
    "gn:admin1_code":"B8",
    "gn:asciiname":"Dobrava pri Skocjanu",
    "gn:country_code":"SI",
    "gn:dem":159,
    "gn:feature_class":"P",
    "gn:feature_code":"PPL",
    "gn:name":"Dobrava pri \u0160kocjanu",
    "gn:population":197,
    "gn:timezone":"Europe/Ljubljana",
    "iso:country":"SI",
    "name:bos_x_preferred":[
        "Dobrava pri \u0160kocjanu"
    ],
    "name:ceb_x_preferred":[
        "Dobrava pri \u0160kocjanu"
    ],
    "name:hrv_x_preferred":[
        "Dobrava pri \u0160kocjanu"
    ],
    "name:nld_x_preferred":[
        "Dobrava pri \u0160kocjanu"
    ],
    "name:pol_x_preferred":[
        "Dobrava pri \u0160kocjanu"
    ],
    "name:ron_x_preferred":[
        "Dobrava pri \u0160kocjanu"
    ],
    "name:slv_x_preferred":[
        "Dobrava pri \u0160kocjanu"
    ],
    "name:ukr_x_preferred":[
        "\u0414\u043e\u0431\u0440\u0430\u0432\u0430-\u043f\u0440\u0438-\u0428\u043a\u043e\u0446\u044f\u043d\u0443"
    ],
    "name:und_x_variant":[
        "Dobrava"
    ],
    "wof:name":"Dobrava pri Skocjanu",
    "wof:placetype":"locality",
    "wof:population":197
},
  "geometry": {"coordinates":[15.31872,45.87452],"type":"Point"}
}