{
  "type": "Feature",
  "properties": {
    "gn:admin1_code":"B8",
    "gn:asciiname":"Dobrava pri Skocjanu",
    "gn:country_code":"SI",
    "gn:dem":159,
    "gn:feature_class":"P",
    "gn:feature_code":"PPL",
    "gn:name":"Dobrava pri \u0160kocjanu",
    "gn:population":197,
    "gn:timezone":"Europe/Ljubljana",
    "iso:country":"SI",
    "name:und_x_variant":[
        "Dobrava",
        "Dobrava pri \u0160kocjanu"
    ],
    "wof:name":"Dobrava pri Skocjanu",
    "wof:placetype":"locality",
    "wof:population":197
},
  "geometry": {"coordinates":[15.31872,45.87452],"type":"Point"}
}