{
  "type": "Feature",
  "properties": {
    "gn:admin1_code":"17",
    "gn:asciiname":"Decina",
    "gn:country_code":"SI",
    "gn:dem":239,
    "gn:feature_class":"P",
    "gn:feature_code":"PPL",
    "gn:name":"De\u010dina",
    "gn:population":1,
    "gn:timezone":"Europe/Ljubljana",
    "iso:country":"SI",
    "name:und_x_variant":[
        "De\u010dina"
    ],
    "wof:name":"Decina",
    "wof:placetype":"locality",
    "wof:population":1
},
  "geometry": {"coordinates":[15.08899,45.47678],"type":"Point"}
}