{
  "type": "Feature",
  "properties": {
    "gn:admin1_code":"01",
    "gn:asciiname":"Visnje",
    "gn:country_code":"SI",
    "gn:dem":750,
    "gn:feature_class":"P",
    "gn:feature_code":"PPL",
    "gn:name":"Vi\u0161nje",
    "gn:population":178,
    "gn:timezone":"Europe/Ljubljana",
    "iso:country":"SI",
    "name:bos_x_preferred":[
        "Vi\u0161nje"
    ],
    "name:bul_x_preferred":[
        "\u0412\u0438\u0448\u043d\u0435"
    ],
    "name:ceb_x_preferred":[
        "Vi\u0161nje"
    ],
    "name:hrv_x_preferred":[
        "Vi\u0161nje"
    ],
    "name:hun_x_preferred":[
        "Vi\u0161nje"
    ],
    "name:ita_x_preferred":[
        "Visne"
    ],
    "name:nld_x_preferred":[
        "Vi\u0161nje"
    ],
    "name:pol_x_preferred":[
        "Vi\u0161nje"
    ],
    "name:ron_x_preferred":[
        "Vi\u0161nje"
    ],
    "name:slv_x_preferred":[
        "Vi\u0161nje"
    ],
    "name:srp_x_preferred":[
        "\u0412\u0438\u0448\u045a\u0435"
    ],
    "name:ukr_x_preferred":[
        "\u0412\u0438\u0448\u043d\u0454"
    ],
    "wof:name":"Visnje",
    "wof:placetype":"locality",
    "wof:population":178
},
  "geometry": {"coordinates":[14.02833,45.87056],"type":"Point"}
}