{
  "type": "Feature",
  "properties": {
    "gn:admin1_code":"01",
    "gn:asciiname":"Visnje",
    "gn:country_code":"SI",
    "gn:dem":750,
    "gn:feature_class":"P",
    "gn:feature_code":"PPL",
    "gn:name":"Vi\u0161nje",
    "gn:population":178,
    "gn:timezone":"Europe/Ljubljana",
    "iso:country":"SI",
    "name:und_x_variant":[
        "Visne",
        "Vi\u0161nje"
    ],
    "wof:name":"Visnje",
    "wof:placetype":"locality",
    "wof:population":178
},
  "geometry": {"coordinates":[14.02833,45.87056],"type":"Point"}
}