{
  "type": "Feature",
  "properties": {
    "gn:admin1_code":"F9",
    "gn:asciiname":"Smolinci",
    "gn:country_code":"SI",
    "gn:dem":269,
    "gn:feature_class":"P",
    "gn:feature_code":"PPL",
    "gn:name":"Smolinci",
    "gn:population":138,
    "gn:timezone":"Europe/Ljubljana",
    "iso:country":"SI",
    "name:bos_x_preferred":[
        "Smolinci"
    ],
    "name:ceb_x_preferred":[
        "Smolinci"
    ],
    "name:nld_x_preferred":[
        "Smolinci"
    ],
    "name:pol_x_preferred":[
        "Smolinci"
    ],
    "name:ron_x_preferred":[
        "Smolinci"
    ],
    "name:slv_x_preferred":[
        "Smolinci"
    ],
    "name:ukr_x_preferred":[
        "\u0421\u043c\u043e\u043b\u0438\u043d\u0446\u0456"
    ],
    "wof:name":"Smolinci",
    "wof:placetype":"locality",
    "wof:population":138
},
  "geometry": {"coordinates":[15.97089,46.54408],"type":"Point"}
}