{
  "type": "Feature",
  "properties": {
    "gn:admin1_code":"20",
    "gn:asciiname":"Rapljevo",
    "gn:country_code":"SI",
    "gn:dem":452,
    "gn:feature_class":"P",
    "gn:feature_code":"PPL",
    "gn:name":"Rapljevo",
    "gn:population":69,
    "gn:timezone":"Europe/Ljubljana",
    "iso:country":"SI",
    "name:und_x_variant":[
        "Veliko Rapljevo",
        "Rapljevo"
    ],
    "wof:name":"Rapljevo",
    "wof:placetype":"locality",
    "wof:population":69
},
  "geometry": {"coordinates":[14.78944,45.76278],"type":"Point"}
}