{
  "type": "Feature",
  "properties": {
    "gn:admin1_code":"20",
    "gn:asciiname":"Rapljevo",
    "gn:country_code":"SI",
    "gn:dem":452,
    "gn:feature_class":"P",
    "gn:feature_code":"PPL",
    "gn:name":"Rapljevo",
    "gn:population":69,
    "gn:timezone":"Europe/Ljubljana",
    "iso:country":"SI",
    "name:bos_x_preferred":[
        "Rapljevo"
    ],
    "name:bul_x_preferred":[
        "\u0420\u0430\u043f\u043b\u0435\u0432\u043e"
    ],
    "name:nld_x_preferred":[
        "Rapljevo"
    ],
    "name:pol_x_preferred":[
        "Rapljevo"
    ],
    "name:ron_x_preferred":[
        "Rapljevo"
    ],
    "name:slv_x_preferred":[
        "Rapljevo"
    ],
    "name:ukr_x_preferred":[
        "\u0420\u0430\u043f\u043b\u0454\u0432\u043e"
    ],
    "name:und_x_variant":[
        "Veliko Rapljevo"
    ],
    "wof:name":"Rapljevo",
    "wof:placetype":"locality",
    "wof:population":69
},
  "geometry": {"coordinates":[14.78944,45.76278],"type":"Point"}
}