{
  "type": "Feature",
  "properties": {
    "gn:admin1_code":"27",
    "gn:asciiname":"Hotavlje",
    "gn:country_code":"SI",
    "gn:dem":467,
    "gn:feature_class":"P",
    "gn:feature_code":"PPL",
    "gn:name":"Hotavlje",
    "gn:population":396,
    "gn:timezone":"Europe/Ljubljana",
    "iso:country":"SI",
    "name:bos_x_preferred":[
        "Hotavlje"
    ],
    "name:ceb_x_preferred":[
        "Hotavlje"
    ],
    "name:hrv_x_preferred":[
        "Hotavlje"
    ],
    "name:nld_x_preferred":[
        "Hotavlje"
    ],
    "name:pol_x_preferred":[
        "Hotavlje"
    ],
    "name:ron_x_preferred":[
        "Hotavlje"
    ],
    "name:slv_x_preferred":[
        "Hotavlje"
    ],
    "name:ukr_x_preferred":[
        "\u0425\u043e\u0442\u0430\u0432\u043b\u0454"
    ],
    "wof:name":"Hotavlje",
    "wof:placetype":"locality",
    "wof:population":396
},
  "geometry": {"coordinates":[14.11861,46.11222],"type":"Point"}
}