{
  "type": "Feature",
  "properties": {
    "gn:admin1_code":"27",
    "gn:asciiname":"Hotavlje",
    "gn:country_code":"SI",
    "gn:dem":467,
    "gn:feature_class":"P",
    "gn:feature_code":"PPL",
    "gn:name":"Hotavlje",
    "gn:population":396,
    "gn:timezone":"Europe/Ljubljana",
    "iso:country":"SI",
    "wof:name":"Hotavlje",
    "wof:placetype":"locality",
    "wof:population":396
},
  "geometry": {"coordinates":[14.11861,46.11222],"type":"Point"}
}