{
  "type": "Feature",
  "properties": {
    "gn:admin1_code":"54",
    "gn:asciiname":"Velika Vas pri Krskem",
    "gn:country_code":"SI",
    "gn:dem":158,
    "gn:feature_class":"P",
    "gn:feature_code":"PPL",
    "gn:name":"Velika Vas pri Kr\u0161kem",
    "gn:population":266,
    "gn:timezone":"Europe/Ljubljana",
    "iso:country":"SI",
    "name:bos_x_preferred":[
        "Velika vas pri Kr\u0161kem"
    ],
    "name:ceb_x_preferred":[
        "Velika Vas pri Kr\u0161kem"
    ],
    "name:fas_x_preferred":[
        "\u0648\u0644\u06cc\u06a9\u0627 \u0648\u0627\u0633 \u067e\u0631\u06cc \u06a9\u0631\u0634\u06a9\u0645"
    ],
    "name:hrv_x_preferred":[
        "Velika vas pri Kr\u0161kem"
    ],
    "name:nld_x_preferred":[
        "Velika vas pri Kr\u0161kem"
    ],
    "name:pol_x_preferred":[
        "Velika vas pri Kr\u0161kem"
    ],
    "name:ron_x_preferred":[
        "Velika vas pri Kr\u0161kem"
    ],
    "name:slv_x_preferred":[
        "Velika vas pri Kr\u0161kem"
    ],
    "name:ukr_x_preferred":[
        "\u0412\u0435\u043b\u0438\u043a\u0430 \u0412\u0430\u0441-\u043f\u0440\u0438-\u041a\u0440\u0448\u043a\u0435\u043c"
    ],
    "name:und_x_variant":[
        "Velika Vas"
    ],
    "wof:name":"Velika Vas pri Krskem",
    "wof:placetype":"locality",
    "wof:population":266
},
  "geometry": {"coordinates":[15.45972,45.92028],"type":"Point"}
}