{
  "type": "Feature",
  "properties": {
    "gn:admin1_code":"54",
    "gn:asciiname":"Velika Vas pri Krskem",
    "gn:country_code":"SI",
    "gn:dem":158,
    "gn:feature_class":"P",
    "gn:feature_code":"PPL",
    "gn:name":"Velika Vas pri Kr\u0161kem",
    "gn:population":266,
    "gn:timezone":"Europe/Ljubljana",
    "iso:country":"SI",
    "name:und_x_variant":[
        "Velika Vas",
        "Velika Vas pri Kr\u0161kem"
    ],
    "wof:name":"Velika Vas pri Krskem",
    "wof:placetype":"locality",
    "wof:population":266
},
  "geometry": {"coordinates":[15.45972,45.92028],"type":"Point"}
}