{
  "type": "Feature",
  "properties": {
    "gn:admin1_code":"B4",
    "gn:asciiname":"Dolenje Vrhpolje",
    "gn:country_code":"SI",
    "gn:dem":233,
    "gn:feature_class":"P",
    "gn:feature_code":"PPL",
    "gn:name":"Dolenje Vrhpolje",
    "gn:population":139,
    "gn:timezone":"Europe/Ljubljana",
    "iso:country":"SI",
    "name:bos_x_preferred":[
        "Dolenje Vrhpolje"
    ],
    "name:ceb_x_preferred":[
        "Dolenje Vrhpolje"
    ],
    "name:hrv_x_preferred":[
        "Dolenje Vrhpolje"
    ],
    "name:nld_x_preferred":[
        "Dolenje Vrhpolje"
    ],
    "name:pol_x_preferred":[
        "Dolenje Vrhpolje"
    ],
    "name:ron_x_preferred":[
        "Dolenje Vrhpolje"
    ],
    "name:slv_x_preferred":[
        "Dolenje Vrhpolje"
    ],
    "wof:name":"Dolenje Vrhpolje",
    "wof:placetype":"locality",
    "wof:population":139
},
  "geometry": {"coordinates":[15.33566,45.82177],"type":"Point"}
}