{
  "type": "Feature",
  "properties": {
    "gn:admin1_code":"27",
    "gn:asciiname":"Gorenja Dobrava",
    "gn:country_code":"SI",
    "gn:dem":432,
    "gn:feature_class":"P",
    "gn:feature_code":"PPL",
    "gn:name":"Gorenja Dobrava",
    "gn:population":136,
    "gn:timezone":"Europe/Ljubljana",
    "iso:country":"SI",
    "wof:name":"Gorenja Dobrava",
    "wof:placetype":"locality",
    "wof:population":136
},
  "geometry": {"coordinates":[14.15493,46.09084],"type":"Point"}
}