{
  "type": "Feature",
  "properties": {
    "gn:admin1_code":"27",
    "gn:asciiname":"Gorenja Dobrava",
    "gn:country_code":"SI",
    "gn:dem":432,
    "gn:feature_class":"P",
    "gn:feature_code":"PPL",
    "gn:name":"Gorenja Dobrava",
    "gn:population":136,
    "gn:timezone":"Europe/Ljubljana",
    "iso:country":"SI",
    "name:bos_x_preferred":[
        "Gorenja Dobrava"
    ],
    "name:ceb_x_preferred":[
        "Gorenja Dobrava"
    ],
    "name:hrv_x_preferred":[
        "Gorenja Dobrava"
    ],
    "name:nld_x_preferred":[
        "Gorenja Dobrava"
    ],
    "name:pol_x_preferred":[
        "Gorenja Dobrava"
    ],
    "name:ron_x_preferred":[
        "Gorenja Dobrava"
    ],
    "name:slv_x_preferred":[
        "Gorenja Dobrava"
    ],
    "name:ukr_x_preferred":[
        "\u0413\u043e\u0440\u0435\u043d\u044f \u0414\u043e\u0431\u0440\u0430\u0432\u0430"
    ],
    "wof:name":"Gorenja Dobrava",
    "wof:placetype":"locality",
    "wof:population":136
},
  "geometry": {"coordinates":[14.15493,46.09084],"type":"Point"}
}