{
  "type": "Feature",
  "properties": {
    "gn:admin1_code":"44",
    "gn:asciiname":"Kal nad Kanalom",
    "gn:country_code":"SI",
    "gn:dem":667,
    "gn:feature_class":"P",
    "gn:feature_code":"PPL",
    "gn:name":"Kal nad Kanalom",
    "gn:population":327,
    "gn:timezone":"Europe/Ljubljana",
    "iso:country":"SI",
    "name:und_x_variant":[
        "Cal di Canale",
        "Kal Kanalski",
        "Kal"
    ],
    "wof:name":"Kal nad Kanalom",
    "wof:placetype":"locality",
    "wof:population":327
},
  "geometry": {"coordinates":[13.74028,46.08333],"type":"Point"}
}