{
  "type": "Feature",
  "properties": {
    "gn:admin1_code":"44",
    "gn:asciiname":"Kal nad Kanalom",
    "gn:country_code":"SI",
    "gn:dem":667,
    "gn:feature_class":"P",
    "gn:feature_code":"PPL",
    "gn:name":"Kal nad Kanalom",
    "gn:population":327,
    "gn:timezone":"Europe/Ljubljana",
    "iso:country":"SI",
    "name:bos_x_preferred":[
        "Kal nad Kanalom"
    ],
    "name:ceb_x_preferred":[
        "Kal nad Kanalom"
    ],
    "name:nld_x_preferred":[
        "Kal nad Kanalom"
    ],
    "name:pol_x_preferred":[
        "Kal nad Kanalom"
    ],
    "name:ron_x_preferred":[
        "Kal nad Kanalom"
    ],
    "name:slv_x_preferred":[
        "Kal nad Kanalom"
    ],
    "name:ukr_x_preferred":[
        "\u041a\u0430\u043b-\u043d\u0430\u0434-\u041a\u0430\u043d\u0430\u043b\u043e\u043c"
    ],
    "name:und_x_variant":[
        "Cal di Canale",
        "Kal Kanalski",
        "Kal"
    ],
    "wof:name":"Kal nad Kanalom",
    "wof:placetype":"locality",
    "wof:population":327
},
  "geometry": {"coordinates":[13.74028,46.08333],"type":"Point"}
}