{
  "type": "Feature",
  "properties": {
    "gn:admin1_code":"57",
    "gn:asciiname":"Panece",
    "gn:country_code":"SI",
    "gn:dem":487,
    "gn:feature_class":"P",
    "gn:feature_code":"PPL",
    "gn:name":"Pane\u010de",
    "gn:population":129,
    "gn:timezone":"Europe/Ljubljana",
    "iso:country":"SI",
    "name:bos_x_preferred":[
        "Pane\u010de"
    ],
    "name:ceb_x_preferred":[
        "Pane\u010de"
    ],
    "name:hrv_x_preferred":[
        "Pane\u010de"
    ],
    "name:nld_x_preferred":[
        "Pane\u010de"
    ],
    "name:pol_x_preferred":[
        "Pane\u010de"
    ],
    "name:ron_x_preferred":[
        "Pane\u010de"
    ],
    "name:slv_x_preferred":[
        "Pane\u010de"
    ],
    "name:ukr_x_preferred":[
        "\u041f\u0430\u043d\u0435\u0447\u0435"
    ],
    "wof:name":"Panece",
    "wof:placetype":"locality",
    "wof:population":129
},
  "geometry": {"coordinates":[15.28233,46.09133],"type":"Point"}
}