{
  "type": "Feature",
  "properties": {
    "gn:admin1_code":"39",
    "gn:asciiname":"Gradicek",
    "gn:country_code":"SI",
    "gn:dem":277,
    "gn:feature_class":"P",
    "gn:feature_code":"PPL",
    "gn:name":"Gradi\u010dek",
    "gn:population":28,
    "gn:timezone":"Europe/Ljubljana",
    "iso:country":"SI",
    "name:bos_x_preferred":[
        "Gradi\u010dek"
    ],
    "name:nld_x_preferred":[
        "Gradi\u010dek"
    ],
    "name:pol_x_preferred":[
        "Gradi\u010dek"
    ],
    "name:ron_x_preferred":[
        "Gradi\u010dek"
    ],
    "name:slv_x_preferred":[
        "Gradi\u010dek"
    ],
    "name:tur_x_preferred":[
        "Gradi\u010dek"
    ],
    "name:ukr_x_preferred":[
        "\u0413\u0440\u0430\u0434\u0438\u0447\u0435\u043a"
    ],
    "wof:name":"Gradicek",
    "wof:placetype":"locality",
    "wof:population":28
},
  "geometry": {"coordinates":[14.76917,45.88806],"type":"Point"}
}