{
  "type": "Feature",
  "properties": {
    "gn:admin1_code":"39",
    "gn:asciiname":"Gradicek",
    "gn:country_code":"SI",
    "gn:dem":277,
    "gn:feature_class":"P",
    "gn:feature_code":"PPL",
    "gn:name":"Gradi\u010dek",
    "gn:population":28,
    "gn:timezone":"Europe/Ljubljana",
    "iso:country":"SI",
    "name:und_x_variant":[
        "Gradi\u010dek"
    ],
    "wof:name":"Gradicek",
    "wof:placetype":"locality",
    "wof:population":28
},
  "geometry": {"coordinates":[14.76917,45.88806],"type":"Point"}
}