{
  "type": "Feature",
  "properties": {
    "gn:admin1_code":"D2",
    "gn:asciiname":"Daber",
    "gn:country_code":"SI",
    "gn:dem":628,
    "gn:feature_class":"P",
    "gn:feature_code":"PPL",
    "gn:name":"Daber",
    "gn:population":22,
    "gn:timezone":"Europe/Ljubljana",
    "iso:country":"SI",
    "wof:name":"Daber",
    "wof:placetype":"locality",
    "wof:population":22
},
  "geometry": {"coordinates":[13.88702,46.11622],"type":"Point"}
}