{
  "type": "Feature",
  "properties": {
    "gn:admin1_code":"B6",
    "gn:asciiname":"Lukovec",
    "gn:country_code":"SI",
    "gn:dem":305,
    "gn:feature_class":"P",
    "gn:feature_code":"PPL",
    "gn:name":"Lukovec",
    "gn:population":186,
    "gn:timezone":"Europe/Ljubljana",
    "iso:country":"SI",
    "name:bos_x_preferred":[
        "Lukovec"
    ],
    "name:ceb_x_preferred":[
        "Lukovec"
    ],
    "name:nld_x_preferred":[
        "Lukovec"
    ],
    "name:pol_x_preferred":[
        "Lukovec"
    ],
    "name:ron_x_preferred":[
        "Lukovec"
    ],
    "name:slv_x_historical":[
        "Lukovica"
    ],
    "name:slv_x_preferred":[
        "Lukovica"
    ],
    "name:slv_x_variant":[
        "Lukovec"
    ],
    "name:ukr_x_preferred":[
        "\u041b\u0443\u043a\u043e\u0432\u0435\u0446\u044c"
    ],
    "wof:name":"Lukovec",
    "wof:placetype":"locality",
    "wof:population":186
},
  "geometry": {"coordinates":[15.3079,45.99317],"type":"Point"}
}