{
  "type": "Feature",
  "properties": {
    "gn:admin1_code":"B6",
    "gn:asciiname":"Lukovec",
    "gn:country_code":"SI",
    "gn:dem":305,
    "gn:feature_class":"P",
    "gn:feature_code":"PPL",
    "gn:name":"Lukovec",
    "gn:population":186,
    "gn:timezone":"Europe/Ljubljana",
    "iso:country":"SI",
    "name:slv_x_historical":[
        "Lukovica"
    ],
    "name:slv_x_preferred":[
        "Lukovica"
    ],
    "wof:name":"Lukovec",
    "wof:placetype":"locality",
    "wof:population":186
},
  "geometry": {"coordinates":[15.3079,45.99317],"type":"Point"}
}