{
  "type": "Feature",
  "properties": {
    "gn:admin1_code":"B9",
    "gn:asciiname":"Krizna Gora",
    "gn:country_code":"SI",
    "gn:dem":675,
    "gn:feature_class":"P",
    "gn:feature_code":"PPL",
    "gn:name":"Kri\u017ena Gora",
    "gn:population":101,
    "gn:timezone":"Europe/Ljubljana",
    "iso:country":"SI",
    "name:bos_x_preferred":[
        "Kri\u017ena Gora"
    ],
    "name:ceb_x_preferred":[
        "Kri\u017ena Gora"
    ],
    "name:hrv_x_preferred":[
        "Kri\u017ena Gora"
    ],
    "name:nld_x_preferred":[
        "Kri\u017ena Gora"
    ],
    "name:pol_x_preferred":[
        "Kri\u017ena Gora"
    ],
    "name:ron_x_preferred":[
        "Kri\u017ena Gora"
    ],
    "name:slv_x_preferred":[
        "Kri\u017ena Gora"
    ],
    "name:ukr_x_preferred":[
        "\u041a\u0440\u0438\u0436\u043d\u0430 \u0413\u043e\u0440\u0430"
    ],
    "name:und_x_variant":[
        "Kri\u017ena Gora"
    ],
    "wof:name":"Krizna Gora",
    "wof:placetype":"locality",
    "wof:population":101
},
  "geometry": {"coordinates":[14.27501,46.19668],"type":"Point"}
}