{
  "type": "Feature",
  "properties": {
    "iso:country":"SI",
    "name:ron_x_preferred":[
        "Gunclje"
    ],
    "name:slv_x_preferred":[
        "Gunclje"
    ],
    "wof:name":"Gunclje",
    "wof:placetype":"neighbourhood"
},
  "geometry": {"coordinates":[14.45328716912637,46.10194378805234],"type":"Point"}
}