{
  "type": "Feature",
  "properties": {
    "gn:admin1_code":"B6",
    "gn:asciiname":"Dolnje Impolje",
    "gn:country_code":"SI",
    "gn:dem":347,
    "gn:feature_class":"P",
    "gn:feature_code":"PPL",
    "gn:name":"Dolnje Impolje",
    "gn:population":30,
    "gn:timezone":"Europe/Ljubljana",
    "iso:country":"SI",
    "name:bos_x_preferred":[
        "Dolnje Impolje"
    ],
    "name:nld_x_preferred":[
        "Dolnje Impolje"
    ],
    "name:pol_x_preferred":[
        "Dolnje Impolje"
    ],
    "name:ron_x_preferred":[
        "Dolnje Impolje"
    ],
    "name:slv_x_historical":[
        "Dolenje Impole"
    ],
    "name:slv_x_preferred":[
        "Dolenje Impole"
    ],
    "name:slv_x_variant":[
        "Dolnje Impolje"
    ],
    "name:ukr_x_preferred":[
        "\u0414\u043e\u043b\u043d\u0454 \u0406\u043c\u043f\u043e\u043b\u0454"
    ],
    "wof:name":"Dolnje Impolje",
    "wof:placetype":"locality",
    "wof:population":30
},
  "geometry": {"coordinates":[15.31973,45.97194],"type":"Point"}
}