{
  "type": "Feature",
  "properties": {
    "gn:admin1_code":"39",
    "gn:asciiname":"Podsmreka pri Visnji Gori",
    "gn:country_code":"SI",
    "gn:dem":358,
    "gn:feature_class":"P",
    "gn:feature_code":"PPL",
    "gn:name":"Podsmreka pri Vi\u0161nji Gori",
    "gn:population":33,
    "gn:timezone":"Europe/Ljubljana",
    "iso:country":"SI",
    "name:bos_x_preferred":[
        "Podsmreka pri Vi\u0161nji Gori"
    ],
    "name:nld_x_preferred":[
        "Podsmreka pri Vi\u0161nji Gori"
    ],
    "name:pol_x_preferred":[
        "Podsmreka pri Vi\u0161nji Gori"
    ],
    "name:ron_x_preferred":[
        "Podsmreka pri Vi\u0161nji Gori"
    ],
    "name:slv_x_preferred":[
        "Podsmreka pri Vi\u0161nji Gori"
    ],
    "name:ukr_x_preferred":[
        "\u041f\u043e\u0434\u0441\u043c\u0440\u0435\u043a\u0430-\u043f\u0440\u0438-\u0412\u0438\u0448\u043d\u0456 \u0413\u043e\u0440\u0438"
    ],
    "wof:name":"Podsmreka pri Visnji Gori",
    "wof:placetype":"locality",
    "wof:population":33
},
  "geometry": {"coordinates":[14.76498,45.95102],"type":"Point"}
}