{
  "type": "Feature",
  "properties": {
    "gn:admin1_code":"A1",
    "gn:asciiname":"Kopela",
    "gn:country_code":"SI",
    "gn:dem":269,
    "gn:feature_class":"P",
    "gn:feature_code":"PPL",
    "gn:name":"Kopela",
    "gn:population":0,
    "gn:timezone":"Europe/Ljubljana",
    "iso:country":"SI",
    "wof:name":"Kopela",
    "wof:placetype":"locality"
},
  "geometry": {"coordinates":[16.03667,46.62194],"type":"Point"}
}