{
  "type": "Feature",
  "properties": {
    "gn:admin1_code":"84",
    "gn:asciiname":"Ozeljan",
    "gn:country_code":"SI",
    "gn:dem":111,
    "gn:feature_class":"P",
    "gn:feature_code":"PPL",
    "gn:name":"Ozeljan",
    "gn:population":847,
    "gn:timezone":"Europe/Ljubljana",
    "iso:country":"SI",
    "name:und_x_variant":[
        "Ossegliano",
        "Ozeljan"
    ],
    "wof:name":"Ozeljan",
    "wof:placetype":"locality",
    "wof:population":847
},
  "geometry": {"coordinates":[13.73028,45.94361],"type":"Point"}
}