{
  "type": "Feature",
  "properties": {
    "gn:admin1_code":"J2",
    "gn:asciiname":"Nebova",
    "gn:country_code":"SI",
    "gn:dem":327,
    "gn:feature_class":"P",
    "gn:feature_code":"PPL",
    "gn:name":"Nebova",
    "gn:population":128,
    "gn:timezone":"Europe/Ljubljana",
    "iso:country":"SI",
    "name:bos_x_preferred":[
        "Nebova"
    ],
    "name:bul_x_preferred":[
        "\u041d\u0435\u0431\u043e\u0432\u0430"
    ],
    "name:ceb_x_preferred":[
        "Nebova"
    ],
    "name:nld_x_preferred":[
        "Nebova"
    ],
    "name:pol_x_preferred":[
        "Nebova"
    ],
    "name:ron_x_preferred":[
        "Nebova"
    ],
    "name:slv_x_preferred":[
        "Nebova"
    ],
    "name:ukr_x_preferred":[
        "\u041d\u0435\u0431\u043e\u0432\u0430"
    ],
    "wof:name":"Nebova",
    "wof:placetype":"locality",
    "wof:population":128
},
  "geometry": {"coordinates":[15.7289,46.55387],"type":"Point"}
}