{
  "type": "Feature",
  "properties": {
    "iso:country":"SI",
    "name:deu_x_preferred":[
        "St. Peter"
    ],
    "name:deu_x_variant":[
        "Sankt Peter",
        "Skt Peter",
        "Skt. Peter",
        "St Peter"
    ],
    "name:eng_x_preferred":[
        "Sankt Peter bei Graz"
    ],
    "name:eng_x_variant":[
        "Skt Peter bei Graz",
        "Skt. Peter bei Graz",
        "St Peter bei Graz",
        "St. Peter bei Graz",
        "Sankt Peter bei Graz"
    ],
    "qs:gn_adm0_cc":"AT",
    "qs:gn_fcode":"PPL",
    "qs:gn_local":7871499,
    "qs:gn_nam_loc":"Graz, Graz Stadt, Steiermark, AT",
    "qs:gn_namadm1":"81",
    "qs:gn_name":"Sveti Peter",
    "qs:local_max":3393,
    "qs:local_sum":13910,
    "qs:localhoods":22,
    "qs:name":"St. Peter",
    "qs:name_adm0":"\u00d6sterreich",
    "qs:name_adm1":"Steiermark",
    "qs:name_adm2":"Graz Stadt",
    "qs:name_en":"Sankt Peter bei Graz",
    "qs:name_lau":"Graz",
    "qs:name_local":"Graz",
    "qs:photo_max":87,
    "qs:photo_sum":186,
    "qs:placetype":"Suburb",
    "qs:quad_count":14,
    "qs:woe_adm0":23424750,
    "qs:woe_adm1":2344713,
    "qs:woe_adm2":12591740,
    "qs:woe_lau":12674996,
    "qs:woe_local":12674996,
    "qs:woe_ver":"7.10.0",
    "wof:lang":[
        "ger"
    ],
    "wof:name":"St. Peter",
    "wof:placetype":"neighbourhood"
},
  "geometry": {"coordinates":[15.478186,47.048936],"type":"Point"}
}