{
  "type": "Feature",
  "properties": {
    "gn:admin1_code":"C8",
    "gn:asciiname":"Prepolje",
    "gn:country_code":"SI",
    "gn:dem":243,
    "gn:feature_class":"P",
    "gn:feature_code":"PPL",
    "gn:name":"Prepolje",
    "gn:population":538,
    "gn:timezone":"Europe/Ljubljana",
    "iso:country":"SI",
    "name:bos_x_preferred":[
        "Prepolje"
    ],
    "name:ceb_x_preferred":[
        "Prepolje"
    ],
    "name:nld_x_preferred":[
        "Prepolje"
    ],
    "name:pol_x_preferred":[
        "Prepolje"
    ],
    "name:ron_x_preferred":[
        "Prepolje"
    ],
    "name:slv_x_preferred":[
        "Prepolje"
    ],
    "name:ukr_x_preferred":[
        "\u041f\u0440\u0435\u043f\u043e\u043b\u0454"
    ],
    "wof:name":"Prepolje",
    "wof:placetype":"locality",
    "wof:population":538
},
  "geometry": {"coordinates":[15.76389,46.44417],"type":"Point"}
}