{
  "type": "Feature",
  "properties": {
    "gn:admin1_code":"C4",
    "gn:asciiname":"Spitalic pri Slov. Konjicah",
    "gn:country_code":"SI",
    "gn:dem":391,
    "gn:feature_class":"P",
    "gn:feature_code":"PPL",
    "gn:name":"\u0160pitali\u010d pri Slov. Konjicah",
    "gn:population":14,
    "gn:timezone":"Europe/Ljubljana",
    "iso:country":"SI",
    "name:und_x_variant":[
        "\u0160pitali\u010d pri Slov. Konjicah"
    ],
    "wof:name":"Spitalic pri Slov. Konjicah",
    "wof:placetype":"locality",
    "wof:population":14
},
  "geometry": {"coordinates":[15.40767,46.30898],"type":"Point"}
}