{
  "type": "Feature",
  "properties": {
    "gn:admin1_code":"84",
    "gn:asciiname":"Gorenja vas",
    "gn:country_code":"SI",
    "gn:dem":308,
    "gn:feature_class":"P",
    "gn:feature_code":"PPLL",
    "gn:name":"Gorenja vas",
    "gn:population":0,
    "gn:timezone":"Europe/Ljubljana",
    "iso:country":"SI",
    "wof:name":"Gorenja vas",
    "wof:placetype":"locality"
},
  "geometry": {"coordinates":[13.66596,46.00438],"type":"Point"}
}