{
  "type": "Feature",
  "properties": {
    "gn:admin1_code":"27",
    "gn:asciiname":"Hotovlja",
    "gn:country_code":"SI",
    "gn:dem":544,
    "gn:feature_class":"P",
    "gn:feature_code":"PPL",
    "gn:name":"Hotovlja",
    "gn:population":254,
    "gn:timezone":"Europe/Ljubljana",
    "iso:country":"SI",
    "name:bos_x_preferred":[
        "Hotovlja"
    ],
    "name:ceb_x_preferred":[
        "Hotovlja"
    ],
    "name:hrv_x_preferred":[
        "Hotovlja"
    ],
    "name:nld_x_preferred":[
        "Hotovlja"
    ],
    "name:pol_x_preferred":[
        "Hotovlja"
    ],
    "name:ron_x_preferred":[
        "Hotovlja"
    ],
    "name:slv_x_preferred":[
        "Hotovlja"
    ],
    "name:ukr_x_preferred":[
        "\u0425\u043e\u0442\u043e\u0432\u043b\u044f"
    ],
    "wof:name":"Hotovlja",
    "wof:placetype":"locality",
    "wof:population":254
},
  "geometry": {"coordinates":[14.19402,46.11316],"type":"Point"}
}