{
  "type": "Feature",
  "properties": {
    "gn:admin1_code":"27",
    "gn:asciiname":"Hotovlja",
    "gn:country_code":"SI",
    "gn:dem":544,
    "gn:feature_class":"P",
    "gn:feature_code":"PPL",
    "gn:name":"Hotovlja",
    "gn:population":254,
    "gn:timezone":"Europe/Ljubljana",
    "iso:country":"SI",
    "wof:name":"Hotovlja",
    "wof:placetype":"locality",
    "wof:population":254
},
  "geometry": {"coordinates":[14.19402,46.11316],"type":"Point"}
}