{
  "type": "Feature",
  "properties": {
    "gn:admin1_code":"I5",
    "gn:asciiname":"Prezenjske Njive",
    "gn:country_code":"SI",
    "gn:dem":620,
    "gn:feature_class":"P",
    "gn:feature_code":"PPL",
    "gn:name":"Pre\u017eenjske Njive",
    "gn:population":20,
    "gn:timezone":"Europe/Ljubljana",
    "iso:country":"SI",
    "name:bos_x_preferred":[
        "Pre\u017eenjske Njive"
    ],
    "name:bul_x_preferred":[
        "\u041f\u0440\u0435\u0436\u0435\u043d\u0441\u043a\u0435 \u041d\u0438\u0432\u0435"
    ],
    "name:nld_x_preferred":[
        "Pre\u017eenjske Njive"
    ],
    "name:pol_x_preferred":[
        "Pre\u017eenjske Njive"
    ],
    "name:ron_x_preferred":[
        "Pre\u017eenjske Njive"
    ],
    "name:slv_x_preferred":[
        "Pre\u017eenjske Njive"
    ],
    "name:ukr_x_preferred":[
        "\u041f\u0440\u0435\u0436\u0435\u043d\u044c\u0441\u044c\u043a\u0435 \u041d\u0456\u0432\u0435"
    ],
    "wof:name":"Prezenjske Njive",
    "wof:placetype":"locality",
    "wof:population":20
},
  "geometry": {"coordinates":[14.991,46.03125],"type":"Point"}
}