{
  "type": "Feature",
  "properties": {
    "gn:admin1_code":"I5",
    "gn:asciiname":"Prezenjske Njive",
    "gn:country_code":"SI",
    "gn:dem":620,
    "gn:feature_class":"P",
    "gn:feature_code":"PPL",
    "gn:name":"Pre\u017eenjske Njive",
    "gn:population":20,
    "gn:timezone":"Europe/Ljubljana",
    "iso:country":"SI",
    "name:und_x_variant":[
        "Pre\u017eenjske Njive"
    ],
    "wof:name":"Prezenjske Njive",
    "wof:placetype":"locality",
    "wof:population":20
},
  "geometry": {"coordinates":[14.991,46.03125],"type":"Point"}
}