{
  "type": "Feature",
  "properties": {
    "gn:admin1_code":"84",
    "gn:asciiname":"Na Obcinah",
    "gn:country_code":"SI",
    "gn:dem":625,
    "gn:feature_class":"P",
    "gn:feature_code":"PPL",
    "gn:name":"Na Ob\u010dinah",
    "gn:population":0,
    "gn:timezone":"Europe/Ljubljana",
    "iso:country":"SI",
    "name:slv_x_historical":[
        "Ob\u010dine"
    ],
    "name:slv_x_preferred":[
        "Ob\u010dine"
    ],
    "wof:name":"Na Obcinah",
    "wof:placetype":"locality"
},
  "geometry": {"coordinates":[13.79555,46.0777],"type":"Point"}
}