{
  "type": "Feature",
  "properties": {
    "gn:admin1_code":"17",
    "gn:asciiname":"Marindol",
    "gn:country_code":"SI",
    "gn:dem":227,
    "gn:feature_class":"P",
    "gn:feature_code":"PPL",
    "gn:name":"Marindol",
    "gn:population":95,
    "gn:timezone":"Europe/Ljubljana",
    "iso:country":"SI",
    "name:bos_x_preferred":[
        "Marindol"
    ],
    "name:hrv_x_preferred":[
        "Marindol"
    ],
    "name:nld_x_preferred":[
        "Marindol"
    ],
    "name:pol_x_preferred":[
        "Marindol"
    ],
    "name:ron_x_preferred":[
        "Marindol"
    ],
    "name:slv_x_preferred":[
        "Marindol"
    ],
    "name:srp_x_preferred":[
        "\u041c\u0430\u0440\u0438\u043d\u0434\u043e\u043b"
    ],
    "name:ukr_x_preferred":[
        "\u041c\u0430\u0440\u0438\u043d\u0434\u043e\u043b"
    ],
    "wof:name":"Marindol",
    "wof:placetype":"locality",
    "wof:population":95
},
  "geometry": {"coordinates":[15.33322,45.50502],"type":"Point"}
}