{
  "type": "Feature",
  "properties": {
    "gn:admin1_code":"17",
    "gn:asciiname":"Marindol",
    "gn:country_code":"SI",
    "gn:dem":227,
    "gn:feature_class":"P",
    "gn:feature_code":"PPL",
    "gn:name":"Marindol",
    "gn:population":95,
    "gn:timezone":"Europe/Ljubljana",
    "iso:country":"SI",
    "wof:name":"Marindol",
    "wof:placetype":"locality",
    "wof:population":95
},
  "geometry": {"coordinates":[15.33322,45.50502],"type":"Point"}
}