{
  "type": "Feature",
  "properties": {
    "gn:admin1_code":"68",
    "gn:asciiname":"Podmilj",
    "gn:country_code":"SI",
    "gn:dem":486,
    "gn:feature_class":"P",
    "gn:feature_code":"PPL",
    "gn:name":"Podmilj",
    "gn:population":53,
    "gn:timezone":"Europe/Ljubljana",
    "iso:country":"SI",
    "name:bos_x_preferred":[
        "Podmilj"
    ],
    "name:nld_x_preferred":[
        "Podmilj"
    ],
    "name:pol_x_preferred":[
        "Podmilj"
    ],
    "name:ron_x_preferred":[
        "Podmilj"
    ],
    "name:slv_x_preferred":[
        "Podmilj"
    ],
    "name:ukr_x_preferred":[
        "\u041f\u043e\u0434\u043c\u0438\u043b\u044c"
    ],
    "wof:name":"Podmilj",
    "wof:placetype":"locality",
    "wof:population":53
},
  "geometry": {"coordinates":[14.84395,46.17679],"type":"Point"}
}