{
  "type": "Feature",
  "properties": {
    "gn:admin1_code":"I4",
    "gn:asciiname":"Gornji Lakos",
    "gn:country_code":"SI",
    "gn:dem":163,
    "gn:feature_class":"P",
    "gn:feature_code":"PPL",
    "gn:name":"Gornji Lako\u0161",
    "gn:population":421,
    "gn:timezone":"Europe/Ljubljana",
    "iso:country":"SI",
    "name:bos_x_preferred":[
        "Gornji Lako\u0161"
    ],
    "name:ceb_x_preferred":[
        "Gornji Lako\u0161"
    ],
    "name:epo_x_preferred":[
        "Gornji Lako\u0161"
    ],
    "name:hrv_x_preferred":[
        "Gornji Lako\u0161"
    ],
    "name:hun_x_preferred":[
        "Fels\u0151lakos"
    ],
    "name:nld_x_preferred":[
        "Gornji Lako\u0161"
    ],
    "name:pol_x_preferred":[
        "Gornji Lako\u0161"
    ],
    "name:ron_x_preferred":[
        "Gornji Lako\u0161"
    ],
    "name:slv_x_preferred":[
        "Gornji Lako\u0161"
    ],
    "name:ukr_x_preferred":[
        "\u0413\u043e\u0440\u043d\u0438\u0439 \u041b\u0430\u043a\u043e\u0448"
    ],
    "name:und_x_variant":[
        "Dolnji Lakos",
        "Als\u00f3lendvalakos",
        "Fels\u0151lakos",
        "Als\u00f3lakos",
        "Gornji Lako\u0161"
    ],
    "wof:name":"Gornji Lakos",
    "wof:placetype":"locality",
    "wof:population":421
},
  "geometry": {"coordinates":[16.41806,46.55306],"type":"Point"}
}