{
  "type": "Feature",
  "properties": {
    "gn:admin1_code":"I4",
    "gn:asciiname":"Gornji Lakos",
    "gn:country_code":"SI",
    "gn:dem":163,
    "gn:feature_class":"P",
    "gn:feature_code":"PPL",
    "gn:name":"Gornji Lako\u0161",
    "gn:population":421,
    "gn:timezone":"Europe/Ljubljana",
    "iso:country":"SI",
    "name:und_x_variant":[
        "Dolnji Lakos",
        "Als\u00f3lendvalakos",
        "Fels\u0151lakos",
        "Als\u00f3lakos",
        "Gornji Lako\u0161"
    ],
    "wof:name":"Gornji Lakos",
    "wof:placetype":"locality",
    "wof:population":421
},
  "geometry": {"coordinates":[16.41806,46.55306],"type":"Point"}
}