{
  "type": "Feature",
  "properties": {
    "gn:admin1_code":"87",
    "gn:asciiname":"Dobrovscak",
    "gn:country_code":"SI",
    "gn:dem":269,
    "gn:feature_class":"P",
    "gn:feature_code":"PPL",
    "gn:name":"Dobrov\u0161\u010dak",
    "gn:population":11,
    "gn:timezone":"Europe/Ljubljana",
    "iso:country":"SI",
    "name:und_x_variant":[
        "Dobrov\u0161\u010dak"
    ],
    "wof:name":"Dobrovscak",
    "wof:placetype":"locality",
    "wof:population":11
},
  "geometry": {"coordinates":[16.13391,46.44853],"type":"Point"}
}