{
  "type": "Feature",
  "properties": {
    "gn:admin1_code":"87",
    "gn:asciiname":"Dobrovscak",
    "gn:country_code":"SI",
    "gn:dem":269,
    "gn:feature_class":"P",
    "gn:feature_code":"PPL",
    "gn:name":"Dobrov\u0161\u010dak",
    "gn:population":11,
    "gn:timezone":"Europe/Ljubljana",
    "iso:country":"SI",
    "name:bos_x_preferred":[
        "Dobrov\u0161\u010dak"
    ],
    "name:bul_x_preferred":[
        "\u0414\u043e\u0431\u0440\u043e\u0432\u0448\u0447\u0430\u043a"
    ],
    "name:nld_x_preferred":[
        "Dobrov\u0161\u010dak"
    ],
    "name:pol_x_preferred":[
        "Dobrov\u0161\u010dak"
    ],
    "name:ron_x_preferred":[
        "Dobrov\u0161\u010dak"
    ],
    "name:slv_x_preferred":[
        "Dobrov\u0161\u010dak"
    ],
    "name:ukr_x_preferred":[
        "\u0414\u043e\u0431\u0440\u043e\u0432\u0449\u0430\u043a"
    ],
    "name:und_x_variant":[
        "Dobrov\u0161\u010dak"
    ],
    "wof:name":"Dobrovscak",
    "wof:placetype":"locality",
    "wof:population":11
},
  "geometry": {"coordinates":[16.13391,46.44853],"type":"Point"}
}