{
  "type": "Feature",
  "properties": {
    "gn:admin1_code":"D8",
    "gn:asciiname":"Podkraj",
    "gn:country_code":"SI",
    "gn:dem":618,
    "gn:feature_class":"P",
    "gn:feature_code":"PPL",
    "gn:name":"Podkraj",
    "gn:population":16,
    "gn:timezone":"Europe/Ljubljana",
    "iso:country":"SI",
    "name:bos_x_preferred":[
        "Podkraj"
    ],
    "name:nld_x_preferred":[
        "Podkraj"
    ],
    "name:pol_x_preferred":[
        "Podkraj"
    ],
    "name:ron_x_preferred":[
        "Podkraj"
    ],
    "name:sco_x_preferred":[
        "Podkraj"
    ],
    "name:slv_x_preferred":[
        "Podkraj"
    ],
    "name:ukr_x_preferred":[
        "\u041f\u043e\u0434\u043a\u0440\u0430\u0439"
    ],
    "wof:name":"Podkraj",
    "wof:placetype":"locality",
    "wof:population":16
},
  "geometry": {"coordinates":[14.64708,45.81666],"type":"Point"}
}