{
  "type": "Feature",
  "properties": {
    "gn:admin1_code":"D8",
    "gn:asciiname":"Podkraj",
    "gn:country_code":"SI",
    "gn:dem":618,
    "gn:feature_class":"P",
    "gn:feature_code":"PPL",
    "gn:name":"Podkraj",
    "gn:population":16,
    "gn:timezone":"Europe/Ljubljana",
    "iso:country":"SI",
    "wof:name":"Podkraj",
    "wof:placetype":"locality",
    "wof:population":16
},
  "geometry": {"coordinates":[14.64708,45.81666],"type":"Point"}
}