{
  "type": "Feature",
  "properties": {
    "gn:admin1_code":"07",
    "gn:asciiname":"Snezece",
    "gn:country_code":"SI",
    "gn:dem":132,
    "gn:feature_class":"P",
    "gn:feature_code":"PPL",
    "gn:name":"Sne\u017ee\u010de",
    "gn:population":53,
    "gn:timezone":"Europe/Ljubljana",
    "iso:country":"SI",
    "name:bos_x_preferred":[
        "Sne\u017ee\u010de"
    ],
    "name:nld_x_preferred":[
        "Sne\u017ee\u010de"
    ],
    "name:pol_x_preferred":[
        "Sne\u017ee\u010de"
    ],
    "name:ron_x_preferred":[
        "Sne\u017ee\u010de"
    ],
    "name:slv_x_preferred":[
        "Sne\u017ee\u010de"
    ],
    "name:ukr_x_preferred":[
        "\u0421\u043d\u0435\u0436\u0435\u0447\u0435"
    ],
    "name:und_x_variant":[
        "Sne\u017ee\u010de"
    ],
    "wof:name":"Snezece",
    "wof:placetype":"locality",
    "wof:population":53
},
  "geometry": {"coordinates":[13.53052,46.00766],"type":"Point"}
}