{
  "type": "Feature",
  "properties": {
    "gn:admin1_code":"F5",
    "gn:asciiname":"Cresnjevec ob Bistrici",
    "gn:country_code":"SI",
    "gn:dem":238,
    "gn:feature_class":"P",
    "gn:feature_code":"PPL",
    "gn:name":"\u010cre\u0161njevec ob Bistrici",
    "gn:population":81,
    "gn:timezone":"Europe/Ljubljana",
    "iso:country":"SI",
    "name:bos_x_preferred":[
        "\u010cre\u0161njevec ob Bistrici"
    ],
    "name:hrv_x_preferred":[
        "\u010cre\u0161njevec ob Bistrici"
    ],
    "name:nld_x_preferred":[
        "\u010cre\u0161njevec ob Bistrici"
    ],
    "name:pol_x_preferred":[
        "\u010cre\u0161njevec ob Bistrici"
    ],
    "name:ron_x_preferred":[
        "\u010cre\u0161njevec ob Bistrici"
    ],
    "name:slv_x_preferred":[
        "\u010cre\u0161njevec ob Bistrici"
    ],
    "name:ukr_x_preferred":[
        "\u0427\u0440\u0435\u0448\u043d\u0454\u0432\u0435\u0446\u044c-\u043e\u0431-\u0411\u0438\u0441\u0442\u0440\u0438\u0446\u0456"
    ],
    "wof:name":"Cresnjevec ob Bistrici",
    "wof:placetype":"locality",
    "wof:population":81
},
  "geometry": {"coordinates":[15.63196,46.05725],"type":"Point"}
}