{
  "type": "Feature",
  "properties": {
    "gn:admin1_code":"F5",
    "gn:asciiname":"Cresnjevec ob Bistrici",
    "gn:country_code":"SI",
    "gn:dem":238,
    "gn:feature_class":"P",
    "gn:feature_code":"PPL",
    "gn:name":"\u010cre\u0161njevec ob Bistrici",
    "gn:population":81,
    "gn:timezone":"Europe/Ljubljana",
    "iso:country":"SI",
    "name:und_x_variant":[
        "\u010cre\u0161njevec ob Bistrici"
    ],
    "wof:name":"Cresnjevec ob Bistrici",
    "wof:placetype":"locality",
    "wof:population":81
},
  "geometry": {"coordinates":[15.63196,46.05725],"type":"Point"}
}