{
  "type": "Feature",
  "properties": {
    "gn:admin1_code":"35",
    "gn:asciiname":"Slope",
    "gn:country_code":"SI",
    "gn:dem":643,
    "gn:feature_class":"P",
    "gn:feature_code":"PPL",
    "gn:name":"Slope",
    "gn:population":74,
    "gn:timezone":"Europe/Ljubljana",
    "iso:country":"SI",
    "name:und_x_variant":[
        "Sloppe",
        "Slope"
    ],
    "wof:name":"Slope",
    "wof:placetype":"locality",
    "wof:population":74
},
  "geometry": {"coordinates":[13.98556,45.61528],"type":"Point"}
}