{
  "type": "Feature",
  "properties": {
    "gn:admin1_code":"84",
    "gn:asciiname":"Baske",
    "gn:country_code":"SI",
    "gn:dem":577,
    "gn:feature_class":"P",
    "gn:feature_code":"PPL",
    "gn:name":"Baske",
    "gn:population":0,
    "gn:timezone":"Europe/Ljubljana",
    "iso:country":"SI",
    "wof:name":"Baske",
    "wof:placetype":"locality"
},
  "geometry": {"coordinates":[13.65236,46.02584],"type":"Point"}
}