{
  "type": "Feature",
  "properties": {
    "gn:admin1_code":"A2",
    "gn:asciiname":"St. Janz pri Radljah",
    "gn:country_code":"SI",
    "gn:dem":437,
    "gn:feature_class":"P",
    "gn:feature_code":"PPL",
    "gn:name":"\u0160t. Jan\u017e pri Radljah",
    "gn:population":274,
    "gn:timezone":"Europe/Ljubljana",
    "iso:country":"SI",
    "name:bos_x_preferred":[
        "\u0160ent Jan\u017e pri Radljah"
    ],
    "name:ceb_x_preferred":[
        "\u0160t. Jan\u017e pri Radljah"
    ],
    "name:nld_x_preferred":[
        "\u0160t. Jan\u017e pri Radljah"
    ],
    "name:pol_x_preferred":[
        "\u0160ent Jan\u017e pri Radljah"
    ],
    "name:ron_x_preferred":[
        "\u0160ent Jan\u017e pri Radljah"
    ],
    "name:slv_x_preferred":[
        "\u0160ent Jan\u017e pri Radljah"
    ],
    "name:ukr_x_preferred":[
        "\u0428\u0435\u043d\u0442 \u042f\u043d\u0436-\u043f\u0440\u0438-\u0420\u0430\u0434\u043b\u044f\u0445"
    ],
    "name:und_x_variant":[
        "Suhi Vrh",
        "\u0160ent Janz",
        "Suhi Vrh pri Radljah"
    ],
    "wof:name":"St. Janz pri Radljah",
    "wof:placetype":"locality",
    "wof:population":274
},
  "geometry": {"coordinates":[15.25,46.61667],"type":"Point"}
}