{
  "type": "Feature",
  "properties": {
    "gn:admin1_code":"A2",
    "gn:asciiname":"St. Janz pri Radljah",
    "gn:country_code":"SI",
    "gn:dem":437,
    "gn:feature_class":"P",
    "gn:feature_code":"PPL",
    "gn:name":"\u0160t. Jan\u017e pri Radljah",
    "gn:population":274,
    "gn:timezone":"Europe/Ljubljana",
    "iso:country":"SI",
    "name:und_x_variant":[
        "Suhi Vrh",
        "\u0160ent Janz",
        "Suhi Vrh pri Radljah"
    ],
    "wof:name":"St. Janz pri Radljah",
    "wof:placetype":"locality",
    "wof:population":274
},
  "geometry": {"coordinates":[15.25,46.61667],"type":"Point"}
}