{
  "type": "Feature",
  "properties": {
    "gn:admin1_code":"N4",
    "gn:asciiname":"Prekopa",
    "gn:country_code":"SI",
    "gn:dem":317,
    "gn:feature_class":"P",
    "gn:feature_code":"PPL",
    "gn:name":"Prekopa",
    "gn:population":246,
    "gn:timezone":"Europe/Ljubljana",
    "iso:country":"SI",
    "name:ceb_x_preferred":[
        "Prekopa"
    ],
    "name:hrv_x_preferred":[
        "Prekopa"
    ],
    "name:nld_x_preferred":[
        "Prekopa"
    ],
    "name:pol_x_preferred":[
        "Prekopa"
    ],
    "name:ron_x_preferred":[
        "Prekopa"
    ],
    "name:slv_x_preferred":[
        "Prekopa"
    ],
    "name:ukr_x_preferred":[
        "\u041f\u0440\u0435\u043a\u043e\u043f\u0430"
    ],
    "wof:name":"Prekopa",
    "wof:placetype":"locality",
    "wof:population":246
},
  "geometry": {"coordinates":[14.98333,46.25],"type":"Point"}
}