{
  "type": "Feature",
  "properties": {
    "gn:admin1_code":"N4",
    "gn:asciiname":"Prekopa",
    "gn:country_code":"SI",
    "gn:dem":317,
    "gn:feature_class":"P",
    "gn:feature_code":"PPL",
    "gn:name":"Prekopa",
    "gn:population":246,
    "gn:timezone":"Europe/Ljubljana",
    "iso:country":"SI",
    "wof:name":"Prekopa",
    "wof:placetype":"locality",
    "wof:population":246
},
  "geometry": {"coordinates":[14.98333,46.25],"type":"Point"}
}