{
  "type": "Feature",
  "properties": {
    "gn:admin1_code":"A1",
    "gn:asciiname":"Turjanski Vrh",
    "gn:country_code":"SI",
    "gn:dem":263,
    "gn:feature_class":"P",
    "gn:feature_code":"PPL",
    "gn:name":"Turjanski Vrh",
    "gn:population":81,
    "gn:timezone":"Europe/Ljubljana",
    "iso:country":"SI",
    "name:bos_x_preferred":[
        "Turjanski Vrh"
    ],
    "name:fas_x_preferred":[
        "\u062a\u0648\u0631\u06cc\u0627\u0646\u0633\u06a9\u06cc \u0648\u0631"
    ],
    "name:nld_x_preferred":[
        "Turjanski Vrh"
    ],
    "name:pol_x_preferred":[
        "Turjanski Vrh"
    ],
    "name:ron_x_preferred":[
        "Turjanski Vrh"
    ],
    "name:slv_x_preferred":[
        "Turjanski Vrh"
    ],
    "name:ukr_x_preferred":[
        "\u0422\u0443\u0440\u044f\u043d\u0441\u044c\u043a\u0438\u0439 \u0412\u0440\u0445"
    ],
    "name:urd_x_preferred":[
        "\u062a\u0648\u0631\u06cc\u0627\u0646\u0633\u06a9\u06cc \u0648\u0631\u06be"
    ],
    "wof:name":"Turjanski Vrh",
    "wof:placetype":"locality",
    "wof:population":81
},
  "geometry": {"coordinates":[16.04944,46.61659],"type":"Point"}
}