{
  "type": "Feature",
  "properties": {
    "gn:admin1_code":"A1",
    "gn:asciiname":"Turjanski Vrh",
    "gn:country_code":"SI",
    "gn:dem":263,
    "gn:feature_class":"P",
    "gn:feature_code":"PPL",
    "gn:name":"Turjanski Vrh",
    "gn:population":81,
    "gn:timezone":"Europe/Ljubljana",
    "iso:country":"SI",
    "wof:name":"Turjanski Vrh",
    "wof:placetype":"locality",
    "wof:population":81
},
  "geometry": {"coordinates":[16.04944,46.61659],"type":"Point"}
}