{
  "type": "Feature",
  "properties": {
    "gn:admin1_code":"D5",
    "gn:asciiname":"Kovor",
    "gn:country_code":"SI",
    "gn:dem":541,
    "gn:feature_class":"P",
    "gn:feature_code":"PPL",
    "gn:name":"Kovor",
    "gn:population":788,
    "gn:timezone":"Europe/Ljubljana",
    "iso:country":"SI",
    "wof:name":"Kovor",
    "wof:placetype":"locality",
    "wof:population":788
},
  "geometry": {"coordinates":[14.28333,46.35],"type":"Point"}
}