{
  "type": "Feature",
  "properties": {
    "gn:admin1_code":"D5",
    "gn:asciiname":"Kovor",
    "gn:country_code":"SI",
    "gn:dem":541,
    "gn:feature_class":"P",
    "gn:feature_code":"PPL",
    "gn:name":"Kovor",
    "gn:population":788,
    "gn:timezone":"Europe/Ljubljana",
    "iso:country":"SI",
    "name:bos_x_preferred":[
        "Kovor"
    ],
    "name:ceb_x_preferred":[
        "Kovor"
    ],
    "name:hrv_x_preferred":[
        "Kovor"
    ],
    "name:nld_x_preferred":[
        "Kovor"
    ],
    "name:pol_x_preferred":[
        "Kovor"
    ],
    "name:ron_x_preferred":[
        "Kovor"
    ],
    "name:slv_x_preferred":[
        "Kovor"
    ],
    "name:ukr_x_preferred":[
        "\u041a\u043e\u0432\u043e\u0440"
    ],
    "wof:name":"Kovor",
    "wof:placetype":"locality",
    "wof:population":788
},
  "geometry": {"coordinates":[14.28333,46.35],"type":"Point"}
}