{
  "type": "Feature",
  "properties": {
    "gn:admin1_code":"E9",
    "gn:asciiname":"Turski Vrh",
    "gn:country_code":"SI",
    "gn:dem":241,
    "gn:feature_class":"P",
    "gn:feature_code":"PPL",
    "gn:name":"Tur\u0161ki Vrh",
    "gn:population":419,
    "gn:timezone":"Europe/Ljubljana",
    "iso:country":"SI",
    "name:und_x_variant":[
        "Tur\u0161ki Vrh"
    ],
    "wof:name":"Turski Vrh",
    "wof:placetype":"locality",
    "wof:population":419
},
  "geometry": {"coordinates":[16.05759,46.35543],"type":"Point"}
}