{
  "type": "Feature",
  "properties": {
    "gn:admin1_code":"E9",
    "gn:asciiname":"Turski Vrh",
    "gn:country_code":"SI",
    "gn:dem":241,
    "gn:feature_class":"P",
    "gn:feature_code":"PPL",
    "gn:name":"Tur\u0161ki Vrh",
    "gn:population":419,
    "gn:timezone":"Europe/Ljubljana",
    "iso:country":"SI",
    "name:bos_x_preferred":[
        "Tur\u0161ki Vrh"
    ],
    "name:ceb_x_preferred":[
        "Tur\u0161ki Vrh"
    ],
    "name:fas_x_preferred":[
        "\u062a\u0648\u0631\u0634\u06a9\u06cc \u0648\u0631"
    ],
    "name:nld_x_preferred":[
        "Tur\u0161ki Vrh"
    ],
    "name:pol_x_preferred":[
        "Tur\u0161ki Vrh"
    ],
    "name:ron_x_preferred":[
        "Tur\u0161ki Vrh"
    ],
    "name:slv_x_preferred":[
        "Tur\u0161ki Vrh"
    ],
    "name:ukr_x_preferred":[
        "\u0422\u0443\u0440\u0448\u043a\u0438\u0439 \u0412\u0440\u0445"
    ],
    "name:urd_x_preferred":[
        "\u062a\u0631\u0634\u06a9\u06cc \u0648\u0631\u06c1"
    ],
    "wof:name":"Turski Vrh",
    "wof:placetype":"locality",
    "wof:population":419
},
  "geometry": {"coordinates":[16.05759,46.35543],"type":"Point"}
}