{
  "type": "Feature",
  "properties": {
    "gn:admin1_code":"G4",
    "gn:asciiname":"Smolnik",
    "gn:country_code":"SI",
    "gn:dem":733,
    "gn:feature_class":"P",
    "gn:feature_code":"PPL",
    "gn:name":"Smolnik",
    "gn:population":150,
    "gn:timezone":"Europe/Ljubljana",
    "iso:country":"SI",
    "wof:name":"Smolnik",
    "wof:placetype":"locality",
    "wof:population":150
},
  "geometry": {"coordinates":[14.28214,46.07759],"type":"Point"}
}