{
  "type": "Feature",
  "properties": {
    "gn:admin1_code":"D2",
    "gn:asciiname":"Brdar",
    "gn:country_code":"SI",
    "gn:dem":776,
    "gn:feature_class":"P",
    "gn:feature_code":"PPL",
    "gn:name":"Brdar",
    "gn:population":0,
    "gn:timezone":"Europe/Ljubljana",
    "iso:country":"SI",
    "wof:name":"Brdar",
    "wof:placetype":"locality"
},
  "geometry": {"coordinates":[13.94472,46.18778],"type":"Point"}
}