{
  "type": "Feature",
  "properties": {
    "gn:admin1_code":"M3",
    "gn:asciiname":"Kremberk",
    "gn:country_code":"SI",
    "gn:dem":280,
    "gn:feature_class":"P",
    "gn:feature_code":"PPL",
    "gn:name":"Kremberk",
    "gn:population":257,
    "gn:timezone":"Europe/Ljubljana",
    "iso:country":"SI",
    "wof:name":"Kremberk",
    "wof:placetype":"locality",
    "wof:population":257
},
  "geometry": {"coordinates":[15.83569,46.63953],"type":"Point"}
}