{
  "type": "Feature",
  "properties": {
    "gn:admin1_code":"M3",
    "gn:asciiname":"Kremberk",
    "gn:country_code":"SI",
    "gn:dem":280,
    "gn:feature_class":"P",
    "gn:feature_code":"PPL",
    "gn:name":"Kremberk",
    "gn:population":257,
    "gn:timezone":"Europe/Ljubljana",
    "iso:country":"SI",
    "name:bos_x_preferred":[
        "Kremberk"
    ],
    "name:ceb_x_preferred":[
        "Kremberk"
    ],
    "name:nld_x_preferred":[
        "Kremberk"
    ],
    "name:pol_x_preferred":[
        "Kremberk"
    ],
    "name:ron_x_preferred":[
        "Kremberk"
    ],
    "name:slv_x_preferred":[
        "Kremberk"
    ],
    "name:ukr_x_preferred":[
        "\u041a\u0440\u0435\u043c\u0431\u0435\u0440\u043a"
    ],
    "wof:name":"Kremberk",
    "wof:placetype":"locality",
    "wof:population":257
},
  "geometry": {"coordinates":[15.83569,46.63953],"type":"Point"}
}