{
  "type": "Feature",
  "properties": {
    "gn:admin1_code":"N3",
    "gn:asciiname":"Ilovca",
    "gn:country_code":"SI",
    "gn:dem":354,
    "gn:feature_class":"P",
    "gn:feature_code":"PPL",
    "gn:name":"Ilovca",
    "gn:population":96,
    "gn:timezone":"Europe/Ljubljana",
    "iso:country":"SI",
    "name:bos_x_preferred":[
        "Ilovca"
    ],
    "name:hrv_x_preferred":[
        "Ilovca"
    ],
    "name:nld_x_preferred":[
        "Ilovca"
    ],
    "name:pol_x_preferred":[
        "Ilovca"
    ],
    "name:ron_x_preferred":[
        "Ilovca"
    ],
    "name:slv_x_preferred":[
        "Ilovca"
    ],
    "name:ukr_x_preferred":[
        "\u0406\u043b\u043e\u0432\u0446\u0430"
    ],
    "wof:name":"Ilovca",
    "wof:placetype":"locality",
    "wof:population":96
},
  "geometry": {"coordinates":[15.32056,46.30507],"type":"Point"}
}