{
  "type": "Feature",
  "properties": {
    "gn:admin1_code":"N3",
    "gn:asciiname":"Ilovca",
    "gn:country_code":"SI",
    "gn:dem":354,
    "gn:feature_class":"P",
    "gn:feature_code":"PPL",
    "gn:name":"Ilovca",
    "gn:population":96,
    "gn:timezone":"Europe/Ljubljana",
    "iso:country":"SI",
    "wof:name":"Ilovca",
    "wof:placetype":"locality",
    "wof:population":96
},
  "geometry": {"coordinates":[15.32056,46.30507],"type":"Point"}
}