{
  "type": "Feature",
  "properties": {
    "gn:admin1_code":"32",
    "gn:asciiname":"Ponova Vas",
    "gn:country_code":"SI",
    "gn:dem":333,
    "gn:feature_class":"P",
    "gn:feature_code":"PPL",
    "gn:name":"Ponova Vas",
    "gn:population":569,
    "gn:timezone":"Europe/Ljubljana",
    "iso:country":"SI",
    "wof:name":"Ponova Vas",
    "wof:placetype":"locality",
    "wof:population":569
},
  "geometry": {"coordinates":[14.63278,45.93833],"type":"Point"}
}