{
  "type": "Feature",
  "properties": {
    "gn:admin1_code":"32",
    "gn:asciiname":"Ponova Vas",
    "gn:country_code":"SI",
    "gn:dem":333,
    "gn:feature_class":"P",
    "gn:feature_code":"PPL",
    "gn:name":"Ponova Vas",
    "gn:population":569,
    "gn:timezone":"Europe/Ljubljana",
    "iso:country":"SI",
    "name:bos_x_preferred":[
        "Ponova vas"
    ],
    "name:ceb_x_preferred":[
        "Ponova Vas"
    ],
    "name:nld_x_preferred":[
        "Ponova vas"
    ],
    "name:pol_x_preferred":[
        "Ponova vas"
    ],
    "name:ron_x_preferred":[
        "Ponova vas"
    ],
    "name:slv_x_preferred":[
        "Ponova vas"
    ],
    "name:ukr_x_preferred":[
        "\u041f\u043e\u043d\u043e\u0432\u0430 \u0412\u0430\u0441"
    ],
    "wof:name":"Ponova Vas",
    "wof:placetype":"locality",
    "wof:population":569
},
  "geometry": {"coordinates":[14.63278,45.93833],"type":"Point"}
}