{
  "type": "Feature",
  "properties": {
    "gn:admin1_code":"12",
    "gn:asciiname":"Stiska Vas",
    "gn:country_code":"SI",
    "gn:dem":875,
    "gn:feature_class":"P",
    "gn:feature_code":"PPL",
    "gn:name":"Sti\u0161ka Vas",
    "gn:population":100,
    "gn:timezone":"Europe/Ljubljana",
    "iso:country":"SI",
    "name:und_x_variant":[
        "Sti\u0161ka Vas"
    ],
    "wof:name":"Stiska Vas",
    "wof:placetype":"locality",
    "wof:population":100
},
  "geometry": {"coordinates":[14.51067,46.27858],"type":"Point"}
}