{
  "type": "Feature",
  "properties": {
    "gn:admin1_code":"31",
    "gn:asciiname":"Boreca",
    "gn:country_code":"SI",
    "gn:dem":362,
    "gn:feature_class":"P",
    "gn:feature_code":"PPL",
    "gn:name":"Bore\u010da",
    "gn:population":82,
    "gn:timezone":"Europe/Ljubljana",
    "iso:country":"SI",
    "name:und_x_variant":[
        "Borh\u00e1za",
        "Bore\u010da"
    ],
    "wof:name":"Boreca",
    "wof:placetype":"locality",
    "wof:population":82
},
  "geometry": {"coordinates":[16.14333,46.8375],"type":"Point"}
}