{
  "type": "Feature",
  "properties": {
    "gn:admin1_code":"68",
    "gn:asciiname":"Sentozbolt",
    "gn:country_code":"SI",
    "gn:dem":597,
    "gn:feature_class":"P",
    "gn:feature_code":"PPL",
    "gn:name":"\u0160ento\u017ebolt",
    "gn:population":48,
    "gn:timezone":"Europe/Ljubljana",
    "iso:country":"SI",
    "name:bos_x_preferred":[
        "\u0160ento\u017ebolt"
    ],
    "name:nld_x_preferred":[
        "\u0160ento\u017ebolt"
    ],
    "name:pol_x_preferred":[
        "\u0160ento\u017ebolt"
    ],
    "name:ron_x_preferred":[
        "\u0160ento\u017ebolt"
    ],
    "name:slv_x_preferred":[
        "\u0160ento\u017ebolt"
    ],
    "name:ukr_x_preferred":[
        "\u0428\u0435\u043d\u0442\u043e\u0436\u0431\u043e\u043b\u0442"
    ],
    "name:und_x_variant":[
        "\u0160ent O\u017ebald",
        "\u0160ento\u017ebalt",
        "\u0160ento\u017ebolt"
    ],
    "wof:name":"Sentozbolt",
    "wof:placetype":"locality",
    "wof:population":48
},
  "geometry": {"coordinates":[14.85465,46.18475],"type":"Point"}
}