{
  "type": "Feature",
  "properties": {
    "gn:admin1_code":"L2",
    "gn:asciiname":"Hudi Kot",
    "gn:country_code":"SI",
    "gn:dem":1063,
    "gn:feature_class":"P",
    "gn:feature_code":"PPL",
    "gn:name":"Hudi Kot",
    "gn:population":251,
    "gn:timezone":"Europe/Ljubljana",
    "iso:country":"SI",
    "name:bos_x_preferred":[
        "Hudi Kot"
    ],
    "name:ceb_x_preferred":[
        "Hudi Kot"
    ],
    "name:nld_x_preferred":[
        "Hudi Kot"
    ],
    "name:pol_x_preferred":[
        "Hudi Kot"
    ],
    "name:ron_x_preferred":[
        "Hudi Kot"
    ],
    "name:slv_x_preferred":[
        "Hudi Kot"
    ],
    "name:ukr_x_preferred":[
        "\u0425\u0443\u0434\u0438\u0439 \u041a\u043e\u0442"
    ],
    "wof:name":"Hudi Kot",
    "wof:placetype":"locality",
    "wof:population":251
},
  "geometry": {"coordinates":[15.26667,46.51667],"type":"Point"}
}