{
  "type": "Feature",
  "properties": {
    "gn:admin1_code":"L2",
    "gn:asciiname":"Hudi Kot",
    "gn:country_code":"SI",
    "gn:dem":1063,
    "gn:feature_class":"P",
    "gn:feature_code":"PPL",
    "gn:name":"Hudi Kot",
    "gn:population":251,
    "gn:timezone":"Europe/Ljubljana",
    "iso:country":"SI",
    "wof:name":"Hudi Kot",
    "wof:placetype":"locality",
    "wof:population":251
},
  "geometry": {"coordinates":[15.26667,46.51667],"type":"Point"}
}