{
  "type": "Feature",
  "properties": {
    "gn:admin1_code":"F6",
    "gn:asciiname":"Volcje",
    "gn:country_code":"SI",
    "gn:dem":784,
    "gn:feature_class":"P",
    "gn:feature_code":"PPL",
    "gn:name":"Vol\u010dje",
    "gn:population":32,
    "gn:timezone":"Europe/Ljubljana",
    "iso:country":"SI",
    "name:und_x_variant":[
        "Vol\u010dje"
    ],
    "wof:name":"Volcje",
    "wof:placetype":"locality",
    "wof:population":32
},
  "geometry": {"coordinates":[14.51266,45.78548],"type":"Point"}
}