{
  "type": "Feature",
  "properties": {
    "gn:admin1_code":"44",
    "gn:asciiname":"Prilesje pri Plavah",
    "gn:country_code":"SI",
    "gn:dem":130,
    "gn:feature_class":"P",
    "gn:feature_code":"PPL",
    "gn:name":"Prilesje pri Plavah",
    "gn:population":54,
    "gn:timezone":"Europe/Ljubljana",
    "iso:country":"SI",
    "name:bos_x_preferred":[
        "Prilesje pri Plavah"
    ],
    "name:pol_x_preferred":[
        "Prilesje pri Plavah"
    ],
    "name:slv_x_preferred":[
        "Prilesje pri Plavah"
    ],
    "wof:name":"Prilesje pri Plavah",
    "wof:placetype":"locality",
    "wof:population":54
},
  "geometry": {"coordinates":[13.59503,46.02543],"type":"Point"}
}