{
  "type": "Feature",
  "properties": {
    "iso:country":"SI",
    "wof:name":"Bizovic",
    "wof:placetype":"neighbourhood"
},
  "geometry": {"coordinates":[14.56841479052961,46.03727469057867],"type":"Point"}
}