{
  "type": "Feature",
  "properties": {
    "gn:admin1_code":"K2",
    "gn:asciiname":"Zgornja Kapla",
    "gn:country_code":"SI",
    "gn:dem":727,
    "gn:feature_class":"P",
    "gn:feature_code":"PPL",
    "gn:name":"Zgornja Kapla",
    "gn:population":169,
    "gn:timezone":"Europe/Ljubljana",
    "iso:country":"SI",
    "name:bos_x_preferred":[
        "Zgornja Kapla"
    ],
    "name:ceb_x_preferred":[
        "Zgornja Kapla"
    ],
    "name:nld_x_preferred":[
        "Zgornja Kapla"
    ],
    "name:pol_x_preferred":[
        "Zgornja Kapla"
    ],
    "name:ron_x_preferred":[
        "Zgornja Kapla"
    ],
    "name:slv_x_preferred":[
        "Zgornja Kapla"
    ],
    "name:ukr_x_preferred":[
        "\u0417\u0433\u043e\u0440\u043d\u044f \u041a\u0430\u043f\u043b\u0430"
    ],
    "wof:name":"Zgornja Kapla",
    "wof:placetype":"locality",
    "wof:population":169
},
  "geometry": {"coordinates":[15.3775,46.63889],"type":"Point"}
}