{
  "type": "Feature",
  "properties": {
    "gn:admin1_code":"K2",
    "gn:asciiname":"Zgornja Kapla",
    "gn:country_code":"SI",
    "gn:dem":727,
    "gn:feature_class":"P",
    "gn:feature_code":"PPL",
    "gn:name":"Zgornja Kapla",
    "gn:population":169,
    "gn:timezone":"Europe/Ljubljana",
    "iso:country":"SI",
    "wof:name":"Zgornja Kapla",
    "wof:placetype":"locality",
    "wof:population":169
},
  "geometry": {"coordinates":[15.3775,46.63889],"type":"Point"}
}