{
  "type": "Feature",
  "properties": {
    "gn:admin1_code":"34",
    "gn:asciiname":"Unicno",
    "gn:country_code":"SI",
    "gn:dem":608,
    "gn:feature_class":"P",
    "gn:feature_code":"PPL",
    "gn:name":"Uni\u010dno",
    "gn:population":14,
    "gn:timezone":"Europe/Ljubljana",
    "iso:country":"SI",
    "name:bos_x_preferred":[
        "Uni\u010dno"
    ],
    "name:deu_x_preferred":[
        "Uni\u010dno"
    ],
    "name:nld_x_preferred":[
        "Uni\u010dno"
    ],
    "name:pol_x_preferred":[
        "Uni\u010dno"
    ],
    "name:ron_x_preferred":[
        "Uni\u010dno"
    ],
    "name:slv_x_preferred":[
        "Uni\u010dno"
    ],
    "name:ukr_x_preferred":[
        "\u0423\u043d\u0438\u0447\u043d\u043e"
    ],
    "wof:name":"Unicno",
    "wof:placetype":"locality",
    "wof:population":14
},
  "geometry": {"coordinates":[15.14378,46.15371],"type":"Point"}
}