{
  "type": "Feature",
  "properties": {
    "gn:admin1_code":"34",
    "gn:asciiname":"Unicno",
    "gn:country_code":"SI",
    "gn:dem":608,
    "gn:feature_class":"P",
    "gn:feature_code":"PPL",
    "gn:name":"Uni\u010dno",
    "gn:population":14,
    "gn:timezone":"Europe/Ljubljana",
    "iso:country":"SI",
    "name:und_x_variant":[
        "Uni\u010dno"
    ],
    "wof:name":"Unicno",
    "wof:placetype":"locality",
    "wof:population":14
},
  "geometry": {"coordinates":[15.14378,46.15371],"type":"Point"}
}