{
  "type": "Feature",
  "properties": {
    "gn:admin1_code":"C4",
    "gn:asciiname":"Breg pri Konjicah",
    "gn:country_code":"SI",
    "gn:dem":301,
    "gn:feature_class":"P",
    "gn:feature_code":"PPL",
    "gn:name":"Breg pri Konjicah",
    "gn:population":132,
    "gn:timezone":"Europe/Ljubljana",
    "iso:country":"SI",
    "wof:name":"Breg pri Konjicah",
    "wof:placetype":"locality",
    "wof:population":132
},
  "geometry": {"coordinates":[15.4493,46.33299],"type":"Point"}
}