{
  "type": "Feature",
  "properties": {
    "gn:admin1_code":"54",
    "gn:asciiname":"Dunaj",
    "gn:country_code":"SI",
    "gn:dem":378,
    "gn:feature_class":"P",
    "gn:feature_code":"PPL",
    "gn:name":"Dunaj",
    "gn:population":39,
    "gn:timezone":"Europe/Ljubljana",
    "iso:country":"SI",
    "wof:name":"Dunaj",
    "wof:placetype":"locality",
    "wof:population":39
},
  "geometry": {"coordinates":[15.45645,45.97909],"type":"Point"}
}