{
  "type": "Feature",
  "properties": {
    "gn:admin1_code":"54",
    "gn:asciiname":"Dunaj",
    "gn:country_code":"SI",
    "gn:dem":378,
    "gn:feature_class":"P",
    "gn:feature_code":"PPL",
    "gn:name":"Dunaj",
    "gn:population":39,
    "gn:timezone":"Europe/Ljubljana",
    "iso:country":"SI",
    "name:bos_x_preferred":[
        "Dunaj"
    ],
    "name:hrv_x_preferred":[
        "Dunaj"
    ],
    "name:nld_x_preferred":[
        "Dunaj"
    ],
    "name:pol_x_preferred":[
        "Dunaj"
    ],
    "name:ron_x_preferred":[
        "Dunaj"
    ],
    "name:slv_x_preferred":[
        "Dunaj"
    ],
    "name:ukr_x_preferred":[
        "\u0414\u0443\u043d\u0430\u0439"
    ],
    "wof:name":"Dunaj",
    "wof:placetype":"locality",
    "wof:population":39
},
  "geometry": {"coordinates":[15.45645,45.97909],"type":"Point"}
}