{
  "type": "Feature",
  "properties": {
    "gn:admin1_code":"C5",
    "gn:asciiname":"Platinovec",
    "gn:country_code":"SI",
    "gn:dem":325,
    "gn:feature_class":"P",
    "gn:feature_code":"PPL",
    "gn:name":"Platinovec",
    "gn:population":112,
    "gn:timezone":"Europe/Ljubljana",
    "iso:country":"SI",
    "wof:name":"Platinovec",
    "wof:placetype":"locality",
    "wof:population":112
},
  "geometry": {"coordinates":[15.45616,46.21155],"type":"Point"}
}