{
  "type": "Feature",
  "properties": {
    "gn:admin1_code":"C5",
    "gn:asciiname":"Platinovec",
    "gn:country_code":"SI",
    "gn:dem":325,
    "gn:feature_class":"P",
    "gn:feature_code":"PPL",
    "gn:name":"Platinovec",
    "gn:population":112,
    "gn:timezone":"Europe/Ljubljana",
    "iso:country":"SI",
    "name:bos_x_preferred":[
        "Platinovec"
    ],
    "name:ceb_x_preferred":[
        "Platinovec"
    ],
    "name:hrv_x_preferred":[
        "Platinovec"
    ],
    "name:nld_x_preferred":[
        "Platinovec"
    ],
    "name:pol_x_preferred":[
        "Platinovec"
    ],
    "name:ron_x_preferred":[
        "Platinovec"
    ],
    "name:slv_x_preferred":[
        "Platinovec"
    ],
    "name:ukr_x_preferred":[
        "\u041f\u043b\u0430\u0442\u0438\u043d\u043e\u0432\u0435\u0446\u044c"
    ],
    "wof:name":"Platinovec",
    "wof:placetype":"locality",
    "wof:population":112
},
  "geometry": {"coordinates":[15.45616,46.21155],"type":"Point"}
}