{
  "type": "Feature",
  "properties": {
    "iso:country":"SI",
    "name:bos_x_preferred":[
        "Soteska"
    ],
    "name:slv_x_preferred":[
        "Soteska"
    ],
    "wof:name":"Soteska",
    "wof:placetype":"neighbourhood"
},
  "geometry": {"coordinates":[14.57225407042424,46.09307262561598],"type":"Point"}
}