{
  "type": "Feature",
  "properties": {
    "gn:admin1_code":"D5",
    "gn:asciiname":"Spodnje Vetrno",
    "gn:country_code":"SI",
    "gn:dem":766,
    "gn:feature_class":"P",
    "gn:feature_code":"PPL",
    "gn:name":"Spodnje Vetrno",
    "gn:population":53,
    "gn:timezone":"Europe/Ljubljana",
    "iso:country":"SI",
    "name:bos_x_preferred":[
        "Spodnje Vetrno"
    ],
    "name:hrv_x_preferred":[
        "Spodnje Vetrno"
    ],
    "name:nld_x_preferred":[
        "Spodnje Vetrno"
    ],
    "name:pol_x_preferred":[
        "Spodnje Vetrno"
    ],
    "name:ron_x_preferred":[
        "Spodnje Vetrno"
    ],
    "name:slv_x_preferred":[
        "Spodnje Vetrno"
    ],
    "name:ukr_x_preferred":[
        "\u0421\u043f\u043e\u0434\u043d\u0454 \u0412\u0435\u0442\u0440\u043d\u043e"
    ],
    "wof:name":"Spodnje Vetrno",
    "wof:placetype":"locality",
    "wof:population":53
},
  "geometry": {"coordinates":[14.32405,46.33793],"type":"Point"}
}