{
  "type": "Feature",
  "properties": {
    "gn:admin1_code":"L8",
    "gn:asciiname":"Visole",
    "gn:country_code":"SI",
    "gn:dem":462,
    "gn:feature_class":"P",
    "gn:feature_code":"PPL",
    "gn:name":"Visole",
    "gn:population":539,
    "gn:timezone":"Europe/Ljubljana",
    "iso:country":"SI",
    "name:bos_x_preferred":[
        "Visole"
    ],
    "name:ceb_x_preferred":[
        "Visole"
    ],
    "name:nld_x_preferred":[
        "Visole"
    ],
    "name:pol_x_preferred":[
        "Visole"
    ],
    "name:ron_x_preferred":[
        "Visole"
    ],
    "name:slv_x_preferred":[
        "Visole"
    ],
    "name:ukr_x_preferred":[
        "\u0412\u0438\u0441\u043e\u043b\u0435"
    ],
    "wof:name":"Visole",
    "wof:placetype":"locality",
    "wof:population":539
},
  "geometry": {"coordinates":[15.52757,46.40353],"type":"Point"}
}