{
  "type": "Feature",
  "properties": {
    "gn:admin1_code":"68",
    "gn:asciiname":"Log",
    "gn:country_code":"SI",
    "gn:dem":694,
    "gn:feature_class":"P",
    "gn:feature_code":"PPL",
    "gn:name":"Log",
    "gn:population":21,
    "gn:timezone":"Europe/Ljubljana",
    "iso:country":"SI",
    "name:bos_x_preferred":[
        "Log"
    ],
    "name:nld_x_preferred":[
        "Log"
    ],
    "name:pol_x_preferred":[
        "Log"
    ],
    "name:ron_x_preferred":[
        "Log"
    ],
    "name:slv_x_preferred":[
        "Log"
    ],
    "name:ukr_x_preferred":[
        "\u041b\u043e\u0433"
    ],
    "wof:name":"Log",
    "wof:placetype":"locality",
    "wof:population":21
},
  "geometry": {"coordinates":[14.84091,46.19088],"type":"Point"}
}