{
  "type": "Feature",
  "properties": {
    "gn:admin1_code":"32",
    "gn:asciiname":"Dolenja Vas pri Polici",
    "gn:country_code":"SI",
    "gn:dem":497,
    "gn:feature_class":"P",
    "gn:feature_code":"PPL",
    "gn:name":"Dolenja Vas pri Polici",
    "gn:population":87,
    "gn:timezone":"Europe/Ljubljana",
    "iso:country":"SI",
    "name:bos_x_preferred":[
        "Dolenja vas pri Polici"
    ],
    "name:nld_x_preferred":[
        "Dolenja vas pri Polici"
    ],
    "name:pol_x_preferred":[
        "Dolenja vas pri Polici"
    ],
    "name:ron_x_preferred":[
        "Dolenja vas pri Polici"
    ],
    "name:slv_x_preferred":[
        "Dolenja vas pri Polici"
    ],
    "name:srp_x_preferred":[
        "\u0414\u043e\u043b\u0435\u045a\u0430 \u0412\u0430\u0441 \u043f\u0440\u0438 \u041f\u043e\u043b\u0438\u0446\u0438"
    ],
    "name:ukr_x_preferred":[
        "\u0414\u043e\u043b\u0435\u043d\u044f \u0412\u0430\u0441-\u043f\u0440\u0438-\u041f\u043e\u043b\u0438\u0446\u0456"
    ],
    "wof:name":"Dolenja Vas pri Polici",
    "wof:placetype":"locality",
    "wof:population":87
},
  "geometry": {"coordinates":[14.68996,45.99402],"type":"Point"}
}