{
  "type": "Feature",
  "properties": {
    "gn:admin1_code":"32",
    "gn:asciiname":"Dolenja Vas pri Polici",
    "gn:country_code":"SI",
    "gn:dem":497,
    "gn:feature_class":"P",
    "gn:feature_code":"PPL",
    "gn:name":"Dolenja Vas pri Polici",
    "gn:population":87,
    "gn:timezone":"Europe/Ljubljana",
    "iso:country":"SI",
    "wof:name":"Dolenja Vas pri Polici",
    "wof:placetype":"locality",
    "wof:population":87
},
  "geometry": {"coordinates":[14.68996,45.99402],"type":"Point"}
}