{
  "type": "Feature",
  "properties": {
    "gn:admin1_code":"36",
    "gn:asciiname":"Idrsek",
    "gn:country_code":"SI",
    "gn:dem":706,
    "gn:feature_class":"P",
    "gn:feature_code":"PPL",
    "gn:name":"Idr\u0161ek",
    "gn:population":41,
    "gn:timezone":"Europe/Ljubljana",
    "iso:country":"SI",
    "name:bos_x_preferred":[
        "Idr\u0161ek"
    ],
    "name:nld_x_preferred":[
        "Idr\u0161ek"
    ],
    "name:pol_x_preferred":[
        "Idr\u0161ek"
    ],
    "name:ron_x_preferred":[
        "Idr\u0161ek"
    ],
    "name:slv_x_preferred":[
        "Idr\u0161ek"
    ],
    "name:ukr_x_preferred":[
        "\u0406\u0434\u0440\u0448\u0435\u043a"
    ],
    "name:und_x_variant":[
        "Idr\u0161ek"
    ],
    "wof:name":"Idrsek",
    "wof:placetype":"locality",
    "wof:population":41
},
  "geometry": {"coordinates":[14.06007,46.01483],"type":"Point"}
}