{
  "type": "Feature",
  "properties": {
    "gn:admin1_code":"D7",
    "gn:asciiname":"Podgorje",
    "gn:country_code":"SI",
    "gn:dem":470,
    "gn:feature_class":"P",
    "gn:feature_code":"PPL",
    "gn:name":"Podgorje",
    "gn:population":164,
    "gn:timezone":"Europe/Ljubljana",
    "iso:country":"SI",
    "wof:name":"Podgorje",
    "wof:placetype":"locality",
    "wof:population":164
},
  "geometry": {"coordinates":[15.075,46.36028],"type":"Point"}
}