{
  "type": "Feature",
  "properties": {
    "gn:admin1_code":"D7",
    "gn:asciiname":"Podgorje",
    "gn:country_code":"SI",
    "gn:dem":470,
    "gn:feature_class":"P",
    "gn:feature_code":"PPL",
    "gn:name":"Podgorje",
    "gn:population":164,
    "gn:timezone":"Europe/Ljubljana",
    "iso:country":"SI",
    "name:bos_x_preferred":[
        "Podgorje"
    ],
    "name:ceb_x_preferred":[
        "Podgorje"
    ],
    "name:hrv_x_preferred":[
        "Podgorje"
    ],
    "name:ita_x_preferred":[
        "Podgorje"
    ],
    "name:nld_x_preferred":[
        "Podgorje"
    ],
    "name:pol_x_preferred":[
        "Podgorje"
    ],
    "name:ron_x_preferred":[
        "Podgorje"
    ],
    "name:slv_x_preferred":[
        "Podgorje"
    ],
    "name:ukr_x_preferred":[
        "\u041f\u043e\u0434\u0433\u043e\u0440'\u0454"
    ],
    "wof:name":"Podgorje",
    "wof:placetype":"locality",
    "wof:population":164
},
  "geometry": {"coordinates":[15.075,46.36028],"type":"Point"}
}