{
  "type": "Feature",
  "properties": {
    "gn:admin1_code":"I2",
    "gn:asciiname":"Gornji Slaveci",
    "gn:country_code":"SI",
    "gn:dem":252,
    "gn:feature_class":"P",
    "gn:feature_code":"PPL",
    "gn:name":"Gornji Slave\u010di",
    "gn:population":451,
    "gn:timezone":"Europe/Ljubljana",
    "iso:country":"SI",
    "name:und_x_variant":[
        "Gornja Slave\u010da",
        "Gornji Slavi\u010di",
        "Falud",
        "Gornji Slave\u010di"
    ],
    "wof:name":"Gornji Slaveci",
    "wof:placetype":"locality",
    "wof:population":451
},
  "geometry": {"coordinates":[16.06667,46.81667],"type":"Point"}
}