{
  "type": "Feature",
  "properties": {
    "gn:admin1_code":"I2",
    "gn:asciiname":"Gornji Slaveci",
    "gn:country_code":"SI",
    "gn:dem":252,
    "gn:feature_class":"P",
    "gn:feature_code":"PPL",
    "gn:name":"Gornji Slave\u010di",
    "gn:population":451,
    "gn:timezone":"Europe/Ljubljana",
    "iso:country":"SI",
    "name:bos_x_preferred":[
        "Gornji Slave\u010di"
    ],
    "name:ceb_x_preferred":[
        "Gornji Slave\u010di"
    ],
    "name:deu_x_preferred":[
        "Gornji Slave\u010di"
    ],
    "name:epo_x_preferred":[
        "Gornji Slave\u010di"
    ],
    "name:hrv_x_preferred":[
        "Gornji Slave\u010di"
    ],
    "name:hun_x_preferred":[
        "Fels\u0151csalog\u00e1ny"
    ],
    "name:nld_x_preferred":[
        "Gornji Slave\u010di"
    ],
    "name:pol_x_preferred":[
        "Gornji Slave\u010di"
    ],
    "name:ron_x_preferred":[
        "Gornji Slave\u010di"
    ],
    "name:slv_x_preferred":[
        "Gornji Slave\u010di"
    ],
    "name:ukr_x_preferred":[
        "\u0413\u043e\u0440\u043d\u0456 \u0421\u043b\u0430\u0432\u0435\u0447\u0456"
    ],
    "name:und_x_variant":[
        "Gornja Slave\u010da",
        "Gornji Slavi\u010di",
        "Falud"
    ],
    "wof:name":"Gornji Slaveci",
    "wof:placetype":"locality",
    "wof:population":451
},
  "geometry": {"coordinates":[16.06667,46.81667],"type":"Point"}
}