{
  "type": "Feature",
  "properties": {
    "gn:admin1_code":"D2",
    "gn:asciiname":"Bukovski Vrh",
    "gn:country_code":"SI",
    "gn:dem":846,
    "gn:feature_class":"P",
    "gn:feature_code":"PPL",
    "gn:name":"Bukovski Vrh",
    "gn:population":23,
    "gn:timezone":"Europe/Ljubljana",
    "iso:country":"SI",
    "wof:name":"Bukovski Vrh",
    "wof:placetype":"locality",
    "wof:population":23
},
  "geometry": {"coordinates":[13.88285,46.14433],"type":"Point"}
}