{
  "type": "Feature",
  "properties": {
    "gn:admin1_code":"C5",
    "gn:asciiname":"Strtenica",
    "gn:country_code":"SI",
    "gn:dem":233,
    "gn:feature_class":"P",
    "gn:feature_code":"PPL",
    "gn:name":"Strtenica",
    "gn:population":97,
    "gn:timezone":"Europe/Ljubljana",
    "iso:country":"SI",
    "name:bos_x_preferred":[
        "Strtenica"
    ],
    "name:hrv_x_preferred":[
        "Strtenica"
    ],
    "name:nld_x_preferred":[
        "Strtenica"
    ],
    "name:pol_x_preferred":[
        "Strtenica"
    ],
    "name:ron_x_preferred":[
        "Strtenica"
    ],
    "name:slv_x_preferred":[
        "Strtenica"
    ],
    "name:ukr_x_preferred":[
        "\u0421\u0442\u0440\u0442\u0435\u043d\u0438\u0446\u044f"
    ],
    "wof:name":"Strtenica",
    "wof:placetype":"locality",
    "wof:population":97
},
  "geometry": {"coordinates":[15.52556,46.18917],"type":"Point"}
}