{
  "type": "Feature",
  "properties": {
    "gn:admin1_code":"N5",
    "gn:asciiname":"Zavrh pri Galiciji",
    "gn:country_code":"SI",
    "gn:dem":356,
    "gn:feature_class":"P",
    "gn:feature_code":"PPL",
    "gn:name":"Zavrh pri Galiciji",
    "gn:population":135,
    "gn:timezone":"Europe/Ljubljana",
    "iso:country":"SI",
    "wof:name":"Zavrh pri Galiciji",
    "wof:placetype":"locality",
    "wof:population":135
},
  "geometry": {"coordinates":[15.21565,46.30815],"type":"Point"}
}