{
  "type": "Feature",
  "properties": {
    "gn:admin1_code":"N5",
    "gn:asciiname":"Zavrh pri Galiciji",
    "gn:country_code":"SI",
    "gn:dem":356,
    "gn:feature_class":"P",
    "gn:feature_code":"PPL",
    "gn:name":"Zavrh pri Galiciji",
    "gn:population":135,
    "gn:timezone":"Europe/Ljubljana",
    "iso:country":"SI",
    "name:ceb_x_preferred":[
        "Zavrh pri Galiciji"
    ],
    "name:hrv_x_preferred":[
        "Zavrh pri Galiciji"
    ],
    "name:nld_x_preferred":[
        "Zavrh pri Galiciji"
    ],
    "name:pol_x_preferred":[
        "Zavrh pri Galiciji"
    ],
    "name:ron_x_preferred":[
        "Zavrh pri Galiciji"
    ],
    "name:slv_x_preferred":[
        "Zavrh pri Galiciji"
    ],
    "name:ukr_x_preferred":[
        "\u0417\u0430\u0432\u0440\u0445-\u043f\u0440\u0438-\u0413\u0430\u043b\u0438\u0446\u0456\u0457"
    ],
    "wof:name":"Zavrh pri Galiciji",
    "wof:placetype":"locality",
    "wof:population":135
},
  "geometry": {"coordinates":[15.21565,46.30815],"type":"Point"}
}