{
  "type": "Feature",
  "properties": {
    "gn:admin1_code":"44",
    "gn:asciiname":"Zamedvedje",
    "gn:country_code":"SI",
    "gn:dem":184,
    "gn:feature_class":"P",
    "gn:feature_code":"PPL",
    "gn:name":"Zamedvedje",
    "gn:population":0,
    "gn:timezone":"Europe/Ljubljana",
    "iso:country":"SI",
    "wof:name":"Zamedvedje",
    "wof:placetype":"locality"
},
  "geometry": {"coordinates":[13.58659,46.0507],"type":"Point"}
}