{
  "type": "Feature",
  "properties": {
    "gn:admin1_code":"50",
    "gn:asciiname":"Krkavce",
    "gn:country_code":"SI",
    "gn:dem":100,
    "gn:feature_class":"P",
    "gn:feature_code":"PPL",
    "gn:name":"Krkav\u010de",
    "gn:population":290,
    "gn:timezone":"Europe/Ljubljana",
    "iso:country":"SI",
    "name:und_x_variant":[
        "Carcase",
        "Carcauzze",
        "Krkav\u010de"
    ],
    "wof:name":"Krkavce",
    "wof:placetype":"locality",
    "wof:population":290
},
  "geometry": {"coordinates":[13.69444,45.46278],"type":"Point"}
}