{
  "type": "Feature",
  "properties": {
    "gn:admin1_code":"50",
    "gn:asciiname":"Krkavce",
    "gn:country_code":"SI",
    "gn:dem":100,
    "gn:feature_class":"P",
    "gn:feature_code":"PPL",
    "gn:name":"Krkav\u010de",
    "gn:population":290,
    "gn:timezone":"Europe/Ljubljana",
    "iso:country":"SI",
    "name:bos_x_preferred":[
        "Krkav\u010de"
    ],
    "name:bul_x_preferred":[
        "\u041a\u044a\u0440\u043a\u0430\u0432\u0446\u0435"
    ],
    "name:ceb_x_preferred":[
        "Krkav\u010de"
    ],
    "name:ita_x_preferred":[
        "Carcase"
    ],
    "name:nld_x_preferred":[
        "Krkav\u010de"
    ],
    "name:pol_x_preferred":[
        "Krkav\u010de"
    ],
    "name:ron_x_preferred":[
        "Krkav\u010de"
    ],
    "name:slv_x_preferred":[
        "Krkav\u010de"
    ],
    "name:srp_x_preferred":[
        "\u041a\u0440\u043a\u0430\u0432\u0447\u0435"
    ],
    "name:ukr_x_preferred":[
        "\u041a\u0440\u043a\u0430\u0432\u0447\u0435"
    ],
    "name:und_x_variant":[
        "Carcauzze"
    ],
    "wof:name":"Krkavce",
    "wof:placetype":"locality",
    "wof:population":290
},
  "geometry": {"coordinates":[13.69444,45.46278],"type":"Point"}
}