{
  "type": "Feature",
  "properties": {
    "gn:country":"SI",
    "gn:fcode":"PPL",
    "gn:population":0,
    "iso:country":"SI",
    "name:bos_x_preferred":[
        "Domanj\u0161evci"
    ],
    "name:ceb_x_preferred":[
        "Domanj\u0161evci"
    ],
    "name:ces_x_preferred":[
        "Domanj\u0161evci"
    ],
    "name:eng_x_preferred":[
        "Domanj\u0161evci"
    ],
    "name:epo_x_preferred":[
        "Domanj\u0161evci"
    ],
    "name:fra_x_preferred":[
        "Domanj\u0161evci"
    ],
    "name:hrv_x_preferred":[
        "Domanj\u0161evci"
    ],
    "name:hun_x_preferred":[
        "Domonkosfa"
    ],
    "name:nld_x_preferred":[
        "Domanj\u0161evci"
    ],
    "name:pol_x_preferred":[
        "Domanj\u0161evci"
    ],
    "name:ron_x_preferred":[
        "Domanj\u0161evci"
    ],
    "name:slv_x_preferred":[
        "Domanj\u0161evci"
    ],
    "name:ukr_x_preferred":[
        "\u0414\u043e\u043c\u0430\u043d\u044c\u0448\u0435\u0432\u0446\u0456"
    ],
    "name:und_x_variant":[
        "Domanj\u0161ovci"
    ],
    "qs_pg:aaroncc":"SI",
    "qs_pg:gn_country":"SI",
    "qs_pg:gn_fcode":"PPL",
    "qs_pg:gn_pop":0,
    "qs_pg:name":"Domanj\u00b5evci",
    "qs_pg:name_adm0":"Slovenija",
    "qs_pg:name_adm1":"Murska Sobota",
    "qs_pg:photos":40,
    "qs_pg:photos_1k":8,
    "qs_pg:photos_9k":1,
    "qs_pg:photos_9r":2,
    "qs_pg:photos_all":40,
    "qs_pg:photos_sr":2,
    "qs_pg:pop_sr":0,
    "qs_pg:qs_pg_placetype":"locality",
    "qs_pg:qs_pg_placetype_gp":"Town",
    "qs_pg:woe_adm0":23424945,
    "woe:adm0_id":23424945,
    "woe:name_adm0":"Slovenija",
    "woe:name_adm1":"Murska Sobota",
    "woe:placetype":"Town",
    "wof:name":"Domanj\u00b5evci",
    "wof:placetype":"locality",
    "wof:population":278
},
  "geometry": {"coordinates":[16.30611,46.78167],"type":"Point"}
}