{
  "type": "Feature",
  "properties": {
    "gn:admin1_code":"32",
    "gn:asciiname":"Kozljevec",
    "gn:country_code":"SI",
    "gn:dem":449,
    "gn:feature_class":"P",
    "gn:feature_code":"PPL",
    "gn:name":"Ko\u017eljevec",
    "gn:population":27,
    "gn:timezone":"Europe/Ljubljana",
    "iso:country":"SI",
    "name:bos_x_preferred":[
        "Ko\u017eljevec"
    ],
    "name:nld_x_preferred":[
        "Ko\u017eljevec"
    ],
    "name:pol_x_preferred":[
        "Ko\u017eljevec"
    ],
    "name:ron_x_preferred":[
        "Ko\u017eljevec"
    ],
    "name:slv_x_preferred":[
        "Ko\u017eljevec"
    ],
    "name:srp_x_preferred":[
        "\u041a\u043e\u0436\u0459\u0435\u0432\u0435\u0446"
    ],
    "name:ukr_x_preferred":[
        "\u041a\u043e\u0436\u043b\u0454\u0432\u0435\u0446\u044c"
    ],
    "name:und_x_variant":[
        "Ko\u017eljevec"
    ],
    "wof:name":"Kozljevec",
    "wof:placetype":"locality",
    "wof:population":27
},
  "geometry": {"coordinates":[14.71875,45.99691],"type":"Point"}
}