{
  "type": "Feature",
  "properties": {
    "gn:admin1_code":"77",
    "gn:asciiname":"Zgornji Tustanj",
    "gn:country_code":"SI",
    "gn:dem":474,
    "gn:feature_class":"P",
    "gn:feature_code":"PPL",
    "gn:name":"Zgornji Tu\u0161tanj",
    "gn:population":77,
    "gn:timezone":"Europe/Ljubljana",
    "iso:country":"SI",
    "name:bos_x_preferred":[
        "Zgornji Tu\u0161tanj"
    ],
    "name:nld_x_preferred":[
        "Zgornji Tu\u0161tanj"
    ],
    "name:pol_x_preferred":[
        "Zgornji Tu\u0161tanj"
    ],
    "name:ron_x_preferred":[
        "Zgornji Tu\u0161tanj"
    ],
    "name:slv_x_preferred":[
        "Zgornji Tu\u0161tanj"
    ],
    "name:ukr_x_preferred":[
        "\u0417\u0433\u043e\u0440\u043d\u0456\u0439 \u0422\u0443\u0448\u0442\u0430\u043d\u044c"
    ],
    "name:und_x_variant":[
        "Zgornji Tu\u0161tanj"
    ],
    "wof:name":"Zgornji Tustanj",
    "wof:placetype":"locality",
    "wof:population":77
},
  "geometry": {"coordinates":[14.72478,46.11981],"type":"Point"}
}