{
  "type": "Feature",
  "properties": {
    "gn:admin1_code":"B9",
    "gn:asciiname":"Pungert",
    "gn:country_code":"SI",
    "gn:dem":418,
    "gn:feature_class":"P",
    "gn:feature_code":"PPL",
    "gn:name":"Pungert",
    "gn:population":147,
    "gn:timezone":"Europe/Ljubljana",
    "iso:country":"SI",
    "name:bos_x_preferred":[
        "Pungert"
    ],
    "name:ceb_x_preferred":[
        "Pungert"
    ],
    "name:hrv_x_preferred":[
        "Pungert"
    ],
    "name:nld_x_preferred":[
        "Pungert"
    ],
    "name:pol_x_preferred":[
        "Pungert"
    ],
    "name:ron_x_preferred":[
        "Pungert"
    ],
    "name:slv_x_preferred":[
        "Pungert"
    ],
    "name:ukr_x_preferred":[
        "\u041f\u0443\u043d\u0433\u0435\u0440\u0442"
    ],
    "wof:name":"Pungert",
    "wof:placetype":"locality",
    "wof:population":147
},
  "geometry": {"coordinates":[14.33175,46.15223],"type":"Point"}
}