{
  "type": "Feature",
  "properties": {
    "gn:admin1_code":"66",
    "gn:asciiname":"Srednja Vas pri Dragi",
    "gn:country_code":"SI",
    "gn:dem":776,
    "gn:feature_class":"P",
    "gn:feature_code":"PPL",
    "gn:name":"Srednja Vas pri Dragi",
    "gn:population":44,
    "gn:timezone":"Europe/Ljubljana",
    "iso:country":"SI",
    "name:bos_x_preferred":[
        "Srednja vas pri Dragi"
    ],
    "name:hrv_x_preferred":[
        "Srednja Vas pri Dragi"
    ],
    "name:nld_x_preferred":[
        "Srednja vas pri Dragi"
    ],
    "name:pol_x_preferred":[
        "Srednja vas pri Dragi"
    ],
    "name:ron_x_preferred":[
        "Srednja vas pri Dragi"
    ],
    "name:slv_x_preferred":[
        "Srednja vas pri Dragi"
    ],
    "name:ukr_x_preferred":[
        "\u0421\u0440\u0435\u0434\u043d\u044f \u0412\u0430\u0441-\u043f\u0440\u0438-\u0414\u0440\u0430\u0433\u0456"
    ],
    "name:und_x_variant":[
        "Srednja Vas"
    ],
    "wof:name":"Srednja Vas pri Dragi",
    "wof:placetype":"locality",
    "wof:population":44
},
  "geometry": {"coordinates":[14.66306,45.61667],"type":"Point"}
}