{
  "type": "Feature",
  "properties": {
    "gn:admin1_code":"G7",
    "gn:asciiname":"Turnse",
    "gn:country_code":"SI",
    "gn:dem":337,
    "gn:feature_class":"P",
    "gn:feature_code":"PPL",
    "gn:name":"Turn\u0161e",
    "gn:population":267,
    "gn:timezone":"Europe/Ljubljana",
    "iso:country":"SI",
    "name:und_x_variant":[
        "Turn\u0161e"
    ],
    "wof:name":"Turnse",
    "wof:placetype":"locality",
    "wof:population":267
},
  "geometry": {"coordinates":[14.62005,46.16549000000001],"type":"Point"}
}