{
  "type": "Feature",
  "properties": {
    "gn:admin1_code":"G7",
    "gn:asciiname":"Turnse",
    "gn:country_code":"SI",
    "gn:dem":337,
    "gn:feature_class":"P",
    "gn:feature_code":"PPL",
    "gn:name":"Turn\u0161e",
    "gn:population":267,
    "gn:timezone":"Europe/Ljubljana",
    "iso:country":"SI",
    "name:bos_x_preferred":[
        "Turn\u0161e"
    ],
    "name:ceb_x_preferred":[
        "Turn\u0161e"
    ],
    "name:fas_x_preferred":[
        "\u062a\u0648\u0631\u0646\u0634"
    ],
    "name:pol_x_preferred":[
        "Turn\u0161e"
    ],
    "name:ron_x_preferred":[
        "Turn\u0161e"
    ],
    "name:slv_x_preferred":[
        "Turn\u0161e"
    ],
    "name:ukr_x_preferred":[
        "\u0422\u0443\u0440\u043d\u0448\u0435"
    ],
    "name:urd_x_preferred":[
        "\u062a\u0631\u0646\u0634"
    ],
    "wof:name":"Turnse",
    "wof:placetype":"locality",
    "wof:population":267
},
  "geometry": {"coordinates":[14.62005,46.16549000000001],"type":"Point"}
}