{
  "type": "Feature",
  "properties": {
    "gn:admin1_code":"57",
    "gn:asciiname":"Strmca",
    "gn:country_code":"SI",
    "gn:dem":311,
    "gn:feature_class":"P",
    "gn:feature_code":"PPL",
    "gn:name":"Strmca",
    "gn:population":404,
    "gn:timezone":"Europe/Ljubljana",
    "iso:country":"SI",
    "name:bos_x_preferred":[
        "Strmca"
    ],
    "name:ceb_x_preferred":[
        "Strmca"
    ],
    "name:hrv_x_preferred":[
        "Strmca"
    ],
    "name:nld_x_preferred":[
        "Strmca"
    ],
    "name:pol_x_preferred":[
        "Strmca"
    ],
    "name:ron_x_preferred":[
        "Strmca"
    ],
    "name:slv_x_preferred":[
        "Strmca"
    ],
    "name:ukr_x_preferred":[
        "\u0421\u0442\u0440\u043c\u0446\u0430"
    ],
    "wof:name":"Strmca",
    "wof:placetype":"locality",
    "wof:population":404
},
  "geometry": {"coordinates":[15.21992,46.15007],"type":"Point"}
}