{
  "type": "Feature",
  "properties": {
    "gn:gn_country":"SI",
    "gn:gn_fcode":"PPL",
    "gn:gn_pop":0,
    "gn:population":117,
    "iso:country":"SI",
    "name:eng_x_preferred":[
        "Resnik"
    ],
    "name:hrv_x_preferred":[
        "Resnik"
    ],
    "name:nld_x_preferred":[
        "Resnik"
    ],
    "name:ron_x_preferred":[
        "Resnik"
    ],
    "name:slv_x_preferred":[
        "Resnik"
    ],
    "name:ukr_x_preferred":[
        "\u0420\u0435\u0441\u043d\u0438\u043a"
    ],
    "qs_pg:aaroncc":"SI",
    "qs_pg:gn_country":"SI",
    "qs_pg:gn_fcode":"PPL",
    "qs_pg:gn_pop":0,
    "qs_pg:name":"Resnik",
    "qs_pg:name_adm0":"Slovenija",
    "qs_pg:name_adm1":"Slovenske Konjice",
    "qs_pg:photos":9,
    "qs_pg:photos_1k":2,
    "qs_pg:photos_9k":1,
    "qs_pg:photos_9r":1,
    "qs_pg:photos_all":9,
    "qs_pg:photos_sr":1,
    "qs_pg:pop_sr":0,
    "qs_pg:qs_pg_placetype":"locality",
    "qs_pg:qs_pg_placetype_gp":"Town",
    "qs_pg:woe_adm0":23424945,
    "woe:adm0_id":23424945,
    "woe:name_adm0":"Slovenija",
    "woe:name_adm1":"Slovenske Konjice",
    "woe:placetype":"Town",
    "wof:name":"Resnik",
    "wof:placetype":"locality",
    "wof:population":117
},
  "geometry": {"coordinates":[15.36667,46.43333],"type":"Point"}
}