{
  "type": "Feature",
  "properties": {
    "gn:admin1_code":"F1",
    "gn:asciiname":"Selca",
    "gn:country_code":"SI",
    "gn:dem":469,
    "gn:feature_class":"P",
    "gn:feature_code":"PPL",
    "gn:name":"Selca",
    "gn:population":666,
    "gn:timezone":"Europe/Ljubljana",
    "iso:country":"SI",
    "name:und_x_variant":[
        "Selzach",
        "Selce",
        "Selca"
    ],
    "wof:name":"Selca",
    "wof:placetype":"locality",
    "wof:population":666
},
  "geometry": {"coordinates":[14.20556,46.22444],"type":"Point"}
}