{
  "type": "Feature",
  "properties": {
    "gn:population":116,
    "iso:country":"SI",
    "name:hbs_x_preferred":[
        "Dobje pri Planini"
    ],
    "name:hrv_x_preferred":[
        "Dobje pri Planini"
    ],
    "name:nld_x_preferred":[
        "Dobje pri Planini"
    ],
    "name:ron_x_preferred":[
        "Dobje pri Planini"
    ],
    "name:slv_x_preferred":[
        "Dobje pri Planini"
    ],
    "name:srp_x_preferred":[
        "\u0414\u043e\u0431\u0458\u0435 \u043f\u0440\u0438 \u041f\u043b\u0430\u043d\u0438\u043d\u0438"
    ],
    "name:ukr_x_preferred":[
        "\u0414\u043e\u0431\u0454-\u043f\u0440\u0438-\u041f\u043b\u0430\u043d\u0438\u043d\u0456"
    ],
    "name:unk_x_variant":[
        "Dobje"
    ],
    "qs:a0":"Slovenija",
    "qs:a1":"*",
    "qs:a1r":"0",
    "qs:adm0":"Slovenija",
    "qs:la_lc":"*",
    "qs:level":"locality",
    "qs:loc":"Dobje pri Planini",
    "qs:loc_alt":"Dobje pri Planini",
    "qs:pop":0,
    "qs:type":"buffered point",
    "wd:wordcount":226,
    "wof:name":"Dobje pri Planini",
    "wof:placetype":"locality",
    "wof:population":116
},
  "geometry": {"coordinates":[15.396429,46.1366],"type":"Point"}
}