{
  "type": "Feature",
  "properties": {
    "gn:admin1_code":"94",
    "gn:asciiname":"Hrenovice",
    "gn:country_code":"SI",
    "gn:dem":566,
    "gn:feature_class":"P",
    "gn:feature_code":"PPL",
    "gn:name":"Hrenovice",
    "gn:population":193,
    "gn:timezone":"Europe/Ljubljana",
    "iso:country":"SI",
    "name:bos_x_preferred":[
        "Hrenovice"
    ],
    "name:ceb_x_preferred":[
        "Hrenovice"
    ],
    "name:hrv_x_preferred":[
        "Hrenovice"
    ],
    "name:ita_x_preferred":[
        "Crenovizza"
    ],
    "name:nld_x_preferred":[
        "Hrenovice"
    ],
    "name:pol_x_preferred":[
        "Hrenovice"
    ],
    "name:ron_x_preferred":[
        "Hrenovice"
    ],
    "name:slv_x_preferred":[
        "Hrenovice"
    ],
    "name:ukr_x_preferred":[
        "\u0425\u0440\u0435\u043d\u043e\u0432\u0438\u0446\u0435"
    ],
    "name:und_x_variant":[
        "Hrenovilz"
    ],
    "wof:name":"Hrenovice",
    "wof:placetype":"locality",
    "wof:population":193
},
  "geometry": {"coordinates":[14.13194,45.78],"type":"Point"}
}