{
  "type": "Feature",
  "properties": {
    "gn:admin1_code":"L7",
    "gn:asciiname":"Sele",
    "gn:country_code":"SI",
    "gn:dem":490,
    "gn:feature_class":"P",
    "gn:feature_code":"PPL",
    "gn:name":"Sele",
    "gn:population":27,
    "gn:timezone":"Europe/Ljubljana",
    "iso:country":"SI",
    "wof:name":"Sele",
    "wof:placetype":"locality",
    "wof:population":27
},
  "geometry": {"coordinates":[15.41975,46.17476],"type":"Point"}
}