{
  "type": "Feature",
  "properties": {
    "gn:admin1_code":"04",
    "gn:asciiname":"Hebat",
    "gn:country_code":"SI",
    "gn:dem":1047,
    "gn:feature_class":"P",
    "gn:feature_code":"PPL",
    "gn:name":"Hebat",
    "gn:population":0,
    "gn:timezone":"Europe/Ljubljana",
    "iso:country":"SI",
    "wof:name":"Hebat",
    "wof:placetype":"locality"
},
  "geometry": {"coordinates":[13.87028,46.29722],"type":"Point"}
}