{
  "type": "Feature",
  "properties": {
    "gn:admin1_code":"N3",
    "gn:asciiname":"Lemberg pri Novi Cerkvi",
    "gn:country_code":"SI",
    "gn:dem":327,
    "gn:feature_class":"P",
    "gn:feature_code":"PPL",
    "gn:name":"Lemberg pri Novi Cerkvi",
    "gn:population":140,
    "gn:timezone":"Europe/Ljubljana",
    "iso:country":"SI",
    "wof:name":"Lemberg pri Novi Cerkvi",
    "wof:placetype":"locality",
    "wof:population":140
},
  "geometry": {"coordinates":[15.24523,46.32087],"type":"Point"}
}