{
  "type": "Feature",
  "properties": {
    "gn:admin1_code":"54",
    "gn:asciiname":"Stari Grad",
    "gn:country_code":"SI",
    "gn:dem":181,
    "gn:feature_class":"P",
    "gn:feature_code":"PPL",
    "gn:name":"Stari Grad",
    "gn:population":213,
    "gn:timezone":"Europe/Ljubljana",
    "iso:country":"SI",
    "wof:name":"Stari Grad",
    "wof:placetype":"locality",
    "wof:population":213
},
  "geometry": {"coordinates":[15.53971,45.94932],"type":"Point"}
}