{
  "type": "Feature",
  "properties": {
    "gn:admin1_code":"H7",
    "gn:asciiname":"Grintovec",
    "gn:country_code":"SI",
    "gn:dem":503,
    "gn:feature_class":"P",
    "gn:feature_code":"PPLL",
    "gn:name":"Grintovec",
    "gn:population":0,
    "gn:timezone":"Europe/Ljubljana",
    "iso:country":"SI",
    "name:ces_x_preferred":[
        "Grintovec"
    ],
    "name:deu_x_preferred":[
        "Grintovec"
    ],
    "name:eus_x_preferred":[
        "Grintovec mendia"
    ],
    "name:fra_x_preferred":[
        "Grintovec"
    ],
    "name:hrv_x_preferred":[
        "Grintovec"
    ],
    "name:hun_x_preferred":[
        "Grintovec"
    ],
    "name:ita_x_preferred":[
        "Grintovec"
    ],
    "name:nld_x_preferred":[
        "Grintovec"
    ],
    "name:nno_x_preferred":[
        "Grintovec"
    ],
    "name:pol_x_preferred":[
        "Grintovec"
    ],
    "name:slv_x_preferred":[
        "Grintovec"
    ],
    "name:spa_x_preferred":[
        "Grintovec"
    ],
    "name:srp_x_preferred":[
        "\u0413\u0440\u0438\u043d\u0442\u043e\u0432\u0435\u0446"
    ],
    "name:zho_x_preferred":[
        "\u683c\u6797\u6258\u8cbb\u514b\u5cf0"
    ],
    "wof:name":"Grintovec",
    "wof:placetype":"locality"
},
  "geometry": {"coordinates":[14.89843,45.68951],"type":"Point"}
}