{
  "type": "Feature",
  "properties": {
    "gn:admin1_code":"H7",
    "gn:asciiname":"Grintovec",
    "gn:country_code":"SI",
    "gn:dem":503,
    "gn:feature_class":"P",
    "gn:feature_code":"PPLL",
    "gn:name":"Grintovec",
    "gn:population":0,
    "gn:timezone":"Europe/Ljubljana",
    "iso:country":"SI",
    "wof:name":"Grintovec",
    "wof:placetype":"locality"
},
  "geometry": {"coordinates":[14.89843,45.68951],"type":"Point"}
}