{
  "type": "Feature",
  "properties": {
    "gn:admin1_code":"01",
    "gn:asciiname":"Vrtovin",
    "gn:country_code":"SI",
    "gn:dem":1130,
    "gn:feature_class":"P",
    "gn:feature_code":"PPL",
    "gn:name":"Vrtovin",
    "gn:population":492,
    "gn:timezone":"Europe/Ljubljana",
    "iso:country":"SI",
    "name:bos_x_preferred":[
        "Vrtovin"
    ],
    "name:bul_x_preferred":[
        "\u0412\u0440\u044a\u0442\u043e\u0432\u0438\u043d"
    ],
    "name:ceb_x_preferred":[
        "Vrtovin"
    ],
    "name:hun_x_preferred":[
        "Vrtovin"
    ],
    "name:ita_x_preferred":[
        "Vertovino"
    ],
    "name:nld_x_preferred":[
        "Vrtovin"
    ],
    "name:pol_x_preferred":[
        "Vrtovin"
    ],
    "name:ron_x_preferred":[
        "Vrtovin"
    ],
    "name:slv_x_preferred":[
        "Vrtovin"
    ],
    "name:srp_x_preferred":[
        "\u0412\u0440\u0442\u043e\u0432\u0438\u043d"
    ],
    "name:ukr_x_preferred":[
        "\u0412\u0440\u0442\u043e\u0432\u0438\u043d"
    ],
    "wof:name":"Vrtovin",
    "wof:placetype":"locality",
    "wof:population":492
},
  "geometry": {"coordinates":[13.83036,45.93131],"type":"Point"}
}