{
  "type": "Feature",
  "properties": {
    "gn:admin1_code":"G4",
    "gn:asciiname":"Srednji Vrh",
    "gn:country_code":"SI",
    "gn:dem":677,
    "gn:feature_class":"P",
    "gn:feature_code":"PPL",
    "gn:name":"Srednji Vrh",
    "gn:population":98,
    "gn:timezone":"Europe/Ljubljana",
    "iso:country":"SI",
    "wof:name":"Srednji Vrh",
    "wof:placetype":"locality",
    "wof:population":98
},
  "geometry": {"coordinates":[14.24519,46.07246],"type":"Point"}
}