{
  "type": "Feature",
  "properties": {
    "gn:admin1_code":"G4",
    "gn:asciiname":"Srednji Vrh",
    "gn:country_code":"SI",
    "gn:dem":677,
    "gn:feature_class":"P",
    "gn:feature_code":"PPL",
    "gn:name":"Srednji Vrh",
    "gn:population":98,
    "gn:timezone":"Europe/Ljubljana",
    "iso:country":"SI",
    "name:bos_x_preferred":[
        "Srednji Vrh"
    ],
    "name:bul_x_preferred":[
        "\u0421\u0440\u0435\u0434\u043d\u0438 \u0432\u0440\u044a\u0445"
    ],
    "name:nld_x_preferred":[
        "Srednji Vrh"
    ],
    "name:pol_x_preferred":[
        "Srednji Vrh"
    ],
    "name:ron_x_preferred":[
        "Srednji Vrh"
    ],
    "name:slv_x_preferred":[
        "Srednji Vrh"
    ],
    "name:ukr_x_preferred":[
        "\u0421\u0440\u0435\u0434\u043d\u0456\u0439 \u0412\u0440\u0445"
    ],
    "wof:name":"Srednji Vrh",
    "wof:placetype":"locality",
    "wof:population":98
},
  "geometry": {"coordinates":[14.24519,46.07246],"type":"Point"}
}