{
  "type": "Feature",
  "properties": {
    "gn:admin1_code":"66",
    "gn:asciiname":"Glazuta",
    "gn:country_code":"SI",
    "gn:dem":1012,
    "gn:feature_class":"P",
    "gn:feature_code":"PPL",
    "gn:name":"Gla\u017euta",
    "gn:population":0,
    "gn:timezone":"Europe/Ljubljana",
    "iso:country":"SI",
    "name:bos_x_preferred":[
        "Gla\u017euta"
    ],
    "name:nld_x_preferred":[
        "Gla\u017euta"
    ],
    "name:pol_x_preferred":[
        "Gla\u017euta"
    ],
    "name:ron_x_preferred":[
        "Gla\u017euta"
    ],
    "name:slv_x_preferred":[
        "Gla\u017euta"
    ],
    "name:ukr_x_preferred":[
        "\u0413\u043b\u0430\u0436\u0443\u0442\u0430"
    ],
    "name:und_x_variant":[
        "Gla\u017euta"
    ],
    "wof:name":"Glazuta",
    "wof:placetype":"locality"
},
  "geometry": {"coordinates":[14.68417,45.6625],"type":"Point"}
}