{
  "type": "Feature",
  "properties": {
    "gn:admin1_code":"F2",
    "gn:asciiname":"Ledinica",
    "gn:country_code":"SI",
    "gn:dem":565,
    "gn:feature_class":"P",
    "gn:feature_code":"PPL",
    "gn:name":"Ledinica",
    "gn:population":75,
    "gn:timezone":"Europe/Ljubljana",
    "iso:country":"SI",
    "name:bos_x_preferred":[
        "Ledinica"
    ],
    "name:bul_x_preferred":[
        "\u041b\u0435\u0434\u0438\u043d\u0438\u0446\u0430"
    ],
    "name:hrv_x_preferred":[
        "Ledinica"
    ],
    "name:nld_x_preferred":[
        "Ledinica"
    ],
    "name:pol_x_preferred":[
        "Ledinica"
    ],
    "name:ron_x_preferred":[
        "Ledinica"
    ],
    "name:slv_x_preferred":[
        "Ledinica"
    ],
    "name:ukr_x_preferred":[
        "\u041b\u0435\u0434\u0438\u043d\u0438\u0446\u044f"
    ],
    "wof:name":"Ledinica",
    "wof:placetype":"locality",
    "wof:population":75
},
  "geometry": {"coordinates":[14.09191,46.05577],"type":"Point"}
}