{
  "type": "Feature",
  "properties": {
    "gn:admin1_code":"B9",
    "gn:asciiname":"Sveti Florijan nad Skofjo Loko",
    "gn:country_code":"SI",
    "gn:dem":660,
    "gn:feature_class":"P",
    "gn:feature_code":"PPL",
    "gn:name":"Sveti Florijan nad \u0160kofjo Loko",
    "gn:population":31,
    "gn:timezone":"Europe/Ljubljana",
    "iso:country":"SI",
    "name:bos_x_preferred":[
        "Sveti Florijan nad \u0160kofjo Loko"
    ],
    "name:hrv_x_preferred":[
        "Sveti Florjan nad \u0160kofjo Loko"
    ],
    "name:nld_x_preferred":[
        "Florjan nad Zmincem"
    ],
    "name:pol_x_preferred":[
        "Sveti Florjan nad \u0160kofjo Loko"
    ],
    "name:ron_x_preferred":[
        "Sveti Florijan nad \u0160kofjo Loko"
    ],
    "name:slv_x_preferred":[
        "Sveti Florijan nad \u0160kofjo Loko"
    ],
    "name:ukr_x_preferred":[
        "\u0421\u0432\u0435\u0442\u0438\u0439 \u0424\u043b\u043e\u0440\u044f\u043d-\u043d\u0430\u0434-\u0428\u043a\u043e\u0444\u044c\u043e \u041b\u043e\u043a\u043e"
    ],
    "name:und_x_variant":[
        "Sveti Florijan nad \u0160kofjo Loko"
    ],
    "wof:name":"Sveti Florijan nad Skofjo Loko",
    "wof:placetype":"locality",
    "wof:population":31
},
  "geometry": {"coordinates":[14.23005,46.14384],"type":"Point"}
}