{
  "type": "Feature",
  "properties": {
    "gn:admin1_code":"B9",
    "gn:asciiname":"Sveti Florijan nad Skofjo Loko",
    "gn:country_code":"SI",
    "gn:dem":660,
    "gn:feature_class":"P",
    "gn:feature_code":"PPL",
    "gn:name":"Sveti Florijan nad \u0160kofjo Loko",
    "gn:population":31,
    "gn:timezone":"Europe/Ljubljana",
    "iso:country":"SI",
    "name:und_x_variant":[
        "Sveti Florijan nad \u0160kofjo Loko"
    ],
    "wof:name":"Sveti Florijan nad Skofjo Loko",
    "wof:placetype":"locality",
    "wof:population":31
},
  "geometry": {"coordinates":[14.23005,46.14384],"type":"Point"}
}