{
  "type": "Feature",
  "properties": {
    "gn:admin1_code":"N8",
    "gn:asciiname":"Lazina",
    "gn:country_code":"SI",
    "gn:dem":485,
    "gn:feature_class":"P",
    "gn:feature_code":"PPL",
    "gn:name":"Lazina",
    "gn:population":17,
    "gn:timezone":"Europe/Ljubljana",
    "iso:country":"SI",
    "name:bos_x_preferred":[
        "Lazina"
    ],
    "name:bul_x_preferred":[
        "\u041b\u0430\u0437\u0438\u043d\u0430"
    ],
    "name:hrv_x_preferred":[
        "Lazina"
    ],
    "name:nld_x_preferred":[
        "Lazina"
    ],
    "name:pol_x_preferred":[
        "Lazina"
    ],
    "name:ron_x_preferred":[
        "Lazina"
    ],
    "name:slv_x_preferred":[
        "Lazina"
    ],
    "name:ukr_x_preferred":[
        "\u041b\u0430\u0437\u0438\u043d\u0430"
    ],
    "wof:name":"Lazina",
    "wof:placetype":"locality",
    "wof:population":17
},
  "geometry": {"coordinates":[14.89335,45.77214],"type":"Point"}
}