{
  "type": "Feature",
  "properties": {
    "gn:admin1_code":"06",
    "gn:asciiname":"Zapodnem",
    "gn:country_code":"SI",
    "gn:dem":1600,
    "gn:feature_class":"P",
    "gn:feature_code":"PPL",
    "gn:name":"Zapodnem",
    "gn:population":0,
    "gn:timezone":"Europe/Ljubljana",
    "iso:country":"SI",
    "wof:name":"Zapodnem",
    "wof:placetype":"locality"
},
  "geometry": {"coordinates":[13.73028,46.39917],"type":"Point"}
}