{
  "type": "Feature",
  "properties": {
    "gn:gn_country":"SI",
    "gn:gn_fcode":"PPL",
    "gn:gn_pop":0,
    "iso:country":"SI",
    "name:bos_x_preferred":[
        "Stara Fu\u017eina"
    ],
    "name:eng_x_preferred":[
        "Stara Fu\u017eina"
    ],
    "name:hrv_x_preferred":[
        "Stara Fu\u017eina"
    ],
    "name:nld_x_preferred":[
        "Stara Fu\u017eina"
    ],
    "name:ron_x_preferred":[
        "Stara Fu\u017eina"
    ],
    "name:slv_x_preferred":[
        "Stara Fu\u017eina"
    ],
    "name:ukr_x_preferred":[
        "\u0421\u0442\u0430\u0440\u0430 \u0424\u0443\u0436\u0438\u043d\u0430"
    ],
    "qs_pg:aaroncc":"SI",
    "qs_pg:gn_country":"SI",
    "qs_pg:gn_fcode":"PPL",
    "qs_pg:gn_pop":0,
    "qs_pg:name":"Stara Fu\u017eina",
    "qs_pg:name_adm0":"Slovenija",
    "qs_pg:name_adm1":"Radovljica",
    "qs_pg:photos":183,
    "qs_pg:photos_1k":37,
    "qs_pg:photos_9k":1,
    "qs_pg:photos_9r":4,
    "qs_pg:photos_all":183,
    "qs_pg:photos_sr":4,
    "qs_pg:pop_sr":0,
    "qs_pg:qs_pg_placetype":"locality",
    "qs_pg:qs_pg_placetype_gp":"Town",
    "qs_pg:woe_adm0":23424945,
    "woe:adm0_id":23424945,
    "woe:name_adm0":"Slovenija",
    "woe:name_adm1":"Radovljica",
    "woe:placetype":"Town",
    "wof:name":"Stara Fu\u017eina",
    "wof:placetype":"locality"
},
  "geometry": {"coordinates":[13.89611,46.28778],"type":"Point"}
}