{
  "type": "Feature",
  "properties": {
    "iso:country":"SI",
    "name:bos_x_preferred":[
        "Vol\u010dja Draga"
    ],
    "name:dut_x_preferred":[
        "Vol\u010dja Draga"
    ],
    "name:eng_x_preferred":[
        "Vol\u010dja Draga"
    ],
    "name:rum_x_preferred":[
        "Vol\u010dja Draga"
    ],
    "name:slv_x_preferred":[
        "Vol\u010dja Draga"
    ],
    "name:ukr_x_preferred":[
        "\u0412\u043e\u043b\u0447\u044f \u0414\u0440\u0430\u0433\u0430"
    ],
    "qs_pg:aaroncc":"SI",
    "qs_pg:name":"Vol\u010dja Draga",
    "qs_pg:name_adm0":"Slovenija",
    "qs_pg:name_adm1":"Nova Gorica",
    "qs_pg:photos":112,
    "qs_pg:photos_1k":23,
    "qs_pg:photos_9k":1,
    "qs_pg:photos_9r":3,
    "qs_pg:photos_all":112,
    "qs_pg:photos_sr":3,
    "qs_pg:pop_sr":0,
    "qs_pg:qs_pg_placetype":"locality",
    "qs_pg:qs_pg_placetype_gp":"Town",
    "qs_pg:woe_adm0":23424945,
    "woe:adm0_id":23424945,
    "woe:name_adm0":"Slovenija",
    "woe:name_adm1":"Nova Gorica",
    "woe:placetype":"Town",
    "wof:name":"Vol\u010dja Draga",
    "wof:placetype":"locality"
},
  "geometry": {"coordinates":[13.697633,45.904672],"type":"Point"}
}