{
  "type": "Feature",
  "properties": {
    "gn:admin1_code":"92",
    "gn:asciiname":"Pecelj",
    "gn:country_code":"SI",
    "gn:dem":221,
    "gn:feature_class":"P",
    "gn:feature_code":"PPL",
    "gn:name":"Pecelj",
    "gn:population":55,
    "gn:timezone":"Europe/Ljubljana",
    "iso:country":"SI",
    "name:bos_x_preferred":[
        "Pecelj"
    ],
    "name:hrv_x_preferred":[
        "Pecelj"
    ],
    "name:nld_x_preferred":[
        "Pecelj"
    ],
    "name:pol_x_preferred":[
        "Pecelj"
    ],
    "name:ron_x_preferred":[
        "Pecelj"
    ],
    "name:slv_x_preferred":[
        "Pecelj"
    ],
    "name:ukr_x_preferred":[
        "\u041f\u0435\u0446\u0435\u043b\u044c"
    ],
    "wof:name":"Pecelj",
    "wof:placetype":"locality",
    "wof:population":55
},
  "geometry": {"coordinates":[15.58463,46.11458],"type":"Point"}
}