{
  "type": "Feature",
  "properties": {
    "gn:admin1_code":"38",
    "gn:asciiname":"Kalec",
    "gn:country_code":"SI",
    "gn:dem":575,
    "gn:feature_class":"P",
    "gn:feature_code":"PPLL",
    "gn:name":"Kalec",
    "gn:population":0,
    "gn:timezone":"Europe/Ljubljana",
    "iso:country":"SI",
    "name:ces_x_preferred":[
        "Kalec"
    ],
    "name:spa_x_preferred":[
        "Kalec"
    ],
    "wof:name":"Kalec",
    "wof:placetype":"locality"
},
  "geometry": {"coordinates":[14.24566,45.64075],"type":"Point"}
}