{
  "type": "Feature",
  "properties": {
    "gn:admin1_code":"C5",
    "gn:asciiname":"Orehovec",
    "gn:country_code":"SI",
    "gn:dem":318,
    "gn:feature_class":"P",
    "gn:feature_code":"PPL",
    "gn:name":"Orehovec",
    "gn:population":52,
    "gn:timezone":"Europe/Ljubljana",
    "iso:country":"SI",
    "wof:name":"Orehovec",
    "wof:placetype":"locality",
    "wof:population":52
},
  "geometry": {"coordinates":[15.53336,46.18139],"type":"Point"}
}