{
  "type": "Feature",
  "properties": {
    "gn:admin1_code":"C5",
    "gn:asciiname":"Orehovec",
    "gn:country_code":"SI",
    "gn:dem":318,
    "gn:feature_class":"P",
    "gn:feature_code":"PPL",
    "gn:name":"Orehovec",
    "gn:population":52,
    "gn:timezone":"Europe/Ljubljana",
    "iso:country":"SI",
    "name:bos_x_preferred":[
        "Orehovec"
    ],
    "name:hrv_x_preferred":[
        "Orehovec"
    ],
    "name:nld_x_preferred":[
        "Orehovec"
    ],
    "name:pol_x_preferred":[
        "Orehovec"
    ],
    "name:ron_x_preferred":[
        "Orehovec"
    ],
    "name:slv_x_preferred":[
        "Orehovec"
    ],
    "name:ukr_x_preferred":[
        "\u041e\u0440\u0435\u0445\u043e\u0432\u0435\u0446\u044c"
    ],
    "wof:name":"Orehovec",
    "wof:placetype":"locality",
    "wof:population":52
},
  "geometry": {"coordinates":[15.53336,46.18139],"type":"Point"}
}