{
  "type": "Feature",
  "properties": {
    "gn:admin1_code":"08",
    "gn:asciiname":"Racja Vas",
    "gn:country_code":"SI",
    "gn:dem":150,
    "gn:feature_class":"P",
    "gn:feature_code":"PPL",
    "gn:name":"Ra\u010dja Vas",
    "gn:population":110,
    "gn:timezone":"Europe/Ljubljana",
    "iso:country":"SI",
    "name:bos_x_preferred":[
        "Ra\u010dja vas"
    ],
    "name:ceb_x_preferred":[
        "Ra\u010dja Vas"
    ],
    "name:hrv_x_preferred":[
        "Ra\u010dja vas"
    ],
    "name:nld_x_preferred":[
        "Ra\u010dja vas"
    ],
    "name:pol_x_preferred":[
        "Ra\u010dja vas"
    ],
    "name:ron_x_preferred":[
        "Ra\u010dja vas"
    ],
    "name:slv_x_preferred":[
        "Ra\u010dja vas"
    ],
    "name:ukr_x_preferred":[
        "\u0420\u0430\u0447\u044f \u0412\u0430\u0441"
    ],
    "wof:name":"Racja Vas",
    "wof:placetype":"locality",
    "wof:population":110
},
  "geometry": {"coordinates":[15.54148,45.8881],"type":"Point"}
}