{
  "type": "Feature",
  "properties": {
    "gn:admin1_code":"B6",
    "gn:asciiname":"Mala Hubajnica",
    "gn:country_code":"SI",
    "gn:dem":430,
    "gn:feature_class":"P",
    "gn:feature_code":"PPL",
    "gn:name":"Mala Hubajnica",
    "gn:population":44,
    "gn:timezone":"Europe/Ljubljana",
    "iso:country":"SI",
    "name:slv_x_historical":[
        "Mala Hubanjica"
    ],
    "name:slv_x_preferred":[
        "Mala Hubanjica"
    ],
    "wof:name":"Mala Hubajnica",
    "wof:placetype":"locality",
    "wof:population":44
},
  "geometry": {"coordinates":[15.29852,45.95765],"type":"Point"}
}