{
  "type": "Feature",
  "properties": {
    "gn:admin1_code":"B6",
    "gn:asciiname":"Mala Hubajnica",
    "gn:country_code":"SI",
    "gn:dem":430,
    "gn:feature_class":"P",
    "gn:feature_code":"PPL",
    "gn:name":"Mala Hubajnica",
    "gn:population":44,
    "gn:timezone":"Europe/Ljubljana",
    "iso:country":"SI",
    "name:bos_x_preferred":[
        "Mala Hubajnica"
    ],
    "name:nld_x_preferred":[
        "Mala Hubajnica"
    ],
    "name:pol_x_preferred":[
        "Mala Hubajnica"
    ],
    "name:ron_x_preferred":[
        "Mala Hubajnica"
    ],
    "name:slv_x_historical":[
        "Mala Hubanjica"
    ],
    "name:slv_x_preferred":[
        "Mala Hubanjica"
    ],
    "name:slv_x_variant":[
        "Mala Hubajnica"
    ],
    "name:ukr_x_preferred":[
        "\u041c\u0430\u043b\u0430 \u0425\u0443\u0431\u0430\u0439\u043d\u0438\u0446\u044f"
    ],
    "wof:name":"Mala Hubajnica",
    "wof:placetype":"locality",
    "wof:population":44
},
  "geometry": {"coordinates":[15.29852,45.95765],"type":"Point"}
}