{
  "type": "Feature",
  "properties": {
    "gn:admin1_code":"77",
    "gn:asciiname":"Gorica",
    "gn:country_code":"SI",
    "gn:dem":364,
    "gn:feature_class":"P",
    "gn:feature_code":"PPL",
    "gn:name":"Gorica",
    "gn:population":137,
    "gn:timezone":"Europe/Ljubljana",
    "iso:country":"SI",
    "wof:name":"Gorica",
    "wof:placetype":"locality",
    "wof:population":137
},
  "geometry": {"coordinates":[14.72717,46.13782],"type":"Point"}
}