{
  "type": "Feature",
  "properties": {
    "gn:admin1_code":"50",
    "gn:asciiname":"Hrastovlje",
    "gn:country_code":"SI",
    "gn:dem":158,
    "gn:feature_class":"P",
    "gn:feature_code":"PPL",
    "gn:name":"Hrastovlje",
    "gn:population":154,
    "gn:timezone":"Europe/Ljubljana",
    "iso:country":"SI",
    "name:arg_x_preferred":[
        "Hrastovlje"
    ],
    "name:bel_x_preferred":[
        "\u0425\u0440\u0430\u0441\u0442\u043e\u045e\u043b\u0435"
    ],
    "name:bos_x_preferred":[
        "Hrastovlje"
    ],
    "name:bul_x_preferred":[
        "\u0425\u0440\u0430\u0441\u0442\u043e\u0432\u043b\u0435"
    ],
    "name:ceb_x_preferred":[
        "Hrastovlje"
    ],
    "name:ces_x_preferred":[
        "Hrastovlje"
    ],
    "name:deu_x_preferred":[
        "Hrastovlje"
    ],
    "name:fra_x_preferred":[
        "Hrastovlje"
    ],
    "name:ita_x_preferred":[
        "Cristoglie"
    ],
    "name:nld_x_preferred":[
        "Hrastovlje"
    ],
    "name:pol_x_preferred":[
        "Hrastovlje"
    ],
    "name:ron_x_preferred":[
        "Hrastovlje"
    ],
    "name:slv_x_preferred":[
        "Hrastovlje"
    ],
    "name:spa_x_preferred":[
        "Hrastovlje"
    ],
    "name:ukr_x_preferred":[
        "\u0425\u0440\u0430\u0441\u0442\u043e\u0432\u043b\u0454"
    ],
    "name:und_x_variant":[
        "Cristoglle",
        "Hrastovlje"
    ],
    "wof:name":"Hrastovlje",
    "wof:placetype":"locality",
    "wof:population":154
},
  "geometry": {"coordinates":[13.89972,45.51222],"type":"Point"}
}