{
  "type": "Feature",
  "properties": {
    "gn:admin1_code":"50",
    "gn:asciiname":"Hrastovlje",
    "gn:country_code":"SI",
    "gn:dem":158,
    "gn:feature_class":"P",
    "gn:feature_code":"PPL",
    "gn:name":"Hrastovlje",
    "gn:population":154,
    "gn:timezone":"Europe/Ljubljana",
    "iso:country":"SI",
    "name:und_x_variant":[
        "Cristoglle",
        "Hrastovlje"
    ],
    "wof:name":"Hrastovlje",
    "wof:placetype":"locality",
    "wof:population":154
},
  "geometry": {"coordinates":[13.89972,45.51222],"type":"Point"}
}