{
  "type": "Feature",
  "properties": {
    "gn:admin1_code":"C4",
    "gn:asciiname":"Draza Vas",
    "gn:country_code":"SI",
    "gn:dem":284,
    "gn:feature_class":"P",
    "gn:feature_code":"PPL",
    "gn:name":"Dra\u017ea Vas",
    "gn:population":518,
    "gn:timezone":"Europe/Ljubljana",
    "iso:country":"SI",
    "name:bos_x_preferred":[
        "Dra\u017ea vas"
    ],
    "name:ceb_x_preferred":[
        "Dra\u017ea Vas"
    ],
    "name:hrv_x_preferred":[
        "Dra\u017ea vas"
    ],
    "name:nld_x_preferred":[
        "Dra\u017ea vas"
    ],
    "name:pol_x_preferred":[
        "Dra\u017ea vas"
    ],
    "name:ron_x_preferred":[
        "Dra\u017ea vas"
    ],
    "name:slv_x_preferred":[
        "Dra\u017ea vas"
    ],
    "name:ukr_x_preferred":[
        "\u0414\u0440\u0430\u0436\u0430 \u0412\u0430\u0441"
    ],
    "name:und_x_variant":[
        "Dra\u017ea Vas"
    ],
    "wof:name":"Draza Vas",
    "wof:placetype":"locality",
    "wof:population":518
},
  "geometry": {"coordinates":[15.48333,46.33333],"type":"Point"}
}