{
  "type": "Feature",
  "properties": {
    "gn:admin1_code":"54",
    "gn:asciiname":"Pristava ob Krki",
    "gn:country_code":"SI",
    "gn:dem":150,
    "gn:feature_class":"P",
    "gn:feature_code":"PPL",
    "gn:name":"Pristava ob Krki",
    "gn:population":38,
    "gn:timezone":"Europe/Ljubljana",
    "iso:country":"SI",
    "wof:name":"Pristava ob Krki",
    "wof:placetype":"locality",
    "wof:population":38
},
  "geometry": {"coordinates":[15.497,45.86797],"type":"Point"}
}