{
  "type": "Feature",
  "properties": {
    "gn:admin1_code":"54",
    "gn:asciiname":"Pristava ob Krki",
    "gn:country_code":"SI",
    "gn:dem":150,
    "gn:feature_class":"P",
    "gn:feature_code":"PPL",
    "gn:name":"Pristava ob Krki",
    "gn:population":38,
    "gn:timezone":"Europe/Ljubljana",
    "iso:country":"SI",
    "name:bos_x_preferred":[
        "Pristava ob Krki"
    ],
    "name:hrv_x_preferred":[
        "Pristava ob Krki"
    ],
    "name:nld_x_preferred":[
        "Pristava ob Krki"
    ],
    "name:pol_x_preferred":[
        "Pristava ob Krki"
    ],
    "name:ron_x_preferred":[
        "Pristava ob Krki"
    ],
    "name:slv_x_preferred":[
        "Pristava ob Krki"
    ],
    "name:ukr_x_preferred":[
        "\u041f\u0440\u0438\u0441\u0442\u0430\u0432\u0430-\u043e\u0431-\u041a\u0440\u043a\u0456"
    ],
    "wof:name":"Pristava ob Krki",
    "wof:placetype":"locality",
    "wof:population":38
},
  "geometry": {"coordinates":[15.497,45.86797],"type":"Point"}
}