{
  "type": "Feature",
  "properties": {
    "gn:admin1_code":"J1",
    "gn:asciiname":"Sitez",
    "gn:country_code":"SI",
    "gn:dem":292,
    "gn:feature_class":"P",
    "gn:feature_code":"PPL",
    "gn:name":"Site\u017e",
    "gn:population":41,
    "gn:timezone":"Europe/Ljubljana",
    "iso:country":"SI",
    "name:bos_x_preferred":[
        "Site\u017e"
    ],
    "name:nld_x_preferred":[
        "Site\u017e"
    ],
    "name:pol_x_preferred":[
        "Site\u017e"
    ],
    "name:ron_x_preferred":[
        "Site\u017e"
    ],
    "name:slv_x_preferred":[
        "Site\u017e"
    ],
    "name:und_x_variant":[
        "Site\u017e"
    ],
    "wof:name":"Sitez",
    "wof:placetype":"locality",
    "wof:population":41
},
  "geometry": {"coordinates":[15.76896,46.30344],"type":"Point"}
}