{
  "type": "Feature",
  "properties": {
    "iso:country":"SI",
    "name:bos_x_preferred":[
        "Cirkulane"
    ],
    "name:ceb_x_preferred":[
        "Cirkulane"
    ],
    "name:ces_x_preferred":[
        "Cirkulane"
    ],
    "name:ces_x_variant":[
        "Ob\u010dina Cirkulane"
    ],
    "name:che_x_preferred":[
        "\u0426\u0438\u0440\u043a\u0443\u043b\u0430\u043d\u0435"
    ],
    "name:deu_x_preferred":[
        "Cirkulane"
    ],
    "name:eng_x_preferred":[
        "Cirkulane"
    ],
    "name:fra_x_preferred":[
        "Cirkulane"
    ],
    "name:hrv_x_preferred":[
        "Op\u0107ina Cirkulane"
    ],
    "name:hrv_x_variant":[
        "Cirkulane"
    ],
    "name:hun_x_preferred":[
        "Cirkulane"
    ],
    "name:ita_x_preferred":[
        "Cirkulane"
    ],
    "name:jpn_x_preferred":[
        "\u30c4\u30a3\u30eb\u30af\u30e9\u30cd"
    ],
    "name:kor_x_preferred":[
        "\uce58\ub974\ucfe8\ub77c\ub124"
    ],
    "name:nld_x_preferred":[
        "Cirkulane"
    ],
    "name:pol_x_preferred":[
        "Gmina Cirkulane"
    ],
    "name:pol_x_variant":[
        "Cirkulane"
    ],
    "name:por_x_preferred":[
        "Cirkulane"
    ],
    "name:ron_x_preferred":[
        "Cirkulane"
    ],
    "name:slv_x_preferred":[
        "Cirkulane"
    ],
    "name:slv_x_variant":[
        "Ob\u010dina Cirkulane"
    ],
    "name:srp_x_preferred":[
        "\u0426\u0438\u0440\u043a\u0443\u043b\u0430\u043d\u0435"
    ],
    "name:tat_x_preferred":[
        "\u0426\u0438\u0440\u043a\u0443\u043b\u0430\u043d\u0435"
    ],
    "name:tha_x_preferred":[
        "\u0e0b\u0e35\u0e23\u0e4c\u0e01\u0e39\u0e25\u0e32\u0e41\u0e19"
    ],
    "name:ukr_x_preferred":[
        "\u0426\u0438\u0440\u043a\u0443\u043b\u0430\u043d\u0435"
    ],
    "name:urd_x_preferred":[
        "\u062a\u0633\u06cc\u0631\u06a9\u0648\u0644\u0627\u0646\u06d2"
    ],
    "name:vec_x_preferred":[
        "Cirkulane"
    ],
    "name:vie_x_preferred":[
        "Cirkulane"
    ],
    "name:zho_x_preferred":[
        "\u9f4a\u723e\u5eab\u62c9\u5167"
    ],
    "qs:a0":"Slovenija",
    "qs:a1":"*",
    "qs:a1r":"0",
    "qs:adm0":"Slovenija",
    "qs:la_lc":"*",
    "qs:level":"locality",
    "qs:loc":"Cirkulane",
    "qs:loc_alt":"Cirkulane",
    "qs:pop":0,
    "qs:type":"buffered point",
    "wd:wordcount":140,
    "wof:name":"Cirkulane",
    "wof:placetype":"locality"
},
  "geometry": {"coordinates":[15.994944,46.344247],"type":"Point"}
}