{
  "type": "Feature",
  "properties": {
    "iso:country":"SI",
    "name:bos_x_preferred":[
        "Cirkulane"
    ],
    "name:ces_x_preferred":[
        "Cirkulane"
    ],
    "name:cze_x_preferred":[
        "Ob\u010dina Cirkulane"
    ],
    "name:deu_x_preferred":[
        "Cirkulane"
    ],
    "name:dut_x_preferred":[
        "Cirkulane"
    ],
    "name:eng_x_preferred":[
        "Cirkulane"
    ],
    "name:fra_x_preferred":[
        "Cirkulane"
    ],
    "name:fre_x_preferred":[
        "Cirkulane"
    ],
    "name:ger_x_preferred":[
        "Cirkulane"
    ],
    "name:hrv_x_preferred":[
        "Op\u0107ina Cirkulane"
    ],
    "name:hun_x_preferred":[
        "Cirkulane"
    ],
    "name:ita_x_preferred":[
        "Cirkulane"
    ],
    "name:jpn_x_preferred":[
        "\u30c4\u30a3\u30eb\u30af\u30e9\u30cd"
    ],
    "name:kor_x_preferred":[
        "\uce58\ub974\ucfe8\ub77c\ub124"
    ],
    "name:pol_x_preferred":[
        "Gmina Cirkulane"
    ],
    "name:por_x_preferred":[
        "Cirkulane"
    ],
    "name:ron_x_preferred":[
        "Cirkulane"
    ],
    "name:rum_x_preferred":[
        "Cirkulane"
    ],
    "name:slv_x_preferred":[
        "Cirkulane"
    ],
    "name:ukr_x_preferred":[
        "\u0426\u0438\u0440\u043a\u0443\u043b\u0430\u043d\u0435"
    ],
    "name:urd_x_preferred":[
        "\u062a\u0633\u06cc\u0631\u06a9\u0648\u0644\u0627\u0646\u06d2"
    ],
    "name:vie_x_preferred":[
        "Cirkulane"
    ],
    "qs:a0":"Slovenija",
    "qs:a1":"*",
    "qs:a1r":"0",
    "qs:adm0":"Slovenija",
    "qs:la_lc":"*",
    "qs:level":"locality",
    "qs:loc":"Cirkulane",
    "qs:loc_alt":"Cirkulane",
    "qs:pop":0,
    "qs:type":"buffered point",
    "wd:wordcount":140,
    "wof:name":"Cirkulane",
    "wof:placetype":"locality"
},
  "geometry": {"coordinates":[15.994944,46.344247],"type":"Point"}
}