{
  "type": "Feature",
  "properties": {
    "gn:admin1_code":"F7",
    "gn:asciiname":"Male Braslovce",
    "gn:country_code":"SI",
    "gn:dem":298,
    "gn:feature_class":"P",
    "gn:feature_code":"PPL",
    "gn:name":"Male Braslov\u010de",
    "gn:population":235,
    "gn:timezone":"Europe/Ljubljana",
    "iso:country":"SI",
    "name:ceb_x_preferred":[
        "Male Braslov\u010de"
    ],
    "name:hrv_x_preferred":[
        "Male Braslov\u010de"
    ],
    "name:nld_x_preferred":[
        "Male Braslov\u010de"
    ],
    "name:pol_x_preferred":[
        "Male Braslov\u010de"
    ],
    "name:ron_x_preferred":[
        "Male Braslov\u010de"
    ],
    "name:slv_x_preferred":[
        "Male Braslov\u010de"
    ],
    "name:ukr_x_preferred":[
        "\u041c\u0430\u043b\u0435 \u0411\u0440\u0430\u0441\u043b\u043e\u0432\u0447\u0435"
    ],
    "wof:name":"Male Braslovce",
    "wof:placetype":"locality",
    "wof:population":235
},
  "geometry": {"coordinates":[15.04404,46.30141],"type":"Point"}
}