{
  "type": "Feature",
  "properties": {
    "gn:admin1_code":"F7",
    "gn:asciiname":"Male Braslovce",
    "gn:country_code":"SI",
    "gn:dem":298,
    "gn:feature_class":"P",
    "gn:feature_code":"PPL",
    "gn:name":"Male Braslov\u010de",
    "gn:population":235,
    "gn:timezone":"Europe/Ljubljana",
    "iso:country":"SI",
    "name:und_x_variant":[
        "Male Braslov\u010de"
    ],
    "wof:name":"Male Braslovce",
    "wof:placetype":"locality",
    "wof:population":235
},
  "geometry": {"coordinates":[15.04404,46.30141],"type":"Point"}
}