{
  "type": "Feature",
  "properties": {
    "gn:admin1_code":"31",
    "gn:asciiname":"Panovci",
    "gn:country_code":"SI",
    "gn:dem":330,
    "gn:feature_class":"P",
    "gn:feature_code":"PPL",
    "gn:name":"Panovci",
    "gn:population":40,
    "gn:timezone":"Europe/Ljubljana",
    "iso:country":"SI",
    "name:bos_x_preferred":[
        "Panovci"
    ],
    "name:epo_x_preferred":[
        "Panovci"
    ],
    "name:hrv_x_preferred":[
        "Panovci"
    ],
    "name:hun_x_preferred":[
        "\u00darisz\u00e9k"
    ],
    "name:nld_x_preferred":[
        "Panovci"
    ],
    "name:pol_x_preferred":[
        "Panovci"
    ],
    "name:ron_x_preferred":[
        "Panovci"
    ],
    "name:slv_x_preferred":[
        "Panovci"
    ],
    "name:ukr_x_preferred":[
        "\u041f\u0430\u043d\u043e\u0432\u0446\u0456"
    ],
    "wof:name":"Panovci",
    "wof:placetype":"locality",
    "wof:population":40
},
  "geometry": {"coordinates":[16.24056,46.76306],"type":"Point"}
}