{
  "type": "Feature",
  "properties": {
    "gn:admin1_code":"31",
    "gn:asciiname":"Panovci",
    "gn:country_code":"SI",
    "gn:dem":330,
    "gn:feature_class":"P",
    "gn:feature_code":"PPL",
    "gn:name":"Panovci",
    "gn:population":40,
    "gn:timezone":"Europe/Ljubljana",
    "iso:country":"SI",
    "name:und_x_variant":[
        "\u00darisz\u00e9k",
        "Panovci"
    ],
    "wof:name":"Panovci",
    "wof:placetype":"locality",
    "wof:population":40
},
  "geometry": {"coordinates":[16.24056,46.76306],"type":"Point"}
}