{
  "type": "Feature",
  "properties": {
    "gn:admin1_code":"68",
    "gn:asciiname":"Brdo pri Lukovici",
    "gn:country_code":"SI",
    "gn:dem":388,
    "gn:feature_class":"P",
    "gn:feature_code":"PPL",
    "gn:name":"Brdo pri Lukovici",
    "gn:population":9,
    "gn:timezone":"Europe/Ljubljana",
    "iso:country":"SI",
    "name:bos_x_preferred":[
        "Brdo pri Lukovici"
    ],
    "name:nld_x_preferred":[
        "Brdo pri Lukovici"
    ],
    "name:pol_x_preferred":[
        "Brdo pri Lukovici"
    ],
    "name:ron_x_preferred":[
        "Brdo pri Lukovici"
    ],
    "name:slv_x_preferred":[
        "Brdo pri Lukovici"
    ],
    "name:ukr_x_preferred":[
        "\u0411\u0440\u0434\u043e-\u043f\u0440\u0438-\u041b\u0443\u043a\u043e\u0432\u0438\u0446\u0456"
    ],
    "wof:name":"Brdo pri Lukovici",
    "wof:placetype":"locality",
    "wof:population":9
},
  "geometry": {"coordinates":[14.68302,46.17306],"type":"Point"}
}