{
  "type": "Feature",
  "properties": {
    "gn:admin1_code":"68",
    "gn:asciiname":"Brdo pri Lukovici",
    "gn:country_code":"SI",
    "gn:dem":388,
    "gn:feature_class":"P",
    "gn:feature_code":"PPL",
    "gn:name":"Brdo pri Lukovici",
    "gn:population":9,
    "gn:timezone":"Europe/Ljubljana",
    "iso:country":"SI",
    "wof:name":"Brdo pri Lukovici",
    "wof:placetype":"locality",
    "wof:population":9
},
  "geometry": {"coordinates":[14.68302,46.17306],"type":"Point"}
}