{
  "type": "Feature",
  "properties": {
    "gn:admin1_code":"I2",
    "gn:asciiname":"Dolic",
    "gn:country_code":"SI",
    "gn:dem":276,
    "gn:feature_class":"P",
    "gn:feature_code":"PPL",
    "gn:name":"Doli\u010d",
    "gn:population":392,
    "gn:timezone":"Europe/Ljubljana",
    "iso:country":"SI",
    "name:bos_x_preferred":[
        "Doli\u010d"
    ],
    "name:ceb_x_preferred":[
        "Doli\u010d"
    ],
    "name:deu_x_preferred":[
        "Doli\u010d"
    ],
    "name:epo_x_preferred":[
        "Doli\u010d"
    ],
    "name:hrv_x_preferred":[
        "Doli\u010d"
    ],
    "name:hun_x_preferred":[
        "V\u00f6lgyk\u00f6z"
    ],
    "name:nld_x_preferred":[
        "Doli\u010d"
    ],
    "name:pol_x_preferred":[
        "Doli\u010d"
    ],
    "name:ron_x_preferred":[
        "Doli\u010d"
    ],
    "name:slv_x_preferred":[
        "Doli\u010d"
    ],
    "name:ukr_x_preferred":[
        "\u0414\u043e\u043b\u0438\u0447"
    ],
    "wof:name":"Dolic",
    "wof:placetype":"locality",
    "wof:population":392
},
  "geometry": {"coordinates":[16.10722,46.83655],"type":"Point"}
}