{
  "type": "Feature",
  "properties": {
    "gn:admin1_code":"I2",
    "gn:asciiname":"Dolic",
    "gn:country_code":"SI",
    "gn:dem":276,
    "gn:feature_class":"P",
    "gn:feature_code":"PPL",
    "gn:name":"Doli\u010d",
    "gn:population":392,
    "gn:timezone":"Europe/Ljubljana",
    "iso:country":"SI",
    "name:und_x_variant":[
        "Doli\u010d"
    ],
    "wof:name":"Dolic",
    "wof:placetype":"locality",
    "wof:population":392
},
  "geometry": {"coordinates":[16.10722,46.83655],"type":"Point"}
}