{
  "type": "Feature",
  "properties": {
    "gn:admin1_code":"64",
    "gn:asciiname":"Grcarevec",
    "gn:country_code":"SI",
    "gn:dem":493,
    "gn:feature_class":"P",
    "gn:feature_code":"PPL",
    "gn:name":"Gr\u010darevec",
    "gn:population":206,
    "gn:timezone":"Europe/Ljubljana",
    "iso:country":"SI",
    "name:und_x_variant":[
        "Gr\u010darevec"
    ],
    "wof:name":"Grcarevec",
    "wof:placetype":"locality",
    "wof:population":206
},
  "geometry": {"coordinates":[14.21333,45.87528],"type":"Point"}
}