{
  "type": "Feature",
  "properties": {
    "gn:admin1_code":"B3",
    "gn:asciiname":"Trate",
    "gn:country_code":"SI",
    "gn:dem":374,
    "gn:feature_class":"P",
    "gn:feature_code":"PPLL",
    "gn:name":"Trate",
    "gn:population":287,
    "gn:timezone":"Europe/Ljubljana",
    "iso:country":"SI",
    "wof:name":"Trate",
    "wof:placetype":"locality",
    "wof:population":287
},
  "geometry": {"coordinates":[15.78639,46.69306],"type":"Point"}
}