{
  "type": "Feature",
  "properties": {
    "gn:admin1_code":"F6",
    "gn:asciiname":"Lahovo",
    "gn:country_code":"SI",
    "gn:dem":739,
    "gn:feature_class":"P",
    "gn:feature_code":"PPL",
    "gn:name":"Lahovo",
    "gn:population":7,
    "gn:timezone":"Europe/Ljubljana",
    "iso:country":"SI",
    "wof:name":"Lahovo",
    "wof:placetype":"locality",
    "wof:population":7
},
  "geometry": {"coordinates":[14.51544,45.79775],"type":"Point"}
}