{
  "type": "Feature",
  "properties": {
    "gn:admin1_code":"08",
    "gn:asciiname":"Zgornji Obrez",
    "gn:country_code":"SI",
    "gn:dem":159,
    "gn:feature_class":"P",
    "gn:feature_code":"PPL",
    "gn:name":"Zgornji Obre\u017e",
    "gn:population":175,
    "gn:timezone":"Europe/Ljubljana",
    "iso:country":"SI",
    "name:bos_x_preferred":[
        "Zgornji Obre\u017e"
    ],
    "name:ceb_x_preferred":[
        "Zgornji Obre\u017e"
    ],
    "name:hrv_x_preferred":[
        "Zgornji Obre\u017e"
    ],
    "name:nld_x_preferred":[
        "Zgornji Obre\u017e"
    ],
    "name:pol_x_preferred":[
        "Zgornji Obre\u017e"
    ],
    "name:ron_x_preferred":[
        "Zgornji Obre\u017e"
    ],
    "name:slv_x_preferred":[
        "Zgornji Obre\u017e"
    ],
    "name:ukr_x_preferred":[
        "\u0417\u0433\u043e\u0440\u043d\u0456\u0439 \u041e\u0431\u0440\u0435\u0436"
    ],
    "wof:name":"Zgornji Obrez",
    "wof:placetype":"locality",
    "wof:population":175
},
  "geometry": {"coordinates":[15.56429,45.93898],"type":"Point"}
}