{
  "type": "Feature",
  "properties": {
    "gn:admin1_code":"08",
    "gn:asciiname":"Zgornji Obrez",
    "gn:country_code":"SI",
    "gn:dem":159,
    "gn:feature_class":"P",
    "gn:feature_code":"PPL",
    "gn:name":"Zgornji Obre\u017e",
    "gn:population":175,
    "gn:timezone":"Europe/Ljubljana",
    "iso:country":"SI",
    "name:und_x_variant":[
        "Zgornji Obre\u017e"
    ],
    "wof:name":"Zgornji Obrez",
    "wof:placetype":"locality",
    "wof:population":175
},
  "geometry": {"coordinates":[15.56429,45.93898],"type":"Point"}
}