{
  "type": "Feature",
  "properties": {
    "gn:admin1_code":"91",
    "gn:asciiname":"Petelinje",
    "gn:country_code":"SI",
    "gn:dem":546,
    "gn:feature_class":"P",
    "gn:feature_code":"PPL",
    "gn:name":"Petelinje",
    "gn:population":292,
    "gn:timezone":"Europe/Ljubljana",
    "iso:country":"SI",
    "name:bos_x_preferred":[
        "Petelinje"
    ],
    "name:ceb_x_preferred":[
        "Petelinje"
    ],
    "name:hrv_x_preferred":[
        "Petelinje"
    ],
    "name:nld_x_preferred":[
        "Petelinje"
    ],
    "name:pol_x_preferred":[
        "Petelinje"
    ],
    "name:ron_x_preferred":[
        "Petelinje"
    ],
    "name:slv_x_historical":[
        "Peteline"
    ],
    "name:slv_x_preferred":[
        "Peteline"
    ],
    "name:slv_x_variant":[
        "Petelinje"
    ],
    "name:ukr_x_preferred":[
        "\u041f\u0435\u0442\u0435\u043b\u0438\u043d\u0454"
    ],
    "name:und_x_variant":[
        "Petteline"
    ],
    "wof:name":"Petelinje",
    "wof:placetype":"locality",
    "wof:population":292
},
  "geometry": {"coordinates":[14.19605,45.68981],"type":"Point"}
}