{
  "type": "Feature",
  "properties": {
    "gn:admin1_code":"91",
    "gn:asciiname":"Petelinje",
    "gn:country_code":"SI",
    "gn:dem":546,
    "gn:feature_class":"P",
    "gn:feature_code":"PPL",
    "gn:name":"Petelinje",
    "gn:population":292,
    "gn:timezone":"Europe/Ljubljana",
    "iso:country":"SI",
    "name:slv_x_historical":[
        "Peteline"
    ],
    "name:slv_x_preferred":[
        "Peteline"
    ],
    "name:und_x_variant":[
        "Petteline",
        "Petelinje"
    ],
    "wof:name":"Petelinje",
    "wof:placetype":"locality",
    "wof:population":292
},
  "geometry": {"coordinates":[14.19605,45.68981],"type":"Point"}
}