{
  "type": "Feature",
  "properties": {
    "gn:admin1_code":"F6",
    "gn:asciiname":"Storovo",
    "gn:country_code":"SI",
    "gn:dem":801,
    "gn:feature_class":"P",
    "gn:feature_code":"PPL",
    "gn:name":"\u0160torovo",
    "gn:population":5,
    "gn:timezone":"Europe/Ljubljana",
    "iso:country":"SI",
    "name:bos_x_preferred":[
        "\u0160torovo"
    ],
    "name:hrv_x_preferred":[
        "\u0160torovo"
    ],
    "name:nld_x_preferred":[
        "\u0160torovo"
    ],
    "name:pol_x_preferred":[
        "\u0160torovo"
    ],
    "name:ron_x_preferred":[
        "\u0160torovo"
    ],
    "name:slv_x_preferred":[
        "\u0160torovo"
    ],
    "name:ukr_x_preferred":[
        "\u0428\u0442\u043e\u0440\u043e\u0432\u043e"
    ],
    "wof:name":"Storovo",
    "wof:placetype":"locality",
    "wof:population":5
},
  "geometry": {"coordinates":[14.50978,45.81617],"type":"Point"}
}