{
  "type": "Feature",
  "properties": {
    "gn:admin1_code":"F6",
    "gn:asciiname":"Storovo",
    "gn:country_code":"SI",
    "gn:dem":801,
    "gn:feature_class":"P",
    "gn:feature_code":"PPL",
    "gn:name":"\u0160torovo",
    "gn:population":5,
    "gn:timezone":"Europe/Ljubljana",
    "iso:country":"SI",
    "name:und_x_variant":[
        "\u0160torovo"
    ],
    "wof:name":"Storovo",
    "wof:placetype":"locality",
    "wof:population":5
},
  "geometry": {"coordinates":[14.50978,45.81617],"type":"Point"}
}