{
  "type": "Feature",
  "properties": {
    "gn:admin1_code":"20",
    "gn:asciiname":"Predstruge",
    "gn:country_code":"SI",
    "gn:dem":534,
    "gn:feature_class":"P",
    "gn:feature_code":"PPL",
    "gn:name":"Predstruge",
    "gn:population":264,
    "gn:timezone":"Europe/Ljubljana",
    "iso:country":"SI",
    "wof:name":"Predstruge",
    "wof:placetype":"locality",
    "wof:population":264
},
  "geometry": {"coordinates":[14.67341,45.86523],"type":"Point"}
}