{
  "type": "Feature",
  "properties": {
    "gn:admin1_code":"20",
    "gn:asciiname":"Predstruge",
    "gn:country_code":"SI",
    "gn:dem":534,
    "gn:feature_class":"P",
    "gn:feature_code":"PPL",
    "gn:name":"Predstruge",
    "gn:population":264,
    "gn:timezone":"Europe/Ljubljana",
    "iso:country":"SI",
    "name:bos_x_preferred":[
        "Predstruge"
    ],
    "name:bul_x_preferred":[
        "\u041f\u0440\u0435\u0434\u0441\u0442\u0440\u0443\u0433\u0435"
    ],
    "name:ceb_x_preferred":[
        "Predstruge"
    ],
    "name:nld_x_preferred":[
        "Predstruge"
    ],
    "name:pol_x_preferred":[
        "Predstruge"
    ],
    "name:ron_x_preferred":[
        "Predstruge"
    ],
    "name:slv_x_preferred":[
        "Predstruge"
    ],
    "name:ukr_x_preferred":[
        "\u041f\u0440\u0435\u0434\u0441\u0442\u0440\u0443\u0433\u0435"
    ],
    "wof:name":"Predstruge",
    "wof:placetype":"locality",
    "wof:population":264
},
  "geometry": {"coordinates":[14.67341,45.86523],"type":"Point"}
}