{
  "type": "Feature",
  "properties": {
    "gn:admin1_code":"44",
    "gn:asciiname":"Marchici",
    "gn:country_code":"SI",
    "gn:dem":434,
    "gn:feature_class":"P",
    "gn:feature_code":"PPL",
    "gn:name":"Marchici",
    "gn:population":0,
    "gn:timezone":"Europe/Ljubljana",
    "iso:country":"SI",
    "wof:name":"Marchici",
    "wof:placetype":"locality"
},
  "geometry": {"coordinates":[13.58722,46.08611],"type":"Point"}
}