{
  "type": "Feature",
  "properties": {
    "gn:admin1_code":"94",
    "gn:asciiname":"Brezje pod Nanosom",
    "gn:country_code":"SI",
    "gn:dem":563,
    "gn:feature_class":"P",
    "gn:feature_code":"PPL",
    "gn:name":"Brezje pod Nanosom",
    "gn:population":43,
    "gn:timezone":"Europe/Ljubljana",
    "iso:country":"SI",
    "name:bos_x_preferred":[
        "Brezje pod Nanosom"
    ],
    "name:hrv_x_preferred":[
        "Brezje pod Nanosom"
    ],
    "name:ita_x_preferred":[
        "Bresie"
    ],
    "name:nld_x_preferred":[
        "Brezje pod Nanosom"
    ],
    "name:pol_x_preferred":[
        "Brezje pod Nanosom"
    ],
    "name:ron_x_preferred":[
        "Brezje pod Nanosom"
    ],
    "name:slv_x_historical":[
        "Brezje"
    ],
    "name:slv_x_preferred":[
        "Brezje"
    ],
    "name:slv_x_variant":[
        "Brezje pod Nanosom"
    ],
    "name:ukr_x_preferred":[
        "\u0411\u0440\u0435\u0437\u0454-\u043f\u043e\u0434-\u041d\u0430\u043d\u043e\u0441\u043e\u043c"
    ],
    "name:und_x_variant":[
        "Brezje Pod Nanosom"
    ],
    "wof:name":"Brezje pod Nanosom",
    "wof:placetype":"locality",
    "wof:population":43
},
  "geometry": {"coordinates":[14.08894,45.77524],"type":"Point"}
}