{
  "type": "Feature",
  "properties": {
    "gn:admin1_code":"94",
    "gn:asciiname":"Brezje pod Nanosom",
    "gn:country_code":"SI",
    "gn:dem":563,
    "gn:feature_class":"P",
    "gn:feature_code":"PPL",
    "gn:name":"Brezje pod Nanosom",
    "gn:population":43,
    "gn:timezone":"Europe/Ljubljana",
    "iso:country":"SI",
    "name:slv_x_historical":[
        "Brezje"
    ],
    "name:slv_x_preferred":[
        "Brezje"
    ],
    "name:und_x_variant":[
        "Brezje Pod Nanosom"
    ],
    "wof:name":"Brezje pod Nanosom",
    "wof:placetype":"locality",
    "wof:population":43
},
  "geometry": {"coordinates":[14.08894,45.77524],"type":"Point"}
}