{
  "type": "Feature",
  "properties": {
    "gn:admin1_code":"O3",
    "gn:asciiname":"Koprivnik",
    "gn:country_code":"SI",
    "gn:dem":163,
    "gn:feature_class":"P",
    "gn:feature_code":"PPL",
    "gn:name":"Koprivnik",
    "gn:population":12,
    "gn:timezone":"Europe/Ljubljana",
    "iso:country":"SI",
    "name:bos_x_preferred":[
        "Koprivnik"
    ],
    "name:ita_x_preferred":[
        "Koprivnik"
    ],
    "name:nld_x_preferred":[
        "Koprivnik"
    ],
    "name:pol_x_preferred":[
        "Koprivnik"
    ],
    "name:ron_x_preferred":[
        "Koprivnik"
    ],
    "name:slv_x_preferred":[
        "Koprivnik"
    ],
    "name:ukr_x_preferred":[
        "\u041a\u043e\u043f\u0440\u0438\u0432\u043d\u0438\u043a"
    ],
    "wof:name":"Koprivnik",
    "wof:placetype":"locality",
    "wof:population":12
},
  "geometry": {"coordinates":[15.39963,45.87915],"type":"Point"}
}