{
  "type": "Feature",
  "properties": {
    "gn:admin1_code":"89",
    "gn:asciiname":"Dolnja Pocehova",
    "gn:country_code":"SI",
    "gn:dem":255,
    "gn:feature_class":"P",
    "gn:feature_code":"PPL",
    "gn:name":"Dolnja Po\u010dehova",
    "gn:population":338,
    "gn:timezone":"Europe/Ljubljana",
    "iso:country":"SI",
    "name:bos_x_preferred":[
        "Dolnja Po\u010dehova"
    ],
    "name:ceb_x_preferred":[
        "Dolnja Po\u010dehova"
    ],
    "name:nld_x_preferred":[
        "Dolnja Po\u010dehova"
    ],
    "name:pol_x_preferred":[
        "Dolnja Po\u010dehova"
    ],
    "name:ron_x_preferred":[
        "Dolnja Po\u010dehova"
    ],
    "name:slv_x_preferred":[
        "Dolnja Po\u010dehova"
    ],
    "name:ukr_x_preferred":[
        "\u0414\u043e\u043b\u043d\u044f \u041f\u043e\u0447\u0435\u0445\u043e\u0432\u0430"
    ],
    "wof:name":"Dolnja Pocehova",
    "wof:placetype":"locality",
    "wof:population":338
},
  "geometry": {"coordinates":[15.66431,46.59755],"type":"Point"}
}