{
  "type": "Feature",
  "properties": {
    "gn:admin1_code":"89",
    "gn:asciiname":"Dolnja Pocehova",
    "gn:country_code":"SI",
    "gn:dem":255,
    "gn:feature_class":"P",
    "gn:feature_code":"PPL",
    "gn:name":"Dolnja Po\u010dehova",
    "gn:population":338,
    "gn:timezone":"Europe/Ljubljana",
    "iso:country":"SI",
    "name:und_x_variant":[
        "Dolnja Po\u010dehova"
    ],
    "wof:name":"Dolnja Pocehova",
    "wof:placetype":"locality",
    "wof:population":338
},
  "geometry": {"coordinates":[15.66431,46.59755],"type":"Point"}
}