{
  "type": "Feature",
  "properties": {
    "gn:admin1_code":"I1",
    "gn:asciiname":"Boreci",
    "gn:country_code":"SI",
    "gn:dem":182,
    "gn:feature_class":"P",
    "gn:feature_code":"PPL",
    "gn:name":"Boreci",
    "gn:population":289,
    "gn:timezone":"Europe/Ljubljana",
    "iso:country":"SI",
    "name:bos_x_preferred":[
        "Boreci"
    ],
    "name:ceb_x_preferred":[
        "Boreci"
    ],
    "name:hrv_x_preferred":[
        "Boreci"
    ],
    "name:nld_x_preferred":[
        "Boreci"
    ],
    "name:pol_x_preferred":[
        "Boreci"
    ],
    "name:ron_x_preferred":[
        "Boreci"
    ],
    "name:slv_x_preferred":[
        "Boreci"
    ],
    "name:ukr_x_preferred":[
        "\u0411\u043e\u0440\u0435\u0446\u0456"
    ],
    "wof:name":"Boreci",
    "wof:placetype":"locality",
    "wof:population":289
},
  "geometry": {"coordinates":[16.14139,46.55917],"type":"Point"}
}