{
  "type": "Feature",
  "properties": {
    "gn:admin1_code":"25",
    "gn:asciiname":"Selovec",
    "gn:country_code":"SI",
    "gn:dem":718,
    "gn:feature_class":"P",
    "gn:feature_code":"PPL",
    "gn:name":"Selovec",
    "gn:population":471,
    "gn:timezone":"Europe/Ljubljana",
    "iso:country":"SI",
    "wof:name":"Selovec",
    "wof:placetype":"locality",
    "wof:population":471
},
  "geometry": {"coordinates":[15.02648,46.55071],"type":"Point"}
}