{
  "type": "Feature",
  "properties": {
    "gn:admin1_code":"25",
    "gn:asciiname":"Selovec",
    "gn:country_code":"SI",
    "gn:dem":718,
    "gn:feature_class":"P",
    "gn:feature_code":"PPL",
    "gn:name":"Selovec",
    "gn:population":471,
    "gn:timezone":"Europe/Ljubljana",
    "iso:country":"SI",
    "name:bos_x_preferred":[
        "Selovec"
    ],
    "name:bul_x_preferred":[
        "\u0421\u0435\u043b\u043e\u0432\u0435\u0446"
    ],
    "name:ceb_x_preferred":[
        "Selovec"
    ],
    "name:nld_x_preferred":[
        "Selovec"
    ],
    "name:pol_x_preferred":[
        "Selovec"
    ],
    "name:ron_x_preferred":[
        "Selovec"
    ],
    "name:slv_x_preferred":[
        "Selovec"
    ],
    "name:ukr_x_preferred":[
        "\u0421\u0435\u043b\u043e\u0432\u0435\u0446\u044c"
    ],
    "wof:name":"Selovec",
    "wof:placetype":"locality",
    "wof:population":471
},
  "geometry": {"coordinates":[15.02648,46.55071],"type":"Point"}
}