{
  "type": "Feature",
  "properties": {
    "gn:admin1_code":"D8",
    "gn:asciiname":"Hlebce",
    "gn:country_code":"SI",
    "gn:dem":514,
    "gn:feature_class":"P",
    "gn:feature_code":"PPL",
    "gn:name":"Hleb\u010de",
    "gn:population":38,
    "gn:timezone":"Europe/Ljubljana",
    "iso:country":"SI",
    "name:bos_x_preferred":[
        "Hleb\u010de"
    ],
    "name:nld_x_preferred":[
        "Hleb\u010de"
    ],
    "name:pol_x_preferred":[
        "Hleb\u010de"
    ],
    "name:ron_x_preferred":[
        "Hleb\u010de"
    ],
    "name:slv_x_preferred":[
        "Hleb\u010de"
    ],
    "name:ukr_x_preferred":[
        "\u0425\u043b\u0435\u0431\u0447\u0435"
    ],
    "name:und_x_variant":[
        "Hleb\u010de"
    ],
    "wof:name":"Hlebce",
    "wof:placetype":"locality",
    "wof:population":38
},
  "geometry": {"coordinates":[14.60963,45.84448],"type":"Point"}
}