{
  "type": "Feature",
  "properties": {
    "gn:admin1_code":"E1",
    "gn:asciiname":"Rovna",
    "gn:country_code":"SI",
    "gn:dem":102,
    "gn:feature_class":"P",
    "gn:feature_code":"PPLL",
    "gn:name":"Rovna",
    "gn:population":0,
    "gn:timezone":"Europe/Ljubljana",
    "iso:country":"SI",
    "name:ceb_x_preferred":[
        "Rovna"
    ],
    "name:slv_x_preferred":[
        "Rouna"
    ],
    "name:swe_x_preferred":[
        "Rovna"
    ],
    "wof:name":"Rovna",
    "wof:placetype":"locality"
},
  "geometry": {"coordinates":[13.9332,45.84953],"type":"Point"}
}