{
  "type": "Feature",
  "properties": {
    "gn:admin1_code":"L5",
    "gn:asciiname":"Spodnja Selnica",
    "gn:country_code":"SI",
    "gn:dem":289,
    "gn:feature_class":"P",
    "gn:feature_code":"PPL",
    "gn:name":"Spodnja Selnica",
    "gn:population":135,
    "gn:timezone":"Europe/Ljubljana",
    "iso:country":"SI",
    "wof:name":"Spodnja Selnica",
    "wof:placetype":"locality",
    "wof:population":135
},
  "geometry": {"coordinates":[15.51193,46.55215],"type":"Point"}
}