{
  "type": "Feature",
  "properties": {
    "gn:admin1_code":"L5",
    "gn:asciiname":"Spodnja Selnica",
    "gn:country_code":"SI",
    "gn:dem":289,
    "gn:feature_class":"P",
    "gn:feature_code":"PPL",
    "gn:name":"Spodnja Selnica",
    "gn:population":135,
    "gn:timezone":"Europe/Ljubljana",
    "iso:country":"SI",
    "name:bos_x_preferred":[
        "Spodnja Selnica"
    ],
    "name:ceb_x_preferred":[
        "Spodnja Selnica"
    ],
    "name:nld_x_preferred":[
        "Spodnja Selnica"
    ],
    "name:pol_x_preferred":[
        "Spodnja Selnica"
    ],
    "name:ron_x_preferred":[
        "Spodnja Selnica"
    ],
    "name:slv_x_preferred":[
        "Spodnja Selnica"
    ],
    "name:ukr_x_preferred":[
        "\u0421\u043f\u043e\u0434\u043d\u044f \u0421\u0435\u043b\u043d\u0438\u0446\u044f"
    ],
    "wof:name":"Spodnja Selnica",
    "wof:placetype":"locality",
    "wof:population":135
},
  "geometry": {"coordinates":[15.51193,46.55215],"type":"Point"}
}