{
  "type": "Feature",
  "properties": {
    "gn:admin1_code":"F6",
    "gn:asciiname":"Sleme",
    "gn:country_code":"SI",
    "gn:dem":789,
    "gn:feature_class":"P",
    "gn:feature_code":"PPL",
    "gn:name":"Sleme",
    "gn:population":11,
    "gn:timezone":"Europe/Ljubljana",
    "iso:country":"SI",
    "name:bos_x_preferred":[
        "Sleme"
    ],
    "name:hrv_x_preferred":[
        "Sleme"
    ],
    "name:nld_x_preferred":[
        "Sleme"
    ],
    "name:pol_x_preferred":[
        "Sleme"
    ],
    "name:ron_x_preferred":[
        "Sleme"
    ],
    "name:slv_x_preferred":[
        "Sleme"
    ],
    "name:ukr_x_preferred":[
        "\u0421\u043b\u0435\u043c\u0435"
    ],
    "wof:name":"Sleme",
    "wof:placetype":"locality",
    "wof:population":11
},
  "geometry": {"coordinates":[14.45546,45.80132],"type":"Point"}
}