{
  "type": "Feature",
  "properties": {
    "gn:admin1_code":"L7",
    "gn:asciiname":"Trska Gorca",
    "gn:country_code":"SI",
    "gn:dem":357,
    "gn:feature_class":"P",
    "gn:feature_code":"PPL",
    "gn:name":"Tr\u0161ka Gorca",
    "gn:population":42,
    "gn:timezone":"Europe/Ljubljana",
    "iso:country":"SI",
    "name:bos_x_preferred":[
        "Tr\u0161ka Gorca"
    ],
    "name:fas_x_preferred":[
        "\u062a\u0631\u0634\u06a9\u0627 \u06af\u0648\u0631\u06a9\u0627"
    ],
    "name:hrv_x_preferred":[
        "Tr\u0161ka Gorca"
    ],
    "name:nld_x_preferred":[
        "Tr\u0161ka Gorca"
    ],
    "name:pol_x_preferred":[
        "Tr\u0161ka Gorca"
    ],
    "name:ron_x_preferred":[
        "Tr\u0161ka Gorca"
    ],
    "name:slv_x_preferred":[
        "Tr\u0161ka Gorca"
    ],
    "name:ukr_x_preferred":[
        "\u0422\u0440\u0448\u043a\u0430 \u0413\u043e\u0440\u0446\u0430"
    ],
    "wof:name":"Trska Gorca",
    "wof:placetype":"locality",
    "wof:population":42
},
  "geometry": {"coordinates":[15.40865,46.16989],"type":"Point"}
}