{
  "type": "Feature",
  "properties": {
    "gn:admin1_code":"L7",
    "gn:asciiname":"Trska Gorca",
    "gn:country_code":"SI",
    "gn:dem":357,
    "gn:feature_class":"P",
    "gn:feature_code":"PPL",
    "gn:name":"Tr\u0161ka Gorca",
    "gn:population":42,
    "gn:timezone":"Europe/Ljubljana",
    "iso:country":"SI",
    "name:und_x_variant":[
        "Tr\u0161ka Gorca"
    ],
    "wof:name":"Trska Gorca",
    "wof:placetype":"locality",
    "wof:population":42
},
  "geometry": {"coordinates":[15.40865,46.16989],"type":"Point"}
}