{
  "type": "Feature",
  "properties": {
    "gn:admin1_code":"P5",
    "gn:asciiname":"Loke",
    "gn:country_code":"SI",
    "gn:dem":172,
    "gn:feature_class":"P",
    "gn:feature_code":"PPL",
    "gn:name":"Loke",
    "gn:population":54,
    "gn:timezone":"Europe/Ljubljana",
    "iso:country":"SI",
    "name:bos_x_preferred":[
        "Loke"
    ],
    "name:hrv_x_preferred":[
        "Loke"
    ],
    "name:nld_x_preferred":[
        "Loke"
    ],
    "name:pol_x_preferred":[
        "Loke"
    ],
    "name:ron_x_preferred":[
        "Loke"
    ],
    "name:slv_x_preferred":[
        "Loke"
    ],
    "name:ukr_x_preferred":[
        "\u041b\u043e\u043a\u0435"
    ],
    "wof:name":"Loke",
    "wof:placetype":"locality",
    "wof:population":54
},
  "geometry": {"coordinates":[15.11194,45.79026],"type":"Point"}
}