{
  "type": "Feature",
  "properties": {
    "gn:admin1_code":"P5",
    "gn:asciiname":"Loke",
    "gn:country_code":"SI",
    "gn:dem":172,
    "gn:feature_class":"P",
    "gn:feature_code":"PPL",
    "gn:name":"Loke",
    "gn:population":54,
    "gn:timezone":"Europe/Ljubljana",
    "iso:country":"SI",
    "wof:name":"Loke",
    "wof:placetype":"locality",
    "wof:population":54
},
  "geometry": {"coordinates":[15.11194,45.79026],"type":"Point"}
}