{
  "type": "Feature",
  "properties": {
    "gn:admin1_code":"L5",
    "gn:asciiname":"Bistrica pri Rusah",
    "gn:country_code":"SI",
    "gn:dem":288,
    "gn:feature_class":"P",
    "gn:feature_code":"PPL",
    "gn:name":"Bistrica pri Ru\u0161ah",
    "gn:population":0,
    "gn:timezone":"Europe/Ljubljana",
    "iso:country":"SI",
    "name:und_x_variant":[
        "Bistrica",
        "Bistrica pri Ru\u0161ah"
    ],
    "wof:name":"Bistrica pri Rusah",
    "wof:placetype":"locality"
},
  "geometry": {"coordinates":[15.51444,46.55722],"type":"Point"}
}