{
  "type": "Feature",
  "properties": {
    "gn:admin1_code":"84",
    "gn:asciiname":"Sveta Gora",
    "gn:country_code":"SI",
    "gn:dem":574,
    "gn:feature_class":"P",
    "gn:feature_code":"PPL",
    "gn:name":"Sveta Gora",
    "gn:population":18,
    "gn:timezone":"Europe/Ljubljana",
    "iso:country":"SI",
    "wof:name":"Sveta Gora",
    "wof:placetype":"locality",
    "wof:population":18
},
  "geometry": {"coordinates":[13.65842,45.99579],"type":"Point"}
}