{
  "type": "Feature",
  "properties": {
    "gn:admin1_code":"37",
    "gn:asciiname":"Strahomer",
    "gn:country_code":"SI",
    "gn:dem":310,
    "gn:feature_class":"P",
    "gn:feature_code":"PPL",
    "gn:name":"Strahomer",
    "gn:population":156,
    "gn:timezone":"Europe/Ljubljana",
    "iso:country":"SI",
    "wof:name":"Strahomer",
    "wof:placetype":"locality",
    "wof:population":156
},
  "geometry": {"coordinates":[14.48944,45.94417],"type":"Point"}
}