{
  "type": "Feature",
  "properties": {
    "gn:admin1_code":"37",
    "gn:asciiname":"Strahomer",
    "gn:country_code":"SI",
    "gn:dem":310,
    "gn:feature_class":"P",
    "gn:feature_code":"PPL",
    "gn:name":"Strahomer",
    "gn:population":156,
    "gn:timezone":"Europe/Ljubljana",
    "iso:country":"SI",
    "name:bos_x_preferred":[
        "Strahomer"
    ],
    "name:bul_x_preferred":[
        "\u0421\u0442\u0440\u0430\u0445\u043e\u043c\u0435\u0440"
    ],
    "name:ceb_x_preferred":[
        "Strahomer"
    ],
    "name:nld_x_preferred":[
        "Strahomer"
    ],
    "name:pol_x_preferred":[
        "Strahomer"
    ],
    "name:ron_x_preferred":[
        "Strahomer"
    ],
    "name:slv_x_preferred":[
        "Strahomer"
    ],
    "name:ukr_x_preferred":[
        "\u0421\u0442\u0440\u0430\u0445\u043e\u043c\u0435\u0440"
    ],
    "wof:name":"Strahomer",
    "wof:placetype":"locality",
    "wof:population":156
},
  "geometry": {"coordinates":[14.48944,45.94417],"type":"Point"}
}