{
  "type": "Feature",
  "properties": {
    "gn:admin1_code":"05",
    "gn:asciiname":"Zabocevo",
    "gn:country_code":"SI",
    "gn:dem":357,
    "gn:feature_class":"P",
    "gn:feature_code":"PPL",
    "gn:name":"Zabo\u010devo",
    "gn:population":105,
    "gn:timezone":"Europe/Ljubljana",
    "iso:country":"SI",
    "name:und_x_variant":[
        "Sobo\u010devo",
        "Sabo\u010devo",
        "Zabocevo"
    ],
    "wof:name":"Zabocevo",
    "wof:placetype":"locality",
    "wof:population":105
},
  "geometry": {"coordinates":[14.39917,45.9075],"type":"Point"}
}