{
  "type": "Feature",
  "properties": {
    "gn:admin1_code":"05",
    "gn:asciiname":"Zabocevo",
    "gn:country_code":"SI",
    "gn:dem":357,
    "gn:feature_class":"P",
    "gn:feature_code":"PPL",
    "gn:name":"Zabo\u010devo",
    "gn:population":105,
    "gn:timezone":"Europe/Ljubljana",
    "iso:country":"SI",
    "name:bos_x_preferred":[
        "Zabo\u010devo"
    ],
    "name:ceb_x_preferred":[
        "Zabo\u010devo"
    ],
    "name:epo_x_preferred":[
        "Zabo\u010devo"
    ],
    "name:nld_x_preferred":[
        "Zabo\u010devo"
    ],
    "name:pol_x_preferred":[
        "Zabo\u010devo"
    ],
    "name:ron_x_preferred":[
        "Zabo\u010devo"
    ],
    "name:slv_x_preferred":[
        "Zabo\u010devo"
    ],
    "name:ukr_x_preferred":[
        "\u0417\u0430\u0431\u043e\u0447\u0435\u0432\u043e"
    ],
    "name:und_x_variant":[
        "Sobo\u010devo",
        "Sabo\u010devo",
        "Zabocevo"
    ],
    "name:urd_x_preferred":[
        "\u0632\u0628\u0648\u0686\u0627\u0648\u0648"
    ],
    "wof:name":"Zabocevo",
    "wof:placetype":"locality",
    "wof:population":105
},
  "geometry": {"coordinates":[14.39917,45.9075],"type":"Point"}
}