{
  "type": "Feature",
  "properties": {
    "gn:admin1_code":"01",
    "gn:asciiname":"Brje",
    "gn:country_code":"SI",
    "gn:dem":202,
    "gn:feature_class":"P",
    "gn:feature_code":"PPL",
    "gn:name":"Brje",
    "gn:population":384,
    "gn:timezone":"Europe/Ljubljana",
    "iso:country":"SI",
    "name:bos_x_preferred":[
        "Brje"
    ],
    "name:bul_x_preferred":[
        "\u0411\u0440\u0435"
    ],
    "name:ceb_x_preferred":[
        "Brje"
    ],
    "name:hun_x_preferred":[
        "Brje"
    ],
    "name:nld_x_preferred":[
        "Brje"
    ],
    "name:pol_x_preferred":[
        "Brje"
    ],
    "name:ron_x_preferred":[
        "Brje"
    ],
    "name:slv_x_preferred":[
        "Brje"
    ],
    "name:srp_x_preferred":[
        "\u0411\u0440\u0458\u0435"
    ],
    "name:ukr_x_preferred":[
        "\u0411\u0440\u0454"
    ],
    "wof:name":"Brje",
    "wof:placetype":"locality",
    "wof:population":384
},
  "geometry": {"coordinates":[13.81739,45.86329],"type":"Point"}
}