{
  "type": "Feature",
  "properties": {
    "gn:admin1_code":"35",
    "gn:asciiname":"Klanec pri Kozini",
    "gn:country_code":"SI",
    "gn:dem":456,
    "gn:feature_class":"P",
    "gn:feature_code":"PPL",
    "gn:name":"Klanec pri Kozini",
    "gn:population":115,
    "gn:timezone":"Europe/Ljubljana",
    "iso:country":"SI",
    "name:und_x_variant":[
        "Sveti Peter",
        "Clanz",
        "San Pietro di Madrasso",
        "San Pietro",
        "Klanec",
        "Klanec pri Kozini"
    ],
    "wof:name":"Klanec pri Kozini",
    "wof:placetype":"locality",
    "wof:population":115
},
  "geometry": {"coordinates":[13.92333,45.59417],"type":"Point"}
}