{
  "type": "Feature",
  "properties": {
    "gn:admin1_code":"35",
    "gn:asciiname":"Klanec pri Kozini",
    "gn:country_code":"SI",
    "gn:dem":456,
    "gn:feature_class":"P",
    "gn:feature_code":"PPL",
    "gn:name":"Klanec pri Kozini",
    "gn:population":115,
    "gn:timezone":"Europe/Ljubljana",
    "iso:country":"SI",
    "name:bos_x_preferred":[
        "Klanec pri Kozini"
    ],
    "name:ceb_x_preferred":[
        "Klanec pri Kozini"
    ],
    "name:nld_x_preferred":[
        "Klanec pri Kozini"
    ],
    "name:pol_x_preferred":[
        "Klanec pri Kozini"
    ],
    "name:ron_x_preferred":[
        "Klanec pri Kozini"
    ],
    "name:slv_x_preferred":[
        "Klanec pri Kozini"
    ],
    "name:ukr_x_preferred":[
        "\u041a\u043b\u0430\u043d\u0435\u0446-\u043f\u0440\u0438-\u041a\u043e\u0437\u0456\u043d\u0456"
    ],
    "name:und_x_variant":[
        "Sveti Peter",
        "Clanz",
        "San Pietro di Madrasso",
        "San Pietro",
        "Klanec",
        "Klanec pri Kozini"
    ],
    "wof:name":"Klanec pri Kozini",
    "wof:placetype":"locality",
    "wof:population":115
},
  "geometry": {"coordinates":[13.92333,45.59417],"type":"Point"}
}