{
  "type": "Feature",
  "properties": {
    "gn:admin1_code":"J2",
    "gn:asciiname":"Za Kalvarijo",
    "gn:country_code":"SI",
    "gn:dem":335,
    "gn:feature_class":"P",
    "gn:feature_code":"PPL",
    "gn:name":"Za Kalvarijo",
    "gn:population":157,
    "gn:timezone":"Europe/Ljubljana",
    "iso:country":"SI",
    "wof:name":"Za Kalvarijo",
    "wof:placetype":"locality",
    "wof:population":157
},
  "geometry": {"coordinates":[15.64031,46.57164],"type":"Point"}
}