{
  "type": "Feature",
  "properties": {
    "gn:admin1_code":"J2",
    "gn:asciiname":"Za Kalvarijo",
    "gn:country_code":"SI",
    "gn:dem":335,
    "gn:feature_class":"P",
    "gn:feature_code":"PPL",
    "gn:name":"Za Kalvarijo",
    "gn:population":157,
    "gn:timezone":"Europe/Ljubljana",
    "iso:country":"SI",
    "name:bos_x_preferred":[
        "Za Kalvarijo"
    ],
    "name:bul_x_preferred":[
        "\u0417\u0430 \u041a\u0430\u043b\u0432\u0430\u0440\u0438\u0439\u043e"
    ],
    "name:ceb_x_preferred":[
        "Za Kalvarijo"
    ],
    "name:nld_x_preferred":[
        "Za Kalvarijo"
    ],
    "name:pol_x_preferred":[
        "Za Kalvarijo"
    ],
    "name:ron_x_preferred":[
        "Za Kalvarijo"
    ],
    "name:slv_x_preferred":[
        "Za Kalvarijo"
    ],
    "name:ukr_x_preferred":[
        "\u0417\u0430 \u041a\u0430\u043b\u0432\u0430\u0440\u0456\u0439\u043e"
    ],
    "name:urd_x_preferred":[
        "\u0632\u0627 \u06a9\u0627\u0644\u0648\u0627\u0631\u06cc\u0648"
    ],
    "wof:name":"Za Kalvarijo",
    "wof:placetype":"locality",
    "wof:population":157
},
  "geometry": {"coordinates":[15.64031,46.57164],"type":"Point"}
}