{
  "type": "Feature",
  "properties": {
    "gn:country":"SI",
    "gn:fcode":"PPL",
    "gn:population":1837,
    "iso:country":"SI",
    "name:bos_x_preferred":[
        "Vnanje Gorice"
    ],
    "name:ceb_x_preferred":[
        "Vnanje Gorice"
    ],
    "name:che_x_preferred":[
        "\u0412\u043d\u0430\u043d\u0435 \u0413\u043e\u0440\u0438\u0446\u0435"
    ],
    "name:eng_x_preferred":[
        "Vnanje Gorice"
    ],
    "name:fra_x_preferred":[
        "Vnanje Gorice"
    ],
    "name:hrv_x_preferred":[
        "Vnanje Gorice"
    ],
    "name:nld_x_preferred":[
        "Vnanje Gorice"
    ],
    "name:pol_x_preferred":[
        "Vnanje Gorice"
    ],
    "name:ron_x_preferred":[
        "Vnanje Gorice"
    ],
    "name:slv_x_preferred":[
        "Vnanje Gorice"
    ],
    "name:tat_x_preferred":[
        "\u0412\u043d\u0430\u043d\u0435 \u0413\u043e\u0440\u0438\u0446\u0435"
    ],
    "name:ukr_x_preferred":[
        "\u0412\u043d\u0430\u043d\u0454 \u0413\u043e\u0440\u0438\u0446\u0435"
    ],
    "qs_pg:aaroncc":"SI",
    "qs_pg:gn_country":"SI",
    "qs_pg:gn_fcode":"PPL",
    "qs_pg:gn_pop":1837,
    "qs_pg:name":"Vnanjegorice",
    "qs_pg:name_adm0":"Slovenija",
    "qs_pg:name_adm1":"Ljubljana",
    "qs_pg:photos_9r":0,
    "qs_pg:photos_sr":0,
    "qs_pg:pop_sr":3,
    "qs_pg:qs_pg_placetype":"locality",
    "qs_pg:qs_pg_placetype_gp":"Town",
    "qs_pg:woe_adm0":23424945,
    "woe:adm0_id":23424945,
    "woe:name_adm0":"Slovenija",
    "woe:name_adm1":"Ljubljana",
    "woe:placetype":"Town",
    "wof:name":"Vnanjegorice",
    "wof:placetype":"locality",
    "wof:population":2195
},
  "geometry": {"coordinates":[14.42194,46.00722],"type":"Point"}
}