{
  "type": "Feature",
  "properties": {
    "gn:admin1_code":"57",
    "gn:asciiname":"Breze",
    "gn:country_code":"SI",
    "gn:dem":575,
    "gn:feature_class":"P",
    "gn:feature_code":"PPL",
    "gn:name":"Breze",
    "gn:population":0,
    "gn:timezone":"Europe/Ljubljana",
    "iso:country":"SI",
    "name:bos_x_preferred":[
        "Breze"
    ],
    "name:bul_x_preferred":[
        "\u0411\u0440\u0435\u0437\u0435"
    ],
    "name:ceb_x_preferred":[
        "Breze"
    ],
    "name:deu_x_preferred":[
        "Breze"
    ],
    "name:fra_x_preferred":[
        "Breze"
    ],
    "name:hrv_x_preferred":[
        "Breze"
    ],
    "name:hun_x_preferred":[
        "Breze"
    ],
    "name:nld_x_preferred":[
        "Breze"
    ],
    "name:pol_x_preferred":[
        "Breze"
    ],
    "name:ron_x_preferred":[
        "Breze"
    ],
    "name:rus_x_preferred":[
        "\u0411\u0440\u0435\u0437\u0435"
    ],
    "name:srp_x_preferred":[
        "\u0411\u0440\u0435\u0437\u0435"
    ],
    "name:swe_x_preferred":[
        "Breze"
    ],
    "name:und_x_variant":[
        "Sveti Rupert",
        "Breze pri Celje",
        "\u0160ent Ruperti"
    ],
    "wof:name":"Breze",
    "wof:placetype":"locality"
},
  "geometry": {"coordinates":[15.35056,46.16528],"type":"Point"}
}