{
  "type": "Feature",
  "properties": {
    "gn:admin1_code":"57",
    "gn:asciiname":"Breze",
    "gn:country_code":"SI",
    "gn:dem":575,
    "gn:feature_class":"P",
    "gn:feature_code":"PPL",
    "gn:name":"Breze",
    "gn:population":0,
    "gn:timezone":"Europe/Ljubljana",
    "iso:country":"SI",
    "name:und_x_variant":[
        "Sveti Rupert",
        "Breze pri Celje",
        "\u0160ent Ruperti",
        "Breze"
    ],
    "wof:name":"Breze",
    "wof:placetype":"locality"
},
  "geometry": {"coordinates":[15.35056,46.16528],"type":"Point"}
}