{
  "type": "Feature",
  "properties": {
    "gn:admin1_code":"27",
    "gn:asciiname":"Gorenja Zetina",
    "gn:country_code":"SI",
    "gn:dem":954,
    "gn:feature_class":"P",
    "gn:feature_code":"PPL",
    "gn:name":"Gorenja \u017detina",
    "gn:population":60,
    "gn:timezone":"Europe/Ljubljana",
    "iso:country":"SI",
    "name:bos_x_preferred":[
        "Gorenja \u017detina"
    ],
    "name:hrv_x_preferred":[
        "Gorenja \u017detina"
    ],
    "name:nld_x_preferred":[
        "Gorenja \u017detina"
    ],
    "name:pol_x_preferred":[
        "Gorenja \u017detina"
    ],
    "name:ron_x_preferred":[
        "Gorenja \u017detina"
    ],
    "name:slv_x_preferred":[
        "Gorenja \u017detina"
    ],
    "name:ukr_x_preferred":[
        "\u0413\u043e\u0440\u0435\u043d\u044f \u0416\u0435\u0442\u0438\u043d\u0430"
    ],
    "name:und_x_variant":[
        "Gorenja Vas",
        "Gorenja \u017detina"
    ],
    "wof:name":"Gorenja Zetina",
    "wof:placetype":"locality",
    "wof:population":60
},
  "geometry": {"coordinates":[14.15,46.16667],"type":"Point"}
}