{
  "type": "Feature",
  "properties": {
    "gn:admin1_code":"K4",
    "gn:asciiname":"Groblje",
    "gn:country_code":"SI",
    "gn:dem":271,
    "gn:feature_class":"P",
    "gn:feature_code":"PPL",
    "gn:name":"Groblje",
    "gn:population":0,
    "gn:timezone":"Europe/Ljubljana",
    "iso:country":"SI",
    "name:bos_x_preferred":[
        "Groblje"
    ],
    "name:slv_x_preferred":[
        "Groblje"
    ],
    "wof:name":"Groblje",
    "wof:placetype":"locality"
},
  "geometry": {"coordinates":[15.09722,46.25472],"type":"Point"}
}