{
  "type": "Feature",
  "properties": {
    "gn:admin1_code":"H9",
    "gn:asciiname":"Fara",
    "gn:country_code":"SI",
    "gn:dem":259,
    "gn:feature_class":"P",
    "gn:feature_code":"PPL",
    "gn:name":"Fara",
    "gn:population":41,
    "gn:timezone":"Europe/Ljubljana",
    "iso:country":"SI",
    "name:bos_x_preferred":[
        "Fara"
    ],
    "name:hrv_x_preferred":[
        "Fara"
    ],
    "name:nld_x_preferred":[
        "Fara"
    ],
    "name:pol_x_preferred":[
        "Fara"
    ],
    "name:ron_x_preferred":[
        "Fara"
    ],
    "name:sco_x_preferred":[
        "Fara"
    ],
    "name:slv_x_preferred":[
        "Fara"
    ],
    "name:srp_x_preferred":[
        "\u0424\u0430\u0440\u0430"
    ],
    "name:ukr_x_preferred":[
        "\u0424\u0430\u0440\u0430"
    ],
    "wof:name":"Fara",
    "wof:placetype":"locality",
    "wof:population":41
},
  "geometry": {"coordinates":[14.87833,45.47667],"type":"Point"}
}