{
  "type": "Feature",
  "properties": {
    "gn:admin1_code":"D4",
    "gn:asciiname":"Dobravica pri Vel. Gabru",
    "gn:country_code":"SI",
    "gn:dem":313,
    "gn:feature_class":"P",
    "gn:feature_code":"PPL",
    "gn:name":"Dobravica pri Vel. Gabru",
    "gn:population":21,
    "gn:timezone":"Europe/Ljubljana",
    "iso:country":"SI",
    "wof:name":"Dobravica pri Vel. Gabru",
    "wof:placetype":"locality",
    "wof:population":21
},
  "geometry": {"coordinates":[14.88187,45.91925],"type":"Point"}
}