{
  "type": "Feature",
  "properties": {
    "gn:gn_country":"SI",
    "gn:gn_fcode":"PPL",
    "gn:gn_pop":0,
    "gn:population":359,
    "iso:country":"SI",
    "name:bos_x_preferred":[
        "Selce"
    ],
    "name:cat_x_preferred":[
        "Selce"
    ],
    "name:ceb_x_preferred":[
        "Selce"
    ],
    "name:ces_x_preferred":[
        "Selce"
    ],
    "name:deu_x_preferred":[
        "Selce"
    ],
    "name:epo_x_preferred":[
        "Selce"
    ],
    "name:fra_x_preferred":[
        "Selce"
    ],
    "name:hrv_x_preferred":[
        "Selce"
    ],
    "name:hun_x_preferred":[
        "Selce"
    ],
    "name:ita_x_preferred":[
        "Selce"
    ],
    "name:nld_x_preferred":[
        "Selce"
    ],
    "name:pol_x_preferred":[
        "Selce"
    ],
    "name:ron_x_preferred":[
        "Selce"
    ],
    "name:slk_x_preferred":[
        "Selce"
    ],
    "name:slv_x_preferred":[
        "Selce"
    ],
    "name:swe_x_preferred":[
        "Selce"
    ],
    "qs_pg:aaroncc":"SI",
    "qs_pg:gn_country":"SI",
    "qs_pg:gn_fcode":"PPL",
    "qs_pg:gn_pop":0,
    "qs_pg:name":"Selce",
    "qs_pg:name_adm0":"Slovenija",
    "qs_pg:name_adm1":"Lenart",
    "qs_pg:photos":4,
    "qs_pg:photos_1k":1,
    "qs_pg:photos_9k":1,
    "qs_pg:photos_9r":1,
    "qs_pg:photos_all":4,
    "qs_pg:photos_sr":1,
    "qs_pg:pop_sr":0,
    "qs_pg:qs_pg_placetype":"locality",
    "qs_pg:qs_pg_placetype_gp":"Town",
    "qs_pg:woe_adm0":23424945,
    "woe:adm0_id":23424945,
    "woe:name_adm0":"Slovenija",
    "woe:name_adm1":"Lenart",
    "woe:placetype":"Town",
    "wof:name":"Selce",
    "wof:placetype":"locality",
    "wof:population":359
},
  "geometry": {"coordinates":[15.83333,46.51667],"type":"Point"}
}