{
  "type": "Feature",
  "properties": {
    "gn:admin1_code":"84",
    "gn:asciiname":"Vodice",
    "gn:country_code":"SI",
    "gn:dem":551,
    "gn:feature_class":"P",
    "gn:feature_code":"PPL",
    "gn:name":"Vodice",
    "gn:population":0,
    "gn:timezone":"Europe/Ljubljana",
    "iso:country":"SI",
    "wof:name":"Vodice",
    "wof:placetype":"locality"
},
  "geometry": {"coordinates":[13.63039,46.01905],"type":"Point"}
}