{
  "type": "Feature",
  "properties": {
    "gn:admin1_code":"84",
    "gn:asciiname":"Vodice",
    "gn:country_code":"SI",
    "gn:dem":551,
    "gn:feature_class":"P",
    "gn:feature_code":"PPL",
    "gn:name":"Vodice",
    "gn:population":0,
    "gn:timezone":"Europe/Ljubljana",
    "iso:country":"SI",
    "name:bos_x_preferred":[
        "Vodice"
    ],
    "name:bul_x_preferred":[
        "\u0412\u043e\u0434\u0438\u0446\u0435"
    ],
    "name:ceb_x_preferred":[
        "Vodice"
    ],
    "name:ces_x_preferred":[
        "Vodice"
    ],
    "name:deu_x_preferred":[
        "Vodice"
    ],
    "name:fra_x_preferred":[
        "Vodice"
    ],
    "name:hrv_x_preferred":[
        "Vodice"
    ],
    "name:hun_x_preferred":[
        "Vodice"
    ],
    "name:ita_x_preferred":[
        "Vodice"
    ],
    "name:jpn_x_preferred":[
        "\u30f4\u30a9\u30c7\u30a3\u30c4\u30a7"
    ],
    "name:kor_x_preferred":[
        "\ubcf4\ub514\uccb4"
    ],
    "name:nld_x_preferred":[
        "Vodice"
    ],
    "name:ron_x_preferred":[
        "Vodice"
    ],
    "name:slk_x_preferred":[
        "Vodice"
    ],
    "name:slv_x_preferred":[
        "Vodice"
    ],
    "name:srp_x_preferred":[
        "\u0412\u043e\u0434\u0438\u0446\u0435"
    ],
    "name:swe_x_preferred":[
        "Vodice"
    ],
    "name:ukr_x_preferred":[
        "\u0412\u043e\u0434\u0438\u0446\u0435"
    ],
    "name:vie_x_preferred":[
        "Vodice"
    ],
    "wof:name":"Vodice",
    "wof:placetype":"locality"
},
  "geometry": {"coordinates":[13.63039,46.01905],"type":"Point"}
}