{
  "type": "Feature",
  "properties": {
    "gn:admin1_code":"91",
    "gn:asciiname":"Smihel",
    "gn:country_code":"SI",
    "gn:dem":438,
    "gn:feature_class":"P",
    "gn:feature_code":"PPL",
    "gn:name":"\u0160mihel",
    "gn:population":108,
    "gn:timezone":"Europe/Ljubljana",
    "iso:country":"SI",
    "name:und_x_variant":[
        "\u0160mihel"
    ],
    "wof:name":"Smihel",
    "wof:placetype":"locality",
    "wof:population":108
},
  "geometry": {"coordinates":[14.16862,45.65403],"type":"Point"}
}