{
  "type": "Feature",
  "properties": {
    "gn:admin1_code":"91",
    "gn:asciiname":"Smihel",
    "gn:country_code":"SI",
    "gn:dem":438,
    "gn:feature_class":"P",
    "gn:feature_code":"PPL",
    "gn:name":"\u0160mihel",
    "gn:population":108,
    "gn:timezone":"Europe/Ljubljana",
    "iso:country":"SI",
    "name:bos_x_preferred":[
        "\u0160mihel"
    ],
    "name:ceb_x_preferred":[
        "\u0160mihel"
    ],
    "name:hrv_x_preferred":[
        "\u0160mihel"
    ],
    "name:nld_x_preferred":[
        "\u0160mihel"
    ],
    "name:pol_x_preferred":[
        "\u0160mihel"
    ],
    "name:ron_x_preferred":[
        "\u0160mihel"
    ],
    "name:slv_x_preferred":[
        "\u0160mihel"
    ],
    "name:ukr_x_preferred":[
        "\u0428\u043c\u0438\u0445\u0435\u043b"
    ],
    "wof:name":"Smihel",
    "wof:placetype":"locality",
    "wof:population":108
},
  "geometry": {"coordinates":[14.16862,45.65403],"type":"Point"}
}