{
  "type": "Feature",
  "properties": {
    "gn:admin1_code":"57",
    "gn:asciiname":"Suhadol",
    "gn:country_code":"SI",
    "gn:dem":342,
    "gn:feature_class":"P",
    "gn:feature_code":"PPL",
    "gn:name":"Suhadol",
    "gn:population":27,
    "gn:timezone":"Europe/Ljubljana",
    "iso:country":"SI",
    "name:bos_x_preferred":[
        "Suhadol"
    ],
    "name:hrv_x_preferred":[
        "Suhadol"
    ],
    "name:nld_x_preferred":[
        "Suhadol"
    ],
    "name:pol_x_preferred":[
        "Suhadol"
    ],
    "name:ron_x_preferred":[
        "Suhadol"
    ],
    "name:slv_x_preferred":[
        "Suhadol"
    ],
    "name:ukr_x_preferred":[
        "\u0421\u0443\u0445\u0430\u0434\u043e\u043b"
    ],
    "wof:name":"Suhadol",
    "wof:placetype":"locality",
    "wof:population":27
},
  "geometry": {"coordinates":[15.14414,46.10479],"type":"Point"}
}