{
  "type": "Feature",
  "properties": {
    "gn:admin1_code":"C4",
    "gn:asciiname":"Zbelovska Gora",
    "gn:country_code":"SI",
    "gn:dem":315,
    "gn:feature_class":"P",
    "gn:feature_code":"PPL",
    "gn:name":"Zbelovska Gora",
    "gn:population":325,
    "gn:timezone":"Europe/Ljubljana",
    "iso:country":"SI",
    "wof:name":"Zbelovska Gora",
    "wof:placetype":"locality",
    "wof:population":325
},
  "geometry": {"coordinates":[15.52774,46.28656],"type":"Point"}
}