{
  "type": "Feature",
  "properties": {
    "gn:admin1_code":"C4",
    "gn:asciiname":"Zbelovska Gora",
    "gn:country_code":"SI",
    "gn:dem":315,
    "gn:feature_class":"P",
    "gn:feature_code":"PPL",
    "gn:name":"Zbelovska Gora",
    "gn:population":325,
    "gn:timezone":"Europe/Ljubljana",
    "iso:country":"SI",
    "name:bos_x_preferred":[
        "Zbelovska Gora"
    ],
    "name:ceb_x_preferred":[
        "Zbelovska Gora"
    ],
    "name:hrv_x_preferred":[
        "Zbelovska Gora"
    ],
    "name:nld_x_preferred":[
        "Zbelovska Gora"
    ],
    "name:pol_x_preferred":[
        "Zbelovska Gora"
    ],
    "name:ron_x_preferred":[
        "Zbelovska Gora"
    ],
    "name:slv_x_preferred":[
        "Zbelovska Gora"
    ],
    "name:ukr_x_preferred":[
        "\u0417\u0431\u0435\u043b\u043e\u0432\u0441\u044c\u043a\u0430 \u0413\u043e\u0440\u0430"
    ],
    "wof:name":"Zbelovska Gora",
    "wof:placetype":"locality",
    "wof:population":325
},
  "geometry": {"coordinates":[15.52774,46.28656],"type":"Point"}
}