{
  "type": "Feature",
  "properties": {
    "gn:admin1_code":"84",
    "gn:asciiname":"Preval",
    "gn:country_code":"SI",
    "gn:dem":803,
    "gn:feature_class":"P",
    "gn:feature_code":"PPL",
    "gn:name":"Preval",
    "gn:population":0,
    "gn:timezone":"Europe/Ljubljana",
    "iso:country":"SI",
    "wof:name":"Preval",
    "wof:placetype":"locality"
},
  "geometry": {"coordinates":[13.78511,46.07354],"type":"Point"}
}