{
  "type": "Feature",
  "properties": {
    "gn:admin1_code":"K6",
    "gn:asciiname":"Poljana",
    "gn:country_code":"SI",
    "gn:dem":452,
    "gn:feature_class":"P",
    "gn:feature_code":"PPL",
    "gn:name":"Poljana",
    "gn:population":128,
    "gn:timezone":"Europe/Ljubljana",
    "iso:country":"SI",
    "name:bos_x_preferred":[
        "Poljana"
    ],
    "name:ceb_x_preferred":[
        "Poljana"
    ],
    "name:nld_x_preferred":[
        "Poljana"
    ],
    "name:pol_x_preferred":[
        "Poljana"
    ],
    "name:ron_x_preferred":[
        "Poljana"
    ],
    "name:slv_x_preferred":[
        "Poljana"
    ],
    "name:ukr_x_preferred":[
        "\u041f\u043e\u043b\u044f\u043d\u0430"
    ],
    "wof:name":"Poljana",
    "wof:placetype":"locality",
    "wof:population":128
},
  "geometry": {"coordinates":[14.87306,46.54528],"type":"Point"}
}