{
  "type": "Feature",
  "properties": {
    "gn:admin1_code":"45",
    "gn:asciiname":"Sikole",
    "gn:country_code":"SI",
    "gn:dem":243,
    "gn:feature_class":"P",
    "gn:feature_code":"PPL",
    "gn:name":"\u0160ikole",
    "gn:population":323,
    "gn:timezone":"Europe/Ljubljana",
    "iso:country":"SI",
    "name:und_x_variant":[
        "\u0160ikole"
    ],
    "wof:name":"Sikole",
    "wof:placetype":"locality",
    "wof:population":323
},
  "geometry": {"coordinates":[15.70306,46.405],"type":"Point"}
}