{
  "type": "Feature",
  "properties": {
    "gn:admin1_code":"E1",
    "gn:asciiname":"Vrhpolje",
    "gn:country_code":"SI",
    "gn:dem":137,
    "gn:feature_class":"P",
    "gn:feature_code":"PPL",
    "gn:name":"Vrhpolje",
    "gn:population":549,
    "gn:timezone":"Europe/Ljubljana",
    "iso:country":"SI",
    "name:und_x_variant":[
        "Verpogliano",
        "Vrhpolje"
    ],
    "wof:name":"Vrhpolje",
    "wof:placetype":"locality",
    "wof:population":549
},
  "geometry": {"coordinates":[13.96139,45.86444],"type":"Point"}
}