{
  "type": "Feature",
  "properties": {
    "gn:admin1_code":"E1",
    "gn:asciiname":"Vrhpolje",
    "gn:country_code":"SI",
    "gn:dem":137,
    "gn:feature_class":"P",
    "gn:feature_code":"PPL",
    "gn:name":"Vrhpolje",
    "gn:population":549,
    "gn:timezone":"Europe/Ljubljana",
    "iso:country":"SI",
    "name:bos_x_preferred":[
        "Vrhpolje"
    ],
    "name:ceb_x_preferred":[
        "Vrhpolje"
    ],
    "name:hun_x_preferred":[
        "Vrhpolje"
    ],
    "name:ita_x_preferred":[
        "Verpogliano"
    ],
    "name:nld_x_preferred":[
        "Vrhpolje"
    ],
    "name:pol_x_preferred":[
        "Vrhpolje"
    ],
    "name:ron_x_preferred":[
        "Vrhpolje"
    ],
    "name:slv_x_preferred":[
        "Vrhpolje"
    ],
    "name:ukr_x_preferred":[
        "\u0412\u0440\u0445\u043f\u043e\u043b\u0454"
    ],
    "name:und_x_variant":[
        "Verpogliano",
        "Vrhpolje"
    ],
    "wof:name":"Vrhpolje",
    "wof:placetype":"locality",
    "wof:population":549
},
  "geometry": {"coordinates":[13.96139,45.86444],"type":"Point"}
}