{
  "type": "Feature",
  "properties": {
    "gn:admin1_code":"D4",
    "gn:asciiname":"Velike Dole",
    "gn:country_code":"SI",
    "gn:dem":338,
    "gn:feature_class":"P",
    "gn:feature_code":"PPL",
    "gn:name":"Velike Dole",
    "gn:population":50,
    "gn:timezone":"Europe/Ljubljana",
    "iso:country":"SI",
    "wof:name":"Velike Dole",
    "wof:placetype":"locality",
    "wof:population":50
},
  "geometry": {"coordinates":[14.89626,45.90589],"type":"Point"}
}