{
  "type": "Feature",
  "properties": {
    "gn:admin1_code":"D4",
    "gn:asciiname":"Velike Dole",
    "gn:country_code":"SI",
    "gn:dem":338,
    "gn:feature_class":"P",
    "gn:feature_code":"PPL",
    "gn:name":"Velike Dole",
    "gn:population":50,
    "gn:timezone":"Europe/Ljubljana",
    "iso:country":"SI",
    "name:bos_x_preferred":[
        "Velike Dole"
    ],
    "name:fas_x_preferred":[
        "\u0648\u0644\u06cc\u06a9 \u062f\u0648\u0644\u0647"
    ],
    "name:hrv_x_preferred":[
        "Velike Dole"
    ],
    "name:nld_x_preferred":[
        "Velike Dole"
    ],
    "name:pol_x_preferred":[
        "Velike Dole"
    ],
    "name:ron_x_preferred":[
        "Velike Dole"
    ],
    "name:slv_x_preferred":[
        "Velike Dole"
    ],
    "name:ukr_x_preferred":[
        "\u0412\u0435\u043b\u0438\u043a\u0435 \u0414\u043e\u043b\u0435"
    ],
    "wof:name":"Velike Dole",
    "wof:placetype":"locality",
    "wof:population":50
},
  "geometry": {"coordinates":[14.89626,45.90589],"type":"Point"}
}