{
  "type": "Feature",
  "properties": {
    "gn:admin1_code":"50",
    "gn:asciiname":"Galantici",
    "gn:country_code":"SI",
    "gn:dem":308,
    "gn:feature_class":"P",
    "gn:feature_code":"PPL",
    "gn:name":"Galanti\u010di",
    "gn:population":14,
    "gn:timezone":"Europe/Ljubljana",
    "iso:country":"SI",
    "name:und_x_variant":[
        "Galanti\u010di"
    ],
    "wof:name":"Galantici",
    "wof:placetype":"locality",
    "wof:population":14
},
  "geometry": {"coordinates":[13.87482,45.49261],"type":"Point"}
}