{
  "type": "Feature",
  "properties": {
    "gn:admin1_code":"D2",
    "gn:asciiname":"Lisec",
    "gn:country_code":"SI",
    "gn:dem":768,
    "gn:feature_class":"P",
    "gn:feature_code":"PPL",
    "gn:name":"Lisec",
    "gn:population":0,
    "gn:timezone":"Europe/Ljubljana",
    "iso:country":"SI",
    "name:bos_x_preferred":[
        "Lisec"
    ],
    "name:bul_x_preferred":[
        "\u041b\u0438\u0441\u0435\u0446"
    ],
    "name:nld_x_preferred":[
        "Lisec"
    ],
    "name:pol_x_preferred":[
        "Lisec"
    ],
    "name:ron_x_preferred":[
        "Lisec"
    ],
    "name:slv_x_preferred":[
        "Lisec"
    ],
    "name:ukr_x_preferred":[
        "\u041b\u0456\u0441\u0435\u0446"
    ],
    "wof:name":"Lisec",
    "wof:placetype":"locality"
},
  "geometry": {"coordinates":[13.83889,46.19722],"type":"Point"}
}