{
  "type": "Feature",
  "properties": {
    "gn:admin1_code":"D4",
    "gn:asciiname":"Zidani Most",
    "gn:country_code":"SI",
    "gn:dem":274,
    "gn:feature_class":"P",
    "gn:feature_code":"PPL",
    "gn:name":"Zidani Most",
    "gn:population":54,
    "gn:timezone":"Europe/Ljubljana",
    "iso:country":"SI",
    "name:bos_x_preferred":[
        "Zidani Most"
    ],
    "name:hrv_x_preferred":[
        "Zidani Most"
    ],
    "name:nld_x_preferred":[
        "Zidani Most"
    ],
    "name:pol_x_preferred":[
        "Zidani Most"
    ],
    "name:ron_x_preferred":[
        "Zidani Most"
    ],
    "name:slv_x_preferred":[
        "Zidani Most"
    ],
    "name:ukr_x_preferred":[
        "\u0417\u0438\u0434\u0430\u043d\u0438\u0439 \u041c\u043e\u0441\u0442"
    ],
    "wof:name":"Zidani Most",
    "wof:placetype":"locality",
    "wof:population":54
},
  "geometry": {"coordinates":[14.98037,45.91336],"type":"Point"}
}