{
  "type": "Feature",
  "properties": {
    "gn:admin1_code":"D4",
    "gn:asciiname":"Zidani Most",
    "gn:country_code":"SI",
    "gn:dem":274,
    "gn:feature_class":"P",
    "gn:feature_code":"PPL",
    "gn:name":"Zidani Most",
    "gn:population":54,
    "gn:timezone":"Europe/Ljubljana",
    "iso:country":"SI",
    "wof:name":"Zidani Most",
    "wof:placetype":"locality",
    "wof:population":54
},
  "geometry": {"coordinates":[14.98037,45.91336],"type":"Point"}
}