{
  "type": "Feature",
  "properties": {
    "gn:admin1_code":"54",
    "gn:asciiname":"Kerinov Grm",
    "gn:country_code":"SI",
    "gn:dem":157,
    "gn:feature_class":"P",
    "gn:feature_code":"PPL",
    "gn:name":"Kerinov Grm",
    "gn:population":79,
    "gn:timezone":"Europe/Ljubljana",
    "iso:country":"SI",
    "name:bos_x_preferred":[
        "Kerinov Grm"
    ],
    "name:pol_x_preferred":[
        "Kerinov Grm"
    ],
    "name:rmy_x_preferred":[
        "Kerinov Grm"
    ],
    "name:ron_x_preferred":[
        "Kerinov Grm"
    ],
    "name:slv_x_preferred":[
        "Kerinov Grm"
    ],
    "wof:name":"Kerinov Grm",
    "wof:placetype":"locality",
    "wof:population":79
},
  "geometry": {"coordinates":[15.49058,45.9051],"type":"Point"}
}