{
  "type": "Feature",
  "properties": {
    "gn:admin1_code":"C2",
    "gn:asciiname":"Gmajna",
    "gn:country_code":"SI",
    "gn:dem":634,
    "gn:feature_class":"P",
    "gn:feature_code":"PPL",
    "gn:name":"Gmajna",
    "gn:population":457,
    "gn:timezone":"Europe/Ljubljana",
    "iso:country":"SI",
    "wof:name":"Gmajna",
    "wof:placetype":"locality",
    "wof:population":457
},
  "geometry": {"coordinates":[15.061,46.52756],"type":"Point"}
}