{
  "type": "Feature",
  "properties": {
    "gn:admin1_code":"B6",
    "gn:asciiname":"Kompolje",
    "gn:country_code":"SI",
    "gn:dem":179,
    "gn:feature_class":"P",
    "gn:feature_code":"PPL",
    "gn:name":"Kompolje",
    "gn:population":98,
    "gn:timezone":"Europe/Ljubljana",
    "iso:country":"SI",
    "name:bos_x_preferred":[
        "Kompolje"
    ],
    "name:nld_x_preferred":[
        "Kompolje"
    ],
    "name:pol_x_preferred":[
        "Kompolje"
    ],
    "name:ron_x_preferred":[
        "Kompolje"
    ],
    "name:slv_x_preferred":[
        "Kompolje"
    ],
    "name:ukr_x_preferred":[
        "\u041a\u043e\u043c\u043f\u043e\u043b\u0454"
    ],
    "wof:name":"Kompolje",
    "wof:placetype":"locality",
    "wof:population":98
},
  "geometry": {"coordinates":[15.26667,46.03333],"type":"Point"}
}