{
  "type": "Feature",
  "properties": {
    "gn:admin1_code":"K8",
    "gn:asciiname":"Navrski Vrh",
    "gn:country_code":"SI",
    "gn:dem":466,
    "gn:feature_class":"P",
    "gn:feature_code":"PPL",
    "gn:name":"Navr\u0161ki Vrh",
    "gn:population":62,
    "gn:timezone":"Europe/Ljubljana",
    "iso:country":"SI",
    "name:und_x_variant":[
        "Navr\u0161ki Vrh"
    ],
    "wof:name":"Navrski Vrh",
    "wof:placetype":"locality",
    "wof:population":62
},
  "geometry": {"coordinates":[14.96667,46.53333],"type":"Point"}
}