{
  "type": "Feature",
  "properties": {
    "gn:admin1_code":"K8",
    "gn:asciiname":"Navrski Vrh",
    "gn:country_code":"SI",
    "gn:dem":466,
    "gn:feature_class":"P",
    "gn:feature_code":"PPL",
    "gn:name":"Navr\u0161ki Vrh",
    "gn:population":62,
    "gn:timezone":"Europe/Ljubljana",
    "iso:country":"SI",
    "name:bos_x_preferred":[
        "Navr\u0161ki Vrh"
    ],
    "name:nld_x_preferred":[
        "Navr\u0161ki Vrh"
    ],
    "name:pol_x_preferred":[
        "Navr\u0161ki Vrh"
    ],
    "name:ron_x_preferred":[
        "Navr\u0161ki Vrh"
    ],
    "name:slv_x_preferred":[
        "Navr\u0161ki Vrh"
    ],
    "name:ukr_x_preferred":[
        "\u041d\u0430\u0432\u0440\u0448\u043a\u0438\u0439 \u0412\u0440\u0445"
    ],
    "name:und_x_variant":[
        "Navr\u0161ki Vrh"
    ],
    "wof:name":"Navrski Vrh",
    "wof:placetype":"locality",
    "wof:population":62
},
  "geometry": {"coordinates":[14.96667,46.53333],"type":"Point"}
}