{
  "type": "Feature",
  "properties": {
    "gn:admin1_code":"29",
    "gn:asciiname":"Negova",
    "gn:country_code":"SI",
    "gn:dem":274,
    "gn:feature_class":"P",
    "gn:feature_code":"PPL",
    "gn:name":"Negova",
    "gn:population":347,
    "gn:timezone":"Europe/Ljubljana",
    "iso:country":"SI",
    "wof:name":"Negova",
    "wof:placetype":"locality",
    "wof:population":347
},
  "geometry": {"coordinates":[15.93889,46.60944],"type":"Point"}
}