{
  "type": "Feature",
  "properties": {
    "gn:admin1_code":"01",
    "gn:asciiname":"Budanje",
    "gn:country_code":"SI",
    "gn:dem":245,
    "gn:feature_class":"P",
    "gn:feature_code":"PPL",
    "gn:name":"Budanje",
    "gn:population":817,
    "gn:timezone":"Europe/Ljubljana",
    "iso:country":"SI",
    "name:bos_x_preferred":[
        "Budanje"
    ],
    "name:bul_x_preferred":[
        "\u0411\u0443\u0434\u0430\u043d\u0435"
    ],
    "name:ceb_x_preferred":[
        "Budanje"
    ],
    "name:hun_x_preferred":[
        "Budanje"
    ],
    "name:ita_x_preferred":[
        "Budagne"
    ],
    "name:nld_x_preferred":[
        "Budanje"
    ],
    "name:pol_x_preferred":[
        "Budanje"
    ],
    "name:ron_x_preferred":[
        "Budanje"
    ],
    "name:slv_x_preferred":[
        "Budanje"
    ],
    "name:srp_x_preferred":[
        "\u0411\u0443\u0434\u0430\u045a\u0435"
    ],
    "name:ukr_x_preferred":[
        "\u0411\u0443\u0434\u0430\u043d\u0454"
    ],
    "wof:name":"Budanje",
    "wof:placetype":"locality",
    "wof:population":817
},
  "geometry": {"coordinates":[13.948,45.87471],"type":"Point"}
}