{
  "type": "Feature",
  "properties": {
    "gn:admin1_code":"01",
    "gn:asciiname":"Budanje",
    "gn:country_code":"SI",
    "gn:dem":245,
    "gn:feature_class":"P",
    "gn:feature_code":"PPL",
    "gn:name":"Budanje",
    "gn:population":817,
    "gn:timezone":"Europe/Ljubljana",
    "iso:country":"SI",
    "name:und_x_variant":[
        "Budagne",
        "Budanje"
    ],
    "wof:name":"Budanje",
    "wof:placetype":"locality",
    "wof:population":817
},
  "geometry": {"coordinates":[13.948,45.87471],"type":"Point"}
}