{
  "type": "Feature",
  "properties": {
    "gn:admin1_code":"D2",
    "gn:asciiname":"Ostroznik",
    "gn:country_code":"SI",
    "gn:dem":811,
    "gn:feature_class":"P",
    "gn:feature_code":"PPL",
    "gn:name":"Ostro\u017enik",
    "gn:population":0,
    "gn:timezone":"Europe/Ljubljana",
    "iso:country":"SI",
    "wof:name":"Ostroznik",
    "wof:placetype":"locality"
},
  "geometry": {"coordinates":[13.84861,46.13722],"type":"Point"}
}