{
  "type": "Feature",
  "properties": {
    "gn:admin1_code":"C4",
    "gn:asciiname":"Preloge pri Konjicah",
    "gn:country_code":"SI",
    "gn:dem":418,
    "gn:feature_class":"P",
    "gn:feature_code":"PPL",
    "gn:name":"Preloge pri Konjicah",
    "gn:population":166,
    "gn:timezone":"Europe/Ljubljana",
    "iso:country":"SI",
    "name:bos_x_preferred":[
        "Preloge pri Konjicah"
    ],
    "name:ceb_x_preferred":[
        "Preloge pri Konjicah"
    ],
    "name:hrv_x_preferred":[
        "Preloge pri Konjicah"
    ],
    "name:nld_x_preferred":[
        "Preloge pri Konjicah"
    ],
    "name:pol_x_preferred":[
        "Preloge pri Konjicah"
    ],
    "name:ron_x_preferred":[
        "Preloge pri Konjicah"
    ],
    "name:slv_x_preferred":[
        "Preloge pri Konjicah"
    ],
    "name:ukr_x_preferred":[
        "\u041f\u0440\u0435\u043b\u043e\u0433\u0435-\u043f\u0440\u0438-\u041a\u043e\u043d\u0456\u0446\u0430\u0445"
    ],
    "wof:name":"Preloge pri Konjicah",
    "wof:placetype":"locality",
    "wof:population":166
},
  "geometry": {"coordinates":[15.39717,46.34787],"type":"Point"}
}