{
  "type": "Feature",
  "properties": {
    "gn:admin1_code":"L7",
    "gn:asciiname":"Zagaj pri Ponikvi",
    "gn:country_code":"SI",
    "gn:dem":311,
    "gn:feature_class":"P",
    "gn:feature_code":"PPL",
    "gn:name":"Zagaj pri Ponikvi",
    "gn:population":116,
    "gn:timezone":"Europe/Ljubljana",
    "iso:country":"SI",
    "wof:name":"Zagaj pri Ponikvi",
    "wof:placetype":"locality",
    "wof:population":116
},
  "geometry": {"coordinates":[15.43146,46.26969],"type":"Point"}
}