{
  "type": "Feature",
  "properties": {
    "gn:admin1_code":"L7",
    "gn:asciiname":"Zagaj pri Ponikvi",
    "gn:country_code":"SI",
    "gn:dem":311,
    "gn:feature_class":"P",
    "gn:feature_code":"PPL",
    "gn:name":"Zagaj pri Ponikvi",
    "gn:population":116,
    "gn:timezone":"Europe/Ljubljana",
    "iso:country":"SI",
    "name:bos_x_preferred":[
        "Zagaj pri Ponikvi"
    ],
    "name:ceb_x_preferred":[
        "Zagaj pri Ponikvi"
    ],
    "name:hrv_x_preferred":[
        "Zagaj pri Ponikvi"
    ],
    "name:nld_x_preferred":[
        "Zagaj pri Ponikvi"
    ],
    "name:pol_x_preferred":[
        "Zagaj pri Ponikvi"
    ],
    "name:ron_x_preferred":[
        "Zagaj pri Ponikvi"
    ],
    "name:slv_x_preferred":[
        "Zagaj pri Ponikvi"
    ],
    "name:ukr_x_preferred":[
        "\u0417\u0430\u0433\u0430\u0439-\u043f\u0440\u0438-\u041f\u043e\u043d\u0438\u043a\u0432\u0456"
    ],
    "name:urd_x_preferred":[
        "\u0632\u06af\u0627\u062c \u067e\u0631 \u067e\u0648\u0646\u06a9\u0648\u06cc"
    ],
    "wof:name":"Zagaj pri Ponikvi",
    "wof:placetype":"locality",
    "wof:population":116
},
  "geometry": {"coordinates":[15.43146,46.26969],"type":"Point"}
}