{
  "type": "Feature",
  "properties": {
    "gn:admin1_code":"35",
    "gn:asciiname":"Poljane pri Podgradu",
    "gn:country_code":"SI",
    "gn:dem":600,
    "gn:feature_class":"P",
    "gn:feature_code":"PPL",
    "gn:name":"Poljane pri Podgradu",
    "gn:population":6,
    "gn:timezone":"Europe/Ljubljana",
    "iso:country":"SI",
    "name:und_x_variant":[
        "Pogliane",
        "Poljane"
    ],
    "wof:name":"Poljane pri Podgradu",
    "wof:placetype":"locality",
    "wof:population":6
},
  "geometry": {"coordinates":[14.10333,45.50611],"type":"Point"}
}