{
  "type": "Feature",
  "properties": {
    "gn:admin1_code":"35",
    "gn:asciiname":"Poljane pri Podgradu",
    "gn:country_code":"SI",
    "gn:dem":600,
    "gn:feature_class":"P",
    "gn:feature_code":"PPL",
    "gn:name":"Poljane pri Podgradu",
    "gn:population":6,
    "gn:timezone":"Europe/Ljubljana",
    "iso:country":"SI",
    "name:bos_x_preferred":[
        "Poljane pri Podgradu"
    ],
    "name:nld_x_preferred":[
        "Poljane pri Podgradu"
    ],
    "name:pol_x_preferred":[
        "Poljane pri Podgradu"
    ],
    "name:ron_x_preferred":[
        "Poljane pri Podgradu"
    ],
    "name:sco_x_preferred":[
        "Poljane pri Podgradu"
    ],
    "name:slv_x_preferred":[
        "Poljane pri Podgradu"
    ],
    "name:ukr_x_preferred":[
        "\u041f\u043e\u043b\u044f\u043d\u0435-\u043f\u0440\u0438-\u041f\u043e\u0434\u0433\u0440\u0430\u0434\u0443"
    ],
    "name:und_x_variant":[
        "Pogliane",
        "Poljane"
    ],
    "wof:name":"Poljane pri Podgradu",
    "wof:placetype":"locality",
    "wof:population":6
},
  "geometry": {"coordinates":[14.10333,45.50611],"type":"Point"}
}