{
  "type": "Feature",
  "properties": {
    "gn:admin1_code":"P8",
    "gn:asciiname":"Rucmanci",
    "gn:country_code":"SI",
    "gn:dem":251,
    "gn:feature_class":"P",
    "gn:feature_code":"PPL",
    "gn:name":"Rucmanci",
    "gn:population":206,
    "gn:timezone":"Europe/Ljubljana",
    "iso:country":"SI",
    "name:bos_x_preferred":[
        "Rucmanci"
    ],
    "name:ceb_x_preferred":[
        "Rucmanci"
    ],
    "name:nld_x_preferred":[
        "Rucmanci"
    ],
    "name:pol_x_preferred":[
        "Rucmanci"
    ],
    "name:ron_x_preferred":[
        "Rucmanci"
    ],
    "name:slv_x_preferred":[
        "Rucmanci"
    ],
    "name:ukr_x_preferred":[
        "\u0420\u0443\u0446\u043c\u0430\u043d\u0446\u0456"
    ],
    "wof:name":"Rucmanci",
    "wof:placetype":"locality",
    "wof:population":206
},
  "geometry": {"coordinates":[16.04222,46.49306],"type":"Point"}
}