{
  "type": "Feature",
  "properties": {
    "gn:admin1_code":"P8",
    "gn:asciiname":"Rucmanci",
    "gn:country_code":"SI",
    "gn:dem":251,
    "gn:feature_class":"P",
    "gn:feature_code":"PPL",
    "gn:name":"Rucmanci",
    "gn:population":206,
    "gn:timezone":"Europe/Ljubljana",
    "iso:country":"SI",
    "wof:name":"Rucmanci",
    "wof:placetype":"locality",
    "wof:population":206
},
  "geometry": {"coordinates":[16.04222,46.49306],"type":"Point"}
}