{
  "type": "Feature",
  "properties": {
    "gn:admin1_code":"73",
    "gn:asciiname":"Dolnje Dobravice",
    "gn:country_code":"SI",
    "gn:dem":165,
    "gn:feature_class":"P",
    "gn:feature_code":"PPL",
    "gn:name":"Dolnje Dobravice",
    "gn:population":80,
    "gn:timezone":"Europe/Ljubljana",
    "iso:country":"SI",
    "name:bos_x_preferred":[
        "Dolnje Dobravice"
    ],
    "name:hrv_x_preferred":[
        "Dolnje Dobravice"
    ],
    "name:nld_x_preferred":[
        "Dolnje Dobravice"
    ],
    "name:pol_x_preferred":[
        "Dolnje Dobravice"
    ],
    "name:ron_x_preferred":[
        "Dolnje Dobravice"
    ],
    "name:slv_x_preferred":[
        "Dolnje Dobravice"
    ],
    "name:ukr_x_preferred":[
        "\u0414\u043e\u043b\u043d\u0454 \u0414\u043e\u0431\u0440\u0430\u0432\u0438\u0446\u0435"
    ],
    "name:und_x_variant":[
        "Dolenje Dobravica",
        "Dolenje Dobravice"
    ],
    "wof:name":"Dolnje Dobravice",
    "wof:placetype":"locality",
    "wof:population":80
},
  "geometry": {"coordinates":[15.26667,45.63333],"type":"Point"}
}