{
  "type": "Feature",
  "properties": {
    "gn:admin1_code":"73",
    "gn:asciiname":"Dolnje Dobravice",
    "gn:country_code":"SI",
    "gn:dem":165,
    "gn:feature_class":"P",
    "gn:feature_code":"PPL",
    "gn:name":"Dolnje Dobravice",
    "gn:population":80,
    "gn:timezone":"Europe/Ljubljana",
    "iso:country":"SI",
    "name:und_x_variant":[
        "Dolenje Dobravica",
        "Dolenje Dobravice",
        "Dolnje Dobravice"
    ],
    "wof:name":"Dolnje Dobravice",
    "wof:placetype":"locality",
    "wof:population":80
},
  "geometry": {"coordinates":[15.26667,45.63333],"type":"Point"}
}