{
  "type": "Feature",
  "properties": {
    "gn:admin1_code":"73",
    "gn:asciiname":"Trnovec",
    "gn:country_code":"SI",
    "gn:dem":255,
    "gn:feature_class":"P",
    "gn:feature_code":"PPL",
    "gn:name":"Trnovec",
    "gn:population":103,
    "gn:timezone":"Europe/Ljubljana",
    "iso:country":"SI",
    "name:bos_x_preferred":[
        "Trnovec"
    ],
    "name:ceb_x_preferred":[
        "Trnovec"
    ],
    "name:hrv_x_preferred":[
        "Trnovec"
    ],
    "name:nld_x_preferred":[
        "Trnovec"
    ],
    "name:pol_x_preferred":[
        "Trnovec"
    ],
    "name:ron_x_preferred":[
        "Trnovec"
    ],
    "name:slv_x_preferred":[
        "Trnovec"
    ],
    "name:ukr_x_preferred":[
        "\u0422\u0440\u043d\u043e\u0432\u0435\u0446\u044c"
    ],
    "wof:name":"Trnovec",
    "wof:placetype":"locality",
    "wof:population":103
},
  "geometry": {"coordinates":[15.29256,45.66364],"type":"Point"}
}