{
  "type": "Feature",
  "properties": {
    "gn:admin1_code":"73",
    "gn:asciiname":"Trnovec",
    "gn:country_code":"SI",
    "gn:dem":255,
    "gn:feature_class":"P",
    "gn:feature_code":"PPL",
    "gn:name":"Trnovec",
    "gn:population":103,
    "gn:timezone":"Europe/Ljubljana",
    "iso:country":"SI",
    "wof:name":"Trnovec",
    "wof:placetype":"locality",
    "wof:population":103
},
  "geometry": {"coordinates":[15.29256,45.66364],"type":"Point"}
}