{
  "type": "Feature",
  "properties": {
    "gn:admin1_code":"I6",
    "gn:asciiname":"Podgradje",
    "gn:country_code":"SI",
    "gn:dem":212,
    "gn:feature_class":"P",
    "gn:feature_code":"PPL",
    "gn:name":"Podgradje",
    "gn:population":267,
    "gn:timezone":"Europe/Ljubljana",
    "iso:country":"SI",
    "name:bos_x_preferred":[
        "Podgradje"
    ],
    "name:ceb_x_preferred":[
        "Podgradje"
    ],
    "name:pol_x_preferred":[
        "Podgradje"
    ],
    "name:slv_x_preferred":[
        "Podgradje"
    ],
    "name:ukr_x_preferred":[
        "\u041f\u043e\u0434\u0433\u0440\u0430\u0434\u0454"
    ],
    "wof:name":"Podgradje",
    "wof:placetype":"locality",
    "wof:population":267
},
  "geometry": {"coordinates":[16.21251,46.50441],"type":"Point"}
}