{
  "type": "Feature",
  "properties": {
    "gn:admin1_code":"H6",
    "gn:asciiname":"Sela pri Kamniku",
    "gn:country_code":"SI",
    "gn:dem":526,
    "gn:feature_class":"P",
    "gn:feature_code":"PPL",
    "gn:name":"Sela pri Kamniku",
    "gn:population":133,
    "gn:timezone":"Europe/Ljubljana",
    "iso:country":"SI",
    "name:bos_x_preferred":[
        "Sela pri Kamniku"
    ],
    "name:ceb_x_preferred":[
        "Sela pri Kamniku"
    ],
    "name:pol_x_preferred":[
        "Sela pri Kamniku"
    ],
    "name:ron_x_preferred":[
        "Sela pri Kamniku"
    ],
    "name:slv_x_preferred":[
        "Sela pri Kamniku"
    ],
    "name:ukr_x_preferred":[
        "\u0421\u0435\u043b\u0430-\u043f\u0440\u0438-\u041a\u0430\u043c\u043d\u0438\u043a\u0443"
    ],
    "name:und_x_variant":[
        "Sela",
        "Sela pri Kamniku"
    ],
    "wof:name":"Sela pri Kamniku",
    "wof:placetype":"locality",
    "wof:population":133
},
  "geometry": {"coordinates":[14.68679,46.23647],"type":"Point"}
}