{
  "type": "Feature",
  "properties": {
    "gn:admin1_code":"L7",
    "gn:asciiname":"Straska Gorca",
    "gn:country_code":"SI",
    "gn:dem":426,
    "gn:feature_class":"P",
    "gn:feature_code":"PPL",
    "gn:name":"Stra\u0161ka Gorca",
    "gn:population":86,
    "gn:timezone":"Europe/Ljubljana",
    "iso:country":"SI",
    "name:und_x_variant":[
        "Stra\u0161ka Gorca"
    ],
    "wof:name":"Straska Gorca",
    "wof:placetype":"locality",
    "wof:population":86
},
  "geometry": {"coordinates":[15.48836,46.11422],"type":"Point"}
}