{
  "type": "Feature",
  "properties": {
    "gn:admin1_code":"D2",
    "gn:asciiname":"Rut",
    "gn:country_code":"SI",
    "gn:dem":738,
    "gn:feature_class":"P",
    "gn:feature_code":"PPL",
    "gn:name":"Rut",
    "gn:population":43,
    "gn:timezone":"Europe/Ljubljana",
    "iso:country":"SI",
    "name:bos_x_preferred":[
        "Rut"
    ],
    "name:bul_x_preferred":[
        "\u0420\u0443\u0442"
    ],
    "name:deu_x_preferred":[
        "Rut"
    ],
    "name:nld_x_preferred":[
        "Rut"
    ],
    "name:pol_x_preferred":[
        "Rut"
    ],
    "name:ron_x_preferred":[
        "Rut"
    ],
    "name:slv_x_preferred":[
        "Rut"
    ],
    "name:ukr_x_preferred":[
        "\u0420\u0443\u0442"
    ],
    "name:und_x_variant":[
        "Nem\u0161ki Rut",
        "Rutte",
        "Deutschruthd",
        "Rutte di Grac",
        "Rutte di Gracova"
    ],
    "wof:name":"Rut",
    "wof:placetype":"locality",
    "wof:population":43
},
  "geometry": {"coordinates":[13.89472,46.20861],"type":"Point"}
}