{
  "type": "Feature",
  "properties": {
    "gn:admin1_code":"27",
    "gn:asciiname":"Murave",
    "gn:country_code":"SI",
    "gn:dem":775,
    "gn:feature_class":"P",
    "gn:feature_code":"PPL",
    "gn:name":"Murave",
    "gn:population":71,
    "gn:timezone":"Europe/Ljubljana",
    "iso:country":"SI",
    "name:bos_x_preferred":[
        "Murave"
    ],
    "name:hrv_x_preferred":[
        "Murave"
    ],
    "name:nld_x_preferred":[
        "Murave"
    ],
    "name:pol_x_preferred":[
        "Murave"
    ],
    "name:ron_x_preferred":[
        "Murave"
    ],
    "name:slv_x_preferred":[
        "Murave"
    ],
    "name:ukr_x_preferred":[
        "\u041c\u0443\u0440\u0430\u0432\u0435"
    ],
    "wof:name":"Murave",
    "wof:placetype":"locality",
    "wof:population":71
},
  "geometry": {"coordinates":[14.16857,46.16109],"type":"Point"}
}