{
  "type": "Feature",
  "properties": {
    "gn:admin1_code":"A7",
    "gn:asciiname":"Gabrovec pri Kostrivnici",
    "gn:country_code":"SI",
    "gn:dem":288,
    "gn:feature_class":"P",
    "gn:feature_code":"PPL",
    "gn:name":"Gabrovec pri Kostrivnici",
    "gn:population":72,
    "gn:timezone":"Europe/Ljubljana",
    "iso:country":"SI",
    "name:bos_x_preferred":[
        "Gabrovec pri Kostrivnici"
    ],
    "name:bul_x_preferred":[
        "\u0413\u0430\u0431\u0440\u043e\u0432\u0435\u0446 \u043f\u0440\u0438 \u041a\u043e\u0441\u0442\u0440\u0438\u0432\u043d\u0438\u0446\u0438"
    ],
    "name:hrv_x_preferred":[
        "Gabrovec pri Kostrivnici"
    ],
    "name:nld_x_preferred":[
        "Gabrovec pri Kostrivnici"
    ],
    "name:pol_x_preferred":[
        "Gabrovec pri Kostrivnici"
    ],
    "name:ron_x_preferred":[
        "Gabrovec pri Kostrivnici"
    ],
    "name:slv_x_preferred":[
        "Gabrovec pri Kostrivnici"
    ],
    "name:ukr_x_preferred":[
        "\u0413\u0430\u0431\u0440\u043e\u0432\u0435\u0446\u044c-\u043f\u0440\u0438-\u041a\u043e\u0441\u0442\u0440\u0438\u0432\u043d\u0438\u0446\u0456"
    ],
    "wof:name":"Gabrovec pri Kostrivnici",
    "wof:placetype":"locality",
    "wof:population":72
},
  "geometry": {"coordinates":[15.58575,46.26509],"type":"Point"}
}