{
  "type": "Feature",
  "properties": {
    "gn:admin1_code":"A7",
    "gn:asciiname":"Gabrovec pri Kostrivnici",
    "gn:country_code":"SI",
    "gn:dem":288,
    "gn:feature_class":"P",
    "gn:feature_code":"PPL",
    "gn:name":"Gabrovec pri Kostrivnici",
    "gn:population":72,
    "gn:timezone":"Europe/Ljubljana",
    "iso:country":"SI",
    "wof:name":"Gabrovec pri Kostrivnici",
    "wof:placetype":"locality",
    "wof:population":72
},
  "geometry": {"coordinates":[15.58575,46.26509],"type":"Point"}
}