{
  "type": "Feature",
  "properties": {
    "gn:admin1_code":"27",
    "gn:asciiname":"Cabrace",
    "gn:country_code":"SI",
    "gn:dem":511,
    "gn:feature_class":"P",
    "gn:feature_code":"PPL",
    "gn:name":"\u010cabra\u010de",
    "gn:population":55,
    "gn:timezone":"Europe/Ljubljana",
    "iso:country":"SI",
    "name:und_x_variant":[
        "\u010cabra\u010de"
    ],
    "wof:name":"Cabrace",
    "wof:placetype":"locality",
    "wof:population":55
},
  "geometry": {"coordinates":[14.13333,46.13333],"type":"Point"}
}