{
  "type": "Feature",
  "properties": {
    "gn:admin1_code":"27",
    "gn:asciiname":"Cabrace",
    "gn:country_code":"SI",
    "gn:dem":511,
    "gn:feature_class":"P",
    "gn:feature_code":"PPL",
    "gn:name":"\u010cabra\u010de",
    "gn:population":55,
    "gn:timezone":"Europe/Ljubljana",
    "iso:country":"SI",
    "name:bos_x_preferred":[
        "\u010cabra\u010de"
    ],
    "name:hrv_x_preferred":[
        "\u010cabra\u010de"
    ],
    "name:nld_x_preferred":[
        "\u010cabra\u010de"
    ],
    "name:pol_x_preferred":[
        "\u010cabra\u010de"
    ],
    "name:ron_x_preferred":[
        "\u010cabra\u010de"
    ],
    "name:slv_x_preferred":[
        "\u010cabra\u010de"
    ],
    "name:ukr_x_preferred":[
        "\u0427\u0430\u0431\u0440\u0430\u0447\u0435"
    ],
    "wof:name":"Cabrace",
    "wof:placetype":"locality",
    "wof:population":55
},
  "geometry": {"coordinates":[14.13333,46.13333],"type":"Point"}
}