{
  "type": "Feature",
  "properties": {
    "gn:admin1_code":"50",
    "gn:asciiname":"Gracisce",
    "gn:country_code":"SI",
    "gn:dem":330,
    "gn:feature_class":"P",
    "gn:feature_code":"PPL",
    "gn:name":"Gra\u010di\u0161\u010de",
    "gn:population":185,
    "gn:timezone":"Europe/Ljubljana",
    "iso:country":"SI",
    "name:bos_x_preferred":[
        "Gra\u010di\u0161\u010de"
    ],
    "name:bul_x_preferred":[
        "\u0413\u0440\u0430\u0447\u0438\u0448\u0447\u0435"
    ],
    "name:ceb_x_preferred":[
        "Gra\u010di\u0161\u010de"
    ],
    "name:ita_x_preferred":[
        "Gracischie"
    ],
    "name:nld_x_preferred":[
        "Gra\u010di\u0161\u010de"
    ],
    "name:pol_x_preferred":[
        "Gra\u010di\u0161\u010de"
    ],
    "name:ron_x_preferred":[
        "Gra\u010di\u0161\u010de"
    ],
    "name:slv_x_preferred":[
        "Gra\u010di\u0161\u010de"
    ],
    "name:ukr_x_preferred":[
        "\u0413\u0440\u0430\u0447\u0438\u0449\u0435"
    ],
    "name:und_x_variant":[
        "Gra\u010di\u0161\u010de"
    ],
    "wof:name":"Gracisce",
    "wof:placetype":"locality",
    "wof:population":185
},
  "geometry": {"coordinates":[13.87694,45.505],"type":"Point"}
}