{
  "type": "Feature",
  "properties": {
    "gn:admin1_code":"04",
    "gn:asciiname":"Krstenica",
    "gn:country_code":"SI",
    "gn:dem":1669,
    "gn:feature_class":"P",
    "gn:feature_code":"PPL",
    "gn:name":"Krstenica",
    "gn:population":0,
    "gn:timezone":"Europe/Ljubljana",
    "iso:country":"SI",
    "wof:name":"Krstenica",
    "wof:placetype":"locality"
},
  "geometry": {"coordinates":[13.85278,46.3275],"type":"Point"}
}