{
  "type": "Feature",
  "properties": {
    "gn:admin1_code":"B3",
    "gn:asciiname":"Spodnja Velka",
    "gn:country_code":"SI",
    "gn:dem":290,
    "gn:feature_class":"P",
    "gn:feature_code":"PPLL",
    "gn:name":"Spodnja Velka",
    "gn:population":453,
    "gn:timezone":"Europe/Ljubljana",
    "iso:country":"SI",
    "name:bos_x_preferred":[
        "Spodnja Velka"
    ],
    "name:ceb_x_preferred":[
        "Spodnja Velka"
    ],
    "name:nld_x_preferred":[
        "Spodnja Velka"
    ],
    "name:pol_x_preferred":[
        "Spodnja Velka"
    ],
    "name:ron_x_preferred":[
        "Spodnja Velka"
    ],
    "name:slv_x_preferred":[
        "Spodnja Velka"
    ],
    "name:ukr_x_preferred":[
        "\u0421\u043f\u043e\u0434\u043d\u044f \u0412\u0435\u043b\u043a\u0430"
    ],
    "wof:name":"Spodnja Velka",
    "wof:placetype":"locality",
    "wof:population":453
},
  "geometry": {"coordinates":[15.76667,46.65],"type":"Point"}
}