{
  "type": "Feature",
  "properties": {
    "gn:admin1_code":"J1",
    "gn:asciiname":"Spodnja Sveca",
    "gn:country_code":"SI",
    "gn:dem":290,
    "gn:feature_class":"P",
    "gn:feature_code":"PPL",
    "gn:name":"Spodnja Sve\u010da",
    "gn:population":53,
    "gn:timezone":"Europe/Ljubljana",
    "iso:country":"SI",
    "name:bos_x_preferred":[
        "Spodnja Sve\u010da"
    ],
    "name:nld_x_preferred":[
        "Spodnja Sve\u010da"
    ],
    "name:pol_x_preferred":[
        "Spodnja Sve\u010da"
    ],
    "name:ron_x_preferred":[
        "Spodnja Sve\u010da"
    ],
    "name:slv_x_preferred":[
        "Spodnja Sve\u010da"
    ],
    "wof:name":"Spodnja Sveca",
    "wof:placetype":"locality",
    "wof:population":53
},
  "geometry": {"coordinates":[15.71803,46.32205],"type":"Point"}
}