{
  "type": "Feature",
  "properties": {
    "gn:admin1_code":"50",
    "gn:asciiname":"Olika",
    "gn:country_code":"SI",
    "gn:dem":184,
    "gn:feature_class":"P",
    "gn:feature_code":"PPL",
    "gn:name":"Olika",
    "gn:population":2,
    "gn:timezone":"Europe/Ljubljana",
    "iso:country":"SI",
    "wof:name":"Olika",
    "wof:placetype":"locality",
    "wof:population":2
},
  "geometry": {"coordinates":[13.8921,45.45771],"type":"Point"}
}