{
  "type": "Feature",
  "properties": {
    "gn:admin1_code":"72",
    "gn:asciiname":"Preserje pri Radomljah",
    "gn:country_code":"SI",
    "gn:dem":323,
    "gn:feature_class":"P",
    "gn:feature_code":"PPL",
    "gn:name":"Preserje pri Radomljah",
    "gn:population":1531,
    "gn:timezone":"Europe/Ljubljana",
    "iso:country":"SI",
    "name:bos_x_preferred":[
        "Preserje pri Radomljah"
    ],
    "name:ceb_x_preferred":[
        "Preserje pri Radomljah"
    ],
    "name:nld_x_preferred":[
        "Preserje pri Radomljah"
    ],
    "name:pol_x_preferred":[
        "Preserje pri Radomljah"
    ],
    "name:ron_x_preferred":[
        "Preserje pri Radomljah"
    ],
    "name:slv_x_preferred":[
        "Preserje pri Radomljah"
    ],
    "name:ukr_x_preferred":[
        "\u041f\u0440\u0435\u0441\u0435\u0440\u0454-\u043f\u0440\u0438-\u0420\u0430\u0434\u043e\u043c\u043b\u044f\u0445"
    ],
    "name:und_x_variant":[
        "Preserje"
    ],
    "wof:name":"Preserje pri Radomljah",
    "wof:placetype":"locality",
    "wof:population":1531
},
  "geometry": {"coordinates":[14.59698,46.16911],"type":"Point"}
}