{
  "type": "Feature",
  "properties": {
    "gn:admin1_code":"72",
    "gn:asciiname":"Preserje pri Radomljah",
    "gn:country_code":"SI",
    "gn:dem":323,
    "gn:feature_class":"P",
    "gn:feature_code":"PPL",
    "gn:name":"Preserje pri Radomljah",
    "gn:population":1531,
    "gn:timezone":"Europe/Ljubljana",
    "iso:country":"SI",
    "name:und_x_variant":[
        "Preserje",
        "Preserje pri Radomljah"
    ],
    "wof:name":"Preserje pri Radomljah",
    "wof:placetype":"locality",
    "wof:population":1531
},
  "geometry": {"coordinates":[14.59698,46.16911],"type":"Point"}
}