{
  "type": "Feature",
  "properties": {
    "gn:admin1_code":"17",
    "gn:asciiname":"Cresnjevec pri Dragatusu",
    "gn:country_code":"SI",
    "gn:dem":216,
    "gn:feature_class":"P",
    "gn:feature_code":"PPL",
    "gn:name":"\u010cre\u0161njevec pri Dragatu\u0161u",
    "gn:population":5,
    "gn:timezone":"Europe/Ljubljana",
    "iso:country":"SI",
    "name:bos_x_preferred":[
        "\u010cre\u0161njevec pri Dragatu\u0161u"
    ],
    "name:hrv_x_preferred":[
        "\u010cre\u0161njevec pri Dragatu\u0161u"
    ],
    "name:nld_x_preferred":[
        "\u010cre\u0161njevec pri Dragatu\u0161u"
    ],
    "name:pol_x_preferred":[
        "\u010cre\u0161njevec pri Dragatu\u0161u"
    ],
    "name:ron_x_preferred":[
        "\u010cre\u0161njevec pri Dragatu\u0161u"
    ],
    "name:slv_x_preferred":[
        "\u010cre\u0161njevec pri Dragatu\u0161u"
    ],
    "name:ukr_x_preferred":[
        "\u0427\u0440\u0435\u0448\u043d\u0454\u0432\u0435\u0446\u044c-\u043f\u0440\u0438-\u0414\u0440\u0430\u0433\u0430\u0442\u0443\u0448\u0443"
    ],
    "name:und_x_variant":[
        "\u010cre\u0161njevec"
    ],
    "wof:name":"Cresnjevec pri Dragatusu",
    "wof:placetype":"locality",
    "wof:population":5
},
  "geometry": {"coordinates":[15.22403,45.51285],"type":"Point"}
}