{
  "type": "Feature",
  "properties": {
    "gn:admin1_code":"17",
    "gn:asciiname":"Cresnjevec pri Dragatusu",
    "gn:country_code":"SI",
    "gn:dem":216,
    "gn:feature_class":"P",
    "gn:feature_code":"PPL",
    "gn:name":"\u010cre\u0161njevec pri Dragatu\u0161u",
    "gn:population":5,
    "gn:timezone":"Europe/Ljubljana",
    "iso:country":"SI",
    "name:und_x_variant":[
        "\u010cre\u0161njevec",
        "\u010cre\u0161njevec pri Dragatu\u0161u"
    ],
    "wof:name":"Cresnjevec pri Dragatusu",
    "wof:placetype":"locality",
    "wof:population":5
},
  "geometry": {"coordinates":[15.22403,45.51285],"type":"Point"}
}