{
  "type": "Feature",
  "properties": {
    "gn:admin1_code":"57",
    "gn:asciiname":"Goreljce",
    "gn:country_code":"SI",
    "gn:dem":474,
    "gn:feature_class":"P",
    "gn:feature_code":"PPL",
    "gn:name":"Goreljce",
    "gn:population":0,
    "gn:timezone":"Europe/Ljubljana",
    "iso:country":"SI",
    "name:bos_x_preferred":[
        "Goreljce"
    ],
    "name:hrv_x_preferred":[
        "Goreljce"
    ],
    "name:nld_x_preferred":[
        "Goreljce"
    ],
    "name:pol_x_preferred":[
        "Goreljce"
    ],
    "name:ron_x_preferred":[
        "Goreljce"
    ],
    "name:slv_x_preferred":[
        "Goreljce"
    ],
    "name:srp_x_preferred":[
        "\u0413\u043e\u0440\u0435\u0459\u0446\u0435"
    ],
    "name:ukr_x_preferred":[
        "\u0413\u043e\u0440\u0435\u043b\u044c\u0446\u0435"
    ],
    "wof:name":"Goreljce",
    "wof:placetype":"locality"
},
  "geometry": {"coordinates":[15.31667,46.11667],"type":"Point"}
}