{
  "type": "Feature",
  "properties": {
    "gn:admin1_code":"57",
    "gn:asciiname":"Goreljce",
    "gn:country_code":"SI",
    "gn:dem":474,
    "gn:feature_class":"P",
    "gn:feature_code":"PPL",
    "gn:name":"Goreljce",
    "gn:population":0,
    "gn:timezone":"Europe/Ljubljana",
    "iso:country":"SI",
    "wof:name":"Goreljce",
    "wof:placetype":"locality"
},
  "geometry": {"coordinates":[15.31667,46.11667],"type":"Point"}
}