{
  "type": "Feature",
  "properties": {
    "gn:admin1_code":"01",
    "gn:asciiname":"Slokarji",
    "gn:country_code":"SI",
    "gn:dem":254,
    "gn:feature_class":"P",
    "gn:feature_code":"PPL",
    "gn:name":"Slokarji",
    "gn:population":0,
    "gn:timezone":"Europe/Ljubljana",
    "iso:country":"SI",
    "wof:name":"Slokarji",
    "wof:placetype":"locality"
},
  "geometry": {"coordinates":[13.89194,45.91611],"type":"Point"}
}