{
  "type": "Feature",
  "properties": {
    "gn:admin1_code":"E9",
    "gn:asciiname":"Hrastovec",
    "gn:country_code":"SI",
    "gn:dem":303,
    "gn:feature_class":"P",
    "gn:feature_code":"PPL",
    "gn:name":"Hrastovec",
    "gn:population":443,
    "gn:timezone":"Europe/Ljubljana",
    "iso:country":"SI",
    "name:bos_x_preferred":[
        "Hrastovec"
    ],
    "name:ceb_x_preferred":[
        "Hrastovec"
    ],
    "name:nld_x_preferred":[
        "Hrastovec"
    ],
    "name:pol_x_preferred":[
        "Hrastovec"
    ],
    "name:ron_x_preferred":[
        "Hrastovec"
    ],
    "name:slv_x_preferred":[
        "Hrastovec"
    ],
    "name:ukr_x_preferred":[
        "\u0425\u0440\u0430\u0441\u0442\u043e\u0432\u0435\u0446\u044c"
    ],
    "wof:name":"Hrastovec",
    "wof:placetype":"locality",
    "wof:population":443
},
  "geometry": {"coordinates":[16.03722,46.37472],"type":"Point"}
}