{
  "type": "Feature",
  "properties": {
    "gn:admin1_code":"E9",
    "gn:asciiname":"Hrastovec",
    "gn:country_code":"SI",
    "gn:dem":303,
    "gn:feature_class":"P",
    "gn:feature_code":"PPL",
    "gn:name":"Hrastovec",
    "gn:population":443,
    "gn:timezone":"Europe/Ljubljana",
    "iso:country":"SI",
    "wof:name":"Hrastovec",
    "wof:placetype":"locality",
    "wof:population":443
},
  "geometry": {"coordinates":[16.03722,46.37472],"type":"Point"}
}