{
  "type": "Feature",
  "properties": {
    "gn:admin1_code":"A7",
    "gn:asciiname":"Drevenik",
    "gn:country_code":"SI",
    "gn:dem":584,
    "gn:feature_class":"P",
    "gn:feature_code":"PPL",
    "gn:name":"Drevenik",
    "gn:population":66,
    "gn:timezone":"Europe/Ljubljana",
    "iso:country":"SI",
    "wof:name":"Drevenik",
    "wof:placetype":"locality",
    "wof:population":66
},
  "geometry": {"coordinates":[15.59555,46.27743],"type":"Point"}
}