{
  "type": "Feature",
  "properties": {
    "gn:admin1_code":"39",
    "gn:asciiname":"Male Vrhe",
    "gn:country_code":"SI",
    "gn:dem":575,
    "gn:feature_class":"P",
    "gn:feature_code":"PPL",
    "gn:name":"Male Vrhe",
    "gn:population":26,
    "gn:timezone":"Europe/Ljubljana",
    "iso:country":"SI",
    "name:und_x_variant":[
        "Mali Vrhi",
        "Male Vrhe"
    ],
    "wof:name":"Male Vrhe",
    "wof:placetype":"locality",
    "wof:population":26
},
  "geometry": {"coordinates":[14.76417,45.91833],"type":"Point"}
}