{
  "type": "Feature",
  "properties": {
    "gn:admin1_code":"39",
    "gn:asciiname":"Male Vrhe",
    "gn:country_code":"SI",
    "gn:dem":575,
    "gn:feature_class":"P",
    "gn:feature_code":"PPL",
    "gn:name":"Male Vrhe",
    "gn:population":26,
    "gn:timezone":"Europe/Ljubljana",
    "iso:country":"SI",
    "name:bos_x_preferred":[
        "Male Vrhe"
    ],
    "name:nld_x_preferred":[
        "Male Vrhe"
    ],
    "name:pol_x_preferred":[
        "Male Vrhe"
    ],
    "name:ron_x_preferred":[
        "Male Vrhe"
    ],
    "name:slv_x_preferred":[
        "Male Vrhe"
    ],
    "name:ukr_x_preferred":[
        "\u041c\u0430\u043b\u0435 \u0412\u0440\u0445\u0435"
    ],
    "name:und_x_variant":[
        "Mali Vrhi"
    ],
    "wof:name":"Male Vrhe",
    "wof:placetype":"locality",
    "wof:population":26
},
  "geometry": {"coordinates":[14.76417,45.91833],"type":"Point"}
}