{
  "type": "Feature",
  "properties": {
    "gn:admin1_code":"D8",
    "gn:asciiname":"Gorenje Kalisce",
    "gn:country_code":"SI",
    "gn:dem":778,
    "gn:feature_class":"P",
    "gn:feature_code":"PPL",
    "gn:name":"Gorenje Kali\u0161\u010de",
    "gn:population":5,
    "gn:timezone":"Europe/Ljubljana",
    "iso:country":"SI",
    "name:bos_x_preferred":[
        "Gorenje Kali\u0161\u010de"
    ],
    "name:nld_x_preferred":[
        "Gorenje Kali\u0161\u010de"
    ],
    "name:pol_x_preferred":[
        "Gorenje Kali\u0161\u010de"
    ],
    "name:ron_x_preferred":[
        "Gorenje Kali\u0161\u010de"
    ],
    "name:slv_x_preferred":[
        "Gorenje Kali\u0161\u010de"
    ],
    "name:ukr_x_preferred":[
        "\u0413\u043e\u0440\u0435\u043d\u0454 \u041a\u0430\u043b\u0438\u0449\u0435"
    ],
    "name:und_x_variant":[
        "Gorenje Kali\u0161\u010de"
    ],
    "wof:name":"Gorenje Kalisce",
    "wof:placetype":"locality",
    "wof:population":5
},
  "geometry": {"coordinates":[14.57771,45.8177],"type":"Point"}
}