{
  "type": "Feature",
  "properties": {
    "gn:admin1_code":"O7",
    "gn:asciiname":"Log",
    "gn:country_code":"SI",
    "gn:dem":250,
    "gn:feature_class":"P",
    "gn:feature_code":"PPL",
    "gn:name":"Log",
    "gn:population":38,
    "gn:timezone":"Europe/Ljubljana",
    "iso:country":"SI",
    "wof:name":"Log",
    "wof:placetype":"locality",
    "wof:population":38
},
  "geometry": {"coordinates":[15.10578,45.94275],"type":"Point"}
}