{
  "type": "Feature",
  "properties": {
    "gn:admin1_code":"36",
    "gn:asciiname":"Godovic",
    "gn:country_code":"SI",
    "gn:dem":599,
    "gn:feature_class":"P",
    "gn:feature_code":"PPL",
    "gn:name":"Godovi\u010d",
    "gn:population":704,
    "gn:timezone":"Europe/Ljubljana",
    "iso:country":"SI",
    "name:bos_x_preferred":[
        "Godovi\u010d"
    ],
    "name:ceb_x_preferred":[
        "Godovi\u010d"
    ],
    "name:ita_x_preferred":[
        "Godovici"
    ],
    "name:nld_x_preferred":[
        "Godovi\u010d"
    ],
    "name:pol_x_preferred":[
        "Godovi\u010d"
    ],
    "name:ron_x_preferred":[
        "Godovi\u010d"
    ],
    "name:slv_x_preferred":[
        "Godovi\u010d"
    ],
    "name:ukr_x_preferred":[
        "\u0413\u043e\u0434\u043e\u0432\u0438\u0447"
    ],
    "name:und_x_variant":[
        "Godovitsch",
        "Godovici",
        "Godovi\u010d"
    ],
    "wof:name":"Godovic",
    "wof:placetype":"locality",
    "wof:population":704
},
  "geometry": {"coordinates":[14.09361,45.95778],"type":"Point"}
}