{
  "type": "Feature",
  "properties": {
    "gn:admin1_code":"04",
    "gn:asciiname":"Valica",
    "gn:cc2":"SI",
    "gn:country_code":"SI",
    "gn:dem":86,
    "gn:feature_class":"P",
    "gn:feature_code":"PPL",
    "gn:name":"Valica",
    "gn:population":0,
    "gn:timezone":"Europe/Ljubljana",
    "iso:country":"SI",
    "name:bos_x_preferred":[
        "Valica"
    ],
    "name:fra_x_preferred":[
        "Valica"
    ],
    "name:hrv_x_preferred":[
        "Valica"
    ],
    "name:hun_x_preferred":[
        "Valica"
    ],
    "name:ita_x_preferred":[
        "Valizza"
    ],
    "name:nld_x_preferred":[
        "Valica"
    ],
    "name:slv_x_preferred":[
        "Valica"
    ],
    "name:srp_x_preferred":[
        "\u0412\u0430\u043b\u0438\u0446\u0430"
    ],
    "name:ukr_x_preferred":[
        "\u0412\u0430\u043b\u0438\u0446\u044f"
    ],
    "name:und_x_variant":[
        "Valiza",
        "Valica",
        "Valizza"
    ],
    "wof:name":"Valica",
    "wof:placetype":"locality"
},
  "geometry": {"coordinates":[13.57389,45.4675],"type":"Point"}
}