{
  "type": "Feature",
  "properties": {
    "iso:country":"SI",
    "wof:name":"Zavoglje",
    "wof:placetype":"neighbourhood"
},
  "geometry": {"coordinates":[14.61059179723346,46.04273318057851],"type":"Point"}
}