{
  "type": "Feature",
  "properties": {
    "gn:admin1_code":"O7",
    "gn:asciiname":"Dolenje Zabukovje",
    "gn:country_code":"SI",
    "gn:dem":486,
    "gn:feature_class":"P",
    "gn:feature_code":"PPL",
    "gn:name":"Dolenje Zabukovje",
    "gn:population":22,
    "gn:timezone":"Europe/Ljubljana",
    "iso:country":"SI",
    "name:bos_x_preferred":[
        "Dolenje Zabukovje"
    ],
    "name:hrv_x_preferred":[
        "Dolenje Zabukovje"
    ],
    "name:nld_x_preferred":[
        "Dolenje Zabukovje"
    ],
    "name:pol_x_preferred":[
        "Dolenje Zabukovje"
    ],
    "name:ron_x_preferred":[
        "Dolenje Zabukovje"
    ],
    "name:slv_x_preferred":[
        "Dolenje Zabukovje"
    ],
    "name:ukr_x_preferred":[
        "\u0414\u043e\u043b\u0435\u043d\u0454 \u0417\u0430\u0431\u0443\u043a\u043e\u0432\u0454"
    ],
    "wof:name":"Dolenje Zabukovje",
    "wof:placetype":"locality",
    "wof:population":22
},
  "geometry": {"coordinates":[15.13505,45.91575],"type":"Point"}
}