{
  "type": "Feature",
  "properties": {
    "gn:admin1_code":"O7",
    "gn:asciiname":"Dolenje Zabukovje",
    "gn:country_code":"SI",
    "gn:dem":486,
    "gn:feature_class":"P",
    "gn:feature_code":"PPL",
    "gn:name":"Dolenje Zabukovje",
    "gn:population":22,
    "gn:timezone":"Europe/Ljubljana",
    "iso:country":"SI",
    "wof:name":"Dolenje Zabukovje",
    "wof:placetype":"locality",
    "wof:population":22
},
  "geometry": {"coordinates":[15.13505,45.91575],"type":"Point"}
}