{
  "type": "Feature",
  "properties": {
    "gn:admin1_code":"M6",
    "gn:asciiname":"Murski Petrovci",
    "gn:country_code":"SI",
    "gn:dem":199,
    "gn:feature_class":"P",
    "gn:feature_code":"PPL",
    "gn:name":"Murski Petrovci",
    "gn:population":111,
    "gn:timezone":"Europe/Ljubljana",
    "iso:country":"SI",
    "name:bos_x_preferred":[
        "Murski Petrovci"
    ],
    "name:ceb_x_preferred":[
        "Murski Petrovci"
    ],
    "name:epo_x_preferred":[
        "Murski Petrovci"
    ],
    "name:hrv_x_preferred":[
        "Murski Petrovci"
    ],
    "name:hun_x_preferred":[
        "Murapetr\u00f3c"
    ],
    "name:nld_x_preferred":[
        "Murski Petrovci"
    ],
    "name:pol_x_preferred":[
        "Murski Petrovci"
    ],
    "name:ron_x_preferred":[
        "Murski Petrovci"
    ],
    "name:slv_x_preferred":[
        "Murski Petrovci"
    ],
    "name:ukr_x_preferred":[
        "\u041c\u0443\u0440\u0441\u044c\u043a\u0456 \u041f\u0435\u0442\u0440\u043e\u0432\u0446\u0456"
    ],
    "name:und_x_variant":[
        "Murapetr\u00f3cz",
        "Petrovci"
    ],
    "wof:name":"Murski Petrovci",
    "wof:placetype":"locality",
    "wof:population":111
},
  "geometry": {"coordinates":[16.05556,46.66611],"type":"Point"}
}