{
  "type": "Feature",
  "properties": {
    "gn:admin1_code":"O3",
    "gn:asciiname":"Rzisce",
    "gn:country_code":"SI",
    "gn:dem":482,
    "gn:feature_class":"P",
    "gn:feature_code":"PPL",
    "gn:name":"R\u017ei\u0161\u010de",
    "gn:population":17,
    "gn:timezone":"Europe/Ljubljana",
    "iso:country":"SI",
    "name:und_x_variant":[
        "R\u017ei\u0161\u010de"
    ],
    "wof:name":"Rzisce",
    "wof:placetype":"locality",
    "wof:population":17
},
  "geometry": {"coordinates":[15.38326,45.82027],"type":"Point"}
}