{
  "type": "Feature",
  "properties": {
    "gn:population":250,
    "iso:country":"SI",
    "name:ceb_x_preferred":[
        "Makole"
    ],
    "name:ces_x_preferred":[
        "Ob\u010dina Makole"
    ],
    "name:che_x_preferred":[
        "\u041c\u0430\u043a\u043e\u043b\u0435"
    ],
    "name:cym_x_preferred":[
        "Bwrdeistref Makole"
    ],
    "name:deu_x_preferred":[
        "Makole"
    ],
    "name:eng_x_preferred":[
        "Makole Municipality"
    ],
    "name:epo_x_preferred":[
        "Ob\u010dina Makole"
    ],
    "name:fas_x_preferred":[
        "\u0634\u0647\u0631\u062f\u0627\u0631\u06cc \u0645\u0627\u06a9\u0648\u0644\u0647"
    ],
    "name:fra_x_preferred":[
        "Makole"
    ],
    "name:hbs_x_preferred":[
        "Op\u0107ina Makole"
    ],
    "name:hrv_x_preferred":[
        "Op\u0107ina Makole"
    ],
    "name:ind_x_preferred":[
        "Munisipalitas Makole"
    ],
    "name:ita_x_preferred":[
        "Makole"
    ],
    "name:jpn_x_preferred":[
        "\u30de\u30b3\u30ec"
    ],
    "name:kor_x_preferred":[
        "\ub9c8\ucf5c\ub808"
    ],
    "name:nan_x_preferred":[
        "Makole Kong-si\u0101"
    ],
    "name:nld_x_preferred":[
        "Makole"
    ],
    "name:pol_x_preferred":[
        "Gmina Makole"
    ],
    "name:por_x_preferred":[
        "Makole"
    ],
    "name:ron_x_preferred":[
        "Comuna Makole"
    ],
    "name:rus_x_preferred":[
        "\u041c\u0430\u043a\u043e\u043b\u0435"
    ],
    "name:slv_x_preferred":[
        "Ob\u010dina Makole"
    ],
    "name:tat_x_preferred":[
        "\u041c\u0430\u043a\u043e\u043b\u0435"
    ],
    "name:tha_x_preferred":[
        "\u0e40\u0e17\u0e28\u0e1a\u0e32\u0e25\u0e21\u0e32\u0e01\u0e2d\u0e41\u0e25"
    ],
    "name:ukr_x_preferred":[
        "\u041c\u0430\u043a\u043e\u043b\u0435"
    ],
    "name:vec_x_preferred":[
        "Makole"
    ],
    "name:vie_x_preferred":[
        "Makole"
    ],
    "name:zho_x_preferred":[
        "\u99ac\u79d1\u840a"
    ],
    "qs:a0":"Slovenija",
    "qs:a1":"*",
    "qs:a1r":"0",
    "qs:adm0":"Slovenija",
    "qs:la_lc":"*",
    "qs:level":"locality",
    "qs:loc":"Makole",
    "qs:loc_alt":"Makole",
    "qs:pop":0,
    "qs:type":"buffered point",
    "wd:wordcount":150,
    "wof:name":"Makole",
    "wof:placetype":"locality",
    "wof:population":250
},
  "geometry": {"coordinates":[15.668625,46.318016],"type":"Point"}
}