{
  "type": "Feature",
  "properties": {
    "gn:admin1_code":"L9",
    "gn:asciiname":"Mala Kostrevnica",
    "gn:country_code":"SI",
    "gn:dem":325,
    "gn:feature_class":"P",
    "gn:feature_code":"PPL",
    "gn:name":"Mala Kostrevnica",
    "gn:population":242,
    "gn:timezone":"Europe/Ljubljana",
    "iso:country":"SI",
    "wof:name":"Mala Kostrevnica",
    "wof:placetype":"locality",
    "wof:population":242
},
  "geometry": {"coordinates":[14.86667,46.03333],"type":"Point"}
}