{
  "type": "Feature",
  "properties": {
    "gn:admin1_code":"L9",
    "gn:asciiname":"Mala Kostrevnica",
    "gn:country_code":"SI",
    "gn:dem":325,
    "gn:feature_class":"P",
    "gn:feature_code":"PPL",
    "gn:name":"Mala Kostrevnica",
    "gn:population":242,
    "gn:timezone":"Europe/Ljubljana",
    "iso:country":"SI",
    "name:bos_x_preferred":[
        "Mala Kostrevnica"
    ],
    "name:ceb_x_preferred":[
        "Mala Kostrevnica"
    ],
    "name:nld_x_preferred":[
        "Mala Kostrevnica"
    ],
    "name:pol_x_preferred":[
        "Mala Kostrevnica"
    ],
    "name:ron_x_preferred":[
        "Mala Kostrevnica"
    ],
    "name:slv_x_preferred":[
        "Mala Kostrevnica"
    ],
    "name:ukr_x_preferred":[
        "\u041c\u0430\u043b\u0430 \u041a\u043e\u0441\u0442\u0440\u0435\u0432\u043d\u0438\u0446\u044f"
    ],
    "wof:name":"Mala Kostrevnica",
    "wof:placetype":"locality",
    "wof:population":242
},
  "geometry": {"coordinates":[14.86667,46.03333],"type":"Point"}
}