{
  "type": "Feature",
  "properties": {
    "gn:admin1_code":"N4",
    "gn:asciiname":"Vologa",
    "gn:country_code":"SI",
    "gn:dem":687,
    "gn:feature_class":"P",
    "gn:feature_code":"PPL",
    "gn:name":"Vologa",
    "gn:population":41,
    "gn:timezone":"Europe/Ljubljana",
    "iso:country":"SI",
    "name:hrv_x_preferred":[
        "Vologa"
    ],
    "name:nld_x_preferred":[
        "Vologa"
    ],
    "name:pol_x_preferred":[
        "Vologa"
    ],
    "name:ron_x_preferred":[
        "Vologa"
    ],
    "name:slv_x_preferred":[
        "Vologa"
    ],
    "name:ukr_x_preferred":[
        "\u0412\u043e\u043b\u043e\u0433\u0430"
    ],
    "wof:name":"Vologa",
    "wof:placetype":"locality",
    "wof:population":41
},
  "geometry": {"coordinates":[14.90972,46.25686],"type":"Point"}
}