{
  "type": "Feature",
  "properties": {
    "gn:admin1_code":"B6",
    "gn:asciiname":"Vrh pri Bostanju",
    "gn:country_code":"SI",
    "gn:dem":443,
    "gn:feature_class":"P",
    "gn:feature_code":"PPL",
    "gn:name":"Vrh pri Bo\u0161tanju",
    "gn:population":200,
    "gn:timezone":"Europe/Ljubljana",
    "iso:country":"SI",
    "name:bos_x_preferred":[
        "Vrh pri Bo\u0161tanju"
    ],
    "name:ceb_x_preferred":[
        "Vrh pri Bo\u0161tanju"
    ],
    "name:nld_x_preferred":[
        "Vrh pri Bo\u0161tanju"
    ],
    "name:pol_x_preferred":[
        "Vrh pri Bo\u0161tanju"
    ],
    "name:ron_x_preferred":[
        "Vrh pri Bo\u0161tanju"
    ],
    "name:slv_x_preferred":[
        "Vrh pri Bo\u0161tanju"
    ],
    "name:ukr_x_preferred":[
        "\u0412\u0440\u0445-\u043f\u0440\u0438-\u0411\u043e\u0448\u0442\u0430\u043d\u044e"
    ],
    "name:und_x_variant":[
        "Vrh pri Bo\u0161tanju"
    ],
    "wof:name":"Vrh pri Bostanju",
    "wof:placetype":"locality",
    "wof:population":200
},
  "geometry": {"coordinates":[15.24984,46.0043],"type":"Point"}
}