{
  "type": "Feature",
  "properties": {
    "gn:admin1_code":"B6",
    "gn:asciiname":"Vrh pri Bostanju",
    "gn:country_code":"SI",
    "gn:dem":443,
    "gn:feature_class":"P",
    "gn:feature_code":"PPL",
    "gn:name":"Vrh pri Bo\u0161tanju",
    "gn:population":200,
    "gn:timezone":"Europe/Ljubljana",
    "iso:country":"SI",
    "name:und_x_variant":[
        "Vrh pri Bo\u0161tanju"
    ],
    "wof:name":"Vrh pri Bostanju",
    "wof:placetype":"locality",
    "wof:population":200
},
  "geometry": {"coordinates":[15.24984,46.0043],"type":"Point"}
}