{
  "type": "Feature",
  "properties": {
    "gn:admin1_code":"L8",
    "gn:asciiname":"Kostanjevec",
    "gn:country_code":"SI",
    "gn:dem":333,
    "gn:feature_class":"P",
    "gn:feature_code":"PPL",
    "gn:name":"Kostanjevec",
    "gn:population":326,
    "gn:timezone":"Europe/Ljubljana",
    "iso:country":"SI",
    "name:bos_x_preferred":[
        "Kostanjevec"
    ],
    "name:ceb_x_preferred":[
        "Kostanjevec"
    ],
    "name:nld_x_preferred":[
        "Kostanjevec"
    ],
    "name:pol_x_preferred":[
        "Kostanjevec"
    ],
    "name:ron_x_preferred":[
        "Kostanjevec"
    ],
    "name:slv_x_preferred":[
        "Kostanjevec"
    ],
    "name:ukr_x_preferred":[
        "\u041a\u043e\u0441\u0442\u0430\u043d\u0454\u0432\u0435\u0446\u044c"
    ],
    "wof:name":"Kostanjevec",
    "wof:placetype":"locality",
    "wof:population":326
},
  "geometry": {"coordinates":[15.51935,46.39484],"type":"Point"}
}