{
  "type": "Feature",
  "properties": {
    "gn:admin1_code":"L8",
    "gn:asciiname":"Kostanjevec",
    "gn:country_code":"SI",
    "gn:dem":333,
    "gn:feature_class":"P",
    "gn:feature_code":"PPL",
    "gn:name":"Kostanjevec",
    "gn:population":326,
    "gn:timezone":"Europe/Ljubljana",
    "iso:country":"SI",
    "wof:name":"Kostanjevec",
    "wof:placetype":"locality",
    "wof:population":326
},
  "geometry": {"coordinates":[15.51935,46.39484],"type":"Point"}
}