{
  "type": "Feature",
  "properties": {
    "gn:admin1_code":"91",
    "gn:asciiname":"Velika Pristava",
    "gn:country_code":"SI",
    "gn:dem":450,
    "gn:feature_class":"P",
    "gn:feature_code":"PPL",
    "gn:name":"Velika Pristava",
    "gn:population":57,
    "gn:timezone":"Europe/Ljubljana",
    "iso:country":"SI",
    "name:und_x_variant":[
        "Prestava Grande",
        "Velika Pristava"
    ],
    "wof:name":"Velika Pristava",
    "wof:placetype":"locality",
    "wof:population":57
},
  "geometry": {"coordinates":[14.18528,45.65694000000001],"type":"Point"}
}