{
  "type": "Feature",
  "properties": {
    "gn:admin1_code":"91",
    "gn:asciiname":"Velika Pristava",
    "gn:country_code":"SI",
    "gn:dem":450,
    "gn:feature_class":"P",
    "gn:feature_code":"PPL",
    "gn:name":"Velika Pristava",
    "gn:population":57,
    "gn:timezone":"Europe/Ljubljana",
    "iso:country":"SI",
    "name:bos_x_preferred":[
        "Velika Pristava"
    ],
    "name:fas_x_preferred":[
        "\u0648\u0644\u06cc\u06a9\u0627 \u067e\u0631\u06cc\u0633\u062a\u0648\u0627"
    ],
    "name:hrv_x_preferred":[
        "Velika Pristava"
    ],
    "name:nld_x_preferred":[
        "Velika Pristava"
    ],
    "name:pol_x_preferred":[
        "Velika Pristava"
    ],
    "name:ron_x_preferred":[
        "Velika Pristava"
    ],
    "name:slv_x_preferred":[
        "Velika Pristava"
    ],
    "name:ukr_x_preferred":[
        "\u0412\u0435\u043b\u0438\u043a\u0430 \u041f\u0440\u0438\u0441\u0442\u0430\u0432\u0430"
    ],
    "name:und_x_variant":[
        "Prestava Grande"
    ],
    "wof:name":"Velika Pristava",
    "wof:placetype":"locality",
    "wof:population":57
},
  "geometry": {"coordinates":[14.18528,45.65694000000001],"type":"Point"}
}