{
  "type": "Feature",
  "properties": {
    "gn:admin1_code":"H6",
    "gn:asciiname":"Bela Pec",
    "gn:country_code":"SI",
    "gn:dem":724,
    "gn:feature_class":"P",
    "gn:feature_code":"PPL",
    "gn:name":"Bela Pe\u010d",
    "gn:population":23,
    "gn:timezone":"Europe/Ljubljana",
    "iso:country":"SI",
    "name:bos_x_preferred":[
        "Bela Pe\u010d"
    ],
    "name:pol_x_preferred":[
        "Bela Pe\u010d"
    ],
    "name:ron_x_preferred":[
        "Bela Pe\u010d"
    ],
    "name:slv_x_preferred":[
        "Bela Pe\u010d"
    ],
    "name:tha_x_preferred":[
        "\u0e40\u0e1a\u0e25\u0e32\u0e40\u0e1e\u0e0a"
    ],
    "name:ukr_x_preferred":[
        "\u0411\u0435\u043b\u0430 \u041f\u0435\u0447"
    ],
    "wof:name":"Bela Pec",
    "wof:placetype":"locality",
    "wof:population":23
},
  "geometry": {"coordinates":[14.71781,46.2487],"type":"Point"}
}