{
  "type": "Feature",
  "properties": {
    "gn:admin1_code":"H6",
    "gn:asciiname":"Bela Pec",
    "gn:country_code":"SI",
    "gn:dem":724,
    "gn:feature_class":"P",
    "gn:feature_code":"PPL",
    "gn:name":"Bela Pe\u010d",
    "gn:population":23,
    "gn:timezone":"Europe/Ljubljana",
    "iso:country":"SI",
    "name:und_x_variant":[
        "Bela Pe\u010d"
    ],
    "wof:name":"Bela Pec",
    "wof:placetype":"locality",
    "wof:population":23
},
  "geometry": {"coordinates":[14.71781,46.2487],"type":"Point"}
}