{
  "type": "Feature",
  "properties": {
    "gn:admin1_code":"C5",
    "gn:asciiname":"Sentvid pri Grobelnem",
    "gn:country_code":"SI",
    "gn:dem":272,
    "gn:feature_class":"P",
    "gn:feature_code":"PPL",
    "gn:name":"\u0160entvid pri Grobelnem",
    "gn:population":198,
    "gn:timezone":"Europe/Ljubljana",
    "iso:country":"SI",
    "name:und_x_variant":[
        "\u0160entvid pri Grobelnem"
    ],
    "wof:name":"Sentvid pri Grobelnem",
    "wof:placetype":"locality",
    "wof:population":198
},
  "geometry": {"coordinates":[15.46053,46.22525],"type":"Point"}
}