{
  "type": "Feature",
  "properties": {
    "gn:admin1_code":"C5",
    "gn:asciiname":"Sentvid pri Grobelnem",
    "gn:country_code":"SI",
    "gn:dem":272,
    "gn:feature_class":"P",
    "gn:feature_code":"PPL",
    "gn:name":"\u0160entvid pri Grobelnem",
    "gn:population":198,
    "gn:timezone":"Europe/Ljubljana",
    "iso:country":"SI",
    "name:bos_x_preferred":[
        "\u0160entvid pri Grobelnem"
    ],
    "name:ceb_x_preferred":[
        "\u0160entvid pri Grobelnem"
    ],
    "name:hrv_x_preferred":[
        "\u0160entvid pri Grobelnem"
    ],
    "name:nld_x_preferred":[
        "\u0160entvid pri Grobelnem"
    ],
    "name:pol_x_preferred":[
        "\u0160entvid pri Grobelnem"
    ],
    "name:ron_x_preferred":[
        "\u0160entvid pri Grobelnem"
    ],
    "name:slv_x_preferred":[
        "\u0160entvid pri Grobelnem"
    ],
    "name:ukr_x_preferred":[
        "\u0428\u0435\u043d\u0442\u0432\u0438\u0434-\u043f\u0440\u0438-\u0413\u0440\u043e\u0431\u0435\u043b\u043d\u0435\u043c"
    ],
    "wof:name":"Sentvid pri Grobelnem",
    "wof:placetype":"locality",
    "wof:population":198
},
  "geometry": {"coordinates":[15.46053,46.22525],"type":"Point"}
}