{
  "type": "Feature",
  "properties": {
    "gn:admin1_code":"26",
    "gn:asciiname":"Spodnja Korena",
    "gn:country_code":"SI",
    "gn:dem":326,
    "gn:feature_class":"P",
    "gn:feature_code":"PPL",
    "gn:name":"Spodnja Korena",
    "gn:population":414,
    "gn:timezone":"Europe/Ljubljana",
    "iso:country":"SI",
    "wof:name":"Spodnja Korena",
    "wof:placetype":"locality",
    "wof:population":414
},
  "geometry": {"coordinates":[15.76955,46.51192],"type":"Point"}
}