{
  "type": "Feature",
  "properties": {
    "gn:admin1_code":"26",
    "gn:asciiname":"Spodnja Korena",
    "gn:country_code":"SI",
    "gn:dem":326,
    "gn:feature_class":"P",
    "gn:feature_code":"PPL",
    "gn:name":"Spodnja Korena",
    "gn:population":414,
    "gn:timezone":"Europe/Ljubljana",
    "iso:country":"SI",
    "name:bos_x_preferred":[
        "Spodnja Korena"
    ],
    "name:ceb_x_preferred":[
        "Spodnja Korena"
    ],
    "name:nld_x_preferred":[
        "Spodnja Korena"
    ],
    "name:pol_x_preferred":[
        "Spodnja Korena"
    ],
    "name:ron_x_preferred":[
        "Spodnja Korena"
    ],
    "name:slv_x_preferred":[
        "Spodnja Korena"
    ],
    "name:ukr_x_preferred":[
        "\u0421\u043f\u043e\u0434\u043d\u044f \u041a\u043e\u0440\u0435\u043d\u0430"
    ],
    "wof:name":"Spodnja Korena",
    "wof:placetype":"locality",
    "wof:population":414
},
  "geometry": {"coordinates":[15.76955,46.51192],"type":"Point"}
}