{
  "type": "Feature",
  "properties": {
    "gn:gn_country":"SI",
    "gn:gn_fcode":"PPL",
    "gn:gn_pop":0,
    "gn:population":505,
    "iso:country":"SI",
    "name:dut_x_preferred":[
        "Srednja vas v Bohinju"
    ],
    "name:eng_x_preferred":[
        "Srednja Vas v Bohinju"
    ],
    "name:hrv_x_preferred":[
        "Srednja vas v Bohinju"
    ],
    "name:rum_x_preferred":[
        "Srednja vas v Bohinju"
    ],
    "name:slv_x_preferred":[
        "Srednja vas v Bohinju"
    ],
    "name:ukr_x_preferred":[
        "\u0421\u0440\u0435\u0434\u043d\u044f \u0412\u0430\u0441 \u0432 \u0411\u043e\u0445\u0456\u043d\u044e"
    ],
    "name:unk_x_variant":[
        "Srednja Vas"
    ],
    "qs_pg:aaroncc":"SI",
    "qs_pg:gn_country":"SI",
    "qs_pg:gn_fcode":"PPL",
    "qs_pg:gn_pop":0,
    "qs_pg:name":"Srednja Vas V Bohinju",
    "qs_pg:name_adm0":"Slovenija",
    "qs_pg:name_adm1":"Radovljica",
    "qs_pg:photos":247,
    "qs_pg:photos_1k":50,
    "qs_pg:photos_9k":1,
    "qs_pg:photos_9r":4,
    "qs_pg:photos_all":247,
    "qs_pg:photos_sr":4,
    "qs_pg:pop_sr":0,
    "qs_pg:qs_pg_placetype":"locality",
    "qs_pg:qs_pg_placetype_gp":"Town",
    "qs_pg:woe_adm0":23424945,
    "woe:adm0_id":23424945,
    "woe:name_adm0":"Slovenija",
    "woe:name_adm1":"Radovljica",
    "woe:placetype":"Town",
    "wof:name":"Srednja Vas V Bohinju",
    "wof:placetype":"locality",
    "wof:population":505
},
  "geometry": {"coordinates":[13.92556,46.29702],"type":"Point"}
}