{
  "type": "Feature",
  "properties": {
    "gn:admin1_code":"04",
    "gn:asciiname":"Podjelje",
    "gn:country_code":"SI",
    "gn:dem":1038,
    "gn:feature_class":"P",
    "gn:feature_code":"PPL",
    "gn:name":"Podjelje",
    "gn:population":67,
    "gn:timezone":"Europe/Ljubljana",
    "iso:country":"SI",
    "wof:name":"Podjelje",
    "wof:placetype":"locality",
    "wof:population":67
},
  "geometry": {"coordinates":[13.96667,46.31667],"type":"Point"}
}