{
  "type": "Feature",
  "properties": {
    "gn:admin1_code":"04",
    "gn:asciiname":"Podjelje",
    "gn:country_code":"SI",
    "gn:dem":1038,
    "gn:feature_class":"P",
    "gn:feature_code":"PPL",
    "gn:name":"Podjelje",
    "gn:population":67,
    "gn:timezone":"Europe/Ljubljana",
    "iso:country":"SI",
    "name:bos_x_preferred":[
        "Podjelje"
    ],
    "name:hrv_x_preferred":[
        "Podjelje"
    ],
    "name:ita_x_preferred":[
        "Podjelje"
    ],
    "name:nld_x_preferred":[
        "Podjelje"
    ],
    "name:pol_x_preferred":[
        "Podjelje"
    ],
    "name:ron_x_preferred":[
        "Podjelje"
    ],
    "name:slv_x_preferred":[
        "Podjelje"
    ],
    "name:ukr_x_preferred":[
        "\u041f\u043e\u0434\u0454\u043b\u0454"
    ],
    "wof:name":"Podjelje",
    "wof:placetype":"locality",
    "wof:population":67
},
  "geometry": {"coordinates":[13.96667,46.31667],"type":"Point"}
}