{
  "type": "Feature",
  "properties": {
    "gn:admin1_code":"F6",
    "gn:asciiname":"Veliki Vrh",
    "gn:country_code":"SI",
    "gn:dem":815,
    "gn:feature_class":"P",
    "gn:feature_code":"PPL",
    "gn:name":"Veliki Vrh",
    "gn:population":57,
    "gn:timezone":"Europe/Ljubljana",
    "iso:country":"SI",
    "wof:name":"Veliki Vrh",
    "wof:placetype":"locality",
    "wof:population":57
},
  "geometry": {"coordinates":[14.52822,45.77645],"type":"Point"}
}