{
  "type": "Feature",
  "properties": {
    "gn:admin1_code":"08",
    "gn:asciiname":"Pesjak",
    "gn:country_code":"SI",
    "gn:dem":212,
    "gn:feature_class":"P",
    "gn:feature_code":"PPL",
    "gn:name":"Pesjak",
    "gn:population":0,
    "gn:timezone":"Europe/Ljubljana",
    "iso:country":"SI",
    "name:und_x_variant":[
        "Pesnjak",
        "Pesjak"
    ],
    "wof:name":"Pesjak",
    "wof:placetype":"locality"
},
  "geometry": {"coordinates":[15.66667,45.96667],"type":"Point"}
}