{
  "type": "Feature",
  "properties": {
    "gn:admin1_code":"57",
    "gn:asciiname":"Lahomsek",
    "gn:country_code":"SI",
    "gn:dem":354,
    "gn:feature_class":"P",
    "gn:feature_code":"PPL",
    "gn:name":"Lahom\u0161ek",
    "gn:population":109,
    "gn:timezone":"Europe/Ljubljana",
    "iso:country":"SI",
    "name:und_x_variant":[
        "Lahom\u0161ek"
    ],
    "wof:name":"Lahomsek",
    "wof:placetype":"locality",
    "wof:population":109
},
  "geometry": {"coordinates":[15.25086,46.14942],"type":"Point"}
}