{
  "type": "Feature",
  "properties": {
    "gn:admin1_code":"57",
    "gn:asciiname":"Lahomsek",
    "gn:country_code":"SI",
    "gn:dem":354,
    "gn:feature_class":"P",
    "gn:feature_code":"PPL",
    "gn:name":"Lahom\u0161ek",
    "gn:population":109,
    "gn:timezone":"Europe/Ljubljana",
    "iso:country":"SI",
    "name:bos_x_preferred":[
        "Lahom\u0161ek"
    ],
    "name:ceb_x_preferred":[
        "Lahom\u0161ek"
    ],
    "name:hrv_x_preferred":[
        "Lahom\u0161ek"
    ],
    "name:nld_x_preferred":[
        "Lahom\u0161ek"
    ],
    "name:pol_x_preferred":[
        "Lahom\u0161ek"
    ],
    "name:ron_x_preferred":[
        "Lahom\u0161ek"
    ],
    "name:slv_x_preferred":[
        "Lahom\u0161ek"
    ],
    "name:ukr_x_preferred":[
        "\u041b\u0430\u0445\u043e\u043c\u0448\u0435\u043a"
    ],
    "name:und_x_variant":[
        "Lahom\u0161ek"
    ],
    "name:urd_x_preferred":[
        "\u0644\u0627\u06c1\u0648\u0645\u0634\u06cc\u06a9"
    ],
    "wof:name":"Lahomsek",
    "wof:placetype":"locality",
    "wof:population":109
},
  "geometry": {"coordinates":[15.25086,46.14942],"type":"Point"}
}