{
  "type": "Feature",
  "properties": {
    "gn:admin1_code":"51",
    "gn:asciiname":"Podsreda",
    "gn:country_code":"SI",
    "gn:dem":252,
    "gn:feature_class":"P",
    "gn:feature_code":"PPL",
    "gn:name":"Podsreda",
    "gn:population":191,
    "gn:timezone":"Europe/Ljubljana",
    "iso:country":"SI",
    "wof:name":"Podsreda",
    "wof:placetype":"locality",
    "wof:population":191
},
  "geometry": {"coordinates":[15.59056,46.04139],"type":"Point"}
}