{
  "type": "Feature",
  "properties": {
    "gn:admin1_code":"51",
    "gn:asciiname":"Podsreda",
    "gn:country_code":"SI",
    "gn:dem":252,
    "gn:feature_class":"P",
    "gn:feature_code":"PPL",
    "gn:name":"Podsreda",
    "gn:population":191,
    "gn:timezone":"Europe/Ljubljana",
    "iso:country":"SI",
    "name:bos_x_preferred":[
        "Podsreda"
    ],
    "name:cat_x_preferred":[
        "Podsreda"
    ],
    "name:ceb_x_preferred":[
        "Podsreda"
    ],
    "name:hrv_x_preferred":[
        "Podsreda"
    ],
    "name:hun_x_preferred":[
        "Podsreda"
    ],
    "name:ita_x_preferred":[
        "Podsreda"
    ],
    "name:kor_x_preferred":[
        "\ud3ec\ub4dc\uc2a4\ub808\ub2e4"
    ],
    "name:nld_x_preferred":[
        "Podsreda"
    ],
    "name:pol_x_preferred":[
        "Podsreda"
    ],
    "name:ron_x_preferred":[
        "Podsreda"
    ],
    "name:slv_x_preferred":[
        "Podsreda"
    ],
    "name:spa_x_preferred":[
        "Podsreda"
    ],
    "name:ukr_x_preferred":[
        "\u041f\u043e\u0434\u0441\u0440\u0435\u0434\u0430"
    ],
    "wof:name":"Podsreda",
    "wof:placetype":"locality",
    "wof:population":191
},
  "geometry": {"coordinates":[15.59056,46.04139],"type":"Point"}
}