{
  "type": "Feature",
  "properties": {
    "gn:admin1_code":"87",
    "gn:asciiname":"Lacaves",
    "gn:country_code":"SI",
    "gn:dem":219,
    "gn:feature_class":"P",
    "gn:feature_code":"PPL",
    "gn:name":"La\u010daves",
    "gn:population":129,
    "gn:timezone":"Europe/Ljubljana",
    "iso:country":"SI",
    "name:und_x_variant":[
        "La\u010daves"
    ],
    "wof:name":"Lacaves",
    "wof:placetype":"locality",
    "wof:population":129
},
  "geometry": {"coordinates":[16.2444,46.45143],"type":"Point"}
}