{
  "type": "Feature",
  "properties": {
    "gn:admin1_code":"87",
    "gn:asciiname":"Lacaves",
    "gn:country_code":"SI",
    "gn:dem":219,
    "gn:feature_class":"P",
    "gn:feature_code":"PPL",
    "gn:name":"La\u010daves",
    "gn:population":129,
    "gn:timezone":"Europe/Ljubljana",
    "iso:country":"SI",
    "name:bos_x_preferred":[
        "La\u010daves"
    ],
    "name:bul_x_preferred":[
        "\u041b\u0430\u0447\u0430\u0432\u0435\u0441"
    ],
    "name:ceb_x_preferred":[
        "La\u010daves"
    ],
    "name:nld_x_preferred":[
        "La\u010daves"
    ],
    "name:pol_x_preferred":[
        "La\u010daves"
    ],
    "name:ron_x_preferred":[
        "La\u010daves"
    ],
    "name:slv_x_preferred":[
        "La\u010daves"
    ],
    "name:ukr_x_preferred":[
        "\u041b\u0430\u0447\u0430\u0432\u0435\u0441"
    ],
    "name:urd_x_preferred":[
        "\u0644\u0627\u0686\u0627\u0648\u06cc\u0633"
    ],
    "wof:name":"Lacaves",
    "wof:placetype":"locality",
    "wof:population":129
},
  "geometry": {"coordinates":[16.2444,46.45143],"type":"Point"}
}