{
  "type": "Feature",
  "properties": {
    "gn:admin1_code":"91",
    "gn:asciiname":"Ribnica",
    "gn:country_code":"SI",
    "gn:dem":492,
    "gn:feature_class":"P",
    "gn:feature_code":"PPL",
    "gn:name":"Ribnica",
    "gn:population":14,
    "gn:timezone":"Europe/Ljubljana",
    "iso:country":"SI",
    "name:bos_x_preferred":[
        "Ribnica"
    ],
    "name:heb_x_preferred":[
        "\u05e8\u05d9\u05d1\u05e0\u05d9\u05e7\u05d4"
    ],
    "name:hrv_x_preferred":[
        "Ribnica"
    ],
    "name:nld_x_preferred":[
        "Ribnica"
    ],
    "name:pol_x_preferred":[
        "Ribnica"
    ],
    "name:ron_x_preferred":[
        "Ribnica"
    ],
    "name:slv_x_preferred":[
        "Ribnica"
    ],
    "name:ukr_x_preferred":[
        "\u0420\u0438\u0431\u043d\u0438\u0446\u044f"
    ],
    "name:und_x_variant":[
        "Ribbenizza",
        "Ribenizza"
    ],
    "wof:name":"Ribnica",
    "wof:placetype":"locality",
    "wof:population":14
},
  "geometry": {"coordinates":[14.16528,45.63222],"type":"Point"}
}