{
  "type": "Feature",
  "properties": {
    "gn:admin1_code":"H3",
    "gn:asciiname":"Samotorica",
    "gn:country_code":"SI",
    "gn:dem":713,
    "gn:feature_class":"P",
    "gn:feature_code":"PPL",
    "gn:name":"Samotorica",
    "gn:population":66,
    "gn:timezone":"Europe/Ljubljana",
    "iso:country":"SI",
    "wof:name":"Samotorica",
    "wof:placetype":"locality",
    "wof:population":66
},
  "geometry": {"coordinates":[14.26285,46.03544],"type":"Point"}
}