{
  "type": "Feature",
  "properties": {
    "gn:admin1_code":"H3",
    "gn:asciiname":"Samotorica",
    "gn:country_code":"SI",
    "gn:dem":713,
    "gn:feature_class":"P",
    "gn:feature_code":"PPL",
    "gn:name":"Samotorica",
    "gn:population":66,
    "gn:timezone":"Europe/Ljubljana",
    "iso:country":"SI",
    "name:bos_x_preferred":[
        "Samotorica"
    ],
    "name:nld_x_preferred":[
        "Samotorica"
    ],
    "name:pol_x_preferred":[
        "Samotorica"
    ],
    "name:ron_x_preferred":[
        "Samotorica"
    ],
    "name:slv_x_preferred":[
        "Samotorica"
    ],
    "name:ukr_x_preferred":[
        "\u0421\u0430\u043c\u043e\u0442\u043e\u0440\u0438\u0446\u044f"
    ],
    "wof:name":"Samotorica",
    "wof:placetype":"locality",
    "wof:population":66
},
  "geometry": {"coordinates":[14.26285,46.03544],"type":"Point"}
}