{
  "type": "Feature",
  "properties": {
    "gn:admin1_code":"N9",
    "gn:asciiname":"Mahovci",
    "gn:country_code":"SI",
    "gn:dem":221,
    "gn:feature_class":"P",
    "gn:feature_code":"PPL",
    "gn:name":"Mahovci",
    "gn:population":110,
    "gn:timezone":"Europe/Ljubljana",
    "iso:country":"SI",
    "name:bos_x_preferred":[
        "Mahovci"
    ],
    "name:ceb_x_preferred":[
        "Mahovci"
    ],
    "name:ces_x_preferred":[
        "Mahovci"
    ],
    "name:hrv_x_preferred":[
        "Mahovci"
    ],
    "name:nld_x_preferred":[
        "Mahovci"
    ],
    "name:pol_x_preferred":[
        "Mahovci"
    ],
    "name:ron_x_preferred":[
        "Mahovci"
    ],
    "name:slv_x_preferred":[
        "Mahovci"
    ],
    "name:ukr_x_preferred":[
        "\u041c\u0430\u0445\u043e\u0432\u0446\u0456"
    ],
    "wof:name":"Mahovci",
    "wof:placetype":"locality",
    "wof:population":110
},
  "geometry": {"coordinates":[15.87906,46.68602],"type":"Point"}
}