{
  "type": "Feature",
  "properties": {
    "gn:admin1_code":"N3",
    "gn:asciiname":"Bezovica",
    "gn:country_code":"SI",
    "gn:dem":336,
    "gn:feature_class":"P",
    "gn:feature_code":"PPL",
    "gn:name":"Bezovica",
    "gn:population":42,
    "gn:timezone":"Europe/Ljubljana",
    "iso:country":"SI",
    "name:bos_x_preferred":[
        "Bezovica"
    ],
    "name:nld_x_preferred":[
        "Bezovica"
    ],
    "name:pol_x_preferred":[
        "Bezovica"
    ],
    "name:ron_x_preferred":[
        "Bezovica"
    ],
    "name:slv_x_preferred":[
        "Bezovica"
    ],
    "name:ukr_x_preferred":[
        "\u0411\u0435\u0437\u043e\u0432\u0438\u0446\u044f"
    ],
    "wof:name":"Bezovica",
    "wof:placetype":"locality",
    "wof:population":42
},
  "geometry": {"coordinates":[15.34804,46.29214],"type":"Point"}
}