{
  "type": "Feature",
  "properties": {
    "gn:admin1_code":"N3",
    "gn:asciiname":"Bezovica",
    "gn:country_code":"SI",
    "gn:dem":336,
    "gn:feature_class":"P",
    "gn:feature_code":"PPL",
    "gn:name":"Bezovica",
    "gn:population":42,
    "gn:timezone":"Europe/Ljubljana",
    "iso:country":"SI",
    "wof:name":"Bezovica",
    "wof:placetype":"locality",
    "wof:population":42
},
  "geometry": {"coordinates":[15.34804,46.29214],"type":"Point"}
}