{
  "type": "Feature",
  "properties": {
    "gn:gn_country":"SI",
    "gn:gn_fcode":"PPL",
    "gn:gn_pop":0,
    "gn:population":256,
    "iso:country":"SI",
    "name:bul_x_preferred":[
        "\u041c\u0438\u043a\u043b\u0430\u0432\u0436 \u043f\u0440\u0438 \u041e\u0440\u043c\u043e\u0436\u0443"
    ],
    "name:deu_x_preferred":[
        "Miklav\u017e pri Ormo\u017eu"
    ],
    "name:eng_x_preferred":[
        "Miklav\u017e pri Ormo\u017eu"
    ],
    "name:hun_x_preferred":[
        "Miklav\u017e pri Ormo\u017eu"
    ],
    "name:nld_x_preferred":[
        "Miklav\u017e pri Ormo\u017eu"
    ],
    "name:ron_x_preferred":[
        "Miklav\u017e pri Ormo\u017eu"
    ],
    "name:slv_x_preferred":[
        "Miklav\u017e pri Ormo\u017eu"
    ],
    "name:ukr_x_preferred":[
        "\u041c\u0438\u043a\u043b\u0430\u0432\u0436-\u043f\u0440\u0438-\u041e\u0440\u043c\u043e\u0436\u0443"
    ],
    "name:unk_x_variant":[
        "Sveti Miklav\u017e"
    ],
    "qs_pg:aaroncc":"SI",
    "qs_pg:gn_country":"SI",
    "qs_pg:gn_fcode":"PPL",
    "qs_pg:gn_pop":0,
    "qs_pg:name":"Miklav\u017e Pri Ormo\u017eu",
    "qs_pg:name_adm0":"Slovenija",
    "qs_pg:name_adm1":"Ormoz",
    "qs_pg:photos":40,
    "qs_pg:photos_1k":8,
    "qs_pg:photos_9k":1,
    "qs_pg:photos_9r":2,
    "qs_pg:photos_all":40,
    "qs_pg:photos_sr":2,
    "qs_pg:pop_sr":0,
    "qs_pg:qs_pg_placetype":"locality",
    "qs_pg:qs_pg_placetype_gp":"Town",
    "qs_pg:woe_adm0":23424945,
    "woe:adm0_id":23424945,
    "woe:name_adm0":"Slovenija",
    "woe:name_adm1":"Ormoz",
    "woe:placetype":"Town",
    "wof:name":"Miklav\u017e Pri Ormo\u017eu",
    "wof:placetype":"locality",
    "wof:population":256
},
  "geometry": {"coordinates":[16.21361,46.46],"type":"Point"}
}