{
  "type": "Feature",
  "properties": {
    "gn:admin1_code":"P1",
    "gn:asciiname":"Zigoni",
    "gn:country_code":"SI",
    "gn:dem":63,
    "gn:feature_class":"P",
    "gn:feature_code":"PPL",
    "gn:name":"\u017digoni",
    "gn:population":0,
    "gn:timezone":"Europe/Ljubljana",
    "iso:country":"SI",
    "wof:name":"Zigoni",
    "wof:placetype":"locality"
},
  "geometry": {"coordinates":[13.66778,45.87972],"type":"Point"}
}