{
  "type": "Feature",
  "properties": {
    "iso:country":"SI",
    "name:slv_x_preferred":[
        "Jan\u010de"
    ],
    "wof:name":"Jance",
    "wof:placetype":"neighbourhood"
},
  "geometry": {"coordinates":[14.71236383720755,46.05240542475742],"type":"Point"}
}