{
  "type": "Feature",
  "properties": {
    "gn:asciiname":"Ples",
    "gn:country_code":"SI",
    "gn:dem":220,
    "gn:feature_class":"P",
    "gn:feature_code":"PPL",
    "gn:name":"Ples",
    "gn:population":72,
    "gn:timezone":"Europe/Ljubljana",
    "iso:country":"SI",
    "name:bos_x_preferred":[
        "Ples"
    ],
    "name:ceb_x_preferred":[
        "Ples"
    ],
    "name:ces_x_preferred":[
        "Ples"
    ],
    "name:deu_x_preferred":[
        "Ples"
    ],
    "name:hye_x_preferred":[
        "\u054a\u056c\u0565\u057d"
    ],
    "name:ita_x_preferred":[
        "Ples"
    ],
    "name:nld_x_preferred":[
        "Ples"
    ],
    "name:pol_x_preferred":[
        "Ples"
    ],
    "name:rus_x_preferred":[
        "\u041f\u043b\u0435\u0441"
    ],
    "name:slv_x_preferred":[
        "Ples"
    ],
    "name:swe_x_preferred":[
        "Ples"
    ],
    "name:ukr_x_preferred":[
        "\u041f\u043b\u0435\u0441"
    ],
    "wof:name":"Ples",
    "wof:placetype":"locality",
    "wof:population":72
},
  "geometry": {"coordinates":[15.65275,46.07422],"type":"Point"}
}