{
  "type": "Feature",
  "properties": {
    "gn:population":778,
    "iso:country":"SI",
    "name:ara_x_preferred":[
        "\u0641\u0631\u0627\u0646\u0633\u0643\u0648"
    ],
    "name:ben_x_preferred":[
        "\u09ad\u09cd\u09b0\u09be\u09a8\u09b8\u09cd\u0995\u09cb"
    ],
    "name:bos_x_preferred":[
        "Vransko"
    ],
    "name:dan_x_preferred":[
        "Vransko"
    ],
    "name:deu_x_preferred":[
        "Vransko"
    ],
    "name:ell_x_preferred":[
        "\u0392\u03c1\u03ac\u03bd\u03c3\u03ba\u03bf"
    ],
    "name:eng_x_preferred":[
        "Vransko"
    ],
    "name:fin_x_preferred":[
        "Vransko"
    ],
    "name:fra_x_preferred":[
        "Vransko"
    ],
    "name:guj_x_preferred":[
        "\u0ab5\u0acd\u0ab0\u0abe\u0aa8\u0acd\u0ab8\u0acd\u0a95\u0acb"
    ],
    "name:hbs_x_preferred":[
        "Vransko"
    ],
    "name:hin_x_preferred":[
        "\u0935\u094d\u0930\u093e\u0928\u094d\u0938\u0915\u094b"
    ],
    "name:hrv_x_preferred":[
        "Vransko"
    ],
    "name:ind_x_preferred":[
        "Vransko"
    ],
    "name:ita_x_preferred":[
        "Vransko"
    ],
    "name:jpn_x_preferred":[
        "\u30f4\u30e9\u30f3\u30b9\u30b3"
    ],
    "name:kan_x_preferred":[
        "\u0cb5\u0ccd\u0caf\u0cbe\u0ca8\u0ccd\u0cb8\u0ccd\u0c95\u0cca"
    ],
    "name:kor_x_preferred":[
        "\ube0c\ub780\uc2a4\ucf54"
    ],
    "name:lav_x_preferred":[
        "Vransko"
    ],
    "name:lit_x_preferred":[
        "Vranskas"
    ],
    "name:mar_x_preferred":[
        "\u0935\u094d\u0930\u093e\u0928\u094d\u0938\u094d\u0915\u094b"
    ],
    "name:msa_x_preferred":[
        "Vransko"
    ],
    "name:nld_x_preferred":[
        "Vransko"
    ],
    "name:nob_x_preferred":[
        "Vransko"
    ],
    "name:pol_x_preferred":[
        "Gmina Vransko"
    ],
    "name:por_x_preferred":[
        "Vransko"
    ],
    "name:ron_x_preferred":[
        "Vransko"
    ],
    "name:rus_x_preferred":[
        "\u0412\u0440\u0430\u043d\u0441\u043a\u043e"
    ],
    "name:sin_x_preferred":[
        "\u0dc0\u0dd2\u0dbb\u0dcf\u0db1\u0dca\u0dc3\u0dca\u0d9a\u0ddd"
    ],
    "name:slv_x_preferred":[
        "Vransko"
    ],
    "name:spa_x_preferred":[
        "Vransko"
    ],
    "name:srp_x_preferred":[
        "\u0412\u0440\u0430\u043d\u0441\u043a\u043e"
    ],
    "name:swe_x_preferred":[
        "Vransko"
    ],
    "name:tam_x_preferred":[
        "\u0bb5\u0bb0\u0ba9\u0bcd\u0bb8\u0bcd\u0b95\u0bcd\u0b95\u0bcb"
    ],
    "name:tel_x_preferred":[
        "\u0c35\u0c4d\u0c30\u0c3e\u0c28\u0c4d\u0c38\u0c4d\u0c15\u0c4b"
    ],
    "name:tha_x_preferred":[
        "\u0e27\u0e23\u0e32\u0e19\u0e2a\u0e42\u0e01"
    ],
    "name:tur_x_preferred":[
        "Vransko"
    ],
    "name:ukr_x_preferred":[
        "\u0412\u0440\u0430\u043d\u0441\u044c\u043a\u043e"
    ],
    "name:unk_x_variant":[
        "Franz"
    ],
    "name:urd_x_preferred":[
        "\u0648\u0631\u0627\u0646\u0633\u06a9\u0648"
    ],
    "name:vie_x_preferred":[
        "Vransko"
    ],
    "qs:a0":"Slovenija",
    "qs:a1":"*",
    "qs:a1r":"0",
    "qs:adm0":"Slovenija",
    "qs:la_lc":"*",
    "qs:level":"locality",
    "qs:loc":"Vransko",
    "qs:loc_alt":"Vransko",
    "qs:pop":0,
    "qs:type":"buffered point",
    "wof:name":"Vransko",
    "wof:placetype":"locality",
    "wof:population":778
},
  "geometry": {"coordinates":[14.939043,46.251186],"type":"Point"}
}