{
  "type": "Feature",
  "properties": {
    "gn:admin1_code":"07",
    "gn:asciiname":"Vrhovlje pri Kozbani",
    "gn:country_code":"SI",
    "gn:dem":361,
    "gn:feature_class":"P",
    "gn:feature_code":"PPL",
    "gn:name":"Vrhovlje pri Ko\u017ebani",
    "gn:population":18,
    "gn:timezone":"Europe/Ljubljana",
    "iso:country":"SI",
    "name:und_x_variant":[
        "Vrhovlje pri Ko\u017ebani"
    ],
    "wof:name":"Vrhovlje pri Kozbani",
    "wof:placetype":"locality",
    "wof:population":18
},
  "geometry": {"coordinates":[13.51705,46.0442],"type":"Point"}
}