{
  "type": "Feature",
  "properties": {
    "gn:admin1_code":"07",
    "gn:asciiname":"Vrhovlje pri Kozbani",
    "gn:country_code":"SI",
    "gn:dem":361,
    "gn:feature_class":"P",
    "gn:feature_code":"PPL",
    "gn:name":"Vrhovlje pri Ko\u017ebani",
    "gn:population":18,
    "gn:timezone":"Europe/Ljubljana",
    "iso:country":"SI",
    "name:bos_x_preferred":[
        "Vrhovlje pri Ko\u017ebani"
    ],
    "name:nld_x_preferred":[
        "Vrhovlje pri Ko\u017ebani"
    ],
    "name:pol_x_preferred":[
        "Vrhovlje pri Ko\u017ebani"
    ],
    "name:ron_x_preferred":[
        "Vrhovlje pri Ko\u017ebani"
    ],
    "name:slv_x_preferred":[
        "Vrhovlje pri Ko\u017ebani"
    ],
    "name:ukr_x_preferred":[
        "\u0412\u0440\u0445\u043e\u0432\u043b\u0454-\u043f\u0440\u0438-\u041a\u043e\u0436\u0431\u0430\u043d\u0456"
    ],
    "name:und_x_variant":[
        "Vrhovlje pri Ko\u017ebani"
    ],
    "wof:name":"Vrhovlje pri Kozbani",
    "wof:placetype":"locality",
    "wof:population":18
},
  "geometry": {"coordinates":[13.51705,46.0442],"type":"Point"}
}