{
  "type": "Feature",
  "properties": {
    "gn:admin1_code":"O7",
    "gn:asciiname":"Pugled pri Mokronogu",
    "gn:country_code":"SI",
    "gn:dem":371,
    "gn:feature_class":"P",
    "gn:feature_code":"PPL",
    "gn:name":"Pugled pri Mokronogu",
    "gn:population":16,
    "gn:timezone":"Europe/Ljubljana",
    "iso:country":"SI",
    "name:slv_x_historical":[
        "Pogled"
    ],
    "name:slv_x_preferred":[
        "Pogled"
    ],
    "wof:name":"Pugled pri Mokronogu",
    "wof:placetype":"locality",
    "wof:population":16
},
  "geometry": {"coordinates":[15.13355,45.93302],"type":"Point"}
}