{
  "type": "Feature",
  "properties": {
    "gn:admin1_code":"O7",
    "gn:asciiname":"Pugled pri Mokronogu",
    "gn:country_code":"SI",
    "gn:dem":371,
    "gn:feature_class":"P",
    "gn:feature_code":"PPL",
    "gn:name":"Pugled pri Mokronogu",
    "gn:population":16,
    "gn:timezone":"Europe/Ljubljana",
    "iso:country":"SI",
    "name:bos_x_preferred":[
        "Pugled pri Mokronogu"
    ],
    "name:hrv_x_preferred":[
        "Pugled pri Mokronogu"
    ],
    "name:nld_x_preferred":[
        "Pugled pri Mokronogu"
    ],
    "name:pol_x_preferred":[
        "Pugled pri Mokronogu"
    ],
    "name:ron_x_preferred":[
        "Pugled pri Mokronogu"
    ],
    "name:slv_x_historical":[
        "Pogled"
    ],
    "name:slv_x_preferred":[
        "Pogled"
    ],
    "name:slv_x_variant":[
        "Pugled pri Mokronogu"
    ],
    "name:ukr_x_preferred":[
        "\u041f\u0443\u0433\u043b\u0435\u0434-\u043f\u0440\u0438-\u041c\u043e\u043a\u0440\u043e\u043d\u043e\u0433\u0443"
    ],
    "wof:name":"Pugled pri Mokronogu",
    "wof:placetype":"locality",
    "wof:population":16
},
  "geometry": {"coordinates":[15.13355,45.93302],"type":"Point"}
}