{
  "type": "Feature",
  "properties": {
    "gn:admin1_code":"L5",
    "gn:asciiname":"Zgornji Boc",
    "gn:country_code":"SI",
    "gn:dem":861,
    "gn:feature_class":"P",
    "gn:feature_code":"PPL",
    "gn:name":"Zgornji Bo\u010d",
    "gn:population":261,
    "gn:timezone":"Europe/Ljubljana",
    "iso:country":"SI",
    "name:bos_x_preferred":[
        "Zgornji Bo\u010d"
    ],
    "name:ceb_x_preferred":[
        "Zgornji Bo\u010d"
    ],
    "name:nld_x_preferred":[
        "Zgornji Bo\u010d"
    ],
    "name:pol_x_preferred":[
        "Zgornji Bo\u010d"
    ],
    "name:ron_x_preferred":[
        "Zgornji Bo\u010d"
    ],
    "name:slv_x_preferred":[
        "Zgornji Bo\u010d"
    ],
    "name:ukr_x_preferred":[
        "\u0417\u0433\u043e\u0440\u043d\u0438\u0439 \u0411\u043e\u0447"
    ],
    "wof:name":"Zgornji Boc",
    "wof:placetype":"locality",
    "wof:population":261
},
  "geometry": {"coordinates":[15.46667,46.58333],"type":"Point"}
}