{
  "type": "Feature",
  "properties": {
    "gn:admin1_code":"L5",
    "gn:asciiname":"Zgornji Boc",
    "gn:country_code":"SI",
    "gn:dem":861,
    "gn:feature_class":"P",
    "gn:feature_code":"PPL",
    "gn:name":"Zgornji Bo\u010d",
    "gn:population":261,
    "gn:timezone":"Europe/Ljubljana",
    "iso:country":"SI",
    "name:und_x_variant":[
        "Zgornji Bo\u010d"
    ],
    "wof:name":"Zgornji Boc",
    "wof:placetype":"locality",
    "wof:population":261
},
  "geometry": {"coordinates":[15.46667,46.58333],"type":"Point"}
}