{
  "type": "Feature",
  "properties": {
    "gn:admin1_code":"A7",
    "gn:asciiname":"Kamna Gorca",
    "gn:country_code":"SI",
    "gn:dem":281,
    "gn:feature_class":"P",
    "gn:feature_code":"PPL",
    "gn:name":"Kamna Gorca",
    "gn:population":112,
    "gn:timezone":"Europe/Ljubljana",
    "iso:country":"SI",
    "wof:name":"Kamna Gorca",
    "wof:placetype":"locality",
    "wof:population":112
},
  "geometry": {"coordinates":[15.59175,46.24206],"type":"Point"}
}