{
  "type": "Feature",
  "properties": {
    "gn:admin1_code":"E7",
    "gn:asciiname":"Kal",
    "gn:country_code":"SI",
    "gn:dem":680,
    "gn:feature_class":"P",
    "gn:feature_code":"PPL",
    "gn:name":"Kal",
    "gn:population":99,
    "gn:timezone":"Europe/Ljubljana",
    "iso:country":"SI",
    "wof:name":"Kal",
    "wof:placetype":"locality",
    "wof:population":99
},
  "geometry": {"coordinates":[14.95141,46.11521],"type":"Point"}
}