{
  "type": "Feature",
  "properties": {
    "gn:admin1_code":"50",
    "gn:asciiname":"Hrvatini",
    "gn:country_code":"SI",
    "gn:dem":160,
    "gn:feature_class":"P",
    "gn:feature_code":"PPL",
    "gn:name":"Hrvatini",
    "gn:population":1232,
    "gn:timezone":"Europe/Ljubljana",
    "iso:country":"SI",
    "name:bos_x_preferred":[
        "Hrvatini"
    ],
    "name:bul_x_preferred":[
        "\u0425\u044a\u0440\u0432\u0430\u0442\u0438\u043d\u0438"
    ],
    "name:ceb_x_preferred":[
        "Hrvatini"
    ],
    "name:ita_x_preferred":[
        "Crevatini"
    ],
    "name:nld_x_preferred":[
        "Hrvatini"
    ],
    "name:pol_x_preferred":[
        "Hrvatini"
    ],
    "name:ron_x_preferred":[
        "Hrvatini"
    ],
    "name:slv_x_preferred":[
        "Hrvatini"
    ],
    "name:ukr_x_preferred":[
        "\u0425\u0440\u0432\u0430\u0442\u0438\u043d\u0438"
    ],
    "name:und_x_variant":[
        "Hrvatin"
    ],
    "wof:name":"Hrvatini",
    "wof:placetype":"locality",
    "wof:population":1232
},
  "geometry": {"coordinates":[13.75667,45.58278],"type":"Point"}
}