{
  "type": "Feature",
  "properties": {
    "gn:admin1_code":"50",
    "gn:asciiname":"Hrvatini",
    "gn:country_code":"SI",
    "gn:dem":160,
    "gn:feature_class":"P",
    "gn:feature_code":"PPL",
    "gn:name":"Hrvatini",
    "gn:population":1232,
    "gn:timezone":"Europe/Ljubljana",
    "iso:country":"SI",
    "name:und_x_variant":[
        "Crevatini",
        "Hrvatin",
        "Hrvatini"
    ],
    "wof:name":"Hrvatini",
    "wof:placetype":"locality",
    "wof:population":1232
},
  "geometry": {"coordinates":[13.75667,45.58278],"type":"Point"}
}