{
  "type": "Feature",
  "properties": {
    "gn:admin1_code":"D1",
    "gn:asciiname":"Stara Gora",
    "gn:country_code":"SI",
    "gn:dem":257,
    "gn:feature_class":"P",
    "gn:feature_code":"PPL",
    "gn:name":"Stara Gora",
    "gn:population":72,
    "gn:timezone":"Europe/Ljubljana",
    "iso:country":"SI",
    "name:bos_x_preferred":[
        "Stara Gora"
    ],
    "name:hrv_x_preferred":[
        "Stara Gora"
    ],
    "name:nld_x_preferred":[
        "Stara Gora"
    ],
    "name:pol_x_preferred":[
        "Stara Gora"
    ],
    "name:ron_x_preferred":[
        "Stara Gora"
    ],
    "name:slv_x_preferred":[
        "Stara Gora"
    ],
    "name:ukr_x_preferred":[
        "\u0421\u0442\u0430\u0440\u0430 \u0413\u043e\u0440\u0430"
    ],
    "wof:name":"Stara Gora",
    "wof:placetype":"locality",
    "wof:population":72
},
  "geometry": {"coordinates":[16.03126,46.55034000000001],"type":"Point"}
}