{
  "type": "Feature",
  "properties": {
    "gn:admin1_code":"39",
    "gn:asciiname":"Malo Globoko",
    "gn:country_code":"SI",
    "gn:dem":306,
    "gn:feature_class":"P",
    "gn:feature_code":"PPL",
    "gn:name":"Malo Globoko",
    "gn:population":52,
    "gn:timezone":"Europe/Ljubljana",
    "iso:country":"SI",
    "name:bos_x_preferred":[
        "Malo Globoko"
    ],
    "name:nld_x_preferred":[
        "Malo Globoko"
    ],
    "name:pol_x_preferred":[
        "Malo Globoko"
    ],
    "name:ron_x_preferred":[
        "Malo Globoko"
    ],
    "name:slv_x_preferred":[
        "Malo Globoko"
    ],
    "name:ukr_x_preferred":[
        "\u041c\u0430\u043b\u043e \u0413\u043b\u043e\u0431\u043e\u043a\u043e"
    ],
    "wof:name":"Malo Globoko",
    "wof:placetype":"locality",
    "wof:population":52
},
  "geometry": {"coordinates":[14.82398,45.86055],"type":"Point"}
}