{
  "type": "Feature",
  "properties": {
    "gn:admin1_code":"39",
    "gn:asciiname":"Breg pri Temenici",
    "gn:country_code":"SI",
    "gn:dem":337,
    "gn:feature_class":"P",
    "gn:feature_code":"PPL",
    "gn:name":"Breg pri Temenici",
    "gn:population":41,
    "gn:timezone":"Europe/Ljubljana",
    "iso:country":"SI",
    "name:bos_x_preferred":[
        "Breg pri Temenici"
    ],
    "name:nld_x_preferred":[
        "Breg pri Temenici"
    ],
    "name:pol_x_preferred":[
        "Breg pri Temenici"
    ],
    "name:ron_x_preferred":[
        "Breg pri Temenici"
    ],
    "name:slv_x_preferred":[
        "Breg pri Temenici"
    ],
    "name:ukr_x_preferred":[
        "\u0411\u0440\u0435\u0433-\u043f\u0440\u0438-\u0422\u0435\u043c\u0435\u043d\u0438\u0446\u0456"
    ],
    "wof:name":"Breg pri Temenici",
    "wof:placetype":"locality",
    "wof:population":41
},
  "geometry": {"coordinates":[14.89532,45.94922],"type":"Point"}
}