{
  "type": "Feature",
  "properties": {
    "gn:admin1_code":"D8",
    "gn:asciiname":"Pusce",
    "gn:country_code":"SI",
    "gn:dem":523,
    "gn:feature_class":"P",
    "gn:feature_code":"PPL",
    "gn:name":"Pu\u0161\u010de",
    "gn:population":52,
    "gn:timezone":"Europe/Ljubljana",
    "iso:country":"SI",
    "name:bos_x_preferred":[
        "Pu\u0161\u010de"
    ],
    "name:nld_x_preferred":[
        "Pu\u0161\u010de"
    ],
    "name:pol_x_preferred":[
        "Pu\u0161\u010de"
    ],
    "name:ron_x_preferred":[
        "Pu\u0161\u010de"
    ],
    "name:slv_x_preferred":[
        "Pu\u0161\u010de"
    ],
    "name:ukr_x_preferred":[
        "\u041f\u0443\u0449\u0435"
    ],
    "wof:name":"Pusce",
    "wof:placetype":"locality",
    "wof:population":52
},
  "geometry": {"coordinates":[14.62402,45.8432],"type":"Point"}
}