{
  "type": "Feature",
  "properties": {
    "gn:admin1_code":"N5",
    "gn:asciiname":"Velika Piresica",
    "gn:country_code":"SI",
    "gn:dem":280,
    "gn:feature_class":"P",
    "gn:feature_code":"PPL",
    "gn:name":"Velika Pire\u0161ica",
    "gn:population":452,
    "gn:timezone":"Europe/Ljubljana",
    "iso:country":"SI",
    "name:und_x_variant":[
        "Velika Pire\u0161ica"
    ],
    "wof:name":"Velika Piresica",
    "wof:placetype":"locality",
    "wof:population":452
},
  "geometry": {"coordinates":[15.17944,46.28556],"type":"Point"}
}