{
  "type": "Feature",
  "properties": {
    "gn:admin1_code":"N5",
    "gn:asciiname":"Velika Piresica",
    "gn:country_code":"SI",
    "gn:dem":280,
    "gn:feature_class":"P",
    "gn:feature_code":"PPL",
    "gn:name":"Velika Pire\u0161ica",
    "gn:population":452,
    "gn:timezone":"Europe/Ljubljana",
    "iso:country":"SI",
    "name:ceb_x_preferred":[
        "Velika Pire\u0161ica"
    ],
    "name:fas_x_preferred":[
        "\u0648\u0644\u06cc\u06a9\u0627 \u067e\u06cc\u0631\u0634\u06cc\u06a9\u0627"
    ],
    "name:hrv_x_preferred":[
        "Velika Pire\u0161ica"
    ],
    "name:nld_x_preferred":[
        "Velika Pire\u0161ica"
    ],
    "name:pol_x_preferred":[
        "Velika Pire\u0161ica"
    ],
    "name:ron_x_preferred":[
        "Velika Pire\u0161ica"
    ],
    "name:slv_x_preferred":[
        "Velika Pire\u0161ica"
    ],
    "name:ukr_x_preferred":[
        "\u0412\u0435\u043b\u0438\u043a\u0430 \u041f\u0438\u0440\u0435\u0448\u0438\u0446\u044f"
    ],
    "name:und_x_variant":[
        "Velika Pire\u0161ica"
    ],
    "wof:name":"Velika Piresica",
    "wof:placetype":"locality",
    "wof:population":452
},
  "geometry": {"coordinates":[15.17944,46.28556],"type":"Point"}
}