{
  "type": "Feature",
  "properties": {
    "gn:admin1_code":"B9",
    "gn:asciiname":"Vincarje",
    "gn:country_code":"SI",
    "gn:dem":403,
    "gn:feature_class":"P",
    "gn:feature_code":"PPL",
    "gn:name":"Vincarje",
    "gn:population":141,
    "gn:timezone":"Europe/Ljubljana",
    "iso:country":"SI",
    "name:bos_x_preferred":[
        "Vincarje"
    ],
    "name:ceb_x_preferred":[
        "Vincarje"
    ],
    "name:hrv_x_preferred":[
        "Vincarje"
    ],
    "name:nld_x_preferred":[
        "Vincarje"
    ],
    "name:pol_x_preferred":[
        "Vincarje"
    ],
    "name:ron_x_preferred":[
        "Vincarje"
    ],
    "name:slv_x_preferred":[
        "Vincarje"
    ],
    "name:ukr_x_preferred":[
        "\u0412\u0456\u043d\u0446\u0430\u0440\u0454"
    ],
    "wof:name":"Vincarje",
    "wof:placetype":"locality",
    "wof:population":141
},
  "geometry": {"coordinates":[14.27209,46.17267],"type":"Point"}
}