{
  "type": "Feature",
  "properties": {
    "gn:admin1_code":"46",
    "gn:asciiname":"Libusnje",
    "gn:country_code":"SI",
    "gn:dem":417,
    "gn:feature_class":"P",
    "gn:feature_code":"PPL",
    "gn:name":"Libu\u0161nje",
    "gn:population":40,
    "gn:timezone":"Europe/Ljubljana",
    "iso:country":"SI",
    "name:und_x_variant":[
        "Libussina",
        "Libu\u0161nje"
    ],
    "wof:name":"Libusnje",
    "wof:placetype":"locality",
    "wof:population":40
},
  "geometry": {"coordinates":[13.62584,46.22666],"type":"Point"}
}