{
  "type": "Feature",
  "properties": {
    "gn:admin1_code":"36",
    "gn:asciiname":"Mrzia Rupa",
    "gn:country_code":"SI",
    "gn:dem":871,
    "gn:feature_class":"P",
    "gn:feature_code":"PPL",
    "gn:name":"Mrzia Rupa",
    "gn:population":0,
    "gn:timezone":"Europe/Ljubljana",
    "iso:country":"SI",
    "wof:name":"Mrzia Rupa",
    "wof:placetype":"locality"
},
  "geometry": {"coordinates":[13.88694,46.01083],"type":"Point"}
}