{
  "type": "Feature",
  "properties": {
    "gn:admin1_code":"B9",
    "gn:asciiname":"Sv. Duh",
    "gn:country_code":"SI",
    "gn:dem":361,
    "gn:feature_class":"P",
    "gn:feature_code":"PPL",
    "gn:name":"Sv. Duh",
    "gn:population":1066,
    "gn:timezone":"Europe/Ljubljana",
    "iso:country":"SI",
    "name:bos_x_preferred":[
        "Sveti Duh"
    ],
    "name:ceb_x_preferred":[
        "Sv. Duh"
    ],
    "name:hrv_x_preferred":[
        "Sv. Duh"
    ],
    "name:nld_x_preferred":[
        "Sv. Duh"
    ],
    "name:pol_x_preferred":[
        "Sveti Duh"
    ],
    "name:ron_x_preferred":[
        "Sveti Duh"
    ],
    "name:slv_x_preferred":[
        "Sveti Duh"
    ],
    "name:ukr_x_preferred":[
        "\u0421\u0432\u0435\u0442\u0438\u0439 \u0414\u0443\u0445"
    ],
    "wof:name":"Sv. Duh",
    "wof:placetype":"locality",
    "wof:population":1066
},
  "geometry": {"coordinates":[14.33333,46.18333],"type":"Point"}
}