{
  "type": "Feature",
  "properties": {
    "gn:admin1_code":"B9",
    "gn:asciiname":"Sv. Duh",
    "gn:country_code":"SI",
    "gn:dem":361,
    "gn:feature_class":"P",
    "gn:feature_code":"PPL",
    "gn:name":"Sv. Duh",
    "gn:population":1066,
    "gn:timezone":"Europe/Ljubljana",
    "iso:country":"SI",
    "name:und_x_variant":[
        "Sveti Duh"
    ],
    "wof:name":"Sv. Duh",
    "wof:placetype":"locality",
    "wof:population":1066
},
  "geometry": {"coordinates":[14.33333,46.18333],"type":"Point"}
}