{
  "type": "Feature",
  "properties": {
    "gn:admin1_code":"I1",
    "gn:asciiname":"Berkovci",
    "gn:country_code":"SI",
    "gn:dem":189,
    "gn:feature_class":"P",
    "gn:feature_code":"PPL",
    "gn:name":"Berkovci",
    "gn:population":146,
    "gn:timezone":"Europe/Ljubljana",
    "iso:country":"SI",
    "name:bos_x_preferred":[
        "Berkovci"
    ],
    "name:ceb_x_preferred":[
        "Berkovci"
    ],
    "name:hrv_x_preferred":[
        "Berkovci"
    ],
    "name:nld_x_preferred":[
        "Berkovci"
    ],
    "name:pol_x_preferred":[
        "Berkovci"
    ],
    "name:ron_x_preferred":[
        "Berkovci"
    ],
    "name:slv_x_preferred":[
        "Berkovci"
    ],
    "name:ukr_x_preferred":[
        "\u0411\u0435\u0440\u043a\u043e\u0432\u0446\u0456"
    ],
    "name:und_x_variant":[
        "Berkeh\u00e1za",
        "Berkovci"
    ],
    "wof:name":"Berkovci",
    "wof:placetype":"locality",
    "wof:population":146
},
  "geometry": {"coordinates":[16.08306,46.55278],"type":"Point"}
}