{
  "type": "Feature",
  "properties": {
    "gn:admin1_code":"13",
    "gn:asciiname":"Dolenje Jezero",
    "gn:country_code":"SI",
    "gn:dem":553,
    "gn:feature_class":"P",
    "gn:feature_code":"PPL",
    "gn:name":"Dolenje Jezero",
    "gn:population":230,
    "gn:timezone":"Europe/Ljubljana",
    "iso:country":"SI",
    "name:bos_x_preferred":[
        "Dolenje Jezero"
    ],
    "name:ceb_x_preferred":[
        "Dolenje Jezero"
    ],
    "name:hrv_x_preferred":[
        "Dolenje Jezero"
    ],
    "name:nld_x_preferred":[
        "Dolenje Jezero"
    ],
    "name:pol_x_preferred":[
        "Dolenje Jezero"
    ],
    "name:ron_x_preferred":[
        "Dolenje Jezero"
    ],
    "name:slv_x_preferred":[
        "Dolenje Jezero"
    ],
    "name:ukr_x_preferred":[
        "\u0414\u043e\u043b\u0435\u043d\u0454 \u0404\u0437\u0435\u0440\u043e"
    ],
    "wof:name":"Dolenje Jezero",
    "wof:placetype":"locality",
    "wof:population":230
},
  "geometry": {"coordinates":[14.35917,45.77472],"type":"Point"}
}