{
  "type": "Feature",
  "properties": {
    "gn:admin1_code":"27",
    "gn:asciiname":"Bacne",
    "gn:country_code":"SI",
    "gn:dem":497,
    "gn:feature_class":"P",
    "gn:feature_code":"PPL",
    "gn:name":"Ba\u010dne",
    "gn:population":23,
    "gn:timezone":"Europe/Ljubljana",
    "iso:country":"SI",
    "name:und_x_variant":[
        "Ba\u010dne"
    ],
    "wof:name":"Bacne",
    "wof:placetype":"locality",
    "wof:population":23
},
  "geometry": {"coordinates":[14.17955,46.09073],"type":"Point"}
}