{
  "type": "Feature",
  "properties": {
    "gn:admin1_code":"I5",
    "gn:asciiname":"Klenik",
    "gn:country_code":"SI",
    "gn:dem":646,
    "gn:feature_class":"P",
    "gn:feature_code":"PPL",
    "gn:name":"Klenik",
    "gn:population":55,
    "gn:timezone":"Europe/Ljubljana",
    "iso:country":"SI",
    "wof:name":"Klenik",
    "wof:placetype":"locality",
    "wof:population":55
},
  "geometry": {"coordinates":[14.84861,46.12338],"type":"Point"}
}