{
  "type": "Feature",
  "properties": {
    "gn:admin1_code":"I5",
    "gn:asciiname":"Klenik",
    "gn:country_code":"SI",
    "gn:dem":646,
    "gn:feature_class":"P",
    "gn:feature_code":"PPL",
    "gn:name":"Klenik",
    "gn:population":55,
    "gn:timezone":"Europe/Ljubljana",
    "iso:country":"SI",
    "name:bos_x_preferred":[
        "Klenik"
    ],
    "name:bul_x_preferred":[
        "\u041a\u043b\u0435\u043d\u0438\u043a"
    ],
    "name:nld_x_preferred":[
        "Klenik"
    ],
    "name:pol_x_preferred":[
        "Klenik"
    ],
    "name:ron_x_preferred":[
        "Klenik"
    ],
    "name:slv_x_preferred":[
        "Klenik"
    ],
    "name:ukr_x_preferred":[
        "\u041a\u043b\u0435\u043d\u0438\u043a"
    ],
    "wof:name":"Klenik",
    "wof:placetype":"locality",
    "wof:population":55
},
  "geometry": {"coordinates":[14.84861,46.12338],"type":"Point"}
}