{
  "type": "Feature",
  "properties": {
    "gn:admin1_code":"B6",
    "gn:asciiname":"Srednik",
    "gn:country_code":"SI",
    "gn:dem":467,
    "gn:feature_class":"P",
    "gn:feature_code":"PPL",
    "gn:name":"Srednik",
    "gn:population":61,
    "gn:timezone":"Europe/Ljubljana",
    "iso:country":"SI",
    "name:bos_x_preferred":[
        "Srednik"
    ],
    "name:nld_x_preferred":[
        "Srednik"
    ],
    "name:pol_x_preferred":[
        "Srednik"
    ],
    "name:ron_x_preferred":[
        "Srednik"
    ],
    "name:slv_x_preferred":[
        "Srednik"
    ],
    "name:ukr_x_preferred":[
        "\u0421\u0440\u0435\u0434\u043d\u0438\u043a"
    ],
    "wof:name":"Srednik",
    "wof:placetype":"locality",
    "wof:population":61
},
  "geometry": {"coordinates":[15.17068,46.02602],"type":"Point"}
}