{
  "type": "Feature",
  "properties": {
    "gn:admin1_code":"B6",
    "gn:asciiname":"Srednik",
    "gn:country_code":"SI",
    "gn:dem":467,
    "gn:feature_class":"P",
    "gn:feature_code":"PPL",
    "gn:name":"Srednik",
    "gn:population":61,
    "gn:timezone":"Europe/Ljubljana",
    "iso:country":"SI",
    "wof:name":"Srednik",
    "wof:placetype":"locality",
    "wof:population":61
},
  "geometry": {"coordinates":[15.17068,46.02602],"type":"Point"}
}