{
  "type": "Feature",
  "properties": {
    "gn:admin1_code":"D8",
    "gn:asciiname":"Krvava Pec",
    "gn:country_code":"SI",
    "gn:dem":771,
    "gn:feature_class":"P",
    "gn:feature_code":"PPL",
    "gn:name":"Krvava Pe\u010d",
    "gn:population":21,
    "gn:timezone":"Europe/Ljubljana",
    "iso:country":"SI",
    "name:bos_x_preferred":[
        "Krvava Pe\u010d"
    ],
    "name:nld_x_preferred":[
        "Krvava Pe\u010d"
    ],
    "name:pol_x_preferred":[
        "Krvava Pe\u010d"
    ],
    "name:ron_x_preferred":[
        "Krvava Pe\u010d"
    ],
    "name:slv_x_preferred":[
        "Krvava Pe\u010d"
    ],
    "name:ukr_x_preferred":[
        "\u041a\u0440\u0432\u0430\u0432\u0430 \u041f\u0435\u0447"
    ],
    "name:und_x_variant":[
        "Krvava Pe\u010d"
    ],
    "wof:name":"Krvava Pec",
    "wof:placetype":"locality",
    "wof:population":21
},
  "geometry": {"coordinates":[14.51472,45.86583],"type":"Point"}
}