{
  "type": "Feature",
  "properties": {
    "gn:admin1_code":"E5",
    "gn:asciiname":"Velika Ligojna",
    "gn:country_code":"SI",
    "gn:dem":302,
    "gn:feature_class":"P",
    "gn:feature_code":"PPL",
    "gn:name":"Velika Ligojna",
    "gn:population":391,
    "gn:timezone":"Europe/Ljubljana",
    "iso:country":"SI",
    "name:bos_x_preferred":[
        "Velika Ligojna"
    ],
    "name:ceb_x_preferred":[
        "Velika Ligojna"
    ],
    "name:fas_x_preferred":[
        "\u0648\u0644\u06cc\u06a9\u0627 \u0644\u06cc\u06af\u0648\u06cc\u0646\u0627"
    ],
    "name:nld_x_preferred":[
        "Velika Ligojna"
    ],
    "name:pol_x_preferred":[
        "Velika Ligojna"
    ],
    "name:ron_x_preferred":[
        "Velika Ligojna"
    ],
    "name:slv_x_preferred":[
        "Velika Ligojna"
    ],
    "name:ukr_x_preferred":[
        "\u0412\u0435\u043b\u0438\u043a\u0430 \u041b\u0438\u0433\u043e\u0439\u043d\u0430"
    ],
    "name:und_x_variant":[
        "Ligojna"
    ],
    "wof:name":"Velika Ligojna",
    "wof:placetype":"locality",
    "wof:population":391
},
  "geometry": {"coordinates":[14.29278,45.9925],"type":"Point"}
}