{
  "type": "Feature",
  "properties": {
    "gn:admin1_code":"E5",
    "gn:asciiname":"Velika Ligojna",
    "gn:country_code":"SI",
    "gn:dem":302,
    "gn:feature_class":"P",
    "gn:feature_code":"PPL",
    "gn:name":"Velika Ligojna",
    "gn:population":391,
    "gn:timezone":"Europe/Ljubljana",
    "iso:country":"SI",
    "name:und_x_variant":[
        "Ligojna",
        "Velika Ligojna"
    ],
    "wof:name":"Velika Ligojna",
    "wof:placetype":"locality",
    "wof:population":391
},
  "geometry": {"coordinates":[14.29278,45.9925],"type":"Point"}
}