{
  "type": "Feature",
  "properties": {
    "gn:admin1_code":"84",
    "gn:asciiname":"Fobca",
    "gn:country_code":"SI",
    "gn:dem":327,
    "gn:feature_class":"P",
    "gn:feature_code":"PPL",
    "gn:name":"Fobca",
    "gn:population":0,
    "gn:timezone":"Europe/Ljubljana",
    "iso:country":"SI",
    "wof:name":"Fobca",
    "wof:placetype":"locality"
},
  "geometry": {"coordinates":[13.6909,46.00984],"type":"Point"}
}