{
  "type": "Feature",
  "properties": {
    "gn:admin1_code":"B1",
    "gn:asciiname":"Praproce",
    "gn:country_code":"SI",
    "gn:dem":255,
    "gn:feature_class":"P",
    "gn:feature_code":"PPL",
    "gn:name":"Prapro\u010de",
    "gn:population":21,
    "gn:timezone":"Europe/Ljubljana",
    "iso:country":"SI",
    "name:und_x_variant":[
        "Prapro\u010de"
    ],
    "wof:name":"Praproce",
    "wof:placetype":"locality",
    "wof:population":21
},
  "geometry": {"coordinates":[15.23083,45.675],"type":"Point"}
}