{
  "type": "Feature",
  "properties": {
    "gn:admin1_code":"B1",
    "gn:asciiname":"Praproce",
    "gn:country_code":"SI",
    "gn:dem":255,
    "gn:feature_class":"P",
    "gn:feature_code":"PPL",
    "gn:name":"Prapro\u010de",
    "gn:population":21,
    "gn:timezone":"Europe/Ljubljana",
    "iso:country":"SI",
    "name:bos_x_preferred":[
        "Prapro\u010de"
    ],
    "name:hrv_x_preferred":[
        "Prapro\u010de"
    ],
    "name:nld_x_preferred":[
        "Prapro\u010de"
    ],
    "name:pol_x_preferred":[
        "Prapro\u010de"
    ],
    "name:ron_x_preferred":[
        "Prapro\u010de"
    ],
    "name:slv_x_preferred":[
        "Prapro\u010de"
    ],
    "name:ukr_x_preferred":[
        "\u041f\u0440\u0430\u043f\u0440\u043e\u0447\u0435"
    ],
    "name:und_x_variant":[
        "Prapro\u010de"
    ],
    "wof:name":"Praproce",
    "wof:placetype":"locality",
    "wof:population":21
},
  "geometry": {"coordinates":[15.23083,45.675],"type":"Point"}
}