{
  "type": "Feature",
  "properties": {
    "gn:admin1_code":"E1",
    "gn:asciiname":"Dobrava",
    "gn:country_code":"SI",
    "gn:dem":163,
    "gn:feature_class":"P",
    "gn:feature_code":"PPLL",
    "gn:name":"Dobrava",
    "gn:population":0,
    "gn:timezone":"Europe/Ljubljana",
    "iso:country":"SI",
    "wof:name":"Dobrava",
    "wof:placetype":"locality"
},
  "geometry": {"coordinates":[13.97332,45.8078],"type":"Point"}
}