{
  "type": "Feature",
  "properties": {
    "gn:admin1_code":"E1",
    "gn:asciiname":"Dobrava",
    "gn:country_code":"SI",
    "gn:dem":163,
    "gn:feature_class":"P",
    "gn:feature_code":"PPLL",
    "gn:name":"Dobrava",
    "gn:population":0,
    "gn:timezone":"Europe/Ljubljana",
    "iso:country":"SI",
    "name:bos_x_preferred":[
        "Dobrava"
    ],
    "name:ceb_x_preferred":[
        "Dobrava"
    ],
    "name:hrv_x_preferred":[
        "Dobrava"
    ],
    "name:nld_x_preferred":[
        "Dobrava"
    ],
    "name:slv_x_preferred":[
        "Dobrava"
    ],
    "name:srp_x_preferred":[
        "\u0414\u043e\u0431\u0440\u0430\u0432\u0430"
    ],
    "name:swe_x_preferred":[
        "Dobrava"
    ],
    "wof:name":"Dobrava",
    "wof:placetype":"locality"
},
  "geometry": {"coordinates":[13.97332,45.8078],"type":"Point"}
}