{
  "type": "Feature",
  "properties": {
    "gn:admin1_code":"B7",
    "gn:asciiname":"Utovlje",
    "gn:country_code":"SI",
    "gn:dem":337,
    "gn:feature_class":"P",
    "gn:feature_code":"PPL",
    "gn:name":"Utovlje",
    "gn:population":34,
    "gn:timezone":"Europe/Ljubljana",
    "iso:country":"SI",
    "name:und_x_variant":[
        "Uttoglie",
        "Utovlje"
    ],
    "wof:name":"Utovlje",
    "wof:placetype":"locality",
    "wof:population":34
},
  "geometry": {"coordinates":[13.88333,45.75389000000001],"type":"Point"}
}