{
  "type": "Feature",
  "properties": {
    "gn:admin1_code":"54",
    "gn:asciiname":"Gmajna",
    "gn:country_code":"SI",
    "gn:dem":158,
    "gn:feature_class":"P",
    "gn:feature_code":"PPL",
    "gn:name":"Gmajna",
    "gn:population":167,
    "gn:timezone":"Europe/Ljubljana",
    "iso:country":"SI",
    "name:bos_x_preferred":[
        "Gmajna"
    ],
    "name:ceb_x_preferred":[
        "Gmajna"
    ],
    "name:hrv_x_preferred":[
        "Gmajna"
    ],
    "name:nld_x_preferred":[
        "Gmajna"
    ],
    "name:pol_x_preferred":[
        "Gmajna"
    ],
    "name:ron_x_preferred":[
        "Gmajna"
    ],
    "name:slv_x_preferred":[
        "Gmajna"
    ],
    "name:ukr_x_preferred":[
        "\u0413\u043c\u0430\u0439\u043d\u0430"
    ],
    "wof:name":"Gmajna",
    "wof:placetype":"locality",
    "wof:population":167
},
  "geometry": {"coordinates":[15.35606,45.89902],"type":"Point"}
}