{
  "type": "Feature",
  "properties": {
    "gn:admin1_code":"54",
    "gn:asciiname":"Gmajna",
    "gn:country_code":"SI",
    "gn:dem":158,
    "gn:feature_class":"P",
    "gn:feature_code":"PPL",
    "gn:name":"Gmajna",
    "gn:population":167,
    "gn:timezone":"Europe/Ljubljana",
    "iso:country":"SI",
    "wof:name":"Gmajna",
    "wof:placetype":"locality",
    "wof:population":167
},
  "geometry": {"coordinates":[15.35606,45.89902],"type":"Point"}
}