{
  "type": "Feature",
  "properties": {
    "gn:admin1_code":"L8",
    "gn:asciiname":"Korplje",
    "gn:country_code":"SI",
    "gn:dem":288,
    "gn:feature_class":"P",
    "gn:feature_code":"PPL",
    "gn:name":"Korplje",
    "gn:population":49,
    "gn:timezone":"Europe/Ljubljana",
    "iso:country":"SI",
    "name:bos_x_preferred":[
        "Korplje"
    ],
    "name:nld_x_preferred":[
        "Korplje"
    ],
    "name:pol_x_preferred":[
        "Korplje"
    ],
    "name:ron_x_preferred":[
        "Korplje"
    ],
    "name:slv_x_preferred":[
        "Korplje"
    ],
    "name:ukr_x_preferred":[
        "\u041a\u043e\u0440\u043f\u043b\u0454"
    ],
    "wof:name":"Korplje",
    "wof:placetype":"locality",
    "wof:population":49
},
  "geometry": {"coordinates":[15.51391,46.37919],"type":"Point"}
}