{
  "type": "Feature",
  "properties": {
    "gn:admin1_code":"H7",
    "gn:asciiname":"Novi Lazi",
    "gn:country_code":"SI",
    "gn:dem":541,
    "gn:feature_class":"P",
    "gn:feature_code":"PPL",
    "gn:name":"Novi Lazi",
    "gn:population":127,
    "gn:timezone":"Europe/Ljubljana",
    "iso:country":"SI",
    "name:bos_x_preferred":[
        "Novi Lazi"
    ],
    "name:ceb_x_preferred":[
        "Novi Lazi"
    ],
    "name:hrv_x_preferred":[
        "Novi Lazi"
    ],
    "name:nld_x_preferred":[
        "Novi Lazi"
    ],
    "name:pol_x_preferred":[
        "Novi Lazi"
    ],
    "name:ron_x_preferred":[
        "Novi Lazi"
    ],
    "name:slv_x_preferred":[
        "Novi Lazi"
    ],
    "name:ukr_x_preferred":[
        "\u041d\u043e\u0432\u0456 \u041b\u0430\u0437\u0456"
    ],
    "wof:name":"Novi Lazi",
    "wof:placetype":"locality",
    "wof:population":127
},
  "geometry": {"coordinates":[14.8475,45.57222],"type":"Point"}
}