{
  "type": "Feature",
  "properties": {
    "gn:admin1_code":"H7",
    "gn:asciiname":"Novi Lazi",
    "gn:country_code":"SI",
    "gn:dem":541,
    "gn:feature_class":"P",
    "gn:feature_code":"PPL",
    "gn:name":"Novi Lazi",
    "gn:population":127,
    "gn:timezone":"Europe/Ljubljana",
    "iso:country":"SI",
    "wof:name":"Novi Lazi",
    "wof:placetype":"locality",
    "wof:population":127
},
  "geometry": {"coordinates":[14.8475,45.57222],"type":"Point"}
}