{
  "type": "Feature",
  "properties": {
    "gn:admin1_code":"44",
    "gn:asciiname":"Kosi",
    "gn:country_code":"SI",
    "gn:dem":430,
    "gn:feature_class":"P",
    "gn:feature_code":"PPL",
    "gn:name":"Kosi",
    "gn:population":0,
    "gn:timezone":"Europe/Ljubljana",
    "iso:country":"SI",
    "wof:name":"Kosi",
    "wof:placetype":"locality"
},
  "geometry": {"coordinates":[13.64081,46.13303],"type":"Point"}
}