{
  "type": "Feature",
  "properties": {
    "gn:admin1_code":"J2",
    "gn:asciiname":"Meljski Hrib",
    "gn:country_code":"SI",
    "gn:dem":345,
    "gn:feature_class":"P",
    "gn:feature_code":"PPL",
    "gn:name":"Meljski Hrib",
    "gn:population":289,
    "gn:timezone":"Europe/Ljubljana",
    "iso:country":"SI",
    "wof:name":"Meljski Hrib",
    "wof:placetype":"locality",
    "wof:population":289
},
  "geometry": {"coordinates":[15.66667,46.56667],"type":"Point"}
}