{
  "type": "Feature",
  "properties": {
    "gn:admin1_code":"J2",
    "gn:asciiname":"Meljski Hrib",
    "gn:country_code":"SI",
    "gn:dem":345,
    "gn:feature_class":"P",
    "gn:feature_code":"PPL",
    "gn:name":"Meljski Hrib",
    "gn:population":289,
    "gn:timezone":"Europe/Ljubljana",
    "iso:country":"SI",
    "name:bos_x_preferred":[
        "Meljski Hrib"
    ],
    "name:bul_x_preferred":[
        "\u041c\u0435\u043b\u0441\u043a\u0438 \u0425\u0440\u0438\u0431"
    ],
    "name:ceb_x_preferred":[
        "Meljski Hrib"
    ],
    "name:nld_x_preferred":[
        "Meljski Hrib"
    ],
    "name:pol_x_preferred":[
        "Meljski Hrib"
    ],
    "name:ron_x_preferred":[
        "Meljski Hrib"
    ],
    "name:sco_x_preferred":[
        "Meljski Hrib"
    ],
    "name:slv_x_preferred":[
        "Meljski Hrib"
    ],
    "name:ukr_x_preferred":[
        "\u041c\u0435\u043b\u044c\u0441\u044c\u043a\u0438\u0439 \u0425\u0440\u0438\u0431"
    ],
    "wof:name":"Meljski Hrib",
    "wof:placetype":"locality",
    "wof:population":289
},
  "geometry": {"coordinates":[15.66667,46.56667],"type":"Point"}
}