{
  "type": "Feature",
  "properties": {
    "gn:admin1_code":"54",
    "gn:asciiname":"Anze",
    "gn:country_code":"SI",
    "gn:dem":270,
    "gn:feature_class":"P",
    "gn:feature_code":"PPL",
    "gn:name":"An\u017ee",
    "gn:population":110,
    "gn:timezone":"Europe/Ljubljana",
    "iso:country":"SI",
    "name:bos_x_preferred":[
        "An\u017ee"
    ],
    "name:ceb_x_preferred":[
        "An\u017ee"
    ],
    "name:hrv_x_preferred":[
        "An\u017ee"
    ],
    "name:nld_x_preferred":[
        "An\u017ee"
    ],
    "name:pol_x_preferred":[
        "An\u017ee"
    ],
    "name:ron_x_preferred":[
        "An\u017ee"
    ],
    "name:slv_x_preferred":[
        "An\u017ee"
    ],
    "name:ukr_x_preferred":[
        "\u0410\u043d\u0436\u0435"
    ],
    "wof:name":"Anze",
    "wof:placetype":"locality",
    "wof:population":110
},
  "geometry": {"coordinates":[15.51209,45.992],"type":"Point"}
}