{
  "type": "Feature",
  "properties": {
    "gn:admin1_code":"D4",
    "gn:asciiname":"Babna Gora",
    "gn:country_code":"SI",
    "gn:dem":320,
    "gn:feature_class":"P",
    "gn:feature_code":"PPL",
    "gn:name":"Babna Gora",
    "gn:population":24,
    "gn:timezone":"Europe/Ljubljana",
    "iso:country":"SI",
    "name:bos_x_preferred":[
        "Babna Gora"
    ],
    "name:hrv_x_preferred":[
        "Babna Gora"
    ],
    "name:nld_x_preferred":[
        "Babna Gora"
    ],
    "name:pol_x_preferred":[
        "Babna Gora"
    ],
    "name:ron_x_preferred":[
        "Babna Gora"
    ],
    "name:slv_x_preferred":[
        "Babna Gora"
    ],
    "name:ukr_x_preferred":[
        "\u0411\u0430\u0431\u043d\u0430 \u0413\u043e\u0440\u0430"
    ],
    "wof:name":"Babna Gora",
    "wof:placetype":"locality",
    "wof:population":24
},
  "geometry": {"coordinates":[14.91486,45.89538],"type":"Point"}
}