{
  "type": "Feature",
  "properties": {
    "gn:admin1_code":"D4",
    "gn:asciiname":"Babna Gora",
    "gn:country_code":"SI",
    "gn:dem":320,
    "gn:feature_class":"P",
    "gn:feature_code":"PPL",
    "gn:name":"Babna Gora",
    "gn:population":24,
    "gn:timezone":"Europe/Ljubljana",
    "iso:country":"SI",
    "wof:name":"Babna Gora",
    "wof:placetype":"locality",
    "wof:population":24
},
  "geometry": {"coordinates":[14.91486,45.89538],"type":"Point"}
}