{
  "type": "Feature",
  "properties": {
    "iso:country":"SI",
    "wof:name":"Spodnje Gameljne",
    "wof:placetype":"neighbourhood"
},
  "geometry": {"coordinates":[14.50290283924098,46.12219135770422],"type":"Point"}
}