{
  "type": "Feature",
  "properties": {
    "gn:admin1_code":"F6",
    "gn:asciiname":"Glina",
    "gn:country_code":"SI",
    "gn:dem":754,
    "gn:feature_class":"P",
    "gn:feature_code":"PPL",
    "gn:name":"Glina",
    "gn:population":32,
    "gn:timezone":"Europe/Ljubljana",
    "iso:country":"SI",
    "name:bos_x_preferred":[
        "Glina"
    ],
    "name:nld_x_preferred":[
        "Glina"
    ],
    "name:pol_x_preferred":[
        "Glina"
    ],
    "name:ron_x_preferred":[
        "Glina"
    ],
    "name:slv_x_preferred":[
        "Glina"
    ],
    "name:ukr_x_preferred":[
        "\u0413\u043b\u0438\u043d\u0430"
    ],
    "wof:name":"Glina",
    "wof:placetype":"locality",
    "wof:population":32
},
  "geometry": {"coordinates":[14.49583,45.77167],"type":"Point"}
}