{
  "type": "Feature",
  "properties": {
    "gn:admin1_code":"B3",
    "gn:asciiname":"Plodrsnica",
    "gn:country_code":"SI",
    "gn:dem":340,
    "gn:feature_class":"P",
    "gn:feature_code":"PPL",
    "gn:name":"Plodr\u0161nica",
    "gn:population":124,
    "gn:timezone":"Europe/Ljubljana",
    "iso:country":"SI",
    "wof:name":"Plodrsnica",
    "wof:placetype":"locality",
    "wof:population":124
},
  "geometry": {"coordinates":[15.76682,46.64533],"type":"Point"}
}