{
  "type": "Feature",
  "properties": {
    "gn:admin1_code":"B3",
    "gn:asciiname":"Plodrsnica",
    "gn:country_code":"SI",
    "gn:dem":340,
    "gn:feature_class":"P",
    "gn:feature_code":"PPL",
    "gn:name":"Plodr\u0161nica",
    "gn:population":124,
    "gn:timezone":"Europe/Ljubljana",
    "iso:country":"SI",
    "name:bos_x_preferred":[
        "Plodr\u0161nica"
    ],
    "name:ceb_x_preferred":[
        "Plodr\u0161nica"
    ],
    "name:nld_x_preferred":[
        "Plodr\u0161nica"
    ],
    "name:pol_x_preferred":[
        "Plodr\u0161nica"
    ],
    "name:ron_x_preferred":[
        "Plodr\u0161nica"
    ],
    "name:slv_x_preferred":[
        "Plodr\u0161nica"
    ],
    "name:ukr_x_preferred":[
        "\u041f\u043b\u043e\u0434\u0440\u0448\u043d\u0438\u0446\u044f"
    ],
    "wof:name":"Plodrsnica",
    "wof:placetype":"locality",
    "wof:population":124
},
  "geometry": {"coordinates":[15.76682,46.64533],"type":"Point"}
}