{
  "type": "Feature",
  "properties": {
    "gn:admin1_code":"O1",
    "gn:asciiname":"Medribnik",
    "gn:country_code":"SI",
    "gn:dem":248,
    "gn:feature_class":"P",
    "gn:feature_code":"PPL",
    "gn:name":"Medribnik",
    "gn:population":144,
    "gn:timezone":"Europe/Ljubljana",
    "iso:country":"SI",
    "wof:name":"Medribnik",
    "wof:placetype":"locality",
    "wof:population":144
},
  "geometry": {"coordinates":[16.00515,46.32299],"type":"Point"}
}