{
  "type": "Feature",
  "properties": {
    "gn:admin1_code":"O1",
    "gn:asciiname":"Medribnik",
    "gn:country_code":"SI",
    "gn:dem":248,
    "gn:feature_class":"P",
    "gn:feature_code":"PPL",
    "gn:name":"Medribnik",
    "gn:population":144,
    "gn:timezone":"Europe/Ljubljana",
    "iso:country":"SI",
    "name:bos_x_preferred":[
        "Medribnik"
    ],
    "name:ceb_x_preferred":[
        "Medribnik"
    ],
    "name:nld_x_preferred":[
        "Medribnik"
    ],
    "name:pol_x_preferred":[
        "Medribnik"
    ],
    "name:ron_x_preferred":[
        "Medribnik"
    ],
    "name:slv_x_preferred":[
        "Medribnik"
    ],
    "name:ukr_x_preferred":[
        "\u041c\u0435\u0434\u0440\u0438\u0431\u043d\u0438\u043a"
    ],
    "wof:name":"Medribnik",
    "wof:placetype":"locality",
    "wof:population":144
},
  "geometry": {"coordinates":[16.00515,46.32299],"type":"Point"}
}