{
  "type": "Feature",
  "properties": {
    "gn:admin1_code":"27",
    "gn:asciiname":"Dolenje Brdo",
    "gn:country_code":"SI",
    "gn:dem":551,
    "gn:feature_class":"P",
    "gn:feature_code":"PPL",
    "gn:name":"Dolenje Brdo",
    "gn:population":79,
    "gn:timezone":"Europe/Ljubljana",
    "iso:country":"SI",
    "name:bos_x_preferred":[
        "Dolenje Brdo"
    ],
    "name:hrv_x_preferred":[
        "Dolenje Brdo"
    ],
    "name:nld_x_preferred":[
        "Dolenje Brdo"
    ],
    "name:pol_x_preferred":[
        "Dolenje Brdo"
    ],
    "name:ron_x_preferred":[
        "Dolenje Brdo"
    ],
    "name:slv_x_preferred":[
        "Dolenje Brdo"
    ],
    "name:ukr_x_preferred":[
        "\u0414\u043e\u043b\u0435\u043d\u0454 \u0411\u0440\u0434\u043e"
    ],
    "wof:name":"Dolenje Brdo",
    "wof:placetype":"locality",
    "wof:population":79
},
  "geometry": {"coordinates":[14.15299,46.12334],"type":"Point"}
}