{
  "type": "Feature",
  "properties": {
    "gn:admin1_code":"O5",
    "gn:asciiname":"Pecke",
    "gn:country_code":"SI",
    "gn:dem":257,
    "gn:feature_class":"P",
    "gn:feature_code":"PPL",
    "gn:name":"Pe\u010dke",
    "gn:population":287,
    "gn:timezone":"Europe/Ljubljana",
    "iso:country":"SI",
    "name:bos_x_preferred":[
        "Pe\u010dke"
    ],
    "name:ceb_x_preferred":[
        "Pe\u010dke"
    ],
    "name:nld_x_preferred":[
        "Pe\u010dke"
    ],
    "name:pol_x_preferred":[
        "Pe\u010dke"
    ],
    "name:ron_x_preferred":[
        "Pe\u010dke"
    ],
    "name:slv_x_preferred":[
        "Pe\u010dke"
    ],
    "name:ukr_x_preferred":[
        "\u041f\u0435\u0447\u043a\u0435"
    ],
    "name:und_x_variant":[
        "Pe\u010dke"
    ],
    "wof:name":"Pecke",
    "wof:placetype":"locality",
    "wof:population":287
},
  "geometry": {"coordinates":[15.675,46.33472],"type":"Point"}
}