{
  "type": "Feature",
  "properties": {
    "gn:admin1_code":"17",
    "gn:asciiname":"Bistrica",
    "gn:country_code":"SI",
    "gn:dem":488,
    "gn:feature_class":"P",
    "gn:feature_code":"PPL",
    "gn:name":"Bistrica",
    "gn:population":3,
    "gn:timezone":"Europe/Ljubljana",
    "iso:country":"SI",
    "name:bos_x_preferred":[
        "Bistrica"
    ],
    "name:hrv_x_preferred":[
        "Bistrica"
    ],
    "name:nld_x_preferred":[
        "Bistrica"
    ],
    "name:pol_x_preferred":[
        "Bistrica"
    ],
    "name:ron_x_preferred":[
        "Bistrica"
    ],
    "name:slv_x_preferred":[
        "Bistrica"
    ],
    "name:ukr_x_preferred":[
        "\u0411\u0438\u0441\u0442\u0440\u0438\u0446\u044f"
    ],
    "wof:name":"Bistrica",
    "wof:placetype":"locality",
    "wof:population":3
},
  "geometry": {"coordinates":[15.11029,45.5698],"type":"Point"}
}