{
  "type": "Feature",
  "properties": {
    "gn:admin1_code":"17",
    "gn:asciiname":"Bistrica",
    "gn:country_code":"SI",
    "gn:dem":488,
    "gn:feature_class":"P",
    "gn:feature_code":"PPL",
    "gn:name":"Bistrica",
    "gn:population":3,
    "gn:timezone":"Europe/Ljubljana",
    "iso:country":"SI",
    "wof:name":"Bistrica",
    "wof:placetype":"locality",
    "wof:population":3
},
  "geometry": {"coordinates":[15.11029,45.5698],"type":"Point"}
}