{
  "type": "Feature",
  "properties": {
    "gn:admin1_code":"38",
    "gn:asciiname":"Susak",
    "gn:country_code":"SI",
    "gn:dem":608,
    "gn:feature_class":"P",
    "gn:feature_code":"PPL",
    "gn:name":"Su\u0161ak",
    "gn:population":92,
    "gn:timezone":"Europe/Ljubljana",
    "iso:country":"SI",
    "name:bos_x_preferred":[
        "Su\u0161ak"
    ],
    "name:hrv_x_preferred":[
        "Su\u0161ak"
    ],
    "name:nld_x_preferred":[
        "Su\u0161ak"
    ],
    "name:pol_x_preferred":[
        "Su\u0161ak"
    ],
    "name:ron_x_preferred":[
        "Su\u0161ak"
    ],
    "name:slv_x_preferred":[
        "Su\u0161ak"
    ],
    "name:ukr_x_preferred":[
        "\u0421\u0443\u0448\u0430\u043a"
    ],
    "name:und_x_variant":[
        "Sussa"
    ],
    "wof:name":"Susak",
    "wof:placetype":"locality",
    "wof:population":92
},
  "geometry": {"coordinates":[14.32972,45.49056],"type":"Point"}
}