{
  "type": "Feature",
  "properties": {
    "gn:admin1_code":"38",
    "gn:asciiname":"Susak",
    "gn:country_code":"SI",
    "gn:dem":608,
    "gn:feature_class":"P",
    "gn:feature_code":"PPL",
    "gn:name":"Su\u0161ak",
    "gn:population":92,
    "gn:timezone":"Europe/Ljubljana",
    "iso:country":"SI",
    "name:und_x_variant":[
        "Sussa",
        "Su\u0161ak"
    ],
    "wof:name":"Susak",
    "wof:placetype":"locality",
    "wof:population":92
},
  "geometry": {"coordinates":[14.32972,45.49056],"type":"Point"}
}