{
  "type": "Feature",
  "properties": {
    "gn:admin1_code":"D2",
    "gn:asciiname":"Ravne",
    "gn:country_code":"SI",
    "gn:dem":695,
    "gn:feature_class":"P",
    "gn:feature_code":"PPL",
    "gn:name":"Ravne",
    "gn:population":0,
    "gn:timezone":"Europe/Ljubljana",
    "iso:country":"SI",
    "wof:name":"Ravne",
    "wof:placetype":"locality"
},
  "geometry": {"coordinates":[13.75666,46.12955],"type":"Point"}
}