{
  "type": "Feature",
  "properties": {
    "gn:admin1_code":"D2",
    "gn:asciiname":"Ravne",
    "gn:country_code":"SI",
    "gn:dem":695,
    "gn:feature_class":"P",
    "gn:feature_code":"PPL",
    "gn:name":"Ravne",
    "gn:population":0,
    "gn:timezone":"Europe/Ljubljana",
    "iso:country":"SI",
    "name:bos_x_preferred":[
        "Ravne"
    ],
    "name:ceb_x_preferred":[
        "Ravne"
    ],
    "name:deu_x_preferred":[
        "Ravne"
    ],
    "name:fra_x_preferred":[
        "Ravne"
    ],
    "name:hrv_x_preferred":[
        "Ravne"
    ],
    "name:nld_x_preferred":[
        "Ravne"
    ],
    "name:ron_x_preferred":[
        "Ravne"
    ],
    "name:rus_x_preferred":[
        "\u0420\u0430\u0432\u043d\u0435"
    ],
    "name:sco_x_preferred":[
        "Ravne"
    ],
    "name:slv_x_preferred":[
        "Ravne"
    ],
    "name:srp_x_preferred":[
        "\u0420\u0430\u0432\u043d\u0435"
    ],
    "name:swe_x_preferred":[
        "Ravne"
    ],
    "wof:name":"Ravne",
    "wof:placetype":"locality"
},
  "geometry": {"coordinates":[13.75666,46.12955],"type":"Point"}
}