{
  "type": "Feature",
  "properties": {
    "gn:admin1_code":"D5",
    "gn:asciiname":"Grahovse",
    "gn:country_code":"SI",
    "gn:dem":1013,
    "gn:feature_class":"P",
    "gn:feature_code":"PPL",
    "gn:name":"Grahov\u0161e",
    "gn:population":136,
    "gn:timezone":"Europe/Ljubljana",
    "iso:country":"SI",
    "name:bos_x_preferred":[
        "Grahov\u0161e"
    ],
    "name:ceb_x_preferred":[
        "Grahov\u0161e"
    ],
    "name:pol_x_preferred":[
        "Grahov\u0161e"
    ],
    "name:ron_x_preferred":[
        "Grahov\u0161e"
    ],
    "name:slv_x_preferred":[
        "Grahov\u0161e"
    ],
    "name:ukr_x_preferred":[
        "\u0413\u0440\u0430\u0445\u043e\u0432\u0448\u0435"
    ],
    "name:und_x_variant":[
        "Grahov\u0161e"
    ],
    "wof:name":"Grahovse",
    "wof:placetype":"locality",
    "wof:population":136
},
  "geometry": {"coordinates":[14.37667,46.36725],"type":"Point"}
}