{
  "type": "Feature",
  "properties": {
    "gn:admin1_code":"12",
    "gn:asciiname":"Dvorje",
    "gn:country_code":"SI",
    "gn:dem":609,
    "gn:feature_class":"P",
    "gn:feature_code":"PPL",
    "gn:name":"Dvorje",
    "gn:population":431,
    "gn:timezone":"Europe/Ljubljana",
    "iso:country":"SI",
    "wof:name":"Dvorje",
    "wof:placetype":"locality",
    "wof:population":431
},
  "geometry": {"coordinates":[14.48353,46.26726],"type":"Point"}
}