{
  "type": "Feature",
  "properties": {
    "gn:admin1_code":"12",
    "gn:asciiname":"Dvorje",
    "gn:country_code":"SI",
    "gn:dem":609,
    "gn:feature_class":"P",
    "gn:feature_code":"PPL",
    "gn:name":"Dvorje",
    "gn:population":431,
    "gn:timezone":"Europe/Ljubljana",
    "iso:country":"SI",
    "name:bos_x_preferred":[
        "Dvorje"
    ],
    "name:ceb_x_preferred":[
        "Dvorje"
    ],
    "name:nld_x_preferred":[
        "Dvorje"
    ],
    "name:pol_x_preferred":[
        "Dvorje"
    ],
    "name:ron_x_preferred":[
        "Dvorje"
    ],
    "name:slv_x_preferred":[
        "Dvorje"
    ],
    "name:ukr_x_preferred":[
        "\u0414\u0432\u043e\u0440\u0454"
    ],
    "wof:name":"Dvorje",
    "wof:placetype":"locality",
    "wof:population":431
},
  "geometry": {"coordinates":[14.48353,46.26726],"type":"Point"}
}