{
  "type": "Feature",
  "properties": {
    "gn:admin1_code":"B6",
    "gn:asciiname":"Zabukovje nad Sevnico",
    "gn:country_code":"SI",
    "gn:dem":535,
    "gn:feature_class":"P",
    "gn:feature_code":"PPL",
    "gn:name":"Zabukovje nad Sevnico",
    "gn:population":181,
    "gn:timezone":"Europe/Ljubljana",
    "iso:country":"SI",
    "name:und_x_variant":[
        "Zabukovje",
        "Zabukovje nad Sevnico"
    ],
    "wof:name":"Zabukovje nad Sevnico",
    "wof:placetype":"locality",
    "wof:population":181
},
  "geometry": {"coordinates":[15.3675,46.055],"type":"Point"}
}