{
  "type": "Feature",
  "properties": {
    "gn:admin1_code":"B6",
    "gn:asciiname":"Zabukovje nad Sevnico",
    "gn:country_code":"SI",
    "gn:dem":535,
    "gn:feature_class":"P",
    "gn:feature_code":"PPL",
    "gn:name":"Zabukovje nad Sevnico",
    "gn:population":181,
    "gn:timezone":"Europe/Ljubljana",
    "iso:country":"SI",
    "name:bos_x_preferred":[
        "Zabukovje nad Sevnico"
    ],
    "name:ceb_x_preferred":[
        "Zabukovje nad Sevnico"
    ],
    "name:nld_x_preferred":[
        "Zabukovje nad Sevnico"
    ],
    "name:pol_x_preferred":[
        "Zabukovje nad Sevnico"
    ],
    "name:ron_x_preferred":[
        "Zabukovje nad Sevnico"
    ],
    "name:slv_x_preferred":[
        "Zabukovje nad Sevnico"
    ],
    "name:ukr_x_preferred":[
        "\u0417\u0430\u0431\u0443\u043a\u043e\u0432\u0454-\u043d\u0430\u0434-\u0421\u0435\u0432\u043d\u0438\u0446\u043e"
    ],
    "name:und_x_variant":[
        "Zabukovje",
        "Zabukovje nad Sevnico"
    ],
    "name:urd_x_preferred":[
        "\u0632\u0628\u06a9\u0648\u0648\u062c\u06d2 \u0646\u0627\u062f \u0633\u0648\u0646\u06cc\u06a9\u0648"
    ],
    "wof:name":"Zabukovje nad Sevnico",
    "wof:placetype":"locality",
    "wof:population":181
},
  "geometry": {"coordinates":[15.3675,46.055],"type":"Point"}
}