{
  "type": "Feature",
  "properties": {
    "gn:admin1_code":"A3",
    "gn:asciiname":"Gorica",
    "gn:country_code":"SI",
    "gn:dem":493,
    "gn:feature_class":"P",
    "gn:feature_code":"PPL",
    "gn:name":"Gorica",
    "gn:population":83,
    "gn:timezone":"Europe/Ljubljana",
    "iso:country":"SI",
    "name:bos_x_preferred":[
        "Gorica"
    ],
    "name:hrv_x_preferred":[
        "Gorica"
    ],
    "name:nld_x_preferred":[
        "Gorica"
    ],
    "name:pol_x_preferred":[
        "Gorica"
    ],
    "name:ron_x_preferred":[
        "Gorica"
    ],
    "name:slv_x_preferred":[
        "Gorica"
    ],
    "name:ukr_x_preferred":[
        "\u0413\u043e\u0440\u0438\u0446\u044f"
    ],
    "wof:name":"Gorica",
    "wof:placetype":"locality",
    "wof:population":83
},
  "geometry": {"coordinates":[14.19526,46.34383],"type":"Point"}
}