{
  "type": "Feature",
  "properties": {
    "gn:admin1_code":"17",
    "gn:asciiname":"Dolnja Paka",
    "gn:country_code":"SI",
    "gn:dem":179,
    "gn:feature_class":"P",
    "gn:feature_code":"PPL",
    "gn:name":"Dolnja Paka",
    "gn:population":39,
    "gn:timezone":"Europe/Ljubljana",
    "iso:country":"SI",
    "name:bos_x_preferred":[
        "Dolnja Paka"
    ],
    "name:hrv_x_preferred":[
        "Dolnja Paka"
    ],
    "name:nld_x_preferred":[
        "Dolnja Paka"
    ],
    "name:pol_x_preferred":[
        "Dolnja Paka"
    ],
    "name:ron_x_preferred":[
        "Dolnja Paka"
    ],
    "name:slv_x_preferred":[
        "Dolnja Paka"
    ],
    "name:ukr_x_preferred":[
        "\u0414\u043e\u043b\u043d\u044f \u041f\u0430\u043a\u0430"
    ],
    "wof:name":"Dolnja Paka",
    "wof:placetype":"locality",
    "wof:population":39
},
  "geometry": {"coordinates":[15.16809,45.57862],"type":"Point"}
}