{
  "type": "Feature",
  "properties": {
    "gn:admin1_code":"17",
    "gn:asciiname":"Dolnja Paka",
    "gn:country_code":"SI",
    "gn:dem":179,
    "gn:feature_class":"P",
    "gn:feature_code":"PPL",
    "gn:name":"Dolnja Paka",
    "gn:population":39,
    "gn:timezone":"Europe/Ljubljana",
    "iso:country":"SI",
    "wof:name":"Dolnja Paka",
    "wof:placetype":"locality",
    "wof:population":39
},
  "geometry": {"coordinates":[15.16809,45.57862],"type":"Point"}
}