{
  "type": "Feature",
  "properties": {
    "gn:admin1_code":"C4",
    "gn:asciiname":"Spodnja Pristava",
    "gn:country_code":"SI",
    "gn:dem":306,
    "gn:feature_class":"P",
    "gn:feature_code":"PPL",
    "gn:name":"Spodnja Pristava",
    "gn:population":36,
    "gn:timezone":"Europe/Ljubljana",
    "iso:country":"SI",
    "name:bos_x_preferred":[
        "Spodnja Pristava"
    ],
    "name:hrv_x_preferred":[
        "Spodnja Pristava"
    ],
    "name:nld_x_preferred":[
        "Spodnja Pristava"
    ],
    "name:pol_x_preferred":[
        "Spodnja Pristava"
    ],
    "name:ron_x_preferred":[
        "Spodnja Pristava"
    ],
    "name:slv_x_preferred":[
        "Spodnja Pristava"
    ],
    "name:ukr_x_preferred":[
        "\u0421\u043f\u043e\u0434\u043d\u044f \u041f\u0440\u0438\u0441\u0442\u0430\u0432\u0430"
    ],
    "wof:name":"Spodnja Pristava",
    "wof:placetype":"locality",
    "wof:population":36
},
  "geometry": {"coordinates":[15.47247,46.32608],"type":"Point"}
}