{
  "type": "Feature",
  "properties": {
    "gn:admin1_code":"17",
    "gn:asciiname":"Sela pri Otovcu",
    "gn:country_code":"SI",
    "gn:dem":197,
    "gn:feature_class":"P",
    "gn:feature_code":"PPL",
    "gn:name":"Sela pri Otovcu",
    "gn:population":69,
    "gn:timezone":"Europe/Ljubljana",
    "iso:country":"SI",
    "wof:name":"Sela pri Otovcu",
    "wof:placetype":"locality",
    "wof:population":69
},
  "geometry": {"coordinates":[15.16254,45.59952],"type":"Point"}
}