{
  "type": "Feature",
  "properties": {
    "gn:admin1_code":"17",
    "gn:asciiname":"Sela pri Otovcu",
    "gn:country_code":"SI",
    "gn:dem":197,
    "gn:feature_class":"P",
    "gn:feature_code":"PPL",
    "gn:name":"Sela pri Otovcu",
    "gn:population":69,
    "gn:timezone":"Europe/Ljubljana",
    "iso:country":"SI",
    "name:bos_x_preferred":[
        "Sela pri Otovcu"
    ],
    "name:hrv_x_preferred":[
        "Sela pri Otovcu"
    ],
    "name:nld_x_preferred":[
        "Sela pri Otovcu"
    ],
    "name:pol_x_preferred":[
        "Sela pri Otovcu"
    ],
    "name:ron_x_preferred":[
        "Sela pri Otovcu"
    ],
    "name:slv_x_preferred":[
        "Sela pri Otovcu"
    ],
    "name:ukr_x_preferred":[
        "\u0421\u0435\u043b\u0430-\u043f\u0440\u0438-\u041e\u0442\u043e\u0432\u0446\u0443"
    ],
    "wof:name":"Sela pri Otovcu",
    "wof:placetype":"locality",
    "wof:population":69
},
  "geometry": {"coordinates":[15.16254,45.59952],"type":"Point"}
}