{
  "type": "Feature",
  "properties": {
    "gn:admin1_code":"D4",
    "gn:asciiname":"Velika Sevnica",
    "gn:country_code":"SI",
    "gn:dem":330,
    "gn:feature_class":"P",
    "gn:feature_code":"PPL",
    "gn:name":"Velika \u0160evnica",
    "gn:population":54,
    "gn:timezone":"Europe/Ljubljana",
    "iso:country":"SI",
    "name:bos_x_preferred":[
        "Velika \u0160evnica"
    ],
    "name:fas_x_preferred":[
        "\u0648\u0644\u06cc\u06a9\u0627 \u0634\u0648\u0646\u06cc\u06a9\u0627"
    ],
    "name:hrv_x_preferred":[
        "Velika \u0160evnica"
    ],
    "name:nld_x_preferred":[
        "Velika \u0160evnica"
    ],
    "name:pol_x_preferred":[
        "Velika \u0160evnica"
    ],
    "name:ron_x_preferred":[
        "Velika \u0160evnica"
    ],
    "name:slv_x_preferred":[
        "Velika \u0160evnica"
    ],
    "name:ukr_x_preferred":[
        "\u0412\u0435\u043b\u0438\u043a\u0430 \u0428\u0435\u0432\u043d\u0438\u0446\u044f"
    ],
    "wof:name":"Velika Sevnica",
    "wof:placetype":"locality",
    "wof:population":54
},
  "geometry": {"coordinates":[15.00009,45.94249],"type":"Point"}
}