{
  "type": "Feature",
  "properties": {
    "gn:admin1_code":"H1",
    "gn:asciiname":"Hotinja Vas",
    "gn:country_code":"SI",
    "gn:dem":268,
    "gn:feature_class":"P",
    "gn:feature_code":"PPL",
    "gn:name":"Hotinja Vas",
    "gn:population":1344,
    "gn:timezone":"Europe/Ljubljana",
    "iso:country":"SI",
    "name:bos_x_preferred":[
        "Hotinja vas"
    ],
    "name:ceb_x_preferred":[
        "Hotinja Vas"
    ],
    "name:nld_x_preferred":[
        "Hotinja vas"
    ],
    "name:pol_x_preferred":[
        "Hotinja vas"
    ],
    "name:ron_x_preferred":[
        "Hotinja vas"
    ],
    "name:slv_x_preferred":[
        "Hotinja vas"
    ],
    "name:ukr_x_preferred":[
        "\u0425\u043e\u0442\u0438\u043d\u044f \u0412\u0430\u0441"
    ],
    "wof:name":"Hotinja Vas",
    "wof:placetype":"locality",
    "wof:population":1344
},
  "geometry": {"coordinates":[15.66667,46.46667],"type":"Point"}
}