{
  "type": "Feature",
  "properties": {
    "gn:admin1_code":"09",
    "gn:asciiname":"Preserje",
    "gn:country_code":"SI",
    "gn:dem":360,
    "gn:feature_class":"P",
    "gn:feature_code":"PPL",
    "gn:name":"Preserje",
    "gn:population":336,
    "gn:timezone":"Europe/Ljubljana",
    "iso:country":"SI",
    "wof:name":"Preserje",
    "wof:placetype":"locality",
    "wof:population":336
},
  "geometry": {"coordinates":[14.41889,45.95694],"type":"Point"}
}