{
  "type": "Feature",
  "properties": {
    "gn:admin1_code":"91",
    "gn:asciiname":"Radohova Vas",
    "gn:country_code":"SI",
    "gn:dem":547,
    "gn:feature_class":"P",
    "gn:feature_code":"PPL",
    "gn:name":"Radohova Vas",
    "gn:population":0,
    "gn:timezone":"Europe/Ljubljana",
    "iso:country":"SI",
    "name:bos_x_preferred":[
        "Radohova vas"
    ],
    "name:ceb_x_preferred":[
        "Radohova Vas"
    ],
    "name:nld_x_preferred":[
        "Radohova vas"
    ],
    "name:pol_x_preferred":[
        "Radohova vas"
    ],
    "name:ron_x_preferred":[
        "Radohova vas"
    ],
    "name:slv_x_preferred":[
        "Radohova vas"
    ],
    "name:ukr_x_preferred":[
        "\u0420\u0430\u0434\u043e\u0445\u043e\u0432\u0430 \u0412\u0430\u0441"
    ],
    "wof:name":"Radohova Vas",
    "wof:placetype":"locality"
},
  "geometry": {"coordinates":[14.2025,45.67528],"type":"Point"}
}