{
  "type": "Feature",
  "properties": {
    "gn:admin1_code":"L9",
    "gn:asciiname":"Jablaniski Potok",
    "gn:country_code":"SI",
    "gn:dem":449,
    "gn:feature_class":"P",
    "gn:feature_code":"PPL",
    "gn:name":"Jablani\u0161ki Potok",
    "gn:population":9,
    "gn:timezone":"Europe/Ljubljana",
    "iso:country":"SI",
    "name:bos_x_preferred":[
        "Jablani\u0161ki Potok"
    ],
    "name:nld_x_preferred":[
        "Jablani\u0161ki Potok"
    ],
    "name:pol_x_preferred":[
        "Jablani\u0161ki Potok"
    ],
    "name:ron_x_preferred":[
        "Jablani\u0161ki Potok"
    ],
    "name:slv_x_preferred":[
        "Jablani\u0161ki Potok"
    ],
    "name:ukr_x_preferred":[
        "\u042f\u0431\u043b\u0430\u043d\u0438\u0448\u043a\u0438\u0439 \u041f\u043e\u0442\u043e\u043a"
    ],
    "name:und_x_variant":[
        "Jablani\u0161ki Potok"
    ],
    "name:urd_x_preferred":[
        "\u062c\u0628\u0644\u0627\u0646\u06cc\u0634\u06a9\u06cc \u067e\u0648\u062a\u0648\u06a9"
    ],
    "wof:name":"Jablaniski Potok",
    "wof:placetype":"locality",
    "wof:population":9
},
  "geometry": {"coordinates":[14.8994,46.05155],"type":"Point"}
}