{
  "type": "Feature",
  "properties": {
    "iso:country":"SI",
    "wof:name":"Dobrunje",
    "wof:placetype":"neighbourhood"
},
  "geometry": {"coordinates":[14.58152378944378,46.0379668173362],"type":"Point"}
}