{
  "type": "Feature",
  "properties": {
    "gn:admin1_code":"32",
    "gn:asciiname":"Lobcek",
    "gn:country_code":"SI",
    "gn:dem":364,
    "gn:feature_class":"P",
    "gn:feature_code":"PPL",
    "gn:name":"Lob\u010dek",
    "gn:population":140,
    "gn:timezone":"Europe/Ljubljana",
    "iso:country":"SI",
    "name:bos_x_preferred":[
        "Lob\u010dek"
    ],
    "name:ceb_x_preferred":[
        "Lob\u010dek"
    ],
    "name:nld_x_preferred":[
        "Lob\u010dek"
    ],
    "name:pol_x_preferred":[
        "Lob\u010dek"
    ],
    "name:ron_x_preferred":[
        "Lob\u010dek"
    ],
    "name:slv_x_preferred":[
        "Lob\u010dek"
    ],
    "name:srp_x_preferred":[
        "\u041b\u043e\u0431\u0447\u0435\u043a"
    ],
    "name:ukr_x_preferred":[
        "\u041b\u043e\u0431\u0447\u0435\u043a"
    ],
    "wof:name":"Lobcek",
    "wof:placetype":"locality",
    "wof:population":140
},
  "geometry": {"coordinates":[14.68875,45.93581],"type":"Point"}
}