{
  "type": "Feature",
  "properties": {
    "gn:admin1_code":"32",
    "gn:asciiname":"Lobcek",
    "gn:country_code":"SI",
    "gn:dem":364,
    "gn:feature_class":"P",
    "gn:feature_code":"PPL",
    "gn:name":"Lob\u010dek",
    "gn:population":140,
    "gn:timezone":"Europe/Ljubljana",
    "iso:country":"SI",
    "name:und_x_variant":[
        "Lob\u010dek"
    ],
    "wof:name":"Lobcek",
    "wof:placetype":"locality",
    "wof:population":140
},
  "geometry": {"coordinates":[14.68875,45.93581],"type":"Point"}
}