{
  "type": "Feature",
  "properties": {
    "gn:admin1_code":"H9",
    "gn:asciiname":"Potok",
    "gn:country_code":"SI",
    "gn:dem":228,
    "gn:feature_class":"P",
    "gn:feature_code":"PPL",
    "gn:name":"Potok",
    "gn:population":75,
    "gn:timezone":"Europe/Ljubljana",
    "iso:country":"SI",
    "name:bos_x_preferred":[
        "Potok"
    ],
    "name:hrv_x_preferred":[
        "Potok"
    ],
    "name:nld_x_preferred":[
        "Potok"
    ],
    "name:pol_x_preferred":[
        "Potok"
    ],
    "name:ron_x_preferred":[
        "Potok"
    ],
    "name:sco_x_preferred":[
        "Potok"
    ],
    "name:slv_x_preferred":[
        "Potok"
    ],
    "name:ukr_x_preferred":[
        "\u041f\u043e\u0442\u043e\u043a"
    ],
    "wof:name":"Potok",
    "wof:placetype":"locality",
    "wof:population":75
},
  "geometry": {"coordinates":[14.87455,45.47533],"type":"Point"}
}