{
  "type": "Feature",
  "properties": {
    "gn:admin1_code":"H9",
    "gn:asciiname":"Potok",
    "gn:country_code":"SI",
    "gn:dem":228,
    "gn:feature_class":"P",
    "gn:feature_code":"PPL",
    "gn:name":"Potok",
    "gn:population":75,
    "gn:timezone":"Europe/Ljubljana",
    "iso:country":"SI",
    "wof:name":"Potok",
    "wof:placetype":"locality",
    "wof:population":75
},
  "geometry": {"coordinates":[14.87455,45.47533],"type":"Point"}
}