{
  "type": "Feature",
  "properties": {
    "gn:admin1_code":"I4",
    "gn:asciiname":"Kot",
    "gn:country_code":"SI",
    "gn:dem":162,
    "gn:feature_class":"P",
    "gn:feature_code":"PPL",
    "gn:name":"Kot",
    "gn:population":117,
    "gn:timezone":"Europe/Ljubljana",
    "iso:country":"SI",
    "wof:name":"Kot",
    "wof:placetype":"locality",
    "wof:population":117
},
  "geometry": {"coordinates":[16.38833,46.54417],"type":"Point"}
}