{
  "type": "Feature",
  "properties": {
    "gn:admin1_code":"I4",
    "gn:asciiname":"Kot",
    "gn:country_code":"SI",
    "gn:dem":162,
    "gn:feature_class":"P",
    "gn:feature_code":"PPL",
    "gn:name":"Kot",
    "gn:population":117,
    "gn:timezone":"Europe/Ljubljana",
    "iso:country":"SI",
    "name:bos_x_preferred":[
        "Kot"
    ],
    "name:ceb_x_preferred":[
        "Kot"
    ],
    "name:epo_x_preferred":[
        "Kot"
    ],
    "name:hrv_x_preferred":[
        "Kot"
    ],
    "name:hun_x_preferred":[
        "K\u00f3t"
    ],
    "name:nld_x_preferred":[
        "Kot"
    ],
    "name:pol_x_preferred":[
        "Kot"
    ],
    "name:ron_x_preferred":[
        "Kot"
    ],
    "name:slv_x_preferred":[
        "Kot"
    ],
    "name:ukr_x_preferred":[
        "\u041a\u043e\u0442"
    ],
    "wof:name":"Kot",
    "wof:placetype":"locality",
    "wof:population":117
},
  "geometry": {"coordinates":[16.38833,46.54417],"type":"Point"}
}