{
  "type": "Feature",
  "properties": {
    "gn:admin1_code":"H6",
    "gn:asciiname":"Spodnje Stranje",
    "gn:country_code":"SI",
    "gn:dem":420,
    "gn:feature_class":"P",
    "gn:feature_code":"PPL",
    "gn:name":"Spodnje Stranje",
    "gn:population":265,
    "gn:timezone":"Europe/Ljubljana",
    "iso:country":"SI",
    "wof:name":"Spodnje Stranje",
    "wof:placetype":"locality",
    "wof:population":265
},
  "geometry": {"coordinates":[14.59974,46.24798],"type":"Point"}
}