{
  "type": "Feature",
  "properties": {
    "gn:admin1_code":"84",
    "gn:asciiname":"Raven",
    "gn:country_code":"SI",
    "gn:dem":704,
    "gn:feature_class":"P",
    "gn:feature_code":"PPL",
    "gn:name":"Raven",
    "gn:population":0,
    "gn:timezone":"Europe/Ljubljana",
    "iso:country":"SI",
    "name:ang_x_preferred":[
        "Hr\u00e6fn"
    ],
    "name:ara_x_preferred":[
        "\u063a\u062f\u0627\u0641"
    ],
    "name:bre_x_preferred":[
        "Bran"
    ],
    "name:fas_x_preferred":[
        "\u063a\u0631\u0627\u0628"
    ],
    "name:fin_x_preferred":[
        "Korppi"
    ],
    "name:fra_x_preferred":[
        "Corbeau"
    ],
    "name:slv_x_historical":[
        "Ravna"
    ],
    "name:slv_x_preferred":[
        "Ravna"
    ],
    "name:srp_x_preferred":[
        "\u0413\u0430\u0432\u0440\u0430\u043d"
    ],
    "name:swe_x_preferred":[
        "Korp"
    ],
    "name:tha_x_preferred":[
        "\u0e19\u0e01\u0e40\u0e23\u0e40\u0e27\u0e19"
    ],
    "wof:name":"Raven",
    "wof:placetype":"locality"
},
  "geometry": {"coordinates":[13.71094,46.05096],"type":"Point"}
}