{
  "type": "Feature",
  "properties": {
    "gn:admin1_code":"84",
    "gn:asciiname":"Raven",
    "gn:country_code":"SI",
    "gn:dem":704,
    "gn:feature_class":"P",
    "gn:feature_code":"PPL",
    "gn:name":"Raven",
    "gn:population":0,
    "gn:timezone":"Europe/Ljubljana",
    "iso:country":"SI",
    "name:slv_x_historical":[
        "Ravna"
    ],
    "name:slv_x_preferred":[
        "Ravna"
    ],
    "wof:name":"Raven",
    "wof:placetype":"locality"
},
  "geometry": {"coordinates":[13.71094,46.05096],"type":"Point"}
}