{
  "type": "Feature",
  "properties": {
    "gn:admin1_code":"D8",
    "gn:asciiname":"Javorje",
    "gn:country_code":"SI",
    "gn:dem":497,
    "gn:feature_class":"P",
    "gn:feature_code":"PPL",
    "gn:name":"Javorje",
    "gn:population":12,
    "gn:timezone":"Europe/Ljubljana",
    "iso:country":"SI",
    "name:bos_x_preferred":[
        "Javorje"
    ],
    "name:nld_x_preferred":[
        "Javorje"
    ],
    "name:pol_x_preferred":[
        "Javorje"
    ],
    "name:ron_x_preferred":[
        "Javorje"
    ],
    "name:slv_x_preferred":[
        "Javorje"
    ],
    "name:ukr_x_preferred":[
        "\u042f\u0432\u043e\u0440\u0454"
    ],
    "name:urd_x_preferred":[
        "\u062c\u0648\u0648\u0631\u062c\u06d2"
    ],
    "wof:name":"Javorje",
    "wof:placetype":"locality",
    "wof:population":12
},
  "geometry": {"coordinates":[14.59779,45.86546],"type":"Point"}
}