{
  "type": "Feature",
  "properties": {
    "gn:admin1_code":"D8",
    "gn:asciiname":"Javorje",
    "gn:country_code":"SI",
    "gn:dem":497,
    "gn:feature_class":"P",
    "gn:feature_code":"PPL",
    "gn:name":"Javorje",
    "gn:population":12,
    "gn:timezone":"Europe/Ljubljana",
    "iso:country":"SI",
    "wof:name":"Javorje",
    "wof:placetype":"locality",
    "wof:population":12
},
  "geometry": {"coordinates":[14.59779,45.86546],"type":"Point"}
}