{
  "type": "Feature",
  "properties": {
    "gn:admin1_code":"O9",
    "gn:asciiname":"Sentjanz",
    "gn:country_code":"SI",
    "gn:dem":369,
    "gn:feature_class":"P",
    "gn:feature_code":"PPL",
    "gn:name":"\u0160entjan\u017e",
    "gn:population":237,
    "gn:timezone":"Europe/Ljubljana",
    "iso:country":"SI",
    "name:und_x_variant":[
        "\u0160entjan\u017e"
    ],
    "wof:name":"Sentjanz",
    "wof:placetype":"locality",
    "wof:population":237
},
  "geometry": {"coordinates":[14.89692,46.31638],"type":"Point"}
}