{
  "type": "Feature",
  "properties": {
    "gn:admin1_code":"91",
    "gn:asciiname":"Zagorje",
    "gn:country_code":"SI",
    "gn:dem":570,
    "gn:feature_class":"P",
    "gn:feature_code":"PPL",
    "gn:name":"Zagorje",
    "gn:population":351,
    "gn:timezone":"Europe/Ljubljana",
    "iso:country":"SI",
    "name:bos_x_preferred":[
        "Zagorje"
    ],
    "name:ceb_x_preferred":[
        "Zagorje"
    ],
    "name:hrv_x_preferred":[
        "Zagorje"
    ],
    "name:ita_x_preferred":[
        "Sagoria"
    ],
    "name:nld_x_preferred":[
        "Zagorje"
    ],
    "name:pol_x_preferred":[
        "Zagorje"
    ],
    "name:ron_x_preferred":[
        "Zagorje"
    ],
    "name:slv_x_preferred":[
        "Zagorje"
    ],
    "name:ukr_x_preferred":[
        "\u0417\u0430\u0433\u043e\u0440\u0454"
    ],
    "name:und_x_variant":[
        "Sagorje",
        "Sagoria",
        "Sag\u00f3ria San Martino",
        "Zagorje"
    ],
    "name:urd_x_preferred":[
        "\u0632\u06af\u0648\u0631\u062c\u06d2"
    ],
    "name:zho_x_preferred":[
        "\u624e\u6208\u5217"
    ],
    "wof:name":"Zagorje",
    "wof:placetype":"locality",
    "wof:population":351
},
  "geometry": {"coordinates":[14.22444,45.63972],"type":"Point"}
}