{
  "type": "Feature",
  "properties": {
    "gn:admin1_code":"A1",
    "gn:asciiname":"Janzev Vrh",
    "gn:country_code":"SI",
    "gn:dem":244,
    "gn:feature_class":"P",
    "gn:feature_code":"PPL",
    "gn:name":"Jan\u017eev Vrh",
    "gn:population":262,
    "gn:timezone":"Europe/Ljubljana",
    "iso:country":"SI",
    "name:und_x_variant":[
        "Jan\u017eev Vrh"
    ],
    "wof:name":"Janzev Vrh",
    "wof:placetype":"locality",
    "wof:population":262
},
  "geometry": {"coordinates":[16.00443,46.6253],"type":"Point"}
}