{
  "type": "Feature",
  "properties": {
    "gn:admin1_code":"A1",
    "gn:asciiname":"Janzev Vrh",
    "gn:country_code":"SI",
    "gn:dem":244,
    "gn:feature_class":"P",
    "gn:feature_code":"PPL",
    "gn:name":"Jan\u017eev Vrh",
    "gn:population":262,
    "gn:timezone":"Europe/Ljubljana",
    "iso:country":"SI",
    "name:bos_x_preferred":[
        "Jan\u017eev Vrh"
    ],
    "name:ceb_x_preferred":[
        "Jan\u017eev Vrh"
    ],
    "name:nld_x_preferred":[
        "Jan\u017eev Vrh"
    ],
    "name:pol_x_preferred":[
        "Jan\u017eev Vrh"
    ],
    "name:ron_x_preferred":[
        "Jan\u017eev Vrh"
    ],
    "name:slv_x_preferred":[
        "Jan\u017eev Vrh"
    ],
    "name:ukr_x_preferred":[
        "\u042f\u043d\u0436\u0435\u0432 \u0412\u0440\u0445"
    ],
    "name:und_x_variant":[
        "Jan\u017eev Vrh"
    ],
    "name:urd_x_preferred":[
        "\u062c\u0646\u0698\u06cc\u0648 \u0648\u0631\u06c1"
    ],
    "wof:name":"Janzev Vrh",
    "wof:placetype":"locality",
    "wof:population":262
},
  "geometry": {"coordinates":[16.00443,46.6253],"type":"Point"}
}