{
  "type": "Feature",
  "properties": {
    "gn:admin1_code":"49",
    "gn:asciiname":"Veckoti",
    "gn:country_code":"SI",
    "gn:dem":174,
    "gn:feature_class":"P",
    "gn:feature_code":"PPL",
    "gn:name":"Ve\u010dkoti",
    "gn:population":10,
    "gn:timezone":"Europe/Ljubljana",
    "iso:country":"SI",
    "name:bos_x_preferred":[
        "Ve\u010dkoti"
    ],
    "name:nld_x_preferred":[
        "Ve\u010dkoti"
    ],
    "name:pol_x_preferred":[
        "Ve\u010dkoti"
    ],
    "name:ron_x_preferred":[
        "Ve\u010dkoti"
    ],
    "name:slv_x_preferred":[
        "Ve\u010dkoti"
    ],
    "name:ukr_x_preferred":[
        "\u0412\u0435\u0447\u043a\u043e\u0442\u0438"
    ],
    "name:und_x_variant":[
        "Ve\u010dkoti"
    ],
    "wof:name":"Veckoti",
    "wof:placetype":"locality",
    "wof:population":10
},
  "geometry": {"coordinates":[13.88139,45.81139],"type":"Point"}
}