{
  "type": "Feature",
  "properties": {
    "gn:admin1_code":"55",
    "gn:asciiname":"Podigrac",
    "gn:country_code":"SI",
    "gn:dem":323,
    "gn:feature_class":"P",
    "gn:feature_code":"PPL",
    "gn:name":"Podigrac",
    "gn:population":69,
    "gn:timezone":"Europe/Ljubljana",
    "iso:country":"SI",
    "name:bos_x_preferred":[
        "Podigrac"
    ],
    "name:hrv_x_preferred":[
        "Podigrac"
    ],
    "name:nld_x_preferred":[
        "Podigrac"
    ],
    "name:pol_x_preferred":[
        "Podigrac"
    ],
    "name:ron_x_preferred":[
        "Podigrac"
    ],
    "name:slv_x_preferred":[
        "Podigrac"
    ],
    "name:ukr_x_preferred":[
        "\u041f\u043e\u0434\u0438\u0433\u0440\u0430\u0446"
    ],
    "wof:name":"Podigrac",
    "wof:placetype":"locality",
    "wof:population":69
},
  "geometry": {"coordinates":[15.61657,46.67398],"type":"Point"}
}