{
  "type": "Feature",
  "properties": {
    "gn:admin1_code":"08",
    "gn:asciiname":"Sveti Lovrenc",
    "gn:country_code":"SI",
    "gn:dem":191,
    "gn:feature_class":"P",
    "gn:feature_code":"PPL",
    "gn:name":"Sveti Lovrenc",
    "gn:population":0,
    "gn:timezone":"Europe/Ljubljana",
    "iso:country":"SI",
    "name:deu_x_historical":[
        "Sankt Lorenzen"
    ],
    "name:deu_x_preferred":[
        "Sankt Lorenzen"
    ],
    "wof:name":"Sveti Lovrenc",
    "wof:placetype":"locality"
},
  "geometry": {"coordinates":[15.69732,46.01529],"type":"Point"}
}