{
  "type": "Feature",
  "properties": {
    "gn:admin1_code":"C4",
    "gn:asciiname":"Gabrovnik",
    "gn:country_code":"SI",
    "gn:dem":337,
    "gn:feature_class":"P",
    "gn:feature_code":"PPL",
    "gn:name":"Gabrovnik",
    "gn:population":198,
    "gn:timezone":"Europe/Ljubljana",
    "iso:country":"SI",
    "wof:name":"Gabrovnik",
    "wof:placetype":"locality",
    "wof:population":198
},
  "geometry": {"coordinates":[15.44282,46.35404000000001],"type":"Point"}
}