{
  "type": "Feature",
  "properties": {
    "gn:admin1_code":"G6",
    "gn:asciiname":"Gorenje Polje",
    "gn:country_code":"SI",
    "gn:dem":291,
    "gn:feature_class":"P",
    "gn:feature_code":"PPL",
    "gn:name":"Gorenje Polje",
    "gn:population":85,
    "gn:timezone":"Europe/Ljubljana",
    "iso:country":"SI",
    "wof:name":"Gorenje Polje",
    "wof:placetype":"locality",
    "wof:population":85
},
  "geometry": {"coordinates":[15.04196,45.77339],"type":"Point"}
}