{
  "type": "Feature",
  "properties": {
    "gn:admin1_code":"G6",
    "gn:asciiname":"Gorenje Polje",
    "gn:country_code":"SI",
    "gn:dem":291,
    "gn:feature_class":"P",
    "gn:feature_code":"PPL",
    "gn:name":"Gorenje Polje",
    "gn:population":85,
    "gn:timezone":"Europe/Ljubljana",
    "iso:country":"SI",
    "name:bos_x_preferred":[
        "Gorenje Polje"
    ],
    "name:hrv_x_preferred":[
        "Gorenje Polje"
    ],
    "name:nld_x_preferred":[
        "Gorenje Polje"
    ],
    "name:pol_x_preferred":[
        "Gorenje Polje"
    ],
    "name:ron_x_preferred":[
        "Gorenje Polje"
    ],
    "name:slv_x_preferred":[
        "Gorenje Polje"
    ],
    "name:ukr_x_preferred":[
        "\u0413\u043e\u0440\u0435\u043d\u0454 \u041f\u043e\u043b\u0454"
    ],
    "wof:name":"Gorenje Polje",
    "wof:placetype":"locality",
    "wof:population":85
},
  "geometry": {"coordinates":[15.04196,45.77339],"type":"Point"}
}