{
  "type": "Feature",
  "properties": {
    "gn:admin1_code":"H6",
    "gn:asciiname":"Stahovica",
    "gn:country_code":"SI",
    "gn:dem":590,
    "gn:feature_class":"P",
    "gn:feature_code":"PPL",
    "gn:name":"Stahovica",
    "gn:population":178,
    "gn:timezone":"Europe/Ljubljana",
    "iso:country":"SI",
    "wof:name":"Stahovica",
    "wof:placetype":"locality",
    "wof:population":178
},
  "geometry": {"coordinates":[14.61719,46.27683],"type":"Point"}
}