{
  "type": "Feature",
  "properties": {
    "gn:admin1_code":"35",
    "gn:asciiname":"Petrinje",
    "gn:country_code":"SI",
    "gn:dem":449,
    "gn:feature_class":"P",
    "gn:feature_code":"PPL",
    "gn:name":"Petrinje",
    "gn:population":39,
    "gn:timezone":"Europe/Ljubljana",
    "iso:country":"SI",
    "name:und_x_variant":[
        "Petrigna",
        "Petri",
        "Petrinje"
    ],
    "wof:name":"Petrinje",
    "wof:placetype":"locality",
    "wof:population":39
},
  "geometry": {"coordinates":[13.90194,45.57111],"type":"Point"}
}