{
  "type": "Feature",
  "properties": {
    "gn:admin1_code":"35",
    "gn:asciiname":"Petrinje",
    "gn:country_code":"SI",
    "gn:dem":449,
    "gn:feature_class":"P",
    "gn:feature_code":"PPL",
    "gn:name":"Petrinje",
    "gn:population":39,
    "gn:timezone":"Europe/Ljubljana",
    "iso:country":"SI",
    "name:bos_x_preferred":[
        "Petrinje"
    ],
    "name:nld_x_preferred":[
        "Petrinje"
    ],
    "name:pol_x_preferred":[
        "Petrinje"
    ],
    "name:ron_x_preferred":[
        "Petrinje"
    ],
    "name:slv_x_preferred":[
        "Petrinje"
    ],
    "name:ukr_x_preferred":[
        "\u041f\u0435\u0442\u0440\u0438\u043d\u0454"
    ],
    "name:und_x_variant":[
        "Petrigna",
        "Petri"
    ],
    "wof:name":"Petrinje",
    "wof:placetype":"locality",
    "wof:population":39
},
  "geometry": {"coordinates":[13.90194,45.57111],"type":"Point"}
}