{
  "type": "Feature",
  "properties": {
    "gn:admin1_code":"13",
    "gn:asciiname":"Podskrajnik",
    "gn:country_code":"SI",
    "gn:dem":567,
    "gn:feature_class":"P",
    "gn:feature_code":"PPL",
    "gn:name":"Podskrajnik",
    "gn:population":85,
    "gn:timezone":"Europe/Ljubljana",
    "iso:country":"SI",
    "name:bos_x_preferred":[
        "Podskrajnik"
    ],
    "name:hrv_x_preferred":[
        "Podskrajnik"
    ],
    "name:nld_x_preferred":[
        "Podskrajnik"
    ],
    "name:pol_x_preferred":[
        "Podskrajnik"
    ],
    "name:ron_x_preferred":[
        "Podskrajnik"
    ],
    "name:slv_x_preferred":[
        "Podskrajnik"
    ],
    "name:ukr_x_preferred":[
        "\u041f\u043e\u0434\u0441\u043a\u0440\u0430\u0439\u043d\u0438\u043a"
    ],
    "wof:name":"Podskrajnik",
    "wof:placetype":"locality",
    "wof:population":85
},
  "geometry": {"coordinates":[14.33291,45.79826],"type":"Point"}
}