{
  "type": "Feature",
  "properties": {
    "gn:admin1_code":"73",
    "gn:asciiname":"Prilozje",
    "gn:country_code":"SI",
    "gn:dem":159,
    "gn:feature_class":"P",
    "gn:feature_code":"PPL",
    "gn:name":"Prilozje",
    "gn:population":31,
    "gn:timezone":"Europe/Ljubljana",
    "iso:country":"SI",
    "name:bos_x_preferred":[
        "Prilozje"
    ],
    "name:hrv_x_preferred":[
        "Prilozje"
    ],
    "name:nld_x_preferred":[
        "Prilozje"
    ],
    "name:pol_x_preferred":[
        "Prilozje"
    ],
    "name:ron_x_preferred":[
        "Prilozje"
    ],
    "name:slv_x_preferred":[
        "Prilozje"
    ],
    "name:ukr_x_preferred":[
        "\u041f\u0440\u0438\u043b\u043e\u0437\u0454"
    ],
    "wof:name":"Prilozje",
    "wof:placetype":"locality",
    "wof:population":31
},
  "geometry": {"coordinates":[15.26858,45.59268],"type":"Point"}
}