{
  "type": "Feature",
  "properties": {
    "gn:admin1_code":"D8",
    "gn:asciiname":"Medvedjek",
    "gn:country_code":"SI",
    "gn:dem":576,
    "gn:feature_class":"P",
    "gn:feature_code":"PPL",
    "gn:name":"Medvedjek",
    "gn:population":18,
    "gn:timezone":"Europe/Ljubljana",
    "iso:country":"SI",
    "name:bos_x_preferred":[
        "Medvedjek"
    ],
    "name:nld_x_preferred":[
        "Medvedjek"
    ],
    "name:pol_x_preferred":[
        "Medvedjek"
    ],
    "name:ron_x_preferred":[
        "Medvedjek"
    ],
    "name:slv_x_preferred":[
        "Medvedjek"
    ],
    "name:ukr_x_preferred":[
        "\u041c\u0435\u0434\u0432\u0435\u0434\u0454\u043a"
    ],
    "wof:name":"Medvedjek",
    "wof:placetype":"locality",
    "wof:population":18
},
  "geometry": {"coordinates":[14.63152,45.81833],"type":"Point"}
}