{
  "type": "Feature",
  "properties": {
    "gn:admin1_code":"08",
    "gn:asciiname":"Brezovica na Bizeljskem",
    "gn:country_code":"SI",
    "gn:dem":225,
    "gn:feature_class":"P",
    "gn:feature_code":"PPL",
    "gn:name":"Brezovica na Bizeljskem",
    "gn:population":99,
    "gn:timezone":"Europe/Ljubljana",
    "iso:country":"SI",
    "name:bos_x_preferred":[
        "Brezovica na Bizeljskem"
    ],
    "name:hrv_x_preferred":[
        "Brezovica na Bizeljskem"
    ],
    "name:nld_x_preferred":[
        "Brezovica na Bizeljskem"
    ],
    "name:pol_x_preferred":[
        "Brezovica na Bizeljskem"
    ],
    "name:ron_x_preferred":[
        "Brezovica na Bizeljskem"
    ],
    "name:slv_x_preferred":[
        "Brezovica na Bizeljskem"
    ],
    "name:ukr_x_preferred":[
        "\u0411\u0440\u0435\u0437\u043e\u0432\u0438\u0446\u044f-\u043d\u0430-\u0411\u0456\u0437\u0435\u043b\u044c\u0441\u044c\u043a\u0435\u043c"
    ],
    "wof:name":"Brezovica na Bizeljskem",
    "wof:placetype":"locality",
    "wof:population":99
},
  "geometry": {"coordinates":[15.68854,45.9987],"type":"Point"}
}