{
  "type": "Feature",
  "properties": {
    "gn:admin1_code":"08",
    "gn:asciiname":"Brezovica na Bizeljskem",
    "gn:country_code":"SI",
    "gn:dem":225,
    "gn:feature_class":"P",
    "gn:feature_code":"PPL",
    "gn:name":"Brezovica na Bizeljskem",
    "gn:population":99,
    "gn:timezone":"Europe/Ljubljana",
    "iso:country":"SI",
    "wof:name":"Brezovica na Bizeljskem",
    "wof:placetype":"locality",
    "wof:population":99
},
  "geometry": {"coordinates":[15.68854,45.9987],"type":"Point"}
}