{
  "type": "Feature",
  "properties": {
    "gn:admin1_code":"38",
    "gn:asciiname":"Podstenjsek",
    "gn:country_code":"SI",
    "gn:dem":519,
    "gn:feature_class":"P",
    "gn:feature_code":"PPL",
    "gn:name":"Podstenj\u0161ek",
    "gn:population":12,
    "gn:timezone":"Europe/Ljubljana",
    "iso:country":"SI",
    "name:bos_x_preferred":[
        "Podstenj\u0161ek"
    ],
    "name:ces_x_preferred":[
        "Podstenj\u0161ek"
    ],
    "name:hrv_x_preferred":[
        "Podstenj\u0161ek"
    ],
    "name:nld_x_preferred":[
        "Podstenj\u0161ek"
    ],
    "name:pol_x_preferred":[
        "Podstenj\u0161ek"
    ],
    "name:ron_x_preferred":[
        "Podstenj\u0161ek"
    ],
    "name:slv_x_preferred":[
        "Podstenj\u0161ek"
    ],
    "name:ukr_x_preferred":[
        "\u041f\u043e\u0434\u0441\u0442\u0435\u043d\u044c\u0448\u0435\u043a"
    ],
    "name:und_x_variant":[
        "Podstenj\u0161ek"
    ],
    "wof:name":"Podstenjsek",
    "wof:placetype":"locality",
    "wof:population":12
},
  "geometry": {"coordinates":[14.21914,45.60492],"type":"Point"}
}