{
  "type": "Feature",
  "properties": {
    "gn:admin1_code":"J3",
    "gn:asciiname":"Nova Vas pri Markovcih",
    "gn:country_code":"SI",
    "gn:dem":209,
    "gn:feature_class":"P",
    "gn:feature_code":"PPL",
    "gn:name":"Nova Vas pri Markovcih",
    "gn:population":410,
    "gn:timezone":"Europe/Ljubljana",
    "iso:country":"SI",
    "name:und_x_variant":[
        "Nova Vas",
        "Nova Vas pri Markovcih"
    ],
    "wof:name":"Nova Vas pri Markovcih",
    "wof:placetype":"locality",
    "wof:population":410
},
  "geometry": {"coordinates":[15.93333,46.38333],"type":"Point"}
}