{
  "type": "Feature",
  "properties": {
    "gn:admin1_code":"J3",
    "gn:asciiname":"Nova Vas pri Markovcih",
    "gn:country_code":"SI",
    "gn:dem":209,
    "gn:feature_class":"P",
    "gn:feature_code":"PPL",
    "gn:name":"Nova Vas pri Markovcih",
    "gn:population":410,
    "gn:timezone":"Europe/Ljubljana",
    "iso:country":"SI",
    "name:bos_x_preferred":[
        "Nova vas pri Markovcih"
    ],
    "name:ceb_x_preferred":[
        "Nova Vas pri Markovcih"
    ],
    "name:nld_x_preferred":[
        "Nova vas pri Markovcih"
    ],
    "name:pol_x_preferred":[
        "Nova vas pri Markovcih"
    ],
    "name:ron_x_preferred":[
        "Nova vas pri Markovcih"
    ],
    "name:slv_x_preferred":[
        "Nova vas pri Markovcih"
    ],
    "name:ukr_x_preferred":[
        "\u041d\u043e\u0432\u0430 \u0412\u0430\u0441-\u043f\u0440\u0438-\u041c\u0430\u0440\u043a\u043e\u0432\u0446\u0438\u0445"
    ],
    "name:und_x_variant":[
        "Nova Vas"
    ],
    "wof:name":"Nova Vas pri Markovcih",
    "wof:placetype":"locality",
    "wof:population":410
},
  "geometry": {"coordinates":[15.93333,46.38333],"type":"Point"}
}