{
  "type": "Feature",
  "properties": {
    "gn:admin1_code":"N8",
    "gn:asciiname":"Vrhovo pri Zuzemberku",
    "gn:country_code":"SI",
    "gn:dem":290,
    "gn:feature_class":"P",
    "gn:feature_code":"PPL",
    "gn:name":"Vrhovo pri \u017du\u017eemberku",
    "gn:population":23,
    "gn:timezone":"Europe/Ljubljana",
    "iso:country":"SI",
    "name:und_x_variant":[
        "Vrhovo",
        "Vrhovo pri \u017du\u017eemberku"
    ],
    "wof:name":"Vrhovo pri Zuzemberku",
    "wof:placetype":"locality",
    "wof:population":23
},
  "geometry": {"coordinates":[14.90278,45.85361],"type":"Point"}
}