{
  "type": "Feature",
  "properties": {
    "gn:admin1_code":"N8",
    "gn:asciiname":"Vrhovo pri Zuzemberku",
    "gn:country_code":"SI",
    "gn:dem":290,
    "gn:feature_class":"P",
    "gn:feature_code":"PPL",
    "gn:name":"Vrhovo pri \u017du\u017eemberku",
    "gn:population":23,
    "gn:timezone":"Europe/Ljubljana",
    "iso:country":"SI",
    "name:bos_x_preferred":[
        "Vrhovo pri \u017du\u017eemberku"
    ],
    "name:bul_x_preferred":[
        "\u0412\u044a\u0440\u0445\u043e\u0432\u043e \u043f\u0440\u0438 \u0416\u0443\u0436\u0435\u043c\u0431\u0435\u0440\u043a\u0443"
    ],
    "name:hrv_x_preferred":[
        "Vrhovo pri \u017du\u017eemberku"
    ],
    "name:nld_x_preferred":[
        "Vrhovo pri \u017du\u017eemberku"
    ],
    "name:pol_x_preferred":[
        "Vrhovo pri \u017du\u017eemberku"
    ],
    "name:ron_x_preferred":[
        "Vrhovo pri \u017du\u017eemberku"
    ],
    "name:slv_x_preferred":[
        "Vrhovo pri \u017du\u017eemberku"
    ],
    "name:ukr_x_preferred":[
        "\u0412\u0440\u0445\u043e\u0432\u043e-\u043f\u0440\u0438-\u0416\u0443\u0436\u0435\u043c\u0431\u0435\u0440\u043a\u0443"
    ],
    "name:und_x_variant":[
        "Vrhovo"
    ],
    "wof:name":"Vrhovo pri Zuzemberku",
    "wof:placetype":"locality",
    "wof:population":23
},
  "geometry": {"coordinates":[14.90278,45.85361],"type":"Point"}
}