{
  "type": "Feature",
  "properties": {
    "gn:admin1_code":"14",
    "gn:asciiname":"Hudajuzna",
    "gn:country_code":"SI",
    "gn:dem":515,
    "gn:feature_class":"P",
    "gn:feature_code":"PPL",
    "gn:name":"Hudaju\u017ena",
    "gn:population":101,
    "gn:timezone":"Europe/Ljubljana",
    "iso:country":"SI",
    "name:und_x_variant":[
        "Hudaju\u017ena"
    ],
    "wof:name":"Hudajuzna",
    "wof:placetype":"locality",
    "wof:population":101
},
  "geometry": {"coordinates":[13.91667,46.16667],"type":"Point"}
}