{
  "type": "Feature",
  "properties": {
    "gn:admin1_code":"14",
    "gn:asciiname":"Hudajuzna",
    "gn:country_code":"SI",
    "gn:dem":515,
    "gn:feature_class":"P",
    "gn:feature_code":"PPL",
    "gn:name":"Hudaju\u017ena",
    "gn:population":101,
    "gn:timezone":"Europe/Ljubljana",
    "iso:country":"SI",
    "name:bos_x_preferred":[
        "Hudaju\u017ena"
    ],
    "name:bul_x_preferred":[
        "\u0425\u0443\u0434\u0430\u044e\u0436\u043d\u0430"
    ],
    "name:ceb_x_preferred":[
        "Hudaju\u017ena"
    ],
    "name:nld_x_preferred":[
        "Hudaju\u017ena"
    ],
    "name:pol_x_preferred":[
        "Hudaju\u017ena"
    ],
    "name:ron_x_preferred":[
        "Hudaju\u017ena"
    ],
    "name:slv_x_preferred":[
        "Hudaju\u017ena"
    ],
    "name:ukr_x_preferred":[
        "\u0425\u0443\u0434\u0430\u044e\u0436\u043d\u0430"
    ],
    "wof:name":"Hudajuzna",
    "wof:placetype":"locality",
    "wof:population":101
},
  "geometry": {"coordinates":[13.91667,46.16667],"type":"Point"}
}