{
  "type": "Feature",
  "properties": {
    "gn:country":"SI",
    "gn:fcode":"PPL",
    "gn:population":0,
    "iso:country":"SI",
    "name:bos_x_preferred":[
        "Duplje"
    ],
    "name:ceb_x_preferred":[
        "Duplje"
    ],
    "name:che_x_preferred":[
        "\u0414\u0443\u043f\u043b\u0435"
    ],
    "name:eng_x_preferred":[
        "Duplje"
    ],
    "name:fra_x_preferred":[
        "Duplje"
    ],
    "name:hrv_x_preferred":[
        "Duplje"
    ],
    "name:hun_x_preferred":[
        "Duplje"
    ],
    "name:mkd_x_preferred":[
        "\u0414\u0443\u043f\u0459\u0435"
    ],
    "name:nld_x_preferred":[
        "Duplje"
    ],
    "name:pol_x_preferred":[
        "Duplje"
    ],
    "name:ron_x_preferred":[
        "Duplje"
    ],
    "name:slv_x_preferred":[
        "Duplje"
    ],
    "name:srp_x_preferred":[
        "\u0414\u0443\u043f\u0459\u0435"
    ],
    "name:tat_x_preferred":[
        "\u0414\u0443\u043f\u043b\u0435"
    ],
    "name:ukr_x_preferred":[
        "\u0414\u0443\u043f\u043b\u0454"
    ],
    "name:und_x_variant":[
        "Duple"
    ],
    "qs_pg:aaroncc":"SI",
    "qs_pg:gn_country":"SI",
    "qs_pg:gn_fcode":"PPL",
    "qs_pg:gn_pop":0,
    "qs_pg:name":"Duplje",
    "qs_pg:name_adm0":"Slovenija",
    "qs_pg:name_adm1":"Ajdovscina",
    "qs_pg:photos":80,
    "qs_pg:photos_1k":16,
    "qs_pg:photos_9k":1,
    "qs_pg:photos_9r":3,
    "qs_pg:photos_all":80,
    "qs_pg:photos_sr":3,
    "qs_pg:pop_sr":0,
    "qs_pg:qs_pg_placetype":"locality",
    "qs_pg:qs_pg_placetype_gp":"Town",
    "qs_pg:woe_adm0":23424945,
    "woe:adm0_id":23424945,
    "woe:name_adm0":"Slovenija",
    "woe:name_adm1":"Ajdovscina",
    "woe:placetype":"Town",
    "wof:name":"Duplje",
    "wof:placetype":"locality",
    "wof:population":215
},
  "geometry": {"coordinates":[13.94972,45.86528],"type":"Point"}
}