{
  "type": "Feature",
  "properties": {
    "gn:admin1_code":"B6",
    "gn:asciiname":"Pavla Vas",
    "gn:country_code":"SI",
    "gn:dem":350,
    "gn:feature_class":"P",
    "gn:feature_code":"PPL",
    "gn:name":"Pavla Vas",
    "gn:population":54,
    "gn:timezone":"Europe/Ljubljana",
    "iso:country":"SI",
    "name:slv_x_historical":[
        "Pavlja Vas"
    ],
    "name:slv_x_preferred":[
        "Pavlja Vas"
    ],
    "wof:name":"Pavla Vas",
    "wof:placetype":"locality",
    "wof:population":54
},
  "geometry": {"coordinates":[15.20357,45.94216],"type":"Point"}
}