{
  "type": "Feature",
  "properties": {
    "gn:admin1_code":"P6",
    "gn:asciiname":"Nadbisec",
    "gn:country_code":"SI",
    "gn:dem":314,
    "gn:feature_class":"P",
    "gn:feature_code":"PPL",
    "gn:name":"Nadbi\u0161ec",
    "gn:population":90,
    "gn:timezone":"Europe/Ljubljana",
    "iso:country":"SI",
    "name:und_x_variant":[
        "Nadbi\u0161ec"
    ],
    "wof:name":"Nadbisec",
    "wof:placetype":"locality",
    "wof:population":90
},
  "geometry": {"coordinates":[15.84931,46.5391],"type":"Point"}
}