{
  "type": "Feature",
  "properties": {
    "gn:admin1_code":"P6",
    "gn:asciiname":"Nadbisec",
    "gn:country_code":"SI",
    "gn:dem":314,
    "gn:feature_class":"P",
    "gn:feature_code":"PPL",
    "gn:name":"Nadbi\u0161ec",
    "gn:population":90,
    "gn:timezone":"Europe/Ljubljana",
    "iso:country":"SI",
    "name:bos_x_preferred":[
        "Nadbi\u0161ec"
    ],
    "name:nld_x_preferred":[
        "Nadbi\u0161ec"
    ],
    "name:pol_x_preferred":[
        "Nadbi\u0161ec"
    ],
    "name:ron_x_preferred":[
        "Nadbi\u0161ec"
    ],
    "name:slv_x_preferred":[
        "Nadbi\u0161ec"
    ],
    "name:ukr_x_preferred":[
        "\u041d\u0430\u0434\u0431\u0438\u0448\u0435\u0446\u044c"
    ],
    "wof:name":"Nadbisec",
    "wof:placetype":"locality",
    "wof:population":90
},
  "geometry": {"coordinates":[15.84931,46.5391],"type":"Point"}
}