{
  "type": "Feature",
  "properties": {
    "gn:admin1_code":"B1",
    "gn:asciiname":"Rozni Dol",
    "gn:country_code":"SI",
    "gn:dem":331,
    "gn:feature_class":"P",
    "gn:feature_code":"PPL",
    "gn:name":"Ro\u017eni Dol",
    "gn:population":57,
    "gn:timezone":"Europe/Ljubljana",
    "iso:country":"SI",
    "name:bos_x_preferred":[
        "Ro\u017eni Dol"
    ],
    "name:hrv_x_preferred":[
        "Ro\u017eni Dol"
    ],
    "name:nld_x_preferred":[
        "Ro\u017eni Dol"
    ],
    "name:pol_x_preferred":[
        "Ro\u017eni Dol"
    ],
    "name:ron_x_preferred":[
        "Ro\u017eni Dol"
    ],
    "name:slv_x_preferred":[
        "Ro\u017eni Dol"
    ],
    "name:ukr_x_preferred":[
        "\u0420\u043e\u0436\u043d\u0438\u0439 \u0414\u043e\u043b"
    ],
    "wof:name":"Rozni Dol",
    "wof:placetype":"locality",
    "wof:population":57
},
  "geometry": {"coordinates":[15.14472,45.68083],"type":"Point"}
}