{
  "type": "Feature",
  "properties": {
    "gn:admin1_code":"F1",
    "gn:asciiname":"Torka",
    "gn:country_code":"SI",
    "gn:dem":1308,
    "gn:feature_class":"P",
    "gn:feature_code":"PPL",
    "gn:name":"Torka",
    "gn:population":2,
    "gn:timezone":"Europe/Ljubljana",
    "iso:country":"SI",
    "wof:name":"Torka",
    "wof:placetype":"locality",
    "wof:population":2
},
  "geometry": {"coordinates":[14.08907,46.23119000000001],"type":"Point"}
}