{
  "type": "Feature",
  "properties": {
    "gn:admin1_code":"N2",
    "gn:asciiname":"Dolena",
    "gn:country_code":"SI",
    "gn:dem":314,
    "gn:feature_class":"P",
    "gn:feature_code":"PPL",
    "gn:name":"Dolena",
    "gn:population":180,
    "gn:timezone":"Europe/Ljubljana",
    "iso:country":"SI",
    "name:bos_x_preferred":[
        "Dolena"
    ],
    "name:ceb_x_preferred":[
        "Dolena"
    ],
    "name:nld_x_preferred":[
        "Dolena"
    ],
    "name:pol_x_preferred":[
        "Dolena"
    ],
    "name:ron_x_preferred":[
        "Dolena"
    ],
    "name:slv_x_preferred":[
        "Dolena"
    ],
    "name:ukr_x_preferred":[
        "\u0414\u043e\u043b\u0435\u043d\u0430"
    ],
    "wof:name":"Dolena",
    "wof:placetype":"locality",
    "wof:population":180
},
  "geometry": {"coordinates":[15.81062,46.32884],"type":"Point"}
}