{
  "type": "Feature",
  "properties": {
    "gn:admin1_code":"08",
    "gn:asciiname":"Laze",
    "gn:country_code":"SI",
    "gn:dem":362,
    "gn:feature_class":"P",
    "gn:feature_code":"PPL",
    "gn:name":"Laze",
    "gn:population":47,
    "gn:timezone":"Europe/Ljubljana",
    "iso:country":"SI",
    "wof:name":"Laze",
    "wof:placetype":"locality",
    "wof:population":47
},
  "geometry": {"coordinates":[15.63148,45.84878],"type":"Point"}
}