{
  "type": "Feature",
  "properties": {
    "gn:admin1_code":"H7",
    "gn:asciiname":"Mala Gora",
    "gn:country_code":"SI",
    "gn:dem":482,
    "gn:feature_class":"P",
    "gn:feature_code":"PPL",
    "gn:name":"Mala Gora",
    "gn:population":8,
    "gn:timezone":"Europe/Ljubljana",
    "iso:country":"SI",
    "name:bos_x_preferred":[
        "Mala Gora"
    ],
    "name:hrv_x_preferred":[
        "Mala Gora"
    ],
    "name:nld_x_preferred":[
        "Mala Gora"
    ],
    "name:pol_x_preferred":[
        "Mala Gora"
    ],
    "name:ron_x_preferred":[
        "Mala Gora"
    ],
    "name:slv_x_preferred":[
        "Mala Gora"
    ],
    "name:ukr_x_preferred":[
        "\u041c\u0430\u043b\u0430 \u0413\u043e\u0440\u0430"
    ],
    "wof:name":"Mala Gora",
    "wof:placetype":"locality",
    "wof:population":8
},
  "geometry": {"coordinates":[14.86833,45.69083],"type":"Point"}
}