{
  "type": "Feature",
  "properties": {
    "gn:admin1_code":"C4",
    "gn:asciiname":"Vesenik",
    "gn:country_code":"SI",
    "gn:dem":345,
    "gn:feature_class":"P",
    "gn:feature_code":"PPL",
    "gn:name":"Ve\u0161enik",
    "gn:population":373,
    "gn:timezone":"Europe/Ljubljana",
    "iso:country":"SI",
    "name:bos_x_preferred":[
        "Ve\u0161enik"
    ],
    "name:ceb_x_preferred":[
        "Ve\u0161enik"
    ],
    "name:hrv_x_preferred":[
        "Ve\u0161enik"
    ],
    "name:nld_x_preferred":[
        "Ve\u0161enik"
    ],
    "name:pol_x_preferred":[
        "Ve\u0161enik"
    ],
    "name:ron_x_preferred":[
        "Ve\u0161enik"
    ],
    "name:slv_x_preferred":[
        "Ve\u0161enik"
    ],
    "name:ukr_x_preferred":[
        "\u0412\u0435\u0448\u0435\u043d\u0438\u043a"
    ],
    "wof:name":"Vesenik",
    "wof:placetype":"locality",
    "wof:population":373
},
  "geometry": {"coordinates":[15.44095,46.34743],"type":"Point"}
}