{
  "type": "Feature",
  "properties": {
    "gn:admin1_code":"C4",
    "gn:asciiname":"Vesenik",
    "gn:country_code":"SI",
    "gn:dem":345,
    "gn:feature_class":"P",
    "gn:feature_code":"PPL",
    "gn:name":"Ve\u0161enik",
    "gn:population":373,
    "gn:timezone":"Europe/Ljubljana",
    "iso:country":"SI",
    "name:und_x_variant":[
        "Ve\u0161enik"
    ],
    "wof:name":"Vesenik",
    "wof:placetype":"locality",
    "wof:population":373
},
  "geometry": {"coordinates":[15.44095,46.34743],"type":"Point"}
}