{
  "type": "Feature",
  "properties": {
    "gn:admin1_code":"C5",
    "gn:asciiname":"Spodnje Mestinje",
    "gn:country_code":"SI",
    "gn:dem":208,
    "gn:feature_class":"P",
    "gn:feature_code":"PPL",
    "gn:name":"Spodnje Mestinje",
    "gn:population":46,
    "gn:timezone":"Europe/Ljubljana",
    "iso:country":"SI",
    "name:bos_x_preferred":[
        "Spodnje Mestinje"
    ],
    "name:hrv_x_preferred":[
        "Spodnje Mestinje"
    ],
    "name:nld_x_preferred":[
        "Spodnje Mestinje"
    ],
    "name:pol_x_preferred":[
        "Spodnje Mestinje"
    ],
    "name:ron_x_preferred":[
        "Spodnje Mestinje"
    ],
    "name:slv_x_preferred":[
        "Spodnje Mestinje"
    ],
    "name:ukr_x_preferred":[
        "\u0421\u043f\u043e\u0434\u043d\u0454 \u041c\u0435\u0441\u0442\u0438\u043d\u0454"
    ],
    "wof:name":"Spodnje Mestinje",
    "wof:placetype":"locality",
    "wof:population":46
},
  "geometry": {"coordinates":[15.57139,46.20389],"type":"Point"}
}