{
  "type": "Feature",
  "properties": {
    "gn:admin1_code":"C5",
    "gn:asciiname":"Spodnje Mestinje",
    "gn:country_code":"SI",
    "gn:dem":208,
    "gn:feature_class":"P",
    "gn:feature_code":"PPL",
    "gn:name":"Spodnje Mestinje",
    "gn:population":46,
    "gn:timezone":"Europe/Ljubljana",
    "iso:country":"SI",
    "wof:name":"Spodnje Mestinje",
    "wof:placetype":"locality",
    "wof:population":46
},
  "geometry": {"coordinates":[15.57139,46.20389],"type":"Point"}
}