{
  "type": "Feature",
  "properties": {
    "gn:gn_country":"SI",
    "gn:gn_fcode":"PPL",
    "gn:gn_pop":120,
    "gn:population":112,
    "iso:country":"SI",
    "name:dut_x_preferred":[
        "Sv. Duh na Ostrem Vrhu"
    ],
    "name:eng_x_preferred":[
        "Sveti Duh na Ostrem Vrhu"
    ],
    "name:ger_x_preferred":[
        "Kirche zum Heiligen Geist am Osterberg"
    ],
    "name:rum_x_preferred":[
        "Sveti Duh na Ostrem Vrhu"
    ],
    "name:slv_x_preferred":[
        "Sv. Duh na Ostrem Vrhu"
    ],
    "name:ukr_x_preferred":[
        "\u0421\u0432\u0435\u0442\u0438\u0439 \u0414\u0443\u0445-\u043d\u0430-\u041e\u0441\u0442\u0440\u0435\u043c \u0412\u0440\u0445\u0443"
    ],
    "qs_pg:aaroncc":"SI",
    "qs_pg:gn_country":"SI",
    "qs_pg:gn_fcode":"PPL",
    "qs_pg:gn_pop":120,
    "qs_pg:name":"Sv. Duh Na Ostrem Vrhu",
    "qs_pg:name_adm0":"Slovenija",
    "qs_pg:name_adm1":"Ruse",
    "qs_pg:photos_9k":1,
    "qs_pg:photos_9r":1,
    "qs_pg:photos_all":2,
    "qs_pg:photos_sr":0,
    "qs_pg:pop_sr":1,
    "qs_pg:qs_pg_placetype":"locality",
    "qs_pg:qs_pg_placetype_gp":"Town",
    "qs_pg:woe_adm0":23424945,
    "woe:adm0_id":23424945,
    "woe:name_adm0":"Slovenija",
    "woe:name_adm1":"Ruse",
    "woe:placetype":"Town",
    "wof:name":"Sv. Duh Na Ostrem Vrhu",
    "wof:placetype":"locality",
    "wof:population":112
},
  "geometry": {"coordinates":[15.46128,46.61457],"type":"Point"}
}