{
  "type": "Feature",
  "properties": {
    "gn:admin1_code":"I6",
    "gn:asciiname":"Drakovci",
    "gn:country_code":"SI",
    "gn:dem":213,
    "gn:feature_class":"P",
    "gn:feature_code":"PPL",
    "gn:name":"Drakovci",
    "gn:population":248,
    "gn:timezone":"Europe/Ljubljana",
    "iso:country":"SI",
    "name:bos_x_preferred":[
        "Drakovci"
    ],
    "name:ceb_x_preferred":[
        "Drakovci"
    ],
    "name:hrv_x_preferred":[
        "Drakovci"
    ],
    "name:nld_x_preferred":[
        "Drakovci"
    ],
    "name:pol_x_preferred":[
        "Drakovci"
    ],
    "name:ron_x_preferred":[
        "Drakovci"
    ],
    "name:slv_x_preferred":[
        "Drakovci"
    ],
    "name:ukr_x_preferred":[
        "\u0414\u0440\u0430\u043a\u043e\u0432\u0446\u0456"
    ],
    "wof:name":"Drakovci",
    "wof:placetype":"locality",
    "wof:population":248
},
  "geometry": {"coordinates":[16.03507999999999,46.53332],"type":"Point"}
}