{
  "type": "Feature",
  "properties": {
    "gn:admin1_code":"I6",
    "gn:asciiname":"Drakovci",
    "gn:country_code":"SI",
    "gn:dem":213,
    "gn:feature_class":"P",
    "gn:feature_code":"PPL",
    "gn:name":"Drakovci",
    "gn:population":248,
    "gn:timezone":"Europe/Ljubljana",
    "iso:country":"SI",
    "wof:name":"Drakovci",
    "wof:placetype":"locality",
    "wof:population":248
},
  "geometry": {"coordinates":[16.03507999999999,46.53332],"type":"Point"}
}