{
  "type": "Feature",
  "properties": {
    "gn:admin1_code":"A3",
    "gn:asciiname":"Poljsica pri Podnartu",
    "gn:country_code":"SI",
    "gn:dem":492,
    "gn:feature_class":"P",
    "gn:feature_code":"PPL",
    "gn:name":"Polj\u0161ica pri Podnartu",
    "gn:population":97,
    "gn:timezone":"Europe/Ljubljana",
    "iso:country":"SI",
    "name:und_x_variant":[
        "Polj\u0161ica pri Podnartu",
        "Polj\u0161ica",
        "Polj\u0161\u010dica",
        "Polj\u0161\u010dica pri Podnartu"
    ],
    "wof:name":"Poljsica pri Podnartu",
    "wof:placetype":"locality",
    "wof:population":97
},
  "geometry": {"coordinates":[14.25,46.28333],"type":"Point"}
}