{
  "type": "Feature",
  "properties": {
    "gn:admin1_code":"A3",
    "gn:asciiname":"Poljsica pri Podnartu",
    "gn:country_code":"SI",
    "gn:dem":492,
    "gn:feature_class":"P",
    "gn:feature_code":"PPL",
    "gn:name":"Polj\u0161ica pri Podnartu",
    "gn:population":97,
    "gn:timezone":"Europe/Ljubljana",
    "iso:country":"SI",
    "name:bos_x_preferred":[
        "Polj\u0161ica pri Podnartu"
    ],
    "name:ceb_x_preferred":[
        "Polj\u0161ica pri Podnartu"
    ],
    "name:hrv_x_preferred":[
        "Polj\u0161ica pri Podnartu"
    ],
    "name:nld_x_preferred":[
        "Polj\u0161ica pri Podnartu"
    ],
    "name:pol_x_preferred":[
        "Polj\u0161ica pri Podnartu"
    ],
    "name:ron_x_preferred":[
        "Polj\u0161ica pri Podnartu"
    ],
    "name:slv_x_preferred":[
        "Polj\u0161ica pri Podnartu"
    ],
    "name:ukr_x_preferred":[
        "\u041f\u043e\u043b\u044c\u0448\u0438\u0446\u044f-\u043f\u0440\u0438-\u041f\u043e\u0434\u043d\u0430\u0440\u0442\u0443"
    ],
    "name:und_x_variant":[
        "Polj\u0161ica",
        "Polj\u0161\u010dica",
        "Polj\u0161\u010dica pri Podnartu"
    ],
    "wof:name":"Poljsica pri Podnartu",
    "wof:placetype":"locality",
    "wof:population":97
},
  "geometry": {"coordinates":[14.25,46.28333],"type":"Point"}
}