{
  "type": "Feature",
  "properties": {
    "gn:admin1_code":"17",
    "gn:asciiname":"Pobrezje",
    "gn:country_code":"SI",
    "gn:dem":175,
    "gn:feature_class":"P",
    "gn:feature_code":"PPL",
    "gn:name":"Pobre\u017eje",
    "gn:population":9,
    "gn:timezone":"Europe/Ljubljana",
    "iso:country":"SI",
    "name:bos_x_preferred":[
        "Pobre\u017eje"
    ],
    "name:hrv_x_preferred":[
        "Pobre\u017eje"
    ],
    "name:nld_x_preferred":[
        "Pobre\u017eje"
    ],
    "name:pol_x_preferred":[
        "Pobre\u017eje"
    ],
    "name:ron_x_preferred":[
        "Pobre\u017eje"
    ],
    "name:slv_x_preferred":[
        "Pobre\u017eje"
    ],
    "name:ukr_x_preferred":[
        "\u041f\u043e\u0431\u0440\u0435\u0436\u0454"
    ],
    "name:und_x_variant":[
        "Pobre\u017eje"
    ],
    "wof:name":"Pobrezje",
    "wof:placetype":"locality",
    "wof:population":9
},
  "geometry": {"coordinates":[15.31202,45.53005],"type":"Point"}
}