{
  "type": "Feature",
  "properties": {
    "gn:admin1_code":"52",
    "gn:asciiname":"Circice",
    "gn:country_code":"SI",
    "gn:dem":379,
    "gn:feature_class":"P",
    "gn:feature_code":"PPL",
    "gn:name":"\u010cir\u010di\u010de",
    "gn:population":0,
    "gn:timezone":"Europe/Ljubljana",
    "iso:country":"SI",
    "wof:name":"Circice",
    "wof:placetype":"locality"
},
  "geometry": {"coordinates":[14.36428,46.23068],"type":"Point"}
}