{
  "type": "Feature",
  "properties": {
    "gn:admin1_code":"L5",
    "gn:asciiname":"Veliki Boc",
    "gn:country_code":"SI",
    "gn:dem":747,
    "gn:feature_class":"P",
    "gn:feature_code":"PPL",
    "gn:name":"Veliki Bo\u010d",
    "gn:population":106,
    "gn:timezone":"Europe/Ljubljana",
    "iso:country":"SI",
    "name:bos_x_preferred":[
        "Veliki Bo\u010d"
    ],
    "name:ceb_x_preferred":[
        "Veliki Bo\u010d"
    ],
    "name:fas_x_preferred":[
        "\u0648\u0644\u06cc\u06a9\u06cc \u0628\u0686"
    ],
    "name:nld_x_preferred":[
        "Veliki Bo\u010d"
    ],
    "name:pol_x_preferred":[
        "Veliki Bo\u010d"
    ],
    "name:ron_x_preferred":[
        "Veliki Bo\u010d"
    ],
    "name:slv_x_preferred":[
        "Veliki Bo\u010d"
    ],
    "name:ukr_x_preferred":[
        "\u0412\u0435\u043b\u0438\u043a\u0438\u0439 \u0411\u043e\u0447"
    ],
    "wof:name":"Veliki Boc",
    "wof:placetype":"locality",
    "wof:population":106
},
  "geometry": {"coordinates":[15.49673,46.60648],"type":"Point"}
}