{
  "type": "Feature",
  "properties": {
    "gn:admin1_code":"50",
    "gn:asciiname":"Zazid",
    "gn:country_code":"SI",
    "gn:dem":383,
    "gn:feature_class":"P",
    "gn:feature_code":"PPL",
    "gn:name":"Zazid",
    "gn:population":70,
    "gn:timezone":"Europe/Ljubljana",
    "iso:country":"SI",
    "name:bos_x_preferred":[
        "Zazid"
    ],
    "name:bul_x_preferred":[
        "\u0417\u0430\u0437\u0438\u0434"
    ],
    "name:ita_x_preferred":[
        "Sasseto"
    ],
    "name:nld_x_preferred":[
        "Zazid"
    ],
    "name:pol_x_preferred":[
        "Zazid"
    ],
    "name:ron_x_preferred":[
        "Zazid"
    ],
    "name:slv_x_preferred":[
        "Zazid"
    ],
    "name:ukr_x_preferred":[
        "\u0417\u0430\u0437\u0438\u0434"
    ],
    "name:und_x_variant":[
        "Sasseto",
        "Zazid"
    ],
    "wof:name":"Zazid",
    "wof:placetype":"locality",
    "wof:population":70
},
  "geometry": {"coordinates":[13.93139,45.50194000000001],"type":"Point"}
}