{
  "type": "Feature",
  "properties": {
    "gn:admin1_code":"52",
    "gn:asciiname":"Pangrsica",
    "gn:country_code":"SI",
    "gn:dem":465,
    "gn:feature_class":"P",
    "gn:feature_code":"PPL",
    "gn:name":"Pangr\u0161ica",
    "gn:population":79,
    "gn:timezone":"Europe/Ljubljana",
    "iso:country":"SI",
    "name:bos_x_preferred":[
        "Pangr\u0161ica"
    ],
    "name:hrv_x_preferred":[
        "Pangr\u0161ica"
    ],
    "name:nld_x_preferred":[
        "Pangr\u0161ica"
    ],
    "name:pol_x_preferred":[
        "Pangr\u0161ica"
    ],
    "name:ron_x_preferred":[
        "Pangr\u0161ica"
    ],
    "name:slv_x_preferred":[
        "Pangr\u0161ica"
    ],
    "name:ukr_x_preferred":[
        "\u041f\u0430\u043d\u0433\u0440\u0448\u0438\u0446\u044f"
    ],
    "wof:name":"Pangrsica",
    "wof:placetype":"locality",
    "wof:population":79
},
  "geometry": {"coordinates":[14.3603,46.31056],"type":"Point"}
}