{
  "type": "Feature",
  "properties": {
    "gn:admin1_code":"52",
    "gn:asciiname":"Pangrsica",
    "gn:country_code":"SI",
    "gn:dem":465,
    "gn:feature_class":"P",
    "gn:feature_code":"PPL",
    "gn:name":"Pangr\u0161ica",
    "gn:population":79,
    "gn:timezone":"Europe/Ljubljana",
    "iso:country":"SI",
    "name:und_x_variant":[
        "Pangr\u0161ica"
    ],
    "wof:name":"Pangrsica",
    "wof:placetype":"locality",
    "wof:population":79
},
  "geometry": {"coordinates":[14.3603,46.31056],"type":"Point"}
}