{
  "type": "Feature",
  "properties": {
    "gn:admin1_code":"C4",
    "gn:asciiname":"Slatina pri Ponikvi",
    "gn:country_code":"SI",
    "gn:dem":340,
    "gn:feature_class":"P",
    "gn:feature_code":"PPL",
    "gn:name":"Slatina pri Ponikvi",
    "gn:population":108,
    "gn:timezone":"Europe/Ljubljana",
    "iso:country":"SI",
    "name:und_x_variant":[
        "Slatina",
        "Slatina pri Ponikvi"
    ],
    "wof:name":"Slatina pri Ponikvi",
    "wof:placetype":"locality",
    "wof:population":108
},
  "geometry": {"coordinates":[15.46092,46.28194000000001],"type":"Point"}
}