{
  "type": "Feature",
  "properties": {
    "gn:admin1_code":"32",
    "gn:asciiname":"Mala Stara Vas",
    "gn:country_code":"SI",
    "gn:dem":356,
    "gn:feature_class":"P",
    "gn:feature_code":"PPL",
    "gn:name":"Mala Stara Vas",
    "gn:population":99,
    "gn:timezone":"Europe/Ljubljana",
    "iso:country":"SI",
    "wof:name":"Mala Stara Vas",
    "wof:placetype":"locality",
    "wof:population":99
},
  "geometry": {"coordinates":[14.67179,45.97507],"type":"Point"}
}