{
  "type": "Feature",
  "properties": {
    "gn:admin1_code":"32",
    "gn:asciiname":"Mala Stara Vas",
    "gn:country_code":"SI",
    "gn:dem":356,
    "gn:feature_class":"P",
    "gn:feature_code":"PPL",
    "gn:name":"Mala Stara Vas",
    "gn:population":99,
    "gn:timezone":"Europe/Ljubljana",
    "iso:country":"SI",
    "name:bos_x_preferred":[
        "Mala Stara vas"
    ],
    "name:nld_x_preferred":[
        "Mala Stara vas"
    ],
    "name:pol_x_preferred":[
        "Mala Stara vas"
    ],
    "name:ron_x_preferred":[
        "Mala Stara vas"
    ],
    "name:slv_x_preferred":[
        "Mala Stara vas"
    ],
    "name:srp_x_preferred":[
        "\u041c\u0430\u043b\u0430 \u0421\u0442\u0430\u0440\u0430 \u0412\u0430\u0441"
    ],
    "name:ukr_x_preferred":[
        "\u041c\u0430\u043b\u0430 \u0421\u0442\u0430\u0440\u0430 \u0412\u0430\u0441"
    ],
    "wof:name":"Mala Stara Vas",
    "wof:placetype":"locality",
    "wof:population":99
},
  "geometry": {"coordinates":[14.67179,45.97507],"type":"Point"}
}