{
  "type": "Feature",
  "properties": {
    "gn:admin1_code":"E1",
    "gn:asciiname":"Erzelj",
    "gn:country_code":"SI",
    "gn:dem":348,
    "gn:feature_class":"P",
    "gn:feature_code":"PPL",
    "gn:name":"Erzelj",
    "gn:population":70,
    "gn:timezone":"Europe/Ljubljana",
    "iso:country":"SI",
    "name:bos_x_preferred":[
        "Erzelj"
    ],
    "name:hun_x_preferred":[
        "Erzelj"
    ],
    "name:ita_x_preferred":[
        "Ersel"
    ],
    "name:nld_x_preferred":[
        "Erzelj"
    ],
    "name:pol_x_preferred":[
        "Erzelj"
    ],
    "name:ron_x_preferred":[
        "Erzelj"
    ],
    "name:slv_x_preferred":[
        "Erzelj"
    ],
    "name:srp_x_preferred":[
        "\u0415\u0440\u0437\u0435\u0459"
    ],
    "name:ukr_x_preferred":[
        "\u0415\u0440\u0437\u0435\u043b\u044c"
    ],
    "name:und_x_variant":[
        "Ersel in Monte"
    ],
    "wof:name":"Erzelj",
    "wof:placetype":"locality",
    "wof:population":70
},
  "geometry": {"coordinates":[13.91028,45.83278],"type":"Point"}
}