{
  "type": "Feature",
  "properties": {
    "gn:admin1_code":"E1",
    "gn:asciiname":"Erzelj",
    "gn:country_code":"SI",
    "gn:dem":348,
    "gn:feature_class":"P",
    "gn:feature_code":"PPL",
    "gn:name":"Erzelj",
    "gn:population":70,
    "gn:timezone":"Europe/Ljubljana",
    "iso:country":"SI",
    "name:und_x_variant":[
        "Ersel in Monte",
        "Erzelj"
    ],
    "wof:name":"Erzelj",
    "wof:placetype":"locality",
    "wof:population":70
},
  "geometry": {"coordinates":[13.91028,45.83278],"type":"Point"}
}