{
  "type": "Feature",
  "properties": {
    "gn:admin1_code":"E7",
    "gn:asciiname":"Borje",
    "gn:country_code":"SI",
    "gn:dem":727,
    "gn:feature_class":"P",
    "gn:feature_code":"PPL",
    "gn:name":"Borje",
    "gn:population":40,
    "gn:timezone":"Europe/Ljubljana",
    "iso:country":"SI",
    "wof:name":"Borje",
    "wof:placetype":"locality",
    "wof:population":40
},
  "geometry": {"coordinates":[14.93441,46.12303],"type":"Point"}
}