{
  "type": "Feature",
  "properties": {
    "gn:admin1_code":"B1",
    "gn:asciiname":"Lipovec",
    "gn:country_code":"SI",
    "gn:dem":220,
    "gn:feature_class":"P",
    "gn:feature_code":"PPL",
    "gn:name":"Lipovec",
    "gn:population":37,
    "gn:timezone":"Europe/Ljubljana",
    "iso:country":"SI",
    "name:bos_x_preferred":[
        "Lipovec"
    ],
    "name:hrv_x_preferred":[
        "Lipovec"
    ],
    "name:nld_x_preferred":[
        "Lipovec"
    ],
    "name:pol_x_preferred":[
        "Lipovec"
    ],
    "name:ron_x_preferred":[
        "Lipovec"
    ],
    "name:slv_x_preferred":[
        "Lipovec"
    ],
    "name:ukr_x_preferred":[
        "\u041b\u0438\u043f\u043e\u0432\u0435\u0446\u044c"
    ],
    "wof:name":"Lipovec",
    "wof:placetype":"locality",
    "wof:population":37
},
  "geometry": {"coordinates":[15.18333,45.63333],"type":"Point"}
}