{
  "type": "Feature",
  "properties": {
    "gn:admin1_code":"B1",
    "gn:asciiname":"Lipovec",
    "gn:country_code":"SI",
    "gn:dem":220,
    "gn:feature_class":"P",
    "gn:feature_code":"PPL",
    "gn:name":"Lipovec",
    "gn:population":37,
    "gn:timezone":"Europe/Ljubljana",
    "iso:country":"SI",
    "wof:name":"Lipovec",
    "wof:placetype":"locality",
    "wof:population":37
},
  "geometry": {"coordinates":[15.18333,45.63333],"type":"Point"}
}