{
  "type": "Feature",
  "properties": {
    "gn:admin1_code":"08",
    "gn:asciiname":"Spodnja Susica",
    "gn:country_code":"SI",
    "gn:dem":166,
    "gn:feature_class":"P",
    "gn:feature_code":"PPL",
    "gn:name":"Spodnja Su\u0161ica",
    "gn:population":0,
    "gn:timezone":"Europe/Ljubljana",
    "iso:country":"SI",
    "wof:name":"Spodnja Susica",
    "wof:placetype":"locality"
},
  "geometry": {"coordinates":[15.69389,46.01028],"type":"Point"}
}