{
  "type": "Feature",
  "properties": {
    "gn:admin1_code":"37",
    "gn:asciiname":"Gornji Ig",
    "gn:country_code":"SI",
    "gn:dem":634,
    "gn:feature_class":"P",
    "gn:feature_code":"PPL",
    "gn:name":"Gornji Ig",
    "gn:population":26,
    "gn:timezone":"Europe/Ljubljana",
    "iso:country":"SI",
    "name:bos_x_preferred":[
        "Gornji Ig"
    ],
    "name:bul_x_preferred":[
        "\u0413\u043e\u0440\u043d\u0438 \u0418\u0433"
    ],
    "name:ceb_x_preferred":[
        "Gornji Ig"
    ],
    "name:nld_x_preferred":[
        "Gornji Ig"
    ],
    "name:pol_x_preferred":[
        "Gornji Ig"
    ],
    "name:ron_x_preferred":[
        "Gornji Ig"
    ],
    "name:slv_x_preferred":[
        "Gornji Ig"
    ],
    "name:ukr_x_preferred":[
        "\u0413\u043e\u0440\u043d'\u0457 \u0406\u0433"
    ],
    "name:und_x_variant":[
        "Gorenji Ig"
    ],
    "wof:name":"Gornji Ig",
    "wof:placetype":"locality",
    "wof:population":26
},
  "geometry": {"coordinates":[14.49556,45.92],"type":"Point"}
}