{
  "type": "Feature",
  "properties": {
    "gn:admin1_code":"37",
    "gn:asciiname":"Gornji Ig",
    "gn:country_code":"SI",
    "gn:dem":634,
    "gn:feature_class":"P",
    "gn:feature_code":"PPL",
    "gn:name":"Gornji Ig",
    "gn:population":26,
    "gn:timezone":"Europe/Ljubljana",
    "iso:country":"SI",
    "name:und_x_variant":[
        "Gorenji Ig",
        "Gornji Ig"
    ],
    "wof:name":"Gornji Ig",
    "wof:placetype":"locality",
    "wof:population":26
},
  "geometry": {"coordinates":[14.49556,45.92],"type":"Point"}
}