{
  "type": "Feature",
  "properties": {
    "gn:admin1_code":"H7",
    "gn:asciiname":"Mozelj",
    "gn:country_code":"SI",
    "gn:dem":486,
    "gn:feature_class":"P",
    "gn:feature_code":"PPL",
    "gn:name":"Mozelj",
    "gn:population":197,
    "gn:timezone":"Europe/Ljubljana",
    "iso:country":"SI",
    "wof:name":"Mozelj",
    "wof:placetype":"locality",
    "wof:population":197
},
  "geometry": {"coordinates":[14.93333,45.58639],"type":"Point"}
}