{
  "type": "Feature",
  "properties": {
    "gn:admin1_code":"H7",
    "gn:asciiname":"Mozelj",
    "gn:country_code":"SI",
    "gn:dem":486,
    "gn:feature_class":"P",
    "gn:feature_code":"PPL",
    "gn:name":"Mozelj",
    "gn:population":197,
    "gn:timezone":"Europe/Ljubljana",
    "iso:country":"SI",
    "name:bos_x_preferred":[
        "Mozelj"
    ],
    "name:ceb_x_preferred":[
        "Mozelj"
    ],
    "name:hrv_x_preferred":[
        "Mozelj"
    ],
    "name:nld_x_preferred":[
        "Mozelj"
    ],
    "name:pol_x_preferred":[
        "Mozelj"
    ],
    "name:ron_x_preferred":[
        "Mozelj"
    ],
    "name:slv_x_preferred":[
        "Mozelj"
    ],
    "name:ukr_x_preferred":[
        "\u041c\u043e\u0437\u0435\u043b\u044c"
    ],
    "wof:name":"Mozelj",
    "wof:placetype":"locality",
    "wof:population":197
},
  "geometry": {"coordinates":[14.93333,45.58639],"type":"Point"}
}