{
  "type": "Feature",
  "properties": {
    "gn:admin1_code":"D4",
    "gn:asciiname":"Gorenje Medvedje Selo",
    "gn:country_code":"SI",
    "gn:dem":286,
    "gn:feature_class":"P",
    "gn:feature_code":"PPL",
    "gn:name":"Gorenje Medvedje Selo",
    "gn:population":54,
    "gn:timezone":"Europe/Ljubljana",
    "iso:country":"SI",
    "wof:name":"Gorenje Medvedje Selo",
    "wof:placetype":"locality",
    "wof:population":54
},
  "geometry": {"coordinates":[15.02171,45.92079],"type":"Point"}
}