{
  "type": "Feature",
  "properties": {
    "gn:admin1_code":"D4",
    "gn:asciiname":"Gorenje Medvedje Selo",
    "gn:country_code":"SI",
    "gn:dem":286,
    "gn:feature_class":"P",
    "gn:feature_code":"PPL",
    "gn:name":"Gorenje Medvedje Selo",
    "gn:population":54,
    "gn:timezone":"Europe/Ljubljana",
    "iso:country":"SI",
    "name:bos_x_preferred":[
        "Gorenje Medvedje selo"
    ],
    "name:hrv_x_preferred":[
        "Gorenje Medvedje selo"
    ],
    "name:nld_x_preferred":[
        "Gorenje Medvedje selo"
    ],
    "name:pol_x_preferred":[
        "Gorenje Medvedje selo"
    ],
    "name:ron_x_preferred":[
        "Gorenje Medvedje selo"
    ],
    "name:slv_x_preferred":[
        "Gorenje Medvedje selo"
    ],
    "name:ukr_x_preferred":[
        "\u0413\u043e\u0440\u0435\u043d\u0454 \u041c\u0435\u0434\u0432\u0435\u0434\u0454 \u0421\u0435\u043b\u043e"
    ],
    "wof:name":"Gorenje Medvedje Selo",
    "wof:placetype":"locality",
    "wof:population":54
},
  "geometry": {"coordinates":[15.02171,45.92079],"type":"Point"}
}