{
  "type": "Feature",
  "properties": {
    "gn:admin1_code":"24",
    "gn:asciiname":"Slomi",
    "gn:country_code":"SI",
    "gn:dem":272,
    "gn:feature_class":"P",
    "gn:feature_code":"PPL",
    "gn:name":"Slomi",
    "gn:population":95,
    "gn:timezone":"Europe/Ljubljana",
    "iso:country":"SI",
    "name:und_x_variant":[
        "Slom",
        "Slomi"
    ],
    "wof:name":"Slomi",
    "wof:placetype":"locality",
    "wof:population":95
},
  "geometry": {"coordinates":[15.98909,46.45208],"type":"Point"}
}