{
  "type": "Feature",
  "properties": {
    "gn:admin1_code":"24",
    "gn:asciiname":"Slomi",
    "gn:country_code":"SI",
    "gn:dem":272,
    "gn:feature_class":"P",
    "gn:feature_code":"PPL",
    "gn:name":"Slomi",
    "gn:population":95,
    "gn:timezone":"Europe/Ljubljana",
    "iso:country":"SI",
    "name:bos_x_preferred":[
        "Slomi"
    ],
    "name:bul_x_preferred":[
        "\u0421\u043b\u043e\u043c\u0438"
    ],
    "name:nld_x_preferred":[
        "Slomi"
    ],
    "name:pol_x_preferred":[
        "Slomi"
    ],
    "name:ron_x_preferred":[
        "Slomi"
    ],
    "name:slv_x_preferred":[
        "Slomi"
    ],
    "name:ukr_x_preferred":[
        "\u0421\u043b\u043e\u043c\u0456"
    ],
    "name:und_x_variant":[
        "Slom"
    ],
    "wof:name":"Slomi",
    "wof:placetype":"locality",
    "wof:population":95
},
  "geometry": {"coordinates":[15.98909,46.45208],"type":"Point"}
}