{
  "type": "Feature",
  "properties": {
    "gn:admin1_code":"J2",
    "gn:asciiname":"Gaj nad Mariborom",
    "gn:country_code":"SI",
    "gn:dem":535,
    "gn:feature_class":"P",
    "gn:feature_code":"PPL",
    "gn:name":"Gaj nad Mariborom",
    "gn:population":228,
    "gn:timezone":"Europe/Ljubljana",
    "iso:country":"SI",
    "name:und_x_variant":[
        "Sveti Kri\u017e",
        "Gaj",
        "Gaj nad Mariborom"
    ],
    "wof:name":"Gaj nad Mariborom",
    "wof:placetype":"locality",
    "wof:population":228
},
  "geometry": {"coordinates":[15.56121,46.62321],"type":"Point"}
}