{
  "type": "Feature",
  "properties": {
    "gn:admin1_code":"J2",
    "gn:asciiname":"Gaj nad Mariborom",
    "gn:country_code":"SI",
    "gn:dem":535,
    "gn:feature_class":"P",
    "gn:feature_code":"PPL",
    "gn:name":"Gaj nad Mariborom",
    "gn:population":228,
    "gn:timezone":"Europe/Ljubljana",
    "iso:country":"SI",
    "name:bos_x_preferred":[
        "Gaj nad Mariborom"
    ],
    "name:bul_x_preferred":[
        "\u0413\u0430\u0439 \u043d\u0430\u0434 \u041c\u0430\u0440\u0438\u0431\u043e\u0440\u043e\u043c"
    ],
    "name:ceb_x_preferred":[
        "Gaj nad Mariborom"
    ],
    "name:nld_x_preferred":[
        "Gaj nad Mariborom"
    ],
    "name:pol_x_preferred":[
        "Gaj nad Mariborom"
    ],
    "name:ron_x_preferred":[
        "Gaj nad Mariborom"
    ],
    "name:slv_x_preferred":[
        "Gaj nad Mariborom"
    ],
    "name:ukr_x_preferred":[
        "\u0413\u0430\u0439-\u043d\u0430\u0434-\u041c\u0430\u0440\u0438\u0431\u043e\u0440\u043e\u043c"
    ],
    "name:und_x_variant":[
        "Sveti Kri\u017e",
        "Gaj",
        "Gaj nad Mariborom"
    ],
    "wof:name":"Gaj nad Mariborom",
    "wof:placetype":"locality",
    "wof:population":228
},
  "geometry": {"coordinates":[15.56121,46.62321],"type":"Point"}
}