{
  "type": "Feature",
  "properties": {
    "gn:admin1_code":"K5",
    "gn:asciiname":"Nova Vas",
    "gn:country_code":"SI",
    "gn:dem":514,
    "gn:feature_class":"P",
    "gn:feature_code":"PPL",
    "gn:name":"Nova Vas",
    "gn:population":130,
    "gn:timezone":"Europe/Ljubljana",
    "iso:country":"SI",
    "name:bos_x_preferred":[
        "Nova vas"
    ],
    "name:ceb_x_preferred":[
        "Nova Vas"
    ],
    "name:hrv_x_preferred":[
        "Nova vas"
    ],
    "name:nld_x_preferred":[
        "Nova vas"
    ],
    "name:pol_x_preferred":[
        "Nova vas"
    ],
    "name:ron_x_preferred":[
        "Nova vas"
    ],
    "name:sco_x_preferred":[
        "Nova Vas"
    ],
    "name:slv_x_preferred":[
        "Nova vas"
    ],
    "name:ukr_x_preferred":[
        "\u041d\u043e\u0432\u0430 \u0432\u0430\u0441"
    ],
    "wof:name":"Nova Vas",
    "wof:placetype":"locality",
    "wof:population":130
},
  "geometry": {"coordinates":[14.42256,46.30876],"type":"Point"}
}