{
  "type": "Feature",
  "properties": {
    "gn:admin1_code":"K5",
    "gn:asciiname":"Nova Vas",
    "gn:country_code":"SI",
    "gn:dem":514,
    "gn:feature_class":"P",
    "gn:feature_code":"PPL",
    "gn:name":"Nova Vas",
    "gn:population":130,
    "gn:timezone":"Europe/Ljubljana",
    "iso:country":"SI",
    "wof:name":"Nova Vas",
    "wof:placetype":"locality",
    "wof:population":130
},
  "geometry": {"coordinates":[14.42256,46.30876],"type":"Point"}
}