{
  "type": "Feature",
  "properties": {
    "gn:admin1_code":"76",
    "gn:asciiname":"Zavrse",
    "gn:country_code":"SI",
    "gn:dem":794,
    "gn:feature_class":"P",
    "gn:feature_code":"PPL",
    "gn:name":"Zavr\u0161e",
    "gn:population":422,
    "gn:timezone":"Europe/Ljubljana",
    "iso:country":"SI",
    "name:bos_x_preferred":[
        "Zavr\u0161e"
    ],
    "name:ceb_x_preferred":[
        "Zavr\u0161e"
    ],
    "name:nld_x_preferred":[
        "Zavr\u0161e"
    ],
    "name:pol_x_preferred":[
        "Zavr\u0161e"
    ],
    "name:ron_x_preferred":[
        "Zavr\u0161e"
    ],
    "name:slv_x_preferred":[
        "Zavr\u0161e"
    ],
    "name:ukr_x_preferred":[
        "\u0417\u0430\u0432\u0440\u0448\u0435"
    ],
    "name:und_x_variant":[
        "Zavr\u0161e"
    ],
    "wof:name":"Zavrse",
    "wof:placetype":"locality",
    "wof:population":422
},
  "geometry": {"coordinates":[15.15437,46.42495],"type":"Point"}
}