{
  "type": "Feature",
  "properties": {
    "gn:admin1_code":"B8",
    "gn:asciiname":"Jerman Vrh",
    "gn:country_code":"SI",
    "gn:dem":265,
    "gn:feature_class":"P",
    "gn:feature_code":"PPL",
    "gn:name":"Jerman Vrh",
    "gn:population":71,
    "gn:timezone":"Europe/Ljubljana",
    "iso:country":"SI",
    "wof:name":"Jerman Vrh",
    "wof:placetype":"locality",
    "wof:population":71
},
  "geometry": {"coordinates":[15.31343,45.92373],"type":"Point"}
}