{
  "type": "Feature",
  "properties": {
    "gn:admin1_code":"J7",
    "gn:asciiname":"Jama",
    "gn:country_code":"SI",
    "gn:dem":248,
    "gn:feature_class":"P",
    "gn:feature_code":"PPL",
    "gn:name":"Jama",
    "gn:population":27,
    "gn:timezone":"Europe/Ljubljana",
    "iso:country":"SI",
    "name:bos_x_preferred":[
        "Jama"
    ],
    "name:hrv_x_preferred":[
        "Jama"
    ],
    "name:nld_x_preferred":[
        "Jama"
    ],
    "name:pol_x_preferred":[
        "Jama"
    ],
    "name:ron_x_preferred":[
        "Jama"
    ],
    "name:slv_x_preferred":[
        "Jama"
    ],
    "name:ukr_x_preferred":[
        "\u042f\u043c\u0430"
    ],
    "name:urd_x_preferred":[
        "\u062c\u0645\u0627"
    ],
    "wof:name":"Jama",
    "wof:placetype":"locality",
    "wof:population":27
},
  "geometry": {"coordinates":[15.16118,45.75314],"type":"Point"}
}