{
  "type": "Feature",
  "properties": {
    "gn:admin1_code":"57",
    "gn:asciiname":"Senozete",
    "gn:country_code":"SI",
    "gn:dem":424,
    "gn:feature_class":"P",
    "gn:feature_code":"PPL",
    "gn:name":"Seno\u017eete",
    "gn:population":42,
    "gn:timezone":"Europe/Ljubljana",
    "iso:country":"SI",
    "name:und_x_variant":[
        "Seno\u017eete"
    ],
    "wof:name":"Senozete",
    "wof:placetype":"locality",
    "wof:population":42
},
  "geometry": {"coordinates":[15.20622,46.11296],"type":"Point"}
}