{
  "type": "Feature",
  "properties": {
    "gn:admin1_code":"57",
    "gn:asciiname":"Senozete",
    "gn:country_code":"SI",
    "gn:dem":424,
    "gn:feature_class":"P",
    "gn:feature_code":"PPL",
    "gn:name":"Seno\u017eete",
    "gn:population":42,
    "gn:timezone":"Europe/Ljubljana",
    "iso:country":"SI",
    "name:bos_x_preferred":[
        "Seno\u017eete"
    ],
    "name:nld_x_preferred":[
        "Seno\u017eete"
    ],
    "name:pol_x_preferred":[
        "Seno\u017eete"
    ],
    "name:ron_x_preferred":[
        "Seno\u017eete"
    ],
    "name:slv_x_preferred":[
        "Seno\u017eete"
    ],
    "name:ukr_x_preferred":[
        "\u0421\u0435\u043d\u043e\u0436\u0435\u0442\u0435"
    ],
    "wof:name":"Senozete",
    "wof:placetype":"locality",
    "wof:population":42
},
  "geometry": {"coordinates":[15.20622,46.11296],"type":"Point"}
}