{
  "type": "Feature",
  "properties": {
    "gn:admin1_code":"73",
    "gn:asciiname":"Dojutrovica",
    "gn:country_code":"SI",
    "gn:dem":405,
    "gn:feature_class":"P",
    "gn:feature_code":"PPL",
    "gn:name":"Dojutrovica",
    "gn:population":0,
    "gn:timezone":"Europe/Ljubljana",
    "iso:country":"SI",
    "wof:name":"Dojutrovica",
    "wof:placetype":"locality"
},
  "geometry": {"coordinates":[15.35111,45.69056],"type":"Point"}
}