{
  "type": "Feature",
  "properties": {
    "gn:admin1_code":"14",
    "gn:asciiname":"Trebence",
    "gn:country_code":"SI",
    "gn:dem":483,
    "gn:feature_class":"P",
    "gn:feature_code":"PPL",
    "gn:name":"Treben\u010de",
    "gn:population":95,
    "gn:timezone":"Europe/Ljubljana",
    "iso:country":"SI",
    "name:und_x_variant":[
        "Treben\u010de"
    ],
    "wof:name":"Trebence",
    "wof:placetype":"locality",
    "wof:population":95
},
  "geometry": {"coordinates":[13.98771,46.14334],"type":"Point"}
}