{
  "type": "Feature",
  "properties": {
    "gn:admin1_code":"39",
    "gn:asciiname":"Sela pri Visnji Gori",
    "gn:country_code":"SI",
    "gn:dem":651,
    "gn:feature_class":"P",
    "gn:feature_code":"PPL",
    "gn:name":"Sela pri Vi\u0161nji Gori",
    "gn:population":49,
    "gn:timezone":"Europe/Ljubljana",
    "iso:country":"SI",
    "name:bos_x_preferred":[
        "Sela pri Vi\u0161nji Gori"
    ],
    "name:nld_x_preferred":[
        "Sela pri Vi\u0161nji Gori"
    ],
    "name:pol_x_preferred":[
        "Sela pri Vi\u0161nji Gori"
    ],
    "name:ron_x_preferred":[
        "Sela pri Vi\u0161nji Gori"
    ],
    "name:slv_x_preferred":[
        "Sela pri Vi\u0161nji Gori"
    ],
    "name:ukr_x_preferred":[
        "\u0421\u0435\u043b\u0430-\u043f\u0440\u0438-\u0412\u0438\u0448\u043d\u0456 \u0413\u043e\u0440\u0438"
    ],
    "name:und_x_variant":[
        "Sela"
    ],
    "wof:name":"Sela pri Visnji Gori",
    "wof:placetype":"locality",
    "wof:population":49
},
  "geometry": {"coordinates":[14.77382,45.97718],"type":"Point"}
}