{
  "type": "Feature",
  "properties": {
    "gn:admin1_code":"39",
    "gn:asciiname":"Sela pri Visnji Gori",
    "gn:country_code":"SI",
    "gn:dem":651,
    "gn:feature_class":"P",
    "gn:feature_code":"PPL",
    "gn:name":"Sela pri Vi\u0161nji Gori",
    "gn:population":49,
    "gn:timezone":"Europe/Ljubljana",
    "iso:country":"SI",
    "name:und_x_variant":[
        "Sela",
        "Sela pri Vi\u0161nji Gori"
    ],
    "wof:name":"Sela pri Visnji Gori",
    "wof:placetype":"locality",
    "wof:population":49
},
  "geometry": {"coordinates":[14.77382,45.97718],"type":"Point"}
}