{
  "type": "Feature",
  "properties": {
    "gn:admin1_code":"29",
    "gn:asciiname":"Podgrad",
    "gn:country_code":"SI",
    "gn:dem":210,
    "gn:feature_class":"P",
    "gn:feature_code":"PPL",
    "gn:name":"Podgrad",
    "gn:population":160,
    "gn:timezone":"Europe/Ljubljana",
    "iso:country":"SI",
    "name:bos_x_preferred":[
        "Podgrad"
    ],
    "name:ceb_x_preferred":[
        "Podgrad"
    ],
    "name:fra_x_preferred":[
        "Podgrad"
    ],
    "name:hrv_x_preferred":[
        "Podgrad"
    ],
    "name:nld_x_preferred":[
        "Podgrad"
    ],
    "name:pol_x_preferred":[
        "Podgrad"
    ],
    "name:ron_x_preferred":[
        "Podgrad"
    ],
    "name:slv_x_preferred":[
        "Podgrad"
    ],
    "name:ukr_x_preferred":[
        "\u041f\u043e\u0434\u0433\u0440\u0430\u0434"
    ],
    "wof:name":"Podgrad",
    "wof:placetype":"locality",
    "wof:population":160
},
  "geometry": {"coordinates":[15.97222,46.68167],"type":"Point"}
}