{
  "type": "Feature",
  "properties": {
    "gn:admin1_code":"29",
    "gn:asciiname":"Podgrad",
    "gn:country_code":"SI",
    "gn:dem":210,
    "gn:feature_class":"P",
    "gn:feature_code":"PPL",
    "gn:name":"Podgrad",
    "gn:population":160,
    "gn:timezone":"Europe/Ljubljana",
    "iso:country":"SI",
    "wof:name":"Podgrad",
    "wof:placetype":"locality",
    "wof:population":160
},
  "geometry": {"coordinates":[15.97222,46.68167],"type":"Point"}
}