{
  "type": "Feature",
  "properties": {
    "gn:population":375,
    "iso:country":"SI",
    "name:bos_x_preferred":[
        "Kuzma"
    ],
    "name:ceb_x_preferred":[
        "Kuzma"
    ],
    "name:che_x_preferred":[
        "\u041a\u0443\u0437\u043c\u0430"
    ],
    "name:eng_x_preferred":[
        "Kuzma"
    ],
    "name:epo_x_preferred":[
        "Kuzma"
    ],
    "name:fra_x_preferred":[
        "Kuzma"
    ],
    "name:hbs_x_preferred":[
        "Kuzma"
    ],
    "name:heb_x_preferred":[
        "\u05e7\u05d5\u05d6\u05de\u05d4"
    ],
    "name:hrv_x_preferred":[
        "Kuzma"
    ],
    "name:hun_x_preferred":[
        "Kuzma"
    ],
    "name:mkd_x_preferred":[
        "\u041a\u0443\u0437\u043c\u0430"
    ],
    "name:nld_x_preferred":[
        "Kuzma"
    ],
    "name:pol_x_preferred":[
        "Kuzma"
    ],
    "name:ron_x_preferred":[
        "Kuzma"
    ],
    "name:slv_x_preferred":[
        "Kuzma"
    ],
    "name:spa_x_preferred":[
        "Kuzma"
    ],
    "name:srp_x_preferred":[
        "\u041a\u0443\u0437\u043c\u0430"
    ],
    "name:tat_x_preferred":[
        "\u041a\u0443\u0437\u043c\u0430"
    ],
    "name:tha_x_preferred":[
        "\u0e04\u0e39\u0e0b\u0e21\u0e32"
    ],
    "name:ukr_x_preferred":[
        "\u041a\u0443\u0437\u043c\u0430"
    ],
    "name:und_x_variant":[
        "Kuzdoblanje"
    ],
    "name:vie_x_preferred":[
        "Kuzma"
    ],
    "name:zho_x_preferred":[
        "\u5eab\u8332\u99ac"
    ],
    "qs:a0":"Slovenija",
    "qs:a1":"*",
    "qs:a1r":"0",
    "qs:adm0":"Slovenija",
    "qs:la_lc":"*",
    "qs:level":"locality",
    "qs:loc":"Kuzma",
    "qs:loc_alt":"Kuzma",
    "qs:pop":0,
    "qs:type":"buffered point",
    "wd:wordcount":296,
    "wof:name":"Kuzma",
    "wof:placetype":"locality",
    "wof:population":375
},
  "geometry": {"coordinates":[16.082726,46.841566],"type":"Point"}
}