{
  "type": "Feature",
  "properties": {
    "gn:population":375,
    "iso:country":"SI",
    "name:bos_x_preferred":[
        "Kuzma"
    ],
    "name:eng_x_preferred":[
        "Kuzma"
    ],
    "name:hbs_x_preferred":[
        "Kuzma"
    ],
    "name:hrv_x_preferred":[
        "Kuzma"
    ],
    "name:nld_x_preferred":[
        "Kuzma"
    ],
    "name:ron_x_preferred":[
        "Kuzma"
    ],
    "name:slv_x_preferred":[
        "Kuzma"
    ],
    "name:srp_x_preferred":[
        "\u041a\u0443\u0437\u043c\u0430"
    ],
    "name:ukr_x_preferred":[
        "\u041a\u0443\u0437\u043c\u0430"
    ],
    "name:unk_x_variant":[
        "Kuzdoblanje"
    ],
    "name:vie_x_preferred":[
        "Kuzma"
    ],
    "qs:a0":"Slovenija",
    "qs:a1":"*",
    "qs:a1r":"0",
    "qs:adm0":"Slovenija",
    "qs:la_lc":"*",
    "qs:level":"locality",
    "qs:loc":"Kuzma",
    "qs:loc_alt":"Kuzma",
    "qs:pop":0,
    "qs:type":"buffered point",
    "wd:wordcount":296,
    "wof:name":"Kuzma",
    "wof:placetype":"locality",
    "wof:population":375
},
  "geometry": {"coordinates":[16.082726,46.841566],"type":"Point"}
}