{
  "type": "Feature",
  "properties": {
    "gn:admin1_code":"35",
    "gn:asciiname":"Povzane",
    "gn:country_code":"SI",
    "gn:dem":574,
    "gn:feature_class":"P",
    "gn:feature_code":"PPL",
    "gn:name":"Pov\u017eane",
    "gn:population":107,
    "gn:timezone":"Europe/Ljubljana",
    "iso:country":"SI",
    "name:bos_x_preferred":[
        "Pov\u017eane"
    ],
    "name:ceb_x_preferred":[
        "Pov\u017eane"
    ],
    "name:nld_x_preferred":[
        "Pov\u017eane"
    ],
    "name:pol_x_preferred":[
        "Pov\u017eane"
    ],
    "name:ron_x_preferred":[
        "Pov\u017eane"
    ],
    "name:slv_x_preferred":[
        "Pov\u017eane"
    ],
    "name:ukr_x_preferred":[
        "\u041f\u043e\u0432\u0436\u0430\u043d\u0435"
    ],
    "name:und_x_variant":[
        "Pov\u017eane"
    ],
    "wof:name":"Povzane",
    "wof:placetype":"locality",
    "wof:population":107
},
  "geometry": {"coordinates":[13.99306,45.55978],"type":"Point"}
}