{
  "type": "Feature",
  "properties": {
    "gn:admin1_code":"C4",
    "gn:asciiname":"Petelinjek pri Locah",
    "gn:country_code":"SI",
    "gn:dem":312,
    "gn:feature_class":"P",
    "gn:feature_code":"PPL",
    "gn:name":"Petelinjek pri Lo\u010dah",
    "gn:population":47,
    "gn:timezone":"Europe/Ljubljana",
    "iso:country":"SI",
    "name:bos_x_preferred":[
        "Petelinjek pri Lo\u010dah"
    ],
    "name:hrv_x_preferred":[
        "Petelinjek pri Lo\u010dah"
    ],
    "name:nld_x_preferred":[
        "Petelinjek pri Lo\u010dah"
    ],
    "name:pol_x_preferred":[
        "Petelinjek pri Lo\u010dah"
    ],
    "name:ron_x_preferred":[
        "Petelinjek pri Lo\u010dah"
    ],
    "name:slv_x_preferred":[
        "Petelinjek pri Lo\u010dah"
    ],
    "name:ukr_x_preferred":[
        "\u041f\u0435\u0442\u0435\u043b\u0438\u043d\u0454\u043a-\u043f\u0440\u0438-\u041b\u043e\u0447\u0430\u0445"
    ],
    "name:und_x_variant":[
        "Petelinjek pri Lo\u010dah"
    ],
    "wof:name":"Petelinjek pri Locah",
    "wof:placetype":"locality",
    "wof:population":47
},
  "geometry": {"coordinates":[15.5234,46.33252],"type":"Point"}
}