{
  "type": "Feature",
  "properties": {
    "gn:admin1_code":"39",
    "gn:asciiname":"Leskovec",
    "gn:country_code":"SI",
    "gn:dem":679,
    "gn:feature_class":"P",
    "gn:feature_code":"PPL",
    "gn:name":"Leskovec",
    "gn:population":108,
    "gn:timezone":"Europe/Ljubljana",
    "iso:country":"SI",
    "wof:name":"Leskovec",
    "wof:placetype":"locality",
    "wof:population":108
},
  "geometry": {"coordinates":[14.75306,45.98889000000001],"type":"Point"}
}