{
  "type": "Feature",
  "properties": {
    "gn:admin1_code":"39",
    "gn:asciiname":"Leskovec",
    "gn:country_code":"SI",
    "gn:dem":679,
    "gn:feature_class":"P",
    "gn:feature_code":"PPL",
    "gn:name":"Leskovec",
    "gn:population":108,
    "gn:timezone":"Europe/Ljubljana",
    "iso:country":"SI",
    "name:bos_x_preferred":[
        "Leskovec"
    ],
    "name:ceb_x_preferred":[
        "Leskovec"
    ],
    "name:nld_x_preferred":[
        "Leskovec"
    ],
    "name:pol_x_preferred":[
        "Leskovec"
    ],
    "name:ron_x_preferred":[
        "Leskovec"
    ],
    "name:slv_x_preferred":[
        "Leskovec"
    ],
    "name:ukr_x_preferred":[
        "\u041b\u0435\u0441\u043a\u043e\u0432\u0435\u0446\u044c"
    ],
    "wof:name":"Leskovec",
    "wof:placetype":"locality",
    "wof:population":108
},
  "geometry": {"coordinates":[14.75306,45.98889000000001],"type":"Point"}
}