{
  "type": "Feature",
  "properties": {
    "gn:admin1_code":"B4",
    "gn:asciiname":"Dolenja Gomila",
    "gn:country_code":"SI",
    "gn:dem":153,
    "gn:feature_class":"P",
    "gn:feature_code":"PPLL",
    "gn:name":"Dolenja Gomila",
    "gn:population":0,
    "gn:timezone":"Europe/Ljubljana",
    "iso:country":"SI",
    "wof:name":"Dolenja Gomila",
    "wof:placetype":"locality"
},
  "geometry": {"coordinates":[15.33309,45.86691],"type":"Point"}
}