{
  "type": "Feature",
  "properties": {
    "gn:admin1_code":"01",
    "gn:asciiname":"Gustini",
    "gn:country_code":"SI",
    "gn:dem":371,
    "gn:feature_class":"P",
    "gn:feature_code":"PPL",
    "gn:name":"Gu\u0161tini",
    "gn:population":0,
    "gn:timezone":"Europe/Ljubljana",
    "iso:country":"SI",
    "name:und_x_variant":[
        "O\u0161tini",
        "Gu\u0161tini"
    ],
    "wof:name":"Gustini",
    "wof:placetype":"locality"
},
  "geometry": {"coordinates":[13.82083,45.91],"type":"Point"}
}