{
  "type": "Feature",
  "properties": {
    "gn:gn_country":"SI",
    "gn:gn_fcode":"PPL",
    "gn:gn_pop":0,
    "gn:population":348,
    "iso:country":"SI",
    "name:dut_x_preferred":[
        "\u010cepovan"
    ],
    "name:eng_x_preferred":[
        "\u010cepovan"
    ],
    "name:hun_x_preferred":[
        "\u010cepovan"
    ],
    "name:ita_x_preferred":[
        "Chiapovano"
    ],
    "name:rum_x_preferred":[
        "\u010cepovan"
    ],
    "name:slv_x_preferred":[
        "\u010cepovan"
    ],
    "name:ukr_x_preferred":[
        "\u0427\u0435\u043f\u043e\u0432\u0430\u043d"
    ],
    "name:unk_x_variant":[
        "Chiapovano"
    ],
    "qs_pg:aaroncc":"SI",
    "qs_pg:gn_country":"SI",
    "qs_pg:gn_fcode":"PPL",
    "qs_pg:gn_pop":0,
    "qs_pg:name":"\u010cepovan",
    "qs_pg:name_adm0":"Slovenija",
    "qs_pg:name_adm1":"Nova Gorica",
    "qs_pg:photos":32,
    "qs_pg:photos_1k":6,
    "qs_pg:photos_9k":1,
    "qs_pg:photos_9r":2,
    "qs_pg:photos_all":32,
    "qs_pg:photos_sr":2,
    "qs_pg:pop_sr":0,
    "qs_pg:qs_pg_placetype":"locality",
    "qs_pg:qs_pg_placetype_gp":"Town",
    "qs_pg:woe_adm0":23424945,
    "woe:adm0_id":23424945,
    "woe:name_adm0":"Slovenija",
    "woe:name_adm1":"Nova Gorica",
    "woe:placetype":"Town",
    "wof:name":"\u010cepovan",
    "wof:placetype":"locality",
    "wof:population":348
},
  "geometry": {"coordinates":[13.79694,46.04944],"type":"Point"}
}