{
  "type": "Feature",
  "properties": {
    "gn:admin1_code":"J7",
    "gn:asciiname":"Dolenje Karteljevo",
    "gn:country_code":"SI",
    "gn:dem":433,
    "gn:feature_class":"P",
    "gn:feature_code":"PPL",
    "gn:name":"Dolenje Karteljevo",
    "gn:population":116,
    "gn:timezone":"Europe/Ljubljana",
    "iso:country":"SI",
    "wof:name":"Dolenje Karteljevo",
    "wof:placetype":"locality",
    "wof:population":116
},
  "geometry": {"coordinates":[15.15,45.86667],"type":"Point"}
}