{
  "type": "Feature",
  "properties": {
    "gn:admin1_code":"O2",
    "gn:asciiname":"Mevkuz",
    "gn:country_code":"SI",
    "gn:dem":639,
    "gn:feature_class":"P",
    "gn:feature_code":"PPL",
    "gn:name":"Mevku\u017e",
    "gn:population":83,
    "gn:timezone":"Europe/Ljubljana",
    "iso:country":"SI",
    "name:bos_x_preferred":[
        "Mevku\u017e"
    ],
    "name:hrv_x_preferred":[
        "Mevku\u017e"
    ],
    "name:nld_x_preferred":[
        "Mevku\u017e"
    ],
    "name:pol_x_preferred":[
        "Mevku\u017e"
    ],
    "name:ron_x_preferred":[
        "Mevku\u017e"
    ],
    "name:slv_x_preferred":[
        "Mevku\u017e"
    ],
    "name:ukr_x_preferred":[
        "\u041c\u0435\u0432\u043a\u0443\u0436"
    ],
    "name:und_x_variant":[
        "Mevku\u017e"
    ],
    "wof:name":"Mevkuz",
    "wof:placetype":"locality",
    "wof:population":83
},
  "geometry": {"coordinates":[14.06596,46.38398],"type":"Point"}
}