{
  "type": "Feature",
  "properties": {
    "gn:admin1_code":"J7",
    "gn:asciiname":"Gorenje Karteljevo",
    "gn:country_code":"SI",
    "gn:dem":433,
    "gn:feature_class":"P",
    "gn:feature_code":"PPL",
    "gn:name":"Gorenje Karteljevo",
    "gn:population":150,
    "gn:timezone":"Europe/Ljubljana",
    "iso:country":"SI",
    "name:bos_x_preferred":[
        "Gorenje Karteljevo"
    ],
    "name:ceb_x_preferred":[
        "Gorenje Karteljevo"
    ],
    "name:hrv_x_preferred":[
        "Gorenje Karteljevo"
    ],
    "name:nld_x_preferred":[
        "Gorenje Karteljevo"
    ],
    "name:pol_x_preferred":[
        "Gorenje Karteljevo"
    ],
    "name:ron_x_preferred":[
        "Gorenje Karteljevo"
    ],
    "name:slv_x_preferred":[
        "Gorenje Karteljevo"
    ],
    "name:ukr_x_preferred":[
        "\u0413\u043e\u0440\u0435\u043d\u0454 \u041a\u0430\u0440\u0442\u0435\u043b\u0454\u0432\u043e"
    ],
    "wof:name":"Gorenje Karteljevo",
    "wof:placetype":"locality",
    "wof:population":150
},
  "geometry": {"coordinates":[15.15,45.86667],"type":"Point"}
}