{
  "type": "Feature",
  "properties": {
    "gn:admin1_code":"B9",
    "gn:asciiname":"Trnje",
    "gn:country_code":"SI",
    "gn:dem":382,
    "gn:feature_class":"P",
    "gn:feature_code":"PPL",
    "gn:name":"Trnje",
    "gn:population":74,
    "gn:timezone":"Europe/Ljubljana",
    "iso:country":"SI",
    "wof:name":"Trnje",
    "wof:placetype":"locality",
    "wof:population":74
},
  "geometry": {"coordinates":[14.29318,46.17933],"type":"Point"}
}