{
  "type": "Feature",
  "properties": {
    "gn:admin1_code":"I5",
    "gn:asciiname":"Berinjek",
    "gn:country_code":"SI",
    "gn:dem":733,
    "gn:feature_class":"P",
    "gn:feature_code":"PPL",
    "gn:name":"Berinjek",
    "gn:population":11,
    "gn:timezone":"Europe/Ljubljana",
    "iso:country":"SI",
    "wof:name":"Berinjek",
    "wof:placetype":"locality",
    "wof:population":11
},
  "geometry": {"coordinates":[15.03584,46.03359],"type":"Point"}
}