{
  "type": "Feature",
  "properties": {
    "gn:admin1_code":"I5",
    "gn:asciiname":"Berinjek",
    "gn:country_code":"SI",
    "gn:dem":733,
    "gn:feature_class":"P",
    "gn:feature_code":"PPL",
    "gn:name":"Berinjek",
    "gn:population":11,
    "gn:timezone":"Europe/Ljubljana",
    "iso:country":"SI",
    "name:bos_x_preferred":[
        "Berinjek"
    ],
    "name:bul_x_preferred":[
        "\u0411\u0435\u0440\u0438\u043d\u0435\u043a"
    ],
    "name:epo_x_preferred":[
        "Berinjek"
    ],
    "name:nld_x_preferred":[
        "Berinjek"
    ],
    "name:pol_x_preferred":[
        "Berinjek"
    ],
    "name:ron_x_preferred":[
        "Berinjek"
    ],
    "name:slv_x_preferred":[
        "Berinjek"
    ],
    "name:ukr_x_preferred":[
        "\u0411\u0435\u0440\u0438\u043d\u0454\u043a"
    ],
    "wof:name":"Berinjek",
    "wof:placetype":"locality",
    "wof:population":11
},
  "geometry": {"coordinates":[15.03584,46.03359],"type":"Point"}
}