{
  "type": "Feature",
  "properties": {
    "gn:admin1_code":"20",
    "gn:asciiname":"Podtabor",
    "gn:country_code":"SI",
    "gn:dem":539,
    "gn:feature_class":"P",
    "gn:feature_code":"PPL",
    "gn:name":"Podtabor",
    "gn:population":92,
    "gn:timezone":"Europe/Ljubljana",
    "iso:country":"SI",
    "name:bos_x_preferred":[
        "Podtabor"
    ],
    "name:bul_x_preferred":[
        "\u041f\u043e\u0434\u0442\u0430\u0431\u043e\u0440"
    ],
    "name:nld_x_preferred":[
        "Podtabor"
    ],
    "name:pol_x_preferred":[
        "Podtabor"
    ],
    "name:ron_x_preferred":[
        "Podtabor"
    ],
    "name:slv_x_preferred":[
        "Podtabor"
    ],
    "name:ukr_x_preferred":[
        "\u041f\u043e\u0434\u0442\u0430\u0431\u043e\u0440"
    ],
    "wof:name":"Podtabor",
    "wof:placetype":"locality",
    "wof:population":92
},
  "geometry": {"coordinates":[14.76805,45.77187],"type":"Point"}
}