{
  "type": "Feature",
  "properties": {
    "gn:admin1_code":"80",
    "gn:asciiname":"Crnelavci",
    "gn:cc2":"SI",
    "gn:country_code":"SI",
    "gn:dem":194,
    "gn:feature_class":"P",
    "gn:feature_code":"PPL",
    "gn:name":"\u010crnelavci",
    "gn:population":0,
    "gn:timezone":"Europe/Ljubljana",
    "iso:country":"SI",
    "name:und_x_variant":[
        "\u010crneslavci",
        "\u010crnelavci"
    ],
    "wof:name":"Crnelavci",
    "wof:placetype":"locality"
},
  "geometry": {"coordinates":[16.13972,46.67083],"type":"Point"}
}