{
  "type": "Feature",
  "properties": {
    "gn:admin1_code":"87",
    "gn:asciiname":"Runec",
    "gn:country_code":"SI",
    "gn:dem":316,
    "gn:feature_class":"P",
    "gn:feature_code":"PPL",
    "gn:name":"Rune\u010d",
    "gn:population":177,
    "gn:timezone":"Europe/Ljubljana",
    "iso:country":"SI",
    "name:bos_x_preferred":[
        "Rune\u010d"
    ],
    "name:bul_x_preferred":[
        "\u0420\u0443\u043d\u0435\u0447"
    ],
    "name:ceb_x_preferred":[
        "Rune\u010d"
    ],
    "name:nld_x_preferred":[
        "Rune\u010d"
    ],
    "name:pol_x_preferred":[
        "Rune\u010d"
    ],
    "name:ron_x_preferred":[
        "Rune\u010d"
    ],
    "name:slv_x_preferred":[
        "Rune\u010d"
    ],
    "name:ukr_x_preferred":[
        "\u0420\u0443\u043d\u0435\u0447"
    ],
    "name:und_x_variant":[
        "Rune\u010d"
    ],
    "wof:name":"Runec",
    "wof:placetype":"locality",
    "wof:population":177
},
  "geometry": {"coordinates":[16.13,46.46361],"type":"Point"}
}