{
  "type": "Feature",
  "properties": {
    "gn:admin1_code":"I6",
    "gn:asciiname":"Moravci v Slov. Goricah",
    "gn:country_code":"SI",
    "gn:dem":300,
    "gn:feature_class":"P",
    "gn:feature_code":"PPL",
    "gn:name":"Moravci v Slov. Goricah",
    "gn:population":396,
    "gn:timezone":"Europe/Ljubljana",
    "iso:country":"SI",
    "name:bos_x_preferred":[
        "Moravci v Slovenskih goricah"
    ],
    "name:ceb_x_preferred":[
        "Moravci v Slov. Goricah"
    ],
    "name:hrv_x_preferred":[
        "Moravci v Slovenskih Goricah"
    ],
    "name:nld_x_preferred":[
        "Moravci v Slovenskih Goricah"
    ],
    "name:pol_x_preferred":[
        "Moravci v Slovenskih Goricah"
    ],
    "name:ron_x_preferred":[
        "Moravci v Slovenskih goricah"
    ],
    "name:slv_x_preferred":[
        "Moravci v Slovenskih goricah"
    ],
    "name:ukr_x_preferred":[
        "\u041c\u043e\u0440\u0430\u0432\u0446\u0456-\u0432-\u0421\u043b\u043e\u0432\u0435\u043d\u0441\u044c\u043a\u0438\u0445 \u0413\u043e\u0440\u0438\u0446\u044f\u0445"
    ],
    "name:und_x_variant":[
        "Moravci"
    ],
    "wof:name":"Moravci v Slov. Goricah",
    "wof:placetype":"locality",
    "wof:population":396
},
  "geometry": {"coordinates":[16.02639,46.52222],"type":"Point"}
}