{
  "type": "Feature",
  "properties": {
    "gn:admin1_code":"I6",
    "gn:asciiname":"Moravci v Slov. Goricah",
    "gn:country_code":"SI",
    "gn:dem":300,
    "gn:feature_class":"P",
    "gn:feature_code":"PPL",
    "gn:name":"Moravci v Slov. Goricah",
    "gn:population":396,
    "gn:timezone":"Europe/Ljubljana",
    "iso:country":"SI",
    "name:und_x_variant":[
        "Moravci",
        "Moravci v Slovenskih Goricah"
    ],
    "wof:name":"Moravci v Slov. Goricah",
    "wof:placetype":"locality",
    "wof:population":396
},
  "geometry": {"coordinates":[16.02639,46.52222],"type":"Point"}
}