{
  "type": "Feature",
  "properties": {
    "iso:country":"SI",
    "name:slv_x_preferred":[
        "Toma\u010devo"
    ],
    "wof:name":"Tomacevo",
    "wof:placetype":"neighbourhood"
},
  "geometry": {"coordinates":[14.53358181859661,46.08162624686581],"type":"Point"}
}