{
  "type": "Feature",
  "properties": {
    "gn:admin1_code":"O3",
    "gn:asciiname":"Orehovec",
    "gn:country_code":"SI",
    "gn:dem":224,
    "gn:feature_class":"P",
    "gn:feature_code":"PPL",
    "gn:name":"Orehovec",
    "gn:population":226,
    "gn:timezone":"Europe/Ljubljana",
    "iso:country":"SI",
    "name:bos_x_preferred":[
        "Orehovec"
    ],
    "name:ceb_x_preferred":[
        "Orehovec"
    ],
    "name:ita_x_preferred":[
        "Orehovec"
    ],
    "name:pol_x_preferred":[
        "Orehovec"
    ],
    "name:slv_x_preferred":[
        "Orehovec"
    ],
    "name:ukr_x_preferred":[
        "\u041e\u0440\u0435\u0445\u043e\u0432\u0435\u0446\u044c"
    ],
    "wof:name":"Orehovec",
    "wof:placetype":"locality",
    "wof:population":226
},
  "geometry": {"coordinates":[15.42086,45.82566],"type":"Point"}
}