{
  "type": "Feature",
  "properties": {
    "gn:admin1_code":"O3",
    "gn:asciiname":"Orehovec",
    "gn:country_code":"SI",
    "gn:dem":224,
    "gn:feature_class":"P",
    "gn:feature_code":"PPL",
    "gn:name":"Orehovec",
    "gn:population":226,
    "gn:timezone":"Europe/Ljubljana",
    "iso:country":"SI",
    "wof:name":"Orehovec",
    "wof:placetype":"locality",
    "wof:population":226
},
  "geometry": {"coordinates":[15.42086,45.82566],"type":"Point"}
}