{
  "type": "Feature",
  "properties": {
    "gn:admin1_code":"39",
    "gn:asciiname":"Grintovec",
    "gn:country_code":"SI",
    "gn:dem":308,
    "gn:feature_class":"P",
    "gn:feature_code":"PPL",
    "gn:name":"Grintovec",
    "gn:population":95,
    "gn:timezone":"Europe/Ljubljana",
    "iso:country":"SI",
    "name:bos_x_preferred":[
        "Grintovec"
    ],
    "name:nld_x_preferred":[
        "Grintovec"
    ],
    "name:pol_x_preferred":[
        "Grintovec"
    ],
    "name:ron_x_preferred":[
        "Grintovec"
    ],
    "name:slv_x_preferred":[
        "Grintovec"
    ],
    "name:ukr_x_preferred":[
        "\u0413\u0440\u0438\u043d\u0442\u043e\u0432\u0435\u0446\u044c"
    ],
    "wof:name":"Grintovec",
    "wof:placetype":"locality",
    "wof:population":95
},
  "geometry": {"coordinates":[14.8249,45.85386],"type":"Point"}
}