{
  "type": "Feature",
  "properties": {
    "gn:admin1_code":"39",
    "gn:asciiname":"Grintovec",
    "gn:country_code":"SI",
    "gn:dem":308,
    "gn:feature_class":"P",
    "gn:feature_code":"PPL",
    "gn:name":"Grintovec",
    "gn:population":95,
    "gn:timezone":"Europe/Ljubljana",
    "iso:country":"SI",
    "wof:name":"Grintovec",
    "wof:placetype":"locality",
    "wof:population":95
},
  "geometry": {"coordinates":[14.8249,45.85386],"type":"Point"}
}