{
  "type": "Feature",
  "properties": {
    "gn:admin1_code":"B6",
    "gn:asciiname":"Zurkov Dol",
    "gn:country_code":"SI",
    "gn:dem":250,
    "gn:feature_class":"P",
    "gn:feature_code":"PPL",
    "gn:name":"\u017durkov Dol",
    "gn:population":182,
    "gn:timezone":"Europe/Ljubljana",
    "iso:country":"SI",
    "name:und_x_variant":[
        "\u017durkov Dol"
    ],
    "wof:name":"Zurkov Dol",
    "wof:placetype":"locality",
    "wof:population":182
},
  "geometry": {"coordinates":[15.33413,46.02409],"type":"Point"}
}