{
  "type": "Feature",
  "properties": {
    "gn:admin1_code":"B6",
    "gn:asciiname":"Zurkov Dol",
    "gn:country_code":"SI",
    "gn:dem":250,
    "gn:feature_class":"P",
    "gn:feature_code":"PPL",
    "gn:name":"\u017durkov Dol",
    "gn:population":182,
    "gn:timezone":"Europe/Ljubljana",
    "iso:country":"SI",
    "name:bos_x_preferred":[
        "\u017durkov Dol"
    ],
    "name:ceb_x_preferred":[
        "\u017durkov Dol"
    ],
    "name:hye_x_preferred":[
        "\u0536\u0578\u0582\u0580\u056f\u0578\u057e \u0534\u0578\u056c"
    ],
    "name:nld_x_preferred":[
        "\u017durkov Dol"
    ],
    "name:pol_x_preferred":[
        "\u017durkov Dol"
    ],
    "name:ron_x_preferred":[
        "\u017durkov Dol"
    ],
    "name:slv_x_preferred":[
        "\u017durkov Dol"
    ],
    "name:ukr_x_preferred":[
        "\u0416\u0443\u0440\u043a\u043e\u0432 \u0414\u043e\u043b"
    ],
    "name:und_x_variant":[
        "\u017durkov Dol"
    ],
    "wof:name":"Zurkov Dol",
    "wof:placetype":"locality",
    "wof:population":182
},
  "geometry": {"coordinates":[15.33413,46.02409],"type":"Point"}
}