{
  "type": "Feature",
  "properties": {
    "gn:admin1_code":"D6",
    "gn:asciiname":"Nedelica",
    "gn:country_code":"SI",
    "gn:dem":170,
    "gn:feature_class":"P",
    "gn:feature_code":"PPL",
    "gn:name":"Nedelica",
    "gn:population":576,
    "gn:timezone":"Europe/Ljubljana",
    "iso:country":"SI",
    "name:bos_x_preferred":[
        "Nedelica"
    ],
    "name:ceb_x_preferred":[
        "Nedelica"
    ],
    "name:epo_x_preferred":[
        "Nedelica"
    ],
    "name:hun_x_preferred":[
        "Zork\u00f3h\u00e1za"
    ],
    "name:nld_x_preferred":[
        "Nedelica"
    ],
    "name:pol_x_preferred":[
        "Nedelica"
    ],
    "name:ron_x_preferred":[
        "Nedelica"
    ],
    "name:slv_x_preferred":[
        "Nedelica"
    ],
    "name:ukr_x_preferred":[
        "\u041d\u0435\u0434\u0435\u043b\u0438\u0446\u044f"
    ],
    "name:und_x_variant":[
        "Brezovec Del",
        "Brezovec"
    ],
    "wof:name":"Nedelica",
    "wof:placetype":"locality",
    "wof:population":576
},
  "geometry": {"coordinates":[16.33333,46.61667],"type":"Point"}
}