{
  "type": "Feature",
  "properties": {
    "gn:country":"SI",
    "gn:fcode":"PPL",
    "gn:population":0,
    "iso:country":"SI",
    "name:bos_x_preferred":[
        "Ptujska Gora"
    ],
    "name:ceb_x_preferred":[
        "Ptujska Gora"
    ],
    "name:deu_x_preferred":[
        "Ptujska Gora"
    ],
    "name:eng_x_preferred":[
        "Ptujska Gora"
    ],
    "name:fra_x_preferred":[
        "Ptujska Gora"
    ],
    "name:hrv_x_preferred":[
        "Ptujska Gora"
    ],
    "name:ita_x_preferred":[
        "Ptujska Gora"
    ],
    "name:nld_x_preferred":[
        "Ptujska Gora"
    ],
    "name:pol_x_preferred":[
        "Ptujska Gora"
    ],
    "name:ron_x_preferred":[
        "Ptujska Gora"
    ],
    "name:slv_x_preferred":[
        "Ptujska Gora"
    ],
    "qs_pg:aaroncc":"SI",
    "qs_pg:gn_country":"SI",
    "qs_pg:gn_fcode":"PPL",
    "qs_pg:gn_pop":0,
    "qs_pg:name":"Ptujska Gora",
    "qs_pg:name_adm0":"Slovenija",
    "qs_pg:name_adm1":"Ptuj",
    "qs_pg:photos":18,
    "qs_pg:photos_1k":4,
    "qs_pg:photos_9k":1,
    "qs_pg:photos_9r":1,
    "qs_pg:photos_all":18,
    "qs_pg:photos_sr":1,
    "qs_pg:pop_sr":0,
    "qs_pg:qs_pg_placetype":"locality",
    "qs_pg:qs_pg_placetype_gp":"Town",
    "qs_pg:woe_adm0":23424945,
    "woe:adm0_id":23424945,
    "woe:name_adm0":"Slovenija",
    "woe:name_adm1":"Ptuj",
    "woe:placetype":"Town",
    "wof:name":"Ptujska Gora",
    "wof:placetype":"locality",
    "wof:population":381
},
  "geometry": {"coordinates":[15.76,46.355],"type":"Point"}
}