{
  "type": "Feature",
  "properties": {
    "gn:admin1_code":"M6",
    "gn:asciiname":"Petanjci",
    "gn:country_code":"SI",
    "gn:dem":196,
    "gn:feature_class":"P",
    "gn:feature_code":"PPL",
    "gn:name":"Petanjci",
    "gn:population":667,
    "gn:timezone":"Europe/Ljubljana",
    "iso:country":"SI",
    "name:und_x_variant":[
        "Sz\u00e9cs\u00e9nyk\u00fat",
        "Sz\u00e9ch\u00e9nyk\u00fat",
        "Petanjci"
    ],
    "wof:name":"Petanjci",
    "wof:placetype":"locality",
    "wof:population":667
},
  "geometry": {"coordinates":[16.06611,46.65333],"type":"Point"}
}