{
  "type": "Feature",
  "properties": {
    "gn:admin1_code":"I7",
    "gn:asciiname":"Podgora pri Lozu",
    "gn:country_code":"SI",
    "gn:dem":588,
    "gn:feature_class":"P",
    "gn:feature_code":"PPL",
    "gn:name":"Podgora pri Lo\u017eu",
    "gn:population":114,
    "gn:timezone":"Europe/Ljubljana",
    "iso:country":"SI",
    "wof:name":"Podgora pri Lozu",
    "wof:placetype":"locality",
    "wof:population":114
},
  "geometry": {"coordinates":[14.48972,45.68444],"type":"Point"}
}