{
  "type": "Feature",
  "properties": {
    "gn:admin1_code":"I7",
    "gn:asciiname":"Podgora pri Lozu",
    "gn:country_code":"SI",
    "gn:dem":588,
    "gn:feature_class":"P",
    "gn:feature_code":"PPL",
    "gn:name":"Podgora pri Lo\u017eu",
    "gn:population":114,
    "gn:timezone":"Europe/Ljubljana",
    "iso:country":"SI",
    "name:bos_x_preferred":[
        "Podgora pri Lo\u017eu"
    ],
    "name:ceb_x_preferred":[
        "Podgora pri Lo\u017eu"
    ],
    "name:hrv_x_preferred":[
        "Podgora pri Lo\u017eu"
    ],
    "name:pol_x_preferred":[
        "Podgora pri Lo\u017eu"
    ],
    "name:ron_x_preferred":[
        "Podgora pri Lo\u017eu"
    ],
    "name:slv_x_preferred":[
        "Podgora pri Lo\u017eu"
    ],
    "name:ukr_x_preferred":[
        "\u041f\u043e\u0434\u0433\u043e\u0440\u0430-\u043f\u0440\u0438-\u041b\u043e\u0436\u0443"
    ],
    "wof:name":"Podgora pri Lozu",
    "wof:placetype":"locality",
    "wof:population":114
},
  "geometry": {"coordinates":[14.48972,45.68444],"type":"Point"}
}