{
  "type": "Feature",
  "properties": {
    "gn:admin1_code":"I2",
    "gn:asciiname":"Trdkova",
    "gn:country_code":"SI",
    "gn:dem":352,
    "gn:feature_class":"P",
    "gn:feature_code":"PPL",
    "gn:name":"Trdkova",
    "gn:population":178,
    "gn:timezone":"Europe/Ljubljana",
    "iso:country":"SI",
    "name:und_x_variant":[
        "Magasfok",
        "Trdkovo",
        "Trdkova"
    ],
    "wof:name":"Trdkova",
    "wof:placetype":"locality",
    "wof:population":178
},
  "geometry": {"coordinates":[16.12767,46.85327],"type":"Point"}
}