{
  "type": "Feature",
  "properties": {
    "gn:admin1_code":"I2",
    "gn:asciiname":"Trdkova",
    "gn:country_code":"SI",
    "gn:dem":352,
    "gn:feature_class":"P",
    "gn:feature_code":"PPL",
    "gn:name":"Trdkova",
    "gn:population":178,
    "gn:timezone":"Europe/Ljubljana",
    "iso:country":"SI",
    "name:bos_x_preferred":[
        "Trdkova"
    ],
    "name:ceb_x_preferred":[
        "Trdkova"
    ],
    "name:deu_x_preferred":[
        "Trdkova"
    ],
    "name:epo_x_preferred":[
        "Trdkova"
    ],
    "name:hrv_x_preferred":[
        "Trdkova"
    ],
    "name:hun_x_preferred":[
        "T\u00fcrke"
    ],
    "name:nld_x_preferred":[
        "Trdkova"
    ],
    "name:pol_x_preferred":[
        "Trdkova"
    ],
    "name:ron_x_preferred":[
        "Trdkova"
    ],
    "name:slv_x_preferred":[
        "Trdkova"
    ],
    "name:ukr_x_preferred":[
        "\u0422\u0440\u0434\u043a\u043e\u0432\u0430"
    ],
    "name:und_x_variant":[
        "Magasfok",
        "Trdkovo",
        "Trdkova"
    ],
    "wof:name":"Trdkova",
    "wof:placetype":"locality",
    "wof:population":178
},
  "geometry": {"coordinates":[16.12767,46.85327],"type":"Point"}
}