{
  "type": "Feature",
  "properties": {
    "gn:admin1_code":"J1",
    "gn:asciiname":"Grdina",
    "gn:country_code":"SI",
    "gn:dem":364,
    "gn:feature_class":"P",
    "gn:feature_code":"PPL",
    "gn:name":"Grdina",
    "gn:population":128,
    "gn:timezone":"Europe/Ljubljana",
    "iso:country":"SI",
    "wof:name":"Grdina",
    "wof:placetype":"locality",
    "wof:population":128
},
  "geometry": {"coordinates":[15.73156,46.29379],"type":"Point"}
}