{
  "type": "Feature",
  "properties": {
    "gn:admin1_code":"01",
    "gn:asciiname":"Zavino",
    "gn:country_code":"SI",
    "gn:dem":147,
    "gn:feature_class":"P",
    "gn:feature_code":"PPL",
    "gn:name":"Zavino",
    "gn:population":92,
    "gn:timezone":"Europe/Ljubljana",
    "iso:country":"SI",
    "name:bos_x_preferred":[
        "Zavino"
    ],
    "name:bul_x_preferred":[
        "\u0417\u0430\u0432\u0438\u043d\u043e"
    ],
    "name:hun_x_preferred":[
        "Zavino"
    ],
    "name:ita_x_preferred":[
        "Svino"
    ],
    "name:nld_x_preferred":[
        "Zavino"
    ],
    "name:pol_x_preferred":[
        "Zavino"
    ],
    "name:ron_x_preferred":[
        "Zavino"
    ],
    "name:slv_x_preferred":[
        "Zavino"
    ],
    "name:srp_x_preferred":[
        "\u0417\u0430\u0432\u0438\u043d\u043e"
    ],
    "name:ukr_x_preferred":[
        "\u0417\u0430\u0432\u0438\u043d\u043e"
    ],
    "wof:name":"Zavino",
    "wof:placetype":"locality",
    "wof:population":92
},
  "geometry": {"coordinates":[13.83222,45.85361],"type":"Point"}
}