{
  "type": "Feature",
  "properties": {
    "gn:admin1_code":"01",
    "gn:asciiname":"Zavino",
    "gn:country_code":"SI",
    "gn:dem":147,
    "gn:feature_class":"P",
    "gn:feature_code":"PPL",
    "gn:name":"Zavino",
    "gn:population":92,
    "gn:timezone":"Europe/Ljubljana",
    "iso:country":"SI",
    "name:und_x_variant":[
        "Svino",
        "Zavino"
    ],
    "wof:name":"Zavino",
    "wof:placetype":"locality",
    "wof:population":92
},
  "geometry": {"coordinates":[13.83222,45.85361],"type":"Point"}
}