{
  "type": "Feature",
  "properties": {
    "gn:admin1_code":"I5",
    "gn:asciiname":"Zgornji Log",
    "gn:country_code":"SI",
    "gn:dem":247,
    "gn:feature_class":"P",
    "gn:feature_code":"PPL",
    "gn:name":"Zgornji Log",
    "gn:population":148,
    "gn:timezone":"Europe/Ljubljana",
    "iso:country":"SI",
    "name:und_x_variant":[
        "Log",
        "Gornji Log",
        "Gorenji Log"
    ],
    "wof:name":"Zgornji Log",
    "wof:placetype":"locality",
    "wof:population":148
},
  "geometry": {"coordinates":[14.83333,46.08333],"type":"Point"}
}