{
  "type": "Feature",
  "properties": {
    "gn:admin1_code":"I5",
    "gn:asciiname":"Zgornji Log",
    "gn:country_code":"SI",
    "gn:dem":247,
    "gn:feature_class":"P",
    "gn:feature_code":"PPL",
    "gn:name":"Zgornji Log",
    "gn:population":148,
    "gn:timezone":"Europe/Ljubljana",
    "iso:country":"SI",
    "name:bos_x_preferred":[
        "Zgornji Log"
    ],
    "name:bul_x_preferred":[
        "\u0417\u0433\u043e\u0440\u043d\u0438 \u041b\u043e\u0433"
    ],
    "name:ceb_x_preferred":[
        "Zgornji Log"
    ],
    "name:nld_x_preferred":[
        "Zgornji Log"
    ],
    "name:pol_x_preferred":[
        "Zgornji Log"
    ],
    "name:ron_x_preferred":[
        "Zgornji Log"
    ],
    "name:slv_x_preferred":[
        "Zgornji Log"
    ],
    "name:ukr_x_preferred":[
        "\u0417\u0433\u043e\u0440\u043d\u0456\u0439 \u041b\u043e\u0433"
    ],
    "name:und_x_variant":[
        "Log",
        "Gornji Log",
        "Gorenji Log"
    ],
    "wof:name":"Zgornji Log",
    "wof:placetype":"locality",
    "wof:population":148
},
  "geometry": {"coordinates":[14.83333,46.08333],"type":"Point"}
}