{
  "type": "Feature",
  "properties": {
    "gn:admin1_code":"38",
    "gn:asciiname":"Topolc",
    "gn:country_code":"SI",
    "gn:dem":411,
    "gn:feature_class":"P",
    "gn:feature_code":"PPL",
    "gn:name":"Topolc",
    "gn:population":339,
    "gn:timezone":"Europe/Ljubljana",
    "iso:country":"SI",
    "name:bos_x_preferred":[
        "Topolc"
    ],
    "name:ceb_x_preferred":[
        "Topolc"
    ],
    "name:hrv_x_preferred":[
        "Topolc"
    ],
    "name:nld_x_preferred":[
        "Topolc"
    ],
    "name:pol_x_preferred":[
        "Topolc"
    ],
    "name:ron_x_preferred":[
        "Topolc"
    ],
    "name:slv_x_preferred":[
        "Topolc"
    ],
    "name:ukr_x_preferred":[
        "\u0422\u043e\u043f\u043e\u043b\u0446"
    ],
    "name:und_x_variant":[
        "Topolza",
        "Topolec",
        "Topolc"
    ],
    "wof:name":"Topolc",
    "wof:placetype":"locality",
    "wof:population":339
},
  "geometry": {"coordinates":[14.21667,45.58361],"type":"Point"}
}