{
  "type": "Feature",
  "properties": {
    "gn:admin1_code":"89",
    "gn:asciiname":"Slatenik",
    "gn:country_code":"SI",
    "gn:dem":315,
    "gn:feature_class":"P",
    "gn:feature_code":"PPL",
    "gn:name":"Slatenik",
    "gn:population":45,
    "gn:timezone":"Europe/Ljubljana",
    "iso:country":"SI",
    "wof:name":"Slatenik",
    "wof:placetype":"locality",
    "wof:population":45
},
  "geometry": {"coordinates":[15.72694,46.61889],"type":"Point"}
}