{
  "type": "Feature",
  "properties": {
    "gn:admin1_code":"89",
    "gn:asciiname":"Slatenik",
    "gn:country_code":"SI",
    "gn:dem":315,
    "gn:feature_class":"P",
    "gn:feature_code":"PPL",
    "gn:name":"Slatenik",
    "gn:population":45,
    "gn:timezone":"Europe/Ljubljana",
    "iso:country":"SI",
    "name:bos_x_preferred":[
        "Slatenik"
    ],
    "name:nld_x_preferred":[
        "Slatenik"
    ],
    "name:pol_x_preferred":[
        "Slatenik"
    ],
    "name:ron_x_preferred":[
        "Slatenik"
    ],
    "name:slv_x_preferred":[
        "Slatenik"
    ],
    "name:ukr_x_preferred":[
        "\u0421\u043b\u0430\u0442\u0435\u043d\u0438\u043a"
    ],
    "wof:name":"Slatenik",
    "wof:placetype":"locality",
    "wof:population":45
},
  "geometry": {"coordinates":[15.72694,46.61889],"type":"Point"}
}