{
  "type": "Feature",
  "properties": {
    "gn:admin1_code":"B7",
    "gn:asciiname":"Brje pri Koprivi",
    "gn:country_code":"SI",
    "gn:dem":277,
    "gn:feature_class":"P",
    "gn:feature_code":"PPL",
    "gn:name":"Brje pri Koprivi",
    "gn:population":34,
    "gn:timezone":"Europe/Ljubljana",
    "iso:country":"SI",
    "name:bos_x_preferred":[
        "Brje pri Koprivi"
    ],
    "name:nld_x_preferred":[
        "Brje pri Koprivi"
    ],
    "name:pol_x_preferred":[
        "Brje pri Koprivi"
    ],
    "name:ron_x_preferred":[
        "Brje pri Koprivi"
    ],
    "name:slv_x_preferred":[
        "Brje pri Koprivi"
    ],
    "name:ukr_x_preferred":[
        "\u0411\u0440\u0454-\u043f\u0440\u0438-\u041a\u043e\u043f\u0440\u0438\u0432\u0456"
    ],
    "name:und_x_variant":[
        "Brje",
        "Berie",
        "Brje pri Koprivi"
    ],
    "wof:name":"Brje pri Koprivi",
    "wof:placetype":"locality",
    "wof:population":34
},
  "geometry": {"coordinates":[13.84194,45.7775],"type":"Point"}
}