{
  "type": "Feature",
  "properties": {
    "gn:admin1_code":"38",
    "gn:asciiname":"Harije",
    "gn:country_code":"SI",
    "gn:dem":508,
    "gn:feature_class":"P",
    "gn:feature_code":"PPL",
    "gn:name":"Harije",
    "gn:population":275,
    "gn:timezone":"Europe/Ljubljana",
    "iso:country":"SI",
    "name:und_x_variant":[
        "Carie",
        "Ilarie",
        "Harije"
    ],
    "wof:name":"Harije",
    "wof:placetype":"locality",
    "wof:population":275
},
  "geometry": {"coordinates":[14.19611,45.55278],"type":"Point"}
}