{
  "type": "Feature",
  "properties": {
    "gn:admin1_code":"38",
    "gn:asciiname":"Harije",
    "gn:country_code":"SI",
    "gn:dem":508,
    "gn:feature_class":"P",
    "gn:feature_code":"PPL",
    "gn:name":"Harije",
    "gn:population":275,
    "gn:timezone":"Europe/Ljubljana",
    "iso:country":"SI",
    "name:bos_x_preferred":[
        "Harije"
    ],
    "name:ceb_x_preferred":[
        "Harije"
    ],
    "name:hrv_x_preferred":[
        "Harije"
    ],
    "name:nld_x_preferred":[
        "Harije"
    ],
    "name:pol_x_preferred":[
        "Harije"
    ],
    "name:ron_x_preferred":[
        "Harije"
    ],
    "name:slv_x_preferred":[
        "Harije"
    ],
    "name:ukr_x_preferred":[
        "\u0425\u0430\u0440\u0456\u0454"
    ],
    "name:und_x_variant":[
        "Carie",
        "Ilarie"
    ],
    "wof:name":"Harije",
    "wof:placetype":"locality",
    "wof:population":275
},
  "geometry": {"coordinates":[14.19611,45.55278],"type":"Point"}
}