{
  "type": "Feature",
  "properties": {
    "gn:admin1_code":"11",
    "gn:asciiname":"Lokrovec",
    "gn:country_code":"SI",
    "gn:dem":276,
    "gn:feature_class":"P",
    "gn:feature_code":"PPL",
    "gn:name":"Lokrovec",
    "gn:population":309,
    "gn:timezone":"Europe/Ljubljana",
    "iso:country":"SI",
    "name:bos_x_preferred":[
        "Lokrovec"
    ],
    "name:bul_x_preferred":[
        "\u041b\u043e\u043a\u0440\u043e\u0432\u0435\u0446"
    ],
    "name:ceb_x_preferred":[
        "Lokrovec"
    ],
    "name:hrv_x_preferred":[
        "Lokrovec"
    ],
    "name:ita_x_preferred":[
        "Lokrovec"
    ],
    "name:nld_x_preferred":[
        "Lokrovec"
    ],
    "name:pol_x_preferred":[
        "Lokrovec"
    ],
    "name:ron_x_preferred":[
        "Lokrovec"
    ],
    "name:slv_x_preferred":[
        "Lokrovec"
    ],
    "name:ukr_x_preferred":[
        "\u041b\u043e\u043a\u0440\u043e\u0432\u0435\u0446\u044c"
    ],
    "wof:name":"Lokrovec",
    "wof:placetype":"locality",
    "wof:population":309
},
  "geometry": {"coordinates":[15.25,46.26667],"type":"Point"}
}