{
  "type": "Feature",
  "properties": {
    "gn:admin1_code":"11",
    "gn:asciiname":"Lokrovec",
    "gn:country_code":"SI",
    "gn:dem":276,
    "gn:feature_class":"P",
    "gn:feature_code":"PPL",
    "gn:name":"Lokrovec",
    "gn:population":309,
    "gn:timezone":"Europe/Ljubljana",
    "iso:country":"SI",
    "wof:name":"Lokrovec",
    "wof:placetype":"locality",
    "wof:population":309
},
  "geometry": {"coordinates":[15.25,46.26667],"type":"Point"}
}