{
  "type": "Feature",
  "properties": {
    "gn:admin1_code":"54",
    "gn:asciiname":"Prusnja Vas",
    "gn:country_code":"SI",
    "gn:dem":510,
    "gn:feature_class":"P",
    "gn:feature_code":"PPL",
    "gn:name":"Pru\u0161nja Vas",
    "gn:population":47,
    "gn:timezone":"Europe/Ljubljana",
    "iso:country":"SI",
    "name:bos_x_preferred":[
        "Pru\u0161nja vas"
    ],
    "name:hrv_x_preferred":[
        "Pru\u0161nja vas"
    ],
    "name:nld_x_preferred":[
        "Pru\u0161nja vas"
    ],
    "name:pol_x_preferred":[
        "Pru\u0161nja vas"
    ],
    "name:ron_x_preferred":[
        "Pru\u0161nja vas"
    ],
    "name:slv_x_historical":[
        "Pru\u0161na Vas"
    ],
    "name:slv_x_preferred":[
        "Pru\u0161na Vas"
    ],
    "name:slv_x_variant":[
        "Pru\u0161nja vas"
    ],
    "name:ukr_x_preferred":[
        "\u041f\u0440\u0443\u0448\u043d\u044f \u0412\u0430\u0441"
    ],
    "name:und_x_variant":[
        "Pru\u0161nja Vas"
    ],
    "wof:name":"Prusnja Vas",
    "wof:placetype":"locality",
    "wof:population":47
},
  "geometry": {"coordinates":[15.48204,45.8345],"type":"Point"}
}