{
  "type": "Feature",
  "properties": {
    "gn:admin1_code":"D2",
    "gn:asciiname":"Kumar",
    "gn:country_code":"SI",
    "gn:dem":706,
    "gn:feature_class":"P",
    "gn:feature_code":"PPL",
    "gn:name":"Kumar",
    "gn:population":0,
    "gn:timezone":"Europe/Ljubljana",
    "iso:country":"SI",
    "name:ces_x_preferred":[
        "Kum\u00e1r"
    ],
    "name:deu_x_preferred":[
        "Kumar"
    ],
    "name:fas_x_preferred":[
        "\u06a9\u0648\u0645\u0627\u0631"
    ],
    "name:hin_x_preferred":[
        "\u0915\u0941\u092e\u093e\u0930"
    ],
    "name:new_x_preferred":[
        "\u0915\u0941\u092e\u093e\u0930"
    ],
    "name:slv_x_preferred":[
        "Kumar"
    ],
    "name:ukr_x_preferred":[
        "\u041a\u0443\u043c\u0430\u0440"
    ],
    "wof:name":"Kumar",
    "wof:placetype":"locality"
},
  "geometry": {"coordinates":[13.84389,46.06444000000001],"type":"Point"}
}