{
  "type": "Feature",
  "properties": {
    "gn:admin1_code":"D2",
    "gn:asciiname":"Kumar",
    "gn:country_code":"SI",
    "gn:dem":706,
    "gn:feature_class":"P",
    "gn:feature_code":"PPL",
    "gn:name":"Kumar",
    "gn:population":0,
    "gn:timezone":"Europe/Ljubljana",
    "iso:country":"SI",
    "wof:name":"Kumar",
    "wof:placetype":"locality"
},
  "geometry": {"coordinates":[13.84389,46.06444000000001],"type":"Point"}
}