{
  "type": "Feature",
  "properties": {
    "gn:admin1_code":"I6",
    "gn:asciiname":"Zerovinci",
    "gn:country_code":"SI",
    "gn:dem":255,
    "gn:feature_class":"P",
    "gn:feature_code":"PPL",
    "gn:name":"\u017derovinci",
    "gn:population":263,
    "gn:timezone":"Europe/Ljubljana",
    "iso:country":"SI",
    "name:und_x_variant":[
        "\u017derovinci"
    ],
    "wof:name":"Zerovinci",
    "wof:placetype":"locality",
    "wof:population":263
},
  "geometry": {"coordinates":[16.15387999999999,46.48546],"type":"Point"}
}