{
  "type": "Feature",
  "properties": {
    "gn:admin1_code":"I6",
    "gn:asciiname":"Zerovinci",
    "gn:country_code":"SI",
    "gn:dem":255,
    "gn:feature_class":"P",
    "gn:feature_code":"PPL",
    "gn:name":"\u017derovinci",
    "gn:population":263,
    "gn:timezone":"Europe/Ljubljana",
    "iso:country":"SI",
    "name:bos_x_preferred":[
        "\u017derovinci"
    ],
    "name:bul_x_preferred":[
        "\u0416\u0435\u0440\u043e\u0432\u0438\u043d\u0446\u0438"
    ],
    "name:ceb_x_preferred":[
        "\u017derovinci"
    ],
    "name:nld_x_preferred":[
        "\u017derovinci"
    ],
    "name:pol_x_preferred":[
        "\u017derovinci"
    ],
    "name:ron_x_preferred":[
        "\u017derovinci"
    ],
    "name:slv_x_preferred":[
        "\u017derovinci"
    ],
    "name:ukr_x_preferred":[
        "\u0416\u0435\u0440\u043e\u0432\u0438\u043d\u0446\u0456"
    ],
    "wof:name":"Zerovinci",
    "wof:placetype":"locality",
    "wof:population":263
},
  "geometry": {"coordinates":[16.15387999999999,46.48546],"type":"Point"}
}