{
  "type": "Feature",
  "properties": {
    "gn:admin1_code":"P6",
    "gn:asciiname":"Sv. Trojica v Slov. Goricah",
    "gn:country_code":"SI",
    "gn:dem":272,
    "gn:feature_class":"P",
    "gn:feature_code":"PPLA",
    "gn:name":"Sv. Trojica v Slov. Goricah",
    "gn:population":730,
    "gn:timezone":"Europe/Ljubljana",
    "iso:country":"SI",
    "name:ceb_x_preferred":[
        "Sveta Trojica v Slovenskih Goricah"
    ],
    "name:ces_x_preferred":[
        "Ob\u010dina Sveta Trojica v Slovenskih goricah"
    ],
    "name:deu_x_preferred":[
        "Sveta Trojica v Slovenskih goricah"
    ],
    "name:epo_x_preferred":[
        "Ob\u010dina Sveta Trojica v Slovenskih goricah"
    ],
    "name:fra_x_preferred":[
        "Sveta Trojica v Slovenskih goricah"
    ],
    "name:hrv_x_preferred":[
        "Op\u0107ina Sveta Trojica v Slovenskih goricah"
    ],
    "name:hun_x_preferred":[
        "Sveta Trojica v Slovenskih goricah"
    ],
    "name:ind_x_preferred":[
        "Munisipalitas Sveta Trojica v Slovenskih Goricah"
    ],
    "name:ita_x_preferred":[
        "Sveta Trojica v Slovenskih goricah"
    ],
    "name:nld_x_preferred":[
        "Sveta Trojica v Slovenskih goricah"
    ],
    "name:pol_x_preferred":[
        "Gmina Sveta Trojica v Slovenskih goricah"
    ],
    "name:por_x_preferred":[
        "Sveta Trojica v Slovenskih goricah"
    ],
    "name:ron_x_preferred":[
        "Comuna Sveta Trojica v Slovenskih goricah"
    ],
    "name:slv_x_preferred":[
        "Sveta Trojica v Slovenskih goricah"
    ],
    "name:slv_x_variant":[
        "Ob\u010dina Sveta Trojica v Slovenskih goricah"
    ],
    "name:ukr_x_preferred":[
        "\u0421\u0432\u0435\u0442\u0430 \u0422\u0440\u043e\u0457\u0446\u0430-\u0432-\u0421\u043b\u043e\u0432\u0435\u043d\u0441\u044c\u043a\u0438\u0445 \u0413\u043e\u0440\u0438\u0446\u044f\u0445"
    ],
    "name:und_x_variant":[
        "Sveta Trojica",
        "Gradi\u0161\u010de",
        "Gradi\u0161\u010de v Slovenskih Goricah",
        "Sveta Trojica v Slovenskih Goricah"
    ],
    "name:vie_x_preferred":[
        "Sveta Trojica v Slovenskih goricah"
    ],
    "wof:name":"Sv. Trojica v Slov. Goricah",
    "wof:placetype":"locality",
    "wof:population":730
},
  "geometry": {"coordinates":[15.87694,46.57667],"type":"Point"}
}