{
  "type": "Feature",
  "properties": {
    "gn:admin1_code":"P6",
    "gn:asciiname":"Sv. Trojica v Slov. Goricah",
    "gn:country_code":"SI",
    "gn:dem":272,
    "gn:feature_class":"P",
    "gn:feature_code":"PPLA",
    "gn:name":"Sv. Trojica v Slov. Goricah",
    "gn:population":730,
    "gn:timezone":"Europe/Ljubljana",
    "iso:country":"SI",
    "name:slv_x_preferred":[
        "Sveta Trojica v Slovenskih goricah"
    ],
    "name:und_x_variant":[
        "Sveta Trojica",
        "Gradi\u0161\u010de",
        "Gradi\u0161\u010de v Slovenskih Goricah",
        "Sveta Trojica v Slovenskih Goricah"
    ],
    "wof:name":"Sv. Trojica v Slov. Goricah",
    "wof:placetype":"locality",
    "wof:population":730
},
  "geometry": {"coordinates":[15.87694,46.57667],"type":"Point"}
}