{
  "type": "Feature",
  "properties": {
    "gn:admin1_code":"D2",
    "gn:asciiname":"Zakraj",
    "gn:country_code":"SI",
    "gn:dem":650,
    "gn:feature_class":"P",
    "gn:feature_code":"PPL",
    "gn:name":"Zakraj",
    "gn:population":34,
    "gn:timezone":"Europe/Ljubljana",
    "iso:country":"SI",
    "name:bos_x_preferred":[
        "Zakraj"
    ],
    "name:bul_x_preferred":[
        "\u0417\u0430\u043a\u0440\u0430\u0439"
    ],
    "name:nld_x_preferred":[
        "Zakraj"
    ],
    "name:pol_x_preferred":[
        "Zakraj"
    ],
    "name:ron_x_preferred":[
        "Zakraj"
    ],
    "name:slv_x_preferred":[
        "Zakraj"
    ],
    "name:ukr_x_preferred":[
        "\u0417\u0430\u043a\u0440\u0430\u0439"
    ],
    "wof:name":"Zakraj",
    "wof:placetype":"locality",
    "wof:population":34
},
  "geometry": {"coordinates":[13.87623,46.10747],"type":"Point"}
}