{
  "type": "Feature",
  "properties": {
    "gn:gn_country":"SI",
    "gn:gn_fcode":"PPL",
    "gn:gn_pop":0,
    "gn:population":123,
    "iso:country":"SI",
    "name:dut_x_preferred":[
        "Veliki Dol"
    ],
    "name:eng_x_preferred":[
        "Veliki Dol"
    ],
    "name:ita_x_preferred":[
        "Dol Grande"
    ],
    "name:per_x_preferred":[
        "\u0648\u0644\u06cc\u06a9\u06cc \u062f\u0648\u0644\u060c \u0633\u0698\u0627\u0646\u0627"
    ],
    "name:rum_x_preferred":[
        "Veliki Dol"
    ],
    "name:slv_x_preferred":[
        "Veliki Dol"
    ],
    "name:ukr_x_preferred":[
        "\u0412\u0435\u043b\u0456\u043a\u0456 \u0414\u043e\u043b"
    ],
    "name:unk_x_variant":[
        "Dol Grande"
    ],
    "qs_pg:aaroncc":"SI",
    "qs_pg:gn_country":"SI",
    "qs_pg:gn_fcode":"PPL",
    "qs_pg:gn_pop":0,
    "qs_pg:name":"Veliki Dol",
    "qs_pg:name_adm0":"Slovenija",
    "qs_pg:name_adm1":"Sezana",
    "qs_pg:photos":7,
    "qs_pg:photos_1k":1,
    "qs_pg:photos_9k":1,
    "qs_pg:photos_9r":1,
    "qs_pg:photos_all":7,
    "qs_pg:photos_sr":1,
    "qs_pg:pop_sr":0,
    "qs_pg:qs_pg_placetype":"locality",
    "qs_pg:qs_pg_placetype_gp":"Town",
    "qs_pg:woe_adm0":23424945,
    "woe:adm0_id":23424945,
    "woe:name_adm0":"Slovenija",
    "woe:name_adm1":"Sezana",
    "woe:placetype":"Town",
    "wof:name":"Veliki Dol",
    "wof:placetype":"locality",
    "wof:population":123
},
  "geometry": {"coordinates":[13.75194,45.77028],"type":"Point"}
}