{
  "type": "Feature",
  "properties": {
    "gn:admin1_code":"39",
    "gn:asciiname":"Mali Korinj",
    "gn:country_code":"SI",
    "gn:dem":642,
    "gn:feature_class":"P",
    "gn:feature_code":"PPL",
    "gn:name":"Mali Korinj",
    "gn:population":51,
    "gn:timezone":"Europe/Ljubljana",
    "iso:country":"SI",
    "wof:name":"Mali Korinj",
    "wof:placetype":"locality",
    "wof:population":51
},
  "geometry": {"coordinates":[14.79472,45.85111],"type":"Point"}
}