{
  "type": "Feature",
  "properties": {
    "gn:admin1_code":"39",
    "gn:asciiname":"Mali Korinj",
    "gn:country_code":"SI",
    "gn:dem":642,
    "gn:feature_class":"P",
    "gn:feature_code":"PPL",
    "gn:name":"Mali Korinj",
    "gn:population":51,
    "gn:timezone":"Europe/Ljubljana",
    "iso:country":"SI",
    "name:bos_x_preferred":[
        "Mali Korinj"
    ],
    "name:nld_x_preferred":[
        "Mali Korinj"
    ],
    "name:pol_x_preferred":[
        "Mali Korinj"
    ],
    "name:ron_x_preferred":[
        "Mali Korinj"
    ],
    "name:slv_x_preferred":[
        "Mali Korinj"
    ],
    "name:ukr_x_preferred":[
        "\u041c\u0430\u043b\u0438\u0439 \u041a\u043e\u0440\u0438\u043d\u044c"
    ],
    "wof:name":"Mali Korinj",
    "wof:placetype":"locality",
    "wof:population":51
},
  "geometry": {"coordinates":[14.79472,45.85111],"type":"Point"}
}