{
  "type": "Feature",
  "properties": {
    "gn:admin1_code":"B1",
    "gn:asciiname":"Vrcice",
    "gn:country_code":"SI",
    "gn:dem":494,
    "gn:feature_class":"P",
    "gn:feature_code":"PPL",
    "gn:name":"Vr\u010dice",
    "gn:population":45,
    "gn:timezone":"Europe/Ljubljana",
    "iso:country":"SI",
    "name:und_x_variant":[
        "Vr\u010dice"
    ],
    "wof:name":"Vrcice",
    "wof:placetype":"locality",
    "wof:population":45
},
  "geometry": {"coordinates":[15.15,45.65],"type":"Point"}
}