{
  "type": "Feature",
  "properties": {
    "gn:admin1_code":"B1",
    "gn:asciiname":"Vrcice",
    "gn:country_code":"SI",
    "gn:dem":494,
    "gn:feature_class":"P",
    "gn:feature_code":"PPL",
    "gn:name":"Vr\u010dice",
    "gn:population":45,
    "gn:timezone":"Europe/Ljubljana",
    "iso:country":"SI",
    "name:bos_x_preferred":[
        "Vr\u010dice"
    ],
    "name:hrv_x_preferred":[
        "Vr\u010dice"
    ],
    "name:nld_x_preferred":[
        "Vr\u010dice"
    ],
    "name:pol_x_preferred":[
        "Vr\u010dice"
    ],
    "name:ron_x_preferred":[
        "Vr\u010dice"
    ],
    "name:slv_x_preferred":[
        "Vr\u010dice"
    ],
    "name:ukr_x_preferred":[
        "\u0412\u0440\u0447\u0438\u0446\u0435"
    ],
    "wof:name":"Vrcice",
    "wof:placetype":"locality",
    "wof:population":45
},
  "geometry": {"coordinates":[15.15,45.65],"type":"Point"}
}