{
  "type": "Feature",
  "properties": {
    "gn:admin1_code":"49",
    "gn:asciiname":"Kobjeglava",
    "gn:country_code":"SI",
    "gn:dem":312,
    "gn:feature_class":"P",
    "gn:feature_code":"PPL",
    "gn:name":"Kobjeglava",
    "gn:population":182,
    "gn:timezone":"Europe/Ljubljana",
    "iso:country":"SI",
    "name:bos_x_preferred":[
        "Kobjeglava"
    ],
    "name:ceb_x_preferred":[
        "Kobjeglava"
    ],
    "name:ita_x_preferred":[
        "Cobbia"
    ],
    "name:nld_x_preferred":[
        "Kobjeglava"
    ],
    "name:pol_x_preferred":[
        "Kobjeglava"
    ],
    "name:ron_x_preferred":[
        "Kobjeglava"
    ],
    "name:slv_x_preferred":[
        "Kobjeglava"
    ],
    "name:ukr_x_preferred":[
        "\u041a\u043e\u0431\u0454\u0433\u043b\u0430\u0432\u0430"
    ],
    "name:und_x_variant":[
        "C\u00f2bbia",
        "Kobjo",
        "Glava",
        "Kobja Glava",
        "Kobjeglava"
    ],
    "wof:name":"Kobjeglava",
    "wof:placetype":"locality",
    "wof:population":182
},
  "geometry": {"coordinates":[13.80583,45.8175],"type":"Point"}
}