{
  "type": "Feature",
  "properties": {
    "gn:admin1_code":"49",
    "gn:asciiname":"Kobjeglava",
    "gn:country_code":"SI",
    "gn:dem":312,
    "gn:feature_class":"P",
    "gn:feature_code":"PPL",
    "gn:name":"Kobjeglava",
    "gn:population":182,
    "gn:timezone":"Europe/Ljubljana",
    "iso:country":"SI",
    "name:und_x_variant":[
        "C\u00f2bbia",
        "Kobjo",
        "Glava",
        "Kobja Glava",
        "Kobjeglava"
    ],
    "wof:name":"Kobjeglava",
    "wof:placetype":"locality",
    "wof:population":182
},
  "geometry": {"coordinates":[13.80583,45.8175],"type":"Point"}
}