{
  "type": "Feature",
  "properties": {
    "gn:admin1_code":"F6",
    "gn:asciiname":"Hribarjevo",
    "gn:country_code":"SI",
    "gn:dem":726,
    "gn:feature_class":"P",
    "gn:feature_code":"PPL",
    "gn:name":"Hribarjevo",
    "gn:population":23,
    "gn:timezone":"Europe/Ljubljana",
    "iso:country":"SI",
    "wof:name":"Hribarjevo",
    "wof:placetype":"locality",
    "wof:population":23
},
  "geometry": {"coordinates":[14.45467,45.81146],"type":"Point"}
}