{
  "type": "Feature",
  "properties": {
    "gn:admin1_code":"22",
    "gn:asciiname":"Vinje",
    "gn:country_code":"SI",
    "gn:dem":410,
    "gn:feature_class":"P",
    "gn:feature_code":"PPL",
    "gn:name":"Vinje",
    "gn:population":477,
    "gn:timezone":"Europe/Ljubljana",
    "iso:country":"SI",
    "name:bos_x_preferred":[
        "Vinje"
    ],
    "name:ceb_x_preferred":[
        "Vinje"
    ],
    "name:nld_x_preferred":[
        "Vinje"
    ],
    "name:pol_x_preferred":[
        "Vinje"
    ],
    "name:ron_x_preferred":[
        "Vinje"
    ],
    "name:slv_x_preferred":[
        "Vinje"
    ],
    "name:ukr_x_preferred":[
        "\u0412\u0438\u043d\u0454"
    ],
    "wof:name":"Vinje",
    "wof:placetype":"locality",
    "wof:population":477
},
  "geometry": {"coordinates":[14.66667,46.11667],"type":"Point"}
}