{
  "type": "Feature",
  "properties": {
    "gn:admin1_code":"H6",
    "gn:asciiname":"Praproce v Tuhinju",
    "gn:country_code":"SI",
    "gn:dem":752,
    "gn:feature_class":"P",
    "gn:feature_code":"PPL",
    "gn:name":"Prapro\u010de v Tuhinju",
    "gn:population":24,
    "gn:timezone":"Europe/Ljubljana",
    "iso:country":"SI",
    "name:und_x_variant":[
        "Prapro\u010de v Tuhinju"
    ],
    "wof:name":"Praproce v Tuhinju",
    "wof:placetype":"locality",
    "wof:population":24
},
  "geometry": {"coordinates":[14.71741,46.23833],"type":"Point"}
}