{
  "type": "Feature",
  "properties": {
    "gn:admin1_code":"H6",
    "gn:asciiname":"Praproce v Tuhinju",
    "gn:country_code":"SI",
    "gn:dem":752,
    "gn:feature_class":"P",
    "gn:feature_code":"PPL",
    "gn:name":"Prapro\u010de v Tuhinju",
    "gn:population":24,
    "gn:timezone":"Europe/Ljubljana",
    "iso:country":"SI",
    "name:bos_x_preferred":[
        "Prapro\u010de v Tuhinju"
    ],
    "name:pol_x_preferred":[
        "Prapro\u010de v Tuhinju"
    ],
    "name:ron_x_preferred":[
        "Prapro\u010de v Tuhinju"
    ],
    "name:slv_x_preferred":[
        "Prapro\u010de v Tuhinju"
    ],
    "name:ukr_x_preferred":[
        "\u041f\u0440\u0430\u043f\u0440\u043e\u0447\u0435-\u0432-\u0422\u0443\u0445\u0438\u043d\u044e"
    ],
    "wof:name":"Praproce v Tuhinju",
    "wof:placetype":"locality",
    "wof:population":24
},
  "geometry": {"coordinates":[14.71741,46.23833],"type":"Point"}
}