{
  "type": "Feature",
  "properties": {
    "gn:admin1_code":"62",
    "gn:asciiname":"Melise",
    "gn:country_code":"SI",
    "gn:dem":421,
    "gn:feature_class":"P",
    "gn:feature_code":"PPL",
    "gn:name":"Meli\u0161e",
    "gn:population":49,
    "gn:timezone":"Europe/Ljubljana",
    "iso:country":"SI",
    "name:bos_x_preferred":[
        "Meli\u0161e"
    ],
    "name:nld_x_preferred":[
        "Meli\u0161e"
    ],
    "name:pol_x_preferred":[
        "Meli\u0161e"
    ],
    "name:ron_x_preferred":[
        "Meli\u0161e"
    ],
    "name:slv_x_preferred":[
        "Meli\u0161e"
    ],
    "name:ukr_x_preferred":[
        "\u041c\u0435\u043b\u0438\u0448\u0435"
    ],
    "wof:name":"Melise",
    "wof:placetype":"locality",
    "wof:population":49
},
  "geometry": {"coordinates":[14.86297,46.31731],"type":"Point"}
}