{
  "type": "Feature",
  "properties": {
    "gn:admin1_code":"62",
    "gn:asciiname":"Melise",
    "gn:country_code":"SI",
    "gn:dem":421,
    "gn:feature_class":"P",
    "gn:feature_code":"PPL",
    "gn:name":"Meli\u0161e",
    "gn:population":49,
    "gn:timezone":"Europe/Ljubljana",
    "iso:country":"SI",
    "name:und_x_variant":[
        "Meli\u0161e"
    ],
    "wof:name":"Melise",
    "wof:placetype":"locality",
    "wof:population":49
},
  "geometry": {"coordinates":[14.86297,46.31731],"type":"Point"}
}