{
  "type": "Feature",
  "properties": {
    "gn:admin1_code":"A1",
    "gn:asciiname":"Kobilscak",
    "gn:country_code":"SI",
    "gn:dem":250,
    "gn:feature_class":"P",
    "gn:feature_code":"PPL",
    "gn:name":"Kobil\u0161\u010dak",
    "gn:population":51,
    "gn:timezone":"Europe/Ljubljana",
    "iso:country":"SI",
    "name:bos_x_preferred":[
        "Kobil\u0161\u010dak"
    ],
    "name:nld_x_preferred":[
        "Kobil\u0161\u010dak"
    ],
    "name:pol_x_preferred":[
        "Kobil\u0161\u010dak"
    ],
    "name:ron_x_preferred":[
        "Kobil\u0161\u010dak"
    ],
    "name:slv_x_preferred":[
        "Kobil\u0161\u010dak"
    ],
    "name:ukr_x_preferred":[
        "\u041a\u043e\u0431\u0438\u043b\u0449\u0430\u043a"
    ],
    "name:und_x_variant":[
        "Kobil\u0161\u010dak"
    ],
    "wof:name":"Kobilscak",
    "wof:placetype":"locality",
    "wof:population":51
},
  "geometry": {"coordinates":[16.02722,46.63111],"type":"Point"}
}