{
  "type": "Feature",
  "properties": {
    "gn:admin1_code":"20",
    "gn:asciiname":"Podpec",
    "gn:country_code":"SI",
    "gn:dem":497,
    "gn:feature_class":"P",
    "gn:feature_code":"PPL",
    "gn:name":"Podpe\u010d",
    "gn:population":142,
    "gn:timezone":"Europe/Ljubljana",
    "iso:country":"SI",
    "name:bos_x_preferred":[
        "Podpe\u010d"
    ],
    "name:bul_x_preferred":[
        "\u041f\u043e\u0434\u043f\u0435\u0447"
    ],
    "name:ceb_x_preferred":[
        "Podpe\u010d"
    ],
    "name:nld_x_preferred":[
        "Podpe\u010d"
    ],
    "name:pol_x_preferred":[
        "Podpe\u010d"
    ],
    "name:ron_x_preferred":[
        "Podpe\u010d"
    ],
    "name:slv_x_preferred":[
        "Podpe\u010d"
    ],
    "name:ukr_x_preferred":[
        "\u041f\u043e\u0434\u043f\u0435\u0447"
    ],
    "wof:name":"Podpec",
    "wof:placetype":"locality",
    "wof:population":142
},
  "geometry": {"coordinates":[14.685,45.83917],"type":"Point"}
}