{
  "type": "Feature",
  "properties": {
    "gn:admin1_code":"A2",
    "gn:asciiname":"Radelca",
    "gn:country_code":"SI",
    "gn:dem":835,
    "gn:feature_class":"P",
    "gn:feature_code":"PPL",
    "gn:name":"Radelca",
    "gn:population":99,
    "gn:timezone":"Europe/Ljubljana",
    "iso:country":"SI",
    "name:bos_x_preferred":[
        "Radelca"
    ],
    "name:nld_x_preferred":[
        "Radelca"
    ],
    "name:pol_x_preferred":[
        "Radelca"
    ],
    "name:ron_x_preferred":[
        "Radelca"
    ],
    "name:slv_x_preferred":[
        "Radelca"
    ],
    "name:ukr_x_preferred":[
        "\u0420\u0430\u0434\u0435\u043b\u0446\u0430"
    ],
    "wof:name":"Radelca",
    "wof:placetype":"locality",
    "wof:population":99
},
  "geometry": {"coordinates":[15.27841,46.64011],"type":"Point"}
}