{
  "type": "Feature",
  "properties": {
    "gn:admin1_code":"N5",
    "gn:asciiname":"Studence",
    "gn:country_code":"SI",
    "gn:dem":419,
    "gn:feature_class":"P",
    "gn:feature_code":"PPL",
    "gn:name":"Studence",
    "gn:population":600,
    "gn:timezone":"Europe/Ljubljana",
    "iso:country":"SI",
    "name:ceb_x_preferred":[
        "Studence"
    ],
    "name:nld_x_preferred":[
        "Studence"
    ],
    "name:pol_x_preferred":[
        "Studence"
    ],
    "name:ron_x_preferred":[
        "Studence"
    ],
    "name:slv_x_preferred":[
        "Studence"
    ],
    "name:ukr_x_preferred":[
        "\u0421\u0442\u0443\u0434\u0435\u043d\u0446\u0435"
    ],
    "wof:name":"Studence",
    "wof:placetype":"locality",
    "wof:population":600
},
  "geometry": {"coordinates":[15.16275,46.30874],"type":"Point"}
}