{
  "type": "Feature",
  "properties": {
    "gn:admin1_code":"N5",
    "gn:asciiname":"Studence",
    "gn:country_code":"SI",
    "gn:dem":419,
    "gn:feature_class":"P",
    "gn:feature_code":"PPL",
    "gn:name":"Studence",
    "gn:population":600,
    "gn:timezone":"Europe/Ljubljana",
    "iso:country":"SI",
    "wof:name":"Studence",
    "wof:placetype":"locality",
    "wof:population":600
},
  "geometry": {"coordinates":[15.16275,46.30874],"type":"Point"}
}