{
  "type": "Feature",
  "properties": {
    "gn:admin1_code":"44",
    "gn:asciiname":"Breg",
    "gn:country_code":"SI",
    "gn:dem":630,
    "gn:feature_class":"P",
    "gn:feature_code":"PPLF",
    "gn:name":"Breg",
    "gn:population":0,
    "gn:timezone":"Europe/Ljubljana",
    "iso:country":"SI",
    "name:bel_x_preferred":[
        "\u0411\u0440\u044d\u0433"
    ],
    "name:ceb_x_preferred":[
        "Breg"
    ],
    "name:deu_x_preferred":[
        "Breg"
    ],
    "name:fra_x_preferred":[
        "Breg"
    ],
    "name:hrv_x_preferred":[
        "Breg"
    ],
    "name:hun_x_preferred":[
        "Breg"
    ],
    "name:ita_x_preferred":[
        "Breg"
    ],
    "name:nld_x_preferred":[
        "Breg"
    ],
    "name:pol_x_preferred":[
        "Breg"
    ],
    "name:ron_x_preferred":[
        "Breg"
    ],
    "name:slv_x_preferred":[
        "Breg"
    ],
    "name:swe_x_preferred":[
        "Breg"
    ],
    "wof:name":"Breg",
    "wof:placetype":"locality"
},
  "geometry": {"coordinates":[13.72696,46.09076],"type":"Point"}
}