{
  "type": "Feature",
  "properties": {
    "gn:admin1_code":"I6",
    "gn:asciiname":"Hermanci",
    "gn:country_code":"SI",
    "gn:dem":254,
    "gn:feature_class":"P",
    "gn:feature_code":"PPL",
    "gn:name":"Hermanci",
    "gn:population":133,
    "gn:timezone":"Europe/Ljubljana",
    "iso:country":"SI",
    "wof:name":"Hermanci",
    "wof:placetype":"locality",
    "wof:population":133
},
  "geometry": {"coordinates":[16.22698,46.48065],"type":"Point"}
}