{
  "type": "Feature",
  "properties": {
    "gn:admin1_code":"H9",
    "gn:asciiname":"Gotenc",
    "gn:country_code":"SI",
    "gn:dem":411,
    "gn:feature_class":"P",
    "gn:feature_code":"PPL",
    "gn:name":"Gotenc",
    "gn:population":10,
    "gn:timezone":"Europe/Ljubljana",
    "iso:country":"SI",
    "wof:name":"Gotenc",
    "wof:placetype":"locality",
    "wof:population":10
},
  "geometry": {"coordinates":[14.88541,45.49100000000001],"type":"Point"}
}