{
  "type": "Feature",
  "properties": {
    "gn:admin1_code":"H9",
    "gn:asciiname":"Gotenc",
    "gn:country_code":"SI",
    "gn:dem":411,
    "gn:feature_class":"P",
    "gn:feature_code":"PPL",
    "gn:name":"Gotenc",
    "gn:population":10,
    "gn:timezone":"Europe/Ljubljana",
    "iso:country":"SI",
    "name:bos_x_preferred":[
        "Gotenc"
    ],
    "name:hrv_x_preferred":[
        "Gotenc"
    ],
    "name:nld_x_preferred":[
        "Gotenc"
    ],
    "name:pol_x_preferred":[
        "Gotenc"
    ],
    "name:ron_x_preferred":[
        "Gotenc"
    ],
    "name:sco_x_preferred":[
        "Gotenc"
    ],
    "name:slv_x_preferred":[
        "Gotenc"
    ],
    "name:ukr_x_preferred":[
        "\u0413\u043e\u0442\u0435\u043d\u0446"
    ],
    "wof:name":"Gotenc",
    "wof:placetype":"locality",
    "wof:population":10
},
  "geometry": {"coordinates":[14.88541,45.49100000000001],"type":"Point"}
}