{
  "type": "Feature",
  "properties": {
    "gn:admin1_code":"G7",
    "gn:asciiname":"Mala Loka",
    "gn:country_code":"SI",
    "gn:dem":283,
    "gn:feature_class":"P",
    "gn:feature_code":"PPL",
    "gn:name":"Mala Loka",
    "gn:population":187,
    "gn:timezone":"Europe/Ljubljana",
    "iso:country":"SI",
    "wof:name":"Mala Loka",
    "wof:placetype":"locality",
    "wof:population":187
},
  "geometry": {"coordinates":[14.60819,46.10824],"type":"Point"}
}