{
  "type": "Feature",
  "properties": {
    "gn:admin1_code":"N8",
    "gn:asciiname":"Brezova Reber pri Dvoru",
    "gn:country_code":"SI",
    "gn:dem":393,
    "gn:feature_class":"P",
    "gn:feature_code":"PPL",
    "gn:name":"Brezova Reber pri Dvoru",
    "gn:population":41,
    "gn:timezone":"Europe/Ljubljana",
    "iso:country":"SI",
    "name:bos_x_preferred":[
        "Brezova Reber pri Dvoru"
    ],
    "name:bul_x_preferred":[
        "\u0411\u0440\u0435\u0437\u043e\u0432\u0430 \u0420\u0435\u0431\u0435\u0440 \u043f\u0440\u0438 \u0414\u0432\u043e\u0440\u0443"
    ],
    "name:hrv_x_preferred":[
        "Brezova Reber pri Dvoru"
    ],
    "name:nld_x_preferred":[
        "Brezova Reber pri Dvoru"
    ],
    "name:pol_x_preferred":[
        "Brezova Reber pri Dvoru"
    ],
    "name:ron_x_preferred":[
        "Brezova Reber pri Dvoru"
    ],
    "name:slv_x_preferred":[
        "Brezova Reber pri Dvoru"
    ],
    "name:ukr_x_preferred":[
        "\u0411\u0440\u0435\u0437\u043e\u0432\u0430 \u0420\u0435\u0431\u0435\u0440-\u043f\u0440\u0438-\u0414\u0432\u043e\u0440\u0443"
    ],
    "name:und_x_variant":[
        "Brezova Reber",
        "Brezova Reber pri Dvoru"
    ],
    "wof:name":"Brezova Reber pri Dvoru",
    "wof:placetype":"locality",
    "wof:population":41
},
  "geometry": {"coordinates":[15.05,45.81667],"type":"Point"}
}