{
  "type": "Feature",
  "properties": {
    "gn:admin1_code":"L7",
    "gn:asciiname":"Stopce",
    "gn:country_code":"SI",
    "gn:dem":275,
    "gn:feature_class":"P",
    "gn:feature_code":"PPL",
    "gn:name":"Stop\u010de",
    "gn:population":231,
    "gn:timezone":"Europe/Ljubljana",
    "iso:country":"SI",
    "name:bos_x_preferred":[
        "Stop\u010de"
    ],
    "name:ceb_x_preferred":[
        "Stop\u010de"
    ],
    "name:hrv_x_preferred":[
        "Stop\u010de"
    ],
    "name:nld_x_preferred":[
        "Stop\u010de"
    ],
    "name:pol_x_preferred":[
        "Stop\u010de"
    ],
    "name:ron_x_preferred":[
        "Stop\u010de"
    ],
    "name:slv_x_preferred":[
        "Stop\u010de"
    ],
    "name:ukr_x_preferred":[
        "\u0421\u0442\u043e\u043f\u0447\u0435"
    ],
    "name:und_x_variant":[
        "Stop\u010de"
    ],
    "wof:name":"Stopce",
    "wof:placetype":"locality",
    "wof:population":231
},
  "geometry": {"coordinates":[15.42759,46.21604],"type":"Point"}
}