{
  "type": "Feature",
  "properties": {
    "gn:admin1_code":"08",
    "gn:asciiname":"Mrzlava Vas",
    "gn:country_code":"SI",
    "gn:dem":203,
    "gn:feature_class":"P",
    "gn:feature_code":"PPL",
    "gn:name":"Mrzlava Vas",
    "gn:population":168,
    "gn:timezone":"Europe/Ljubljana",
    "iso:country":"SI",
    "wof:name":"Mrzlava Vas",
    "wof:placetype":"locality",
    "wof:population":168
},
  "geometry": {"coordinates":[15.58068,45.87741],"type":"Point"}
}