{
  "type": "Feature",
  "properties": {
    "gn:admin1_code":"78",
    "gn:asciiname":"Pordasinci",
    "gn:country_code":"SI",
    "gn:dem":228,
    "gn:feature_class":"P",
    "gn:feature_code":"PPL",
    "gn:name":"Porda\u0161inci",
    "gn:population":44,
    "gn:timezone":"Europe/Ljubljana",
    "iso:country":"SI",
    "name:bos_x_preferred":[
        "Porda\u0161inci"
    ],
    "name:epo_x_preferred":[
        "Porda\u0161inci"
    ],
    "name:hrv_x_preferred":[
        "Porda\u0161inci"
    ],
    "name:hun_x_preferred":[
        "Kisfalu"
    ],
    "name:nld_x_preferred":[
        "Porda\u0161inci"
    ],
    "name:pol_x_preferred":[
        "Porda\u0161inci"
    ],
    "name:ron_x_preferred":[
        "Porda\u0161inci"
    ],
    "name:slv_x_preferred":[
        "Porda\u0161inci"
    ],
    "name:ukr_x_preferred":[
        "\u041f\u043e\u0440\u0434\u0430\u0448\u0438\u043d\u0446\u0456"
    ],
    "wof:name":"Pordasinci",
    "wof:placetype":"locality",
    "wof:population":44
},
  "geometry": {"coordinates":[16.33333,46.73333],"type":"Point"}
}