{
  "type": "Feature",
  "properties": {
    "gn:admin1_code":"A8",
    "gn:asciiname":"Zahenberc",
    "gn:country_code":"SI",
    "gn:dem":261,
    "gn:feature_class":"P",
    "gn:feature_code":"PPL",
    "gn:name":"\u017dahenberc",
    "gn:population":269,
    "gn:timezone":"Europe/Ljubljana",
    "iso:country":"SI",
    "name:bos_x_preferred":[
        "\u017dahenberc"
    ],
    "name:ceb_x_preferred":[
        "\u017dahenberc"
    ],
    "name:nld_x_preferred":[
        "\u017dahenberc"
    ],
    "name:pol_x_preferred":[
        "\u017dahenberc"
    ],
    "name:ron_x_preferred":[
        "\u017dahenberc"
    ],
    "name:slv_x_preferred":[
        "\u017dahenberc"
    ],
    "name:ukr_x_preferred":[
        "\u0416\u0430\u0445\u0435\u043d\u0431\u0435\u0440\u0446"
    ],
    "name:und_x_variant":[
        "\u017dahenberc"
    ],
    "name:urd_x_preferred":[
        "\u0698\u0627\u0647\u0646\u0628\u0631\u06a9"
    ],
    "wof:name":"Zahenberc",
    "wof:placetype":"locality",
    "wof:population":269
},
  "geometry": {"coordinates":[15.72675,46.23853],"type":"Point"}
}