{
  "type": "Feature",
  "properties": {
    "gn:admin1_code":"A8",
    "gn:asciiname":"Zahenberc",
    "gn:country_code":"SI",
    "gn:dem":261,
    "gn:feature_class":"P",
    "gn:feature_code":"PPL",
    "gn:name":"\u017dahenberc",
    "gn:population":269,
    "gn:timezone":"Europe/Ljubljana",
    "iso:country":"SI",
    "name:und_x_variant":[
        "\u017dahenberc"
    ],
    "wof:name":"Zahenberc",
    "wof:placetype":"locality",
    "wof:population":269
},
  "geometry": {"coordinates":[15.72675,46.23853],"type":"Point"}
}