{
  "type": "Feature",
  "properties": {
    "gn:admin1_code":"D7",
    "gn:asciiname":"Prelska",
    "gn:country_code":"SI",
    "gn:dem":389,
    "gn:feature_class":"P",
    "gn:feature_code":"PPL",
    "gn:name":"Prelska",
    "gn:population":260,
    "gn:timezone":"Europe/Ljubljana",
    "iso:country":"SI",
    "name:bos_x_preferred":[
        "Prelska"
    ],
    "name:ceb_x_preferred":[
        "Prelska"
    ],
    "name:hrv_x_preferred":[
        "Prelska"
    ],
    "name:ita_x_preferred":[
        "Prelska"
    ],
    "name:nld_x_preferred":[
        "Prelska"
    ],
    "name:pol_x_preferred":[
        "Prelska"
    ],
    "name:ron_x_preferred":[
        "Prelska"
    ],
    "name:slv_x_preferred":[
        "Prelska"
    ],
    "name:ukr_x_preferred":[
        "\u041f\u0440\u0435\u043b\u0441\u044c\u043a\u0430"
    ],
    "wof:name":"Prelska",
    "wof:placetype":"locality",
    "wof:population":260
},
  "geometry": {"coordinates":[15.18577,46.33593],"type":"Point"}
}