{
  "type": "Feature",
  "properties": {
    "gn:admin1_code":"D7",
    "gn:asciiname":"Prelska",
    "gn:country_code":"SI",
    "gn:dem":389,
    "gn:feature_class":"P",
    "gn:feature_code":"PPL",
    "gn:name":"Prelska",
    "gn:population":260,
    "gn:timezone":"Europe/Ljubljana",
    "iso:country":"SI",
    "wof:name":"Prelska",
    "wof:placetype":"locality",
    "wof:population":260
},
  "geometry": {"coordinates":[15.18577,46.33593],"type":"Point"}
}