{
  "type": "Feature",
  "properties": {
    "gn:admin1_code":"C1",
    "gn:asciiname":"Lavrica",
    "gn:country_code":"SI",
    "gn:dem":293,
    "gn:feature_class":"P",
    "gn:feature_code":"PPL",
    "gn:name":"Lavrica",
    "gn:population":2438,
    "gn:timezone":"Europe/Ljubljana",
    "iso:country":"SI",
    "name:bos_x_preferred":[
        "Lavrica"
    ],
    "name:ceb_x_preferred":[
        "Lavrica"
    ],
    "name:nld_x_preferred":[
        "Lavrica"
    ],
    "name:pol_x_preferred":[
        "Lavrica"
    ],
    "name:ron_x_preferred":[
        "Lavrica"
    ],
    "name:slv_x_preferred":[
        "Lavrica"
    ],
    "name:ukr_x_preferred":[
        "\u041b\u0430\u0432\u0440\u0438\u0446\u044f"
    ],
    "wof:name":"Lavrica",
    "wof:placetype":"locality",
    "wof:population":2438
},
  "geometry": {"coordinates":[14.5573,46.00002],"type":"Point"}
}