{
  "type": "Feature",
  "properties": {
    "gn:admin1_code":"B9",
    "gn:asciiname":"Suha",
    "gn:country_code":"SI",
    "gn:dem":343,
    "gn:feature_class":"P",
    "gn:feature_code":"PPL",
    "gn:name":"Suha",
    "gn:population":144,
    "gn:timezone":"Europe/Ljubljana",
    "iso:country":"SI",
    "wof:name":"Suha",
    "wof:placetype":"locality",
    "wof:population":144
},
  "geometry": {"coordinates":[14.32691,46.1649],"type":"Point"}
}