{
  "type": "Feature",
  "properties": {
    "gn:admin1_code":"J9",
    "gn:asciiname":"Parecag",
    "gn:country_code":"SI",
    "gn:dem":18,
    "gn:feature_class":"P",
    "gn:feature_code":"PPL",
    "gn:name":"Parecag",
    "gn:population":986,
    "gn:timezone":"Europe/Ljubljana",
    "iso:country":"SI",
    "name:bos_x_preferred":[
        "Parecag"
    ],
    "name:bul_x_preferred":[
        "\u041f\u0430\u0440\u0435\u0446\u0430\u0433"
    ],
    "name:ceb_x_preferred":[
        "Parecag"
    ],
    "name:ita_x_preferred":[
        "Parezzago"
    ],
    "name:nld_x_preferred":[
        "Parecag"
    ],
    "name:pol_x_preferred":[
        "Parecag"
    ],
    "name:ron_x_preferred":[
        "Parecag"
    ],
    "name:rus_x_preferred":[
        "\u041f\u0430\u0440\u0435\u0446\u0430\u0433"
    ],
    "name:slv_x_preferred":[
        "Parecag"
    ],
    "name:ukr_x_preferred":[
        "\u041f\u0430\u0440\u0435\u0446\u0430\u0433"
    ],
    "wof:name":"Parecag",
    "wof:placetype":"locality",
    "wof:population":986
},
  "geometry": {"coordinates":[13.61305,45.48202],"type":"Point"}
}