{
  "type": "Feature",
  "properties": {
    "gn:admin1_code":"A8",
    "gn:asciiname":"Vicna Vas",
    "gn:country_code":"SI",
    "gn:dem":256,
    "gn:feature_class":"P",
    "gn:feature_code":"PPL",
    "gn:name":"Vi\u0107na Vas",
    "gn:population":0,
    "gn:timezone":"Europe/Ljubljana",
    "iso:country":"SI",
    "wof:name":"Vicna Vas",
    "wof:placetype":"locality"
},
  "geometry": {"coordinates":[15.69917,46.24611],"type":"Point"}
}