{
  "type": "Feature",
  "properties": {
    "gn:admin1_code":"87",
    "gn:asciiname":"Strezetina",
    "gn:country_code":"SI",
    "gn:dem":283,
    "gn:feature_class":"P",
    "gn:feature_code":"PPL",
    "gn:name":"Strezetina",
    "gn:population":69,
    "gn:timezone":"Europe/Ljubljana",
    "iso:country":"SI",
    "wof:name":"Strezetina",
    "wof:placetype":"locality",
    "wof:population":69
},
  "geometry": {"coordinates":[16.14445,46.45101],"type":"Point"}
}