{
  "type": "Feature",
  "properties": {
    "gn:admin1_code":"87",
    "gn:asciiname":"Strezetina",
    "gn:country_code":"SI",
    "gn:dem":283,
    "gn:feature_class":"P",
    "gn:feature_code":"PPL",
    "gn:name":"Strezetina",
    "gn:population":69,
    "gn:timezone":"Europe/Ljubljana",
    "iso:country":"SI",
    "name:bos_x_preferred":[
        "Strezetina"
    ],
    "name:bul_x_preferred":[
        "\u0421\u0442\u0440\u0435\u0437\u0435\u0442\u0438\u043d\u0430"
    ],
    "name:nld_x_preferred":[
        "Strezetina"
    ],
    "name:pol_x_preferred":[
        "Strezetina"
    ],
    "name:ron_x_preferred":[
        "Strezetina"
    ],
    "name:slv_x_preferred":[
        "Strezetina"
    ],
    "name:ukr_x_preferred":[
        "\u0421\u0442\u0440\u0435\u0437\u0435\u0442\u0438\u043d\u0430"
    ],
    "wof:name":"Strezetina",
    "wof:placetype":"locality",
    "wof:population":69
},
  "geometry": {"coordinates":[16.14445,46.45101],"type":"Point"}
}