{
  "type": "Feature",
  "properties": {
    "gn:admin1_code":"87",
    "gn:asciiname":"Ritmerk",
    "gn:country_code":"SI",
    "gn:dem":252,
    "gn:feature_class":"P",
    "gn:feature_code":"PPL",
    "gn:name":"Ritmerk",
    "gn:population":53,
    "gn:timezone":"Europe/Ljubljana",
    "iso:country":"SI",
    "name:bos_x_preferred":[
        "Ritmerk"
    ],
    "name:bul_x_preferred":[
        "\u0420\u0438\u0442\u043c\u0435\u0440\u043a"
    ],
    "name:nld_x_preferred":[
        "Ritmerk"
    ],
    "name:pol_x_preferred":[
        "Ritmerk"
    ],
    "name:ron_x_preferred":[
        "Ritmerk"
    ],
    "name:slv_x_preferred":[
        "Ritmerk"
    ],
    "name:ukr_x_preferred":[
        "\u0420\u0438\u0442\u043c\u0435\u0440\u043a"
    ],
    "wof:name":"Ritmerk",
    "wof:placetype":"locality",
    "wof:population":53
},
  "geometry": {"coordinates":[16.04472,46.45206],"type":"Point"}
}