{
  "type": "Feature",
  "properties": {
    "gn:admin1_code":"87",
    "gn:asciiname":"Ritmerk",
    "gn:country_code":"SI",
    "gn:dem":252,
    "gn:feature_class":"P",
    "gn:feature_code":"PPL",
    "gn:name":"Ritmerk",
    "gn:population":53,
    "gn:timezone":"Europe/Ljubljana",
    "iso:country":"SI",
    "wof:name":"Ritmerk",
    "wof:placetype":"locality",
    "wof:population":53
},
  "geometry": {"coordinates":[16.04472,46.45206],"type":"Point"}
}