{
  "type": "Feature",
  "properties": {
    "gn:admin1_code":"G7",
    "gn:asciiname":"Sentpavel pri Domzalah",
    "gn:country_code":"SI",
    "gn:dem":286,
    "gn:feature_class":"P",
    "gn:feature_code":"PPL",
    "gn:name":"\u0160entpavel pri Dom\u017ealah",
    "gn:population":87,
    "gn:timezone":"Europe/Ljubljana",
    "iso:country":"SI",
    "name:bos_x_preferred":[
        "\u0160entpavel pri Dom\u017ealah"
    ],
    "name:nld_x_preferred":[
        "\u0160entpavel pri Dom\u017ealah"
    ],
    "name:pol_x_preferred":[
        "\u0160entpavel pri Dom\u017ealah"
    ],
    "name:ron_x_preferred":[
        "\u0160entpavel pri Dom\u017ealah"
    ],
    "name:slv_x_preferred":[
        "\u0160entpavel pri Dom\u017ealah"
    ],
    "name:ukr_x_preferred":[
        "\u0428\u0435\u043d\u0442\u043f\u0430\u0432\u0435\u043b-\u043f\u0440\u0438-\u0414\u043e\u043c\u0436\u0430\u043b\u0430\u0445"
    ],
    "name:und_x_variant":[
        "\u0160entpavel pri Dom\u017ealah"
    ],
    "wof:name":"Sentpavel pri Domzalah",
    "wof:placetype":"locality",
    "wof:population":87
},
  "geometry": {"coordinates":[14.6033,46.11501],"type":"Point"}
}