{
  "type": "Feature",
  "properties": {
    "gn:admin1_code":"G7",
    "gn:asciiname":"Sentpavel pri Domzalah",
    "gn:country_code":"SI",
    "gn:dem":286,
    "gn:feature_class":"P",
    "gn:feature_code":"PPL",
    "gn:name":"\u0160entpavel pri Dom\u017ealah",
    "gn:population":87,
    "gn:timezone":"Europe/Ljubljana",
    "iso:country":"SI",
    "name:und_x_variant":[
        "\u0160entpavel pri Dom\u017ealah"
    ],
    "wof:name":"Sentpavel pri Domzalah",
    "wof:placetype":"locality",
    "wof:population":87
},
  "geometry": {"coordinates":[14.6033,46.11501],"type":"Point"}
}