{
  "type": "Feature",
  "properties": {
    "gn:admin1_code":"20",
    "gn:asciiname":"Podgorica",
    "gn:country_code":"SI",
    "gn:dem":450,
    "gn:feature_class":"P",
    "gn:feature_code":"PPL",
    "gn:name":"Podgorica",
    "gn:population":59,
    "gn:timezone":"Europe/Ljubljana",
    "iso:country":"SI",
    "wof:name":"Podgorica",
    "wof:placetype":"locality",
    "wof:population":59
},
  "geometry": {"coordinates":[14.70326,45.84467],"type":"Point"}
}