{
  "type": "Feature",
  "properties": {
    "gn:admin1_code":"20",
    "gn:asciiname":"Podgorica",
    "gn:country_code":"SI",
    "gn:dem":450,
    "gn:feature_class":"P",
    "gn:feature_code":"PPL",
    "gn:name":"Podgorica",
    "gn:population":59,
    "gn:timezone":"Europe/Ljubljana",
    "iso:country":"SI",
    "name:bos_x_preferred":[
        "Podgorica"
    ],
    "name:bul_x_preferred":[
        "\u041f\u043e\u0434\u0433\u043e\u0440\u0438\u0446\u0430"
    ],
    "name:nld_x_preferred":[
        "Podgorica"
    ],
    "name:pol_x_preferred":[
        "Podgorica"
    ],
    "name:ron_x_preferred":[
        "Podgorica"
    ],
    "name:slv_x_preferred":[
        "Podgorica"
    ],
    "name:ukr_x_preferred":[
        "\u041f\u043e\u0434\u0433\u043e\u0440\u0456\u0446\u0430"
    ],
    "name:ukr_x_variant":[
        "\u041f\u043e\u0434\u0433\u043e\u0440\u0438\u0446\u044f"
    ],
    "name:vie_x_preferred":[
        "Podgorica"
    ],
    "wof:name":"Podgorica",
    "wof:placetype":"locality",
    "wof:population":59
},
  "geometry": {"coordinates":[14.70326,45.84467],"type":"Point"}
}