{
  "type": "Feature",
  "properties": {
    "gn:population":413,
    "iso:country":"SI",
    "name:bos_x_preferred":[
        "Lu\u010de"
    ],
    "name:cat_x_preferred":[
        "Lu\u010de"
    ],
    "name:ceb_x_preferred":[
        "Lu\u010de"
    ],
    "name:che_x_preferred":[
        "\u041b\u0443\u0447\u0435"
    ],
    "name:dan_x_preferred":[
        "Lu\u010de"
    ],
    "name:deu_x_preferred":[
        "Leutsch"
    ],
    "name:deu_x_variant":[
        "Lu\u010de"
    ],
    "name:eng_x_preferred":[
        "Lu\u010de"
    ],
    "name:fra_x_preferred":[
        "Lu\u010de"
    ],
    "name:gle_x_preferred":[
        "Lu\u010de"
    ],
    "name:hbs_x_preferred":[
        "Lu\u010de"
    ],
    "name:hrv_x_preferred":[
        "Lu\u010de"
    ],
    "name:nld_x_preferred":[
        "Lu\u010de"
    ],
    "name:pol_x_preferred":[
        "Lu\u010de"
    ],
    "name:ron_x_preferred":[
        "Lu\u010de"
    ],
    "name:slv_x_preferred":[
        "Lu\u010de"
    ],
    "name:srp_x_preferred":[
        "\u041b\u0443\u0447\u0435"
    ],
    "name:tat_x_preferred":[
        "\u041b\u0443\u0447\u0435"
    ],
    "name:tha_x_preferred":[
        "\u0e25\u0e39\u0e41\u0e0a"
    ],
    "name:ukr_x_preferred":[
        "\u041b\u0443\u0447\u0435"
    ],
    "name:vie_x_preferred":[
        "Lu\u010de"
    ],
    "qs:a0":"Slovenija",
    "qs:a1":"*",
    "qs:a1r":"0",
    "qs:adm0":"Slovenija",
    "qs:la_lc":"*",
    "qs:level":"locality",
    "qs:loc":"Lu\u010de",
    "qs:loc_alt":"Luce",
    "qs:pop":0,
    "qs:type":"buffered point",
    "wd:wordcount":133,
    "wof:name":"Lu\u010de",
    "wof:placetype":"locality",
    "wof:population":413
},
  "geometry": {"coordinates":[14.737519,46.355813],"type":"Point"}
}