{
  "type": "Feature",
  "properties": {
    "gn:admin1_code":"05",
    "gn:asciiname":"Breg pri Borovnici",
    "gn:country_code":"SI",
    "gn:dem":302,
    "gn:feature_class":"P",
    "gn:feature_code":"PPL",
    "gn:name":"Breg pri Borovnici",
    "gn:population":326,
    "gn:timezone":"Europe/Ljubljana",
    "iso:country":"SI",
    "name:bos_x_preferred":[
        "Breg pri Borovnici"
    ],
    "name:ceb_x_preferred":[
        "Breg pri Borovnici"
    ],
    "name:nld_x_preferred":[
        "Breg pri Borovnici"
    ],
    "name:pol_x_preferred":[
        "Breg pri Borovnici"
    ],
    "name:ron_x_preferred":[
        "Breg pri Borovnici"
    ],
    "name:slv_x_preferred":[
        "Breg pri Borovnici"
    ],
    "name:ukr_x_preferred":[
        "\u0411\u0440\u0435\u0433-\u043f\u0440\u0438-\u0411\u043e\u0440\u043e\u0432\u043d\u0438\u0446\u0456"
    ],
    "name:und_x_variant":[
        "Breg"
    ],
    "wof:name":"Breg pri Borovnici",
    "wof:placetype":"locality",
    "wof:population":326
},
  "geometry": {"coordinates":[14.36667,45.9375],"type":"Point"}
}