{
  "type": "Feature",
  "properties": {
    "gn:admin1_code":"87",
    "gn:asciiname":"Sardinje",
    "gn:country_code":"SI",
    "gn:dem":277,
    "gn:feature_class":"P",
    "gn:feature_code":"PPL",
    "gn:name":"\u0160ardinje",
    "gn:population":121,
    "gn:timezone":"Europe/Ljubljana",
    "iso:country":"SI",
    "name:und_x_variant":[
        "\u0160ardinje"
    ],
    "wof:name":"Sardinje",
    "wof:placetype":"locality",
    "wof:population":121
},
  "geometry": {"coordinates":[16.11364,46.43422],"type":"Point"}
}