{
  "type": "Feature",
  "properties": {
    "gn:admin1_code":"00",
    "gn:asciiname":"Crni Potok pri Dragi",
    "gn:cc2":"SI",
    "gn:country_code":"SI",
    "gn:dem":444,
    "gn:feature_class":"P",
    "gn:feature_code":"PPL",
    "gn:name":"\u010crni Potok pri Dragi",
    "gn:population":27,
    "gn:timezone":"Europe/Ljubljana",
    "iso:country":"SI",
    "name:bos_x_preferred":[
        "\u010crni Potok pri Dragi"
    ],
    "name:hrv_x_preferred":[
        "\u010crni Potok pri Dragi"
    ],
    "name:nld_x_preferred":[
        "\u010crni Potok pri Dragi"
    ],
    "name:pol_x_preferred":[
        "\u010crni Potok pri Dragi"
    ],
    "name:ron_x_preferred":[
        "\u010crni Potok pri Dragi"
    ],
    "name:slv_x_preferred":[
        "\u010crni Potok pri Dragi"
    ],
    "name:ukr_x_preferred":[
        "\u0427\u0440\u043d\u0438\u0439 \u041f\u043e\u0442\u043e\u043a-\u043f\u0440\u0438-\u0414\u0440\u0430\u0433\u0456"
    ],
    "name:und_x_variant":[
        "\u010crni Potok"
    ],
    "wof:name":"Crni Potok pri Dragi",
    "wof:placetype":"locality",
    "wof:population":27
},
  "geometry": {"coordinates":[14.68056,45.58694000000001],"type":"Point"}
}