{
  "type": "Feature",
  "properties": {
    "gn:admin1_code":"00",
    "gn:asciiname":"Crni Potok pri Dragi",
    "gn:cc2":"SI",
    "gn:country_code":"SI",
    "gn:dem":444,
    "gn:feature_class":"P",
    "gn:feature_code":"PPL",
    "gn:name":"\u010crni Potok pri Dragi",
    "gn:population":27,
    "gn:timezone":"Europe/Ljubljana",
    "iso:country":"SI",
    "name:und_x_variant":[
        "\u010crni Potok",
        "\u010crni Potok pri Dragi"
    ],
    "wof:name":"Crni Potok pri Dragi",
    "wof:placetype":"locality",
    "wof:population":27
},
  "geometry": {"coordinates":[14.68056,45.58694000000001],"type":"Point"}
}