{
  "type": "Feature",
  "properties": {
    "gn:admin1_code":"C1",
    "gn:asciiname":"Sela",
    "gn:country_code":"SI",
    "gn:dem":335,
    "gn:feature_class":"P",
    "gn:feature_code":"PPL",
    "gn:name":"Sela",
    "gn:population":0,
    "gn:timezone":"Europe/Ljubljana",
    "iso:country":"SI",
    "name:bos_x_preferred":[
        "Sela"
    ],
    "name:ceb_x_preferred":[
        "Sela"
    ],
    "name:deu_x_preferred":[
        "Sela"
    ],
    "name:est_x_preferred":[
        "Sela"
    ],
    "name:fra_x_preferred":[
        "Sela"
    ],
    "name:glg_x_preferred":[
        "Sela"
    ],
    "name:heb_x_preferred":[
        "\u05e1\u05dc\u05e2"
    ],
    "name:hrv_x_preferred":[
        "Sela"
    ],
    "name:hun_x_preferred":[
        "Sela"
    ],
    "name:ita_x_preferred":[
        "Sela"
    ],
    "name:nld_x_preferred":[
        "Sela"
    ],
    "name:pol_x_preferred":[
        "Sela"
    ],
    "name:por_x_preferred":[
        "Sela"
    ],
    "name:ron_x_preferred":[
        "Sela"
    ],
    "name:rus_x_preferred":[
        "\u0421\u0435\u043b\u0430"
    ],
    "name:slk_x_preferred":[
        "Sela"
    ],
    "name:slv_x_preferred":[
        "Sela"
    ],
    "name:spa_x_preferred":[
        "Sela"
    ],
    "name:srp_x_preferred":[
        "\u0421\u0435\u043b\u0430"
    ],
    "name:swe_x_preferred":[
        "Sela"
    ],
    "name:und_x_variant":[
        "Sela pri Rudniku"
    ],
    "wof:name":"Sela",
    "wof:placetype":"locality"
},
  "geometry": {"coordinates":[14.58556,46.00139],"type":"Point"}
}