{
  "type": "Feature",
  "properties": {
    "gn:admin1_code":"C1",
    "gn:asciiname":"Sela",
    "gn:country_code":"SI",
    "gn:dem":335,
    "gn:feature_class":"P",
    "gn:feature_code":"PPL",
    "gn:name":"Sela",
    "gn:population":0,
    "gn:timezone":"Europe/Ljubljana",
    "iso:country":"SI",
    "name:und_x_variant":[
        "Sela pri Rudniku",
        "Sela"
    ],
    "wof:name":"Sela",
    "wof:placetype":"locality"
},
  "geometry": {"coordinates":[14.58556,46.00139],"type":"Point"}
}