{
  "type": "Feature",
  "properties": {
    "gn:admin1_code":"39",
    "gn:asciiname":"Gabrovcec",
    "gn:country_code":"SI",
    "gn:dem":292,
    "gn:feature_class":"P",
    "gn:feature_code":"PPL",
    "gn:name":"Gabrov\u010dec",
    "gn:population":201,
    "gn:timezone":"Europe/Ljubljana",
    "iso:country":"SI",
    "name:bos_x_preferred":[
        "Gabrov\u010dec"
    ],
    "name:ceb_x_preferred":[
        "Gabrov\u010dec"
    ],
    "name:nld_x_preferred":[
        "Gabrov\u010dec"
    ],
    "name:pol_x_preferred":[
        "Gabrov\u010dec"
    ],
    "name:ron_x_preferred":[
        "Gabrov\u010dec"
    ],
    "name:slv_x_preferred":[
        "Gabrov\u010dec"
    ],
    "name:ukr_x_preferred":[
        "\u0413\u0430\u0431\u0440\u043e\u0432\u0447\u0435\u0446\u044c"
    ],
    "name:und_x_variant":[
        "Gabrov\u010dec"
    ],
    "wof:name":"Gabrovcec",
    "wof:placetype":"locality",
    "wof:population":201
},
  "geometry": {"coordinates":[14.79722,45.88361],"type":"Point"}
}