{
  "type": "Feature",
  "properties": {
    "gn:admin1_code":"39",
    "gn:asciiname":"Velike Rebrce",
    "gn:country_code":"SI",
    "gn:dem":311,
    "gn:feature_class":"P",
    "gn:feature_code":"PPL",
    "gn:name":"Velike Rebrce",
    "gn:population":32,
    "gn:timezone":"Europe/Ljubljana",
    "iso:country":"SI",
    "wof:name":"Velike Rebrce",
    "wof:placetype":"locality",
    "wof:population":32
},
  "geometry": {"coordinates":[14.86433,45.85971],"type":"Point"}
}