{
  "type": "Feature",
  "properties": {
    "gn:admin1_code":"39",
    "gn:asciiname":"Velike Rebrce",
    "gn:country_code":"SI",
    "gn:dem":311,
    "gn:feature_class":"P",
    "gn:feature_code":"PPL",
    "gn:name":"Velike Rebrce",
    "gn:population":32,
    "gn:timezone":"Europe/Ljubljana",
    "iso:country":"SI",
    "name:bos_x_preferred":[
        "Velike Rebrce"
    ],
    "name:fas_x_preferred":[
        "\u0648\u0644\u06cc\u06a9 \u0631\u0628\u0631\u06a9"
    ],
    "name:nld_x_preferred":[
        "Velike Rebrce"
    ],
    "name:pol_x_preferred":[
        "Velike Rebrce"
    ],
    "name:ron_x_preferred":[
        "Velike Rebrce"
    ],
    "name:slv_x_preferred":[
        "Velike Rebrce"
    ],
    "name:ukr_x_preferred":[
        "\u0412\u0435\u043b\u0438\u043a\u0435 \u0420\u0435\u0431\u0440\u0446\u0435"
    ],
    "wof:name":"Velike Rebrce",
    "wof:placetype":"locality",
    "wof:population":32
},
  "geometry": {"coordinates":[14.86433,45.85971],"type":"Point"}
}