{
  "type": "Feature",
  "properties": {
    "gn:admin1_code":"B2",
    "gn:asciiname":"Luze",
    "gn:country_code":"SI",
    "gn:dem":432,
    "gn:feature_class":"P",
    "gn:feature_code":"PPL",
    "gn:name":"Lu\u017ee",
    "gn:population":326,
    "gn:timezone":"Europe/Ljubljana",
    "iso:country":"SI",
    "name:und_x_variant":[
        "Lu\u017ee"
    ],
    "wof:name":"Luze",
    "wof:placetype":"locality",
    "wof:population":326
},
  "geometry": {"coordinates":[14.43333,46.26667],"type":"Point"}
}