{
  "type": "Feature",
  "properties": {
    "gn:admin1_code":"B2",
    "gn:asciiname":"Luze",
    "gn:country_code":"SI",
    "gn:dem":432,
    "gn:feature_class":"P",
    "gn:feature_code":"PPL",
    "gn:name":"Lu\u017ee",
    "gn:population":326,
    "gn:timezone":"Europe/Ljubljana",
    "iso:country":"SI",
    "name:bos_x_preferred":[
        "Lu\u017ee"
    ],
    "name:ceb_x_preferred":[
        "Lu\u017ee"
    ],
    "name:hrv_x_preferred":[
        "Lu\u017ee"
    ],
    "name:pol_x_preferred":[
        "Lu\u017ee"
    ],
    "name:ron_x_preferred":[
        "Lu\u017ee"
    ],
    "name:slv_x_preferred":[
        "Lu\u017ee"
    ],
    "name:ukr_x_preferred":[
        "\u041b\u0443\u0436\u0435"
    ],
    "wof:name":"Luze",
    "wof:placetype":"locality",
    "wof:population":326
},
  "geometry": {"coordinates":[14.43333,46.26667],"type":"Point"}
}