{
  "type": "Feature",
  "properties": {
    "gn:admin1_code":"57",
    "gn:asciiname":"Gozdec",
    "gn:country_code":"SI",
    "gn:dem":416,
    "gn:feature_class":"P",
    "gn:feature_code":"PPL",
    "gn:name":"Gozdec",
    "gn:population":51,
    "gn:timezone":"Europe/Ljubljana",
    "iso:country":"SI",
    "wof:name":"Gozdec",
    "wof:placetype":"locality",
    "wof:population":51
},
  "geometry": {"coordinates":[15.29788,46.11865],"type":"Point"}
}