{
  "type": "Feature",
  "properties": {
    "gn:admin1_code":"57",
    "gn:asciiname":"Gozdec",
    "gn:country_code":"SI",
    "gn:dem":416,
    "gn:feature_class":"P",
    "gn:feature_code":"PPL",
    "gn:name":"Gozdec",
    "gn:population":51,
    "gn:timezone":"Europe/Ljubljana",
    "iso:country":"SI",
    "name:bos_x_preferred":[
        "Gozdec"
    ],
    "name:hrv_x_preferred":[
        "Gozdec"
    ],
    "name:nld_x_preferred":[
        "Gozdec"
    ],
    "name:pol_x_preferred":[
        "Gozdec"
    ],
    "name:ron_x_preferred":[
        "Gozdec"
    ],
    "name:slv_x_preferred":[
        "Gozdec"
    ],
    "name:ukr_x_preferred":[
        "\u0413\u043e\u0437\u0434\u0435\u0446\u044c"
    ],
    "wof:name":"Gozdec",
    "wof:placetype":"locality",
    "wof:population":51
},
  "geometry": {"coordinates":[15.29788,46.11865],"type":"Point"}
}