{
  "type": "Feature",
  "properties": {
    "gn:admin1_code":"I5",
    "gn:asciiname":"Podbukovje pri Vacah",
    "gn:country_code":"SI",
    "gn:dem":505,
    "gn:feature_class":"P",
    "gn:feature_code":"PPL",
    "gn:name":"Podbukovje pri Va\u010dah",
    "gn:population":34,
    "gn:timezone":"Europe/Ljubljana",
    "iso:country":"SI",
    "name:bos_x_preferred":[
        "Podbukovje pri Va\u010dah"
    ],
    "name:bul_x_preferred":[
        "\u041f\u043e\u0434\u0431\u0443\u043a\u043e\u0432\u0435 \u043f\u0440\u0438 \u0412\u0430\u0447\u0430\u0445"
    ],
    "name:nld_x_preferred":[
        "Podbukovje pri Va\u010dah"
    ],
    "name:pol_x_preferred":[
        "Podbukovje pri Va\u010dah"
    ],
    "name:ron_x_preferred":[
        "Podbukovje pri Va\u010dah"
    ],
    "name:slv_x_preferred":[
        "Podbukovje pri Va\u010dah"
    ],
    "name:ukr_x_preferred":[
        "\u041f\u043e\u0434\u0431\u0443\u043a\u043e\u0432\u0454-\u043f\u0440\u0438-\u0412\u0430\u0447\u0430\u0445"
    ],
    "wof:name":"Podbukovje pri Vacah",
    "wof:placetype":"locality",
    "wof:population":34
},
  "geometry": {"coordinates":[14.88522,46.11639],"type":"Point"}
}