{
  "type": "Feature",
  "properties": {
    "gn:admin1_code":"I5",
    "gn:asciiname":"Podbukovje pri Vacah",
    "gn:country_code":"SI",
    "gn:dem":505,
    "gn:feature_class":"P",
    "gn:feature_code":"PPL",
    "gn:name":"Podbukovje pri Va\u010dah",
    "gn:population":34,
    "gn:timezone":"Europe/Ljubljana",
    "iso:country":"SI",
    "name:und_x_variant":[
        "Podbukovje pri Va\u010dah"
    ],
    "wof:name":"Podbukovje pri Vacah",
    "wof:placetype":"locality",
    "wof:population":34
},
  "geometry": {"coordinates":[14.88522,46.11639],"type":"Point"}
}