{
  "type": "Feature",
  "properties": {
    "gn:admin1_code":"B8",
    "gn:asciiname":"Dobruska Vas",
    "gn:country_code":"SI",
    "gn:dem":155,
    "gn:feature_class":"P",
    "gn:feature_code":"PPL",
    "gn:name":"Dobru\u0161ka Vas",
    "gn:population":338,
    "gn:timezone":"Europe/Ljubljana",
    "iso:country":"SI",
    "name:und_x_variant":[
        "Dobru\u0161ka Vas"
    ],
    "wof:name":"Dobruska Vas",
    "wof:placetype":"locality",
    "wof:population":338
},
  "geometry": {"coordinates":[15.30806,45.88917],"type":"Point"}
}