{
  "type": "Feature",
  "properties": {
    "gn:admin1_code":"B8",
    "gn:asciiname":"Dobruska Vas",
    "gn:country_code":"SI",
    "gn:dem":155,
    "gn:feature_class":"P",
    "gn:feature_code":"PPL",
    "gn:name":"Dobru\u0161ka Vas",
    "gn:population":338,
    "gn:timezone":"Europe/Ljubljana",
    "iso:country":"SI",
    "name:bos_x_preferred":[
        "Dobru\u0161ka vas"
    ],
    "name:ceb_x_preferred":[
        "Dobru\u0161ka Vas"
    ],
    "name:hrv_x_preferred":[
        "Dobru\u0161ka vas"
    ],
    "name:nld_x_preferred":[
        "Dobru\u0161ka vas"
    ],
    "name:pol_x_preferred":[
        "Dobru\u0161ka vas"
    ],
    "name:ron_x_preferred":[
        "Dobru\u0161ka vas"
    ],
    "name:slv_x_preferred":[
        "Dobru\u0161ka vas"
    ],
    "name:ukr_x_preferred":[
        "\u0414\u043e\u0431\u0440\u0443\u0448\u043a\u0430 \u0412\u0430\u0441"
    ],
    "wof:name":"Dobruska Vas",
    "wof:placetype":"locality",
    "wof:population":338
},
  "geometry": {"coordinates":[15.30806,45.88917],"type":"Point"}
}