{
  "type": "Feature",
  "properties": {
    "gn:admin1_code":"E7",
    "gn:asciiname":"Podkraj pri Zagorju",
    "gn:country_code":"SI",
    "gn:dem":347,
    "gn:feature_class":"P",
    "gn:feature_code":"PPL",
    "gn:name":"Podkraj pri Zagorju",
    "gn:population":47,
    "gn:timezone":"Europe/Ljubljana",
    "iso:country":"SI",
    "name:nld_x_preferred":[
        "Podkraj pri Zagorju"
    ],
    "name:pol_x_preferred":[
        "Podkraj pri Zagorju"
    ],
    "name:ron_x_preferred":[
        "Podkraj pri Zagorju"
    ],
    "name:slv_x_preferred":[
        "Podkraj pri Zagorju"
    ],
    "name:ukr_x_preferred":[
        "\u041f\u043e\u0434\u043a\u0440\u0430\u0439-\u043f\u0440\u0438-\u0417\u0430\u0433\u043e\u0440\u044e"
    ],
    "wof:name":"Podkraj pri Zagorju",
    "wof:placetype":"locality",
    "wof:population":47
},
  "geometry": {"coordinates":[14.97515,46.13716],"type":"Point"}
}