{
  "type": "Feature",
  "properties": {
    "gn:admin1_code":"B1",
    "gn:asciiname":"Preloge",
    "gn:country_code":"SI",
    "gn:dem":523,
    "gn:feature_class":"P",
    "gn:feature_code":"PPL",
    "gn:name":"Preloge",
    "gn:population":2,
    "gn:timezone":"Europe/Ljubljana",
    "iso:country":"SI",
    "wof:name":"Preloge",
    "wof:placetype":"locality",
    "wof:population":2
},
  "geometry": {"coordinates":[15.16864,45.66627],"type":"Point"}
}