{
  "type": "Feature",
  "properties": {
    "iso:country":"SI",
    "name:slv_x_variant":[
        "Ljubljansko Posavje"
    ],
    "wof:name":"Posavje",
    "wof:placetype":"neighbourhood"
},
  "geometry": {"coordinates":[14.50863368592671,46.09781741859666],"type":"Point"}
}