{
  "type": "Feature",
  "properties": {
    "gn:admin1_code":"39",
    "gn:asciiname":"Dolenja Vas pri Temenici",
    "gn:country_code":"SI",
    "gn:dem":331,
    "gn:feature_class":"P",
    "gn:feature_code":"PPL",
    "gn:name":"Dolenja Vas pri Temenici",
    "gn:population":15,
    "gn:timezone":"Europe/Ljubljana",
    "iso:country":"SI",
    "wof:name":"Dolenja Vas pri Temenici",
    "wof:placetype":"locality",
    "wof:population":15
},
  "geometry": {"coordinates":[14.88482,45.9605],"type":"Point"}
}