{
  "type": "Feature",
  "properties": {
    "gn:admin1_code":"39",
    "gn:asciiname":"Dolenja Vas pri Temenici",
    "gn:country_code":"SI",
    "gn:dem":331,
    "gn:feature_class":"P",
    "gn:feature_code":"PPL",
    "gn:name":"Dolenja Vas pri Temenici",
    "gn:population":15,
    "gn:timezone":"Europe/Ljubljana",
    "iso:country":"SI",
    "name:bos_x_preferred":[
        "Dolenja vas pri Temenici"
    ],
    "name:nld_x_preferred":[
        "Dolenja vas pri Temenici"
    ],
    "name:pol_x_preferred":[
        "Dolenja vas pri Temenici"
    ],
    "name:ron_x_preferred":[
        "Dolenja vas pri Temenici"
    ],
    "name:slv_x_preferred":[
        "Dolenja vas pri Temenici"
    ],
    "name:ukr_x_preferred":[
        "\u0414\u043e\u043b\u0435\u043d\u044f \u0412\u0430\u0441-\u043f\u0440\u0438-\u0422\u0435\u043c\u0435\u043d\u0438\u0446\u0456"
    ],
    "wof:name":"Dolenja Vas pri Temenici",
    "wof:placetype":"locality",
    "wof:population":15
},
  "geometry": {"coordinates":[14.88482,45.9605],"type":"Point"}
}