{
  "type": "Feature",
  "properties": {
    "gn:admin1_code":"H7",
    "gn:asciiname":"Ograja",
    "gn:country_code":"SI",
    "gn:dem":543,
    "gn:feature_class":"P",
    "gn:feature_code":"PPL",
    "gn:name":"Ograja",
    "gn:population":0,
    "gn:timezone":"Europe/Ljubljana",
    "iso:country":"SI",
    "name:bos_x_preferred":[
        "Ograja"
    ],
    "name:slv_x_preferred":[
        "Ograja"
    ],
    "wof:name":"Ograja",
    "wof:placetype":"locality"
},
  "geometry": {"coordinates":[14.8814,45.53653],"type":"Point"}
}