{
  "type": "Feature",
  "properties": {
    "gn:admin1_code":"I1",
    "gn:asciiname":"Stara Nova Vas",
    "gn:country_code":"SI",
    "gn:dem":184,
    "gn:feature_class":"P",
    "gn:feature_code":"PPL",
    "gn:name":"Stara Nova Vas",
    "gn:population":348,
    "gn:timezone":"Europe/Ljubljana",
    "iso:country":"SI",
    "name:bos_x_preferred":[
        "Stara Nova vas"
    ],
    "name:ceb_x_preferred":[
        "Stara Nova Vas"
    ],
    "name:hrv_x_preferred":[
        "Stara Nova vas"
    ],
    "name:nld_x_preferred":[
        "Stara Nova vas"
    ],
    "name:pol_x_preferred":[
        "Stara Nova vas"
    ],
    "name:ron_x_preferred":[
        "Stara Nova vas"
    ],
    "name:slv_x_preferred":[
        "Stara Nova vas"
    ],
    "name:ukr_x_preferred":[
        "\u0421\u0442\u0430\u0440\u0430 \u041d\u043e\u0432\u0430 \u0412\u0430\u0441"
    ],
    "name:und_x_variant":[
        "Stara Nova Ves"
    ],
    "wof:name":"Stara Nova Vas",
    "wof:placetype":"locality",
    "wof:population":348
},
  "geometry": {"coordinates":[16.12278,46.58417],"type":"Point"}
}