{
  "type": "Feature",
  "properties": {
    "gn:admin1_code":"I1",
    "gn:asciiname":"Stara Nova Vas",
    "gn:country_code":"SI",
    "gn:dem":184,
    "gn:feature_class":"P",
    "gn:feature_code":"PPL",
    "gn:name":"Stara Nova Vas",
    "gn:population":348,
    "gn:timezone":"Europe/Ljubljana",
    "iso:country":"SI",
    "name:und_x_variant":[
        "Stara Nova Ves",
        "Stara Nova Vas"
    ],
    "wof:name":"Stara Nova Vas",
    "wof:placetype":"locality",
    "wof:population":348
},
  "geometry": {"coordinates":[16.12278,46.58417],"type":"Point"}
}