{
  "type": "Feature",
  "properties": {
    "gn:admin1_code":"57",
    "gn:asciiname":"Velike Grahovse",
    "gn:country_code":"SI",
    "gn:dem":584,
    "gn:feature_class":"P",
    "gn:feature_code":"PPL",
    "gn:name":"Velike Grahov\u0161e",
    "gn:population":142,
    "gn:timezone":"Europe/Ljubljana",
    "iso:country":"SI",
    "name:bos_x_preferred":[
        "Velike Grahov\u0161e"
    ],
    "name:ceb_x_preferred":[
        "Velike Grahov\u0161e"
    ],
    "name:fas_x_preferred":[
        "\u0648\u0644\u06cc\u06a9 \u06af\u0631\u0647\u0648\u0634"
    ],
    "name:hrv_x_preferred":[
        "Velike Grahov\u0161e"
    ],
    "name:nld_x_preferred":[
        "Velike Grahov\u0161e"
    ],
    "name:pol_x_preferred":[
        "Velike Grahov\u0161e"
    ],
    "name:ron_x_preferred":[
        "Velike Grahov\u0161e"
    ],
    "name:slv_x_preferred":[
        "Velike Grahov\u0161e"
    ],
    "name:ukr_x_preferred":[
        "\u0412\u0435\u043b\u0438\u043a\u0435 \u0413\u0440\u0430\u0445\u043e\u0432\u0448\u0435"
    ],
    "wof:name":"Velike Grahovse",
    "wof:placetype":"locality",
    "wof:population":142
},
  "geometry": {"coordinates":[15.32105,46.13906],"type":"Point"}
}