{
  "type": "Feature",
  "properties": {
    "gn:admin1_code":"27",
    "gn:asciiname":"Podvrh",
    "gn:country_code":"SI",
    "gn:dem":1193,
    "gn:feature_class":"P",
    "gn:feature_code":"PPL",
    "gn:name":"Podvrh",
    "gn:population":37,
    "gn:timezone":"Europe/Ljubljana",
    "iso:country":"SI",
    "wof:name":"Podvrh",
    "wof:placetype":"locality",
    "wof:population":37
},
  "geometry": {"coordinates":[14.16568,46.17018],"type":"Point"}
}