{
  "type": "Feature",
  "properties": {
    "gn:admin1_code":"27",
    "gn:asciiname":"Podvrh",
    "gn:country_code":"SI",
    "gn:dem":1193,
    "gn:feature_class":"P",
    "gn:feature_code":"PPL",
    "gn:name":"Podvrh",
    "gn:population":37,
    "gn:timezone":"Europe/Ljubljana",
    "iso:country":"SI",
    "name:bos_x_preferred":[
        "Podvrh"
    ],
    "name:nld_x_preferred":[
        "Podvrh"
    ],
    "name:pol_x_preferred":[
        "Podvrh"
    ],
    "name:ron_x_preferred":[
        "Podvrh"
    ],
    "name:slv_x_preferred":[
        "Podvrh"
    ],
    "name:ukr_x_preferred":[
        "\u041f\u043e\u0434\u0432\u0440\u0445"
    ],
    "wof:name":"Podvrh",
    "wof:placetype":"locality",
    "wof:population":37
},
  "geometry": {"coordinates":[14.16568,46.17018],"type":"Point"}
}