{
  "type": "Feature",
  "properties": {
    "gn:admin1_code":"08",
    "gn:asciiname":"Brezje pri Bojsnem",
    "gn:country_code":"SI",
    "gn:dem":234,
    "gn:feature_class":"P",
    "gn:feature_code":"PPL",
    "gn:name":"Brezje pri Bojsnem",
    "gn:population":69,
    "gn:timezone":"Europe/Ljubljana",
    "iso:country":"SI",
    "wof:name":"Brezje pri Bojsnem",
    "wof:placetype":"locality",
    "wof:population":69
},
  "geometry": {"coordinates":[15.65969,45.97539],"type":"Point"}
}