{
  "type": "Feature",
  "properties": {
    "gn:admin1_code":"08",
    "gn:asciiname":"Brezje pri Bojsnem",
    "gn:country_code":"SI",
    "gn:dem":234,
    "gn:feature_class":"P",
    "gn:feature_code":"PPL",
    "gn:name":"Brezje pri Bojsnem",
    "gn:population":69,
    "gn:timezone":"Europe/Ljubljana",
    "iso:country":"SI",
    "name:bos_x_preferred":[
        "Brezje pri Bojsnem"
    ],
    "name:hrv_x_preferred":[
        "Brezje pri Bojsnem"
    ],
    "name:nld_x_preferred":[
        "Brezje pri Bojsnem"
    ],
    "name:pol_x_preferred":[
        "Brezje pri Bojsnem"
    ],
    "name:ron_x_preferred":[
        "Brezje pri Bojsnem"
    ],
    "name:slv_x_preferred":[
        "Brezje pri Bojsnem"
    ],
    "name:ukr_x_preferred":[
        "\u0411\u0440\u0435\u0437\u0454-\u043f\u0440\u0438-\u0411\u043e\u0439\u0441\u043d\u0435\u043c"
    ],
    "wof:name":"Brezje pri Bojsnem",
    "wof:placetype":"locality",
    "wof:population":69
},
  "geometry": {"coordinates":[15.65969,45.97539],"type":"Point"}
}