{
  "type": "Feature",
  "properties": {
    "gn:admin1_code":"61",
    "gn:asciiname":"Zagradisce",
    "gn:country_code":"SI",
    "gn:dem":368,
    "gn:feature_class":"P",
    "gn:feature_code":"PPL",
    "gn:name":"Zagradi\u0161\u010de",
    "gn:population":79,
    "gn:timezone":"Europe/Ljubljana",
    "iso:country":"SI",
    "name:und_x_variant":[
        "Zagradi\u0161\u010de"
    ],
    "wof:name":"Zagradisce",
    "wof:placetype":"locality",
    "wof:population":79
},
  "geometry": {"coordinates":[14.63375,46.03066],"type":"Point"}
}