{
  "type": "Feature",
  "properties": {
    "gn:admin1_code":"61",
    "gn:asciiname":"Zagradisce",
    "gn:country_code":"SI",
    "gn:dem":368,
    "gn:feature_class":"P",
    "gn:feature_code":"PPL",
    "gn:name":"Zagradi\u0161\u010de",
    "gn:population":79,
    "gn:timezone":"Europe/Ljubljana",
    "iso:country":"SI",
    "name:bos_x_preferred":[
        "Zagradi\u0161\u010de"
    ],
    "name:bul_x_preferred":[
        "\u0417\u0430\u0433\u0440\u0430\u0434\u0438\u0448\u0447\u0435"
    ],
    "name:nld_x_preferred":[
        "Zagradi\u0161\u010de"
    ],
    "name:pol_x_preferred":[
        "Zagradi\u0161\u010de"
    ],
    "name:ron_x_preferred":[
        "Zagradi\u0161\u010de"
    ],
    "name:slv_x_preferred":[
        "Zagradi\u0161\u010de"
    ],
    "name:ukr_x_preferred":[
        "\u0417\u0430\u0433\u0440\u0430\u0434\u0438\u0449\u0435"
    ],
    "name:und_x_variant":[
        "Zagradi\u0161\u010de"
    ],
    "name:urd_x_preferred":[
        "\u0632\u06af\u0631\u0627\u062f\u06cc\u0634\u0686\u0627"
    ],
    "wof:name":"Zagradisce",
    "wof:placetype":"locality",
    "wof:population":79
},
  "geometry": {"coordinates":[14.63375,46.03066],"type":"Point"}
}