{
  "type": "Feature",
  "properties": {
    "gn:admin1_code":"M9",
    "gn:asciiname":"Mala Polana",
    "gn:country_code":"SI",
    "gn:dem":168,
    "gn:feature_class":"P",
    "gn:feature_code":"PPL",
    "gn:name":"Mala Polana",
    "gn:population":356,
    "gn:timezone":"Europe/Ljubljana",
    "iso:country":"SI",
    "name:bos_x_preferred":[
        "Mala Polana"
    ],
    "name:ceb_x_preferred":[
        "Mala Polana"
    ],
    "name:epo_x_preferred":[
        "Mala Polana"
    ],
    "name:hun_x_preferred":[
        "Kispalina"
    ],
    "name:nld_x_preferred":[
        "Mal\u00e1 Po\u013eana"
    ],
    "name:pol_x_preferred":[
        "Mala Polana"
    ],
    "name:ron_x_preferred":[
        "Mala Polana"
    ],
    "name:slv_x_preferred":[
        "Mala Polana"
    ],
    "name:ukr_x_preferred":[
        "\u041c\u0430\u043b\u0430 \u041f\u043e\u043b\u0430\u043d\u0430"
    ],
    "name:und_x_variant":[
        "Kis-Palina"
    ],
    "wof:name":"Mala Polana",
    "wof:placetype":"locality",
    "wof:population":356
},
  "geometry": {"coordinates":[16.35083,46.58667],"type":"Point"}
}