{
  "type": "Feature",
  "properties": {
    "gn:admin1_code":"M9",
    "gn:asciiname":"Mala Polana",
    "gn:country_code":"SI",
    "gn:dem":168,
    "gn:feature_class":"P",
    "gn:feature_code":"PPL",
    "gn:name":"Mala Polana",
    "gn:population":356,
    "gn:timezone":"Europe/Ljubljana",
    "iso:country":"SI",
    "name:und_x_variant":[
        "Kis-Palina",
        "Mala Polana"
    ],
    "wof:name":"Mala Polana",
    "wof:placetype":"locality",
    "wof:population":356
},
  "geometry": {"coordinates":[16.35083,46.58667],"type":"Point"}
}