{
  "type": "Feature",
  "properties": {
    "gn:admin1_code":"D5",
    "gn:asciiname":"Planina Javornik",
    "gn:country_code":"SI",
    "gn:dem":1567,
    "gn:feature_class":"P",
    "gn:feature_code":"PPL",
    "gn:name":"Planina Javornik",
    "gn:population":0,
    "gn:timezone":"Europe/Ljubljana",
    "iso:country":"SI",
    "wof:name":"Planina Javornik",
    "wof:placetype":"locality"
},
  "geometry": {"coordinates":[14.39806,46.37833],"type":"Point"}
}