{
  "type": "Feature",
  "properties": {
    "gn:admin1_code":"05",
    "gn:asciiname":"Drazica",
    "gn:country_code":"SI",
    "gn:dem":307,
    "gn:feature_class":"P",
    "gn:feature_code":"PPL",
    "gn:name":"Dra\u017eica",
    "gn:population":87,
    "gn:timezone":"Europe/Ljubljana",
    "iso:country":"SI",
    "name:bos_x_preferred":[
        "Dra\u017eica"
    ],
    "name:nld_x_preferred":[
        "Dra\u017eica"
    ],
    "name:pol_x_preferred":[
        "Dra\u017eica"
    ],
    "name:ron_x_preferred":[
        "Dra\u017eica"
    ],
    "name:slv_x_preferred":[
        "Dra\u017eica"
    ],
    "name:ukr_x_preferred":[
        "\u0414\u0440\u0430\u0436\u0438\u0446\u044f"
    ],
    "wof:name":"Drazica",
    "wof:placetype":"locality",
    "wof:population":87
},
  "geometry": {"coordinates":[14.37611,45.91111],"type":"Point"}
}