{
  "type": "Feature",
  "properties": {
    "gn:admin1_code":"05",
    "gn:asciiname":"Drazica",
    "gn:country_code":"SI",
    "gn:dem":307,
    "gn:feature_class":"P",
    "gn:feature_code":"PPL",
    "gn:name":"Dra\u017eica",
    "gn:population":87,
    "gn:timezone":"Europe/Ljubljana",
    "iso:country":"SI",
    "name:und_x_variant":[
        "Dra\u017eica"
    ],
    "wof:name":"Drazica",
    "wof:placetype":"locality",
    "wof:population":87
},
  "geometry": {"coordinates":[14.37611,45.91111],"type":"Point"}
}