{
  "type": "Feature",
  "properties": {
    "gn:admin1_code":"14",
    "gn:asciiname":"Podplece",
    "gn:country_code":"SI",
    "gn:dem":718,
    "gn:feature_class":"P",
    "gn:feature_code":"PPL",
    "gn:name":"Podple\u010de",
    "gn:population":18,
    "gn:timezone":"Europe/Ljubljana",
    "iso:country":"SI",
    "name:bos_x_preferred":[
        "Podple\u010de"
    ],
    "name:nld_x_preferred":[
        "Podple\u010de"
    ],
    "name:pol_x_preferred":[
        "Podple\u010de"
    ],
    "name:ron_x_preferred":[
        "Podple\u010de"
    ],
    "name:slv_x_preferred":[
        "Podple\u010de"
    ],
    "name:ukr_x_preferred":[
        "\u041f\u043e\u0434\u043b\u0435\u0447\u0435"
    ],
    "wof:name":"Podplece",
    "wof:placetype":"locality",
    "wof:population":18
},
  "geometry": {"coordinates":[14.03254,46.12742],"type":"Point"}
}