{
  "type": "Feature",
  "properties": {
    "gn:admin1_code":"B6",
    "gn:asciiname":"Brezovo",
    "gn:country_code":"SI",
    "gn:dem":255,
    "gn:feature_class":"P",
    "gn:feature_code":"PPL",
    "gn:name":"Brezovo",
    "gn:population":46,
    "gn:timezone":"Europe/Ljubljana",
    "iso:country":"SI",
    "name:bos_x_preferred":[
        "Brezovo"
    ],
    "name:nld_x_preferred":[
        "Brezovo"
    ],
    "name:pol_x_preferred":[
        "Brezovo"
    ],
    "name:ron_x_preferred":[
        "Brezovo"
    ],
    "name:slv_x_preferred":[
        "Brezovo"
    ],
    "name:ukr_x_preferred":[
        "\u0411\u0440\u0435\u0437\u043e\u0432\u043e"
    ],
    "wof:name":"Brezovo",
    "wof:placetype":"locality",
    "wof:population":46
},
  "geometry": {"coordinates":[15.34206,45.94647],"type":"Point"}
}