{
  "type": "Feature",
  "properties": {
    "gn:admin1_code":"54",
    "gn:asciiname":"Puste Lozice",
    "gn:country_code":"SI",
    "gn:dem":575,
    "gn:feature_class":"P",
    "gn:feature_code":"PPL",
    "gn:name":"Puste Lo\u017eice",
    "gn:population":0,
    "gn:timezone":"Europe/Ljubljana",
    "iso:country":"SI",
    "wof:name":"Puste Lozice",
    "wof:placetype":"locality"
},
  "geometry": {"coordinates":[15.43722,46.05278],"type":"Point"}
}