{
  "type": "Feature",
  "properties": {
    "gn:admin1_code":"N5",
    "gn:asciiname":"Podlog v Savinjski Dolini",
    "gn:country_code":"SI",
    "gn:dem":270,
    "gn:feature_class":"P",
    "gn:feature_code":"PPL",
    "gn:name":"Podlog v Savinjski Dolini",
    "gn:population":311,
    "gn:timezone":"Europe/Ljubljana",
    "iso:country":"SI",
    "name:und_x_variant":[
        "Podlog",
        "Podlog v Savinjski Dolini"
    ],
    "wof:name":"Podlog v Savinjski Dolini",
    "wof:placetype":"locality",
    "wof:population":311
},
  "geometry": {"coordinates":[15.13333,46.26667],"type":"Point"}
}