{
  "type": "Feature",
  "properties": {
    "gn:admin1_code":"N5",
    "gn:asciiname":"Podlog v Savinjski Dolini",
    "gn:country_code":"SI",
    "gn:dem":270,
    "gn:feature_class":"P",
    "gn:feature_code":"PPL",
    "gn:name":"Podlog v Savinjski Dolini",
    "gn:population":311,
    "gn:timezone":"Europe/Ljubljana",
    "iso:country":"SI",
    "name:ceb_x_preferred":[
        "Podlog v Savinjski Dolini"
    ],
    "name:hrv_x_preferred":[
        "Podlog v Savinjski Dolini"
    ],
    "name:nld_x_preferred":[
        "Podlog v Savinjski Dolini"
    ],
    "name:pol_x_preferred":[
        "Podlog v Savinjski Dolini"
    ],
    "name:ron_x_preferred":[
        "Podlog v Savinjski Dolini"
    ],
    "name:slv_x_preferred":[
        "Podlog v Savinjski dolini"
    ],
    "name:ukr_x_preferred":[
        "\u041f\u043e\u0434\u043b\u043e\u0433-\u0432-\u0421\u0430\u0432\u0438\u043d\u0441\u044c\u043a\u0456\u0439 \u0414\u043e\u043b\u0438\u043d\u0456"
    ],
    "name:und_x_variant":[
        "Podlog"
    ],
    "wof:name":"Podlog v Savinjski Dolini",
    "wof:placetype":"locality",
    "wof:population":311
},
  "geometry": {"coordinates":[15.13333,46.26667],"type":"Point"}
}