{
  "type": "Feature",
  "properties": {
    "gn:admin1_code":"C5",
    "gn:asciiname":"Zavrse pri Grobelnem",
    "gn:country_code":"SI",
    "gn:dem":300,
    "gn:feature_class":"P",
    "gn:feature_code":"PPL",
    "gn:name":"Zavr\u0161e pri Grobelnem",
    "gn:population":140,
    "gn:timezone":"Europe/Ljubljana",
    "iso:country":"SI",
    "name:und_x_variant":[
        "Zavr\u0161e pri Grobelnem"
    ],
    "wof:name":"Zavrse pri Grobelnem",
    "wof:placetype":"locality",
    "wof:population":140
},
  "geometry": {"coordinates":[15.44469,46.22239],"type":"Point"}
}