{
  "type": "Feature",
  "properties": {
    "gn:admin1_code":"C5",
    "gn:asciiname":"Zavrse pri Grobelnem",
    "gn:country_code":"SI",
    "gn:dem":300,
    "gn:feature_class":"P",
    "gn:feature_code":"PPL",
    "gn:name":"Zavr\u0161e pri Grobelnem",
    "gn:population":140,
    "gn:timezone":"Europe/Ljubljana",
    "iso:country":"SI",
    "name:bos_x_preferred":[
        "Zavr\u0161e pri Grobelnem"
    ],
    "name:ceb_x_preferred":[
        "Zavr\u0161e pri Grobelnem"
    ],
    "name:hrv_x_preferred":[
        "Zavr\u0161e pri Grobelnem"
    ],
    "name:nld_x_preferred":[
        "Zavr\u0161e pri Grobelnem"
    ],
    "name:pol_x_preferred":[
        "Zavr\u0161e pri Grobelnem"
    ],
    "name:ron_x_preferred":[
        "Zavr\u0161e pri Grobelnem"
    ],
    "name:slv_x_preferred":[
        "Zavr\u0161e pri Grobelnem"
    ],
    "name:ukr_x_preferred":[
        "\u0417\u0430\u0432\u0440\u0448\u0435-\u043f\u0440\u0438-\u0413\u0440\u043e\u0431\u0435\u043b\u043d\u0435\u043c"
    ],
    "wof:name":"Zavrse pri Grobelnem",
    "wof:placetype":"locality",
    "wof:population":140
},
  "geometry": {"coordinates":[15.44469,46.22239],"type":"Point"}
}