{
  "type": "Feature",
  "properties": {
    "gn:admin1_code":"04",
    "gn:asciiname":"Laski Rovt",
    "gn:country_code":"SI",
    "gn:dem":531,
    "gn:feature_class":"P",
    "gn:feature_code":"PPL",
    "gn:name":"La\u0161ki Rovt",
    "gn:population":41,
    "gn:timezone":"Europe/Ljubljana",
    "iso:country":"SI",
    "name:und_x_variant":[
        "La\u0161ki Rovt"
    ],
    "wof:name":"Laski Rovt",
    "wof:placetype":"locality",
    "wof:population":41
},
  "geometry": {"coordinates":[13.90231,46.2672],"type":"Point"}
}