{
  "type": "Feature",
  "properties": {
    "gn:admin1_code":"04",
    "gn:asciiname":"Laski Rovt",
    "gn:country_code":"SI",
    "gn:dem":531,
    "gn:feature_class":"P",
    "gn:feature_code":"PPL",
    "gn:name":"La\u0161ki Rovt",
    "gn:population":41,
    "gn:timezone":"Europe/Ljubljana",
    "iso:country":"SI",
    "name:bos_x_preferred":[
        "La\u0161ki Rovt"
    ],
    "name:hrv_x_preferred":[
        "La\u0161ki Rovt"
    ],
    "name:ita_x_preferred":[
        "La\u0161ki Rovt"
    ],
    "name:nld_x_preferred":[
        "La\u0161ki Rovt"
    ],
    "name:pol_x_preferred":[
        "La\u0161ki Rovt"
    ],
    "name:ron_x_preferred":[
        "La\u0161ki Rovt"
    ],
    "name:slv_x_preferred":[
        "La\u0161ki Rovt"
    ],
    "name:ukr_x_preferred":[
        "\u041b\u0430\u0448\u043a\u0438\u0439 \u0420\u043e\u0432\u0442"
    ],
    "name:urd_x_preferred":[
        "\u0644\u0627\u0634\u06a9\u06cc \u0631\u0648\u0648\u0679"
    ],
    "wof:name":"Laski Rovt",
    "wof:placetype":"locality",
    "wof:population":41
},
  "geometry": {"coordinates":[13.90231,46.2672],"type":"Point"}
}