{
  "type": "Feature",
  "properties": {
    "gn:admin1_code":"38",
    "gn:asciiname":"Dobropolje",
    "gn:country_code":"SI",
    "gn:dem":420,
    "gn:feature_class":"P",
    "gn:feature_code":"PPL",
    "gn:name":"Dobropolje",
    "gn:population":70,
    "gn:timezone":"Europe/Ljubljana",
    "iso:country":"SI",
    "name:und_x_variant":[
        "Poglie",
        "Dobro Polje"
    ],
    "wof:name":"Dobropolje",
    "wof:placetype":"locality",
    "wof:population":70
},
  "geometry": {"coordinates":[14.2175,45.56639000000001],"type":"Point"}
}