{
  "type": "Feature",
  "properties": {
    "gn:admin1_code":"38",
    "gn:asciiname":"Dobropolje",
    "gn:country_code":"SI",
    "gn:dem":420,
    "gn:feature_class":"P",
    "gn:feature_code":"PPL",
    "gn:name":"Dobropolje",
    "gn:population":70,
    "gn:timezone":"Europe/Ljubljana",
    "iso:country":"SI",
    "name:bos_x_preferred":[
        "Dobropolje"
    ],
    "name:hrv_x_preferred":[
        "Dobro Polje"
    ],
    "name:nld_x_preferred":[
        "Dobro Polje"
    ],
    "name:pol_x_preferred":[
        "Dobro Polje"
    ],
    "name:ron_x_preferred":[
        "Dobro Polje"
    ],
    "name:slv_x_preferred":[
        "Dobropolje"
    ],
    "name:ukr_x_preferred":[
        "\u0414\u043e\u0431\u0440\u043e \u041f\u043e\u043b\u0454"
    ],
    "name:und_x_variant":[
        "Poglie",
        "Dobro Polje"
    ],
    "wof:name":"Dobropolje",
    "wof:placetype":"locality",
    "wof:population":70
},
  "geometry": {"coordinates":[14.2175,45.56639000000001],"type":"Point"}
}