{
  "type": "Feature",
  "properties": {
    "gn:admin1_code":"27",
    "gn:asciiname":"Kremenik",
    "gn:country_code":"SI",
    "gn:dem":711,
    "gn:feature_class":"P",
    "gn:feature_code":"PPL",
    "gn:name":"Kremenik",
    "gn:population":21,
    "gn:timezone":"Europe/Ljubljana",
    "iso:country":"SI",
    "name:bos_x_preferred":[
        "Kremenik"
    ],
    "name:hrv_x_preferred":[
        "Kremenik"
    ],
    "name:nld_x_preferred":[
        "Kremenik"
    ],
    "name:pol_x_preferred":[
        "Kremenik"
    ],
    "name:ron_x_preferred":[
        "Kremenik"
    ],
    "name:slv_x_preferred":[
        "Kremenik"
    ],
    "name:ukr_x_preferred":[
        "\u041a\u0440\u0435\u043c\u0435\u043d\u0438\u043a"
    ],
    "wof:name":"Kremenik",
    "wof:placetype":"locality",
    "wof:population":21
},
  "geometry": {"coordinates":[14.20189,46.0912],"type":"Point"}
}