{
  "type": "Feature",
  "properties": {
    "gn:admin1_code":"08",
    "gn:asciiname":"Glogov Brod",
    "gn:country_code":"SI",
    "gn:dem":160,
    "gn:feature_class":"P",
    "gn:feature_code":"PPL",
    "gn:name":"Glogov Brod",
    "gn:population":124,
    "gn:timezone":"Europe/Ljubljana",
    "iso:country":"SI",
    "name:bos_x_preferred":[
        "Glogov Brod"
    ],
    "name:ceb_x_preferred":[
        "Glogov Brod"
    ],
    "name:hrv_x_preferred":[
        "Glogov Brod"
    ],
    "name:nld_x_preferred":[
        "Glogov Brod"
    ],
    "name:pol_x_preferred":[
        "Glogov Brod"
    ],
    "name:ron_x_preferred":[
        "Glogov Brod"
    ],
    "name:slv_x_preferred":[
        "Glogov Brod"
    ],
    "name:ukr_x_preferred":[
        "\u0413\u043b\u043e\u0433\u043e\u0432 \u0411\u0440\u043e\u0434"
    ],
    "wof:name":"Glogov Brod",
    "wof:placetype":"locality",
    "wof:population":124
},
  "geometry": {"coordinates":[15.59545,45.94555],"type":"Point"}
}