{
  "type": "Feature",
  "properties": {
    "gn:admin1_code":"B6",
    "gn:asciiname":"Log",
    "gn:country_code":"SI",
    "gn:dem":234,
    "gn:feature_class":"P",
    "gn:feature_code":"PPL",
    "gn:name":"Log",
    "gn:population":317,
    "gn:timezone":"Europe/Ljubljana",
    "iso:country":"SI",
    "name:bos_x_preferred":[
        "Log"
    ],
    "name:ceb_x_preferred":[
        "Log"
    ],
    "name:nld_x_preferred":[
        "Log"
    ],
    "name:pol_x_preferred":[
        "Log"
    ],
    "name:ron_x_preferred":[
        "Log"
    ],
    "name:slv_x_preferred":[
        "Log"
    ],
    "name:ukr_x_preferred":[
        "\u041b\u043e\u0433"
    ],
    "wof:name":"Log",
    "wof:placetype":"locality",
    "wof:population":317
},
  "geometry": {"coordinates":[15.32508,45.99652],"type":"Point"}
}