{
  "type": "Feature",
  "properties": {
    "gn:admin1_code":"H7",
    "gn:asciiname":"Stalcerji",
    "gn:country_code":"SI",
    "gn:dem":526,
    "gn:feature_class":"P",
    "gn:feature_code":"PPL",
    "gn:name":"\u0160talcerji",
    "gn:population":183,
    "gn:timezone":"Europe/Ljubljana",
    "iso:country":"SI",
    "name:bos_x_preferred":[
        "\u0160talcerji"
    ],
    "name:ceb_x_preferred":[
        "\u0160talcerji"
    ],
    "name:hrv_x_preferred":[
        "\u0160talcerji"
    ],
    "name:nld_x_preferred":[
        "\u0160talcerji"
    ],
    "name:pol_x_preferred":[
        "\u0160talcerji"
    ],
    "name:ron_x_preferred":[
        "\u0160talcerji"
    ],
    "name:slv_x_preferred":[
        "\u0160talcerji"
    ],
    "name:ukr_x_preferred":[
        "\u0428\u0442\u0430\u043b\u0446\u0435\u0440\u0456"
    ],
    "name:und_x_variant":[
        "\u0160talcarji"
    ],
    "wof:name":"Stalcerji",
    "wof:placetype":"locality",
    "wof:population":183
},
  "geometry": {"coordinates":[14.87222,45.57028],"type":"Point"}
}