{
  "type": "Feature",
  "properties": {
    "gn:admin1_code":"84",
    "gn:asciiname":"Vitovlje",
    "gn:country_code":"SI",
    "gn:dem":445,
    "gn:feature_class":"P",
    "gn:feature_code":"PPL",
    "gn:name":"Vitovlje",
    "gn:population":526,
    "gn:timezone":"Europe/Ljubljana",
    "iso:country":"SI",
    "name:bos_x_preferred":[
        "Vitovlje"
    ],
    "name:ceb_x_preferred":[
        "Vitovlje"
    ],
    "name:deu_x_preferred":[
        "Vitovlje"
    ],
    "name:nld_x_preferred":[
        "Vitovlje"
    ],
    "name:und_x_variant":[
        "Vittuglia"
    ],
    "wof:name":"Vitovlje",
    "wof:placetype":"locality",
    "wof:population":526
},
  "geometry": {"coordinates":[13.76556,45.93917],"type":"Point"}
}