{
  "type": "Feature",
  "properties": {
    "gn:admin1_code":"P9",
    "gn:asciiname":"Barizoni",
    "gn:country_code":"SI",
    "gn:dem":76,
    "gn:feature_class":"P",
    "gn:feature_code":"PPL",
    "gn:name":"Barizoni",
    "gn:population":136,
    "gn:timezone":"Europe/Ljubljana",
    "iso:country":"SI",
    "name:bos_x_preferred":[
        "Barizoni"
    ],
    "name:bul_x_preferred":[
        "\u0411\u0430\u0440\u0438\u0437\u043e\u043d\u0438"
    ],
    "name:ceb_x_preferred":[
        "Barizoni"
    ],
    "name:nld_x_preferred":[
        "Barizoni"
    ],
    "name:pol_x_preferred":[
        "Barizoni"
    ],
    "name:ron_x_preferred":[
        "Barizoni"
    ],
    "name:slv_x_preferred":[
        "Barizoni"
    ],
    "name:srp_x_preferred":[
        "\u0411\u0430\u0440\u0438\u0437\u043e\u043d\u0438"
    ],
    "name:ukr_x_preferred":[
        "\u0411\u0430\u0440\u0438\u0437\u043e\u043d\u0438"
    ],
    "wof:name":"Barizoni",
    "wof:placetype":"locality",
    "wof:population":136
},
  "geometry": {"coordinates":[13.73366,45.59007],"type":"Point"}
}