{
  "type": "Feature",
  "properties": {
    "gn:admin1_code":"B8",
    "gn:asciiname":"Zavinek",
    "gn:country_code":"SI",
    "gn:dem":187,
    "gn:feature_class":"P",
    "gn:feature_code":"PPL",
    "gn:name":"Zavinek",
    "gn:population":64,
    "gn:timezone":"Europe/Ljubljana",
    "iso:country":"SI",
    "name:bos_x_preferred":[
        "Zavinek"
    ],
    "name:hrv_x_preferred":[
        "Zavinek"
    ],
    "name:nld_x_preferred":[
        "Zavinek"
    ],
    "name:pol_x_preferred":[
        "Zavinek"
    ],
    "name:ron_x_preferred":[
        "Zavinek"
    ],
    "name:slv_x_historical":[
        "Zavinjek"
    ],
    "name:slv_x_preferred":[
        "Zavinjek"
    ],
    "name:slv_x_variant":[
        "Zavinek"
    ],
    "name:ukr_x_preferred":[
        "\u0417\u0430\u0432\u0438\u043d\u0435\u043a"
    ],
    "wof:name":"Zavinek",
    "wof:placetype":"locality",
    "wof:population":64
},
  "geometry": {"coordinates":[15.30236,45.90363],"type":"Point"}
}