{
  "type": "Feature",
  "properties": {
    "gn:admin1_code":"36",
    "gn:asciiname":"Majnik",
    "gn:country_code":"SI",
    "gn:dem":440,
    "gn:feature_class":"P",
    "gn:feature_code":"PPL",
    "gn:name":"Majnik",
    "gn:population":0,
    "gn:timezone":"Europe/Ljubljana",
    "iso:country":"SI",
    "wof:name":"Majnik",
    "wof:placetype":"locality"
},
  "geometry": {"coordinates":[13.97917,45.95639],"type":"Point"}
}