{
  "type": "Feature",
  "properties": {
    "gn:admin1_code":"64",
    "gn:asciiname":"Praprotno Brdo",
    "gn:country_code":"SI",
    "gn:dem":640,
    "gn:feature_class":"P",
    "gn:feature_code":"PPL",
    "gn:name":"Praprotno Brdo",
    "gn:population":42,
    "gn:timezone":"Europe/Ljubljana",
    "iso:country":"SI",
    "wof:name":"Praprotno Brdo",
    "wof:placetype":"locality",
    "wof:population":42
},
  "geometry": {"coordinates":[14.18722,45.99722],"type":"Point"}
}