{
  "type": "Feature",
  "properties": {
    "gn:admin1_code":"64",
    "gn:asciiname":"Praprotno Brdo",
    "gn:country_code":"SI",
    "gn:dem":640,
    "gn:feature_class":"P",
    "gn:feature_code":"PPL",
    "gn:name":"Praprotno Brdo",
    "gn:population":42,
    "gn:timezone":"Europe/Ljubljana",
    "iso:country":"SI",
    "name:bos_x_preferred":[
        "Praprotno Brdo"
    ],
    "name:nld_x_preferred":[
        "Praprotno Brdo"
    ],
    "name:pol_x_preferred":[
        "Praprotno Brdo"
    ],
    "name:ron_x_preferred":[
        "Praprotno Brdo"
    ],
    "name:slv_x_preferred":[
        "Praprotno Brdo"
    ],
    "name:ukr_x_preferred":[
        "\u041f\u0440\u0430\u043f\u0440\u043e\u0442\u043d\u043e \u0411\u0440\u0434\u043e"
    ],
    "wof:name":"Praprotno Brdo",
    "wof:placetype":"locality",
    "wof:population":42
},
  "geometry": {"coordinates":[14.18722,45.99722],"type":"Point"}
}