{
  "type": "Feature",
  "properties": {
    "gn:admin1_code":"57",
    "gn:asciiname":"Marijina Vas",
    "gn:country_code":"SI",
    "gn:dem":529,
    "gn:feature_class":"P",
    "gn:feature_code":"PPL",
    "gn:name":"Marijina Vas",
    "gn:population":77,
    "gn:timezone":"Europe/Ljubljana",
    "iso:country":"SI",
    "name:bos_x_preferred":[
        "Marijina vas"
    ],
    "name:hrv_x_preferred":[
        "Marijina vas"
    ],
    "name:nld_x_preferred":[
        "Marijina vas"
    ],
    "name:pol_x_preferred":[
        "Marijina vas"
    ],
    "name:ron_x_preferred":[
        "Marijina vas"
    ],
    "name:slv_x_preferred":[
        "Marijina vas"
    ],
    "name:ukr_x_preferred":[
        "\u041c\u0430\u0440\u0456\u0457\u043d\u0430 \u0412\u0430\u0441"
    ],
    "wof:name":"Marijina Vas",
    "wof:placetype":"locality",
    "wof:population":77
},
  "geometry": {"coordinates":[15.35454,46.08753],"type":"Point"}
}