{
  "type": "Feature",
  "properties": {
    "gn:admin1_code":"57",
    "gn:asciiname":"Marijina Vas",
    "gn:country_code":"SI",
    "gn:dem":529,
    "gn:feature_class":"P",
    "gn:feature_code":"PPL",
    "gn:name":"Marijina Vas",
    "gn:population":77,
    "gn:timezone":"Europe/Ljubljana",
    "iso:country":"SI",
    "wof:name":"Marijina Vas",
    "wof:placetype":"locality",
    "wof:population":77
},
  "geometry": {"coordinates":[15.35454,46.08753],"type":"Point"}
}