{
  "type": "Feature",
  "properties": {
    "gn:admin1_code":"N8",
    "gn:asciiname":"Smihel pri Zuzemberku",
    "gn:country_code":"SI",
    "gn:dem":249,
    "gn:feature_class":"P",
    "gn:feature_code":"PPL",
    "gn:name":"\u0160mihel pri \u017du\u017eemberku",
    "gn:population":116,
    "gn:timezone":"Europe/Ljubljana",
    "iso:country":"SI",
    "name:und_x_variant":[
        "\u0160mihel",
        "\u0160mihel pri \u017du\u017eemberku"
    ],
    "wof:name":"Smihel pri Zuzemberku",
    "wof:placetype":"locality",
    "wof:population":116
},
  "geometry": {"coordinates":[14.88472,45.85028],"type":"Point"}
}