{
  "type": "Feature",
  "properties": {
    "gn:admin1_code":"N8",
    "gn:asciiname":"Smihel pri Zuzemberku",
    "gn:country_code":"SI",
    "gn:dem":249,
    "gn:feature_class":"P",
    "gn:feature_code":"PPL",
    "gn:name":"\u0160mihel pri \u017du\u017eemberku",
    "gn:population":116,
    "gn:timezone":"Europe/Ljubljana",
    "iso:country":"SI",
    "name:bos_x_preferred":[
        "\u0160mihel pri \u017du\u017eemberku"
    ],
    "name:bul_x_preferred":[
        "\u0428\u043c\u0438\u0445\u0435\u043b \u043f\u0440\u0438 \u0416\u0443\u0436\u0435\u043c\u0431\u0435\u0440\u043a\u0443"
    ],
    "name:ceb_x_preferred":[
        "\u0160mihel pri \u017du\u017eemberku"
    ],
    "name:hrv_x_preferred":[
        "\u0160mihel pri \u017du\u017eemberku"
    ],
    "name:nld_x_preferred":[
        "\u0160mihel pri \u017du\u017eemberku"
    ],
    "name:pol_x_preferred":[
        "\u0160mihel pri \u017du\u017eemberku"
    ],
    "name:ron_x_preferred":[
        "\u0160mihel pri \u017du\u017eemberku"
    ],
    "name:slv_x_preferred":[
        "\u0160mihel pri \u017du\u017eemberku"
    ],
    "name:ukr_x_preferred":[
        "\u0428\u043c\u0438\u0445\u0435\u043b-\u043f\u0440\u0438-\u0416\u0443\u0436\u0435\u043c\u0431\u0435\u0440\u043a\u0443"
    ],
    "name:und_x_variant":[
        "\u0160mihel",
        "\u0160mihel pri \u017du\u017eemberku"
    ],
    "wof:name":"Smihel pri Zuzemberku",
    "wof:placetype":"locality",
    "wof:population":116
},
  "geometry": {"coordinates":[14.88472,45.85028],"type":"Point"}
}