{
  "type": "Feature",
  "properties": {
    "gn:admin1_code":"B1",
    "gn:asciiname":"Nestoplja Vas",
    "gn:country_code":"SI",
    "gn:dem":186,
    "gn:feature_class":"P",
    "gn:feature_code":"PPL",
    "gn:name":"Nestoplja Vas",
    "gn:population":24,
    "gn:timezone":"Europe/Ljubljana",
    "iso:country":"SI",
    "wof:name":"Nestoplja Vas",
    "wof:placetype":"locality",
    "wof:population":24
},
  "geometry": {"coordinates":[15.18685,45.62388],"type":"Point"}
}