{
  "type": "Feature",
  "properties": {
    "gn:admin1_code":"B1",
    "gn:asciiname":"Nestoplja Vas",
    "gn:country_code":"SI",
    "gn:dem":186,
    "gn:feature_class":"P",
    "gn:feature_code":"PPL",
    "gn:name":"Nestoplja Vas",
    "gn:population":24,
    "gn:timezone":"Europe/Ljubljana",
    "iso:country":"SI",
    "name:bos_x_preferred":[
        "Nestoplja vas"
    ],
    "name:hrv_x_preferred":[
        "Nestoplja vas"
    ],
    "name:nld_x_preferred":[
        "Nestoplja vas"
    ],
    "name:pol_x_preferred":[
        "Nestoplja vas"
    ],
    "name:ron_x_preferred":[
        "Nestoplja vas"
    ],
    "name:slv_x_preferred":[
        "Nestoplja vas"
    ],
    "name:ukr_x_preferred":[
        "\u041d\u0435\u0441\u0442\u043e\u043f\u043b\u044f \u0412\u0430\u0441"
    ],
    "wof:name":"Nestoplja Vas",
    "wof:placetype":"locality",
    "wof:population":24
},
  "geometry": {"coordinates":[15.18685,45.62388],"type":"Point"}
}