{
  "type": "Feature",
  "properties": {
    "gn:admin1_code":"E7",
    "gn:asciiname":"Polsina",
    "gn:country_code":"SI",
    "gn:dem":455,
    "gn:feature_class":"P",
    "gn:feature_code":"PPL",
    "gn:name":"Pol\u0161ina",
    "gn:population":64,
    "gn:timezone":"Europe/Ljubljana",
    "iso:country":"SI",
    "name:und_x_variant":[
        "Pol\u0161ina"
    ],
    "wof:name":"Polsina",
    "wof:placetype":"locality",
    "wof:population":64
},
  "geometry": {"coordinates":[14.89666,46.1778],"type":"Point"}
}